Workbook
Name _Toc225350871: '5.4.1.1-4 Atmos deposition'!$C$1
Name _Toc225350871: '5.5.1.1-2 Leaching and runoff'!$C$1
Name AgResidue_Equations_CropResidue.VEERG_6_1_1_1__1__NitrousOxideEmissionsFromCropResidues: _xlfn.LAMBDA(_xlpm.M_c,_xlpm.EF_Ni,_xlpm.C_N2O, _xlpm.M_c * _xlpm.EF_Ni * _xlpm.C_N2O * 10 ^ (-3))
Name AgResidue_Equations_CropResidue.VEERG_6_1_1_1__1__NitrousOxideEmissionsFromCropResidues_FunctionName: _xlfn.LAMBDA("VEERG_6_1_1_1__1__NitrousOxideEmissionsFromCropResidues")
Name AgResidue_Equations_CropResidue.VEERG_6_1_1_1__1__NitrousOxideEmissionsFromCropResidues_LatexEquation: _xlfn.LAMBDA("E=\sum\nolimits_c\left(M_{c}\times EF_{N}\right)\times C_{g,N2O}\times 10^{-3}")
Name AgResidue_Equations_CropResidue.VEERG_6_1_1_1__1__NitrousOxideEmissionsFromCropResidues_NIRReference: _xlfn.LAMBDA("")
Name AgResidue_Equations_CropResidue.VEERG_6_1_1_1__1__NitrousOxideEmissionsFromCropResidues_Source: _xlfn.LAMBDA("VEERG 2026: 6.1.1.1, Equation (1)")
Name AgResidue_Equations_CropResidue.VEERG_6_1_1_1__1__NitrousOxideEmissionsFromCropResidues_Title: _xlfn.LAMBDA("Nitrous oxide emissions from the return of crop residues across all crops c to the soil")
Name AgResidue_Equations_CropResidue.VEERG_6_1_1_1__1__NitrousOxideEmissionsFromCropResidues_Unit: _xlfn.LAMBDA("t N2O")
Name AgResidue_Equations_CropResidue.VEERG_6_1_1_1__1__NitrousOxideEmissionsFromCropResidues_Variable: _xlfn.LAMBDA("E")
Name AgResidue_Equations_CropResidue.VEERG_6_1_1_1__2__MassOfNitrogenInCropResidues_LatexEquation: _xlfn.LAMBDA("M_{c}=(P_{c}\times R_{AGc}\times(1-F_{c}-FFOD_{c})\times DM_{c}\times NC_{AGc})+(P_{c}\times R_{AGc}\times R_{BGc}\times DM_{c}\times NC_{BGc})")
Name AgResidue_Equations_CropResidue.VEERG_6_1_1_1__2__MassOfNitrogenInCropResidues_NIRReference: _xlfn.LAMBDA("")
Name AgResidue_Equations_CropResidue.VEERG_6_1_1_1__2__MassOfNitrogenInCropResidues_Source: _xlfn.LAMBDA("VEERG 2026: 6.1.1.1, Equation (2)")
Name AgResidue_Equations_CropResidue.VEERG_6_1_1_1__2__MassOfNitrogenInCropResidues_Title: _xlfn.LAMBDA("Mass of nitrogen in crop residues returned to the soil")
Name AgResidue_Equations_CropResidue.VEERG_6_1_1_1__2__MassOfNitrogenInCropResidues_Unit: _xlfn.LAMBDA("kg N")
Name AgResidue_Equations_CropResidue.VEERG_6_1_1_1__2__MassOfNitrogenInCropResidues_Variable: _xlfn.LAMBDA("M_c")
Name AgResidue_Equations_CropResidue.VEERG_6_1_1_2__1__FractionOfCropResidueRemovedBaled: _xlfn.LAMBDA(_xlpm.B,_xlpm.M_B,_xlpm.P_c,_xlpm.R_AGc, IFERROR((_xlpm.B * _xlpm.M_B) / (_xlpm.P_c * _xlpm.R_AGc), 0))
Name AgResidue_Equations_CropResidue.VEERG_6_1_1_2__1__FractionOfCropResidueRemovedBaled_LatexEquation: _xlfn.LAMBDA("FFOD_{c,baled}=\frac{B\times M_{B}}{P_{c}\times R_{AG,c}}")
Name AgResidue_Equations_CropResidue.VEERG_6_1_1_2__1__FractionOfCropResidueRemovedBaled_NIRReference: _xlfn.LAMBDA("")
Name AgResidue_Equations_CropResidue.VEERG_6_1_1_2__1__FractionOfCropResidueRemovedBaled_Source: _xlfn.LAMBDA("VEERG 2026: 6.1.1.2, Equation (1)")
Name AgResidue_Equations_CropResidue.VEERG_6_1_1_2__1__FractionOfCropResidueRemovedBaled_Title: _xlfn.LAMBDA("Fraction of crop residue that is removed for crop c, calculated where residues are baled")
Name AgResidue_Equations_CropResidue.VEERG_6_1_1_2__1__FractionOfCropResidueRemovedBaled_Unit: _xlfn.LAMBDA("dimensionless")
Name AgResidue_Equations_CropResidue.VEERG_6_1_1_2__1__FractionOfCropResidueRemovedBaled_Variable: _xlfn.LAMBDA("FFOD_cbaled")
Name AgResidue_Equations_CropResidue.VEERG_6_1_1_2__1__FractionOfCropResidueRemovedBaled_Variation: _xlfn.LAMBDA("VARIATION FROM SOURCE: Added 'baled' to variable subscript")
Name AgResidue_Equations_CropResidue.VEERG_6_1_1_2__1a__FractionOfCropResidueRemoved: _xlfn.LAMBDA(_xlpm.FFOD_cbaled,_xlpm.FFOD_cother, _xlpm.FFOD_cbaled + _xlpm.FFOD_cother)
Name AgResidue_Equations_CropResidue.VEERG_6_1_1_2__1a__FractionOfCropResidueRemoved_LatexEquation: _xlfn.LAMBDA("FFOD_{c} = FFOD_{c,baled} + FFOD_{c,other}")
Name AgResidue_Equations_CropResidue.VEERG_6_1_1_2__1a__FractionOfCropResidueRemoved_NIRReference: _xlfn.LAMBDA("")
Name AgResidue_Equations_CropResidue.VEERG_6_1_1_2__1a__FractionOfCropResidueRemoved_Source: _xlfn.LAMBDA("")
Name AgResidue_Equations_CropResidue.VEERG_6_1_1_2__1a__FractionOfCropResidueRemoved_Title: _xlfn.LAMBDA("Fraction of crop residue that is removed for crop c")
Name AgResidue_Equations_CropResidue.VEERG_6_1_1_2__1a__FractionOfCropResidueRemoved_Unit: _xlfn.LAMBDA("dimensionless")
Name AgResidue_Equations_CropResidue.VEERG_6_1_1_2__1a__FractionOfCropResidueRemoved_Variable: _xlfn.LAMBDA("FFOD_c")
Name AgResidue_Equations_CropResidue.VEERG_6_1_1_2__1a__FractionOfCropResidueRemoved_Variation: _xlfn.LAMBDA("VARIATION FROM SOURCE: Added this equation to accommodate user-defined residue removal other than baling.")
Name AgResidue_Equations_FieldBurning.VEERG_6_4_1_1__1__MethaneEmissionsFromBurningOfCropResidues: _xlfn.LAMBDA(_xlpm.Mburnc,_xlpm.CCc,_xlpm.EFCH4,_xlpm.C_CH4, _xlpm.Mburnc * _xlpm.CCc * _xlpm.EFCH4 * _xlpm.C_CH4 * 10 ^ (-3))
Name AgResidue_Equations_FieldBurning.VEERG_6_4_1_1__1__MethaneEmissionsFromBurningOfCropResidues: _xlfn.LAMBDA(_xlpm.Mburnc,_xlpm.CCc,_xlpm.EFCH4,_xlpm.C_CH4, _xlpm.Mburnc * _xlpm.CCc * _xlpm.EFCH4 * _xlpm.C_CH4 * 10 ^ (-3))
Name AgResidue_Equations_FieldBurning.VEERG_6_4_1_1__1__MethaneEmissionsFromBurningOfCropResidues: _xlfn.LAMBDA(_xlpm.Mburnc,_xlpm.CCc,_xlpm.EFCH4,_xlpm.C_CH4, _xlpm.Mburnc * _xlpm.CCc * _xlpm.EFCH4 * _xlpm.C_CH4 * 10 ^ (-3))
Name AgResidue_Equations_FieldBurning.VEERG_6_4_1_1__1__MethaneEmissionsFromBurningOfCropResidues: _xlfn.LAMBDA(_xlpm.Mburnc,_xlpm.CCc,_xlpm.EFCH4,_xlpm.C_CH4, _xlpm.Mburnc * _xlpm.CCc * _xlpm.EFCH4 * _xlpm.C_CH4 * 10 ^ (-3))
Name AgResidue_Equations_FieldBurning.VEERG_6_4_1_1__1__MethaneEmissionsFromBurningOfCropResidues: _xlfn.LAMBDA(_xlpm.Mburnc,_xlpm.CCc,_xlpm.EFCH4,_xlpm.C_CH4, _xlpm.Mburnc * _xlpm.CCc * _xlpm.EFCH4 * _xlpm.C_CH4 * 10 ^ (-3))
Name AgResidue_Equations_FieldBurning.VEERG_6_4_1_1__1__MethaneEmissionsFromBurningOfCropResidues: _xlfn.LAMBDA(_xlpm.Mburnc,_xlpm.CCc,_xlpm.EFCH4,_xlpm.C_CH4, _xlpm.Mburnc * _xlpm.CCc * _xlpm.EFCH4 * _xlpm.C_CH4 * 10 ^ (-3))
Name AgResidue_Equations_FieldBurning.VEERG_6_4_1_1__1__MethaneEmissionsFromBurningOfCropResidues: _xlfn.LAMBDA(_xlpm.Mburnc,_xlpm.CCc,_xlpm.EFCH4,_xlpm.C_CH4, _xlpm.Mburnc * _xlpm.CCc * _xlpm.EFCH4 * _xlpm.C_CH4 * 10 ^ (-3))
Name AgResidue_Equations_FieldBurning.VEERG_6_4_1_1__1__MethaneEmissionsFromBurningOfCropResidues: _xlfn.LAMBDA(_xlpm.M_burnc,_xlpm.CC_c,_xlpm.EF_CH4,_xlpm.C_CH4, (_xlpm.M_burnc * _xlpm.CC_c) * _xlpm.EF_CH4 * _xlpm.C_CH4 * 10 ^ (-3))
Name AgResidue_Equations_FieldBurning.VEERG_6_4_1_1__1__MethaneEmissionsFromBurningOfCropResidues_FunctionName: _xlfn.LAMBDA("VEERG_6_4_1_1__1__MethaneEmissionsFromBurningOfCropResidues")
Name AgResidue_Equations_FieldBurning.VEERG_6_4_1_1__1__MethaneEmissionsFromBurningOfCropResidues_LatexEquation: _xlfn.LAMBDA("E_{CH4}=\sum_{c}(M_{burn,c}\times CC_{c}\times EF_{CH4}\times C_{CH4}\times 10^{-3})")
Name AgResidue_Equations_FieldBurning.VEERG_6_4_1_1__1__MethaneEmissionsFromBurningOfCropResidues_LatexEquation: _xlfn.LAMBDA("E_{CH4}=\sum_{c}(M_{burn,c}\times CC_{c}\times EF_{CH4}\times C_{CH4}\times 10^{-3})")
Name AgResidue_Equations_FieldBurning.VEERG_6_4_1_1__1__MethaneEmissionsFromBurningOfCropResidues_LatexEquation: _xlfn.LAMBDA("E_{CH4}=\sum_{c}(M_{burn,c}\times CC_{c}\times EF_{CH4}\times C_{CH4}\times 10^{-3})")
Name AgResidue_Equations_FieldBurning.VEERG_6_4_1_1__1__MethaneEmissionsFromBurningOfCropResidues_LatexEquation: _xlfn.LAMBDA("E_{CH4}=\sum_{c}(M_{burn,c}\times CC_{c}\times EF_{CH4}\times C_{CH4}\times 10^{-3})")
Name AgResidue_Equations_FieldBurning.VEERG_6_4_1_1__1__MethaneEmissionsFromBurningOfCropResidues_LatexEquation: _xlfn.LAMBDA("E_{CH4}=\sum_{c}(M_{burn,c}\times CC_{c}\times EF_{CH4}\times C_{CH4}\times 10^{-3})")
Name AgResidue_Equations_FieldBurning.VEERG_6_4_1_1__1__MethaneEmissionsFromBurningOfCropResidues_LatexEquation: _xlfn.LAMBDA("E_{CH4}=\sum_{c}(M_{burn,c}\times CC_{c}\times EF_{CH4}\times C_{CH4}\times 10^{-3})")
Name AgResidue_Equations_FieldBurning.VEERG_6_4_1_1__1__MethaneEmissionsFromBurningOfCropResidues_LatexEquation: _xlfn.LAMBDA("E_{CH4}=\sum_{c}(M_{burn,c}\times CC_{c}\times EF_{CH4}\times C_{CH4}\times 10^{-3})")
Name AgResidue_Equations_FieldBurning.VEERG_6_4_1_1__1__MethaneEmissionsFromBurningOfCropResidues_LatexEquation: _xlfn.LAMBDA("E_{CH4}=\sum\nolimits_c(M_{burn,c}\times CC_{c})\times EF_{CH4}\times C_{CH4}\times 10^{-3}")
Name AgResidue_Equations_FieldBurning.VEERG_6_4_1_1__1__MethaneEmissionsFromBurningOfCropResidues_NIRReference: _xlfn.LAMBDA("")
Name AgResidue_Equations_FieldBurning.VEERG_6_4_1_1__1__MethaneEmissionsFromBurningOfCropResidues_Source: _xlfn.LAMBDA("VEERG 2026: 6.4.1.1, Equation (1)")
Name AgResidue_Equations_FieldBurning.VEERG_6_4_1_1__1__MethaneEmissionsFromBurningOfCropResidues_Title: _xlfn.LAMBDA("Methane emissions from the burning of crop residues")
Name AgResidue_Equations_FieldBurning.VEERG_6_4_1_1__1__MethaneEmissionsFromBurningOfCropResidues_Unit: _xlfn.LAMBDA("t CH4")
Name AgResidue_Equations_FieldBurning.VEERG_6_4_1_1__1__MethaneEmissionsFromBurningOfCropResidues_Variable: _xlfn.LAMBDA("ECH4")
Name AgResidue_Equations_FieldBurning.VEERG_6_4_1_1__2__NitrousOxideEmissionsFromBurningOfCropResidues: _xlfn.LAMBDA(_xlpm.Mburnc,_xlpm.NCAGc,_xlpm.EFN2O,_xlpm.CN2O, _xlpm.Mburnc * _xlpm.NCAGc * _xlpm.EFN2O * _xlpm.CN2O * 10 ^ (-3))
Name AgResidue_Equations_FieldBurning.VEERG_6_4_1_1__2__NitrousOxideEmissionsFromBurningOfCropResidues: _xlfn.LAMBDA(_xlpm.Mburnc,_xlpm.NCAGc,_xlpm.EFN2O,_xlpm.CN2O, _xlpm.Mburnc * _xlpm.NCAGc * _xlpm.EFN2O * _xlpm.CN2O * 10 ^ (-3))
Name AgResidue_Equations_FieldBurning.VEERG_6_4_1_1__2__NitrousOxideEmissionsFromBurningOfCropResidues: _xlfn.LAMBDA(_xlpm.Mburnc,_xlpm.NCAGc,_xlpm.EFN2O,_xlpm.CN2O, _xlpm.Mburnc * _xlpm.NCAGc * _xlpm.EFN2O * _xlpm.CN2O * 10 ^ (-3))
Name AgResidue_Equations_FieldBurning.VEERG_6_4_1_1__2__NitrousOxideEmissionsFromBurningOfCropResidues: _xlfn.LAMBDA(_xlpm.Mburnc,_xlpm.NCAGc,_xlpm.EFN2O,_xlpm.CN2O, _xlpm.Mburnc * _xlpm.NCAGc * _xlpm.EFN2O * _xlpm.CN2O * 10 ^ (-3))
Name AgResidue_Equations_FieldBurning.VEERG_6_4_1_1__2__NitrousOxideEmissionsFromBurningOfCropResidues: _xlfn.LAMBDA(_xlpm.Mburnc,_xlpm.NCAGc,_xlpm.EFN2O,_xlpm.CN2O, _xlpm.Mburnc * _xlpm.NCAGc * _xlpm.EFN2O * _xlpm.CN2O * 10 ^ (-3))
Name AgResidue_Equations_FieldBurning.VEERG_6_4_1_1__2__NitrousOxideEmissionsFromBurningOfCropResidues: _xlfn.LAMBDA(_xlpm.Mburnc,_xlpm.NCAGc,_xlpm.EFN2O,_xlpm.CN2O, _xlpm.Mburnc * _xlpm.NCAGc * _xlpm.EFN2O * _xlpm.CN2O * 10 ^ (-3))

Sheet Home
A1: #VALUE!
A3: =HYPERLINK("#'Home'!A1", "Home") -> Home
A4: =HYPERLINK("#'Overview'!A1", "Overview") -> Overview
A5: =HYPERLINK("#'Results'!A1", "Results") -> Results
A8: INPUTS
A9: =HYPERLINK("#'Input - Enterprise'!A1", "Enterprise") -> Enterprise
A10: =HYPERLINK("#'Input - Site'!A1", "Site") -> Site
A11: =HYPERLINK("#'Input - Dairy'!A1", "Dairy") -> Dairy
A12: =HYPERLINK("#'Input - Dairy (Enteric)'!A1", "Dairy (Enteric)") -> Dairy (Enteric)
A13: =HYPERLINK("#'Input - Livestock sales'!A1", "Livestock sales") -> Livestock sales
A14: =HYPERLINK("#'Input - Dairy cattle purchases'!A1", "Dairy cattle purchases") -> Dairy cattle purchases
A15: =HYPERLINK("#'Input - Pasture'!A1", "Pasture") -> Pasture
A16: =HYPERLINK("#'Input - Fert Prod System'!A1", "Fert Prod System") -> Fert Prod System
A17: =HYPERLINK("#'Input - Fertiliser'!A1", "Fertiliser") -> Fertiliser
A18: =HYPERLINK("#'Input - Fuel'!A1", "Fuel") -> Fuel
A19: =HYPERLINK("#'Input - Electricity'!A1", "Electricity") -> Electricity
A20: =HYPERLINK("#'Input - Farm Inputs'!A1", "Farm Inputs") -> Farm Inputs
A21: =HYPERLINK("#'Input - Freight'!A1", "Freight") -> Freight
A22: =HYPERLINK("#'Input - Manure sent off-site'!A1", "Manure sent off-site") -> Manure sent off-site
A23: =HYPERLINK("#'Input - Solid waste'!A1", "Solid waste") -> Solid waste
A24: =HYPERLINK("#'Input - Data quality'!A1", "Data quality") -> Data quality
A27: CALCULATIONS
A28: =HYPERLINK("#'5.1.1.1-2 Inorganic fert N2O'!A1", "5.1.1.1-2 Inorganic fert N2O") -> 5.1.1.1-2 Inorganic fert N2O
A29: =HYPERLINK("#'5.1.1.3-4 Inorganic fert CO2'!A1", "5.1.1.3-4 Inorganic fert CO2") -> 5.1.1.3-4 Inorganic fert CO2
A30: =HYPERLINK("#'5.2.1.1-2 Organic Fert N2O'!A1", "5.2.1.1-2 Organic fert N2O") -> 5.2.1.1-2 Organic fert N2O
A31: =HYPERLINK("#'5.3.1.1-2 Lime CO2'!A1", "5.3.1.1-2 Lime CO2") -> 5.3.1.1-2 Lime CO2
A32: =HYPERLINK("#'5.4.1.1-4 Atmos deposition'!A1", "5.4.1.1-4 Atmos. deposition") -> 5.4.1.1-4 Atmos. deposition
A33: =HYPERLINK("#'5.5.1.1-2 Leaching and runoff'!A1", "5.5.1.1-2 Leaching & runoff") -> 5.5.1.1-2 Leaching & runoff
A34: =HYPERLINK("#'6.2.1.1-2 Pasture residue N2O'!A1", "6.2.1.1-2 Pasture residue N2O") -> 6.2.1.1-2 Pasture residue N2O
A35: =HYPERLINK("#'6.3.1.1-2 Leach runoff pasture'!A1", "6.3.1.1-2 Leach & runoff (pasture)") -> 6.3.1.1-2 Leach & runoff (pasture)
A36: =HYPERLINK("#'8.1.1.1-2 Transport fuel'!A1", "8.1.1.1-2 Transport fuel") -> 8.1.1.1-2 Transport fuel
A37: =HYPERLINK("#'8.2.1.1-2 Stationary fuel'!A1", "8.2.1.1-2 Stationary fuel") -> 8.2.1.1-2 Stationary fuel
A38: =HYPERLINK("#'14.1.1-2 Purchased electricity'!A1", "14.1.1-2 Purchased electricity") -> 14.1.1-2 Purchased electricity
A39: =HYPERLINK("#'15 Scope 3'!A1", "15 Scope 3") -> 15 Scope 3
A40: =HYPERLINK("#'Calcs - Manure sent off-site'!A1", "Calcs - Manure sent off-site") -> Calcs - Manure sent off-site
A41: =HYPERLINK("#'4.3.1.1-2 Methane'!A1", "4.3.1.1-2 Methane") -> 4.3.1.1-2 Methane
A42: =HYPERLINK("#'4.3.1.3-4 Direct N20'!A1", "4.3.1.3-4 Direct N20") -> 4.3.1.3-4 Direct N20
A43: =HYPERLINK("#'4.3.1.5 Atmos deposition'!A1", "4.3.1.5 Atmos deposition") -> 4.3.1.5 Atmos deposition
A44: =HYPERLINK("#'4.3.1.6-7 Leaching and runoff'!A1", "4.3.1.6-7 Leaching and runoff") -> 4.3.1.6-7 Leaching and runoff
A45: =HYPERLINK("#'4.3.1.8 Manure applied to soils'!A1", "4.3.1.8 Manure applied to soils") -> 4.3.1.8 Manure applied to soils
A46: =HYPERLINK("#'4.3.1.9 Soil direct N2O'!A1", "4.3.1.9 Soil direct N2O") -> 4.3.1.9 Soil direct N2O
A47: =HYPERLINK("#'4.3.1.10-11 Soil Atmos Dep'!A1", "4.3.1.10-11 Soil Atmos Dep") -> 4.3.1.10-11 Soil Atmos Dep
A48: =HYPERLINK("#'4.3.1.12-13 Soil leach runoff'!A1", "4.3.1.12-13 Soil leach runoff") -> 4.3.1.12-13 Soil leach runoff
A49: =HYPERLINK("#'3.3.1.1-2 Enteric Methane'!A1", "3.3.1.1-2 Enteric Methane") -> 3.3.1.1-2 Enteric Methane
A50: =HYPERLINK("#'10.1.1-2 Solid waste treatment'!A1", "10.1.1-2 Solid waste treatment") -> 10.1.1-2 Solid waste treatment
A53: APPENDICES
A54: =HYPERLINK("#'Constants - Dairy'!A1", "Constants - Dairy") -> Constants - Dairy
A55: =HYPERLINK("#'Constants - Ag Residue'!A1", "Constants - Ag residue") -> Constants - Ag residue
A56: =HYPERLINK("#'Constants - Common Livestock'!A1", "Constants - Common Livestock") -> Constants - Common Livestock
A57: =HYPERLINK("#'Constants - Electricity'!A1", "Constants - Electricity") -> Constants - Electricity
A58: =HYPERLINK("#'Constants - Fertiliser'!A1", "Constants - Fertiliser") -> Constants - Fertiliser
A59: =HYPERLINK("#'Constants - Fuel'!A1", "Constants - Fuel") -> Constants - Fuel
A60: =HYPERLINK("#'Constants - Scope 3'!A1", "Constants - Scope 3") -> Constants - Scope 3
A61: =HYPERLINK("#'Constants - Common'!A1", "Constants - Common") -> Constants - Common
A62: =HYPERLINK("#'Acknowledgements'!A1", "Acknowledgements") -> Acknowledgements
A63: =HYPERLINK("#'Constants - Solid Waste'!A1", "Constants - Solid Waste") -> Constants - Solid Waste

Sheet Results
A1: #VALUE! | C1: Enterprise: Dairy: Results
A3: =HYPERLINK("#'Home'!A1", "Home") -> Home
A4: =HYPERLINK("#'Overview'!A1", "Overview") -> Overview | D4: ="Emissions breakdown for activities running between " & TEXT(X_Cell_Site_StartDate, "dd mmmm yyyy") & " and " & TEXT('Input - Enterprise'!E13, "dd mmmm yyyy") -> Emissions breakdown for activities running between 01 January 2024 and 31 December 2024
A5: =HYPERLINK("#'Results'!A1", "Results") -> Results
D6: Scope 1 source | E6: GHG emissions method 1 | F6: GHG emissions method 2 | G6: GHG Unit | H6: CO2-e emissions method 1 | I6: CO2-e emissions method 2
D7: 3.3.1.1-2 Enteric methane | E7: {=VEERG_3_3_1_1__1_TotalAnnualMethaneFromEntericFermentationVariation_Result_Method1} -> 32.464683 | F7: {=VEERG_3_3_1_1__1_TotalAnnualMethaneFromEntericFermentationVariation_Result_Method2} -> 32.464683 | G7: t CH4 | H7: {=Common_Equations.Common_ConvertCH4ToCO2e(E7,_xlfn.XLOOKUP("CH4", Table_GWPData[Gas],Table_GWPData[CO2-e factor]))} -> 909.01112 | I7: {=Common_Equations.Common_ConvertCH4ToCO2e(F7,_xlfn.XLOOKUP("CH4", Table_GWPData[Gas],Table_GWPData[CO2-e factor]))} -> 909.01112 | J7: t CO2e
A8: INPUTS | D8: 4.3.1.1-2 Manure methane | E8: {=VEERG_4_3_1_1__1_TotalAnnualMethaneFromManureManagement_Result_Method1} -> 10.314346 | F8: {=VEERG_4_3_1_1__1_TotalAnnualMethaneFromManureManagement_Result_Method2} -> 10.640707 | G8: t CH4 | H8: {=Common_Equations.Common_ConvertCH4ToCO2e(E8,_xlfn.XLOOKUP("CH4", Table_GWPData[Gas],Table_GWPData[CO2-e factor]))} -> 288.80168 | I8: {=Common_Equations.Common_ConvertCH4ToCO2e(F8,_xlfn.XLOOKUP("CH4", Table_GWPData[Gas],Table_GWPData[CO2-e factor]))} -> 297.93979 | J8: t CO2e
A9: =HYPERLINK("#'Input - Enterprise'!A1", "Enterprise") -> Enterprise | D9: 4.3.1.3-4 Manure direct N2O | E9: {=VEERG_4_3_1_3__1_TotalAnnualDirectNitrousOxideEmissionsFromMMS_Result_Method1} -> 0.058975626 | F9: {=VEERG_4_3_1_3__1_TotalAnnualDirectNitrousOxideEmissionsFromMMS_Result_Method2} -> 0.058975626 | G9: t N2O | H9: {=Common_Equations.Common_ConvertN2OToCO2e(E9,_xlfn.XLOOKUP("N2O", Table_GWPData[Gas],Table_GWPData[CO2-e factor]))} -> 15.628541 | I9: {=Common_Equations.Common_ConvertN2OToCO2e(F9,_xlfn.XLOOKUP("N2O", Table_GWPData[Gas],Table_GWPData[CO2-e factor]))} -> 15.628541 | J9: t CO2e
A10: =HYPERLINK("#'Input - Site'!A1", "Site") -> Site | D10: 4.3.1.5 Manure atmospheric deposition | E10: {=VEERG_4_3_1_5__1_AnnualAtmosphericDepositionEmissionsFromMMS_Result_Method1} -> 0.047299753 | F10: {=VEERG_4_3_1_5__1_AnnualAtmosphericDepositionEmissionsFromMMS_Result_Method2} -> 0.047299753 | G10: t N2O | H10: {=Common_Equations.Common_ConvertN2OToCO2e(E10,_xlfn.XLOOKUP("N2O", Table_GWPData[Gas],Table_GWPData[CO2-e factor]))} -> 12.534435 | I10: {=Common_Equations.Common_ConvertN2OToCO2e(F10,_xlfn.XLOOKUP("N2O", Table_GWPData[Gas],Table_GWPData[CO2-e factor]))} -> 12.534435 | J10: t CO2e
A11: =HYPERLINK("#'Input - Dairy'!A1", "Dairy") -> Dairy | D11: 4.3.1.6-7 Manure leaching and runoff | E11: {=VEERG_4_3_1_6__1_AnnualEmissionsFromLeachingAndRunoffFromMMS_Result_Method1} -> 0.0025949275 | F11: {=VEERG_4_3_1_6__1_AnnualEmissionsFromLeachingAndRunoffFromMMS_Result_Method2} -> 0.0025949275 | G11: t N2O | H11: {=Common_Equations.Common_ConvertN2OToCO2e(E11,_xlfn.XLOOKUP("N2O", Table_GWPData[Gas],Table_GWPData[CO2-e factor]))} -> 0.6876558 | I11: {=Common_Equations.Common_ConvertN2OToCO2e(F11,_xlfn.XLOOKUP("N2O", Table_GWPData[Gas],Table_GWPData[CO2-e factor]))} -> 0.6876558 | J11: t CO2e
A12: =HYPERLINK("#'Input - Dairy (Enteric)'!A1", "Dairy (Enteric)") -> Dairy (Enteric) | D12: 4.3.1.9 Soil direct N2O | E12: {=VEERG_4_3_1_9__1_DirectNitrousOxideEmissionsOnPasture_Result_Method1} -> 0.074716451 | F12: {=VEERG_4_3_1_9__1_DirectNitrousOxideEmissionsOnPasture_Result_Method2} -> 0.074716451 | G12: t N2O | H12: {=Common_Equations.Common_ConvertN2OToCO2e(E12,_xlfn.XLOOKUP("N2O", Table_GWPData[Gas],Table_GWPData[CO2-e factor]))} -> 19.79986 | I12: {=Common_Equations.Common_ConvertN2OToCO2e(F12,_xlfn.XLOOKUP("N2O", Table_GWPData[Gas],Table_GWPData[CO2-e factor]))} -> 19.79986 | J12: t CO2e
A13: =HYPERLINK("#'Input - Livestock sales'!A1", "Livestock sales") -> Livestock sales | D13: 4.3.1.10-11 Soil atmospheric deposition | E13: {=VEERG_4_3_1_10__1_AtmosphericDepositionEmissionsFromUrineAndDungOnPasture_Result_Method1} -> 0.046286842 | F13: {=VEERG_4_3_1_10__1_AtmosphericDepositionEmissionsFromUrineAndDungOnPasture_Result_Method2} -> 0.046286842 | G13: t N2O | H13: {=Common_Equations.Common_ConvertN2OToCO2e(E13,_xlfn.XLOOKUP("N2O", Table_GWPData[Gas],Table_GWPData[CO2-e factor]))} -> 12.266013 | I13: {=Common_Equations.Common_ConvertN2OToCO2e(F13,_xlfn.XLOOKUP("N2O", Table_GWPData[Gas],Table_GWPData[CO2-e factor]))} -> 12.266013 | J13: t CO2e
A14: =HYPERLINK("#'Input - Dairy cattle purchases'!A1", "Dairy cattle purchases") -> Dairy cattle purchases | D14: 4.3.1.12-13 Soil leaching and runoff | E14: {=VEERG_4_3_1_12__1_LeachingAndRunoffEmissionsFromUrineAndDungOnPasture_Result_Method1} -> 0.098625716 | F14: {=VEERG_4_3_1_12__1_LeachingAndRunoffEmissionsFromUrineAndDungOnPasture_Result_Method2} -> 0.098625716 | G14: t N2O | H14: {=Common_Equations.Common_ConvertN2OToCO2e(E14,_xlfn.XLOOKUP("N2O", Table_GWPData[Gas],Table_GWPData[CO2-e factor]))} -> 26.135815 | I14: {=Common_Equations.Common_ConvertN2OToCO2e(F14,_xlfn.XLOOKUP("N2O", Table_GWPData[Gas],Table_GWPData[CO2-e factor]))} -> 26.135815 | J14: t CO2e
A15: =HYPERLINK("#'Input - Pasture'!A1", "Pasture") -> Pasture | D15: 5.1.1.1-2 Inorganic fert N2O | E15: {=VEERG_5_1_1_1__1_InorganicFertiliserApplicationN2OEmissions_Result_Method1} -> 1.206185 | F15: {=VEERG_5_1_1_1__1_InorganicFertiliserApplicationN2OEmissions_Result_Method2} -> 1.206185 | G15: t N2O | H15: {=Common_Equations.Common_ConvertN2OToCO2e(E15,_xlfn.XLOOKUP("N2O", Table_GWPData[Gas],Table_GWPData[CO2-e factor]))} -> 319.63904 | I15: {=Common_Equations.Common_ConvertN2OToCO2e(F15,_xlfn.XLOOKUP("N2O", Table_GWPData[Gas],Table_GWPData[CO2-e factor]))} -> 319.63904 | J15: t CO2e
A16: =HYPERLINK("#'Input - Fert Prod System'!A1", "Fert Prod System") -> Fert Prod System | D16: 5.1.1.3-4 Inorganic fert CO2 | E16: {=VEERG_5_1_1_3__1_InorganicFertiliserApplicationCO2Emissions_Result_Method1} -> 73.333333 | F16: =E16 -> 73.333333 | G16: t CO2 | H16: =E16 -> 73.333333 | I16: =F16 -> 73.333333 | J16: t CO2e
A17: =HYPERLINK("#'Input - Fertiliser'!A1", "Fertiliser") -> Fertiliser | D17: 5.2.1.1-2 Organic fert N2O | E17: {=VEERG_5_2_1_1__2_MassOfNitrogenInOrganicFertiliser_Result_Method1} -> 0.055785714 | F17: =E17 -> 0.055785714 | G17: t N2O | H17: {=Common_Equations.Common_ConvertN2OToCO2e(E17,_xlfn.XLOOKUP("N2O", Table_GWPData[Gas],Table_GWPData[CO2-e factor]))} -> 14.783214 | I17: {=Common_Equations.Common_ConvertN2OToCO2e(F17,_xlfn.XLOOKUP("N2O", Table_GWPData[Gas],Table_GWPData[CO2-e factor]))} -> 14.783214 | J17: t CO2e
A18: =HYPERLINK("#'Input - Fuel'!A1", "Fuel") -> Fuel | D18: 5.3.1.1-2 Lime CO2 | E18: {=VEERG_5_3_1_1__1_LimeApplicationCO2Emissions_Result_Method1} -> 758.08333 | F18: =E18 -> 758.08333 | G18: t CO2 | H18: =E18 -> 758.08333 | I18: =F18 -> 758.08333 | J18: t CO2e
A19: =HYPERLINK("#'Input - Electricity'!A1", "Electricity") -> Electricity | D19: 5.4.1.1-4 Atmos. deposition | E19: {=VEERG_5_4_1_3__1_OrganicFertiliserAtmosphericDepositionN2OEmissions_Result_Method1} -> 0.0138237 | F19: =E19 -> 0.0138237 | G19: t N2O | H19: {=Common_Equations.Common_ConvertN2OToCO2e(E19,_xlfn.XLOOKUP("N2O", Table_GWPData[Gas],Table_GWPData[CO2-e factor]))} -> 3.6632805 | I19: {=Common_Equations.Common_ConvertN2OToCO2e(F19,_xlfn.XLOOKUP("N2O", Table_GWPData[Gas],Table_GWPData[CO2-e factor]))} -> 3.6632805 | J19: t CO2e
A20: =HYPERLINK("#'Input - Farm Inputs'!A1", "Farm Inputs") -> Farm Inputs | D20: 5.5.1.1-2 Leaching & runoff | E20: {=VEERG_5_5_1_1__1_FertiliserLeachingAndRunoffN2OEmissions_result_Method1} -> 0.56917155 | F20: =E20 -> 0.56917155 | G20: t N2O | H20: {=Common_Equations.Common_ConvertN2OToCO2e(E20,_xlfn.XLOOKUP("N2O", Table_GWPData[Gas],Table_GWPData[CO2-e factor]))} -> 150.83046 | I20: {=Common_Equations.Common_ConvertN2OToCO2e(F20,_xlfn.XLOOKUP("N2O", Table_GWPData[Gas],Table_GWPData[CO2-e factor]))} -> 150.83046 | J20: t CO2e
A21: =HYPERLINK("#'Input - Freight'!A1", "Freight") -> Freight | D21: 6.2.1.1-2 Pasture residue N2O | E21: {=VEERG_6_2_1_1__1__NitrousOxideEmissionsFromPastureResidues_Result_Method1} -> 5.8320429e-07 | F21: {=VEERG_6_2_1_1__1__NitrousOxideEmissionsFromPastureResidues_Result_Method2} -> 5.8320429e-07 | G21: t N2O | H21: {=Common_Equations.Common_ConvertN2OToCO2e(E21,_xlfn.XLOOKUP("N2O", Table_GWPData[Gas],Table_GWPData[CO2-e factor]))} -> 0.00015454914 | I21: {=Common_Equations.Common_ConvertN2OToCO2e(F21,_xlfn.XLOOKUP("N2O", Table_GWPData[Gas],Table_GWPData[CO2-e factor]))} -> 0.00015454914 | J21: t CO2e
A22: =HYPERLINK("#'Input - Manure sent off-site'!A1", "Manure sent off-site") -> Manure sent off-site | D22: 6.3.1.1-2 Leach & runoff (pasture) | E22: {=VEERG_6_3_1_1__1__LeachingAndRunoffEmissionsCropAndPastureResidue_PastureOnly_Result_Method1} -> 3.0793186e-07 | F22: {=VEERG_6_3_1_1__1__LeachingAndRunoffEmissionsCropAndPastureResidue_PastureOnly_Result_Method2} -> 3.0793186e-07 | G22: t N2O | H22: {=Common_Equations.Common_ConvertN2OToCO2e(E22,_xlfn.XLOOKUP("N2O", Table_GWPData[Gas],Table_GWPData[CO2-e factor]))} -> 8.1601944e-05 | I22: {=Common_Equations.Common_ConvertN2OToCO2e(F22,_xlfn.XLOOKUP("N2O", Table_GWPData[Gas],Table_GWPData[CO2-e factor]))} -> 8.1601944e-05 | J22: t CO2e
A23: =HYPERLINK("#'Input - Solid waste'!A1", "Solid waste") -> Solid waste | D23: 8.1.1.1-2 Transport fuel CO2 | E23: {=VEERG_8_1_1_1__1_FuelCombustionTransport_Result_CO2} -> 83.182 | F23: =E23 -> 83.182 | G23: t CO2 | H23: =E23 -> 83.182 | I23: =F23 -> 83.182 | J23: t CO2e
A24: =HYPERLINK("#'Input - Data quality'!A1", "Data quality") -> Data quality | D24: 8.1.1.1-2 Transport fuel CH4 | E24: {=VEERG_8_1_1_1__1_FuelCombustionTransport_Result_CH4} -> 0.19906 | F24: =E24 -> 0.19906 | G24: t CH4 | H24: {=Common_Equations.Common_ConvertCH4ToCO2e(E24,_xlfn.XLOOKUP("CH4", Table_GWPData[Gas],Table_GWPData[CO2-e factor]))} -> 5.57368 | I24: {=Common_Equations.Common_ConvertCH4ToCO2e(F24,_xlfn.XLOOKUP("CH4", Table_GWPData[Gas],Table_GWPData[CO2-e factor]))} -> 5.57368 | J24: t CO2e
D25: 8.1.1.1-2 Transport fuel N2O | E25: {=VEERG_8_1_1_1__1_FuelCombustionTransport_Result_N2O} -> 0.5845 | F25: =E25 -> 0.5845 | G25: t N2O | H25: {=Common_Equations.Common_ConvertN2OToCO2e(E25,_xlfn.XLOOKUP("N2O", Table_GWPData[Gas],Table_GWPData[CO2-e factor]))} -> 154.8925 | I25: {=Common_Equations.Common_ConvertN2OToCO2e(F25,_xlfn.XLOOKUP("N2O", Table_GWPData[Gas],Table_GWPData[CO2-e factor]))} -> 154.8925 | J25: t CO2e
D26: 8.2.1.1-2 Stationary fuel CO2 | E26: {=VEERG_8_2_1_1__1_FuelCombustionStationary_Result_CO2} -> 29.0708 | F26: =E26 -> 29.0708 | G26: t CO2 | H26: =E26 -> 29.0708 | I26: =F26 -> 29.0708 | J26: t CO2e
A27: CALCULATIONS | D27: 8.2.1.1-2 Stationary fuel CH4 | E27: {=VEERG_8_2_1_1__1_FuelCombustionStationary_Result_CH4} -> 0.0724 | F27: =E27 -> 0.0724 | G27: t CH4 | H27: {=Common_Equations.Common_ConvertCH4ToCO2e(E27,_xlfn.XLOOKUP("CH4", Table_GWPData[Gas],Table_GWPData[CO2-e factor]))} -> 2.0272 | I27: {=Common_Equations.Common_ConvertCH4ToCO2e(F27,_xlfn.XLOOKUP("CH4", Table_GWPData[Gas],Table_GWPData[CO2-e factor]))} -> 2.0272 | J27: t CO2e
A28: =HYPERLINK("#'5.1.1.1-2 Inorganic fert N2O'!A1", "5.1.1.1-2 Inorganic fert N2O") -> 5.1.1.1-2 Inorganic fert N2O | D28: 8.2.1.1-2 Stationary fuel N2O | E28: {=VEERG_8_2_1_1__1_FuelCombustionStationary_Result_N2O} -> 0.0714 | F28: =E28 -> 0.0714 | G28: t N2O | H28: {=Common_Equations.Common_ConvertN2OToCO2e(E28,_xlfn.XLOOKUP("N2O", Table_GWPData[Gas],Table_GWPData[CO2-e factor]))} -> 18.921 | I28: {=Common_Equations.Common_ConvertN2OToCO2e(F28,_xlfn.XLOOKUP("N2O", Table_GWPData[Gas],Table_GWPData[CO2-e factor]))} -> 18.921 | J28: t CO2e
A29: =HYPERLINK("#'5.1.1.3-4 Inorganic fert CO2'!A1", "5.1.1.3-4 Inorganic fert CO2") -> 5.1.1.3-4 Inorganic fert CO2 | D29: 14.1.1-2 Purchased electricity (Location-based) | E29: {=VEERG_14_1_1__1_LocationBasedScopeElectricityEmissions_Result_Method1} -> 16.8 | F29: =E29 -> 16.8 | G29: t CO2e | H29: =E29 -> 16.8 | I29: =F29 -> 16.8 | J29: t CO2e
A30: =HYPERLINK("#'5.2.1.1-2 Organic Fert N2O'!A1", "5.2.1.1-2 Organic fert N2O") -> 5.2.1.1-2 Organic fert N2O | D30: 14.1.1-2 Purchased electricity (Market-based) | E30: {=VEERG_14_1_2__1_MarketBasedScopeElectricityEmissionsVariation_Result_Method1} -> 14.58 | F30: =E30 -> 14.58 | G30: t CO2e | H30: =E30 -> 14.58 | I30: =F30 -> 14.58 | J30: t CO2e
A31: =HYPERLINK("#'5.3.1.1-2 Lime CO2'!A1", "5.3.1.1-2 Lime CO2") -> 5.3.1.1-2 Lime CO2 | D31: Total | H31: =SUM(H7:H30) -> 2930.2452 | I31: =SUM(I7:I30) -> 2939.3833 | J31: t CO2e
A32: =HYPERLINK("#'5.4.1.1-4 Atmos deposition'!A1", "5.4.1.1-4 Atmos. deposition") -> 5.4.1.1-4 Atmos. deposition
A33: =HYPERLINK("#'5.5.1.1-2 Leaching and runoff'!A1", "5.5.1.1-2 Leaching & runoff") -> 5.5.1.1-2 Leaching & runoff
A34: =HYPERLINK("#'6.2.1.1-2 Pasture residue N2O'!A1", "6.2.1.1-2 Pasture residue N2O") -> 6.2.1.1-2 Pasture residue N2O
A35: =HYPERLINK("#'6.3.1.1-2 Leach runoff pasture'!A1", "6.3.1.1-2 Leach & runoff (pasture)") -> 6.3.1.1-2 Leach & runoff (pasture) | D35: Emissions for whole production cycle
A36: =HYPERLINK("#'8.1.1.1-2 Transport fuel'!A1", "8.1.1.1-2 Transport fuel") -> 8.1.1.1-2 Transport fuel | D36: {="There are " & Common_InputFunctions.getOverlappingReportingCycles(X_Cell_Enterprise_ProductionTimeframeStart,X_Cell_Enterprise_ProductionTimeframeEnd,X_Cell_Site_StartDate) & " emissions calculation periods that need to be completed before total product emissions can be determined."} -> There are 3 emissions calculation periods that need to be completed before total product emissions can be determined.
A37: =HYPERLINK("#'8.2.1.1-2 Stationary fuel'!A1", "8.2.1.1-2 Stationary fuel") -> 8.2.1.1-2 Stationary fuel | D37: Enter the method 1 and 2 CO2e emissions from prevoius emissions calculation periods if applicable.
A38: =HYPERLINK("#'14.1.1-2 Purchased electricity'!A1", "14.1.1-2 Purchased electricity") -> 14.1.1-2 Purchased electricity
A39: =HYPERLINK("#'15 Scope 3'!A1", "15 Scope 3") -> 15 Scope 3 | D39: Emissions calculation cycle | E39: CO2-e emissions method 1 | F39: CO2-e emissions method 2
A40: =HYPERLINK("#'Calcs - Manure sent off-site'!A1", "Calcs - Manure sent off-site") -> Calcs - Manure sent off-site | D40: {=Common_InputFunctions.getOverlappingReportingPeriods(X_Cell_Enterprise_ProductionTimeframeStart,X_Cell_Enterprise_ProductionTimeframeEnd,X_Cell_Site_StartDate)} -> 01 Jan 2023 to 31 Dec 2023 | E40: =IF(ISBLANK($D40), 0, IF(ISNUMBER(SEARCH("reporting", $D40)), Result_Enterprise_Method1, "Enter value")) -> Enter value | F40: =IF(ISBLANK($D40), 0, IF(ISNUMBER(SEARCH("reporting", $D40)), Result_Enterprise_Method2, "Enter value")) -> Enter value | G40: t CO2e
A41: =HYPERLINK("#'4.3.1.1-2 Methane'!A1", "4.3.1.1-2 Methane") -> 4.3.1.1-2 Methane | D41: 01 Jan 2024 to 31 Dec 2024 (This reporting cycle) | E41: =IF(ISBLANK($D41), 0, IF(ISNUMBER(SEARCH("reporting", $D41)), Result_Enterprise_Method1, "Enter value")) -> 2930.2452 | F41: =IF(ISBLANK($D41), 0, IF(ISNUMBER(SEARCH("reporting", $D41)), Result_Enterprise_Method2, "Enter value")) -> 2939.3833 | G41: t CO2e
A42: =HYPERLINK("#'4.3.1.3-4 Direct N20'!A1", "4.3.1.3-4 Direct N20") -> 4.3.1.3-4 Direct N20 | D42: 01 Jan 2025 to 31 Dec 2025 | E42: =IF(ISBLANK($D42), 0, IF(ISNUMBER(SEARCH("reporting", $D42)), Result_Enterprise_Method1, "Enter value")) -> Enter value | F42: =IF(ISBLANK($D42), 0, IF(ISNUMBER(SEARCH("reporting", $D42)), Result_Enterprise_Method2, "Enter value")) -> Enter value | G42: t CO2e
A43: =HYPERLINK("#'4.3.1.5 Atmos deposition'!A1", "4.3.1.5 Atmos deposition") -> 4.3.1.5 Atmos deposition | E43: =IF(ISBLANK($D43), 0, IF(ISNUMBER(SEARCH("reporting", $D43)), Result_Enterprise_Method1, "Enter value")) -> 0 | F43: =IF(ISBLANK($D43), 0, IF(ISNUMBER(SEARCH("reporting", $D43)), Result_Enterprise_Method2, "Enter value")) -> 0 | G43: t CO2e
A44: =HYPERLINK("#'4.3.1.6-7 Leaching and runoff'!A1", "4.3.1.6-7 Leaching and runoff") -> 4.3.1.6-7 Leaching and runoff | E44: =IF(ISBLANK($D44), 0, IF(ISNUMBER(SEARCH("reporting", $D44)), Result_Enterprise_Method1, "Enter value")) -> 0 | F44: =IF(ISBLANK($D44), 0, IF(ISNUMBER(SEARCH("reporting", $D44)), Result_Enterprise_Method2, "Enter value")) -> 0 | G44: t CO2e
A45: =HYPERLINK("#'4.3.1.8 Manure applied to soils'!A1", "4.3.1.8 Manure applied to soils") -> 4.3.1.8 Manure applied to soils | D45: Total emissions for production cycle | E45: =SUM(E40:E44) -> 2930.2452 | F45: =SUM(F40:F44) -> 2939.3833
A46: =HYPERLINK("#'4.3.1.9 Soil direct N2O'!A1", "4.3.1.9 Soil direct N2O") -> 4.3.1.9 Soil direct N2O
A47: =HYPERLINK("#'4.3.1.10-11 Soil Atmos Dep'!A1", "4.3.1.10-11 Soil Atmos Dep") -> 4.3.1.10-11 Soil Atmos Dep
A48: =HYPERLINK("#'4.3.1.12-13 Soil leach runoff'!A1", "4.3.1.12-13 Soil leach runoff") -> 4.3.1.12-13 Soil leach runoff | D48: Carbon removals from plantings
A49: =HYPERLINK("#'3.3.1.1-2 Enteric Methane'!A1", "3.3.1.1-2 Enteric Methane") -> 3.3.1.1-2 Enteric Methane
A50: =HYPERLINK("#'10.1.1-2 Solid waste treatment'!A1", "10.1.1-2 Solid waste treatment") -> 10.1.1-2 Solid waste treatment | D50: Emissions calculation cycle | E50: CO2 removed attributed to this enterprise
D51: {=Common_InputFunctions.getOverlappingReportingPeriods(X_Cell_Enterprise_ProductionTimeframeStart,X_Cell_Enterprise_ProductionTimeframeEnd,X_Cell_Site_StartDate)} -> 01 Jan 2023 to 31 Dec 2023 | E51: =IF(ISBLANK(D51), 0, "Enter value") -> Enter value | F51: t CO2
D52: 01 Jan 2024 to 31 Dec 2024 (This reporting cycle) | E52: =IF(ISBLANK(D52), 0, "Enter value") -> Enter value | F52: t CO2
A53: APPENDICES | D53: 01 Jan 2025 to 31 Dec 2025 | E53: =IF(ISBLANK(D53), 0, "Enter value") -> Enter value | F53: t CO2
A54: =HYPERLINK("#'Constants - Dairy'!A1", "Constants - Dairy") -> Constants - Dairy | E54: =IF(ISBLANK(D54), 0, "Enter value") -> 0 | F54: t CO2
A55: =HYPERLINK("#'Constants - Ag Residue'!A1", "Constants - Ag residue") -> Constants - Ag residue | E55: =IF(ISBLANK(D55), 0, "Enter value") -> 0 | F55: t CO2
A56: =HYPERLINK("#'Constants - Common Livestock'!A1", "Constants - Common Livestock") -> Constants - Common Livestock | D56: Total carbon removals for production cycle | E56: =SUM(E51:E55) -> 0
A57: =HYPERLINK("#'Constants - Electricity'!A1", "Constants - Electricity") -> Constants - Electricity
A58: =HYPERLINK("#'Constants - Fertiliser'!A1", "Constants - Fertiliser") -> Constants - Fertiliser
A59: =HYPERLINK("#'Constants - Fuel'!A1", "Constants - Fuel") -> Constants - Fuel | D59: Product emissions
A60: =HYPERLINK("#'Constants - Scope 3'!A1", "Constants - Scope 3") -> Constants - Scope 3
A61: =HYPERLINK("#'Constants - Common'!A1", "Constants - Common") -> Constants - Common | E61: Method 1 | F61: Method 2
A62: =HYPERLINK("#'Acknowledgements'!A1", "Acknowledgements") -> Acknowledgements | D62: Net emissions | E62: =E45-E56 -> 2930.2452 | F62: =F45-E56 -> 2939.3833
A63: =HYPERLINK("#'Constants - Solid Waste'!A1", "Constants - Solid Waste") -> Constants - Solid Waste
D65: Product emissions - Mass
D66: Product | E66: Product type | F66: Amount (tonnnes) | G66: Mass emissions assignment | H66: Emissions intensity (Method 1) | I66: Emissions intensity (Method 2) | J66: Unit
D67: Milk sold - excluding removals | E67: Main product | F67: ='Input - Enterprise'!E24 -> 7519 | G67: =F67/(F67+F69+F71) -> 0.99920266 | H67: =(Result_EmissionsForWholeProductionCycle_Method1/F67)*G67 -> 0.38940135 | I67: =(Result_EmissionsForWholeProductionCycle_Method2/F67)*G67 -> 0.39061572 | J67: t co2e/t milk solids
D68: Milk sold - net emissions | E68: Main product | F68: =F67 -> 7519 | G68: =G67 -> 0.99920266 | H68: =(Result_NetEmissions_Method1/F68)*G68 -> 0.38940135 | I68: =(Result_NetEmissions_Method2/F68)*G68 -> 0.39061572 | J68: t co2e/t milk solids
D69: Liveweight sold - excluding removals | E69: Main product | F69: ='Input - Enterprise'!E22 -> 5 | G69: =F69/(F67+F69+F71) -> 0.00066445183 | H69: =(Result_EmissionsForWholeProductionCycle_Method1/F69)*G69 -> 0.38940135 | I69: =(Result_EmissionsForWholeProductionCycle_Method2/F69)*G69 -> 0.39061572 | J69: t co2e/t liveweight sold
D70: Liveweight sold - net emissions | E70: Main product | F70: =F69 -> 5 | G70: =G69 -> 0.00066445183 | H70: =(Result_NetEmissions_Method1/F70)*G70 -> 0.38940135 | I70: =(Result_NetEmissions_Method2/F70)*G70 -> 0.39061572 | J70: t co2e/t liveweight sold
D71: Manure sold - excluding removals | E71: Co-product | F71: ='Input - Enterprise'!E25 -> 1 | G71: =F71/(F67+F69+F71) -> 0.00013289037 | H71: =(Result_EmissionsForWholeProductionCycle_Method1/F71)*G71 -> 0.38940135 | I71: =(Result_EmissionsForWholeProductionCycle_Method2/F71)*G71 -> 0.39061572 | J71: t co2e/t manure
D72: Manure sold - net emissions | E72: Co-product | F72: =F71 -> 1 | G72: =G71 -> 0.00013289037 | H72: =(Result_NetEmissions_Method1/F72)*G72 -> 0.38940135 | I72: =(Result_NetEmissions_Method2/F72)*G72 -> 0.39061572 | J72: t co2e/t manure
D75: Product emissions - Economic
D76: Product | E76: Product type | F76: Amount (tonnnes) | G76: Economic emissions assignment | H76: Emissions intensity (Method 1) | I76: Emissions intensity (Method 2) | J76: Unit
D77: Milk sold - excluding removals | E77: Main product | F77: =F67 -> 7519 | G77: ='Input - Enterprise'!E29 -> 0.8 | H77: =(Result_EmissionsForWholeProductionCycle_Method1/F77)*G77 -> 0.31176967 | I77: =(Result_EmissionsForWholeProductionCycle_Method2/F77)*G77 -> 0.31274194 | J77: t co2e/t milk solids
D78: Milk sold - net emissions | E78: Main product | F78: =F68 -> 7519 | G78: =G77 -> 0.8 | H78: =(Result_NetEmissions_Method1/F78)*G78 -> 0.31176967 | I78: =(Result_NetEmissions_Method2/F78)*G78 -> 0.31274194 | J78: t co2e/t milk solids
D79: Liveweight sold - excluding removals | E79: Main product | F79: =F69 -> 5 | G79: ='Input - Enterprise'!E27 -> 0.15 | H79: =(Result_EmissionsForWholeProductionCycle_Method1/F79)*G79 -> 87.907356 | I79: =(Result_EmissionsForWholeProductionCycle_Method2/F79)*G79 -> 88.181499 | J79: t co2e/t liveweight sold
D80: Liveweight sold - net emissions | E80: Main product | F80: =F69 -> 5 | G80: =G79 -> 0.15 | H80: =(Result_NetEmissions_Method1/F80)*G80 -> 87.907356 | I80: =(Result_NetEmissions_Method2/F80)*G80 -> 88.181499 | J80: t co2e/t liveweight sold
D81: Manure sold - excluding removals | E81: Co-product | F81: =F71 -> 1 | G81: ='Input - Enterprise'!E28 -> 0.05 | H81: =(Result_EmissionsForWholeProductionCycle_Method1/F81)*G81 -> 146.51226 | I81: =(Result_EmissionsForWholeProductionCycle_Method2/F81)*G81 -> 146.96916 | J81: t co2e/t manure
D82: Manure sold - net emissions | E82: Co-product | F82: =F72 -> 1 | G82: =G81 -> 0.05 | H82: =(Result_NetEmissions_Method1/F82)*G82 -> 146.51226 | I82: =(Result_NetEmissions_Method2/F82)*G82 -> 146.96916 | J82: t co2e/t manure

Sheet Input - Enterprise
A1: #VALUE! | C1: Input - Enterprise
A3: =HYPERLINK("#'Home'!A1", "Home") -> Home
A4: =HYPERLINK("#'Overview'!A1", "Overview") -> Overview
A5: =HYPERLINK("#'Results'!A1", "Results") -> Results | D5: Your business
D7: Farm name | E7: Test Farms
A8: INPUTS | D8: Reporting entity name | E8: Test Farms Pty Ltd
A9: =HYPERLINK("#'Input - Enterprise'!A1", "Enterprise") -> Enterprise
A10: =HYPERLINK("#'Input - Site'!A1", "Site") -> Site | D10: 💡An 'Emissions accounting period' is a 12 month period where the business can report on the emissions, and is typically the same as the business' financial accounting period.
A11: =HYPERLINK("#'Input - Dairy'!A1", "Dairy") -> Dairy
A12: =HYPERLINK("#'Input - Dairy (Enteric)'!A1", "Dairy (Enteric)") -> Dairy (Enteric) | D12: Emissions calculation period start date | E12: 45292 | F12: ← DD/MM/YYYY or DD Month YYYY
A13: =HYPERLINK("#'Input - Livestock sales'!A1", "Livestock sales") -> Livestock sales | D13: Emissions calculation period end date | E13: =DATE(YEAR(E12)+1,MONTH(E12),DAY(E12))-1 -> 45657 | F13: ← Automatically calculated, 12 months after start date
A14: =HYPERLINK("#'Input - Dairy cattle purchases'!A1", "Dairy cattle purchases") -> Dairy cattle purchases
A15: =HYPERLINK("#'Input - Pasture'!A1", "Pasture") -> Pasture
A16: =HYPERLINK("#'Input - Fert Prod System'!A1", "Fert Prod System") -> Fert Prod System | D16: Production
A17: =HYPERLINK("#'Input - Fertiliser'!A1", "Fertiliser") -> Fertiliser
A18: =HYPERLINK("#'Input - Fuel'!A1", "Fuel") -> Fuel | D18: Production timeframe start | E18: 45231 | F18: ← DD/MM/YYYY or DD Month YYYY
A19: =HYPERLINK("#'Input - Electricity'!A1", "Electricity") -> Electricity | D19: Production timeframe end | E19: 45747 | F19: ← DD/MM/YYYY or DD Month YYYY
A20: =HYPERLINK("#'Input - Farm Inputs'!A1", "Farm Inputs") -> Farm Inputs | D20: Production timeframe length | E20: =DATEDIF(E18,E19+1,"m") -> 17 | F20: Months
A21: =HYPERLINK("#'Input - Freight'!A1", "Freight") -> Freight
A22: =HYPERLINK("#'Input - Manure sent off-site'!A1", "Manure sent off-site") -> Manure sent off-site | D22: Liveweight sold | E22: =SUM(Table_Input_LivestockSales[Total liveweight sold])*10^-3 -> 5 | G22: tonnes
A23: =HYPERLINK("#'Input - Solid waste'!A1", "Solid waste") -> Solid waste | D23: Milk produced unit | E23: {=X_Cell_Dairy_MilkProductionUnit} -> Litres of milk
A24: =HYPERLINK("#'Input - Data quality'!A1", "Data quality") -> Data quality | D24: Milk produced | E24: {=X_Cell_Dairy_MilkProductionAmount*365*IF(E23="Milk solds", 1, 1.03)} -> 7519 | G24: tonnes
D25: Manure sold | E25: 1 | G25: tonnes
A27: CALCULATIONS | D27: Percentage of income from liveweight sold | E27: 0.15 | G27: percent
A28: =HYPERLINK("#'5.1.1.1-2 Inorganic fert N2O'!A1", "5.1.1.1-2 Inorganic fert N2O") -> 5.1.1.1-2 Inorganic fert N2O | D28: Percentage of income from manure sold | E28: 0.05 | G28: percent
A29: =HYPERLINK("#'5.1.1.3-4 Inorganic fert CO2'!A1", "5.1.1.3-4 Inorganic fert CO2") -> 5.1.1.3-4 Inorganic fert CO2 | D29: Percentage of income from milk sold | E29: 0.8 | G29: percent
A30: =HYPERLINK("#'5.2.1.1-2 Organic Fert N2O'!A1", "5.2.1.1-2 Organic fert N2O") -> 5.2.1.1-2 Organic fert N2O
A31: =HYPERLINK("#'5.3.1.1-2 Lime CO2'!A1", "5.3.1.1-2 Lime CO2") -> 5.3.1.1-2 Lime CO2
A32: =HYPERLINK("#'5.4.1.1-4 Atmos deposition'!A1", "5.4.1.1-4 Atmos. deposition") -> 5.4.1.1-4 Atmos. deposition
A33: =HYPERLINK("#'5.5.1.1-2 Leaching and runoff'!A1", "5.5.1.1-2 Leaching & runoff") -> 5.5.1.1-2 Leaching & runoff
A34: =HYPERLINK("#'6.2.1.1-2 Pasture residue N2O'!A1", "6.2.1.1-2 Pasture residue N2O") -> 6.2.1.1-2 Pasture residue N2O
A35: =HYPERLINK("#'6.3.1.1-2 Leach runoff pasture'!A1", "6.3.1.1-2 Leach & runoff (pasture)") -> 6.3.1.1-2 Leach & runoff (pasture)
A36: =HYPERLINK("#'8.1.1.1-2 Transport fuel'!A1", "8.1.1.1-2 Transport fuel") -> 8.1.1.1-2 Transport fuel
A37: =HYPERLINK("#'8.2.1.1-2 Stationary fuel'!A1", "8.2.1.1-2 Stationary fuel") -> 8.2.1.1-2 Stationary fuel
A38: =HYPERLINK("#'14.1.1-2 Purchased electricity'!A1", "14.1.1-2 Purchased electricity") -> 14.1.1-2 Purchased electricity
A39: =HYPERLINK("#'15 Scope 3'!A1", "15 Scope 3") -> 15 Scope 3
A40: =HYPERLINK("#'Calcs - Manure sent off-site'!A1", "Calcs - Manure sent off-site") -> Calcs - Manure sent off-site
A41: =HYPERLINK("#'4.3.1.1-2 Methane'!A1", "4.3.1.1-2 Methane") -> 4.3.1.1-2 Methane
A42: =HYPERLINK("#'4.3.1.3-4 Direct N20'!A1", "4.3.1.3-4 Direct N20") -> 4.3.1.3-4 Direct N20
A43: =HYPERLINK("#'4.3.1.5 Atmos deposition'!A1", "4.3.1.5 Atmos deposition") -> 4.3.1.5 Atmos deposition
A44: =HYPERLINK("#'4.3.1.6-7 Leaching and runoff'!A1", "4.3.1.6-7 Leaching and runoff") -> 4.3.1.6-7 Leaching and runoff
A45: =HYPERLINK("#'4.3.1.8 Manure applied to soils'!A1", "4.3.1.8 Manure applied to soils") -> 4.3.1.8 Manure applied to soils
A46: =HYPERLINK("#'4.3.1.9 Soil direct N2O'!A1", "4.3.1.9 Soil direct N2O") -> 4.3.1.9 Soil direct N2O
A47: =HYPERLINK("#'4.3.1.10-11 Soil Atmos Dep'!A1", "4.3.1.10-11 Soil Atmos Dep") -> 4.3.1.10-11 Soil Atmos Dep
A48: =HYPERLINK("#'4.3.1.12-13 Soil leach runoff'!A1", "4.3.1.12-13 Soil leach runoff") -> 4.3.1.12-13 Soil leach runoff
A49: =HYPERLINK("#'3.3.1.1-2 Enteric Methane'!A1", "3.3.1.1-2 Enteric Methane") -> 3.3.1.1-2 Enteric Methane
A50: =HYPERLINK("#'10.1.1-2 Solid waste treatment'!A1", "10.1.1-2 Solid waste treatment") -> 10.1.1-2 Solid waste treatment
A53: APPENDICES
A54: =HYPERLINK("#'Constants - Dairy'!A1", "Constants - Dairy") -> Constants - Dairy
A55: =HYPERLINK("#'Constants - Ag Residue'!A1", "Constants - Ag residue") -> Constants - Ag residue
A56: =HYPERLINK("#'Constants - Common Livestock'!A1", "Constants - Common Livestock") -> Constants - Common Livestock
A57: =HYPERLINK("#'Constants - Electricity'!A1", "Constants - Electricity") -> Constants - Electricity
A58: =HYPERLINK("#'Constants - Fertiliser'!A1", "Constants - Fertiliser") -> Constants - Fertiliser
A59: =HYPERLINK("#'Constants - Fuel'!A1", "Constants - Fuel") -> Constants - Fuel
A60: =HYPERLINK("#'Constants - Scope 3'!A1", "Constants - Scope 3") -> Constants - Scope 3
A61: =HYPERLINK("#'Constants - Common'!A1", "Constants - Common") -> Constants - Common
A62: =HYPERLINK("#'Acknowledgements'!A1", "Acknowledgements") -> Acknowledgements
A63: =HYPERLINK("#'Constants - Solid Waste'!A1", "Constants - Solid Waste") -> Constants - Solid Waste

Sheet Input - Site
A1: #VALUE! | C1: Input - Site
A3: =HYPERLINK("#'Home'!A1", "Home") -> Home
A4: =HYPERLINK("#'Overview'!A1", "Overview") -> Overview
A5: =HYPERLINK("#'Results'!A1", "Results") -> Results | D5: Location and climate
D7: Location information is used to reference some region and climate-specific emission factors
A8: INPUTS | D8: Tip: Use the web-based GAF Location Helper tool to easily get region and climate information. You will need an internet connection to use the GAF Location Helper.
A9: =HYPERLINK("#'Input - Enterprise'!A1", "Enterprise") -> Enterprise
A10: =HYPERLINK("#'Input - Site'!A1", "Site") -> Site | D10: State | E10: Western Australia | F10: ← Please select
A11: =HYPERLINK("#'Input - Dairy'!A1", "Dairy") -> Dairy | D11: Region (ABS Statistical area level 4) if state is WA | E11: Western Australia - Outback (South) | F11: ← Please select
A12: =HYPERLINK("#'Input - Dairy (Enteric)'!A1", "Dairy (Enteric)") -> Dairy (Enteric) | D12: Leaching zone | E12: NO - Not in leaching zone | F12: ← Please select
A13: =HYPERLINK("#'Input - Livestock sales'!A1", "Livestock sales") -> Livestock sales | D13: Elevation | E13: 307.7 | F13: Meters
A14: =HYPERLINK("#'Input - Dairy cattle purchases'!A1", "Dairy cattle purchases") -> Dairy cattle purchases | D14: Average temperature for reporting period | E14: 18 | F14: Degrees celsius
A15: =HYPERLINK("#'Input - Pasture'!A1", "Pasture") -> Pasture | D15: Total rainfall for reporting period | E15: 601 | F15: Millimetres
A16: =HYPERLINK("#'Input - Fert Prod System'!A1", "Fert Prod System") -> Fert Prod System | D16: Potential evapotranspiration for reporting period | E16: 1326 | F16: Millimetres
A17: =HYPERLINK("#'Input - Fertiliser'!A1", "Fertiliser") -> Fertiliser | D17: Number of frost days for reporting period | E17: 7 | F17: Days
A18: =HYPERLINK("#'Input - Fuel'!A1", "Fuel") -> Fuel | D18: MAP:PET ratio | E18: =E15/E16 -> 0.45324284
A19: =HYPERLINK("#'Input - Electricity'!A1", "Electricity") -> Electricity | D19: Rainfall zone | E19: =Common_InputFunctions.Utility_LookupItemFromMinMax(E15,Table_SourceData_RainfallZones[Min rainfall],Table_SourceData_RainfallZones[Max rainfall],Table_SourceData_RainfallZones[Rainfall Zone]) -> High rainfall
A20: =HYPERLINK("#'Input - Farm Inputs'!A1", "Farm Inputs") -> Farm Inputs | D20: Climate zone | E20: =Common_InputFunctions.Utility_GetClimateZone(E14,E15,E17,E13,E18,Table_SourceData_ClimateZones[Min temp],Table_SourceData_ClimateZones[Max temp],Table_SourceData_ClimateZones[Min rainfall],Table_SourceData_ClimateZones[Max rainfall],Table_SourceData_ClimateZones[Min frost days],Table_SourceData_ClimateZones[Max frost days],Table_SourceData_ClimateZones[Min elevation],Table_SourceData_ClimateZones[Max elevation],Table_SourceData_ClimateZones[Min MAP:PET],Table_SourceData_ClimateZones[Max MAP:PET],Table_SourceData_ClimateZones[Climate zone]) -> Warm temperate dry
A21: =HYPERLINK("#'Input - Freight'!A1", "Freight") -> Freight | D21: Wet or dry climate zone | E21: =Common_InputFunctions.Utility_LookupValueInTable($E$20,Table_SourceData_WetDryZones[Climate zone],Table_SourceData_WetDryZones[Wet or Dry Zone]) -> Dry climate zone
A22: =HYPERLINK("#'Input - Manure sent off-site'!A1", "Manure sent off-site") -> Manure sent off-site | D22: Temperature zone | E22: =Common_InputFunctions.Utility_LookupItemFromMinMax(E14,Table_SourceData_TemperatureZones[Min MAT],Table_SourceData_TemperatureZones[Max MAT],Table_SourceData_TemperatureZones[Temperature Zone]) -> Temperate
A23: =HYPERLINK("#'Input - Solid waste'!A1", "Solid waste") -> Solid waste
A24: =HYPERLINK("#'Input - Data quality'!A1", "Data quality") -> Data quality
A27: CALCULATIONS
A28: =HYPERLINK("#'5.1.1.1-2 Inorganic fert N2O'!A1", "5.1.1.1-2 Inorganic fert N2O") -> 5.1.1.1-2 Inorganic fert N2O
A29: =HYPERLINK("#'5.1.1.3-4 Inorganic fert CO2'!A1", "5.1.1.3-4 Inorganic fert CO2") -> 5.1.1.3-4 Inorganic fert CO2
A30: =HYPERLINK("#'5.2.1.1-2 Organic Fert N2O'!A1", "5.2.1.1-2 Organic fert N2O") -> 5.2.1.1-2 Organic fert N2O
A31: =HYPERLINK("#'5.3.1.1-2 Lime CO2'!A1", "5.3.1.1-2 Lime CO2") -> 5.3.1.1-2 Lime CO2
A32: =HYPERLINK("#'5.4.1.1-4 Atmos deposition'!A1", "5.4.1.1-4 Atmos. deposition") -> 5.4.1.1-4 Atmos. deposition
A33: =HYPERLINK("#'5.5.1.1-2 Leaching and runoff'!A1", "5.5.1.1-2 Leaching & runoff") -> 5.5.1.1-2 Leaching & runoff
A34: =HYPERLINK("#'6.2.1.1-2 Pasture residue N2O'!A1", "6.2.1.1-2 Pasture residue N2O") -> 6.2.1.1-2 Pasture residue N2O
A35: =HYPERLINK("#'6.3.1.1-2 Leach runoff pasture'!A1", "6.3.1.1-2 Leach & runoff (pasture)") -> 6.3.1.1-2 Leach & runoff (pasture)
A36: =HYPERLINK("#'8.1.1.1-2 Transport fuel'!A1", "8.1.1.1-2 Transport fuel") -> 8.1.1.1-2 Transport fuel
A37: =HYPERLINK("#'8.2.1.1-2 Stationary fuel'!A1", "8.2.1.1-2 Stationary fuel") -> 8.2.1.1-2 Stationary fuel
A38: =HYPERLINK("#'14.1.1-2 Purchased electricity'!A1", "14.1.1-2 Purchased electricity") -> 14.1.1-2 Purchased electricity
A39: =HYPERLINK("#'15 Scope 3'!A1", "15 Scope 3") -> 15 Scope 3
A40: =HYPERLINK("#'Calcs - Manure sent off-site'!A1", "Calcs - Manure sent off-site") -> Calcs - Manure sent off-site
A41: =HYPERLINK("#'4.3.1.1-2 Methane'!A1", "4.3.1.1-2 Methane") -> 4.3.1.1-2 Methane
A42: =HYPERLINK("#'4.3.1.3-4 Direct N20'!A1", "4.3.1.3-4 Direct N20") -> 4.3.1.3-4 Direct N20
A43: =HYPERLINK("#'4.3.1.5 Atmos deposition'!A1", "4.3.1.5 Atmos deposition") -> 4.3.1.5 Atmos deposition
A44: =HYPERLINK("#'4.3.1.6-7 Leaching and runoff'!A1", "4.3.1.6-7 Leaching and runoff") -> 4.3.1.6-7 Leaching and runoff
A45: =HYPERLINK("#'4.3.1.8 Manure applied to soils'!A1", "4.3.1.8 Manure applied to soils") -> 4.3.1.8 Manure applied to soils
A46: =HYPERLINK("#'4.3.1.9 Soil direct N2O'!A1", "4.3.1.9 Soil direct N2O") -> 4.3.1.9 Soil direct N2O
A47: =HYPERLINK("#'4.3.1.10-11 Soil Atmos Dep'!A1", "4.3.1.10-11 Soil Atmos Dep") -> 4.3.1.10-11 Soil Atmos Dep
A48: =HYPERLINK("#'4.3.1.12-13 Soil leach runoff'!A1", "4.3.1.12-13 Soil leach runoff") -> 4.3.1.12-13 Soil leach runoff
A49: =HYPERLINK("#'3.3.1.1-2 Enteric Methane'!A1", "3.3.1.1-2 Enteric Methane") -> 3.3.1.1-2 Enteric Methane
A50: =HYPERLINK("#'10.1.1-2 Solid waste treatment'!A1", "10.1.1-2 Solid waste treatment") -> 10.1.1-2 Solid waste treatment
A53: APPENDICES
A54: =HYPERLINK("#'Constants - Dairy'!A1", "Constants - Dairy") -> Constants - Dairy
A55: =HYPERLINK("#'Constants - Ag Residue'!A1", "Constants - Ag residue") -> Constants - Ag residue
A56: =HYPERLINK("#'Constants - Common Livestock'!A1", "Constants - Common Livestock") -> Constants - Common Livestock
A57: =HYPERLINK("#'Constants - Electricity'!A1", "Constants - Electricity") -> Constants - Electricity
A58: =HYPERLINK("#'Constants - Fertiliser'!A1", "Constants - Fertiliser") -> Constants - Fertiliser
A59: =HYPERLINK("#'Constants - Fuel'!A1", "Constants - Fuel") -> Constants - Fuel
A60: =HYPERLINK("#'Constants - Scope 3'!A1", "Constants - Scope 3") -> Constants - Scope 3
A61: =HYPERLINK("#'Constants - Common'!A1", "Constants - Common") -> Constants - Common
A62: =HYPERLINK("#'Acknowledgements'!A1", "Acknowledgements") -> Acknowledgements
A63: =HYPERLINK("#'Constants - Solid Waste'!A1", "Constants - Solid Waste") -> Constants - Solid Waste

Sheet Input - Dairy
A1: #VALUE! | C1: Input -Dairy
A3: =HYPERLINK("#'Home'!A1", "Home") -> Home
A4: =HYPERLINK("#'Overview'!A1", "Overview") -> Overview
A5: =HYPERLINK("#'Results'!A1", "Results") -> Results | D5: Herd movement
D7: Breed | E7: Medium Friesian | F7: ← Please select
A8: INPUTS
A9: =HYPERLINK("#'Input - Enterprise'!A1", "Enterprise") -> Enterprise | E9: Milking cows | F9: Heifers > 1 year | G9: Heifers < 1 year | H9: Bulls > 1 year | I9: Bulls < 1 year
A10: =HYPERLINK("#'Input - Site'!A1", "Site") -> Site | D10: ="Average number of head between " & TEXT(X_Cell_Site_StartDate, "dd mmm yy") & " and " & TEXT(X_Cell_Site_EndDate, "dd mmm yy") -> Average number of head between 01 Jan 24 and 31 Dec 24 | E10: 100 | F10: 100 | G10: 100 | H10: 100 | I10: 100 | J10: head
A11: =HYPERLINK("#'Input - Dairy'!A1", "Dairy") -> Dairy
A12: =HYPERLINK("#'Input - Dairy (Enteric)'!A1", "Dairy (Enteric)") -> Dairy (Enteric) | D12: Liveweight
A13: =HYPERLINK("#'Input - Livestock sales'!A1", "Livestock sales") -> Livestock sales | D13: Method 1 default values (Do not edit) | E13: Milking cows | F13: Heifers > 1 year | G13: Heifers < 1 year | H13: Bulls > 1 year | I13: Bulls < 1 year
A14: =HYPERLINK("#'Input - Dairy cattle purchases'!A1", "Dairy cattle purchases") -> Dairy cattle purchases | D14: Average liveweight | E14: =Common_InputFunctions.Utility_LookupValueInTableNumber(X_Cell_Dairy_Breed, Table_SourceData_Dairy_WjCowsHeifers[Breed],Table_SourceData_Dairy_WjCowsHeifers[Milking cows]) -> 550 | F14: =Common_InputFunctions.Utility_LookupValueInTableNumber(X_Cell_Dairy_Breed, Table_SourceData_Dairy_WjCowsHeifers[Breed],Table_SourceData_Dairy_WjCowsHeifers[Heifers > 1]) -> 380 | G14: =Common_InputFunctions.Utility_LookupValueInTableNumber(X_Cell_Dairy_Breed, Table_SourceData_Dairy_WjCowsHeifers[Breed],Table_SourceData_Dairy_WjCowsHeifers[Heifers < 1 (weaned)]) -> 155 | H14: {=Table_SourceData_Dairy_WjBulls[Bulls > 1]} -> 600 | I14: {=Table_SourceData_Dairy_WjBulls[Bulls < 1 (weaned)]} -> 225 | J14: kg/head
A15: =HYPERLINK("#'Input - Pasture'!A1", "Pasture") -> Pasture | D15: Average liveweight gain | E15: {=Table_SourceData_Dairy_LWGj[Milking cows]} -> 0.016 | F15: {=Table_SourceData_Dairy_LWGj[Heifers > 1]} -> 0.6 | G15: {=Table_SourceData_Dairy_LWGj[Heifers < 1 (weaned)]} -> 0.57 | H15: {=Table_SourceData_Dairy_LWGj[Bulls > 1]} -> 0.1 | I15: {=Table_SourceData_Dairy_LWGj[Bulls < 1 (weaned)]} -> 0.8 | J15: kg/head/day
A16: =HYPERLINK("#'Input - Fert Prod System'!A1", "Fert Prod System") -> Fert Prod System
A17: =HYPERLINK("#'Input - Fertiliser'!A1", "Fertiliser") -> Fertiliser | D17: Method 2 custom values (Edit if known) | E17: Milking cows | F17: Heifers > 1 year | G17: Heifers < 1 year | H17: Bulls > 1 year | I17: Bulls < 1 year
A18: =HYPERLINK("#'Input - Fuel'!A1", "Fuel") -> Fuel | D18: Average liveweight | E18: =Common_InputFunctions.Utility_LookupValueInTableNumber(X_Cell_Dairy_Breed, Table_SourceData_Dairy_WjCowsHeifers[Breed],Table_SourceData_Dairy_WjCowsHeifers[Milking cows]) -> 550 | F18: =Common_InputFunctions.Utility_LookupValueInTableNumber(X_Cell_Dairy_Breed, Table_SourceData_Dairy_WjCowsHeifers[Breed],Table_SourceData_Dairy_WjCowsHeifers[Heifers > 1]) -> 380 | G18: =Common_InputFunctions.Utility_LookupValueInTableNumber(X_Cell_Dairy_Breed, Table_SourceData_Dairy_WjCowsHeifers[Breed],Table_SourceData_Dairy_WjCowsHeifers[Heifers < 1 (weaned)]) -> 155 | H18: {=Table_SourceData_Dairy_WjBulls[Bulls > 1]} -> 600 | I18: {=Table_SourceData_Dairy_WjBulls[Bulls < 1 (weaned)]} -> 225 | J18: kg/head
A19: =HYPERLINK("#'Input - Electricity'!A1", "Electricity") -> Electricity | D19: Average liveweight gain | E19: {=Table_SourceData_Dairy_LWGj[Milking cows]} -> 0.016 | F19: {=Table_SourceData_Dairy_LWGj[Heifers > 1]} -> 0.6 | G19: {=Table_SourceData_Dairy_LWGj[Heifers < 1 (weaned)]} -> 0.57 | H19: {=Table_SourceData_Dairy_LWGj[Bulls > 1]} -> 0.1 | I19: {=Table_SourceData_Dairy_LWGj[Bulls < 1 (weaned)]} -> 0.8 | J19: kg/head/day
A20: =HYPERLINK("#'Input - Farm Inputs'!A1", "Farm Inputs") -> Farm Inputs
A21: =HYPERLINK("#'Input - Freight'!A1", "Freight") -> Freight | D21: Duration of stay
A22: =HYPERLINK("#'Input - Manure sent off-site'!A1", "Manure sent off-site") -> Manure sent off-site
A23: =HYPERLINK("#'Input - Solid waste'!A1", "Solid waste") -> Solid waste | D23: Method 1 default values (Do not edit) | E23: Milking cows | F23: Heifers > 1 year | G23: Heifers < 1 year | H23: Bulls > 1 year | I23: Bulls < 1 year
A24: =HYPERLINK("#'Input - Data quality'!A1", "Data quality") -> Data quality | D24: ="Average duration of stay between " & TEXT(X_Cell_Site_StartDate, "dd mmm yy") & " and " & TEXT(X_Cell_Site_EndDate, "dd mmm yy") & " weaned livestock" -> Average duration of stay between 01 Jan 24 and 31 Dec 24 weaned livestock | E24: {=Common_InputFunctions.Utility_LookupValueInTableNumber(E23,Table_SourceData_Dairy_Duration[Animal class j],Table_SourceData_Dairy_Duration[Duration (weaned)])} -> 365 | F24: {=Common_InputFunctions.Utility_LookupValueInTableNumber(F23,Table_SourceData_Dairy_Duration[Animal class j],Table_SourceData_Dairy_Duration[Duration (weaned)])} -> 365 | G24: {=Common_InputFunctions.Utility_LookupValueInTableNumber(G23,Table_SourceData_Dairy_Duration[Animal class j],Table_SourceData_Dairy_Duration[Duration (weaned)])} -> 281 | H24: {=Common_InputFunctions.Utility_LookupValueInTableNumber(H23,Table_SourceData_Dairy_Duration[Animal class j],Table_SourceData_Dairy_Duration[Duration (weaned)])} -> 365 | I24: {=Common_InputFunctions.Utility_LookupValueInTableNumber(I23,Table_SourceData_Dairy_Duration[Animal class j],Table_SourceData_Dairy_Duration[Duration (weaned)])} -> 281 | J24: Days
D25: ="Average duration of stay between " & TEXT(X_Cell_Site_StartDate, "dd mmm yy") & " and " & TEXT(X_Cell_Site_EndDate, "dd mmm yy") & " pre-weaned livestock" -> Average duration of stay between 01 Jan 24 and 31 Dec 24 pre-weaned livestock | E25: {=Common_InputFunctions.Utility_LookupValueInTableNumber(E23,Table_SourceData_Dairy_Duration[Animal class j],Table_SourceData_Dairy_Duration[Duration (pre-weaned)])} -> 0 | F25: {=Common_InputFunctions.Utility_LookupValueInTableNumber(F23,Table_SourceData_Dairy_Duration[Animal class j],Table_SourceData_Dairy_Duration[Duration (pre-weaned)])} -> 0 | G25: {=Common_InputFunctions.Utility_LookupValueInTableNumber(G23,Table_SourceData_Dairy_Duration[Animal class j],Table_SourceData_Dairy_Duration[Duration (pre-weaned)])} -> 84 | H25: {=Common_InputFunctions.Utility_LookupValueInTableNumber(H23,Table_SourceData_Dairy_Duration[Animal class j],Table_SourceData_Dairy_Duration[Duration (pre-weaned)])} -> 0 | I25: {=Common_InputFunctions.Utility_LookupValueInTableNumber(I23,Table_SourceData_Dairy_Duration[Animal class j],Table_SourceData_Dairy_Duration[Duration (pre-weaned)])} -> 84 | J25: Days
A27: CALCULATIONS | D27: Method 2 custom values (Edit if known) | E27: Milking cows | F27: Heifers > 1 year | G27: Heifers < 1 year | H27: Bulls > 1 year | I27: Bulls < 1 year
A28: =HYPERLINK("#'5.1.1.1-2 Inorganic fert N2O'!A1", "5.1.1.1-2 Inorganic fert N2O") -> 5.1.1.1-2 Inorganic fert N2O | D28: ="Average duration of stay between " & TEXT(X_Cell_Site_StartDate, "dd mmm yy") & " and " & TEXT(X_Cell_Site_EndDate, "dd mmm yy") & " weaned livestock" -> Average duration of stay between 01 Jan 24 and 31 Dec 24 weaned livestock | E28: {=Common_InputFunctions.Utility_LookupValueInTableNumber(E27,Table_SourceData_Dairy_Duration[Animal class j],Table_SourceData_Dairy_Duration[Duration (weaned)])} -> 365 | F28: {=Common_InputFunctions.Utility_LookupValueInTableNumber(F27,Table_SourceData_Dairy_Duration[Animal class j],Table_SourceData_Dairy_Duration[Duration (weaned)])} -> 365 | G28: {=Common_InputFunctions.Utility_LookupValueInTableNumber(G27,Table_SourceData_Dairy_Duration[Animal class j],Table_SourceData_Dairy_Duration[Duration (weaned)])} -> 281 | H28: {=Common_InputFunctions.Utility_LookupValueInTableNumber(H27,Table_SourceData_Dairy_Duration[Animal class j],Table_SourceData_Dairy_Duration[Duration (weaned)])} -> 365 | I28: {=Common_InputFunctions.Utility_LookupValueInTableNumber(I27,Table_SourceData_Dairy_Duration[Animal class j],Table_SourceData_Dairy_Duration[Duration (weaned)])} -> 281 | J28: Days
A29: =HYPERLINK("#'5.1.1.3-4 Inorganic fert CO2'!A1", "5.1.1.3-4 Inorganic fert CO2") -> 5.1.1.3-4 Inorganic fert CO2 | D29: ="Average duration of stay between " & TEXT(X_Cell_Site_StartDate, "dd mmm yy") & " and " & TEXT(X_Cell_Site_EndDate, "dd mmm yy") & " pre-weaned livestock" -> Average duration of stay between 01 Jan 24 and 31 Dec 24 pre-weaned livestock | E29: =365-E28 -> 0 | F29: =365-F28 -> 0 | G29: =365-G28 -> 84 | H29: =365-H28 -> 0 | I29: =365-I28 -> 84 | J29: Days
A30: =HYPERLINK("#'5.2.1.1-2 Organic Fert N2O'!A1", "5.2.1.1-2 Organic fert N2O") -> 5.2.1.1-2 Organic fert N2O
A31: =HYPERLINK("#'5.3.1.1-2 Lime CO2'!A1", "5.3.1.1-2 Lime CO2") -> 5.3.1.1-2 Lime CO2
A32: =HYPERLINK("#'5.4.1.1-4 Atmos deposition'!A1", "5.4.1.1-4 Atmos. deposition") -> 5.4.1.1-4 Atmos. deposition
A33: =HYPERLINK("#'5.5.1.1-2 Leaching and runoff'!A1", "5.5.1.1-2 Leaching & runoff") -> 5.5.1.1-2 Leaching & runoff | D33: Diet
A34: =HYPERLINK("#'6.2.1.1-2 Pasture residue N2O'!A1", "6.2.1.1-2 Pasture residue N2O") -> 6.2.1.1-2 Pasture residue N2O
A35: =HYPERLINK("#'6.3.1.1-2 Leach runoff pasture'!A1", "6.3.1.1-2 Leach & runoff (pasture)") -> 6.3.1.1-2 Leach & runoff (pasture) | D35: Method 1 default values (Do not edit) | E35: Milking cows | F35: Heifers > 1 year | G35: Heifers < 1 year | H35: Bulls > 1 year | I35: Bulls < 1 year
A36: =HYPERLINK("#'8.1.1.1-2 Transport fuel'!A1", "8.1.1.1-2 Transport fuel") -> 8.1.1.1-2 Transport fuel | D36: Dry matter digestibility | E36: =SourceData_Dairy_DryMatterDigestibility_Data -> 0.75 | F36: =SourceData_Dairy_DryMatterDigestibility_Data -> 0.75 | G36: =SourceData_Dairy_DryMatterDigestibility_Data -> 0.75 | H36: =SourceData_Dairy_DryMatterDigestibility_Data -> 0.75 | I36: =SourceData_Dairy_DryMatterDigestibility_Data -> 0.75 | J36: Fraction
A37: =HYPERLINK("#'8.2.1.1-2 Stationary fuel'!A1", "8.2.1.1-2 Stationary fuel") -> 8.2.1.1-2 Stationary fuel | D37: Crude protein | E37: =SourceData_Dairy_CrudeProtein_Data -> 0.2 | F37: =SourceData_Dairy_CrudeProtein_Data -> 0.2 | G37: =SourceData_Dairy_CrudeProtein_Data -> 0.2 | H37: =SourceData_Dairy_CrudeProtein_Data -> 0.2 | I37: =SourceData_Dairy_CrudeProtein_Data -> 0.2 | J37: Fraction
A38: =HYPERLINK("#'14.1.1-2 Purchased electricity'!A1", "14.1.1-2 Purchased electricity") -> 14.1.1-2 Purchased electricity
A39: =HYPERLINK("#'15 Scope 3'!A1", "15 Scope 3") -> 15 Scope 3 | D39: Method 2 custom values (Edit if known) | E39: Milking cows | F39: Heifers > 1 year | G39: Heifers < 1 year | H39: Bulls > 1 year | I39: Bulls < 1 year
A40: =HYPERLINK("#'Calcs - Manure sent off-site'!A1", "Calcs - Manure sent off-site") -> Calcs - Manure sent off-site | D40: Dry matter digestibility | E40: =SourceData_Dairy_DryMatterDigestibility_Data -> 0.75 | F40: =SourceData_Dairy_DryMatterDigestibility_Data -> 0.75 | G40: =SourceData_Dairy_DryMatterDigestibility_Data -> 0.75 | H40: =SourceData_Dairy_DryMatterDigestibility_Data -> 0.75 | I40: =SourceData_Dairy_DryMatterDigestibility_Data -> 0.75 | J40: Fraction
A41: =HYPERLINK("#'4.3.1.1-2 Methane'!A1", "4.3.1.1-2 Methane") -> 4.3.1.1-2 Methane | D41: Crude protein | E41: =SourceData_Dairy_CrudeProtein_Data -> 0.2 | F41: =SourceData_Dairy_CrudeProtein_Data -> 0.2 | G41: =SourceData_Dairy_CrudeProtein_Data -> 0.2 | H41: =SourceData_Dairy_CrudeProtein_Data -> 0.2 | I41: =SourceData_Dairy_CrudeProtein_Data -> 0.2 | J41: Fraction
A42: =HYPERLINK("#'4.3.1.3-4 Direct N20'!A1", "4.3.1.3-4 Direct N20") -> 4.3.1.3-4 Direct N20
A43: =HYPERLINK("#'4.3.1.5 Atmos deposition'!A1", "4.3.1.5 Atmos deposition") -> 4.3.1.5 Atmos deposition
A44: =HYPERLINK("#'4.3.1.6-7 Leaching and runoff'!A1", "4.3.1.6-7 Leaching and runoff") -> 4.3.1.6-7 Leaching and runoff
A45: =HYPERLINK("#'4.3.1.8 Manure applied to soils'!A1", "4.3.1.8 Manure applied to soils") -> 4.3.1.8 Manure applied to soils | D45: Milk production
A46: =HYPERLINK("#'4.3.1.9 Soil direct N2O'!A1", "4.3.1.9 Soil direct N2O") -> 4.3.1.9 Soil direct N2O | D46: Milk production for the full 365 days of the year
A47: =HYPERLINK("#'4.3.1.10-11 Soil Atmos Dep'!A1", "4.3.1.10-11 Soil Atmos Dep") -> 4.3.1.10-11 Soil Atmos Dep | D47: Milk production unit | E47: Litres of milk | F47: ← Please select
A48: =HYPERLINK("#'4.3.1.12-13 Soil leach runoff'!A1", "4.3.1.12-13 Soil leach runoff") -> 4.3.1.12-13 Soil leach runoff
A49: =HYPERLINK("#'3.3.1.1-2 Enteric Methane'!A1", "3.3.1.1-2 Enteric Methane") -> 3.3.1.1-2 Enteric Methane | E49: Milking cows
A50: =HYPERLINK("#'10.1.1-2 Solid waste treatment'!A1", "10.1.1-2 Solid waste treatment") -> 10.1.1-2 Solid waste treatment | D50: Average daily milk production | E50: 20 | F50: =IF(X_Cell_Dairy_MilkProductionUnit="Litres of milk", "litres/head/day", "kg milk solids/head/day") -> litres/head/day
D52: For milk solids only: | E52: Method 1 (don't edit) | F52: Method 2 (edit if known)
A53: APPENDICES | D53: Fat content in fat and protein corrected milk | E53: =SourceData_Dairy_FatContentInMilk_Data/100 -> 0.04 | F53: =SourceData_Dairy_FatContentInMilk_Data/100 -> 0.04 | G53: percent
A54: =HYPERLINK("#'Constants - Dairy'!A1", "Constants - Dairy") -> Constants - Dairy | D54: Protein content in fat and protein corrected milk | E54: =SourceData_Dairy_ProteinContentInMilk_Data/100 -> 0.033 | F54: =SourceData_Dairy_ProteinContentInMilk_Data/100 -> 0.033 | G54: percent
A55: =HYPERLINK("#'Constants - Ag Residue'!A1", "Constants - Ag residue") -> Constants - Ag residue
A56: =HYPERLINK("#'Constants - Common Livestock'!A1", "Constants - Common Livestock") -> Constants - Common Livestock
A57: =HYPERLINK("#'Constants - Electricity'!A1", "Constants - Electricity") -> Constants - Electricity
A58: =HYPERLINK("#'Constants - Fertiliser'!A1", "Constants - Fertiliser") -> Constants - Fertiliser | D58: Production systems
A59: =HYPERLINK("#'Constants - Fuel'!A1", "Constants - Fuel") -> Constants - Fuel | D59: Time spent in production systems
A60: =HYPERLINK("#'Constants - Scope 3'!A1", "Constants - Scope 3") -> Constants - Scope 3 | D60: Production system template | E60: System 3: Pasture-grazed 3-9 months/year | F60: ← Please select
A61: =HYPERLINK("#'Constants - Common'!A1", "Constants - Common") -> Constants - Common
A62: =HYPERLINK("#'Acknowledgements'!A1", "Acknowledgements") -> Acknowledgements | D62: Method 1 default values (Do not edit) | E62: Milking cows | F62: Heifers > 1 year | G62: Heifers < 1 year | H62: Bulls > 1 year | I62: Bulls < 1 year
A63: =HYPERLINK("#'Constants - Solid Waste'!A1", "Constants - Solid Waste") -> Constants - Solid Waste | D63: Pasture | E63: =Common_InputFunctions.Utility_LookupValueInTableNumber(X_Cell_Dairy_ProductionSystemTemplate, Table_SourceData_Dairy_ProductionSystemTemplates[Area],Table_SourceData_Dairy_ProductionSystemTemplates[Pasture]) -> 0.534 | F63: =Common_InputFunctions.Utility_LookupValueInTableNumber(X_Cell_Dairy_ProductionSystemTemplate, Table_SourceData_Dairy_ProductionSystemTemplates[Area],Table_SourceData_Dairy_ProductionSystemTemplates[Pasture]) -> 0.534 | G63: =Common_InputFunctions.Utility_LookupValueInTableNumber(X_Cell_Dairy_ProductionSystemTemplate, Table_SourceData_Dairy_ProductionSystemTemplates[Area],Table_SourceData_Dairy_ProductionSystemTemplates[Pasture]) -> 0.534 | H63: =Common_InputFunctions.Utility_LookupValueInTableNumber(X_Cell_Dairy_ProductionSystemTemplate, Table_SourceData_Dairy_ProductionSystemTemplates[Area],Table_SourceData_Dairy_ProductionSystemTemplates[Pasture]) -> 0.534 | I63: =Common_InputFunctions.Utility_LookupValueInTableNumber(X_Cell_Dairy_ProductionSystemTemplate, Table_SourceData_Dairy_ProductionSystemTemplates[Area],Table_SourceData_Dairy_ProductionSystemTemplates[Pasture]) -> 0.534 | J63: Percent
D64: Milking shed | E64: =Common_InputFunctions.Utility_LookupValueInTableNumber(X_Cell_Dairy_ProductionSystemTemplate, Table_SourceData_Dairy_ProductionSystemTemplates[Area],Table_SourceData_Dairy_ProductionSystemTemplates[Milking shed]) -> 0.11 | F64: =Common_InputFunctions.Utility_LookupValueInTableNumber(X_Cell_Dairy_ProductionSystemTemplate, Table_SourceData_Dairy_ProductionSystemTemplates[Area],Table_SourceData_Dairy_ProductionSystemTemplates[Milking shed]) -> 0.11 | G64: =Common_InputFunctions.Utility_LookupValueInTableNumber(X_Cell_Dairy_ProductionSystemTemplate, Table_SourceData_Dairy_ProductionSystemTemplates[Area],Table_SourceData_Dairy_ProductionSystemTemplates[Milking shed]) -> 0.11 | H64: =Common_InputFunctions.Utility_LookupValueInTableNumber(X_Cell_Dairy_ProductionSystemTemplate, Table_SourceData_Dairy_ProductionSystemTemplates[Area],Table_SourceData_Dairy_ProductionSystemTemplates[Milking shed]) -> 0.11 | I64: =Common_InputFunctions.Utility_LookupValueInTableNumber(X_Cell_Dairy_ProductionSystemTemplate, Table_SourceData_Dairy_ProductionSystemTemplates[Area],Table_SourceData_Dairy_ProductionSystemTemplates[Milking shed]) -> 0.11 | J64: Percent
D65: Feed pad | E65: =Common_InputFunctions.Utility_LookupValueInTableNumber(X_Cell_Dairy_ProductionSystemTemplate, Table_SourceData_Dairy_ProductionSystemTemplates[Area],Table_SourceData_Dairy_ProductionSystemTemplates[Feedpad]) -> 0.356 | F65: =Common_InputFunctions.Utility_LookupValueInTableNumber(X_Cell_Dairy_ProductionSystemTemplate, Table_SourceData_Dairy_ProductionSystemTemplates[Area],Table_SourceData_Dairy_ProductionSystemTemplates[Feedpad]) -> 0.356 | G65: =Common_InputFunctions.Utility_LookupValueInTableNumber(X_Cell_Dairy_ProductionSystemTemplate, Table_SourceData_Dairy_ProductionSystemTemplates[Area],Table_SourceData_Dairy_ProductionSystemTemplates[Feedpad]) -> 0.356 | H65: =Common_InputFunctions.Utility_LookupValueInTableNumber(X_Cell_Dairy_ProductionSystemTemplate, Table_SourceData_Dairy_ProductionSystemTemplates[Area],Table_SourceData_Dairy_ProductionSystemTemplates[Feedpad]) -> 0.356 | I65: =Common_InputFunctions.Utility_LookupValueInTableNumber(X_Cell_Dairy_ProductionSystemTemplate, Table_SourceData_Dairy_ProductionSystemTemplates[Area],Table_SourceData_Dairy_ProductionSystemTemplates[Feedpad]) -> 0.356 | J65: Percent
D67: Method 2 custom values (Edit if known) | E67: Milking cows | F67: Heifers > 1 year | G67: Heifers < 1 year | H67: Bulls > 1 year | I67: Bulls < 1 year
D68: Pasture | E68: =Common_InputFunctions.Utility_LookupValueInTableNumber(X_Cell_Dairy_ProductionSystemTemplate, Table_SourceData_Dairy_ProductionSystemTemplates[Area],Table_SourceData_Dairy_ProductionSystemTemplates[Pasture]) -> 0.534 | F68: =Common_InputFunctions.Utility_LookupValueInTableNumber(X_Cell_Dairy_ProductionSystemTemplate, Table_SourceData_Dairy_ProductionSystemTemplates[Area],Table_SourceData_Dairy_ProductionSystemTemplates[Pasture]) -> 0.534 | G68: =Common_InputFunctions.Utility_LookupValueInTableNumber(X_Cell_Dairy_ProductionSystemTemplate, Table_SourceData_Dairy_ProductionSystemTemplates[Area],Table_SourceData_Dairy_ProductionSystemTemplates[Pasture]) -> 0.534 | H68: =Common_InputFunctions.Utility_LookupValueInTableNumber(X_Cell_Dairy_ProductionSystemTemplate, Table_SourceData_Dairy_ProductionSystemTemplates[Area],Table_SourceData_Dairy_ProductionSystemTemplates[Pasture]) -> 0.534 | I68: =Common_InputFunctions.Utility_LookupValueInTableNumber(X_Cell_Dairy_ProductionSystemTemplate, Table_SourceData_Dairy_ProductionSystemTemplates[Area],Table_SourceData_Dairy_ProductionSystemTemplates[Pasture]) -> 0.534 | J68: Percent
D69: Milking shed | E69: =Common_InputFunctions.Utility_LookupValueInTableNumber(X_Cell_Dairy_ProductionSystemTemplate, Table_SourceData_Dairy_ProductionSystemTemplates[Area],Table_SourceData_Dairy_ProductionSystemTemplates[Milking shed]) -> 0.11 | F69: =Common_InputFunctions.Utility_LookupValueInTableNumber(X_Cell_Dairy_ProductionSystemTemplate, Table_SourceData_Dairy_ProductionSystemTemplates[Area],Table_SourceData_Dairy_ProductionSystemTemplates[Milking shed]) -> 0.11 | G69: =Common_InputFunctions.Utility_LookupValueInTableNumber(X_Cell_Dairy_ProductionSystemTemplate, Table_SourceData_Dairy_ProductionSystemTemplates[Area],Table_SourceData_Dairy_ProductionSystemTemplates[Milking shed]) -> 0.11 | H69: =Common_InputFunctions.Utility_LookupValueInTableNumber(X_Cell_Dairy_ProductionSystemTemplate, Table_SourceData_Dairy_ProductionSystemTemplates[Area],Table_SourceData_Dairy_ProductionSystemTemplates[Milking shed]) -> 0.11 | I69: =Common_InputFunctions.Utility_LookupValueInTableNumber(X_Cell_Dairy_ProductionSystemTemplate, Table_SourceData_Dairy_ProductionSystemTemplates[Area],Table_SourceData_Dairy_ProductionSystemTemplates[Milking shed]) -> 0.11 | J69: Percent
D70: Feed pad | E70: =Common_InputFunctions.Utility_LookupValueInTableNumber(X_Cell_Dairy_ProductionSystemTemplate, Table_SourceData_Dairy_ProductionSystemTemplates[Area],Table_SourceData_Dairy_ProductionSystemTemplates[Feedpad]) -> 0.356 | F70: =Common_InputFunctions.Utility_LookupValueInTableNumber(X_Cell_Dairy_ProductionSystemTemplate, Table_SourceData_Dairy_ProductionSystemTemplates[Area],Table_SourceData_Dairy_ProductionSystemTemplates[Feedpad]) -> 0.356 | G70: =Common_InputFunctions.Utility_LookupValueInTableNumber(X_Cell_Dairy_ProductionSystemTemplate, Table_SourceData_Dairy_ProductionSystemTemplates[Area],Table_SourceData_Dairy_ProductionSystemTemplates[Feedpad]) -> 0.356 | H70: =Common_InputFunctions.Utility_LookupValueInTableNumber(X_Cell_Dairy_ProductionSystemTemplate, Table_SourceData_Dairy_ProductionSystemTemplates[Area],Table_SourceData_Dairy_ProductionSystemTemplates[Feedpad]) -> 0.356 | I70: =Common_InputFunctions.Utility_LookupValueInTableNumber(X_Cell_Dairy_ProductionSystemTemplate, Table_SourceData_Dairy_ProductionSystemTemplates[Area],Table_SourceData_Dairy_ProductionSystemTemplates[Feedpad]) -> 0.356 | J70: Percent
D74: Manure management systems
D75: ="From " & $D$64 -> From Milking shed
D77: Stage 1 MMS | E77: Milking cows | F77: Heifers > 1 year | G77: Heifers < 1 year | H77: Bulls > 1 year | I77: Bulls < 1 year | J77: ► | L77: Destination after stage 2 MMS (Percent)
L78: Sold | M78: Fert for own farm (eg crop) | N78: Direct application to soil
D79: ='Constants - Dairy'!$D$8 -> Anaerobic lagoon | E79: 0.25 | F79: 0.25 | G79: 0.25 | H79: 0.25 | I79: 0.25 | J79: Percent | L79: 0.25 | M79: 0.25 | N79: =1-SUM(L79:M79) -> 0.5
D80: ="Were solids separated from " & D79 & "?" -> Were solids separated from Anaerobic lagoon? | E80: Yes
D81: ="Percent solids separated from " & D79 & " (Method 1)" -> Percent solids separated from Anaerobic lagoon (Method 1) | E81: =IF(X_Cell_Dairy_Stage1MMS_1_AnaerobicLagoon_SolidsSeparated="Yes", 20%, 0) -> 0.2
D82: ="Percent solids separated from " & D79 & " (Method 2)" -> Percent solids separated from Anaerobic lagoon (Method 2) | E82: 0.2
D84: ='Constants - Dairy'!$D$9 -> Sump and dispersal system | E84: 0.25 | F84: 0.25 | G84: 0.25 | H84: 0.25 | I84: 0.25 | J84: Percent | L84: 0.25 | M84: 0.25 | N84: =1-SUM(L84:M84) -> 0.5
D85: ="Were solids separated from " & D84 & "?" -> Were solids separated from Sump and dispersal system? | E85: Yes
D86: ="Percent solids separated from " & D84 & " (Method 1)" -> Percent solids separated from Sump and dispersal system (Method 1) | E86: =IF(X_Cell_Dairy_Stage1MMS_1_SumpAndDispersal_SolidsSeparated="Yes", 20%, 0) -> 0.2
D87: ="Percent solids separated from " & D84 & " (Method 2)" -> Percent solids separated from Sump and dispersal system (Method 2) | E87: 0.2
D89: ='Constants - Dairy'!$D$10 -> Drains to paddock | E89: 0.25 | F89: 0.25 | G89: 0.25 | H89: 0.25 | I89: 0.25 | J89: Percent | L89: 0.25 | M89: 0.25 | N89: =1-SUM(L89:M89) -> 0.5
D90: ="Were solids separated from " & D89 & "?" -> Were solids separated from Drains to paddock? | E90: Yes
D91: ="Percent solids separated from " & D89 & " (Method 1)" -> Percent solids separated from Drains to paddock (Method 1) | E91: =IF(X_Cell_Dairy_Stage1MMS_1_DrainsToPaddock_SolidsSeparated="Yes", 20%, 0) -> 0.2
D92: ="Percent solids separated from " & D89 & " (Method 2)" -> Percent solids separated from Drains to paddock (Method 2) | E92: 0.2
D94: ='Constants - Dairy'!$D$11 & " (before solid separation)" -> Solid storage (before solid separation) | E94: 0.25 | F94: 0.25 | G94: 0.25 | H94: 0.25 | I94: 0.25 | J94: Percent | L94: 0.25 | M94: 0.25 | N94: =1-SUM(L94:M94) -> 0.5
D95: Solid storage (after solid separation) - Method 1 | E95: =E94+(E79*X_Cell_Dairy_Stage1MMS_1_AnaerobicLagoon_AmountSeparated_Method1)+(E84*X_Cell_Dairy_Stage1MMS_1_SumpAndDispersal_AmountSeparated_Method1)+(E89*X_Cell_Dairy_Stage1MMS_1_DrainsToPaddock_AmountSeparated_Method1) -> 0.4 | F95: =F94+(F79*X_Cell_Dairy_Stage1MMS_1_AnaerobicLagoon_AmountSeparated_Method1)+(F84*X_Cell_Dairy_Stage1MMS_1_SumpAndDispersal_AmountSeparated_Method1)+(F89*X_Cell_Dairy_Stage1MMS_1_DrainsToPaddock_AmountSeparated_Method1) -> 0.4 | G95: =G94+(G79*X_Cell_Dairy_Stage1MMS_1_AnaerobicLagoon_AmountSeparated_Method1)+(G84*X_Cell_Dairy_Stage1MMS_1_SumpAndDispersal_AmountSeparated_Method1)+(G89*X_Cell_Dairy_Stage1MMS_1_DrainsToPaddock_AmountSeparated_Method1) -> 0.4 | H95: =H94+(H79*X_Cell_Dairy_Stage1MMS_1_AnaerobicLagoon_AmountSeparated_Method1)+(H84*X_Cell_Dairy_Stage1MMS_1_SumpAndDispersal_AmountSeparated_Method1)+(H89*X_Cell_Dairy_Stage1MMS_1_DrainsToPaddock_AmountSeparated_Method1) -> 0.4 | I95: =I94+(I79*X_Cell_Dairy_Stage1MMS_1_AnaerobicLagoon_AmountSeparated_Method1)+(I84*X_Cell_Dairy_Stage1MMS_1_SumpAndDispersal_AmountSeparated_Method1)+(I89*X_Cell_Dairy_Stage1MMS_1_DrainsToPaddock_AmountSeparated_Method1) -> 0.4 | J95: Percent
D96: Solid storage (after solid separation) - Method 2 | E96: =E94+(E79*X_Cell_Dairy_Stage1MMS_1_AnaerobicLagoon_AmountSeparated_Method2)+(E84*X_Cell_Dairy_Stage1MMS_1_SumpAndDispersal_AmountSeparated_Method2)+(E89*X_Cell_Dairy_Stage1MMS_1_DrainsToPaddock_AmountSeparated_Method2) -> 0.4 | F96: =F94+(F79*X_Cell_Dairy_Stage1MMS_1_AnaerobicLagoon_AmountSeparated_Method2)+(F84*X_Cell_Dairy_Stage1MMS_1_SumpAndDispersal_AmountSeparated_Method2)+(F89*X_Cell_Dairy_Stage1MMS_1_DrainsToPaddock_AmountSeparated_Method2) -> 0.4 | G96: =G94+(G79*X_Cell_Dairy_Stage1MMS_1_AnaerobicLagoon_AmountSeparated_Method2)+(G84*X_Cell_Dairy_Stage1MMS_1_SumpAndDispersal_AmountSeparated_Method2)+(G89*X_Cell_Dairy_Stage1MMS_1_DrainsToPaddock_AmountSeparated_Method2) -> 0.4 | H96: =H94+(H79*X_Cell_Dairy_Stage1MMS_1_AnaerobicLagoon_AmountSeparated_Method2)+(H84*X_Cell_Dairy_Stage1MMS_1_SumpAndDispersal_AmountSeparated_Method2)+(H89*X_Cell_Dairy_Stage1MMS_1_DrainsToPaddock_AmountSeparated_Method2) -> 0.4 | I96: =I94+(I79*X_Cell_Dairy_Stage1MMS_1_AnaerobicLagoon_AmountSeparated_Method2)+(I84*X_Cell_Dairy_Stage1MMS_1_SumpAndDispersal_AmountSeparated_Method2)+(I89*X_Cell_Dairy_Stage1MMS_1_DrainsToPaddock_AmountSeparated_Method2) -> 0.4 | J96: Percent
D99: ="From " & $D$65 -> From Feed pad
D101: Stage 1 MMS | E101: Milking cows | F101: Heifers > 1 year | G101: Heifers < 1 year | H101: Bulls > 1 year | I101: Bulls < 1 year | J101: ► | L101: Destination after stage 2 MMS (Percent)
L102: Sold | M102: Fert for own farm (eg crop) | N102: Direct application to soil
D103: ='Constants - Dairy'!$D$8 -> Anaerobic lagoon | E103: 0.25 | F103: 0.25 | G103: 0.25 | H103: 0.25 | I103: 0.25 | J103: Percent | L103: 0.25 | M103: 0.25 | N103: =1-SUM(L103:M103) -> 0.5
D104: ="Were solids separated from " & D103 & "?" -> Were solids separated from Anaerobic lagoon? | E104: No
D105: ="Percent solids separated from " & D103 & " (Method 1)" -> Percent solids separated from Anaerobic lagoon (Method 1) | E105: =IF(X_Cell_Dairy_Stage1MMS_2_AnaerobicLagoon_SolidsSeparated="Yes", 20%, 0) -> 0
D106: ="Percent solids separated from " & D103 & " (Method 2)" -> Percent solids separated from Anaerobic lagoon (Method 2) | E106: =IF(X_Cell_Dairy_Stage1MMS_2_AnaerobicLagoon_SolidsSeparated="Yes", 20%, 0) -> 0
D108: ='Constants - Dairy'!$D$9 -> Sump and dispersal system | E108: 0.25 | F108: 0.25 | G108: 0.25 | H108: 0.25 | I108: 0.25 | J108: Percent | L108: 0.25 | M108: 0.25 | N108: =1-SUM(L108:M108) -> 0.5
D109: ="Were solids separated from " & D108 & "?" -> Were solids separated from Sump and dispersal system? | E109: Yes
D110: ="Percent solids separated from " & D108 & " (Method 1)" -> Percent solids separated from Sump and dispersal system (Method 1) | E110: =IF(X_Cell_Dairy_Stage1MMS_2_SumpAndDispersal_SolidsSeparated="Yes", 20%, 0) -> 0.2
D111: ="Percent solids separated from " & D108 & " (Method 2)" -> Percent solids separated from Sump and dispersal system (Method 2) | E111: =IF(X_Cell_Dairy_Stage1MMS_2_SumpAndDispersal_SolidsSeparated="Yes", 20%, 0) -> 0.2
D113: ='Constants - Dairy'!$D$10 -> Drains to paddock | E113: 0.25 | F113: 0.25 | G113: 0.25 | H113: 0.25 | I113: 0.25 | J113: Percent | L113: 0.25 | M113: 0.25 | N113: =1-SUM(L113:M113) -> 0.5
D114: ="Were solids separated from " & D113 & "?" -> Were solids separated from Drains to paddock? | E114: Yes
D115: ="Percent solids separated from " & D113 & " (Method 1)" -> Percent solids separated from Drains to paddock (Method 1) | E115: =IF(X_Cell_Dairy_Stage1MMS_2_DrainsToPaddock_SolidsSeparated="Yes", 20%, 0) -> 0.2
D116: ="Percent solids separated from " & D113 & " (Method 2)" -> Percent solids separated from Drains to paddock (Method 2) | E116: =IF(X_Cell_Dairy_Stage1MMS_2_DrainsToPaddock_SolidsSeparated="Yes", 20%, 0) -> 0.2
D118: ='Constants - Dairy'!$D$11 & " (before solid separation)" -> Solid storage (before solid separation) | E118: 0.25 | F118: 0.25 | G118: 0.25 | H118: 0.25 | I118: 0.25 | J118: Percent | L118: 0.25 | M118: 0.25 | N118: =1-SUM(L118:M118) -> 0.5
...

Sheet Input - Dairy (Enteric)
A1: #VALUE! | C1: Input -Dairy
A3: =HYPERLINK("#'Home'!A1", "Home") -> Home
A4: =HYPERLINK("#'Overview'!A1", "Overview") -> Overview
A5: =HYPERLINK("#'Results'!A1", "Results") -> Results | D5: Herd movement
D7: Breed | E7: Medium Friesian | F7: ← Please select
A8: INPUTS
A9: =HYPERLINK("#'Input - Enterprise'!A1", "Enterprise") -> Enterprise | E9: Milking cows | F9: Heifers > 1 year | G9: Heifers < 1 year | H9: Bulls > 1 year | I9: Bulls < 1 year
A10: =HYPERLINK("#'Input - Site'!A1", "Site") -> Site | D10: ="Average number of head between " & TEXT(X_Cell_Site_StartDate, "dd mmm yy") & " and " & TEXT(X_Cell_Site_EndDate, "dd mmm yy") -> Average number of head between 01 Jan 24 and 31 Dec 24 | E10: 100 | F10: 100 | G10: 100 | H10: 100 | I10: 100 | J10: head
A11: =HYPERLINK("#'Input - Dairy'!A1", "Dairy") -> Dairy
A12: =HYPERLINK("#'Input - Dairy (Enteric)'!A1", "Dairy (Enteric)") -> Dairy (Enteric) | D12: Liveweight
A13: =HYPERLINK("#'Input - Livestock sales'!A1", "Livestock sales") -> Livestock sales | D13: Method 1 default values (Do not edit) | E13: Milking cows | F13: Heifers > 1 year | G13: Heifers < 1 year | H13: Bulls > 1 year | I13: Bulls < 1 year
A14: =HYPERLINK("#'Input - Dairy cattle purchases'!A1", "Dairy cattle purchases") -> Dairy cattle purchases | D14: Average liveweight | E14: =Common_InputFunctions.Utility_LookupValueInTableNumber(X_Cell_Dairy_Breed, Table_SourceData_Dairy_WjCowsHeifers[Breed],Table_SourceData_Dairy_WjCowsHeifers[Milking cows]) -> 550 | F14: =Common_InputFunctions.Utility_LookupValueInTableNumber(X_Cell_Dairy_Breed, Table_SourceData_Dairy_WjCowsHeifers[Breed],Table_SourceData_Dairy_WjCowsHeifers[Heifers > 1]) -> 380 | G14: =Common_InputFunctions.Utility_LookupValueInTableNumber(X_Cell_Dairy_Breed, Table_SourceData_Dairy_WjCowsHeifers[Breed],Table_SourceData_Dairy_WjCowsHeifers[Heifers < 1 (weaned)]) -> 155 | H14: {=Table_SourceData_Dairy_WjBulls[Bulls > 1]} -> 600 | I14: {=Table_SourceData_Dairy_WjBulls[Bulls < 1 (weaned)]} -> 225 | J14: kg/head
A15: =HYPERLINK("#'Input - Pasture'!A1", "Pasture") -> Pasture | D15: Average liveweight gain | E15: {=Table_SourceData_Dairy_LWGj[Milking cows]} -> 0.016 | F15: {=Table_SourceData_Dairy_LWGj[Heifers > 1]} -> 0.6 | G15: {=Table_SourceData_Dairy_LWGj[Heifers < 1 (weaned)]} -> 0.57 | H15: {=Table_SourceData_Dairy_LWGj[Bulls > 1]} -> 0.1 | I15: {=Table_SourceData_Dairy_LWGj[Bulls < 1 (weaned)]} -> 0.8 | J15: kg/head/day
A16: =HYPERLINK("#'Input - Fert Prod System'!A1", "Fert Prod System") -> Fert Prod System
A17: =HYPERLINK("#'Input - Fertiliser'!A1", "Fertiliser") -> Fertiliser | D17: Method 2 custom values (Edit if known) | E17: Milking cows | F17: Heifers > 1 year | G17: Heifers < 1 year | H17: Bulls > 1 year | I17: Bulls < 1 year
A18: =HYPERLINK("#'Input - Fuel'!A1", "Fuel") -> Fuel | D18: Average liveweight | E18: =Common_InputFunctions.Utility_LookupValueInTableNumber(X_Cell_Dairy_Breed, Table_SourceData_Dairy_WjCowsHeifers[Breed],Table_SourceData_Dairy_WjCowsHeifers[Milking cows]) -> 550 | F18: =Common_InputFunctions.Utility_LookupValueInTableNumber(X_Cell_Dairy_Breed, Table_SourceData_Dairy_WjCowsHeifers[Breed],Table_SourceData_Dairy_WjCowsHeifers[Heifers > 1]) -> 380 | G18: =Common_InputFunctions.Utility_LookupValueInTableNumber(X_Cell_Dairy_Breed, Table_SourceData_Dairy_WjCowsHeifers[Breed],Table_SourceData_Dairy_WjCowsHeifers[Heifers < 1 (weaned)]) -> 155 | H18: {=Table_SourceData_Dairy_WjBulls[Bulls > 1]} -> 600 | I18: {=Table_SourceData_Dairy_WjBulls[Bulls < 1 (weaned)]} -> 225 | J18: kg/head
A19: =HYPERLINK("#'Input - Electricity'!A1", "Electricity") -> Electricity | D19: Average liveweight gain | E19: {=Table_SourceData_Dairy_LWGj[Milking cows]} -> 0.016 | F19: {=Table_SourceData_Dairy_LWGj[Heifers > 1]} -> 0.6 | G19: {=Table_SourceData_Dairy_LWGj[Heifers < 1 (weaned)]} -> 0.57 | H19: {=Table_SourceData_Dairy_LWGj[Bulls > 1]} -> 0.1 | I19: {=Table_SourceData_Dairy_LWGj[Bulls < 1 (weaned)]} -> 0.8 | J19: kg/head/day
A20: =HYPERLINK("#'Input - Farm Inputs'!A1", "Farm Inputs") -> Farm Inputs
A21: =HYPERLINK("#'Input - Freight'!A1", "Freight") -> Freight | D21: Duration of stay
A22: =HYPERLINK("#'Input - Manure sent off-site'!A1", "Manure sent off-site") -> Manure sent off-site
A23: =HYPERLINK("#'Input - Solid waste'!A1", "Solid waste") -> Solid waste | D23: Method 1 default values (Do not edit) | E23: Milking cows | F23: Heifers > 1 year | G23: Heifers < 1 year | H23: Bulls > 1 year | I23: Bulls < 1 year
A24: =HYPERLINK("#'Input - Data quality'!A1", "Data quality") -> Data quality | D24: ="Average duration of stay between " & TEXT(X_Cell_Site_StartDate, "dd mmm yy") & " and " & TEXT(X_Cell_Site_EndDate, "dd mmm yy") & " weaned livestock" -> Average duration of stay between 01 Jan 24 and 31 Dec 24 weaned livestock | E24: {=Common_InputFunctions.Utility_LookupValueInTableNumber(E23,Table_SourceData_Dairy_Duration[Animal class j],Table_SourceData_Dairy_Duration[Duration (weaned)])} -> 365 | F24: {=Common_InputFunctions.Utility_LookupValueInTableNumber(F23,Table_SourceData_Dairy_Duration[Animal class j],Table_SourceData_Dairy_Duration[Duration (weaned)])} -> 365 | G24: {=Common_InputFunctions.Utility_LookupValueInTableNumber(G23,Table_SourceData_Dairy_Duration[Animal class j],Table_SourceData_Dairy_Duration[Duration (weaned)])} -> 281 | H24: {=Common_InputFunctions.Utility_LookupValueInTableNumber(H23,Table_SourceData_Dairy_Duration[Animal class j],Table_SourceData_Dairy_Duration[Duration (weaned)])} -> 365 | I24: {=Common_InputFunctions.Utility_LookupValueInTableNumber(I23,Table_SourceData_Dairy_Duration[Animal class j],Table_SourceData_Dairy_Duration[Duration (weaned)])} -> 281 | J24: Days
D25: ="Average duration of stay between " & TEXT(X_Cell_Site_StartDate, "dd mmm yy") & " and " & TEXT(X_Cell_Site_EndDate, "dd mmm yy") & " pre-weaned livestock" -> Average duration of stay between 01 Jan 24 and 31 Dec 24 pre-weaned livestock | E25: {=Common_InputFunctions.Utility_LookupValueInTableNumber(E23,Table_SourceData_Dairy_Duration[Animal class j],Table_SourceData_Dairy_Duration[Duration (pre-weaned)])} -> 0 | F25: {=Common_InputFunctions.Utility_LookupValueInTableNumber(F23,Table_SourceData_Dairy_Duration[Animal class j],Table_SourceData_Dairy_Duration[Duration (pre-weaned)])} -> 0 | G25: {=Common_InputFunctions.Utility_LookupValueInTableNumber(G23,Table_SourceData_Dairy_Duration[Animal class j],Table_SourceData_Dairy_Duration[Duration (pre-weaned)])} -> 84 | H25: {=Common_InputFunctions.Utility_LookupValueInTableNumber(H23,Table_SourceData_Dairy_Duration[Animal class j],Table_SourceData_Dairy_Duration[Duration (pre-weaned)])} -> 0 | I25: {=Common_InputFunctions.Utility_LookupValueInTableNumber(I23,Table_SourceData_Dairy_Duration[Animal class j],Table_SourceData_Dairy_Duration[Duration (pre-weaned)])} -> 84 | J25: Days
A27: CALCULATIONS | D27: Method 2 custom values (Edit if known) | E27: Milking cows | F27: Heifers > 1 year | G27: Heifers < 1 year | H27: Bulls > 1 year | I27: Bulls < 1 year
A28: =HYPERLINK("#'5.1.1.1-2 Inorganic fert N2O'!A1", "5.1.1.1-2 Inorganic fert N2O") -> 5.1.1.1-2 Inorganic fert N2O | D28: ="Average duration of stay between " & TEXT(X_Cell_Site_StartDate, "dd mmm yy") & " and " & TEXT(X_Cell_Site_EndDate, "dd mmm yy") & " weaned livestock" -> Average duration of stay between 01 Jan 24 and 31 Dec 24 weaned livestock | E28: {=Common_InputFunctions.Utility_LookupValueInTableNumber(E27,Table_SourceData_Dairy_Duration[Animal class j],Table_SourceData_Dairy_Duration[Duration (weaned)])} -> 365 | F28: {=Common_InputFunctions.Utility_LookupValueInTableNumber(F27,Table_SourceData_Dairy_Duration[Animal class j],Table_SourceData_Dairy_Duration[Duration (weaned)])} -> 365 | G28: {=Common_InputFunctions.Utility_LookupValueInTableNumber(G27,Table_SourceData_Dairy_Duration[Animal class j],Table_SourceData_Dairy_Duration[Duration (weaned)])} -> 281 | H28: {=Common_InputFunctions.Utility_LookupValueInTableNumber(H27,Table_SourceData_Dairy_Duration[Animal class j],Table_SourceData_Dairy_Duration[Duration (weaned)])} -> 365 | I28: {=Common_InputFunctions.Utility_LookupValueInTableNumber(I27,Table_SourceData_Dairy_Duration[Animal class j],Table_SourceData_Dairy_Duration[Duration (weaned)])} -> 281 | J28: Days
A29: =HYPERLINK("#'5.1.1.3-4 Inorganic fert CO2'!A1", "5.1.1.3-4 Inorganic fert CO2") -> 5.1.1.3-4 Inorganic fert CO2 | D29: ="Average duration of stay between " & TEXT(X_Cell_Site_StartDate, "dd mmm yy") & " and " & TEXT(X_Cell_Site_EndDate, "dd mmm yy") & " pre-weaned livestock" -> Average duration of stay between 01 Jan 24 and 31 Dec 24 pre-weaned livestock | E29: =365-E28 -> 0 | F29: =365-F28 -> 0 | G29: =365-G28 -> 84 | H29: =365-H28 -> 0 | I29: =365-I28 -> 84 | J29: Days
A30: =HYPERLINK("#'5.2.1.1-2 Organic Fert N2O'!A1", "5.2.1.1-2 Organic fert N2O") -> 5.2.1.1-2 Organic fert N2O
A31: =HYPERLINK("#'5.3.1.1-2 Lime CO2'!A1", "5.3.1.1-2 Lime CO2") -> 5.3.1.1-2 Lime CO2
A32: =HYPERLINK("#'5.4.1.1-4 Atmos deposition'!A1", "5.4.1.1-4 Atmos. deposition") -> 5.4.1.1-4 Atmos. deposition
A33: =HYPERLINK("#'5.5.1.1-2 Leaching and runoff'!A1", "5.5.1.1-2 Leaching & runoff") -> 5.5.1.1-2 Leaching & runoff | D33: Diet
A34: =HYPERLINK("#'6.2.1.1-2 Pasture residue N2O'!A1", "6.2.1.1-2 Pasture residue N2O") -> 6.2.1.1-2 Pasture residue N2O
A35: =HYPERLINK("#'6.3.1.1-2 Leach runoff pasture'!A1", "6.3.1.1-2 Leach & runoff (pasture)") -> 6.3.1.1-2 Leach & runoff (pasture) | D35: Method 1 default values (Do not edit) | E35: Milking cows | F35: Heifers > 1 year | G35: Heifers < 1 year | H35: Bulls > 1 year | I35: Bulls < 1 year
A36: =HYPERLINK("#'8.1.1.1-2 Transport fuel'!A1", "8.1.1.1-2 Transport fuel") -> 8.1.1.1-2 Transport fuel | D36: Dry matter digestibility | E36: =SourceData_Dairy_DryMatterDigestibility_Data -> 0.75 | F36: =SourceData_Dairy_DryMatterDigestibility_Data -> 0.75 | G36: =SourceData_Dairy_DryMatterDigestibility_Data -> 0.75 | H36: =SourceData_Dairy_DryMatterDigestibility_Data -> 0.75 | I36: =SourceData_Dairy_DryMatterDigestibility_Data -> 0.75 | J36: Fraction
A37: =HYPERLINK("#'8.2.1.1-2 Stationary fuel'!A1", "8.2.1.1-2 Stationary fuel") -> 8.2.1.1-2 Stationary fuel | D37: Crude protein | E37: =SourceData_Dairy_CrudeProtein_Data -> 0.2 | F37: =SourceData_Dairy_CrudeProtein_Data -> 0.2 | G37: =SourceData_Dairy_CrudeProtein_Data -> 0.2 | H37: =SourceData_Dairy_CrudeProtein_Data -> 0.2 | I37: =SourceData_Dairy_CrudeProtein_Data -> 0.2 | J37: Fraction
A38: =HYPERLINK("#'14.1.1-2 Purchased electricity'!A1", "14.1.1-2 Purchased electricity") -> 14.1.1-2 Purchased electricity
A39: =HYPERLINK("#'15 Scope 3'!A1", "15 Scope 3") -> 15 Scope 3 | D39: Method 2 custom values (Edit if known) | E39: Milking cows | F39: Heifers > 1 year | G39: Heifers < 1 year | H39: Bulls > 1 year | I39: Bulls < 1 year
A40: =HYPERLINK("#'Calcs - Manure sent off-site'!A1", "Calcs - Manure sent off-site") -> Calcs - Manure sent off-site | D40: Dry matter digestibility | E40: =SourceData_Dairy_DryMatterDigestibility_Data -> 0.75 | F40: =SourceData_Dairy_DryMatterDigestibility_Data -> 0.75 | G40: =SourceData_Dairy_DryMatterDigestibility_Data -> 0.75 | H40: =SourceData_Dairy_DryMatterDigestibility_Data -> 0.75 | I40: =SourceData_Dairy_DryMatterDigestibility_Data -> 0.75 | J40: Fraction
A41: =HYPERLINK("#'4.3.1.1-2 Methane'!A1", "4.3.1.1-2 Methane") -> 4.3.1.1-2 Methane | D41: Crude protein | E41: =SourceData_Dairy_CrudeProtein_Data -> 0.2 | F41: =SourceData_Dairy_CrudeProtein_Data -> 0.2 | G41: =SourceData_Dairy_CrudeProtein_Data -> 0.2 | H41: =SourceData_Dairy_CrudeProtein_Data -> 0.2 | I41: =SourceData_Dairy_CrudeProtein_Data -> 0.2 | J41: Fraction
A42: =HYPERLINK("#'4.3.1.3-4 Direct N20'!A1", "4.3.1.3-4 Direct N20") -> 4.3.1.3-4 Direct N20
A43: =HYPERLINK("#'4.3.1.5 Atmos deposition'!A1", "4.3.1.5 Atmos deposition") -> 4.3.1.5 Atmos deposition
A44: =HYPERLINK("#'4.3.1.6-7 Leaching and runoff'!A1", "4.3.1.6-7 Leaching and runoff") -> 4.3.1.6-7 Leaching and runoff
A45: =HYPERLINK("#'4.3.1.8 Manure applied to soils'!A1", "4.3.1.8 Manure applied to soils") -> 4.3.1.8 Manure applied to soils | D45: Milk production
A46: =HYPERLINK("#'4.3.1.9 Soil direct N2O'!A1", "4.3.1.9 Soil direct N2O") -> 4.3.1.9 Soil direct N2O
A47: =HYPERLINK("#'4.3.1.10-11 Soil Atmos Dep'!A1", "4.3.1.10-11 Soil Atmos Dep") -> 4.3.1.10-11 Soil Atmos Dep | D47: Milk production unit | E47: Litres of milk | F47: ← Please select
A48: =HYPERLINK("#'4.3.1.12-13 Soil leach runoff'!A1", "4.3.1.12-13 Soil leach runoff") -> 4.3.1.12-13 Soil leach runoff
A49: =HYPERLINK("#'3.3.1.1-2 Enteric Methane'!A1", "3.3.1.1-2 Enteric Methane") -> 3.3.1.1-2 Enteric Methane | E49: Milking cows
A50: =HYPERLINK("#'10.1.1-2 Solid waste treatment'!A1", "10.1.1-2 Solid waste treatment") -> 10.1.1-2 Solid waste treatment | D50: Average daily milk production | E50: 20 | F50: =IF(X_Cell_Dairy_MilkProductionUnit="Litres of milk", "litres/head/day", "kg milk solids/head/day") -> litres/head/day
D52: For milk solids only: | E52: Method 1 (don't edit) | F52: Method 2 (edit if known)
A53: APPENDICES | D53: Fat content in fat and protein corrected milk | E53: =SourceData_Dairy_FatContentInMilk_Data/100 -> 0.0021 | F53: =SourceData_Dairy_FatContentInMilk_Data/100 -> 0.0021 | G53: percent
A54: =HYPERLINK("#'Constants - Dairy'!A1", "Constants - Dairy") -> Constants - Dairy | D54: Protein content in fat and protein corrected milk | E54: =SourceData_Dairy_ProteinContentInMilk_Data/100 -> 0.04 | F54: =SourceData_Dairy_ProteinContentInMilk_Data/100 -> 0.04 | G54: percent
A55: =HYPERLINK("#'Constants - Ag Residue'!A1", "Constants - Ag residue") -> Constants - Ag residue
A56: =HYPERLINK("#'Constants - Common Livestock'!A1", "Constants - Common Livestock") -> Constants - Common Livestock
A57: =HYPERLINK("#'Constants - Electricity'!A1", "Constants - Electricity") -> Constants - Electricity
A58: =HYPERLINK("#'Constants - Fertiliser'!A1", "Constants - Fertiliser") -> Constants - Fertiliser
A59: =HYPERLINK("#'Constants - Fuel'!A1", "Constants - Fuel") -> Constants - Fuel
A60: =HYPERLINK("#'Constants - Scope 3'!A1", "Constants - Scope 3") -> Constants - Scope 3
A61: =HYPERLINK("#'Constants - Common'!A1", "Constants - Common") -> Constants - Common
A62: =HYPERLINK("#'Acknowledgements'!A1", "Acknowledgements") -> Acknowledgements
A63: =HYPERLINK("#'Constants - Solid Waste'!A1", "Constants - Solid Waste") -> Constants - Solid Waste

Sheet Input - Livestock sales
A1: #VALUE! | C1: Input - Livestock sales
A3: =HYPERLINK("#'Home'!A1", "Home") -> Home
A4: =HYPERLINK("#'Overview'!A1", "Overview") -> Overview
A5: =HYPERLINK("#'Results'!A1", "Results") -> Results | D5: ⚠️ Livestock sales are not automatically reflected in the duration and head tables - you will need to manually adjust head count and average liveweight
D6: Transaction name | E6: Class (select) | F6: Sale date | G6: Head sold | H6: Average weight per head (kg) | I6: Total liveweight sold
F7: 45566 | G7: 10 | H7: 500 | I7: =G7*H7 -> 5000
A8: INPUTS | I8: =G8*H8 -> 0
A9: =HYPERLINK("#'Input - Enterprise'!A1", "Enterprise") -> Enterprise | I9: =G9*H9 -> 0
A10: =HYPERLINK("#'Input - Site'!A1", "Site") -> Site | I10: =G10*H10 -> 0
A11: =HYPERLINK("#'Input - Dairy'!A1", "Dairy") -> Dairy | I11: =G11*H11 -> 0
A12: =HYPERLINK("#'Input - Dairy (Enteric)'!A1", "Dairy (Enteric)") -> Dairy (Enteric) | I12: =G12*H12 -> 0
A13: =HYPERLINK("#'Input - Livestock sales'!A1", "Livestock sales") -> Livestock sales | I13: =G13*H13 -> 0
A14: =HYPERLINK("#'Input - Dairy cattle purchases'!A1", "Dairy cattle purchases") -> Dairy cattle purchases | I14: =G14*H14 -> 0
A15: =HYPERLINK("#'Input - Pasture'!A1", "Pasture") -> Pasture | I15: =G15*H15 -> 0
A16: =HYPERLINK("#'Input - Fert Prod System'!A1", "Fert Prod System") -> Fert Prod System | I16: =G16*H16 -> 0
A17: =HYPERLINK("#'Input - Fertiliser'!A1", "Fertiliser") -> Fertiliser
A18: =HYPERLINK("#'Input - Fuel'!A1", "Fuel") -> Fuel
A19: =HYPERLINK("#'Input - Electricity'!A1", "Electricity") -> Electricity
A20: =HYPERLINK("#'Input - Farm Inputs'!A1", "Farm Inputs") -> Farm Inputs
A21: =HYPERLINK("#'Input - Freight'!A1", "Freight") -> Freight
A22: =HYPERLINK("#'Input - Manure sent off-site'!A1", "Manure sent off-site") -> Manure sent off-site
A23: =HYPERLINK("#'Input - Solid waste'!A1", "Solid waste") -> Solid waste
A24: =HYPERLINK("#'Input - Data quality'!A1", "Data quality") -> Data quality
A27: CALCULATIONS
A28: =HYPERLINK("#'5.1.1.1-2 Inorganic fert N2O'!A1", "5.1.1.1-2 Inorganic fert N2O") -> 5.1.1.1-2 Inorganic fert N2O
A29: =HYPERLINK("#'5.1.1.3-4 Inorganic fert CO2'!A1", "5.1.1.3-4 Inorganic fert CO2") -> 5.1.1.3-4 Inorganic fert CO2
A30: =HYPERLINK("#'5.2.1.1-2 Organic Fert N2O'!A1", "5.2.1.1-2 Organic fert N2O") -> 5.2.1.1-2 Organic fert N2O
A31: =HYPERLINK("#'5.3.1.1-2 Lime CO2'!A1", "5.3.1.1-2 Lime CO2") -> 5.3.1.1-2 Lime CO2
A32: =HYPERLINK("#'5.4.1.1-4 Atmos deposition'!A1", "5.4.1.1-4 Atmos. deposition") -> 5.4.1.1-4 Atmos. deposition
A33: =HYPERLINK("#'5.5.1.1-2 Leaching and runoff'!A1", "5.5.1.1-2 Leaching & runoff") -> 5.5.1.1-2 Leaching & runoff
A34: =HYPERLINK("#'6.2.1.1-2 Pasture residue N2O'!A1", "6.2.1.1-2 Pasture residue N2O") -> 6.2.1.1-2 Pasture residue N2O
A35: =HYPERLINK("#'6.3.1.1-2 Leach runoff pasture'!A1", "6.3.1.1-2 Leach & runoff (pasture)") -> 6.3.1.1-2 Leach & runoff (pasture)
A36: =HYPERLINK("#'8.1.1.1-2 Transport fuel'!A1", "8.1.1.1-2 Transport fuel") -> 8.1.1.1-2 Transport fuel
A37: =HYPERLINK("#'8.2.1.1-2 Stationary fuel'!A1", "8.2.1.1-2 Stationary fuel") -> 8.2.1.1-2 Stationary fuel
A38: =HYPERLINK("#'14.1.1-2 Purchased electricity'!A1", "14.1.1-2 Purchased electricity") -> 14.1.1-2 Purchased electricity
A39: =HYPERLINK("#'15 Scope 3'!A1", "15 Scope 3") -> 15 Scope 3
A40: =HYPERLINK("#'Calcs - Manure sent off-site'!A1", "Calcs - Manure sent off-site") -> Calcs - Manure sent off-site
A41: =HYPERLINK("#'4.3.1.1-2 Methane'!A1", "4.3.1.1-2 Methane") -> 4.3.1.1-2 Methane
A42: =HYPERLINK("#'4.3.1.3-4 Direct N20'!A1", "4.3.1.3-4 Direct N20") -> 4.3.1.3-4 Direct N20
A43: =HYPERLINK("#'4.3.1.5 Atmos deposition'!A1", "4.3.1.5 Atmos deposition") -> 4.3.1.5 Atmos deposition
A44: =HYPERLINK("#'4.3.1.6-7 Leaching and runoff'!A1", "4.3.1.6-7 Leaching and runoff") -> 4.3.1.6-7 Leaching and runoff
A45: =HYPERLINK("#'4.3.1.8 Manure applied to soils'!A1", "4.3.1.8 Manure applied to soils") -> 4.3.1.8 Manure applied to soils
A46: =HYPERLINK("#'4.3.1.9 Soil direct N2O'!A1", "4.3.1.9 Soil direct N2O") -> 4.3.1.9 Soil direct N2O
A47: =HYPERLINK("#'4.3.1.10-11 Soil Atmos Dep'!A1", "4.3.1.10-11 Soil Atmos Dep") -> 4.3.1.10-11 Soil Atmos Dep
A48: =HYPERLINK("#'4.3.1.12-13 Soil leach runoff'!A1", "4.3.1.12-13 Soil leach runoff") -> 4.3.1.12-13 Soil leach runoff
A49: =HYPERLINK("#'3.3.1.1-2 Enteric Methane'!A1", "3.3.1.1-2 Enteric Methane") -> 3.3.1.1-2 Enteric Methane
A50: =HYPERLINK("#'10.1.1-2 Solid waste treatment'!A1", "10.1.1-2 Solid waste treatment") -> 10.1.1-2 Solid waste treatment
A53: APPENDICES
A54: =HYPERLINK("#'Constants - Dairy'!A1", "Constants - Dairy") -> Constants - Dairy
A55: =HYPERLINK("#'Constants - Ag Residue'!A1", "Constants - Ag residue") -> Constants - Ag residue
A56: =HYPERLINK("#'Constants - Common Livestock'!A1", "Constants - Common Livestock") -> Constants - Common Livestock
A57: =HYPERLINK("#'Constants - Electricity'!A1", "Constants - Electricity") -> Constants - Electricity
A58: =HYPERLINK("#'Constants - Fertiliser'!A1", "Constants - Fertiliser") -> Constants - Fertiliser
A59: =HYPERLINK("#'Constants - Fuel'!A1", "Constants - Fuel") -> Constants - Fuel
A60: =HYPERLINK("#'Constants - Scope 3'!A1", "Constants - Scope 3") -> Constants - Scope 3
A61: =HYPERLINK("#'Constants - Common'!A1", "Constants - Common") -> Constants - Common
A62: =HYPERLINK("#'Acknowledgements'!A1", "Acknowledgements") -> Acknowledgements
A63: =HYPERLINK("#'Constants - Solid Waste'!A1", "Constants - Solid Waste") -> Constants - Solid Waste

Sheet Input - Dairy cattle purchases
A1: #VALUE!
A3: =HYPERLINK("#'Home'!A1", "Home") -> Home
A4: =HYPERLINK("#'Overview'!A1", "Overview") -> Overview
A5: =HYPERLINK("#'Results'!A1", "Results") -> Results | D5: Dairy cattle
D6: Transaction name | E6: Class (select) | F6: Breed (select) | G6: Quantity (head) | H6: Liveweight (kg/head) Method 1 | I6: Liveweight (kg/head) Method 2
D7: Dairy cows from Denise | E7: Heifers < 1 (weaned) | F7: Jersey crossbred | G7: 100 | H7: {=Common_InputFunctions.Utility_LookupValueInTableOneColumnAndHeader(Table_Input_LivestockPurchases_Dairy[[#This Row],[Breed (select)]],Table_Input_LivestockPurchases_Dairy[[#This Row],[Class (select)]],Table_SourceData_Dairy_WjCowsHeifers[Breed],Table_SourceData_Dairy_WjCowsHeifers[#Headers],Table_SourceData_Dairy_WjCowsHeifers[#Data], 0)} -> 130 | I7: 350
A8: INPUTS | E8: Milking cows | F8: Ayrshire | G8: 100 | H8: {=Common_InputFunctions.Utility_LookupValueInTableOneColumnAndHeader(Table_Input_LivestockPurchases_Dairy[[#This Row],[Breed (select)]],Table_Input_LivestockPurchases_Dairy[[#This Row],[Class (select)]],Table_SourceData_Dairy_WjCowsHeifers[Breed],Table_SourceData_Dairy_WjCowsHeifers[#Headers],Table_SourceData_Dairy_WjCowsHeifers[#Data], 0)} -> 540 | I8: 625
A9: =HYPERLINK("#'Input - Enterprise'!A1", "Enterprise") -> Enterprise | E9: Heifers > 1 | F9: Jersey crossbred | H9: {=Common_InputFunctions.Utility_LookupValueInTableOneColumnAndHeader(Table_Input_LivestockPurchases_Dairy[[#This Row],[Breed (select)]],Table_Input_LivestockPurchases_Dairy[[#This Row],[Class (select)]],Table_SourceData_Dairy_WjCowsHeifers[Breed],Table_SourceData_Dairy_WjCowsHeifers[#Headers],Table_SourceData_Dairy_WjCowsHeifers[#Data], 0)} -> 315
A10: =HYPERLINK("#'Input - Site'!A1", "Site") -> Site | H10: {=Common_InputFunctions.Utility_LookupValueInTableOneColumnAndHeader(Table_Input_LivestockPurchases_Dairy[[#This Row],[Breed (select)]],Table_Input_LivestockPurchases_Dairy[[#This Row],[Class (select)]],Table_SourceData_Dairy_WjCowsHeifers[Breed],Table_SourceData_Dairy_WjCowsHeifers[#Headers],Table_SourceData_Dairy_WjCowsHeifers[#Data], 0)} -> 0
A11: =HYPERLINK("#'Input - Dairy'!A1", "Dairy") -> Dairy | H11: {=Common_InputFunctions.Utility_LookupValueInTableOneColumnAndHeader(Table_Input_LivestockPurchases_Dairy[[#This Row],[Breed (select)]],Table_Input_LivestockPurchases_Dairy[[#This Row],[Class (select)]],Table_SourceData_Dairy_WjCowsHeifers[Breed],Table_SourceData_Dairy_WjCowsHeifers[#Headers],Table_SourceData_Dairy_WjCowsHeifers[#Data], 0)} -> 0
A12: =HYPERLINK("#'Input - Dairy (Enteric)'!A1", "Dairy (Enteric)") -> Dairy (Enteric) | H12: {=Common_InputFunctions.Utility_LookupValueInTableOneColumnAndHeader(Table_Input_LivestockPurchases_Dairy[[#This Row],[Breed (select)]],Table_Input_LivestockPurchases_Dairy[[#This Row],[Class (select)]],Table_SourceData_Dairy_WjCowsHeifers[Breed],Table_SourceData_Dairy_WjCowsHeifers[#Headers],Table_SourceData_Dairy_WjCowsHeifers[#Data], 0)} -> 0
A13: =HYPERLINK("#'Input - Livestock sales'!A1", "Livestock sales") -> Livestock sales | H13: {=Common_InputFunctions.Utility_LookupValueInTableOneColumnAndHeader(Table_Input_LivestockPurchases_Dairy[[#This Row],[Breed (select)]],Table_Input_LivestockPurchases_Dairy[[#This Row],[Class (select)]],Table_SourceData_Dairy_WjCowsHeifers[Breed],Table_SourceData_Dairy_WjCowsHeifers[#Headers],Table_SourceData_Dairy_WjCowsHeifers[#Data], 0)} -> 0
A14: =HYPERLINK("#'Input - Dairy cattle purchases'!A1", "Dairy cattle purchases") -> Dairy cattle purchases | H14: {=Common_InputFunctions.Utility_LookupValueInTableOneColumnAndHeader(Table_Input_LivestockPurchases_Dairy[[#This Row],[Breed (select)]],Table_Input_LivestockPurchases_Dairy[[#This Row],[Class (select)]],Table_SourceData_Dairy_WjCowsHeifers[Breed],Table_SourceData_Dairy_WjCowsHeifers[#Headers],Table_SourceData_Dairy_WjCowsHeifers[#Data], 0)} -> 0
A15: =HYPERLINK("#'Input - Pasture'!A1", "Pasture") -> Pasture | H15: {=Common_InputFunctions.Utility_LookupValueInTableOneColumnAndHeader(Table_Input_LivestockPurchases_Dairy[[#This Row],[Breed (select)]],Table_Input_LivestockPurchases_Dairy[[#This Row],[Class (select)]],Table_SourceData_Dairy_WjCowsHeifers[Breed],Table_SourceData_Dairy_WjCowsHeifers[#Headers],Table_SourceData_Dairy_WjCowsHeifers[#Data], 0)} -> 0
A16: =HYPERLINK("#'Input - Fert Prod System'!A1", "Fert Prod System") -> Fert Prod System | H16: {=Common_InputFunctions.Utility_LookupValueInTableOneColumnAndHeader(Table_Input_LivestockPurchases_Dairy[[#This Row],[Breed (select)]],Table_Input_LivestockPurchases_Dairy[[#This Row],[Class (select)]],Table_SourceData_Dairy_WjCowsHeifers[Breed],Table_SourceData_Dairy_WjCowsHeifers[#Headers],Table_SourceData_Dairy_WjCowsHeifers[#Data], 0)} -> 0
A17: =HYPERLINK("#'Input - Fertiliser'!A1", "Fertiliser") -> Fertiliser
A18: =HYPERLINK("#'Input - Fuel'!A1", "Fuel") -> Fuel
A19: =HYPERLINK("#'Input - Electricity'!A1", "Electricity") -> Electricity
A20: =HYPERLINK("#'Input - Farm Inputs'!A1", "Farm Inputs") -> Farm Inputs
A21: =HYPERLINK("#'Input - Freight'!A1", "Freight") -> Freight
A22: =HYPERLINK("#'Input - Manure sent off-site'!A1", "Manure sent off-site") -> Manure sent off-site
A23: =HYPERLINK("#'Input - Solid waste'!A1", "Solid waste") -> Solid waste
A24: =HYPERLINK("#'Input - Data quality'!A1", "Data quality") -> Data quality
A27: CALCULATIONS
A28: =HYPERLINK("#'5.1.1.1-2 Inorganic fert N2O'!A1", "5.1.1.1-2 Inorganic fert N2O") -> 5.1.1.1-2 Inorganic fert N2O
A29: =HYPERLINK("#'5.1.1.3-4 Inorganic fert CO2'!A1", "5.1.1.3-4 Inorganic fert CO2") -> 5.1.1.3-4 Inorganic fert CO2
A30: =HYPERLINK("#'5.2.1.1-2 Organic Fert N2O'!A1", "5.2.1.1-2 Organic fert N2O") -> 5.2.1.1-2 Organic fert N2O
A31: =HYPERLINK("#'5.3.1.1-2 Lime CO2'!A1", "5.3.1.1-2 Lime CO2") -> 5.3.1.1-2 Lime CO2
A32: =HYPERLINK("#'5.4.1.1-4 Atmos deposition'!A1", "5.4.1.1-4 Atmos. deposition") -> 5.4.1.1-4 Atmos. deposition
A33: =HYPERLINK("#'5.5.1.1-2 Leaching and runoff'!A1", "5.5.1.1-2 Leaching & runoff") -> 5.5.1.1-2 Leaching & runoff
A34: =HYPERLINK("#'6.2.1.1-2 Pasture residue N2O'!A1", "6.2.1.1-2 Pasture residue N2O") -> 6.2.1.1-2 Pasture residue N2O
A35: =HYPERLINK("#'6.3.1.1-2 Leach runoff pasture'!A1", "6.3.1.1-2 Leach & runoff (pasture)") -> 6.3.1.1-2 Leach & runoff (pasture)
A36: =HYPERLINK("#'8.1.1.1-2 Transport fuel'!A1", "8.1.1.1-2 Transport fuel") -> 8.1.1.1-2 Transport fuel
A37: =HYPERLINK("#'8.2.1.1-2 Stationary fuel'!A1", "8.2.1.1-2 Stationary fuel") -> 8.2.1.1-2 Stationary fuel
A38: =HYPERLINK("#'14.1.1-2 Purchased electricity'!A1", "14.1.1-2 Purchased electricity") -> 14.1.1-2 Purchased electricity
A39: =HYPERLINK("#'15 Scope 3'!A1", "15 Scope 3") -> 15 Scope 3
A40: =HYPERLINK("#'Calcs - Manure sent off-site'!A1", "Calcs - Manure sent off-site") -> Calcs - Manure sent off-site
A41: =HYPERLINK("#'4.3.1.1-2 Methane'!A1", "4.3.1.1-2 Methane") -> 4.3.1.1-2 Methane
A42: =HYPERLINK("#'4.3.1.3-4 Direct N20'!A1", "4.3.1.3-4 Direct N20") -> 4.3.1.3-4 Direct N20
A43: =HYPERLINK("#'4.3.1.5 Atmos deposition'!A1", "4.3.1.5 Atmos deposition") -> 4.3.1.5 Atmos deposition
A44: =HYPERLINK("#'4.3.1.6-7 Leaching and runoff'!A1", "4.3.1.6-7 Leaching and runoff") -> 4.3.1.6-7 Leaching and runoff
A45: =HYPERLINK("#'4.3.1.8 Manure applied to soils'!A1", "4.3.1.8 Manure applied to soils") -> 4.3.1.8 Manure applied to soils
A46: =HYPERLINK("#'4.3.1.9 Soil direct N2O'!A1", "4.3.1.9 Soil direct N2O") -> 4.3.1.9 Soil direct N2O
A47: =HYPERLINK("#'4.3.1.10-11 Soil Atmos Dep'!A1", "4.3.1.10-11 Soil Atmos Dep") -> 4.3.1.10-11 Soil Atmos Dep
A48: =HYPERLINK("#'4.3.1.12-13 Soil leach runoff'!A1", "4.3.1.12-13 Soil leach runoff") -> 4.3.1.12-13 Soil leach runoff
A49: =HYPERLINK("#'3.3.1.1-2 Enteric Methane'!A1", "3.3.1.1-2 Enteric Methane") -> 3.3.1.1-2 Enteric Methane
A50: =HYPERLINK("#'10.1.1-2 Solid waste treatment'!A1", "10.1.1-2 Solid waste treatment") -> 10.1.1-2 Solid waste treatment
A53: APPENDICES
A54: =HYPERLINK("#'Constants - Dairy'!A1", "Constants - Dairy") -> Constants - Dairy
A55: =HYPERLINK("#'Constants - Ag Residue'!A1", "Constants - Ag residue") -> Constants - Ag residue
A56: =HYPERLINK("#'Constants - Common Livestock'!A1", "Constants - Common Livestock") -> Constants - Common Livestock
A57: =HYPERLINK("#'Constants - Electricity'!A1", "Constants - Electricity") -> Constants - Electricity
A58: =HYPERLINK("#'Constants - Fertiliser'!A1", "Constants - Fertiliser") -> Constants - Fertiliser
A59: =HYPERLINK("#'Constants - Fuel'!A1", "Constants - Fuel") -> Constants - Fuel
A60: =HYPERLINK("#'Constants - Scope 3'!A1", "Constants - Scope 3") -> Constants - Scope 3
A61: =HYPERLINK("#'Constants - Common'!A1", "Constants - Common") -> Constants - Common
A62: =HYPERLINK("#'Acknowledgements'!A1", "Acknowledgements") -> Acknowledgements
A63: =HYPERLINK("#'Constants - Solid Waste'!A1", "Constants - Solid Waste") -> Constants - Solid Waste

Sheet Input - Pasture
A1: #VALUE! | C1: Input - Pasture
A3: =HYPERLINK("#'Home'!A1", "Home") -> Home
A4: =HYPERLINK("#'Overview'!A1", "Overview") -> Overview
A5: =HYPERLINK("#'Results'!A1", "Results") -> Results | D5: Area
D7: If multiple paddocks were managed in the same way at the same time, you can enter information for them all together.
A8: INPUTS
A9: =HYPERLINK("#'Input - Enterprise'!A1", "Enterprise") -> Enterprise | D9: Pasture type | E9: Grass clover mixture | F9: ← Please select
A10: =HYPERLINK("#'Input - Site'!A1", "Site") -> Site | D10: Irrigation method | E10: Surface irrigation | F10: ← Please select
A11: =HYPERLINK("#'Input - Dairy'!A1", "Dairy") -> Dairy
A12: =HYPERLINK("#'Input - Dairy (Enteric)'!A1", "Dairy (Enteric)") -> Dairy (Enteric) | D12: Area under pasture | E12: 1000 | F12: Hectares
A13: =HYPERLINK("#'Input - Livestock sales'!A1", "Livestock sales") -> Livestock sales
A14: =HYPERLINK("#'Input - Dairy cattle purchases'!A1", "Dairy cattle purchases") -> Dairy cattle purchases | D14: Yield
A15: =HYPERLINK("#'Input - Pasture'!A1", "Pasture") -> Pasture
A16: =HYPERLINK("#'Input - Fert Prod System'!A1", "Fert Prod System") -> Fert Prod System | D16: 💡 'Pasture yield' is the average amount of dry matter that is grazed.
A17: =HYPERLINK("#'Input - Fertiliser'!A1", "Fertiliser") -> Fertiliser | D17: A default value is provided based on pasture type. You can edit this if known.
A18: =HYPERLINK("#'Input - Fuel'!A1", "Fuel") -> Fuel
A19: =HYPERLINK("#'Input - Electricity'!A1", "Electricity") -> Electricity | D19: Pasture yield | E19: =_xlfn.XLOOKUP(X_Cell_Pasture_PastureType, Table_SourceData_PastureAttributes[Pasture type],Table_SourceData_PastureAttributes[Average Yield (t DM ha) Yp]) -> 8.34 | F19: Tonnes dry matter / hectare
A20: =HYPERLINK("#'Input - Farm Inputs'!A1", "Farm Inputs") -> Farm Inputs | D20: Total pasture yield | E20: =X_Cell_Pasture_AreaUnderPasture*X_Cell_Pasture_YieldPerHectare -> 8340 | F20: Tonnes
A21: =HYPERLINK("#'Input - Freight'!A1", "Freight") -> Freight
A22: =HYPERLINK("#'Input - Manure sent off-site'!A1", "Manure sent off-site") -> Manure sent off-site
A23: =HYPERLINK("#'Input - Solid waste'!A1", "Solid waste") -> Solid waste | D23: Residue management
A24: =HYPERLINK("#'Input - Data quality'!A1", "Data quality") -> Data quality
D25: Area of pasture renewed or removed | E25: 500 | F25: Hectares
A27: CALCULATIONS
A28: =HYPERLINK("#'5.1.1.1-2 Inorganic fert N2O'!A1", "5.1.1.1-2 Inorganic fert N2O") -> 5.1.1.1-2 Inorganic fert N2O
A29: =HYPERLINK("#'5.1.1.3-4 Inorganic fert CO2'!A1", "5.1.1.3-4 Inorganic fert CO2") -> 5.1.1.3-4 Inorganic fert CO2
A30: =HYPERLINK("#'5.2.1.1-2 Organic Fert N2O'!A1", "5.2.1.1-2 Organic fert N2O") -> 5.2.1.1-2 Organic fert N2O
A31: =HYPERLINK("#'5.3.1.1-2 Lime CO2'!A1", "5.3.1.1-2 Lime CO2") -> 5.3.1.1-2 Lime CO2
A32: =HYPERLINK("#'5.4.1.1-4 Atmos deposition'!A1", "5.4.1.1-4 Atmos. deposition") -> 5.4.1.1-4 Atmos. deposition
A33: =HYPERLINK("#'5.5.1.1-2 Leaching and runoff'!A1", "5.5.1.1-2 Leaching & runoff") -> 5.5.1.1-2 Leaching & runoff
A34: =HYPERLINK("#'6.2.1.1-2 Pasture residue N2O'!A1", "6.2.1.1-2 Pasture residue N2O") -> 6.2.1.1-2 Pasture residue N2O
A35: =HYPERLINK("#'6.3.1.1-2 Leach runoff pasture'!A1", "6.3.1.1-2 Leach & runoff (pasture)") -> 6.3.1.1-2 Leach & runoff (pasture)
A36: =HYPERLINK("#'8.1.1.1-2 Transport fuel'!A1", "8.1.1.1-2 Transport fuel") -> 8.1.1.1-2 Transport fuel
A37: =HYPERLINK("#'8.2.1.1-2 Stationary fuel'!A1", "8.2.1.1-2 Stationary fuel") -> 8.2.1.1-2 Stationary fuel
A38: =HYPERLINK("#'14.1.1-2 Purchased electricity'!A1", "14.1.1-2 Purchased electricity") -> 14.1.1-2 Purchased electricity
A39: =HYPERLINK("#'15 Scope 3'!A1", "15 Scope 3") -> 15 Scope 3
A40: =HYPERLINK("#'Calcs - Manure sent off-site'!A1", "Calcs - Manure sent off-site") -> Calcs - Manure sent off-site
A41: =HYPERLINK("#'4.3.1.1-2 Methane'!A1", "4.3.1.1-2 Methane") -> 4.3.1.1-2 Methane
A42: =HYPERLINK("#'4.3.1.3-4 Direct N20'!A1", "4.3.1.3-4 Direct N20") -> 4.3.1.3-4 Direct N20
A43: =HYPERLINK("#'4.3.1.5 Atmos deposition'!A1", "4.3.1.5 Atmos deposition") -> 4.3.1.5 Atmos deposition
A44: =HYPERLINK("#'4.3.1.6-7 Leaching and runoff'!A1", "4.3.1.6-7 Leaching and runoff") -> 4.3.1.6-7 Leaching and runoff
A45: =HYPERLINK("#'4.3.1.8 Manure applied to soils'!A1", "4.3.1.8 Manure applied to soils") -> 4.3.1.8 Manure applied to soils
A46: =HYPERLINK("#'4.3.1.9 Soil direct N2O'!A1", "4.3.1.9 Soil direct N2O") -> 4.3.1.9 Soil direct N2O
A47: =HYPERLINK("#'4.3.1.10-11 Soil Atmos Dep'!A1", "4.3.1.10-11 Soil Atmos Dep") -> 4.3.1.10-11 Soil Atmos Dep
A48: =HYPERLINK("#'4.3.1.12-13 Soil leach runoff'!A1", "4.3.1.12-13 Soil leach runoff") -> 4.3.1.12-13 Soil leach runoff
A49: =HYPERLINK("#'3.3.1.1-2 Enteric Methane'!A1", "3.3.1.1-2 Enteric Methane") -> 3.3.1.1-2 Enteric Methane
A50: =HYPERLINK("#'10.1.1-2 Solid waste treatment'!A1", "10.1.1-2 Solid waste treatment") -> 10.1.1-2 Solid waste treatment
A53: APPENDICES
A54: =HYPERLINK("#'Constants - Dairy'!A1", "Constants - Dairy") -> Constants - Dairy
A55: =HYPERLINK("#'Constants - Ag Residue'!A1", "Constants - Ag residue") -> Constants - Ag residue
A56: =HYPERLINK("#'Constants - Common Livestock'!A1", "Constants - Common Livestock") -> Constants - Common Livestock
A57: =HYPERLINK("#'Constants - Electricity'!A1", "Constants - Electricity") -> Constants - Electricity
A58: =HYPERLINK("#'Constants - Fertiliser'!A1", "Constants - Fertiliser") -> Constants - Fertiliser
A59: =HYPERLINK("#'Constants - Fuel'!A1", "Constants - Fuel") -> Constants - Fuel
A60: =HYPERLINK("#'Constants - Scope 3'!A1", "Constants - Scope 3") -> Constants - Scope 3
A61: =HYPERLINK("#'Constants - Common'!A1", "Constants - Common") -> Constants - Common
A62: =HYPERLINK("#'Acknowledgements'!A1", "Acknowledgements") -> Acknowledgements
A63: =HYPERLINK("#'Constants - Solid Waste'!A1", "Constants - Solid Waste") -> Constants - Solid Waste

Sheet Input - Fert Prod System
A1: #VALUE! | C1: Input - Fertiliser Production System
A3: =HYPERLINK("#'Home'!A1", "Home") -> Home
A4: =HYPERLINK("#'Overview'!A1", "Overview") -> Overview
A5: =HYPERLINK("#'Results'!A1", "Results") -> Results | D5: These inputs are used for fertiliser calculations, and they take their values from the "Input - Pasture" sheet. Do not edit these cells.
D7: Production system | E7: Pasture
A8: INPUTS | D8: Crop type | E8: Pasture
A9: =HYPERLINK("#'Input - Enterprise'!A1", "Enterprise") -> Enterprise | D9: Irrigation method | E9: {=X_Cell_Pasture_IrrigationMethod} -> Surface irrigation
A10: =HYPERLINK("#'Input - Site'!A1", "Site") -> Site | D10: Area under cropping | E10: {=X_Cell_Pasture_AreaUnderPasture} -> 1000
A11: =HYPERLINK("#'Input - Dairy'!A1", "Dairy") -> Dairy
A12: =HYPERLINK("#'Input - Dairy (Enteric)'!A1", "Dairy (Enteric)") -> Dairy (Enteric)
A13: =HYPERLINK("#'Input - Livestock sales'!A1", "Livestock sales") -> Livestock sales
A14: =HYPERLINK("#'Input - Dairy cattle purchases'!A1", "Dairy cattle purchases") -> Dairy cattle purchases
A15: =HYPERLINK("#'Input - Pasture'!A1", "Pasture") -> Pasture
A16: =HYPERLINK("#'Input - Fert Prod System'!A1", "Fert Prod System") -> Fert Prod System
A17: =HYPERLINK("#'Input - Fertiliser'!A1", "Fertiliser") -> Fertiliser
A18: =HYPERLINK("#'Input - Fuel'!A1", "Fuel") -> Fuel
A19: =HYPERLINK("#'Input - Electricity'!A1", "Electricity") -> Electricity
A20: =HYPERLINK("#'Input - Farm Inputs'!A1", "Farm Inputs") -> Farm Inputs
A21: =HYPERLINK("#'Input - Freight'!A1", "Freight") -> Freight
A22: =HYPERLINK("#'Input - Manure sent off-site'!A1", "Manure sent off-site") -> Manure sent off-site
A23: =HYPERLINK("#'Input - Solid waste'!A1", "Solid waste") -> Solid waste
A24: =HYPERLINK("#'Input - Data quality'!A1", "Data quality") -> Data quality
A27: CALCULATIONS
A28: =HYPERLINK("#'5.1.1.1-2 Inorganic fert N2O'!A1", "5.1.1.1-2 Inorganic fert N2O") -> 5.1.1.1-2 Inorganic fert N2O
A29: =HYPERLINK("#'5.1.1.3-4 Inorganic fert CO2'!A1", "5.1.1.3-4 Inorganic fert CO2") -> 5.1.1.3-4 Inorganic fert CO2
A30: =HYPERLINK("#'5.2.1.1-2 Organic Fert N2O'!A1", "5.2.1.1-2 Organic fert N2O") -> 5.2.1.1-2 Organic fert N2O
A31: =HYPERLINK("#'5.3.1.1-2 Lime CO2'!A1", "5.3.1.1-2 Lime CO2") -> 5.3.1.1-2 Lime CO2
A32: =HYPERLINK("#'5.4.1.1-4 Atmos deposition'!A1", "5.4.1.1-4 Atmos. deposition") -> 5.4.1.1-4 Atmos. deposition
A33: =HYPERLINK("#'5.5.1.1-2 Leaching and runoff'!A1", "5.5.1.1-2 Leaching & runoff") -> 5.5.1.1-2 Leaching & runoff
A34: =HYPERLINK("#'6.2.1.1-2 Pasture residue N2O'!A1", "6.2.1.1-2 Pasture residue N2O") -> 6.2.1.1-2 Pasture residue N2O
A35: =HYPERLINK("#'6.3.1.1-2 Leach runoff pasture'!A1", "6.3.1.1-2 Leach & runoff (pasture)") -> 6.3.1.1-2 Leach & runoff (pasture)
A36: =HYPERLINK("#'8.1.1.1-2 Transport fuel'!A1", "8.1.1.1-2 Transport fuel") -> 8.1.1.1-2 Transport fuel
A37: =HYPERLINK("#'8.2.1.1-2 Stationary fuel'!A1", "8.2.1.1-2 Stationary fuel") -> 8.2.1.1-2 Stationary fuel
A38: =HYPERLINK("#'14.1.1-2 Purchased electricity'!A1", "14.1.1-2 Purchased electricity") -> 14.1.1-2 Purchased electricity
A39: =HYPERLINK("#'15 Scope 3'!A1", "15 Scope 3") -> 15 Scope 3
A40: =HYPERLINK("#'Calcs - Manure sent off-site'!A1", "Calcs - Manure sent off-site") -> Calcs - Manure sent off-site
A41: =HYPERLINK("#'4.3.1.1-2 Methane'!A1", "4.3.1.1-2 Methane") -> 4.3.1.1-2 Methane
A42: =HYPERLINK("#'4.3.1.3-4 Direct N20'!A1", "4.3.1.3-4 Direct N20") -> 4.3.1.3-4 Direct N20
A43: =HYPERLINK("#'4.3.1.5 Atmos deposition'!A1", "4.3.1.5 Atmos deposition") -> 4.3.1.5 Atmos deposition
A44: =HYPERLINK("#'4.3.1.6-7 Leaching and runoff'!A1", "4.3.1.6-7 Leaching and runoff") -> 4.3.1.6-7 Leaching and runoff
A45: =HYPERLINK("#'4.3.1.8 Manure applied to soils'!A1", "4.3.1.8 Manure applied to soils") -> 4.3.1.8 Manure applied to soils
A46: =HYPERLINK("#'4.3.1.9 Soil direct N2O'!A1", "4.3.1.9 Soil direct N2O") -> 4.3.1.9 Soil direct N2O
A47: =HYPERLINK("#'4.3.1.10-11 Soil Atmos Dep'!A1", "4.3.1.10-11 Soil Atmos Dep") -> 4.3.1.10-11 Soil Atmos Dep
A48: =HYPERLINK("#'4.3.1.12-13 Soil leach runoff'!A1", "4.3.1.12-13 Soil leach runoff") -> 4.3.1.12-13 Soil leach runoff
A49: =HYPERLINK("#'3.3.1.1-2 Enteric Methane'!A1", "3.3.1.1-2 Enteric Methane") -> 3.3.1.1-2 Enteric Methane
A50: =HYPERLINK("#'10.1.1-2 Solid waste treatment'!A1", "10.1.1-2 Solid waste treatment") -> 10.1.1-2 Solid waste treatment
A53: APPENDICES
A54: =HYPERLINK("#'Constants - Dairy'!A1", "Constants - Dairy") -> Constants - Dairy
A55: =HYPERLINK("#'Constants - Ag Residue'!A1", "Constants - Ag residue") -> Constants - Ag residue
A56: =HYPERLINK("#'Constants - Common Livestock'!A1", "Constants - Common Livestock") -> Constants - Common Livestock
A57: =HYPERLINK("#'Constants - Electricity'!A1", "Constants - Electricity") -> Constants - Electricity
A58: =HYPERLINK("#'Constants - Fertiliser'!A1", "Constants - Fertiliser") -> Constants - Fertiliser
A59: =HYPERLINK("#'Constants - Fuel'!A1", "Constants - Fuel") -> Constants - Fuel
A60: =HYPERLINK("#'Constants - Scope 3'!A1", "Constants - Scope 3") -> Constants - Scope 3
A61: =HYPERLINK("#'Constants - Common'!A1", "Constants - Common") -> Constants - Common
A62: =HYPERLINK("#'Acknowledgements'!A1", "Acknowledgements") -> Acknowledgements
A63: =HYPERLINK("#'Constants - Solid Waste'!A1", "Constants - Solid Waste") -> Constants - Solid Waste

Sheet Input - Fertiliser
A1: #VALUE! | C1: Input - Fertiliser
A3: =HYPERLINK("#'Home'!A1", "Home") -> Home
A4: =HYPERLINK("#'Overview'!A1", "Overview") -> Overview
A5: =HYPERLINK("#'Results'!A1", "Results") -> Results | D5: Inorganic fertiliser applied
D7: 💡You can add more rows to tables by right-clicking on the table and selecting "Insert > Table rows above/below".
A8: INPUTS | D8: 💡The application area is the same as the area under pasture / cropping by default. You can edit it if the application area is different.
A9: =HYPERLINK("#'Input - Enterprise'!A1", "Enterprise") -> Enterprise
A10: =HYPERLINK("#'Input - Site'!A1", "Site") -> Site | D10: Branded fertiliser products
A11: =HYPERLINK("#'Input - Dairy'!A1", "Dairy") -> Dairy | D11: Product (select) | E11: Amount applied per hectare | F11: Application unit | G11: Density | H11: Application area (ha) | I11: Total applied (kg) | J11: Ingredient 1 | K11: Ingredient 1 percent | L11: Ingredient 2 | M11: Ingredient 2 percent | N11: Ingredient 3 | O11: Ingredient 3 percent | P11: Ingredient 4 | Q11: Ingredient 4 percent | R11: Ingredient 5 | S11: Ingredient 5 percent | T11: Ingredient 6 | U11: Ingredient 6 percent | V11: N application rate (kg/ha) | W11: Urea source | X11: Ammonia source
A12: =HYPERLINK("#'Input - Dairy (Enteric)'!A1", "Dairy (Enteric)") -> Dairy (Enteric) | D12: Aqua Finish | E12: 100 | F12: =_xlfn.XLOOKUP(Table_Input_InorganicFertiliser_Brands[[#This Row],[Product (select)]],FertiliserProducts[Product name],FertiliserProducts[Unit]) -> L | G12: =_xlfn.XLOOKUP(Table_Input_InorganicFertiliser_Brands[[#This Row],[Product (select)]],FertiliserProducts[Product name],FertiliserProducts[Density / gravity]) -> 1.26 | H12: =X_Cell_Fertiliser_AreaUnderCropping -> 1000 | I12: =(Table_Input_InorganicFertiliser_Brands[[#This Row],[Amount applied per hectare]]*Table_Input_InorganicFertiliser_Brands[[#This Row],[Density]])*Table_Input_InorganicFertiliser_Brands[[#This Row],[Application area (ha)]] -> 126000 | J12: {=Fertiliser_InputFunctions.Fertiliser_FertiliserProductLookup(Table_Input_InorganicFertiliser_Brands[[#This Row],[Product (select)]], Table_Input_InorganicFertiliser_Brands[[#Headers],[Ingredient 1]], FertiliserProducts[#Data], FertiliserProducts[Product name], FertiliserProducts[#Headers])} -> Potassium - Generic | K12: {=Fertiliser_InputFunctions.Fertiliser_FertiliserProductLookup(Table_Input_InorganicFertiliser_Brands[[#This Row],[Product (select)]], Table_Input_InorganicFertiliser_Brands[[#Headers],[Ingredient 1 percent]], FertiliserProducts[#Data], FertiliserProducts[Product name], FertiliserProducts[#Headers])} -> 0.225 | L12: {=Fertiliser_InputFunctions.Fertiliser_FertiliserProductLookup(Table_Input_InorganicFertiliser_Brands[[#This Row],[Product (select)]], Table_Input_InorganicFertiliser_Brands[[#Headers],[Ingredient 2]], FertiliserProducts[#Data], FertiliserProducts[Product name], FertiliserProducts[#Headers])} -> Phosphorus - Generic | M12: {=Fertiliser_InputFunctions.Fertiliser_FertiliserProductLookup(Table_Input_InorganicFertiliser_Brands[[#This Row],[Product (select)]], Table_Input_InorganicFertiliser_Brands[[#Headers],[Ingredient 2 percent]], FertiliserProducts[#Data], FertiliserProducts[Product name], FertiliserProducts[#Headers])} -> 0.04 | N12: {=Fertiliser_InputFunctions.Fertiliser_FertiliserProductLookup(Table_Input_InorganicFertiliser_Brands[[#This Row],[Product (select)]], Table_Input_InorganicFertiliser_Brands[[#Headers],[Ingredient 3]], FertiliserProducts[#Data], FertiliserProducts[Product name], FertiliserProducts[#Headers])} -> Nitrogen - Generic | O12: {=Fertiliser_InputFunctions.Fertiliser_FertiliserProductLookup(Table_Input_InorganicFertiliser_Brands[[#This Row],[Product (select)]], Table_Input_InorganicFertiliser_Brands[[#Headers],[Ingredient 3 percent]], FertiliserProducts[#Data], FertiliserProducts[Product name], FertiliserProducts[#Headers])} -> 0.026 | P12: {=Fertiliser_InputFunctions.Fertiliser_FertiliserProductLookup(Table_Input_InorganicFertiliser_Brands[[#This Row],[Product (select)]], Table_Input_InorganicFertiliser_Brands[[#Headers],[Ingredient 4]], FertiliserProducts[#Data], FertiliserProducts[Product name], FertiliserProducts[#Headers])} | Q12: {=Fertiliser_InputFunctions.Fertiliser_FertiliserProductLookup(Table_Input_InorganicFertiliser_Brands[[#This Row],[Product (select)]], Table_Input_InorganicFertiliser_Brands[[#Headers],[Ingredient 4 percent]], FertiliserProducts[#Data], FertiliserProducts[Product name], FertiliserProducts[#Headers])} | R12: {=Fertiliser_InputFunctions.Fertiliser_FertiliserProductLookup(Table_Input_InorganicFertiliser_Brands[[#This Row],[Product (select)]], Table_Input_InorganicFertiliser_Brands[[#Headers],[Ingredient 5]], FertiliserProducts[#Data], FertiliserProducts[Product name], FertiliserProducts[#Headers])} | S12: {=Fertiliser_InputFunctions.Fertiliser_FertiliserProductLookup(Table_Input_InorganicFertiliser_Brands[[#This Row],[Product (select)]], Table_Input_InorganicFertiliser_Brands[[#Headers],[Ingredient 5 percent]], FertiliserProducts[#Data], FertiliserProducts[Product name], FertiliserProducts[#Headers])} | T12: {=Fertiliser_InputFunctions.Fertiliser_FertiliserProductLookup(Table_Input_InorganicFertiliser_Brands[[#This Row],[Product (select)]], Table_Input_InorganicFertiliser_Brands[[#Headers],[Ingredient 6]], FertiliserProducts[#Data], FertiliserProducts[Product name], FertiliserProducts[#Headers])} | U12: {=Fertiliser_InputFunctions.Fertiliser_FertiliserProductLookup(Table_Input_InorganicFertiliser_Brands[[#This Row],[Product (select)]], Table_Input_InorganicFertiliser_Brands[[#Headers],[Ingredient 6 percent]], FertiliserProducts[#Data], FertiliserProducts[Product name], FertiliserProducts[#Headers])} | V12: =(Table_Input_InorganicFertiliser_Brands[[#This Row],[Amount applied per hectare]]*Table_Input_InorganicFertiliser_Brands[[#This Row],[Density]])*(IFERROR((_xlfn.XLOOKUP(Table_Input_InorganicFertiliser_Brands[[#This Row],[Ingredient 1]], Table_Fertiliser_ChemicalCompounds[Fertiliser type f],Table_Fertiliser_ChemicalCompounds[FNinorganic f])*Table_Input_InorganicFertiliser_Brands[[#This Row],[Ingredient 1 percent]]), 0)+ IFERROR((_xlfn.XLOOKUP(Table_Input_InorganicFertiliser_Brands[[#This Row],[Ingredient 2]],Table_Fertiliser_ChemicalCompounds[Fertiliser type f],Table_Fertiliser_ChemicalCompounds[FNinorganic f])*Table_Input_InorganicFertiliser_Brands[[#This Row],[Ingredient 2 percent]]), 0)+ IFERROR((_xlfn.XLOOKUP(Table_Input_InorganicFertiliser_Brands[[#This Row],[Ingredient 3]],Table_Fertiliser_ChemicalCompounds[Fertiliser type f],Table_Fertiliser_ChemicalCompounds[FNinorganic f])*Table_Input_InorganicFertiliser_Brands[[#This Row],[Ingredient 3 percent]]), 0)+ IFERROR((_xlfn.XLOOKUP(Table_Input_InorganicFertiliser_Brands[[#This Row],[Ingredient 4]],Table_Fertiliser_ChemicalCompounds[Fertiliser type f],Table_Fertiliser_ChemicalCompounds[FNinorganic f])*Table_Input_InorganicFertiliser_Brands[[#This Row],[Ingredient 4 percent]]), 0)+ IFERROR((_xlfn.XLOOKUP(Table_Input_InorganicFertiliser_Brands[[#This Row],[Ingredient 5]],Table_Fertiliser_ChemicalCompounds[Fertiliser type f],Table_Fertiliser_ChemicalCompounds[FNinorganic f])*Table_Input_InorganicFertiliser_Brands[[#This Row],[Ingredient 5 percent]]), 0)+ IFERROR((_xlfn.XLOOKUP(Table_Input_InorganicFertiliser_Brands[[#This Row],[Ingredient 6]],Table_Fertiliser_ChemicalCompounds[Fertiliser type f],Table_Fertiliser_ChemicalCompounds[FNinorganic f])*Table_Input_InorganicFertiliser_Brands[[#This Row],[Ingredient 6 percent]]), 0)) -> 3.276 | W12: =_xlfn.XLOOKUP(Table_Input_InorganicFertiliser_Brands[[#This Row],[Product (select)]],FertiliserProducts[Product name],FertiliserProducts[Urea source]) | X12: =_xlfn.XLOOKUP(Table_Input_InorganicFertiliser_Brands[[#This Row],[Product (select)]],FertiliserProducts[Product name],FertiliserProducts[Ammonia source])
A13: =HYPERLINK("#'Input - Livestock sales'!A1", "Livestock sales") -> Livestock sales | D13: CalPhos | E13: 100 | F13: =_xlfn.XLOOKUP(Table_Input_InorganicFertiliser_Brands[[#This Row],[Product (select)]],FertiliserProducts[Product name],FertiliserProducts[Unit]) -> L | G13: =_xlfn.XLOOKUP(Table_Input_InorganicFertiliser_Brands[[#This Row],[Product (select)]],FertiliserProducts[Product name],FertiliserProducts[Density / gravity]) -> 1.285 | H13: =X_Cell_Fertiliser_AreaUnderCropping -> 1000 | I13: =(Table_Input_InorganicFertiliser_Brands[[#This Row],[Amount applied per hectare]]*Table_Input_InorganicFertiliser_Brands[[#This Row],[Density]])*Table_Input_InorganicFertiliser_Brands[[#This Row],[Application area (ha)]] -> 128500 | J13: {=Fertiliser_InputFunctions.Fertiliser_FertiliserProductLookup(Table_Input_InorganicFertiliser_Brands[[#This Row],[Product (select)]], Table_Input_InorganicFertiliser_Brands[[#Headers],[Ingredient 1]], FertiliserProducts[#Data], FertiliserProducts[Product name], FertiliserProducts[#Headers])} -> Phosphorus - Generic | K13: {=Fertiliser_InputFunctions.Fertiliser_FertiliserProductLookup(Table_Input_InorganicFertiliser_Brands[[#This Row],[Product (select)]], Table_Input_InorganicFertiliser_Brands[[#Headers],[Ingredient 1 percent]], FertiliserProducts[#Data], FertiliserProducts[Product name], FertiliserProducts[#Headers])} -> 0.135 | L13: {=Fertiliser_InputFunctions.Fertiliser_FertiliserProductLookup(Table_Input_InorganicFertiliser_Brands[[#This Row],[Product (select)]], Table_Input_InorganicFertiliser_Brands[[#Headers],[Ingredient 2]], FertiliserProducts[#Data], FertiliserProducts[Product name], FertiliserProducts[#Headers])} -> Calcium - Generic | M13: {=Fertiliser_InputFunctions.Fertiliser_FertiliserProductLookup(Table_Input_InorganicFertiliser_Brands[[#This Row],[Product (select)]], Table_Input_InorganicFertiliser_Brands[[#Headers],[Ingredient 2 percent]], FertiliserProducts[#Data], FertiliserProducts[Product name], FertiliserProducts[#Headers])} -> 0.04 | N13: {=Fertiliser_InputFunctions.Fertiliser_FertiliserProductLookup(Table_Input_InorganicFertiliser_Brands[[#This Row],[Product (select)]], Table_Input_InorganicFertiliser_Brands[[#Headers],[Ingredient 3]], FertiliserProducts[#Data], FertiliserProducts[Product name], FertiliserProducts[#Headers])} | O13: {=Fertiliser_InputFunctions.Fertiliser_FertiliserProductLookup(Table_Input_InorganicFertiliser_Brands[[#This Row],[Product (select)]], Table_Input_InorganicFertiliser_Brands[[#Headers],[Ingredient 3 percent]], FertiliserProducts[#Data], FertiliserProducts[Product name], FertiliserProducts[#Headers])} | P13: {=Fertiliser_InputFunctions.Fertiliser_FertiliserProductLookup(Table_Input_InorganicFertiliser_Brands[[#This Row],[Product (select)]], Table_Input_InorganicFertiliser_Brands[[#Headers],[Ingredient 4]], FertiliserProducts[#Data], FertiliserProducts[Product name], FertiliserProducts[#Headers])} | Q13: {=Fertiliser_InputFunctions.Fertiliser_FertiliserProductLookup(Table_Input_InorganicFertiliser_Brands[[#This Row],[Product (select)]], Table_Input_InorganicFertiliser_Brands[[#Headers],[Ingredient 4 percent]], FertiliserProducts[#Data], FertiliserProducts[Product name], FertiliserProducts[#Headers])} | R13: {=Fertiliser_InputFunctions.Fertiliser_FertiliserProductLookup(Table_Input_InorganicFertiliser_Brands[[#This Row],[Product (select)]], Table_Input_InorganicFertiliser_Brands[[#Headers],[Ingredient 5]], FertiliserProducts[#Data], FertiliserProducts[Product name], FertiliserProducts[#Headers])} | S13: {=Fertiliser_InputFunctions.Fertiliser_FertiliserProductLookup(Table_Input_InorganicFertiliser_Brands[[#This Row],[Product (select)]], Table_Input_InorganicFertiliser_Brands[[#Headers],[Ingredient 5 percent]], FertiliserProducts[#Data], FertiliserProducts[Product name], FertiliserProducts[#Headers])} | T13: {=Fertiliser_InputFunctions.Fertiliser_FertiliserProductLookup(Table_Input_InorganicFertiliser_Brands[[#This Row],[Product (select)]], Table_Input_InorganicFertiliser_Brands[[#Headers],[Ingredient 6]], FertiliserProducts[#Data], FertiliserProducts[Product name], FertiliserProducts[#Headers])} | U13: {=Fertiliser_InputFunctions.Fertiliser_FertiliserProductLookup(Table_Input_InorganicFertiliser_Brands[[#This Row],[Product (select)]], Table_Input_InorganicFertiliser_Brands[[#Headers],[Ingredient 6 percent]], FertiliserProducts[#Data], FertiliserProducts[Product name], FertiliserProducts[#Headers])} | V13: =(Table_Input_InorganicFertiliser_Brands[[#This Row],[Amount applied per hectare]]*Table_Input_InorganicFertiliser_Brands[[#This Row],[Density]])*(IFERROR((_xlfn.XLOOKUP(Table_Input_InorganicFertiliser_Brands[[#This Row],[Ingredient 1]], Table_Fertiliser_ChemicalCompounds[Fertiliser type f],Table_Fertiliser_ChemicalCompounds[FNinorganic f])*Table_Input_InorganicFertiliser_Brands[[#This Row],[Ingredient 1 percent]]), 0)+ IFERROR((_xlfn.XLOOKUP(Table_Input_InorganicFertiliser_Brands[[#This Row],[Ingredient 2]],Table_Fertiliser_ChemicalCompounds[Fertiliser type f],Table_Fertiliser_ChemicalCompounds[FNinorganic f])*Table_Input_InorganicFertiliser_Brands[[#This Row],[Ingredient 2 percent]]), 0)+ IFERROR((_xlfn.XLOOKUP(Table_Input_InorganicFertiliser_Brands[[#This Row],[Ingredient 3]],Table_Fertiliser_ChemicalCompounds[Fertiliser type f],Table_Fertiliser_ChemicalCompounds[FNinorganic f])*Table_Input_InorganicFertiliser_Brands[[#This Row],[Ingredient 3 percent]]), 0)+ IFERROR((_xlfn.XLOOKUP(Table_Input_InorganicFertiliser_Brands[[#This Row],[Ingredient 4]],Table_Fertiliser_ChemicalCompounds[Fertiliser type f],Table_Fertiliser_ChemicalCompounds[FNinorganic f])*Table_Input_InorganicFertiliser_Brands[[#This Row],[Ingredient 4 percent]]), 0)+ IFERROR((_xlfn.XLOOKUP(Table_Input_InorganicFertiliser_Brands[[#This Row],[Ingredient 5]],Table_Fertiliser_ChemicalCompounds[Fertiliser type f],Table_Fertiliser_ChemicalCompounds[FNinorganic f])*Table_Input_InorganicFertiliser_Brands[[#This Row],[Ingredient 5 percent]]), 0)+ IFERROR((_xlfn.XLOOKUP(Table_Input_InorganicFertiliser_Brands[[#This Row],[Ingredient 6]],Table_Fertiliser_ChemicalCompounds[Fertiliser type f],Table_Fertiliser_ChemicalCompounds[FNinorganic f])*Table_Input_InorganicFertiliser_Brands[[#This Row],[Ingredient 6 percent]]), 0)) -> 0 | W13: =_xlfn.XLOOKUP(Table_Input_InorganicFertiliser_Brands[[#This Row],[Product (select)]],FertiliserProducts[Product name],FertiliserProducts[Urea source]) | X13: =_xlfn.XLOOKUP(Table_Input_InorganicFertiliser_Brands[[#This Row],[Product (select)]],FertiliserProducts[Product name],FertiliserProducts[Ammonia source])
A14: =HYPERLINK("#'Input - Dairy cattle purchases'!A1", "Dairy cattle purchases") -> Dairy cattle purchases | D14: CalPhos | E14: 100 | F14: =_xlfn.XLOOKUP(Table_Input_InorganicFertiliser_Brands[[#This Row],[Product (select)]],FertiliserProducts[Product name],FertiliserProducts[Unit]) -> L | G14: =_xlfn.XLOOKUP(Table_Input_InorganicFertiliser_Brands[[#This Row],[Product (select)]],FertiliserProducts[Product name],FertiliserProducts[Density / gravity]) -> 1.285 | H14: =X_Cell_Fertiliser_AreaUnderCropping -> 1000 | I14: =(Table_Input_InorganicFertiliser_Brands[[#This Row],[Amount applied per hectare]]*Table_Input_InorganicFertiliser_Brands[[#This Row],[Density]])*Table_Input_InorganicFertiliser_Brands[[#This Row],[Application area (ha)]] -> 128500 | J14: {=Fertiliser_InputFunctions.Fertiliser_FertiliserProductLookup(Table_Input_InorganicFertiliser_Brands[[#This Row],[Product (select)]], Table_Input_InorganicFertiliser_Brands[[#Headers],[Ingredient 1]], FertiliserProducts[#Data], FertiliserProducts[Product name], FertiliserProducts[#Headers])} -> Phosphorus - Generic | K14: {=Fertiliser_InputFunctions.Fertiliser_FertiliserProductLookup(Table_Input_InorganicFertiliser_Brands[[#This Row],[Product (select)]], Table_Input_InorganicFertiliser_Brands[[#Headers],[Ingredient 1 percent]], FertiliserProducts[#Data], FertiliserProducts[Product name], FertiliserProducts[#Headers])} -> 0.135 | L14: {=Fertiliser_InputFunctions.Fertiliser_FertiliserProductLookup(Table_Input_InorganicFertiliser_Brands[[#This Row],[Product (select)]], Table_Input_InorganicFertiliser_Brands[[#Headers],[Ingredient 2]], FertiliserProducts[#Data], FertiliserProducts[Product name], FertiliserProducts[#Headers])} -> Calcium - Generic | M14: {=Fertiliser_InputFunctions.Fertiliser_FertiliserProductLookup(Table_Input_InorganicFertiliser_Brands[[#This Row],[Product (select)]], Table_Input_InorganicFertiliser_Brands[[#Headers],[Ingredient 2 percent]], FertiliserProducts[#Data], FertiliserProducts[Product name], FertiliserProducts[#Headers])} -> 0.04 | N14: {=Fertiliser_InputFunctions.Fertiliser_FertiliserProductLookup(Table_Input_InorganicFertiliser_Brands[[#This Row],[Product (select)]], Table_Input_InorganicFertiliser_Brands[[#Headers],[Ingredient 3]], FertiliserProducts[#Data], FertiliserProducts[Product name], FertiliserProducts[#Headers])} | O14: {=Fertiliser_InputFunctions.Fertiliser_FertiliserProductLookup(Table_Input_InorganicFertiliser_Brands[[#This Row],[Product (select)]], Table_Input_InorganicFertiliser_Brands[[#Headers],[Ingredient 3 percent]], FertiliserProducts[#Data], FertiliserProducts[Product name], FertiliserProducts[#Headers])} | P14: {=Fertiliser_InputFunctions.Fertiliser_FertiliserProductLookup(Table_Input_InorganicFertiliser_Brands[[#This Row],[Product (select)]], Table_Input_InorganicFertiliser_Brands[[#Headers],[Ingredient 4]], FertiliserProducts[#Data], FertiliserProducts[Product name], FertiliserProducts[#Headers])} | Q14: {=Fertiliser_InputFunctions.Fertiliser_FertiliserProductLookup(Table_Input_InorganicFertiliser_Brands[[#This Row],[Product (select)]], Table_Input_InorganicFertiliser_Brands[[#Headers],[Ingredient 4 percent]], FertiliserProducts[#Data], FertiliserProducts[Product name], FertiliserProducts[#Headers])} | R14: {=Fertiliser_InputFunctions.Fertiliser_FertiliserProductLookup(Table_Input_InorganicFertiliser_Brands[[#This Row],[Product (select)]], Table_Input_InorganicFertiliser_Brands[[#Headers],[Ingredient 5]], FertiliserProducts[#Data], FertiliserProducts[Product name], FertiliserProducts[#Headers])} | S14: {=Fertiliser_InputFunctions.Fertiliser_FertiliserProductLookup(Table_Input_InorganicFertiliser_Brands[[#This Row],[Product (select)]], Table_Input_InorganicFertiliser_Brands[[#Headers],[Ingredient 5 percent]], FertiliserProducts[#Data], FertiliserProducts[Product name], FertiliserProducts[#Headers])} | T14: {=Fertiliser_InputFunctions.Fertiliser_FertiliserProductLookup(Table_Input_InorganicFertiliser_Brands[[#This Row],[Product (select)]], Table_Input_InorganicFertiliser_Brands[[#Headers],[Ingredient 6]], FertiliserProducts[#Data], FertiliserProducts[Product name], FertiliserProducts[#Headers])} | U14: {=Fertiliser_InputFunctions.Fertiliser_FertiliserProductLookup(Table_Input_InorganicFertiliser_Brands[[#This Row],[Product (select)]], Table_Input_InorganicFertiliser_Brands[[#Headers],[Ingredient 6 percent]], FertiliserProducts[#Data], FertiliserProducts[Product name], FertiliserProducts[#Headers])} | V14: =(Table_Input_InorganicFertiliser_Brands[[#This Row],[Amount applied per hectare]]*Table_Input_InorganicFertiliser_Brands[[#This Row],[Density]])*(IFERROR((_xlfn.XLOOKUP(Table_Input_InorganicFertiliser_Brands[[#This Row],[Ingredient 1]], Table_Fertiliser_ChemicalCompounds[Fertiliser type f],Table_Fertiliser_ChemicalCompounds[FNinorganic f])*Table_Input_InorganicFertiliser_Brands[[#This Row],[Ingredient 1 percent]]), 0)+ IFERROR((_xlfn.XLOOKUP(Table_Input_InorganicFertiliser_Brands[[#This Row],[Ingredient 2]],Table_Fertiliser_ChemicalCompounds[Fertiliser type f],Table_Fertiliser_ChemicalCompounds[FNinorganic f])*Table_Input_InorganicFertiliser_Brands[[#This Row],[Ingredient 2 percent]]), 0)+ IFERROR((_xlfn.XLOOKUP(Table_Input_InorganicFertiliser_Brands[[#This Row],[Ingredient 3]],Table_Fertiliser_ChemicalCompounds[Fertiliser type f],Table_Fertiliser_ChemicalCompounds[FNinorganic f])*Table_Input_InorganicFertiliser_Brands[[#This Row],[Ingredient 3 percent]]), 0)+ IFERROR((_xlfn.XLOOKUP(Table_Input_InorganicFertiliser_Brands[[#This Row],[Ingredient 4]],Table_Fertiliser_ChemicalCompounds[Fertiliser type f],Table_Fertiliser_ChemicalCompounds[FNinorganic f])*Table_Input_InorganicFertiliser_Brands[[#This Row],[Ingredient 4 percent]]), 0)+ IFERROR((_xlfn.XLOOKUP(Table_Input_InorganicFertiliser_Brands[[#This Row],[Ingredient 5]],Table_Fertiliser_ChemicalCompounds[Fertiliser type f],Table_Fertiliser_ChemicalCompounds[FNinorganic f])*Table_Input_InorganicFertiliser_Brands[[#This Row],[Ingredient 5 percent]]), 0)+ IFERROR((_xlfn.XLOOKUP(Table_Input_InorganicFertiliser_Brands[[#This Row],[Ingredient 6]],Table_Fertiliser_ChemicalCompounds[Fertiliser type f],Table_Fertiliser_ChemicalCompounds[FNinorganic f])*Table_Input_InorganicFertiliser_Brands[[#This Row],[Ingredient 6 percent]]), 0)) -> 0 | W14: =_xlfn.XLOOKUP(Table_Input_InorganicFertiliser_Brands[[#This Row],[Product (select)]],FertiliserProducts[Product name],FertiliserProducts[Urea source]) | X14: =_xlfn.XLOOKUP(Table_Input_InorganicFertiliser_Brands[[#This Row],[Product (select)]],FertiliserProducts[Product name],FertiliserProducts[Ammonia source])
A15: =HYPERLINK("#'Input - Pasture'!A1", "Pasture") -> Pasture | D15: Aqua Grow | E15: 100 | F15: =_xlfn.XLOOKUP(Table_Input_InorganicFertiliser_Brands[[#This Row],[Product (select)]],FertiliserProducts[Product name],FertiliserProducts[Unit]) -> L | G15: =_xlfn.XLOOKUP(Table_Input_InorganicFertiliser_Brands[[#This Row],[Product (select)]],FertiliserProducts[Product name],FertiliserProducts[Density / gravity]) -> 1.26 | H15: =X_Cell_Fertiliser_AreaUnderCropping -> 1000 | I15: =(Table_Input_InorganicFertiliser_Brands[[#This Row],[Amount applied per hectare]]*Table_Input_InorganicFertiliser_Brands[[#This Row],[Density]])*Table_Input_InorganicFertiliser_Brands[[#This Row],[Application area (ha)]] -> 126000 | J15: {=Fertiliser_InputFunctions.Fertiliser_FertiliserProductLookup(Table_Input_InorganicFertiliser_Brands[[#This Row],[Product (select)]], Table_Input_InorganicFertiliser_Brands[[#Headers],[Ingredient 1]], FertiliserProducts[#Data], FertiliserProducts[Product name], FertiliserProducts[#Headers])} -> Potassium - Generic | K15: {=Fertiliser_InputFunctions.Fertiliser_FertiliserProductLookup(Table_Input_InorganicFertiliser_Brands[[#This Row],[Product (select)]], Table_Input_InorganicFertiliser_Brands[[#Headers],[Ingredient 1 percent]], FertiliserProducts[#Data], FertiliserProducts[Product name], FertiliserProducts[#Headers])} -> 0.105 | L15: {=Fertiliser_InputFunctions.Fertiliser_FertiliserProductLookup(Table_Input_InorganicFertiliser_Brands[[#This Row],[Product (select)]], Table_Input_InorganicFertiliser_Brands[[#Headers],[Ingredient 2]], FertiliserProducts[#Data], FertiliserProducts[Product name], FertiliserProducts[#Headers])} -> Nitrogen - Generic | M15: {=Fertiliser_InputFunctions.Fertiliser_FertiliserProductLookup(Table_Input_InorganicFertiliser_Brands[[#This Row],[Product (select)]], Table_Input_InorganicFertiliser_Brands[[#Headers],[Ingredient 2 percent]], FertiliserProducts[#Data], FertiliserProducts[Product name], FertiliserProducts[#Headers])} -> 0.096 | N15: {=Fertiliser_InputFunctions.Fertiliser_FertiliserProductLookup(Table_Input_InorganicFertiliser_Brands[[#This Row],[Product (select)]], Table_Input_InorganicFertiliser_Brands[[#Headers],[Ingredient 3]], FertiliserProducts[#Data], FertiliserProducts[Product name], FertiliserProducts[#Headers])} -> Phosphorus - Generic | O15: {=Fertiliser_InputFunctions.Fertiliser_FertiliserProductLookup(Table_Input_InorganicFertiliser_Brands[[#This Row],[Product (select)]], Table_Input_InorganicFertiliser_Brands[[#Headers],[Ingredient 3 percent]], FertiliserProducts[#Data], FertiliserProducts[Product name], FertiliserProducts[#Headers])} -> 0.05 | P15: {=Fertiliser_InputFunctions.Fertiliser_FertiliserProductLookup(Table_Input_InorganicFertiliser_Brands[[#This Row],[Product (select)]], Table_Input_InorganicFertiliser_Brands[[#Headers],[Ingredient 4]], FertiliserProducts[#Data], FertiliserProducts[Product name], FertiliserProducts[#Headers])} | Q15: {=Fertiliser_InputFunctions.Fertiliser_FertiliserProductLookup(Table_Input_InorganicFertiliser_Brands[[#This Row],[Product (select)]], Table_Input_InorganicFertiliser_Brands[[#Headers],[Ingredient 4 percent]], FertiliserProducts[#Data], FertiliserProducts[Product name], FertiliserProducts[#Headers])} | R15: {=Fertiliser_InputFunctions.Fertiliser_FertiliserProductLookup(Table_Input_InorganicFertiliser_Brands[[#This Row],[Product (select)]], Table_Input_InorganicFertiliser_Brands[[#Headers],[Ingredient 5]], FertiliserProducts[#Data], FertiliserProducts[Product name], FertiliserProducts[#Headers])} | S15: {=Fertiliser_InputFunctions.Fertiliser_FertiliserProductLookup(Table_Input_InorganicFertiliser_Brands[[#This Row],[Product (select)]], Table_Input_InorganicFertiliser_Brands[[#Headers],[Ingredient 5 percent]], FertiliserProducts[#Data], FertiliserProducts[Product name], FertiliserProducts[#Headers])} | T15: {=Fertiliser_InputFunctions.Fertiliser_FertiliserProductLookup(Table_Input_InorganicFertiliser_Brands[[#This Row],[Product (select)]], Table_Input_InorganicFertiliser_Brands[[#Headers],[Ingredient 6]], FertiliserProducts[#Data], FertiliserProducts[Product name], FertiliserProducts[#Headers])} | U15: {=Fertiliser_InputFunctions.Fertiliser_FertiliserProductLookup(Table_Input_InorganicFertiliser_Brands[[#This Row],[Product (select)]], Table_Input_InorganicFertiliser_Brands[[#Headers],[Ingredient 6 percent]], FertiliserProducts[#Data], FertiliserProducts[Product name], FertiliserProducts[#Headers])} | V15: =(Table_Input_InorganicFertiliser_Brands[[#This Row],[Amount applied per hectare]]*Table_Input_InorganicFertiliser_Brands[[#This Row],[Density]])*(IFERROR((_xlfn.XLOOKUP(Table_Input_InorganicFertiliser_Brands[[#This Row],[Ingredient 1]], Table_Fertiliser_ChemicalCompounds[Fertiliser type f],Table_Fertiliser_ChemicalCompounds[FNinorganic f])*Table_Input_InorganicFertiliser_Brands[[#This Row],[Ingredient 1 percent]]), 0)+ IFERROR((_xlfn.XLOOKUP(Table_Input_InorganicFertiliser_Brands[[#This Row],[Ingredient 2]],Table_Fertiliser_ChemicalCompounds[Fertiliser type f],Table_Fertiliser_ChemicalCompounds[FNinorganic f])*Table_Input_InorganicFertiliser_Brands[[#This Row],[Ingredient 2 percent]]), 0)+ IFERROR((_xlfn.XLOOKUP(Table_Input_InorganicFertiliser_Brands[[#This Row],[Ingredient 3]],Table_Fertiliser_ChemicalCompounds[Fertiliser type f],Table_Fertiliser_ChemicalCompounds[FNinorganic f])*Table_Input_InorganicFertiliser_Brands[[#This Row],[Ingredient 3 percent]]), 0)+ IFERROR((_xlfn.XLOOKUP(Table_Input_InorganicFertiliser_Brands[[#This Row],[Ingredient 4]],Table_Fertiliser_ChemicalCompounds[Fertiliser type f],Table_Fertiliser_ChemicalCompounds[FNinorganic f])*Table_Input_InorganicFertiliser_Brands[[#This Row],[Ingredient 4 percent]]), 0)+ IFERROR((_xlfn.XLOOKUP(Table_Input_InorganicFertiliser_Brands[[#This Row],[Ingredient 5]],Table_Fertiliser_ChemicalCompounds[Fertiliser type f],Table_Fertiliser_ChemicalCompounds[FNinorganic f])*Table_Input_InorganicFertiliser_Brands[[#This Row],[Ingredient 5 percent]]), 0)+ IFERROR((_xlfn.XLOOKUP(Table_Input_InorganicFertiliser_Brands[[#This Row],[Ingredient 6]],Table_Fertiliser_ChemicalCompounds[Fertiliser type f],Table_Fertiliser_ChemicalCompounds[FNinorganic f])*Table_Input_InorganicFertiliser_Brands[[#This Row],[Ingredient 6 percent]]), 0)) -> 12.096 | W15: =_xlfn.XLOOKUP(Table_Input_InorganicFertiliser_Brands[[#This Row],[Product (select)]],FertiliserProducts[Product name],FertiliserProducts[Urea source]) | X15: =_xlfn.XLOOKUP(Table_Input_InorganicFertiliser_Brands[[#This Row],[Product (select)]],FertiliserProducts[Product name],FertiliserProducts[Ammonia source])
A16: =HYPERLINK("#'Input - Fert Prod System'!A1", "Fert Prod System") -> Fert Prod System | D16: Aqua NitroCal | E16: 100 | F16: =_xlfn.XLOOKUP(Table_Input_InorganicFertiliser_Brands[[#This Row],[Product (select)]],FertiliserProducts[Product name],FertiliserProducts[Unit]) -> L | G16: =_xlfn.XLOOKUP(Table_Input_InorganicFertiliser_Brands[[#This Row],[Product (select)]],FertiliserProducts[Product name],FertiliserProducts[Density / gravity]) -> 1.5 | H16: =X_Cell_Fertiliser_AreaUnderCropping -> 1000 | I16: =(Table_Input_InorganicFertiliser_Brands[[#This Row],[Amount applied per hectare]]*Table_Input_InorganicFertiliser_Brands[[#This Row],[Density]])*Table_Input_InorganicFertiliser_Brands[[#This Row],[Application area (ha)]] -> 150000 | J16: {=Fertiliser_InputFunctions.Fertiliser_FertiliserProductLookup(Table_Input_InorganicFertiliser_Brands[[#This Row],[Product (select)]], Table_Input_InorganicFertiliser_Brands[[#Headers],[Ingredient 1]], FertiliserProducts[#Data], FertiliserProducts[Product name], FertiliserProducts[#Headers])} -> Calcium - Generic | K16: {=Fertiliser_InputFunctions.Fertiliser_FertiliserProductLookup(Table_Input_InorganicFertiliser_Brands[[#This Row],[Product (select)]], Table_Input_InorganicFertiliser_Brands[[#Headers],[Ingredient 1 percent]], FertiliserProducts[#Data], FertiliserProducts[Product name], FertiliserProducts[#Headers])} -> 0.162 | L16: {=Fertiliser_InputFunctions.Fertiliser_FertiliserProductLookup(Table_Input_InorganicFertiliser_Brands[[#This Row],[Product (select)]], Table_Input_InorganicFertiliser_Brands[[#Headers],[Ingredient 2]], FertiliserProducts[#Data], FertiliserProducts[Product name], FertiliserProducts[#Headers])} -> Nitrogen - Nitrate | M16: {=Fertiliser_InputFunctions.Fertiliser_FertiliserProductLookup(Table_Input_InorganicFertiliser_Brands[[#This Row],[Product (select)]], Table_Input_InorganicFertiliser_Brands[[#Headers],[Ingredient 2 percent]], FertiliserProducts[#Data], FertiliserProducts[Product name], FertiliserProducts[#Headers])} -> 0.132 | N16: {=Fertiliser_InputFunctions.Fertiliser_FertiliserProductLookup(Table_Input_InorganicFertiliser_Brands[[#This Row],[Product (select)]], Table_Input_InorganicFertiliser_Brands[[#Headers],[Ingredient 3]], FertiliserProducts[#Data], FertiliserProducts[Product name], FertiliserProducts[#Headers])} | O16: {=Fertiliser_InputFunctions.Fertiliser_FertiliserProductLookup(Table_Input_InorganicFertiliser_Brands[[#This Row],[Product (select)]], Table_Input_InorganicFertiliser_Brands[[#Headers],[Ingredient 3 percent]], FertiliserProducts[#Data], FertiliserProducts[Product name], FertiliserProducts[#Headers])} | P16: {=Fertiliser_InputFunctions.Fertiliser_FertiliserProductLookup(Table_Input_InorganicFertiliser_Brands[[#This Row],[Product (select)]], Table_Input_InorganicFertiliser_Brands[[#Headers],[Ingredient 4]], FertiliserProducts[#Data], FertiliserProducts[Product name], FertiliserProducts[#Headers])} | Q16: {=Fertiliser_InputFunctions.Fertiliser_FertiliserProductLookup(Table_Input_InorganicFertiliser_Brands[[#This Row],[Product (select)]], Table_Input_InorganicFertiliser_Brands[[#Headers],[Ingredient 4 percent]], FertiliserProducts[#Data], FertiliserProducts[Product name], FertiliserProducts[#Headers])} | R16: {=Fertiliser_InputFunctions.Fertiliser_FertiliserProductLookup(Table_Input_InorganicFertiliser_Brands[[#This Row],[Product (select)]], Table_Input_InorganicFertiliser_Brands[[#Headers],[Ingredient 5]], FertiliserProducts[#Data], FertiliserProducts[Product name], FertiliserProducts[#Headers])} | S16: {=Fertiliser_InputFunctions.Fertiliser_FertiliserProductLookup(Table_Input_InorganicFertiliser_Brands[[#This Row],[Product (select)]], Table_Input_InorganicFertiliser_Brands[[#Headers],[Ingredient 5 percent]], FertiliserProducts[#Data], FertiliserProducts[Product name], FertiliserProducts[#Headers])} | T16: {=Fertiliser_InputFunctions.Fertiliser_FertiliserProductLookup(Table_Input_InorganicFertiliser_Brands[[#This Row],[Product (select)]], Table_Input_InorganicFertiliser_Brands[[#Headers],[Ingredient 6]], FertiliserProducts[#Data], FertiliserProducts[Product name], FertiliserProducts[#Headers])} | U16: {=Fertiliser_InputFunctions.Fertiliser_FertiliserProductLookup(Table_Input_InorganicFertiliser_Brands[[#This Row],[Product (select)]], Table_Input_InorganicFertiliser_Brands[[#Headers],[Ingredient 6 percent]], FertiliserProducts[#Data], FertiliserProducts[Product name], FertiliserProducts[#Headers])} | V16: =(Table_Input_InorganicFertiliser_Brands[[#This Row],[Amount applied per hectare]]*Table_Input_InorganicFertiliser_Brands[[#This Row],[Density]])*(IFERROR((_xlfn.XLOOKUP(Table_Input_InorganicFertiliser_Brands[[#This Row],[Ingredient 1]], Table_Fertiliser_ChemicalCompounds[Fertiliser type f],Table_Fertiliser_ChemicalCompounds[FNinorganic f])*Table_Input_InorganicFertiliser_Brands[[#This Row],[Ingredient 1 percent]]), 0)+ IFERROR((_xlfn.XLOOKUP(Table_Input_InorganicFertiliser_Brands[[#This Row],[Ingredient 2]],Table_Fertiliser_ChemicalCompounds[Fertiliser type f],Table_Fertiliser_ChemicalCompounds[FNinorganic f])*Table_Input_InorganicFertiliser_Brands[[#This Row],[Ingredient 2 percent]]), 0)+ IFERROR((_xlfn.XLOOKUP(Table_Input_InorganicFertiliser_Brands[[#This Row],[Ingredient 3]],Table_Fertiliser_ChemicalCompounds[Fertiliser type f],Table_Fertiliser_ChemicalCompounds[FNinorganic f])*Table_Input_InorganicFertiliser_Brands[[#This Row],[Ingredient 3 percent]]), 0)+ IFERROR((_xlfn.XLOOKUP(Table_Input_InorganicFertiliser_Brands[[#This Row],[Ingredient 4]],Table_Fertiliser_ChemicalCompounds[Fertiliser type f],Table_Fertiliser_ChemicalCompounds[FNinorganic f])*Table_Input_InorganicFertiliser_Brands[[#This Row],[Ingredient 4 percent]]), 0)+ IFERROR((_xlfn.XLOOKUP(Table_Input_InorganicFertiliser_Brands[[#This Row],[Ingredient 5]],Table_Fertiliser_ChemicalCompounds[Fertiliser type f],Table_Fertiliser_ChemicalCompounds[FNinorganic f])*Table_Input_InorganicFertiliser_Brands[[#This Row],[Ingredient 5 percent]]), 0)+ IFERROR((_xlfn.XLOOKUP(Table_Input_InorganicFertiliser_Brands[[#This Row],[Ingredient 6]],Table_Fertiliser_ChemicalCompounds[Fertiliser type f],Table_Fertiliser_ChemicalCompounds[FNinorganic f])*Table_Input_InorganicFertiliser_Brands[[#This Row],[Ingredient 6 percent]]), 0)) -> 19.8 | W16: =_xlfn.XLOOKUP(Table_Input_InorganicFertiliser_Brands[[#This Row],[Product (select)]],FertiliserProducts[Product name],FertiliserProducts[Urea source]) | X16: =_xlfn.XLOOKUP(Table_Input_InorganicFertiliser_Brands[[#This Row],[Product (select)]],FertiliserProducts[Product name],FertiliserProducts[Ammonia source])
A17: =HYPERLINK("#'Input - Fertiliser'!A1", "Fertiliser") -> Fertiliser
A18: =HYPERLINK("#'Input - Fuel'!A1", "Fuel") -> Fuel | D18: Custom fertiliser blends
A19: =HYPERLINK("#'Input - Electricity'!A1", "Electricity") -> Electricity | D19: Custom blend name | E19: Amount applied (kg / ha) | F19: Application area (ha) | G19: Total applied (kg) | H19: Ingredient 1 (select) | I19: Ingredient 1 percent | J19: Ingredient 2 | K19: Ingredient 2 percent | L19: Ingredient 3 | M19: Ingredient 3 percent | N19: Ingredient 4 | O19: Ingredient 4 percent | P19: N application rate (kg/ha) | Q19: Urea source (Select) | R19: Ammonia source (select)
A20: =HYPERLINK("#'Input - Farm Inputs'!A1", "Farm Inputs") -> Farm Inputs | D20: My first custom blend | E20: 100 | F20: =X_Cell_Fertiliser_AreaUnderCropping -> 1000 | G20: =Table_Input_InorganicFertiliser_Custom[[#This Row],[Amount applied (kg / ha)]]*Table_Input_InorganicFertiliser_Custom[[#This Row],[Application area (ha)]] -> 100000 | H20: Calcium nitrate | I20: 0.5 | J20: Zinc - Generic | K20: 0.2 | L20: Potassium - Generic | M20: 0.2 | N20: Sulfur - Generic | O20: 0.1 | P20: =Table_Input_InorganicFertiliser_Custom[[#This Row],[Amount applied (kg / ha)]]* (IFERROR((_xlfn.XLOOKUP(Table_Input_InorganicFertiliser_Custom[[#This Row],[Ingredient 1 (select)]], Table_Fertiliser_ChemicalCompounds[Fertiliser type f],Table_Fertiliser_ChemicalCompounds[FNinorganic f])*Table_Input_InorganicFertiliser_Custom[[#This Row],[Ingredient 1 percent]]), 0) + IFERROR((_xlfn.XLOOKUP(Table_Input_InorganicFertiliser_Custom[[#This Row],[Ingredient 2]], Table_Fertiliser_ChemicalCompounds[Fertiliser type f],Table_Fertiliser_ChemicalCompounds[FNinorganic f])*Table_Input_InorganicFertiliser_Custom[[#This Row],[Ingredient 2 percent]]), 0) + IFERROR((_xlfn.XLOOKUP(Table_Input_InorganicFertiliser_Custom[[#This Row],[Ingredient 3]], Table_Fertiliser_ChemicalCompounds[Fertiliser type f],Table_Fertiliser_ChemicalCompounds[FNinorganic f])*Table_Input_InorganicFertiliser_Custom[[#This Row],[Ingredient 3 percent]]), 0) + IFERROR((_xlfn.XLOOKUP(Table_Input_InorganicFertiliser_Custom[[#This Row],[Ingredient 4]], Table_Fertiliser_ChemicalCompounds[Fertiliser type f],Table_Fertiliser_ChemicalCompounds[FNinorganic f])*Table_Input_InorganicFertiliser_Custom[[#This Row],[Ingredient 4 percent]]), 0) ) -> 7.75
A21: =HYPERLINK("#'Input - Freight'!A1", "Freight") -> Freight | D21: My second custom blend | E21: 100 | F21: =X_Cell_Fertiliser_AreaUnderCropping -> 1000 | G21: =Table_Input_InorganicFertiliser_Custom[[#This Row],[Amount applied (kg / ha)]]*Table_Input_InorganicFertiliser_Custom[[#This Row],[Application area (ha)]] -> 100000 | H21: Urea | I21: 1 | P21: =Table_Input_InorganicFertiliser_Custom[[#This Row],[Amount applied (kg / ha)]]* (IFERROR((_xlfn.XLOOKUP(Table_Input_InorganicFertiliser_Custom[[#This Row],[Ingredient 1 (select)]], Table_Fertiliser_ChemicalCompounds[Fertiliser type f],Table_Fertiliser_ChemicalCompounds[FNinorganic f])*Table_Input_InorganicFertiliser_Custom[[#This Row],[Ingredient 1 percent]]), 0) + IFERROR((_xlfn.XLOOKUP(Table_Input_InorganicFertiliser_Custom[[#This Row],[Ingredient 2]], Table_Fertiliser_ChemicalCompounds[Fertiliser type f],Table_Fertiliser_ChemicalCompounds[FNinorganic f])*Table_Input_InorganicFertiliser_Custom[[#This Row],[Ingredient 2 percent]]), 0) + IFERROR((_xlfn.XLOOKUP(Table_Input_InorganicFertiliser_Custom[[#This Row],[Ingredient 3]], Table_Fertiliser_ChemicalCompounds[Fertiliser type f],Table_Fertiliser_ChemicalCompounds[FNinorganic f])*Table_Input_InorganicFertiliser_Custom[[#This Row],[Ingredient 3 percent]]), 0) + IFERROR((_xlfn.XLOOKUP(Table_Input_InorganicFertiliser_Custom[[#This Row],[Ingredient 4]], Table_Fertiliser_ChemicalCompounds[Fertiliser type f],Table_Fertiliser_ChemicalCompounds[FNinorganic f])*Table_Input_InorganicFertiliser_Custom[[#This Row],[Ingredient 4 percent]]), 0) ) -> 46
A22: =HYPERLINK("#'Input - Manure sent off-site'!A1", "Manure sent off-site") -> Manure sent off-site | D22: My third custom blend | E22: 100 | F22: =X_Cell_Fertiliser_AreaUnderCropping -> 1000 | G22: =Table_Input_InorganicFertiliser_Custom[[#This Row],[Amount applied (kg / ha)]]*Table_Input_InorganicFertiliser_Custom[[#This Row],[Application area (ha)]] -> 100000 | H22: Ammonia | I22: 0.5 | P22: =Table_Input_InorganicFertiliser_Custom[[#This Row],[Amount applied (kg / ha)]]* (IFERROR((_xlfn.XLOOKUP(Table_Input_InorganicFertiliser_Custom[[#This Row],[Ingredient 1 (select)]], Table_Fertiliser_ChemicalCompounds[Fertiliser type f],Table_Fertiliser_ChemicalCompounds[FNinorganic f])*Table_Input_InorganicFertiliser_Custom[[#This Row],[Ingredient 1 percent]]), 0) + IFERROR((_xlfn.XLOOKUP(Table_Input_InorganicFertiliser_Custom[[#This Row],[Ingredient 2]], Table_Fertiliser_ChemicalCompounds[Fertiliser type f],Table_Fertiliser_ChemicalCompounds[FNinorganic f])*Table_Input_InorganicFertiliser_Custom[[#This Row],[Ingredient 2 percent]]), 0) + IFERROR((_xlfn.XLOOKUP(Table_Input_InorganicFertiliser_Custom[[#This Row],[Ingredient 3]], Table_Fertiliser_ChemicalCompounds[Fertiliser type f],Table_Fertiliser_ChemicalCompounds[FNinorganic f])*Table_Input_InorganicFertiliser_Custom[[#This Row],[Ingredient 3 percent]]), 0) + IFERROR((_xlfn.XLOOKUP(Table_Input_InorganicFertiliser_Custom[[#This Row],[Ingredient 4]], Table_Fertiliser_ChemicalCompounds[Fertiliser type f],Table_Fertiliser_ChemicalCompounds[FNinorganic f])*Table_Input_InorganicFertiliser_Custom[[#This Row],[Ingredient 4 percent]]), 0) ) -> 41.175
A23: =HYPERLINK("#'Input - Solid waste'!A1", "Solid waste") -> Solid waste
A24: =HYPERLINK("#'Input - Data quality'!A1", "Data quality") -> Data quality | D24: Soil ameliorants (lime)
D26: 💡 You can add more rows to the table by right-clicking on the table and selecting "Insert > Table rows above/below".
A27: CALCULATIONS | D27: 💡 'Lime' refers to calcium carbonate - CaCO3. 'Dolomite' refers to calcium magnesium carbonate - CaMg(CO3)2
A28: =HYPERLINK("#'5.1.1.1-2 Inorganic fert N2O'!A1", "5.1.1.1-2 Inorganic fert N2O") -> 5.1.1.1-2 Inorganic fert N2O | D28: 💡The application area is the same as the area under pasture / cropping by default. You can edit it if the application area is different.
A29: =HYPERLINK("#'5.1.1.3-4 Inorganic fert CO2'!A1", "5.1.1.3-4 Inorganic fert CO2") -> 5.1.1.3-4 Inorganic fert CO2 | D29: =IF(MAX(Table_Input_Lime[Total]) > 1, "There can not be more than 100% ingredients in a product. Check the table below.", "")
A30: =HYPERLINK("#'5.2.1.1-2 Organic Fert N2O'!A1", "5.2.1.1-2 Organic fert N2O") -> 5.2.1.1-2 Organic fert N2O | D30: Product | E30: Amount applied (t/hectare) | F30: Application area (ha) | G30: Total amount applied (t) | H30: Percent Lime CaCO3 | I30: Percent Dolomite CaMg(CO3)2 | J30: Percent Gypsum | K30: Total
A31: =HYPERLINK("#'5.3.1.1-2 Lime CO2'!A1", "5.3.1.1-2 Lime CO2") -> 5.3.1.1-2 Lime CO2 | D31: Lime product 1 | E31: 1 | F31: =X_Cell_Fertiliser_AreaUnderCropping -> 1000 | G31: =IFERROR(Table_Input_Lime[[#This Row],[Amount applied (t/hectare)]]*Table_Input_Lime[[#This Row],[Application area (ha)]], 0) -> 1000 | H31: 0.8 | I31: 0.1 | J31: 0.1 | K31: =SUM(Table_Input_Lime[[#This Row],[Percent Lime CaCO3]:[Percent Gypsum]]) -> 1
A32: =HYPERLINK("#'5.4.1.1-4 Atmos deposition'!A1", "5.4.1.1-4 Atmos. deposition") -> 5.4.1.1-4 Atmos. deposition | D32: Lime product 2 | E32: 1 | F32: =X_Cell_Fertiliser_AreaUnderCropping -> 1000 | G32: =IFERROR(Table_Input_Lime[[#This Row],[Amount applied (t/hectare)]]*Table_Input_Lime[[#This Row],[Application area (ha)]], 0) -> 1000 | H32: 1 | K32: =SUM(Table_Input_Lime[[#This Row],[Percent Lime CaCO3]:[Percent Gypsum]]) -> 1
A33: =HYPERLINK("#'5.5.1.1-2 Leaching and runoff'!A1", "5.5.1.1-2 Leaching & runoff") -> 5.5.1.1-2 Leaching & runoff | D33: Lime product 3 | E33: 1 | F33: =X_Cell_Fertiliser_AreaUnderCropping -> 1000 | G33: =IFERROR(Table_Input_Lime[[#This Row],[Amount applied (t/hectare)]]*Table_Input_Lime[[#This Row],[Application area (ha)]], 0) -> 1000 | H33: 0 | J33: 1 | K33: =SUM(Table_Input_Lime[[#This Row],[Percent Lime CaCO3]:[Percent Gypsum]]) -> 1
A34: =HYPERLINK("#'6.2.1.1-2 Pasture residue N2O'!A1", "6.2.1.1-2 Pasture residue N2O") -> 6.2.1.1-2 Pasture residue N2O
A35: =HYPERLINK("#'6.3.1.1-2 Leach runoff pasture'!A1", "6.3.1.1-2 Leach & runoff (pasture)") -> 6.3.1.1-2 Leach & runoff (pasture)
A36: =HYPERLINK("#'8.1.1.1-2 Transport fuel'!A1", "8.1.1.1-2 Transport fuel") -> 8.1.1.1-2 Transport fuel | D36: Organic fertiliser applied
A37: =HYPERLINK("#'8.2.1.1-2 Stationary fuel'!A1", "8.2.1.1-2 Stationary fuel") -> 8.2.1.1-2 Stationary fuel
A38: =HYPERLINK("#'14.1.1-2 Purchased electricity'!A1", "14.1.1-2 Purchased electricity") -> 14.1.1-2 Purchased electricity | D38: 💡 You can add more rows to the table by right-clicking on the table and selecting "Insert > Table rows above/below".
A39: =HYPERLINK("#'15 Scope 3'!A1", "15 Scope 3") -> 15 Scope 3 | D39: 💡The application area is the same as the area under pasture / cropping by default. You can edit it if the application area is different.
A40: =HYPERLINK("#'Calcs - Manure sent off-site'!A1", "Calcs - Manure sent off-site") -> Calcs - Manure sent off-site
A41: =HYPERLINK("#'4.3.1.1-2 Methane'!A1", "4.3.1.1-2 Methane") -> 4.3.1.1-2 Methane | D41: Organic fertiliser type (select) | E41: Percentage of N in fertiliser | F41: Amount applied (kg/hectare) | G41: Amount N applied (kg/hectare) | H41: Application area (ha) | I41: Total organic fertliser applied | J41: Total nitrogen applied (kg)
A42: =HYPERLINK("#'4.3.1.3-4 Direct N20'!A1", "4.3.1.3-4 Direct N20") -> 4.3.1.3-4 Direct N20 | D42: Manure - Other | E42: 0.3 | F42: 10 | G42: =Table_Input_OrganicFertiliser[[#This Row],[Amount applied (kg/hectare)]]*Table_Input_OrganicFertiliser[[#This Row],[Percentage of N in fertiliser]] -> 3 | H42: =X_Cell_Fertiliser_AreaUnderCropping -> 1000 | I42: =Table_Input_OrganicFertiliser[[#This Row],[Amount applied (kg/hectare)]]*Table_Input_OrganicFertiliser[[#This Row],[Application area (ha)]] -> 10000 | J42: =IFERROR(Table_Input_OrganicFertiliser[[#This Row],[Amount N applied (kg/hectare)]]*Table_Input_OrganicFertiliser[[#This Row],[Application area (ha)]], 0) -> 3000
A43: =HYPERLINK("#'4.3.1.5 Atmos deposition'!A1", "4.3.1.5 Atmos deposition") -> 4.3.1.5 Atmos deposition | D43: Manure - Poultry | E43: 0.25 | F43: 10 | G43: =Table_Input_OrganicFertiliser[[#This Row],[Amount applied (kg/hectare)]]*Table_Input_OrganicFertiliser[[#This Row],[Percentage of N in fertiliser]] -> 2.5 | H43: =X_Cell_Fertiliser_AreaUnderCropping -> 1000 | I43: =Table_Input_OrganicFertiliser[[#This Row],[Amount applied (kg/hectare)]]*Table_Input_OrganicFertiliser[[#This Row],[Application area (ha)]] -> 10000 | J43: =IFERROR(Table_Input_OrganicFertiliser[[#This Row],[Amount N applied (kg/hectare)]]*Table_Input_OrganicFertiliser[[#This Row],[Application area (ha)]], 0) -> 2500
A44: =HYPERLINK("#'4.3.1.6-7 Leaching and runoff'!A1", "4.3.1.6-7 Leaching and runoff") -> 4.3.1.6-7 Leaching and runoff | D44: Other organic fertiliser | E44: 0.16 | F44: 10 | G44: =Table_Input_OrganicFertiliser[[#This Row],[Amount applied (kg/hectare)]]*Table_Input_OrganicFertiliser[[#This Row],[Percentage of N in fertiliser]] -> 1.6 | H44: =X_Cell_Fertiliser_AreaUnderCropping -> 1000 | I44: =Table_Input_OrganicFertiliser[[#This Row],[Amount applied (kg/hectare)]]*Table_Input_OrganicFertiliser[[#This Row],[Application area (ha)]] -> 10000 | J44: =IFERROR(Table_Input_OrganicFertiliser[[#This Row],[Amount N applied (kg/hectare)]]*Table_Input_OrganicFertiliser[[#This Row],[Application area (ha)]], 0) -> 1600
A45: =HYPERLINK("#'4.3.1.8 Manure applied to soils'!A1", "4.3.1.8 Manure applied to soils") -> 4.3.1.8 Manure applied to soils
A46: =HYPERLINK("#'4.3.1.9 Soil direct N2O'!A1", "4.3.1.9 Soil direct N2O") -> 4.3.1.9 Soil direct N2O
A47: =HYPERLINK("#'4.3.1.10-11 Soil Atmos Dep'!A1", "4.3.1.10-11 Soil Atmos Dep") -> 4.3.1.10-11 Soil Atmos Dep
A48: =HYPERLINK("#'4.3.1.12-13 Soil leach runoff'!A1", "4.3.1.12-13 Soil leach runoff") -> 4.3.1.12-13 Soil leach runoff
A49: =HYPERLINK("#'3.3.1.1-2 Enteric Methane'!A1", "3.3.1.1-2 Enteric Methane") -> 3.3.1.1-2 Enteric Methane
A50: =HYPERLINK("#'10.1.1-2 Solid waste treatment'!A1", "10.1.1-2 Solid waste treatment") -> 10.1.1-2 Solid waste treatment
A53: APPENDICES
A54: =HYPERLINK("#'Constants - Dairy'!A1", "Constants - Dairy") -> Constants - Dairy
A55: =HYPERLINK("#'Constants - Ag Residue'!A1", "Constants - Ag residue") -> Constants - Ag residue
A56: =HYPERLINK("#'Constants - Common Livestock'!A1", "Constants - Common Livestock") -> Constants - Common Livestock
A57: =HYPERLINK("#'Constants - Electricity'!A1", "Constants - Electricity") -> Constants - Electricity
A58: =HYPERLINK("#'Constants - Fertiliser'!A1", "Constants - Fertiliser") -> Constants - Fertiliser
A59: =HYPERLINK("#'Constants - Fuel'!A1", "Constants - Fuel") -> Constants - Fuel
A60: =HYPERLINK("#'Constants - Scope 3'!A1", "Constants - Scope 3") -> Constants - Scope 3
A61: =HYPERLINK("#'Constants - Common'!A1", "Constants - Common") -> Constants - Common
A62: =HYPERLINK("#'Acknowledgements'!A1", "Acknowledgements") -> Acknowledgements
A63: =HYPERLINK("#'Constants - Solid Waste'!A1", "Constants - Solid Waste") -> Constants - Solid Waste

Sheet Input - Fuel
A1: #VALUE! | C1: Input - Fuel
A3: =HYPERLINK("#'Home'!A1", "Home") -> Home
A4: =HYPERLINK("#'Overview'!A1", "Overview") -> Overview
A5: =HYPERLINK("#'Results'!A1", "Results") -> Results | D5: Fuel purchases and consumption
D7: A 'Metropolitan' location is:
A8: INPUTS | D8: ● On or east of the dividing range in NSW (including Canberra and Queanbeyan)
A9: =HYPERLINK("#'Input - Enterprise'!A1", "Enterprise") -> Enterprise | D9: ● In Melbourne, Brisbane, Adelaide or Perth
A10: =HYPERLINK("#'Input - Site'!A1", "Site") -> Site
A11: =HYPERLINK("#'Input - Dairy'!A1", "Dairy") -> Dairy | D11: Is the property in a Metropolitan location? | E11: Metro | F11: ← Please select
A12: =HYPERLINK("#'Input - Dairy (Enteric)'!A1", "Dairy (Enteric)") -> Dairy (Enteric)
A13: =HYPERLINK("#'Input - Livestock sales'!A1", "Livestock sales") -> Livestock sales | D13: 💡 You can add more rows to the table by right-clicking on the table and selecting "Insert > Table rows above/below"
A14: =HYPERLINK("#'Input - Dairy cattle purchases'!A1", "Dairy cattle purchases") -> Dairy cattle purchases | D14: 💡 'Percent consumed" is 100% by default. If you purchased more fuel than was consumed you can edit this field.
A15: =HYPERLINK("#'Input - Pasture'!A1", "Pasture") -> Pasture
A16: =HYPERLINK("#'Input - Fert Prod System'!A1", "Fert Prod System") -> Fert Prod System | D16: Fuel use (select) | E16: Fuel type (select) | F16: Amount purchased | G16: Amount unit | H16: Percent consumed | I16: Amount consumed | J16: Amount consumed unit
A17: =HYPERLINK("#'Input - Fertiliser'!A1", "Fertiliser") -> Fertiliser | D17: Power standalone machinery or heating | E17: Town gas in GJ | F17: 100 | G17: {=Common_InputFunctions.Utility_LookupValueInTable(Table_Input_Fuel[[#This Row],[Fuel type (select)]],Table_FuelTypes_Units[Fuel type], Table_FuelTypes_Units[Input Unit])} -> GJ | H17: =1 -> 1 | I17: =Table_Input_Fuel[[#This Row],[Amount purchased]]*Table_Input_Fuel[[#This Row],[Percent consumed]]*IF(Table_Input_Fuel[[#This Row],[Amount unit]]="L", 10^-3, 1) -> 100 | J17: {=Common_InputFunctions.Utility_LookupValueInTable(Table_Input_Fuel[[#This Row],[Fuel type (select)]],Table_FuelTypes_Units[Fuel type], Table_FuelTypes_Units[Unit])} -> GJ
A18: =HYPERLINK("#'Input - Fuel'!A1", "Fuel") -> Fuel | D18: Power standalone machinery or heating | E18: Petrol | F18: 10000 | G18: {=Common_InputFunctions.Utility_LookupValueInTable(Table_Input_Fuel[[#This Row],[Fuel type (select)]],Table_FuelTypes_Units[Fuel type], Table_FuelTypes_Units[Input Unit])} -> L | H18: =1 -> 1 | I18: =Table_Input_Fuel[[#This Row],[Amount purchased]]*Table_Input_Fuel[[#This Row],[Percent consumed]]*IF(Table_Input_Fuel[[#This Row],[Amount unit]]="L", 10^-3, 1) -> 10 | J18: {=Common_InputFunctions.Utility_LookupValueInTable(Table_Input_Fuel[[#This Row],[Fuel type (select)]],Table_FuelTypes_Units[Fuel type], Table_FuelTypes_Units[Unit])} -> kL
A19: =HYPERLINK("#'Input - Electricity'!A1", "Electricity") -> Electricity | D19: Cars and light commercial vehicles | E19: Diesel | F19: 10000 | G19: {=Common_InputFunctions.Utility_LookupValueInTable(Table_Input_Fuel[[#This Row],[Fuel type (select)]],Table_FuelTypes_Units[Fuel type], Table_FuelTypes_Units[Input Unit])} -> L | H19: =1 -> 1 | I19: =Table_Input_Fuel[[#This Row],[Amount purchased]]*Table_Input_Fuel[[#This Row],[Percent consumed]]*IF(Table_Input_Fuel[[#This Row],[Amount unit]]="L", 10^-3, 1) -> 10 | J19: {=Common_InputFunctions.Utility_LookupValueInTable(Table_Input_Fuel[[#This Row],[Fuel type (select)]],Table_FuelTypes_Units[Fuel type], Table_FuelTypes_Units[Unit])} -> kL
A20: =HYPERLINK("#'Input - Farm Inputs'!A1", "Farm Inputs") -> Farm Inputs | D20: Off-road Agriculture and forestry equipment | E20: Diesel | F20: 10000 | G20: {=Common_InputFunctions.Utility_LookupValueInTable(Table_Input_Fuel[[#This Row],[Fuel type (select)]],Table_FuelTypes_Units[Fuel type], Table_FuelTypes_Units[Input Unit])} -> L | H20: =1 -> 1 | I20: =Table_Input_Fuel[[#This Row],[Amount purchased]]*Table_Input_Fuel[[#This Row],[Percent consumed]]*IF(Table_Input_Fuel[[#This Row],[Amount unit]]="L", 10^-3, 1) -> 10 | J20: {=Common_InputFunctions.Utility_LookupValueInTable(Table_Input_Fuel[[#This Row],[Fuel type (select)]],Table_FuelTypes_Units[Fuel type], Table_FuelTypes_Units[Unit])} -> kL
A21: =HYPERLINK("#'Input - Freight'!A1", "Freight") -> Freight | D21: Vessels | E21: Fuel oil | F21: 10000 | G21: {=Common_InputFunctions.Utility_LookupValueInTable(Table_Input_Fuel[[#This Row],[Fuel type (select)]],Table_FuelTypes_Units[Fuel type], Table_FuelTypes_Units[Input Unit])} -> L | H21: =1 -> 1 | I21: =Table_Input_Fuel[[#This Row],[Amount purchased]]*Table_Input_Fuel[[#This Row],[Percent consumed]]*IF(Table_Input_Fuel[[#This Row],[Amount unit]]="L", 10^-3, 1) -> 10 | J21: {=Common_InputFunctions.Utility_LookupValueInTable(Table_Input_Fuel[[#This Row],[Fuel type (select)]],Table_FuelTypes_Units[Fuel type], Table_FuelTypes_Units[Unit])} -> kL
A22: =HYPERLINK("#'Input - Manure sent off-site'!A1", "Manure sent off-site") -> Manure sent off-site
A23: =HYPERLINK("#'Input - Solid waste'!A1", "Solid waste") -> Solid waste
A24: =HYPERLINK("#'Input - Data quality'!A1", "Data quality") -> Data quality
A27: CALCULATIONS
A28: =HYPERLINK("#'5.1.1.1-2 Inorganic fert N2O'!A1", "5.1.1.1-2 Inorganic fert N2O") -> 5.1.1.1-2 Inorganic fert N2O
A29: =HYPERLINK("#'5.1.1.3-4 Inorganic fert CO2'!A1", "5.1.1.3-4 Inorganic fert CO2") -> 5.1.1.3-4 Inorganic fert CO2
A30: =HYPERLINK("#'5.2.1.1-2 Organic Fert N2O'!A1", "5.2.1.1-2 Organic fert N2O") -> 5.2.1.1-2 Organic fert N2O
A31: =HYPERLINK("#'5.3.1.1-2 Lime CO2'!A1", "5.3.1.1-2 Lime CO2") -> 5.3.1.1-2 Lime CO2
A32: =HYPERLINK("#'5.4.1.1-4 Atmos deposition'!A1", "5.4.1.1-4 Atmos. deposition") -> 5.4.1.1-4 Atmos. deposition
A33: =HYPERLINK("#'5.5.1.1-2 Leaching and runoff'!A1", "5.5.1.1-2 Leaching & runoff") -> 5.5.1.1-2 Leaching & runoff
A34: =HYPERLINK("#'6.2.1.1-2 Pasture residue N2O'!A1", "6.2.1.1-2 Pasture residue N2O") -> 6.2.1.1-2 Pasture residue N2O
A35: =HYPERLINK("#'6.3.1.1-2 Leach runoff pasture'!A1", "6.3.1.1-2 Leach & runoff (pasture)") -> 6.3.1.1-2 Leach & runoff (pasture)
A36: =HYPERLINK("#'8.1.1.1-2 Transport fuel'!A1", "8.1.1.1-2 Transport fuel") -> 8.1.1.1-2 Transport fuel
A37: =HYPERLINK("#'8.2.1.1-2 Stationary fuel'!A1", "8.2.1.1-2 Stationary fuel") -> 8.2.1.1-2 Stationary fuel
A38: =HYPERLINK("#'14.1.1-2 Purchased electricity'!A1", "14.1.1-2 Purchased electricity") -> 14.1.1-2 Purchased electricity
A39: =HYPERLINK("#'15 Scope 3'!A1", "15 Scope 3") -> 15 Scope 3
A40: =HYPERLINK("#'Calcs - Manure sent off-site'!A1", "Calcs - Manure sent off-site") -> Calcs - Manure sent off-site
A41: =HYPERLINK("#'4.3.1.1-2 Methane'!A1", "4.3.1.1-2 Methane") -> 4.3.1.1-2 Methane
A42: =HYPERLINK("#'4.3.1.3-4 Direct N20'!A1", "4.3.1.3-4 Direct N20") -> 4.3.1.3-4 Direct N20
A43: =HYPERLINK("#'4.3.1.5 Atmos deposition'!A1", "4.3.1.5 Atmos deposition") -> 4.3.1.5 Atmos deposition
A44: =HYPERLINK("#'4.3.1.6-7 Leaching and runoff'!A1", "4.3.1.6-7 Leaching and runoff") -> 4.3.1.6-7 Leaching and runoff
A45: =HYPERLINK("#'4.3.1.8 Manure applied to soils'!A1", "4.3.1.8 Manure applied to soils") -> 4.3.1.8 Manure applied to soils
A46: =HYPERLINK("#'4.3.1.9 Soil direct N2O'!A1", "4.3.1.9 Soil direct N2O") -> 4.3.1.9 Soil direct N2O
A47: =HYPERLINK("#'4.3.1.10-11 Soil Atmos Dep'!A1", "4.3.1.10-11 Soil Atmos Dep") -> 4.3.1.10-11 Soil Atmos Dep
A48: =HYPERLINK("#'4.3.1.12-13 Soil leach runoff'!A1", "4.3.1.12-13 Soil leach runoff") -> 4.3.1.12-13 Soil leach runoff
A49: =HYPERLINK("#'3.3.1.1-2 Enteric Methane'!A1", "3.3.1.1-2 Enteric Methane") -> 3.3.1.1-2 Enteric Methane
A50: =HYPERLINK("#'10.1.1-2 Solid waste treatment'!A1", "10.1.1-2 Solid waste treatment") -> 10.1.1-2 Solid waste treatment
A53: APPENDICES
A54: =HYPERLINK("#'Constants - Dairy'!A1", "Constants - Dairy") -> Constants - Dairy
A55: =HYPERLINK("#'Constants - Ag Residue'!A1", "Constants - Ag residue") -> Constants - Ag residue
A56: =HYPERLINK("#'Constants - Common Livestock'!A1", "Constants - Common Livestock") -> Constants - Common Livestock
A57: =HYPERLINK("#'Constants - Electricity'!A1", "Constants - Electricity") -> Constants - Electricity
A58: =HYPERLINK("#'Constants - Fertiliser'!A1", "Constants - Fertiliser") -> Constants - Fertiliser
A59: =HYPERLINK("#'Constants - Fuel'!A1", "Constants - Fuel") -> Constants - Fuel
A60: =HYPERLINK("#'Constants - Scope 3'!A1", "Constants - Scope 3") -> Constants - Scope 3
A61: =HYPERLINK("#'Constants - Common'!A1", "Constants - Common") -> Constants - Common
A62: =HYPERLINK("#'Acknowledgements'!A1", "Acknowledgements") -> Acknowledgements
A63: =HYPERLINK("#'Constants - Solid Waste'!A1", "Constants - Solid Waste") -> Constants - Solid Waste

Sheet Input - Electricity
A1: #VALUE! | C1: Input - Electricity
A3: =HYPERLINK("#'Home'!A1", "Home") -> Home
A4: =HYPERLINK("#'Overview'!A1", "Overview") -> Overview
A5: =HYPERLINK("#'Results'!A1", "Results") -> Results | D5: How do you want to calculate electricity emissions? | E5: Location-based (simpler) | F5: ← Please select
E6: =IF(X_Cell_Electricity_CalculationMethod="Location-based (simpler)", "Complete the fields in the Location-based section", "Complete the fields in the Market-based section") -> Complete the fields in the Location-based section
A8: INPUTS
A9: =HYPERLINK("#'Input - Enterprise'!A1", "Enterprise") -> Enterprise | D9: Option 1: Location-based electricity
A10: =HYPERLINK("#'Input - Site'!A1", "Site") -> Site
A11: =HYPERLINK("#'Input - Dairy'!A1", "Dairy") -> Dairy | D11: State grid electricity purchases
A12: =HYPERLINK("#'Input - Dairy (Enteric)'!A1", "Dairy (Enteric)") -> Dairy (Enteric)
A13: =HYPERLINK("#'Input - Livestock sales'!A1", "Livestock sales") -> Livestock sales | D13: 💡The grid you purchase electricity from is typically the same as the state and region the farm is in.
A14: =HYPERLINK("#'Input - Dairy cattle purchases'!A1", "Dairy cattle purchases") -> Dairy cattle purchases
A15: =HYPERLINK("#'Input - Pasture'!A1", "Pasture") -> Pasture | D15: Amount purchased in kWh | E15: 30000 | F15: kWh
A16: =HYPERLINK("#'Input - Fert Prod System'!A1", "Fert Prod System") -> Fert Prod System | D16: State and region your farm is in | E16: =IF(X_Cell_Site_State="Western Australia", X_Cell_Site_Region, X_Cell_Site_State) -> Western Australia - Outback (South)
A17: =HYPERLINK("#'Input - Fertiliser'!A1", "Fertiliser") -> Fertiliser | D17: Grid where electricity purchased from | E17: Western Australia - North Western Interconnected System (NWIS) | F17: ← Please select
A18: =HYPERLINK("#'Input - Fuel'!A1", "Fuel") -> Fuel
A19: =HYPERLINK("#'Input - Electricity'!A1", "Electricity") -> Electricity
A20: =HYPERLINK("#'Input - Farm Inputs'!A1", "Farm Inputs") -> Farm Inputs
A21: =HYPERLINK("#'Input - Freight'!A1", "Freight") -> Freight | D21: Option 2: Market-based electricity
A22: =HYPERLINK("#'Input - Manure sent off-site'!A1", "Manure sent off-site") -> Manure sent off-site | E22: =IF(E16="ACT", "", "ALERT: Your farm is not in the ACT, so the JRPP is not applicable") -> ALERT: Your farm is not in the ACT, so the JRPP is not applicable
A23: =HYPERLINK("#'Input - Solid waste'!A1", "Solid waste") -> Solid waste | D23: Electricity purchased in kWh (excluding GreenPower providers) | E23: 30000 | F23: kWh
A24: =HYPERLINK("#'Input - Data quality'!A1", "Data quality") -> Data quality | D24: Renewable Power Percentage | E24: 0.1 | F24: percent
D25: Jurisdictional renewable power percentage (ACT only) | E25: 0.1 | F25: percent
A27: CALCULATIONS | D27: Electricity purchased from an accredited GreenPower provider | E27: 10000 | F27: kWh
A28: =HYPERLINK("#'5.1.1.1-2 Inorganic fert N2O'!A1", "5.1.1.1-2 Inorganic fert N2O") -> 5.1.1.1-2 Inorganic fert N2O
A29: =HYPERLINK("#'5.1.1.3-4 Inorganic fert CO2'!A1", "5.1.1.3-4 Inorganic fert CO2") -> 5.1.1.3-4 Inorganic fert CO2 | D29: Start of reporting year | E29: =TEXT(X_Cell_Site_StartDate, "dd mmm yyyy") -> 01 Jan 2024
A30: =HYPERLINK("#'5.2.1.1-2 Organic Fert N2O'!A1", "5.2.1.1-2 Organic fert N2O") -> 5.2.1.1-2 Organic fert N2O | D30: End of reporting year | E30: =TEXT(X_Cell_Site_EndDate, "dd mmm yyyy") -> 31 Dec 2024
A31: =HYPERLINK("#'5.3.1.1-2 Lime CO2'!A1", "5.3.1.1-2 Lime CO2") -> 5.3.1.1-2 Lime CO2
A32: =HYPERLINK("#'5.4.1.1-4 Atmos deposition'!A1", "5.4.1.1-4 Atmos. deposition") -> 5.4.1.1-4 Atmos. deposition | D32: Voluntarily surrendered Renewable Energy Certificates (RECs)
A33: =HYPERLINK("#'5.5.1.1-2 Leaching and runoff'!A1", "5.5.1.1-2 Leaching & runoff") -> 5.5.1.1-2 Leaching & runoff
A34: =HYPERLINK("#'6.2.1.1-2 Pasture residue N2O'!A1", "6.2.1.1-2 Pasture residue N2O") -> 6.2.1.1-2 Pasture residue N2O | D34: 💡 You can add more rows to the table by right-clicking on the table and selecting "Insert > Table rows above/below"
A35: =HYPERLINK("#'6.3.1.1-2 Leach runoff pasture'!A1", "6.3.1.1-2 Leach & runoff (pasture)") -> 6.3.1.1-2 Leach & runoff (pasture)
A36: =HYPERLINK("#'8.1.1.1-2 Transport fuel'!A1", "8.1.1.1-2 Transport fuel") -> 8.1.1.1-2 Transport fuel | D36: Description | E36: Source (select) | F36: Generation date | G36: Number of certificates | H36: MWh | I36: Elegibility
A37: =HYPERLINK("#'8.2.1.1-2 Stationary fuel'!A1", "8.2.1.1-2 Stationary fuel") -> 8.2.1.1-2 Stationary fuel | D37: Dec 2020 certs | E37: Purchased certificate | F37: 44185 | G37: 12 | H37: =Table_Input_RECSurrendered[[#This Row],[Number of certificates]] -> 12 | I37: =IF(DATEDIF(Table_Input_RECSurrendered[[#This Row],[Generation date]],DATEVALUE($E$30),"M")>36,"Ineligible - older than 36 months","Elegible") -> Ineligible - older than 36 months
A38: =HYPERLINK("#'14.1.1-2 Purchased electricity'!A1", "14.1.1-2 Purchased electricity") -> 14.1.1-2 Purchased electricity | D38: Jan 2022 certs | E38: Issued for generated electricity | F38: 44575 | G38: 5 | H38: =Table_Input_RECSurrendered[[#This Row],[Number of certificates]] -> 5 | I38: =IF(DATEDIF(Table_Input_RECSurrendered[[#This Row],[Generation date]],DATEVALUE($E$30),"M")>36,"Ineligible - older than 36 months","Elegible") -> Elegible
A39: =HYPERLINK("#'15 Scope 3'!A1", "15 Scope 3") -> 15 Scope 3 | D39: 2024 certs | E39: Purchased certificate | F39: 45438 | G39: 5 | H39: =Table_Input_RECSurrendered[[#This Row],[Number of certificates]] -> 5 | I39: =IF(DATEDIF(Table_Input_RECSurrendered[[#This Row],[Generation date]],DATEVALUE($E$30),"M")>36,"Ineligible - older than 36 months","Elegible") -> Elegible
A40: =HYPERLINK("#'Calcs - Manure sent off-site'!A1", "Calcs - Manure sent off-site") -> Calcs - Manure sent off-site
A41: =HYPERLINK("#'4.3.1.1-2 Methane'!A1", "4.3.1.1-2 Methane") -> 4.3.1.1-2 Methane | D41: Total elegible voluntarily surrendered RECs | E41: =SUMIF(Table_Input_RECSurrendered[Elegibility], "Elegible", Table_Input_RECSurrendered[MWh]) -> 10 | F41: MWh
A42: =HYPERLINK("#'4.3.1.3-4 Direct N20'!A1", "4.3.1.3-4 Direct N20") -> 4.3.1.3-4 Direct N20
A43: =HYPERLINK("#'4.3.1.5 Atmos deposition'!A1", "4.3.1.5 Atmos deposition") -> 4.3.1.5 Atmos deposition | D43: Renewable Energy Certificates (RECs) for electricity produced on-site and consumed by the entity
A44: =HYPERLINK("#'4.3.1.6-7 Leaching and runoff'!A1", "4.3.1.6-7 Leaching and runoff") -> 4.3.1.6-7 Leaching and runoff
A45: =HYPERLINK("#'4.3.1.8 Manure applied to soils'!A1", "4.3.1.8 Manure applied to soils") -> 4.3.1.8 Manure applied to soils | D45: Description | E45: Source | F45: Generation date | G45: Number of certificates | H45: MWh | I45: Elegibility
A46: =HYPERLINK("#'4.3.1.9 Soil direct N2O'!A1", "4.3.1.9 Soil direct N2O") -> 4.3.1.9 Soil direct N2O | D46: May 2022 generated | E46: ="Issued for generated electricity" -> Issued for generated electricity | F46: 44697 | G46: 10 | H46: =Table_Input_RECConsumedByEntity[[#This Row],[Number of certificates]] -> 10 | I46: =IF(AND(Table_Input_RECConsumedByEntity[[#This Row],[Generation date]]>=DATEVALUE($E$29), Table_Input_RECConsumedByEntity[[#This Row],[Generation date]]<= DATEVALUE($E$30)), "Elegible", "Ineligible - outside reporting year") -> Ineligible - outside reporting year
A47: =HYPERLINK("#'4.3.1.10-11 Soil Atmos Dep'!A1", "4.3.1.10-11 Soil Atmos Dep") -> 4.3.1.10-11 Soil Atmos Dep | D47: Jul 24 certs generated | E47: ="Issued for generated electricity" -> Issued for generated electricity | F47: 45483 | G47: 4 | H47: =Table_Input_RECConsumedByEntity[[#This Row],[Number of certificates]] -> 4 | I47: =IF(AND(Table_Input_RECConsumedByEntity[[#This Row],[Generation date]]>=DATEVALUE($E$29), Table_Input_RECConsumedByEntity[[#This Row],[Generation date]]<= DATEVALUE($E$30)), "Elegible", "Ineligible - outside reporting year") -> Elegible
A48: =HYPERLINK("#'4.3.1.12-13 Soil leach runoff'!A1", "4.3.1.12-13 Soil leach runoff") -> 4.3.1.12-13 Soil leach runoff | D48: 45597 | E48: ="Issued for generated electricity" -> Issued for generated electricity | F48: 45607 | G48: 7 | H48: =Table_Input_RECConsumedByEntity[[#This Row],[Number of certificates]] -> 7 | I48: =IF(AND(Table_Input_RECConsumedByEntity[[#This Row],[Generation date]]>=DATEVALUE($E$29), Table_Input_RECConsumedByEntity[[#This Row],[Generation date]]<= DATEVALUE($E$30)), "Elegible", "Ineligible - outside reporting year") -> Elegible
A49: =HYPERLINK("#'3.3.1.1-2 Enteric Methane'!A1", "3.3.1.1-2 Enteric Methane") -> 3.3.1.1-2 Enteric Methane
A50: =HYPERLINK("#'10.1.1-2 Solid waste treatment'!A1", "10.1.1-2 Solid waste treatment") -> 10.1.1-2 Solid waste treatment | D50: Total elegible RECs for electricity produced on-site and consumed by entity | E50: =SUMIF(Table_Input_RECConsumedByEntity[Elegibility], "Elegible", Table_Input_RECConsumedByEntity[Number of certificates]) -> 11 | F50: MWh
A53: APPENDICES
A54: =HYPERLINK("#'Constants - Dairy'!A1", "Constants - Dairy") -> Constants - Dairy
A55: =HYPERLINK("#'Constants - Ag Residue'!A1", "Constants - Ag residue") -> Constants - Ag residue
A56: =HYPERLINK("#'Constants - Common Livestock'!A1", "Constants - Common Livestock") -> Constants - Common Livestock
A57: =HYPERLINK("#'Constants - Electricity'!A1", "Constants - Electricity") -> Constants - Electricity
A58: =HYPERLINK("#'Constants - Fertiliser'!A1", "Constants - Fertiliser") -> Constants - Fertiliser
A59: =HYPERLINK("#'Constants - Fuel'!A1", "Constants - Fuel") -> Constants - Fuel
A60: =HYPERLINK("#'Constants - Scope 3'!A1", "Constants - Scope 3") -> Constants - Scope 3
A61: =HYPERLINK("#'Constants - Common'!A1", "Constants - Common") -> Constants - Common
A62: =HYPERLINK("#'Acknowledgements'!A1", "Acknowledgements") -> Acknowledgements
A63: =HYPERLINK("#'Constants - Solid Waste'!A1", "Constants - Solid Waste") -> Constants - Solid Waste

Sheet Input - Farm Inputs
A1: #VALUE! | C1: Input - Farm inputs
A3: =HYPERLINK("#'Home'!A1", "Home") -> Home
A4: =HYPERLINK("#'Overview'!A1", "Overview") -> Overview
A5: =HYPERLINK("#'Results'!A1", "Results") -> Results | D5: Chemicals
D6: Pesticides
D7: 💡You can find specific product information in the Australian Government's 'PubCRIS' database search.
A8: INPUTS | D8: Click here to find instructions on how to use the PubCRIS database
A9: =HYPERLINK("#'Input - Enterprise'!A1", "Enterprise") -> Enterprise | K9: {=IF( SUMPRODUCT((Table_Input_Pesticides[Constituent unit (select)]="fraction of product")*(Table_Input_Pesticides[Active ingredient 1 amount]>1)*(Table_Input_Pesticides[Active ingredient 2 amount]<>""))>0, "Alert: If constituent unit is fraction of product, amount cannot exceed 1", IF( SUMPRODUCT((Table_Input_Pesticides[Constituent unit (select)]="grams/litre or grams/kg")*(Table_Input_Pesticides[Active ingredient 1 amount]<1)*(Table_Input_Pesticides[Active ingredient 2 amount]<>""))>0, "Alert: If constituent unit is grams/kg or litre, amount cannot be less than 1", "" ) )} | N9: {=IF( SUMPRODUCT((Table_Input_Pesticides[Constituent unit (select)]="fraction of product")*(Table_Input_Pesticides[Active ingredient 2 amount]>1)*(Table_Input_Pesticides[Active ingredient 2 amount]<>""))>0, "Alert: If constituent unit is fraction of product, amount cannot exceed 1", IF( SUMPRODUCT((Table_Input_Pesticides[Constituent unit (select)]="grams/litre or grams/kg")*(Table_Input_Pesticides[Active ingredient 2 amount]<1)*(Table_Input_Pesticides[Active ingredient 2 amount]<>""))>0, "Alert: If constituent unit is grams/kg or litre, amount cannot be less than 1", "" ) )} | Q9: {=IF( SUMPRODUCT((Table_Input_Pesticides[Constituent unit (select)]="fraction of product")*(Table_Input_Pesticides[Active ingredient 3 amount]>1)*(Table_Input_Pesticides[Active ingredient 3 amount]<>""))>0, "Alert: If constituent unit is fraction of product, amount cannot exceed 1", IF( SUMPRODUCT((Table_Input_Pesticides[Constituent unit (select)]="grams/litre or grams/kg")*(Table_Input_Pesticides[Active ingredient 3 amount]<1)*(Table_Input_Pesticides[Active ingredient 3 amount]<>""))>0, "Alert: If constituent unit is grams/kg or litre, amount cannot be less than 1", "" ) )}
A10: =HYPERLINK("#'Input - Site'!A1", "Site") -> Site | D10: Product name | E10: Amount applied per ha | F10: Application unit (select) | G10: Application area (ha) | H10: Total applied | I10: Constituent unit (select) | J10: Active ingredient 1 (select) | K10: Active ingredient 1 amount | L10: Total active ingredient 1 (kg) | M10: Active ingredient 2 (select) | N10: Active ingredient 2 amount | O10: Total active ingredient 2 (kg) | P10: Active ingredient 3 (select) | Q10: Active ingredient 3 amount | R10: Total active ingredient 3 (kg)
A11: =HYPERLINK("#'Input - Dairy'!A1", "Dairy") -> Dairy | D11: QA MCPA + Picloram SL Herbicide | E11: 10 | F11: kg / hectare | G11: 100 | H11: =Table_Input_Pesticides[[#This Row],[Amount applied per ha]]*Table_Input_Pesticides[[#This Row],[Application area (ha)]] -> 1000 | I11: grams/litre or grams/kg | J11: Pesticides (generic) | K11: 100 | L11: =Table_Input_Pesticides[[#This Row],[Total applied]]*Table_Input_Pesticides[[#This Row],[Active ingredient 1 amount]]*IF(Table_Input_Pesticides[[#This Row],[Constituent unit (select)]]="fraction of product", 1, 10^-3) -> 100 | M11: Pesticides (generic) | N11: 100 | O11: =Table_Input_Pesticides[[#This Row],[Total applied]]*Table_Input_Pesticides[[#This Row],[Active ingredient 2 amount]]*IF(Table_Input_Pesticides[[#This Row],[Constituent unit (select)]]="fraction of product", 1, 10^-3) -> 100 | P11: Glyphosate | Q11: 100 | R11: =Table_Input_Pesticides[[#This Row],[Total applied]]*Table_Input_Pesticides[[#This Row],[Active ingredient 3 amount]]*IF(Table_Input_Pesticides[[#This Row],[Constituent unit (select)]]="fraction of product", 1, 10^-3) -> 100
A12: =HYPERLINK("#'Input - Dairy (Enteric)'!A1", "Dairy (Enteric)") -> Dairy (Enteric) | D12: Heben Propiconazole 550EC Fungicide | E12: 10 | F12: litre / hectare | G12: 100 | H12: =Table_Input_Pesticides[[#This Row],[Amount applied per ha]]*Table_Input_Pesticides[[#This Row],[Application area (ha)]] -> 1000 | I12: grams/litre or grams/kg | J12: Pesticides (generic) | K12: 100 | L12: =Table_Input_Pesticides[[#This Row],[Total applied]]*Table_Input_Pesticides[[#This Row],[Active ingredient 1 amount]]*IF(Table_Input_Pesticides[[#This Row],[Constituent unit (select)]]="fraction of product", 1, 10^-3) -> 100 | M12: 2,4-D | N12: 100 | O12: =Table_Input_Pesticides[[#This Row],[Total applied]]*Table_Input_Pesticides[[#This Row],[Active ingredient 2 amount]]*IF(Table_Input_Pesticides[[#This Row],[Constituent unit (select)]]="fraction of product", 1, 10^-3) -> 100 | P12: Tribenuron methyl | Q12: 100 | R12: =Table_Input_Pesticides[[#This Row],[Total applied]]*Table_Input_Pesticides[[#This Row],[Active ingredient 3 amount]]*IF(Table_Input_Pesticides[[#This Row],[Constituent unit (select)]]="fraction of product", 1, 10^-3) -> 100
A13: =HYPERLINK("#'Input - Livestock sales'!A1", "Livestock sales") -> Livestock sales | D13: NovaGuard Boscalid 500 WG Fungicide | E13: 10 | F13: kg / hectare | G13: 100 | H13: =Table_Input_Pesticides[[#This Row],[Amount applied per ha]]*Table_Input_Pesticides[[#This Row],[Application area (ha)]] -> 1000 | I13: grams/litre or grams/kg | J13: Pesticides (generic) | K13: 100 | L13: =Table_Input_Pesticides[[#This Row],[Total applied]]*Table_Input_Pesticides[[#This Row],[Active ingredient 1 amount]]*IF(Table_Input_Pesticides[[#This Row],[Constituent unit (select)]]="fraction of product", 1, 10^-3) -> 100 | M13: Metolachlor | N13: 100 | O13: =Table_Input_Pesticides[[#This Row],[Total applied]]*Table_Input_Pesticides[[#This Row],[Active ingredient 2 amount]]*IF(Table_Input_Pesticides[[#This Row],[Constituent unit (select)]]="fraction of product", 1, 10^-3) -> 100 | P13: Trifluralin | Q13: 100 | R13: =Table_Input_Pesticides[[#This Row],[Total applied]]*Table_Input_Pesticides[[#This Row],[Active ingredient 3 amount]]*IF(Table_Input_Pesticides[[#This Row],[Constituent unit (select)]]="fraction of product", 1, 10^-3) -> 100
A14: =HYPERLINK("#'Input - Dairy cattle purchases'!A1", "Dairy cattle purchases") -> Dairy cattle purchases | H14: =Table_Input_Pesticides[[#This Row],[Amount applied per ha]]*Table_Input_Pesticides[[#This Row],[Application area (ha)]] -> 0 | L14: =Table_Input_Pesticides[[#This Row],[Total applied]]*Table_Input_Pesticides[[#This Row],[Active ingredient 1 amount]]*IF(Table_Input_Pesticides[[#This Row],[Constituent unit (select)]]="fraction of product", 1, 10^-3) -> 0 | O14: =Table_Input_Pesticides[[#This Row],[Total applied]]*Table_Input_Pesticides[[#This Row],[Active ingredient 2 amount]]*IF(Table_Input_Pesticides[[#This Row],[Constituent unit (select)]]="fraction of product", 1, 10^-3) -> 0 | R14: =Table_Input_Pesticides[[#This Row],[Total applied]]*Table_Input_Pesticides[[#This Row],[Active ingredient 3 amount]]*IF(Table_Input_Pesticides[[#This Row],[Constituent unit (select)]]="fraction of product", 1, 10^-3) -> 0
A15: =HYPERLINK("#'Input - Pasture'!A1", "Pasture") -> Pasture | H15: =Table_Input_Pesticides[[#This Row],[Amount applied per ha]]*Table_Input_Pesticides[[#This Row],[Application area (ha)]] -> 0 | L15: =Table_Input_Pesticides[[#This Row],[Total applied]]*Table_Input_Pesticides[[#This Row],[Active ingredient 1 amount]]*IF(Table_Input_Pesticides[[#This Row],[Constituent unit (select)]]="fraction of product", 1, 10^-3) -> 0 | O15: =Table_Input_Pesticides[[#This Row],[Total applied]]*Table_Input_Pesticides[[#This Row],[Active ingredient 2 amount]]*IF(Table_Input_Pesticides[[#This Row],[Constituent unit (select)]]="fraction of product", 1, 10^-3) -> 0 | R15: =Table_Input_Pesticides[[#This Row],[Total applied]]*Table_Input_Pesticides[[#This Row],[Active ingredient 3 amount]]*IF(Table_Input_Pesticides[[#This Row],[Constituent unit (select)]]="fraction of product", 1, 10^-3) -> 0
A16: =HYPERLINK("#'Input - Fert Prod System'!A1", "Fert Prod System") -> Fert Prod System | H16: =Table_Input_Pesticides[[#This Row],[Amount applied per ha]]*Table_Input_Pesticides[[#This Row],[Application area (ha)]] -> 0 | L16: =Table_Input_Pesticides[[#This Row],[Total applied]]*Table_Input_Pesticides[[#This Row],[Active ingredient 1 amount]]*IF(Table_Input_Pesticides[[#This Row],[Constituent unit (select)]]="fraction of product", 1, 10^-3) -> 0 | O16: =Table_Input_Pesticides[[#This Row],[Total applied]]*Table_Input_Pesticides[[#This Row],[Active ingredient 2 amount]]*IF(Table_Input_Pesticides[[#This Row],[Constituent unit (select)]]="fraction of product", 1, 10^-3) -> 0 | R16: =Table_Input_Pesticides[[#This Row],[Total applied]]*Table_Input_Pesticides[[#This Row],[Active ingredient 3 amount]]*IF(Table_Input_Pesticides[[#This Row],[Constituent unit (select)]]="fraction of product", 1, 10^-3) -> 0
A17: =HYPERLINK("#'Input - Fertiliser'!A1", "Fertiliser") -> Fertiliser | H17: =Table_Input_Pesticides[[#This Row],[Amount applied per ha]]*Table_Input_Pesticides[[#This Row],[Application area (ha)]] -> 0 | L17: =Table_Input_Pesticides[[#This Row],[Total applied]]*Table_Input_Pesticides[[#This Row],[Active ingredient 1 amount]]*IF(Table_Input_Pesticides[[#This Row],[Constituent unit (select)]]="fraction of product", 1, 10^-3) -> 0 | O17: =Table_Input_Pesticides[[#This Row],[Total applied]]*Table_Input_Pesticides[[#This Row],[Active ingredient 2 amount]]*IF(Table_Input_Pesticides[[#This Row],[Constituent unit (select)]]="fraction of product", 1, 10^-3) -> 0 | R17: =Table_Input_Pesticides[[#This Row],[Total applied]]*Table_Input_Pesticides[[#This Row],[Active ingredient 3 amount]]*IF(Table_Input_Pesticides[[#This Row],[Constituent unit (select)]]="fraction of product", 1, 10^-3) -> 0
A18: =HYPERLINK("#'Input - Fuel'!A1", "Fuel") -> Fuel | H18: =Table_Input_Pesticides[[#This Row],[Amount applied per ha]]*Table_Input_Pesticides[[#This Row],[Application area (ha)]] -> 0 | L18: =Table_Input_Pesticides[[#This Row],[Total applied]]*Table_Input_Pesticides[[#This Row],[Active ingredient 1 amount]]*IF(Table_Input_Pesticides[[#This Row],[Constituent unit (select)]]="fraction of product", 1, 10^-3) -> 0 | O18: =Table_Input_Pesticides[[#This Row],[Total applied]]*Table_Input_Pesticides[[#This Row],[Active ingredient 2 amount]]*IF(Table_Input_Pesticides[[#This Row],[Constituent unit (select)]]="fraction of product", 1, 10^-3) -> 0 | R18: =Table_Input_Pesticides[[#This Row],[Total applied]]*Table_Input_Pesticides[[#This Row],[Active ingredient 3 amount]]*IF(Table_Input_Pesticides[[#This Row],[Constituent unit (select)]]="fraction of product", 1, 10^-3) -> 0
A19: =HYPERLINK("#'Input - Electricity'!A1", "Electricity") -> Electricity | H19: =Table_Input_Pesticides[[#This Row],[Amount applied per ha]]*Table_Input_Pesticides[[#This Row],[Application area (ha)]] -> 0 | L19: =Table_Input_Pesticides[[#This Row],[Total applied]]*Table_Input_Pesticides[[#This Row],[Active ingredient 1 amount]]*IF(Table_Input_Pesticides[[#This Row],[Constituent unit (select)]]="fraction of product", 1, 10^-3) -> 0 | O19: =Table_Input_Pesticides[[#This Row],[Total applied]]*Table_Input_Pesticides[[#This Row],[Active ingredient 2 amount]]*IF(Table_Input_Pesticides[[#This Row],[Constituent unit (select)]]="fraction of product", 1, 10^-3) -> 0 | R19: =Table_Input_Pesticides[[#This Row],[Total applied]]*Table_Input_Pesticides[[#This Row],[Active ingredient 3 amount]]*IF(Table_Input_Pesticides[[#This Row],[Constituent unit (select)]]="fraction of product", 1, 10^-3) -> 0
