Workbook
Name AgResidue_Equations_FieldBurning.VEERG_6_4_1_1__1__MethaneEmissionsFromBurningOfCropResidues: _xlfn.LAMBDA(_xlpm.Mburnc,_xlpm.CCc,_xlpm.EFCH4,_xlpm.C_CH4, _xlpm.Mburnc * _xlpm.CCc * _xlpm.EFCH4 * _xlpm.C_CH4 * 10 ^ (-3))
Name AgResidue_Equations_FieldBurning.VEERG_6_4_1_1__1__MethaneEmissionsFromBurningOfCropResidues_FunctionName: _xlfn.LAMBDA("VEERG_6_4_1_1__1__MethaneEmissionsFromBurningOfCropResidues")
Name AgResidue_Equations_FieldBurning.VEERG_6_4_1_1__1__MethaneEmissionsFromBurningOfCropResidues_LatexEquation: _xlfn.LAMBDA("E_{CH4}=\sum_{c}(M_{burn,c}\times CC_{c}\times EF_{CH4}\times C_{CH4}\times 10^{-3})")
Name AgResidue_Equations_FieldBurning.VEERG_6_4_1_1__1__MethaneEmissionsFromBurningOfCropResidues_NIRReference: _xlfn.LAMBDA("")
Name AgResidue_Equations_FieldBurning.VEERG_6_4_1_1__1__MethaneEmissionsFromBurningOfCropResidues_Source: _xlfn.LAMBDA("VEERG 2026: 6.4.1.1, Equation (1)")
Name AgResidue_Equations_FieldBurning.VEERG_6_4_1_1__1__MethaneEmissionsFromBurningOfCropResidues_Title: _xlfn.LAMBDA("Methane emissions from the burning of crop residues")
Name AgResidue_Equations_FieldBurning.VEERG_6_4_1_1__1__MethaneEmissionsFromBurningOfCropResidues_Unit: _xlfn.LAMBDA("t CH4")
Name AgResidue_Equations_FieldBurning.VEERG_6_4_1_1__1__MethaneEmissionsFromBurningOfCropResidues_Variable: _xlfn.LAMBDA("ECH4")
Name AgResidue_Equations_FieldBurning.VEERG_6_4_1_1__2__NitrousOxideEmissionsFromBurningOfCropResidues: _xlfn.LAMBDA(_xlpm.Mburnc,_xlpm.NCAGc,_xlpm.EFN2O,_xlpm.CN2O, _xlpm.Mburnc * _xlpm.NCAGc * _xlpm.EFN2O * _xlpm.CN2O * 10 ^ (-3))
Name AgResidue_Equations_FieldBurning.VEERG_6_4_1_1__2__NitrousOxideEmissionsFromBurningOfCropResidues_FunctionName: _xlfn.LAMBDA("VEERG_6_4_1_1__2__NitrousOxideEmissionsFromBurningOfCropResidues")
Name AgResidue_Equations_FieldBurning.VEERG_6_4_1_1__2__NitrousOxideEmissionsFromBurningOfCropResidues_LatexEquation: _xlfn.LAMBDA("E_{N2O}=\sum_{c}(M_{burn,c}\times NC_{AGc}\times EF_{N2O}\times C_{N2O}\times 10^{-3})")
Name AgResidue_Equations_FieldBurning.VEERG_6_4_1_1__2__NitrousOxideEmissionsFromBurningOfCropResidues_NIRReference: _xlfn.LAMBDA("")
Name AgResidue_Equations_FieldBurning.VEERG_6_4_1_1__2__NitrousOxideEmissionsFromBurningOfCropResidues_Source: _xlfn.LAMBDA("VEERG 2026: 6.4.1.1, Equation (2)")
Name AgResidue_Equations_FieldBurning.VEERG_6_4_1_1__2__NitrousOxideEmissionsFromBurningOfCropResidues_Title: _xlfn.LAMBDA("Nitrous oxide emissions from the burning of crop residues")
Name AgResidue_Equations_FieldBurning.VEERG_6_4_1_1__2__NitrousOxideEmissionsFromBurningOfCropResidues_Unit: _xlfn.LAMBDA("t N2O")
Name AgResidue_Equations_FieldBurning.VEERG_6_4_1_1__2__NitrousOxideEmissionsFromBurningOfCropResidues_Variable: _xlfn.LAMBDA("EN2O")
Name AgResidue_Equations_FieldBurning.VEERG_6_4_1_1__3__MassOfCropResidueBurnt: _xlfn.LAMBDA(_xlpm.Pc,_xlpm.RAGc,_xlpm.Sc,_xlpm.DMc,_xlpm.Zc,_xlpm.Fc, _xlpm.Pc * _xlpm.RAGc * _xlpm.Sc * _xlpm.DMc * _xlpm.Zc * _xlpm.Fc)
Name AgResidue_Equations_FieldBurning.VEERG_6_4_1_1__3__MassOfCropResidueBurnt_FunctionName: _xlfn.LAMBDA("VEERG_6_4_1_1__3__MassOfCropResidueBurnt")
Name AgResidue_Equations_FieldBurning.VEERG_6_4_1_1__3__MassOfCropResidueBurnt_LatexEquation: _xlfn.LAMBDA("M_{burn,c}=P_{c}\times R_{AGc}\times S_{c}\times DM_{c}\times Z_{c}\times F_{c}")
Name AgResidue_Equations_FieldBurning.VEERG_6_4_1_1__3__MassOfCropResidueBurnt_NIRReference: _xlfn.LAMBDA("")
Name AgResidue_Equations_FieldBurning.VEERG_6_4_1_1__3__MassOfCropResidueBurnt_Source: _xlfn.LAMBDA("VEERG 2026: 6.4.1.1, Equation (3)")
Name AgResidue_Equations_FieldBurning.VEERG_6_4_1_1__3__MassOfCropResidueBurnt_Title: _xlfn.LAMBDA("Mass of residue of crop c burnt")
Name AgResidue_Equations_FieldBurning.VEERG_6_4_1_1__3__MassOfCropResidueBurnt_Unit: _xlfn.LAMBDA("kg")
Name AgResidue_Equations_FieldBurning.VEERG_6_4_1_1__3__MassOfCropResidueBurnt_Variable: _xlfn.LAMBDA("Mburnc")
Name AgResidues_Equations_CropResidues.VEERG_6_1_1_1__1__NitrousOxideEmissionsFromCropResidues: _xlfn.LAMBDA(_xlpm.Mc,_xlpm.EFNi,_xlpm.CgN2O, _xlpm.Mc * _xlpm.EFNi * _xlpm.CgN2O * 10 ^ (-3))
Name AgResidues_Equations_CropResidues.VEERG_6_1_1_1__1__NitrousOxideEmissionsFromCropResidues_FunctionName: _xlfn.LAMBDA("VEERG_6_1_1_1__1__NitrousOxideEmissionsFromCropResidues")
Name AgResidues_Equations_CropResidues.VEERG_6_1_1_1__1__NitrousOxideEmissionsFromCropResidues_LatexEquation: _xlfn.LAMBDA("E=\sum_{c}{M_{c}\times EF_{N}\times C_{g,N2O}\times 10^{-3}}")
Name AgResidues_Equations_CropResidues.VEERG_6_1_1_1__1__NitrousOxideEmissionsFromCropResidues_NIRReference: _xlfn.LAMBDA("")
Name AgResidues_Equations_CropResidues.VEERG_6_1_1_1__1__NitrousOxideEmissionsFromCropResidues_Source: _xlfn.LAMBDA("VEERG 2026: 6.1.1.1, Equation (1)")
Name AgResidues_Equations_CropResidues.VEERG_6_1_1_1__1__NitrousOxideEmissionsFromCropResidues_Title: _xlfn.LAMBDA("Nitrous oxide emissions from the return of crop residues across all crops c to the soil")
Name AgResidues_Equations_CropResidues.VEERG_6_1_1_1__1__NitrousOxideEmissionsFromCropResidues_Unit: _xlfn.LAMBDA("t N2O")
Name AgResidues_Equations_CropResidues.VEERG_6_1_1_1__1__NitrousOxideEmissionsFromCropResidues_Variable: _xlfn.LAMBDA("E")
Name AgResidues_Equations_CropResidues.VEERG_6_1_1_1__2__MassOfNitrogenInCropResidues_LatexEquation: _xlfn.LAMBDA("M_{c}=(P_{c}\times R_{AGc}\times(1-F_{c}-FFOD_{c})\times DM_{c}\times NC_{AGc})+(P_{c}\times R_{AGc}\times R_{BGc}\times DM_{c}\times NC_{BGc})")
Name AgResidues_Equations_CropResidues.VEERG_6_1_1_1__2__MassOfNitrogenInCropResidues_NIRReference: _xlfn.LAMBDA("")
Name AgResidues_Equations_CropResidues.VEERG_6_1_1_1__2__MassOfNitrogenInCropResidues_Source: _xlfn.LAMBDA("VEERG 2026: 6.1.1.1, Equation (2)")
Name AgResidues_Equations_CropResidues.VEERG_6_1_1_1__2__MassOfNitrogenInCropResidues_Title: _xlfn.LAMBDA("Mass of nitrogen in crop residues returned to the soil")
Name AgResidues_Equations_CropResidues.VEERG_6_1_1_1__2__MassOfNitrogenInCropResidues_Unit: _xlfn.LAMBDA("kg N")
Name AgResidues_Equations_CropResidues.VEERG_6_1_1_1__2__MassOfNitrogenInCropResidues_Variable: _xlfn.LAMBDA("Mc")
Name AgResidues_Equations_CropResidues.VEERG_6_1_1_2__1__FractionOfCropResidueRemovedBaled: _xlfn.LAMBDA(_xlpm.B,_xlpm.MB,_xlpm.Pc,_xlpm.RAGc, IFERROR((_xlpm.B * _xlpm.MB) / (_xlpm.Pc * _xlpm.RAGc), 0))
Name AgResidues_Equations_CropResidues.VEERG_6_1_1_2__1__FractionOfCropResidueRemovedBaled_LatexEquation: _xlfn.LAMBDA("FFOD_{c,baled}=\frac{B\times M_{B}}{P_{c}\times R_{AG,c}}")
Name AgResidues_Equations_CropResidues.VEERG_6_1_1_2__1__FractionOfCropResidueRemovedBaled_NIRReference: _xlfn.LAMBDA("")
Name AgResidues_Equations_CropResidues.VEERG_6_1_1_2__1__FractionOfCropResidueRemovedBaled_Source: _xlfn.LAMBDA("VEERG 2026: 6.1.1.2, Equation (1)")
Name AgResidues_Equations_CropResidues.VEERG_6_1_1_2__1__FractionOfCropResidueRemovedBaled_Title: _xlfn.LAMBDA("Fraction of crop residue that is removed for crop c, calculated where residues are baled")
Name AgResidues_Equations_CropResidues.VEERG_6_1_1_2__1__FractionOfCropResidueRemovedBaled_Unit: _xlfn.LAMBDA("dimensionless")
Name AgResidues_Equations_CropResidues.VEERG_6_1_1_2__1__FractionOfCropResidueRemovedBaled_Variable: _xlfn.LAMBDA("FFODcbaled")
Name AgResidues_Equations_CropResidues.VEERG_6_1_1_2__1__FractionOfCropResidueRemovedBaled_Variation: _xlfn.LAMBDA("VARIATION FROM SOURCE: Added 'baled' to variable subscript")
Name AgResidues_Equations_CropResidues.VEERG_6_1_1_2__1a__FractionOfCropResidueRemoved: _xlfn.LAMBDA(_xlpm.FFODcbaled,_xlpm.FFODcother, _xlpm.FFODcbaled + _xlpm.FFODcother)
Name AgResidues_Equations_CropResidues.VEERG_6_1_1_2__1a__FractionOfCropResidueRemoved_LatexEquation: _xlfn.LAMBDA("FFOD_{c} = FFOD_{c,baled} + FFOD_{c,other}")
Name AgResidues_Equations_CropResidues.VEERG_6_1_1_2__1a__FractionOfCropResidueRemoved_NIRReference: _xlfn.LAMBDA("")
Name AgResidues_Equations_CropResidues.VEERG_6_1_1_2__1a__FractionOfCropResidueRemoved_Source: _xlfn.LAMBDA("")
Name AgResidues_Equations_CropResidues.VEERG_6_1_1_2__1a__FractionOfCropResidueRemoved_Title: _xlfn.LAMBDA("Fraction of crop residue that is removed for crop c")
Name AgResidues_Equations_CropResidues.VEERG_6_1_1_2__1a__FractionOfCropResidueRemoved_Unit: _xlfn.LAMBDA("dimensionless")
Name AgResidues_Equations_CropResidues.VEERG_6_1_1_2__1a__FractionOfCropResidueRemoved_Variable: _xlfn.LAMBDA("FFODc")
Name AgResidues_Equations_CropResidues.VEERG_6_1_1_2__1a__FractionOfCropResidueRemoved_Variation: _xlfn.LAMBDA("VARIATION FROM SOURCE: Added this equation to accommodate user-defined residue removal other than baling.")
Name AgResidues_Equations_Leaching.VEERG_6_3_1_1__1__LeachingAndRunoffEmissionsCropAndPastureResidue: _xlfn.LAMBDA(_xlpm.Mleachcp,_xlpm.EFleach,_xlpm.CgN2O, _xlpm.Mleachcp * _xlpm.EFleach * _xlpm.CgN2O * 10 ^ (-3))
Name AgResidues_Equations_Leaching.VEERG_6_3_1_1__1__LeachingAndRunoffEmissionsCropAndPastureResidue_LatexEquation: _xlfn.LAMBDA("E_{N2O}=\sum_{c}\sum_{p}(M_{leach,cp}\times EF_{leach}\times Cg_{N2O}\times 10^{-3})")
Name AgResidues_Equations_Leaching.VEERG_6_3_1_1__1__LeachingAndRunoffEmissionsCropAndPastureResidue_NIRReference: _xlfn.LAMBDA("")
Name AgResidues_Equations_Leaching.VEERG_6_3_1_1__1__LeachingAndRunoffEmissionsCropAndPastureResidue_Source: _xlfn.LAMBDA("VEERG 2026: 6.3.1.1, Equation (1)")
Name AgResidues_Equations_Leaching.VEERG_6_3_1_1__1__LeachingAndRunoffEmissionsCropAndPastureResidue_Title: _xlfn.LAMBDA("Nitrous oxide leaching and runoff emissions from crop and pasture residues returned to the soil")
Name AgResidues_Equations_Leaching.VEERG_6_3_1_1__1__LeachingAndRunoffEmissionsCropAndPastureResidue_Unit: _xlfn.LAMBDA("t N2O")

Sheet Input - MMS - Feedlot
A1: #VALUE! | C1: Input - MMS - Feedlot
A3: Home
A4: =HYPERLINK("#'Results'!A1", "Results") -> Results
D5: Intake
A6: INPUTS
A7: =HYPERLINK("#'Input - Site'!A1", "Site") -> Site | E7: Domestic (70-80 days) | F7: Export mid fed (80-200 days) | G7: Export long fed (200+ days)
A8: =HYPERLINK("#'Input - Production'!A1", "Production and outputs") -> Production and outputs | D8: Dry matter intake | E8: 10.4 | F8: 10.8 | G8: 8.2 | H8: kg dry matter / head day
A9: =HYPERLINK("#'Input - Herd - Dairy'!A1", "Herd - Dairy") -> Herd - Dairy | D9: Dry matter digestibility | E9: 0.81 | F9: 0.81 | G9: 0.79 | H9: Percent
A10: =HYPERLINK("#'Input - Feed - Dairy'!A1", "Purchased feed - Livestock") -> Purchased feed - Livestock
A11: =HYPERLINK("#'Input - Herd - Feedlot'!A1", "Herd - Feedlot") -> Herd - Feedlot
A12: =HYPERLINK("#'Input - Pasture'!A1", "Pasture") -> Pasture | D12: Manure management systems
A13: =HYPERLINK("#'Input - Grains'!A1", "Crop - Grains") -> Crop - Grains
A14: =HYPERLINK("#'Input - Fert Lime Chem'!A1", "Fertiliser, Lime & Chemicals") -> Fertiliser, Lime & Chemicals | D14: Production system 1: Stage 1
A15: =HYPERLINK("#'Input - Fuel & Energy'!A1", "Electricity and fuel") -> Electricity and fuel | D15: Stage 1 MMS | E15: Domestic (70-80 days) | F15: Export mid fed (80-200 days) | G15: Export long fed (200+ days)
A16: Waste | D16: Drylot (feed pad) | E16: 1 | F16: 1 | G16: 1 | H16: Percent
A17: Freight and transport
A18: =HYPERLINK("#'Input - Other Farm Inputs'!A1", "Other farm inputs") -> Other farm inputs
A19: =HYPERLINK("#'Input - Data quality'!A1", "Data quality") -> Data quality | D19: Production system 1: Stage 2
D20: Stage 2 MMS | E20: Domestic (70-80 days) | F20: Export mid fed (80-200 days) | G20: Export long fed (200+ days)
A21: CALCULATIONS | D21: ="Sent from " & $D$16 -> Sent from Drylot (feed pad) | E21: =IF($D$24="Pasture range and paddock", "⚠️ ALERT: Manure sent to 'pasture range and paddock do not go to stage 2. Select 'No MMS'.", "")
A22: N2O MMS | D22: ='Calcs - CH4 MMS Feedlot'!O44 -> Solid storage | E22: 0.2 | F22: 0.2 | G22: 0.2 | H22: Percent
A23: Enteric methane | D23: ='Calcs - CH4 MMS Feedlot'!O45 -> Composting (passive windrow) | E23: 0.2 | F23: 0.2 | G23: 0.2 | H23: Percent
A24: =HYPERLINK("#'Calcs - Fert Lime'!A1", "Fertiliser & soil amendments") -> Fertiliser & soil amendments | D24: ='Calcs - CH4 MMS Feedlot'!O46 -> Direct application | E24: 0.6 | F24: 0.6 | G24: 0.6 | H24: Percent
A25: =HYPERLINK("#'Calcs - Residue mgmt - Crop'!A1", "Residue management - Crop") -> Residue management - Crop | D25: Total (must equal 100%) | E25: =IF($D$24="Pasture range and paddock", "N/A", SUM(E22:E24)) -> 1 | F25: =IF($D$24="Pasture range and paddock", "N/A", SUM(F22:F24)) -> 1 | G25: =IF($D$24="Pasture range and paddock", "N/A", SUM(G22:G24)) -> 1 | H25: Percent
A26: =HYPERLINK("#'Calcs - Residue mgmt - Pasture'!A1", "Residue management - Pasture") -> Residue management - Pasture
A27: =HYPERLINK("#'Calcs - Field burning'!A1", "Field burning - Crop") -> Field burning - Crop
A28: =HYPERLINK("#'Calcs - Fuel'!A1", "Fuel") -> Fuel | D28: Production system 1: Post-treatment destinations
A29: =HYPERLINK("#'Calcs - Electricity'!A1", "Electricity") -> Electricity | D29: ="Sent from " & $D$16 -> Sent from Drylot (feed pad) | E29: =IF($D$24="Pasture range and paddock", "⚠️ ALERT Manure sent to 'pasture range and paddock do not go to stage 2, or post-treatment destinations.", "")
A30: =HYPERLINK("#'Calcs - Refrigerants'!A1", "Refrigerants") -> Refrigerants | D30: ="Percent sold from " & $D$22 -> Percent sold from Solid storage | E30: 0.25 | F30: 0.25 | G30: 0.25 | H30: Percent
A31: Waste | D31: ="Percent deposited on farm soils from " & $D$22 -> Percent deposited on farm soils from Solid storage | E31: =1-E30 -> 0.75 | F31: =1-F30 -> 0.75 | G31: =1-G30 -> 0.75 | H31: Percent
A32: Freight and transport
A33: =HYPERLINK("#'Calcs - Scope 3'!A1", "Purchased goods scope 3") -> Purchased goods scope 3 | D33: ="Percent sold from " & $D$23 -> Percent sold from Composting (passive windrow) | E33: 0.25 | F33: 0.25 | G33: 0.25 | H33: Percent
D34: ="Percent deposited on farm soils from " & $D$23 -> Percent deposited on farm soils from Composting (passive windrow) | E34: =1-E33 -> 0.75 | F34: =1-F33 -> 0.75 | G34: =1-G33 -> 0.75 | H34: Percent
A35: APPENDICES
A36: =HYPERLINK("#'Constants - Common'!A1", "Constants - Common") -> Constants - Common | D36: ="Percent sold from " & $D$24 & " for sale" -> Percent sold from Direct application for sale | E36: 0.25 | F36: 0.25 | G36: 0.25 | H36: Percent
A37: =HYPERLINK("#'Constants - Cropping'!A1", "Constants - Cropping") -> Constants - Cropping | D37: ="Percent deposited on farm soils from " & $D$24 -> Percent deposited on farm soils from Direct application | E37: =1-E36 -> 0.75 | F37: =1-F36 -> 0.75 | G37: =1-G36 -> 0.75 | H37: Percent
A38: =HYPERLINK("#'Constants - Livestock'!A1", "Constants - Livestock") -> Constants - Livestock
A39: =HYPERLINK("#'Constants - Dairy'!A1", "Constants - Dairy") -> Constants - Dairy
A40: Sources & acknowledgements

Sheet Calcs - CH4 MMS Feedlot
A1: #VALUE! | C1: Calculations - Manure management - Feedlot
A3: Home | D3: Equations | O3: Source data
A4: =HYPERLINK("#'Results'!A1", "Results") -> Results
D5: {=ManureManagement_Feedlot_Methane.VEERG_4_1_1_1__5_VolatileSolidProduction_Title()} -> Volatile solid production | O5: {=SourceData_Feedlot.SourceData_Feedlot_VSL_Title()} -> Feedlot - Fraction of volatile solids lost during storage in the primary system
A6: INPUTS | D6: {=ManureManagement_Feedlot_Methane.VEERG_4_1_1_1__5_VolatileSolidProduction_Source()} -> VEERG 2026: 4.1.1.1, Equation (5) | O6: {=SourceData_Feedlot.SourceData_Feedlot_VSL_Source()} -> VEERG 2026: 4.1.2.3 CONSTANTS
A7: =HYPERLINK("#'Input - Site'!A1", "Site") -> Site | D7: Function name | E7: {=Common_InputFunctions.Utility_DisplayFunctionName(D30)} -> =ManureManagement_Feedlot_Methane.VEERG_4_1_1_1__5_VolatileSolidProduction(D20,D25,$G$15) | O7: {=SourceData_Feedlot.SourceData_Feedlot_VSL_Variable()} -> VSL | P7: {=SourceData_Feedlot.SourceData_Feedlot_VSL_Data()} -> 0.5 | Q7: {=SourceData_Feedlot.SourceData_Feedlot_VSL_Unit()} -> Fraction
A8: =HYPERLINK("#'Input - Production'!A1", "Production and outputs") -> Production and outputs
A9: =HYPERLINK("#'Input - Herd - Dairy'!A1", "Herd - Dairy") -> Herd - Dairy
A10: =HYPERLINK("#'Input - Feed - Dairy'!A1", "Purchased feed - Livestock") -> Purchased feed - Livestock | D10: Variable | E10: {=ManureManagement_Feedlot_Methane.VEERG_4_1_1_1__5_VolatileSolidProduction_Variable()} -> VSj | O10: {=SourceData_Feedlot.SourceData_Feedlot_MMSm1T3_Title()} -> Fraction of volatile solids to each tertiary system assumed that 2 per cent is run - off from the feed pad.
A11: =HYPERLINK("#'Input - Herd - Feedlot'!A1", "Herd - Feedlot") -> Herd - Feedlot | D11: Unit | E11: {=ManureManagement_Feedlot_Methane.VEERG_4_1_1_1__5_VolatileSolidProduction_Unit()} -> kg/head/day | O11: {=SourceData_Feedlot.SourceData_Feedlot_MMSm1T3_Source()} -> VEERG 2026: 4.1.2.3 CONSTANTS
A12: =HYPERLINK("#'Input - Pasture'!A1", "Pasture") -> Pasture | O12: {=SourceData_Feedlot.SourceData_Feedlot_MMSm1T3_Variable()} -> MMSm1T3 | P12: {=SourceData_Feedlot.SourceData_Feedlot_MMSm1T3_Data()} -> 0.02 | Q12: {=SourceData_Feedlot.SourceData_Feedlot_MMSm1T3_Unit()} -> Fraction
A13: =HYPERLINK("#'Input - Grains'!A1", "Crop - Grains") -> Crop - Grains | D13: {=ManureManagement_Feedlot_Methane.VEERG_4_1_1_1__5_VolatileSolidProduction_Arguments()} -> Ij | E13: dry matter intake for each group : kg DM/head/day | G13: See Table_I_j
A14: =HYPERLINK("#'Input - Fert Lime Chem'!A1", "Fertiliser, Lime & Chemicals") -> Fertiliser, Lime & Chemicals | D14: DMDj | E14: dry matter digestibility for each group : fraction | G14: See Table_DMD_j
A15: =HYPERLINK("#'Input - Fuel & Energy'!A1", "Electricity and fuel") -> Electricity and fuel | D15: A | E15: ash content of manure : fraction | G15: =$P$17 -> 0.16 | O15: {=SourceData_Feedlot.SourceData_Feedlot_AshContent_Title()} -> Ash content of manure.
A16: Waste | O16: {=SourceData_Feedlot.SourceData_Feedlot_AshContent_Source()} -> VEERG 2026: 4.1.2.3 CONSTANTS
A17: Freight and transport | D17: Table_I_j | O17: {=SourceData_Feedlot.SourceData_Feedlot_AshContent_Variable()} -> A | P17: {=SourceData_Feedlot.SourceData_Feedlot_AshContent_Data()} -> 0.16 | Q17: {=SourceData_Feedlot.SourceData_Feedlot_AshContent_Unit()} -> Fraction
A18: =HYPERLINK("#'Input - Other Farm Inputs'!A1", "Other farm inputs") -> Other farm inputs | D18: Dry matter intake
A19: =HYPERLINK("#'Input - Data quality'!A1", "Data quality") -> Data quality | D19: Domestic (70-80 days) | E19: Export mid fed (80-200 days) | F19: Export long fed (200+ days)
D20: ='Input - MMS - Feedlot'!$E$8 -> 10.4 | E20: ='Input - MMS - Feedlot'!$F$8 -> 10.8 | F20: ='Input - MMS - Feedlot'!$G$8 -> 8.2 | G20: kg DM/head/day | O20: {=SourceData_Feedlot.SourceData_Feedlot_MethaneEmissionsPotential_Title()} -> Methane emissions potential.
A21: CALCULATIONS | O21: {=SourceData_Feedlot.SourceData_Feedlot_MethaneEmissionsPotential_Source()} -> VEERG 2026: 4.1.2.3 CONSTANTS
A22: N2O MMS | D22: Table_DMD_j | O22: {=SourceData_Feedlot.SourceData_Feedlot_MethaneEmissionsPotential_Variable()} -> B0 | P22: {=SourceData_Feedlot.SourceData_Feedlot_MethaneEmissionsPotential_Data()} -> 0.19 | Q22: {=SourceData_Feedlot.SourceData_Feedlot_MethaneEmissionsPotential_Unit()} -> m3 CH4 / kg VS
A23: Enteric methane | D23: Dry matter digestibility
A24: =HYPERLINK("#'Calcs - Fert Lime'!A1", "Fertiliser & soil amendments") -> Fertiliser & soil amendments | D24: Domestic (70-80 days) | E24: Export mid fed (80-200 days) | F24: Export long fed (200+ days)
A25: =HYPERLINK("#'Calcs - Residue mgmt - Crop'!A1", "Residue management - Crop") -> Residue management - Crop | D25: ='Input - MMS - Feedlot'!$E$9 -> 0.81 | E25: ='Input - MMS - Feedlot'!$F$9 -> 0.81 | F25: ='Input - MMS - Feedlot'!$G$9 -> 0.79 | G25: Fraction | O25: {=SourceData_Feedlot.SourceData_Feedlot_MCF_Title()} -> Feedlot - MCFs
A26: =HYPERLINK("#'Calcs - Residue mgmt - Pasture'!A1", "Residue management - Pasture") -> Residue management - Pasture | O26: {=SourceData_Feedlot.SourceData_Feedlot_MCF_Source()} -> VEERG 2026: Table A.1.7.4: Feedlot - MCFs
A27: =HYPERLINK("#'Calcs - Field burning'!A1", "Field burning - Crop") -> Field burning - Crop | D27: Table_VS_j | O27: {=SourceData_Feedlot.SourceData_Feedlot_MCF_Variation()} -> VARIATION ON SOURCE:
A28: =HYPERLINK("#'Calcs - Fuel'!A1", "Fuel") -> Fuel | D28: Volatile solid production | O28: Duplicated NSW values for ACT
A29: =HYPERLINK("#'Calcs - Electricity'!A1", "Electricity") -> Electricity | D29: Domestic (70-80 days) | E29: Export mid fed (80-200 days) | F29: Export long fed (200+ days) | O29: Added NT and TAS columns with 'no data' values
A30: =HYPERLINK("#'Calcs - Refrigerants'!A1", "Refrigerants") -> Refrigerants | D30: {=ManureManagement_Feedlot_Methane.VEERG_4_1_1_1__5_VolatileSolidProduction(D20,D25,$G$15)} -> 1.65984 | E30: {=ManureManagement_Feedlot_Methane.VEERG_4_1_1_1__5_VolatileSolidProduction(E20,E25,$G$15)} -> 1.72368 | F30: {=ManureManagement_Feedlot_Methane.VEERG_4_1_1_1__5_VolatileSolidProduction(F20,F25,$G$15)} -> 1.44648 | G30: =E11 -> kg/head/day | O30: Added 'NIR definition' column with MMS names that match NIR definitions.
A31: Waste
A32: Freight and transport | O32: Treatment stage T | P32: MMS m | Q32: NSW | R32: ACT | S32: QLD | T32: NT | U32: SA | V32: VIC | W32: WA | X32: TAS | Y32: NIR definition
A33: =HYPERLINK("#'Calcs - Scope 3'!A1", "Purchased goods scope 3") -> Purchased goods scope 3 | O33: {=Common_InputFunctions.Utility_DisplayArrayInTable(SourceData_Feedlot.SourceData_Feedlot_MCF_Data(), Table_SourceData_Feedlot_MCF[[#Headers],[Treatment stage T]], 0)} -> Primary | P33: {=Common_InputFunctions.Utility_DisplayArrayInTable(SourceData_Feedlot.SourceData_Feedlot_MCF_Data(), Table_SourceData_Feedlot_MCF[[#Headers],[Treatment stage T]], 0)} -> Dry lot (Feedpad) | Q33: {=Common_InputFunctions.Utility_DisplayArrayInTable(SourceData_Feedlot.SourceData_Feedlot_MCF_Data(), Table_SourceData_Feedlot_MCF[[#Headers],[Treatment stage T]], 0)} -> 0.01 | R33: {=Common_InputFunctions.Utility_DisplayArrayInTable(SourceData_Feedlot.SourceData_Feedlot_MCF_Data(), Table_SourceData_Feedlot_MCF[[#Headers],[Treatment stage T]], 0)} -> 0.01 | S33: {=Common_InputFunctions.Utility_DisplayArrayInTable(SourceData_Feedlot.SourceData_Feedlot_MCF_Data(), Table_SourceData_Feedlot_MCF[[#Headers],[Treatment stage T]], 0)} -> 0.03 | T33: {=Common_InputFunctions.Utility_DisplayArrayInTable(SourceData_Feedlot.SourceData_Feedlot_MCF_Data(), Table_SourceData_Feedlot_MCF[[#Headers],[Treatment stage T]], 0)} -> No data | U33: {=Common_InputFunctions.Utility_DisplayArrayInTable(SourceData_Feedlot.SourceData_Feedlot_MCF_Data(), Table_SourceData_Feedlot_MCF[[#Headers],[Treatment stage T]], 0)} -> 0.01 | V33: {=Common_InputFunctions.Utility_DisplayArrayInTable(SourceData_Feedlot.SourceData_Feedlot_MCF_Data(), Table_SourceData_Feedlot_MCF[[#Headers],[Treatment stage T]], 0)} -> 0.01 | ... Y33: {=Common_InputFunctions.Utility_DisplayArrayInTable(SourceData_Feedlot.SourceData_Feedlot_MCF_Data(), Table_SourceData_Feedlot_MCF[[#Headers],[Treatment stage T]], 0)} -> Drylot (feed pad)
D34: {=ManureManagement_Feedlot_Methane.VEERG_4_1_1_1__2_Stage1MethaneProductionDrylot_Title()} -> Production of methane in treatment stage 1 MMS | O34: {=Common_InputFunctions.Utility_DisplayArrayInTable(SourceData_Feedlot.SourceData_Feedlot_MCF_Data(), Table_SourceData_Feedlot_MCF[[#Headers],[Treatment stage T]], 0)} -> Secondary | P34: {=Common_InputFunctions.Utility_DisplayArrayInTable(SourceData_Feedlot.SourceData_Feedlot_MCF_Data(), Table_SourceData_Feedlot_MCF[[#Headers],[Treatment stage T]], 0)} -> Solid Storage (Stockpile) | Q34: {=Common_InputFunctions.Utility_DisplayArrayInTable(SourceData_Feedlot.SourceData_Feedlot_MCF_Data(), Table_SourceData_Feedlot_MCF[[#Headers],[Treatment stage T]], 0)} -> 0.02 | R34: {=Common_InputFunctions.Utility_DisplayArrayInTable(SourceData_Feedlot.SourceData_Feedlot_MCF_Data(), Table_SourceData_Feedlot_MCF[[#Headers],[Treatment stage T]], 0)} -> 0.02 | S34: {=Common_InputFunctions.Utility_DisplayArrayInTable(SourceData_Feedlot.SourceData_Feedlot_MCF_Data(), Table_SourceData_Feedlot_MCF[[#Headers],[Treatment stage T]], 0)} -> 0.02 | T34: {=Common_InputFunctions.Utility_DisplayArrayInTable(SourceData_Feedlot.SourceData_Feedlot_MCF_Data(), Table_SourceData_Feedlot_MCF[[#Headers],[Treatment stage T]], 0)} -> No data | U34: {=Common_InputFunctions.Utility_DisplayArrayInTable(SourceData_Feedlot.SourceData_Feedlot_MCF_Data(), Table_SourceData_Feedlot_MCF[[#Headers],[Treatment stage T]], 0)} -> 0.02 | V34: {=Common_InputFunctions.Utility_DisplayArrayInTable(SourceData_Feedlot.SourceData_Feedlot_MCF_Data(), Table_SourceData_Feedlot_MCF[[#Headers],[Treatment stage T]], 0)} -> 0.02 | ... Y34: {=Common_InputFunctions.Utility_DisplayArrayInTable(SourceData_Feedlot.SourceData_Feedlot_MCF_Data(), Table_SourceData_Feedlot_MCF[[#Headers],[Treatment stage T]], 0)} -> Solid storage
A35: APPENDICES | D35: {=ManureManagement_Feedlot_Methane.VEERG_4_1_1_1__2_Stage1MethaneProductionDrylot_Source()} -> VEERG 2026: 4.1.1.1, Equation (2) | O35: {=Common_InputFunctions.Utility_DisplayArrayInTable(SourceData_Feedlot.SourceData_Feedlot_MCF_Data(), Table_SourceData_Feedlot_MCF[[#Headers],[Treatment stage T]], 0)} -> Secondary | P35: {=Common_InputFunctions.Utility_DisplayArrayInTable(SourceData_Feedlot.SourceData_Feedlot_MCF_Data(), Table_SourceData_Feedlot_MCF[[#Headers],[Treatment stage T]], 0)} -> Composting (Passive Windrow) | Q35: {=Common_InputFunctions.Utility_DisplayArrayInTable(SourceData_Feedlot.SourceData_Feedlot_MCF_Data(), Table_SourceData_Feedlot_MCF[[#Headers],[Treatment stage T]], 0)} -> 0.01 | R35: {=Common_InputFunctions.Utility_DisplayArrayInTable(SourceData_Feedlot.SourceData_Feedlot_MCF_Data(), Table_SourceData_Feedlot_MCF[[#Headers],[Treatment stage T]], 0)} -> 0.01 | S35: {=Common_InputFunctions.Utility_DisplayArrayInTable(SourceData_Feedlot.SourceData_Feedlot_MCF_Data(), Table_SourceData_Feedlot_MCF[[#Headers],[Treatment stage T]], 0)} -> 0.01 | T35: {=Common_InputFunctions.Utility_DisplayArrayInTable(SourceData_Feedlot.SourceData_Feedlot_MCF_Data(), Table_SourceData_Feedlot_MCF[[#Headers],[Treatment stage T]], 0)} -> No data | U35: {=Common_InputFunctions.Utility_DisplayArrayInTable(SourceData_Feedlot.SourceData_Feedlot_MCF_Data(), Table_SourceData_Feedlot_MCF[[#Headers],[Treatment stage T]], 0)} -> 0.01 | V35: {=Common_InputFunctions.Utility_DisplayArrayInTable(SourceData_Feedlot.SourceData_Feedlot_MCF_Data(), Table_SourceData_Feedlot_MCF[[#Headers],[Treatment stage T]], 0)} -> 0.01 | ... Y35: {=Common_InputFunctions.Utility_DisplayArrayInTable(SourceData_Feedlot.SourceData_Feedlot_MCF_Data(), Table_SourceData_Feedlot_MCF[[#Headers],[Treatment stage T]], 0)} -> Composting (passive windrow)
A36: =HYPERLINK("#'Constants - Common'!A1", "Constants - Common") -> Constants - Common | D36: Function name | E36: {=Common_InputFunctions.Utility_DisplayFunctionName(E57)} -> =ManureManagement_Feedlot_Methane.VEERG_4_1_1_1__2_Stage1MethaneProductionDrylot(D30,$G$43,E52,$G$45,$G$46) | O36: {=Common_InputFunctions.Utility_DisplayArrayInTable(SourceData_Feedlot.SourceData_Feedlot_MCF_Data(), Table_SourceData_Feedlot_MCF[[#Headers],[Treatment stage T]], 0)} -> Secondary | P36: {=Common_InputFunctions.Utility_DisplayArrayInTable(SourceData_Feedlot.SourceData_Feedlot_MCF_Data(), Table_SourceData_Feedlot_MCF[[#Headers],[Treatment stage T]], 0)} -> Direct Application to soil | Q36: {=Common_InputFunctions.Utility_DisplayArrayInTable(SourceData_Feedlot.SourceData_Feedlot_MCF_Data(), Table_SourceData_Feedlot_MCF[[#Headers],[Treatment stage T]], 0)} -> 0 | R36: {=Common_InputFunctions.Utility_DisplayArrayInTable(SourceData_Feedlot.SourceData_Feedlot_MCF_Data(), Table_SourceData_Feedlot_MCF[[#Headers],[Treatment stage T]], 0)} -> 0 | S36: {=Common_InputFunctions.Utility_DisplayArrayInTable(SourceData_Feedlot.SourceData_Feedlot_MCF_Data(), Table_SourceData_Feedlot_MCF[[#Headers],[Treatment stage T]], 0)} -> 0 | T36: {=Common_InputFunctions.Utility_DisplayArrayInTable(SourceData_Feedlot.SourceData_Feedlot_MCF_Data(), Table_SourceData_Feedlot_MCF[[#Headers],[Treatment stage T]], 0)} -> No data | U36: {=Common_InputFunctions.Utility_DisplayArrayInTable(SourceData_Feedlot.SourceData_Feedlot_MCF_Data(), Table_SourceData_Feedlot_MCF[[#Headers],[Treatment stage T]], 0)} -> 0 | V36: {=Common_InputFunctions.Utility_DisplayArrayInTable(SourceData_Feedlot.SourceData_Feedlot_MCF_Data(), Table_SourceData_Feedlot_MCF[[#Headers],[Treatment stage T]], 0)} -> 0 | ... Y36: {=Common_InputFunctions.Utility_DisplayArrayInTable(SourceData_Feedlot.SourceData_Feedlot_MCF_Data(), Table_SourceData_Feedlot_MCF[[#Headers],[Treatment stage T]], 0)} -> Direct application
A37: =HYPERLINK("#'Constants - Cropping'!A1", "Constants - Cropping") -> Constants - Cropping | O37: {=Common_InputFunctions.Utility_DisplayArrayInTable(SourceData_Feedlot.SourceData_Feedlot_MCF_Data(), Table_SourceData_Feedlot_MCF[[#Headers],[Treatment stage T]], 0)} -> Tertiary | P37: {=Common_InputFunctions.Utility_DisplayArrayInTable(SourceData_Feedlot.SourceData_Feedlot_MCF_Data(), Table_SourceData_Feedlot_MCF[[#Headers],[Treatment stage T]], 0)} -> Uncovered anaerobic lagoon (Effluent pond) | Q37: {=Common_InputFunctions.Utility_DisplayArrayInTable(SourceData_Feedlot.SourceData_Feedlot_MCF_Data(), Table_SourceData_Feedlot_MCF[[#Headers],[Treatment stage T]], 0)} -> 0.75 | R37: {=Common_InputFunctions.Utility_DisplayArrayInTable(SourceData_Feedlot.SourceData_Feedlot_MCF_Data(), Table_SourceData_Feedlot_MCF[[#Headers],[Treatment stage T]], 0)} -> 0.75 | S37: {=Common_InputFunctions.Utility_DisplayArrayInTable(SourceData_Feedlot.SourceData_Feedlot_MCF_Data(), Table_SourceData_Feedlot_MCF[[#Headers],[Treatment stage T]], 0)} -> 0.77 | T37: {=Common_InputFunctions.Utility_DisplayArrayInTable(SourceData_Feedlot.SourceData_Feedlot_MCF_Data(), Table_SourceData_Feedlot_MCF[[#Headers],[Treatment stage T]], 0)} -> No data | U37: {=Common_InputFunctions.Utility_DisplayArrayInTable(SourceData_Feedlot.SourceData_Feedlot_MCF_Data(), Table_SourceData_Feedlot_MCF[[#Headers],[Treatment stage T]], 0)} -> 0.75 | V37: {=Common_InputFunctions.Utility_DisplayArrayInTable(SourceData_Feedlot.SourceData_Feedlot_MCF_Data(), Table_SourceData_Feedlot_MCF[[#Headers],[Treatment stage T]], 0)} -> 0.75 | ... Y37: {=Common_InputFunctions.Utility_DisplayArrayInTable(SourceData_Feedlot.SourceData_Feedlot_MCF_Data(), Table_SourceData_Feedlot_MCF[[#Headers],[Treatment stage T]], 0)} -> Anaerobic lagoon
A38: =HYPERLINK("#'Constants - Livestock'!A1", "Constants - Livestock") -> Constants - Livestock
A39: =HYPERLINK("#'Constants - Dairy'!A1", "Constants - Dairy") -> Constants - Dairy | D39: Variable | E39: {=ManureManagement_Feedlot_Methane.VEERG_4_1_1_1__2_Stage1MethaneProductionDrylot_Variable()} -> Mjm5T1
A40: Sources & acknowledgements | D40: Unit | E40: {=ManureManagement_Feedlot_Methane.VEERG_4_1_1_1__2_Stage1MethaneProductionDrylot_Unit()} -> kg CH4/head/day | O40: Feedlot manure management systems
D42: {=ManureManagement_Feedlot_Methane.VEERG_4_1_1_1__2_Stage1MethaneProductionDrylot_Arguments()} -> VSj | E42: volatile solid production from feedlot cattle in each group : kg/head/day | G42: See Table_VS_j | O42: MMS | P42: Symbol and MMS
D43: BO | E43: emissions potential : m3 CH4/kg VS | G43: =$P$22 -> 0.19 | O43: ='Constants - Livestock'!$E$16 -> Drylot (feed pad) | P43: ='Constants - Livestock'!$F$16 -> Drylot (feed pad) (m=5)
D44: MMSm5T1 | E44: fraction of manure in primary system drylot MMS : fraction | G44: See Table_MMS_m-5_T-1 | O44: ='Constants - Livestock'!$E$15 -> Solid storage | P44: ='Constants - Livestock'!$F$15 -> Solid storage (m=4)
D45: MCFim5 | E45: methane conversion factor for temperature zone and drylot system : fraction | G45: =HLOOKUP(G47, Table_SourceData_Feedlot_MCF[#All], 2, FALSE) -> #REF! | O45: ='Constants - Livestock'!$E$17 -> Composting (passive windrow) | P45: ='Constants - Livestock'!$F$17 -> Composting (passive windrow) (m=6)
D46: rho | E46: density of methane : kg/m3 | G46: =#REF! -> #REF! | O46: ='Constants - Livestock'!$E$26 -> Direct application | P46: ='Constants - Livestock'!$F$26 -> Direct application (m=13)
D47: i | E47: state | G47: {=Common_InputFunctions.Utility_LookupValueInTable('Input - Site'!$E$21,#REF!,#REF!)} -> #REF! | O47: ='Constants - Livestock'!$E$10 -> Anaerobic lagoon | P47: ='Constants - Livestock'!$E$10 -> Anaerobic lagoon
O48: No MMS | P48: No MMS
D49: Table_MMS_m-5_T-1
D50: Fraction of manure in primary system drylot
D51: Stage 1 MMS | E51: Domestic (70-80 days) | F51: Export mid fed (80-200 days) | G51: Export long fed (200+ days)
D52: ='Input - MMS - Feedlot'!$D$16 -> Drylot (feed pad) | E52: ='Input - MMS - Feedlot'!$E$16 -> 1 | F52: ='Input - MMS - Feedlot'!$F$16 -> 1 | G52: ='Input - MMS - Feedlot'!$G$16 -> 1 | H52: Percent
D54: Table_M_j_m-5_T-1
D55: Fraction of manure in primary system drylot
D56: Stage 1 MMS | E56: Domestic (70-80 days) | F56: Export mid fed (80-200 days) | G56: Export long fed (200+ days)
D57: ='Input - MMS - Feedlot'!$D$16 -> Drylot (feed pad) | E57: {=ManureManagement_Feedlot_Methane.VEERG_4_1_1_1__2_Stage1MethaneProductionDrylot(D30,$G$43,E52,$G$45,$G$46)} -> #REF! | F57: {=ManureManagement_Feedlot_Methane.VEERG_4_1_1_1__2_Stage1MethaneProductionDrylot(E30,$G$43,F52,$G$45,$G$46)} -> #REF! | G57: {=ManureManagement_Feedlot_Methane.VEERG_4_1_1_1__2_Stage1MethaneProductionDrylot(F30,$G$43,G52,$G$45,$G$46)} -> #REF! | H57: Percent
D58: =IF(ISNUMBER($G$45),"", "⚠️ ALERT: No MCFim5 data provided. Zero is used instead.") -> ⚠️ ALERT: No MCFim5 data provided. Zero is used instead.
D61: {=ManureManagement_Feedlot_Methane.VEERG_4_1_1_1__3_Stage2MethaneProduction_Title()} -> Production of methane in treatment stage 2 MMS
D62: {=ManureManagement_Feedlot_Methane.VEERG_4_1_1_1__3_Stage2MethaneProduction_Source()} -> VEERG 2026: 4.1.1.1, Equation (3)
D63: Function name
D66: Variable | E66: {=ManureManagement_Feedlot_Methane.VEERG_4_1_1_1__3_Stage2MethaneProduction_Variable()} -> MjmT2
D67: Unit | E67: {=ManureManagement_Feedlot_Methane.VEERG_4_1_1_1__3_Stage2MethaneProduction_Unit()} -> kg CH4/head/day
D69: {=ManureManagement_Feedlot_Methane.VEERG_4_1_1_1__3_Stage2MethaneProduction_Arguments()} -> VSL | E69: fraction of volatile solids lost during storage in the primary system : fraction | G69: =$P$7 -> 0.5
D70: VSj | E70: volatile solid production from feedlot cattle in each group : kg/head/day | G70: See Table_VS_j
D71: BO | E71: emissions potential : m3 CH4/kg VS | G71: =$P$22 -> 0.19
D72: MMSmT2 | E72: fraction of manure in each secondary system : fraction | G72: See Table_MMS_m_T-2
D73: MCFim | E73: methane conversion factor for temperature zone and MMS : fraction
D74: rho | E74: density of methane : kg/m3 | G74: =#REF! -> #REF!
D75: i | E75: state | G75: {=Common_InputFunctions.Utility_LookupValueInTable('Input - Site'!$E$21,#REF!,#REF!)} -> #REF!
D77: Table_MMS_m_T-2
D78: Fraction of manure sent to stage 2 MMS
D79: Stage 1 MMS | E79: Stage 2 MMS | F79: Domestic (70-80 days) | G79: Export mid fed (80-200 days) | H79: Export long fed (200+ days)
D80: ='Input - MMS - Feedlot'!$D$16 -> Drylot (feed pad) | E80: ='Input - MMS - Feedlot'!$D$22 -> Solid storage | F80: ='Input - MMS - Feedlot'!E22 -> 0.2 | G80: ='Input - MMS - Feedlot'!F22 -> 0.2 | H80: ='Input - MMS - Feedlot'!G22 -> 0.2 | I80: Fraction
D81: ='Input - MMS - Feedlot'!$D$16 -> Drylot (feed pad) | E81: ='Input - MMS - Feedlot'!$D$23 -> Composting (passive windrow) | F81: ='Input - MMS - Feedlot'!E23 -> 0.2 | G81: ='Input - MMS - Feedlot'!F23 -> 0.2 | H81: ='Input - MMS - Feedlot'!G23 -> 0.2 | I81: Fraction
D82: ='Input - MMS - Feedlot'!$D$16 -> Drylot (feed pad) | E82: ='Input - MMS - Feedlot'!$D$24 -> Direct application | F82: ='Input - MMS - Feedlot'!E24 -> 0.6 | G82: ='Input - MMS - Feedlot'!F24 -> 0.6 | H82: ='Input - MMS - Feedlot'!G24 -> 0.6 | I82: Fraction
D84: Table_MCF_i_m
D85: Methane conversion factor for state and MMS
D86: Stage 1 MMS | E86: Stage 2 MMS | F86: MCFim
D87: ='Input - MMS - Feedlot'!$D$16 -> Drylot (feed pad) | E87: ='Input - MMS - Feedlot'!$D$22 -> Solid storage | F87: =HLOOKUP(E87, Table_SourceData_Feedlot_MCF[#All], 2, FALSE) -> #N/A | G87: Fraction
D88: ='Input - MMS - Feedlot'!$D$16 -> Drylot (feed pad) | E88: ='Input - MMS - Feedlot'!$D$23 -> Composting (passive windrow) | F88: ='Input - MMS - Feedlot'!E30 -> 0.25 | G88: Fraction
D89: ='Input - MMS - Feedlot'!$D$16 -> Drylot (feed pad) | E89: ='Input - MMS - Feedlot'!$D$24 -> Direct application | F89: ='Input - MMS - Feedlot'!E31 -> 0.75 | G89: Fraction

Sheet Input - MMS - Poultry
A1: #VALUE! | C1: Input - MMS - Poultry
A3: Home
A4: =HYPERLINK("#'Results'!A1", "Results") -> Results
D5: This tool demostrates inputs for two production system combinations.
A6: INPUTS | D6: Each production system has two primary manure management systems, and three possible secondary manure management systems.
A7: =HYPERLINK("#'Input - Site'!A1", "Site") -> Site
A8: =HYPERLINK("#'Input - Production'!A1", "Production and outputs") -> Production and outputs | D8: Intake
A9: =HYPERLINK("#'Input - Herd - Dairy'!A1", "Herd - Dairy") -> Herd - Dairy | E9: Layers | F9: Meat chicken growers | G9: Meat chicken breeders | H9: Other
A10: =HYPERLINK("#'Input - Feed - Dairy'!A1", "Purchased feed - Livestock") -> Purchased feed - Livestock | D10: Dry matter intake | E10: 10 | F10: 10 | G10: 10 | H10: 10 | I10: kg DM/head/day
A11: =HYPERLINK("#'Input - Herd - Feedlot'!A1", "Herd - Feedlot") -> Herd - Feedlot | D11: Dry matter digestibility | E11: 0.1 | F11: 0.1 | G11: 0.1 | H11: 0.1 | I11: Percent
A12: =HYPERLINK("#'Input - Pasture'!A1", "Pasture") -> Pasture
A13: =HYPERLINK("#'Input - Grains'!A1", "Crop - Grains") -> Crop - Grains
A14: =HYPERLINK("#'Input - Fert Lime Chem'!A1", "Fertiliser, Lime & Chemicals") -> Fertiliser, Lime & Chemicals | D14: Production systems
A15: =HYPERLINK("#'Input - Fuel & Energy'!A1", "Electricity and fuel") -> Electricity and fuel
A16: Waste | D16: Production system (select) | E16: Layers | F16: Meat chicken growers | G16: Meat chicken breeders | H16: Other
A17: Freight and transport | D17: Free range | E17: 0.5 | F17: 0.5 | G17: 0.5 | H17: 0.5 | I17: Percent
A18: =HYPERLINK("#'Input - Other Farm Inputs'!A1", "Other farm inputs") -> Other farm inputs | D18: Cage | E18: 0.5 | F18: 0.5 | G18: 0.5 | H18: 0.5 | I18: Percent
A19: =HYPERLINK("#'Input - Data quality'!A1", "Data quality") -> Data quality | D19: Total (must equal 100%) | E19: =SUM(E17:E18) -> 1 | F19: =SUM(F17:F18) -> 1 | G19: =SUM(G17:G18) -> 1 | H19: =SUM(H17:H18) -> 1 | I19: Percent
A21: CALCULATIONS
A22: N2O MMS | D22: Production system 1 of 2
A23: Enteric methane
A24: =HYPERLINK("#'Calcs - Fert Lime'!A1", "Fertiliser & soil amendments") -> Fertiliser & soil amendments | D24: Production system 1 | E24: =$D$17 -> Free range
A25: =HYPERLINK("#'Calcs - Residue mgmt - Crop'!A1", "Residue management - Crop") -> Residue management - Crop
A26: =HYPERLINK("#'Calcs - Residue mgmt - Pasture'!A1", "Residue management - Pasture") -> Residue management - Pasture | D26: Production system 1: Stage 1
A27: =HYPERLINK("#'Calcs - Field burning'!A1", "Field burning - Crop") -> Field burning - Crop | D27: =IF($E$24="Free range", "⚠️ ALERT: Because this production system is free range, one stage 1 MMS must be 'Pasture, range and paddock.'", "") -> ⚠️ ALERT: Because this production system is free range, one stage 1 MMS must be 'Pasture, range and paddock.'
A28: =HYPERLINK("#'Calcs - Fuel'!A1", "Fuel") -> Fuel | D28: Stage 1 MMS (select) | E28: Layers | F28: Meat chicken growers | G28: Meat chicken breeders | H28: Other
A29: =HYPERLINK("#'Calcs - Electricity'!A1", "Electricity") -> Electricity | D29: Pasture range and paddock | E29: 0.5 | F29: 0.5 | G29: 0.5 | H29: 0.5 | I29: Percent
A30: =HYPERLINK("#'Calcs - Refrigerants'!A1", "Refrigerants") -> Refrigerants | D30: Belt manure removal | E30: 0.5 | F30: 0.5 | G30: 0.5 | H30: 0.5 | I30: Percent
A31: Waste | D31: Total (must equal 100%) | E31: =SUM(E29:E30) -> 1 | F31: =SUM(F29:F30) -> 1 | G31: =SUM(G29:G30) -> 1 | H31: =SUM(H29:H30) -> 1 | I31: Percent
A32: Freight and transport
A33: =HYPERLINK("#'Calcs - Scope 3'!A1", "Purchased goods scope 3") -> Purchased goods scope 3 | D33: Production system 1: Stage 2
A35: APPENDICES | D35: Stage 2 MMS (select) | E35: Layers | F35: Meat chicken growers | G35: Meat chicken breeders | H35: Other
A36: =HYPERLINK("#'Constants - Common'!A1", "Constants - Common") -> Constants - Common | D36: ="Sent from " & $D$29 -> Sent from Pasture range and paddock | E36: =IF($D$29="Pasture range and paddock", "⚠️ ALERT: Manure sent to 'pasture range and paddock do not go to stage 2. Select 'No MMS'.", "") -> ⚠️ ALERT: Manure sent to 'pasture range and paddock do not go to stage 2. Select 'No MMS'.
A37: =HYPERLINK("#'Constants - Cropping'!A1", "Constants - Cropping") -> Constants - Cropping | D37: No MMS | E37: 0.2 | F37: 0.2 | G37: 0.2 | H37: 0.2 | I37: Percent
A38: =HYPERLINK("#'Constants - Livestock'!A1", "Constants - Livestock") -> Constants - Livestock | D38: No MMS | E38: 0.2 | F38: 0.2 | G38: 0.2 | H38: 0.2 | I38: Percent
A39: =HYPERLINK("#'Constants - Dairy'!A1", "Constants - Dairy") -> Constants - Dairy | D39: No MMS | E39: 0.6 | F39: 0.6 | G39: 0.6 | H39: 0.6 | I39: Percent
A40: Sources & acknowledgements | D40: Total (must equal 100%) | E40: =IF($D$29="Pasture range and paddock", "N/A", SUM(E37:E39)) -> N/A | F40: =IF($D$29="Pasture range and paddock", "N/A", SUM(F37:F39)) -> N/A | G40: =IF($D$29="Pasture range and paddock", "N/A", SUM(G37:G39)) -> N/A | H40: =IF($D$29="Pasture range and paddock", "N/A", SUM(H37:H39)) -> N/A | I40: Percent
D42: ="Sent from " & $D$30 -> Sent from Belt manure removal | E42: =IF($D$30="Pasture range and paddock", "Manure sent to 'pasture range and paddock do not go to stage 2. Select 'No MMS'.", "")
D43: Direct processing | E43: 0.2 | F43: 0.2 | G43: 0.2 | H43: 0.2 | I43: Percent
D44: Composting (passive windrow) | E44: 0.2 | F44: 0.2 | G44: 0.2 | H44: 0.2 | I44: Percent
D45: Direct processing | E45: 0.6 | F45: 0.6 | G45: 0.6 | H45: 0.6 | I45: Percent
D46: Total (must equal 100%) | E46: =IF($D$29="Pasture range and paddock", "N/A", SUM(E43:E45)) -> N/A | F46: =IF($D$29="Pasture range and paddock", "N/A", SUM(F43:F45)) -> N/A | G46: =IF($D$29="Pasture range and paddock", "N/A", SUM(G43:G45)) -> N/A | H46: =IF($D$29="Pasture range and paddock", "N/A", SUM(H43:H45)) -> N/A | I46: Percent
D49: Production system 1: Post-treatment destinations
D51: ="Sent from " & $D$29 -> Sent from Pasture range and paddock | E51: =IF($D$29="Pasture range and paddock", "⚠️ ALERT Manure sent to 'pasture range and paddock do not go to stage 2, or post-treatment destinations.", "") -> ⚠️ ALERT Manure sent to 'pasture range and paddock do not go to stage 2, or post-treatment destinations.
D52: ="Percent sold from " & $D$37 -> Percent sold from No MMS | E52: 0.25 | F52: 0.25 | G52: 0.25 | H52: 0.25 | I52: Percent
D53: ="Percent deposited on farm soils from " & $D$37 -> Percent deposited on farm soils from No MMS | E53: =1-E52 -> 0.75 | F53: =1-F52 -> 0.75 | G53: =1-G52 -> 0.75 | H53: =1-H52 -> 0.75 | I53: Percent
D55: ="Percent sold from " & $D$38 -> Percent sold from No MMS | E55: 0.25 | F55: 0.25 | G55: 0.25 | H55: 0.25 | I55: Percent
D56: ="Percent deposited on farm soils from " & $D$38 -> Percent deposited on farm soils from No MMS | E56: =1-E55 -> 0.75 | F56: =1-F55 -> 0.75 | G56: =1-G55 -> 0.75 | H56: =1-H55 -> 0.75 | I56: Percent
D58: ="Percent sold from " & $D$39 & " for sale" -> Percent sold from No MMS for sale | E58: 0.25 | F58: 0.25 | G58: 0.25 | H58: 0.25 | I58: Percent
D59: ="Percent deposited on farm soils from " & $D$39 -> Percent deposited on farm soils from No MMS | E59: =1-E58 -> 0.75 | F59: =1-F58 -> 0.75 | G59: =1-G58 -> 0.75 | H59: =1-H58 -> 0.75 | I59: Percent
D61: ="Sent from " & $D$30 -> Sent from Belt manure removal | E61: =IF($D$30="Pasture range and paddock", "⚠️ ALERT Manure sent to 'pasture range and paddock do not go to stage 2, or post-treatment destinations.", "")
D62: ="Percent sold from " & $D$43 -> Percent sold from Direct processing | E62: 0.25 | F62: 0.25 | G62: 0.25 | H62: 0.25 | I62: Percent
D63: ="Percent deposited on farm soils from " & $D$43 -> Percent deposited on farm soils from Direct processing | E63: =IF($H$31="Solid storage", "N/A", 1-E62) -> 0.75 | F63: =IF($H$31="Solid storage", "N/A", 1-F62) -> 0.75 | G63: =IF($H$31="Solid storage", "N/A", 1-G62) -> 0.75 | H63: =IF($H$31="Solid storage", "N/A", 1-H62) -> 0.75 | I63: Percent
D65: ="Percent sold from " & $D$44 -> Percent sold from Composting (passive windrow) | E65: 0.25 | F65: 0.25 | G65: 0.25 | H65: 0.25 | I65: Percent
D66: ="Percent deposited on farm soils from " & $D$44 -> Percent deposited on farm soils from Composting (passive windrow) | E66: =IF($H$31="Solid storage", "N/A", 1-E65) -> 0.75 | F66: =IF($H$31="Solid storage", "N/A", 1-F65) -> 0.75 | G66: =IF($H$31="Solid storage", "N/A", 1-G65) -> 0.75 | H66: =IF($H$31="Solid storage", "N/A", 1-H65) -> 0.75 | I66: Percent
D68: ="Percent sold from " & $D$45 & " for sale" -> Percent sold from Direct processing for sale | E68: 0.25 | F68: 0.25 | G68: 0.25 | H68: 0.25 | I68: Percent
D69: ="Percent deposited on farm soils from " & $D$45 -> Percent deposited on farm soils from Direct processing | E69: =IF($H$31="Solid storage", "N/A", 1-E68) -> 0.75 | F69: =IF($H$31="Solid storage", "N/A", 1-F68) -> 0.75 | G69: =IF($H$31="Solid storage", "N/A", 1-G68) -> 0.75 | H69: =IF($H$31="Solid storage", "N/A", 1-H68) -> 0.75 | I69: Percent
D72: Production system 2 of 2
D74: Production system 1 | E74: =$D$18 -> Cage
D76: Production system 1: Stage 1
D77: =IF($E$74="Free range", "⚠️ ALERT: Because this production system is free range, one stage 1 MMS must be 'Pasture, range and paddock.'", "")
D78: Stage 1 MMS (select) | E78: Layers | F78: Meat chicken growers | G78: Meat chicken breeders | H78: Other
D79: Belt manure removal | E79: 0.5 | F79: 0.5 | G79: 0.5 | H79: 0.5 | I79: Percent
D80: Poultry manure with bedding | E80: 0.5 | F80: 0.5 | G80: 0.5 | H80: 0.5 | I80: Percent
D81: Total (must equal 100%) | E81: =SUM(E79:E80) -> 1 | F81: =SUM(F79:F80) -> 1 | G81: =SUM(G79:G80) -> 1 | H81: =SUM(H79:H80) -> 1 | I81: Percent
D83: Production system 1: Stage 2
D85: Stage 2 MMS (select) | E85: Layers | F85: Meat chicken growers | G85: Meat chicken breeders | H85: Other
D86: ="Sent from " & $D$79 -> Sent from Belt manure removal | E86: =IF($D$79="Pasture range and paddock", "⚠️ ALERT: Manure sent to 'pasture range and paddock do not go to stage 2. Select 'No MMS'.", "")
D87: Digester / covered lagoons | E87: 0.2 | F87: 0.2 | G87: 0.2 | H87: 0.2 | I87: Percent
D88: Direct processing | E88: 0.2 | F88: 0.2 | G88: 0.2 | H88: 0.2 | I88: Percent
D89: Direct application | E89: 0.6 | F89: 0.6 | G89: 0.6 | H89: 0.6 | I89: Percent
D90: Total (must equal 100%) | E90: =IF($D$79="Pasture range and paddock", "N/A", SUM(E87:E89)) -> 1 | F90: =IF($D$79="Pasture range and paddock", "N/A", SUM(F87:F89)) -> 1 | G90: =IF($D$79="Pasture range and paddock", "N/A", SUM(G87:G89)) -> 1 | H90: =IF($D$79="Pasture range and paddock", "N/A", SUM(H87:H89)) -> 1 | I90: Percent
D92: ="Sent from " & $D$80 -> Sent from Poultry manure with bedding | E92: =IF($D$80="Pasture range and paddock", "Manure sent to 'pasture range and paddock do not go to stage 2. Select 'No MMS'.", "")
D93: Solid storage | E93: 0.2 | F93: 0.2 | G93: 0.2 | H93: 0.2 | I93: Percent
D94: Composting (passive windrow) | E94: 0.2 | F94: 0.2 | G94: 0.2 | H94: 0.2 | I94: Percent
D95: Direct processing | E95: 0.6 | F95: 0.6 | G95: 0.6 | H95: 0.6 | I95: Percent
D96: Total (must equal 100%) | E96: =IF($D$80="Pasture range and paddock", "N/A", SUM(E93:E95)) -> 1 | F96: =IF($D$80="Pasture range and paddock", "N/A", SUM(F93:F95)) -> 1 | G96: =IF($D$80="Pasture range and paddock", "N/A", SUM(G93:G95)) -> 1 | H96: =IF($D$80="Pasture range and paddock", "N/A", SUM(H93:H95)) -> 1 | I96: Percent
D99: Production system 1: Post-treatment destinations
D101: ="Sent from " & $D$79 -> Sent from Belt manure removal | E101: =IF($D$79="Pasture range and paddock", "⚠️ ALERT Manure sent to 'pasture range and paddock do not go to stage 2, or post-treatment destinations.", "")
D102: ="Percent sold from " & $D$87 -> Percent sold from Digester / covered lagoons | E102: 0.25 | F102: 0.25 | G102: 0.25 | H102: 0.25 | I102: Percent
D103: ="Percent deposited on farm soils from " & $D$87 -> Percent deposited on farm soils from Digester / covered lagoons | E103: =IF($D$79="Pasture range and paddock", "N/A", 1-E102) -> 0.75 | F103: =IF($D$79="Pasture range and paddock", "N/A", 1-F102) -> 0.75 | G103: =IF($D$79="Pasture range and paddock", "N/A", 1-G102) -> 0.75 | H103: =IF($D$79="Pasture range and paddock", "N/A", 1-H102) -> 0.75 | I103: Percent
D105: ="Percent sold from " & $D$88 -> Percent sold from Direct processing | E105: 0.25 | F105: 0.25 | G105: 0.25 | H105: 0.25 | I105: Percent
D106: ="Percent deposited on farm soils from " & $D$88 -> Percent deposited on farm soils from Direct processing | E106: =IF($D$79="Pasture range and paddock", "N/A", 1-E105) -> 0.75 | F106: =IF($D$79="Pasture range and paddock", "N/A", 1-F105) -> 0.75 | G106: =IF($D$79="Pasture range and paddock", "N/A", 1-G105) -> 0.75 | H106: =IF($D$79="Pasture range and paddock", "N/A", 1-H105) -> 0.75 | I106: Percent
D108: ="Percent sold from " & $D$89 & " for sale" -> Percent sold from Direct application for sale | E108: 0.25 | F108: 0.25 | G108: 0.25 | H108: 0.25 | I108: Percent
D109: ="Percent deposited on farm soils from " & $D$89 -> Percent deposited on farm soils from Direct application | E109: =IF($D$79="Pasture range and paddock", "N/A", 1-E108) -> 0.75 | F109: =IF($D$79="Pasture range and paddock", "N/A", 1-F108) -> 0.75 | G109: =IF($D$79="Pasture range and paddock", "N/A", 1-G108) -> 0.75 | H109: =IF($D$79="Pasture range and paddock", "N/A", 1-H108) -> 0.75 | I109: Percent
D111: ="Sent from " & $D$80 -> Sent from Poultry manure with bedding | E111: =IF($D$80="Pasture range and paddock", "⚠️ ALERT Manure sent to 'pasture range and paddock do not go to stage 2, or post-treatment destinations.", "")
D112: ="Percent sold from " & $D$93 -> Percent sold from Solid storage | E112: 0.25 | F112: 0.25 | G112: 0.25 | H112: 0.25 | I112: Percent
D113: ="Percent deposited on farm soils from " & $D$93 -> Percent deposited on farm soils from Solid storage | E113: =IF($D$80="Pasture range and paddock", "N/A", 1-E112) -> 0.75 | F113: =IF($D$80="Pasture range and paddock", "N/A", 1-F112) -> 0.75 | G113: =IF($D$80="Pasture range and paddock", "N/A", 1-G112) -> 0.75 | H113: =IF($D$80="Pasture range and paddock", "N/A", 1-H112) -> 0.75 | I113: Percent
D115: ="Percent sold from " & $D$94 -> Percent sold from Composting (passive windrow) | E115: 0.25 | F115: 0.25 | G115: 0.25 | H115: 0.25 | I115: Percent
D116: ="Percent deposited on farm soils from " & $D$94 -> Percent deposited on farm soils from Composting (passive windrow) | E116: =IF($D$80="Pasture range and paddock", "N/A", 1-E115) -> 0.75 | F116: =IF($D$80="Pasture range and paddock", "N/A", 1-F115) -> 0.75 | G116: =IF($D$80="Pasture range and paddock", "N/A", 1-G115) -> 0.75 | H116: =IF($D$80="Pasture range and paddock", "N/A", 1-H115) -> 0.75 | I116: Percent
D118: ="Percent sold from " & $D$95 & " for sale" -> Percent sold from Direct processing for sale | E118: 0.25 | F118: 0.25 | G118: 0.25 | H118: 0.25 | I118: Percent
D119: ="Percent deposited on farm soils from " & $D$95 -> Percent deposited on farm soils from Direct processing | E119: =IF($D$80="Pasture range and paddock", "N/A", 1-E118) -> 0.75 | F119: =IF($D$80="Pasture range and paddock", "N/A", 1-F118) -> 0.75 | G119: =IF($D$80="Pasture range and paddock", "N/A", 1-G118) -> 0.75 | H119: =IF($D$80="Pasture range and paddock", "N/A", 1-H118) -> 0.75 | I119: Percent

Sheet Calcs - CH4 MMS Poultry
A1: #VALUE! | C1: Calculations - Manure management - Poultry
A3: Home | D3: Equations | O3: Source data
A4: =HYPERLINK("#'Results'!A1", "Results") -> Results
D5: {=ManureManagement_Poultry_Methane.VEERG_4_6_1_1__6_VolatileSolidProduction_Title()} -> Volatile solid production | O5: {=SourceData_Poultry.SourceData_Poultry_DietProperties_Title()} -> Poultry - Diet properties
A6: INPUTS | D6: {=ManureManagement_Poultry_Methane.VEERG_4_6_1_1__6_VolatileSolidProduction_Source()} -> VEERG 2026: 4.6.1.1, Equation (6) | O6: {=SourceData_Poultry.SourceData_Poultry_DietProperties_Source()} -> VEERG 2026: Table A.1.7.1: Poultry - Diet properties
A7: =HYPERLINK("#'Input - Site'!A1", "Site") -> Site | D7: Function name | E7: {=Common_InputFunctions.Utility_DisplayFunctionName(D35)} -> =ManureManagement_Poultry_Methane.VEERG_4_6_1_1__6_VolatileSolidProduction(D20,D25,D30)
A8: =HYPERLINK("#'Input - Production'!A1", "Production and outputs") -> Production and outputs | O8: Nutrient analysis | P8: Layers | Q8: Meat chicken growers | R8: Meat chicken breeder | S8: Meat other
A9: =HYPERLINK("#'Input - Herd - Dairy'!A1", "Herd - Dairy") -> Herd - Dairy | O9: {=Common_InputFunctions.Utility_DisplayArrayInTable(SourceData_Poultry.SourceData_Poultry_DietProperties_Data(), Table_SourceData_Poultry_DietProperties[[#Headers],[Nutrient analysis]], 0)} -> Dry matter intake (kg/head/day) | P9: {=Common_InputFunctions.Utility_DisplayArrayInTable(SourceData_Poultry.SourceData_Poultry_DietProperties_Data(), Table_SourceData_Poultry_DietProperties[[#Headers],[Nutrient analysis]], 0)} -> 0.086 | Q9: {=Common_InputFunctions.Utility_DisplayArrayInTable(SourceData_Poultry.SourceData_Poultry_DietProperties_Data(), Table_SourceData_Poultry_DietProperties[[#Headers],[Nutrient analysis]], 0)} -> 0.093 | R9: {=Common_InputFunctions.Utility_DisplayArrayInTable(SourceData_Poultry.SourceData_Poultry_DietProperties_Data(), Table_SourceData_Poultry_DietProperties[[#Headers],[Nutrient analysis]], 0)} -> 0.103 | S9: {=Common_InputFunctions.Utility_DisplayArrayInTable(SourceData_Poultry.SourceData_Poultry_DietProperties_Data(), Table_SourceData_Poultry_DietProperties[[#Headers],[Nutrient analysis]], 0)} -> 0.093
A10: =HYPERLINK("#'Input - Feed - Dairy'!A1", "Purchased feed - Livestock") -> Purchased feed - Livestock | D10: Variable | E10: {=ManureManagement_Poultry_Methane.VEERG_4_6_1_1__6_VolatileSolidProduction_Variable()} -> VSjk | O10: {=Common_InputFunctions.Utility_DisplayArrayInTable(SourceData_Poultry.SourceData_Poultry_DietProperties_Data(), Table_SourceData_Poultry_DietProperties[[#Headers],[Nutrient analysis]], 0)} -> Dry matter digestibility | P10: {=Common_InputFunctions.Utility_DisplayArrayInTable(SourceData_Poultry.SourceData_Poultry_DietProperties_Data(), Table_SourceData_Poultry_DietProperties[[#Headers],[Nutrient analysis]], 0)} -> 0.8 | Q10: {=Common_InputFunctions.Utility_DisplayArrayInTable(SourceData_Poultry.SourceData_Poultry_DietProperties_Data(), Table_SourceData_Poultry_DietProperties[[#Headers],[Nutrient analysis]], 0)} -> 0.8 | R10: {=Common_InputFunctions.Utility_DisplayArrayInTable(SourceData_Poultry.SourceData_Poultry_DietProperties_Data(), Table_SourceData_Poultry_DietProperties[[#Headers],[Nutrient analysis]], 0)} -> 0.8 | S10: {=Common_InputFunctions.Utility_DisplayArrayInTable(SourceData_Poultry.SourceData_Poultry_DietProperties_Data(), Table_SourceData_Poultry_DietProperties[[#Headers],[Nutrient analysis]], 0)} -> 0.8
A11: =HYPERLINK("#'Input - Herd - Feedlot'!A1", "Herd - Feedlot") -> Herd - Feedlot | D11: Unit | E11: {=ManureManagement_Poultry_Methane.VEERG_4_6_1_1__6_VolatileSolidProduction_Unit()} -> kg/head/day | O11: {=Common_InputFunctions.Utility_DisplayArrayInTable(SourceData_Poultry.SourceData_Poultry_DietProperties_Data(), Table_SourceData_Poultry_DietProperties[[#Headers],[Nutrient analysis]], 0)} -> Crude protein | P11: {=Common_InputFunctions.Utility_DisplayArrayInTable(SourceData_Poultry.SourceData_Poultry_DietProperties_Data(), Table_SourceData_Poultry_DietProperties[[#Headers],[Nutrient analysis]], 0)} -> 0.19 | Q11: {=Common_InputFunctions.Utility_DisplayArrayInTable(SourceData_Poultry.SourceData_Poultry_DietProperties_Data(), Table_SourceData_Poultry_DietProperties[[#Headers],[Nutrient analysis]], 0)} -> 0.23 | R11: {=Common_InputFunctions.Utility_DisplayArrayInTable(SourceData_Poultry.SourceData_Poultry_DietProperties_Data(), Table_SourceData_Poultry_DietProperties[[#Headers],[Nutrient analysis]], 0)} -> 0.19 | S11: {=Common_InputFunctions.Utility_DisplayArrayInTable(SourceData_Poultry.SourceData_Poultry_DietProperties_Data(), Table_SourceData_Poultry_DietProperties[[#Headers],[Nutrient analysis]], 0)} -> 0.23
A12: =HYPERLINK("#'Input - Pasture'!A1", "Pasture") -> Pasture | O12: {=Common_InputFunctions.Utility_DisplayArrayInTable(SourceData_Poultry.SourceData_Poultry_DietProperties_Data(), Table_SourceData_Poultry_DietProperties[[#Headers],[Nutrient analysis]], 0)} -> Nitrogen retention rate | P12: {=Common_InputFunctions.Utility_DisplayArrayInTable(SourceData_Poultry.SourceData_Poultry_DietProperties_Data(), Table_SourceData_Poultry_DietProperties[[#Headers],[Nutrient analysis]], 0)} -> 0.35 | Q12: {=Common_InputFunctions.Utility_DisplayArrayInTable(SourceData_Poultry.SourceData_Poultry_DietProperties_Data(), Table_SourceData_Poultry_DietProperties[[#Headers],[Nutrient analysis]], 0)} -> 0.47 | R12: {=Common_InputFunctions.Utility_DisplayArrayInTable(SourceData_Poultry.SourceData_Poultry_DietProperties_Data(), Table_SourceData_Poultry_DietProperties[[#Headers],[Nutrient analysis]], 0)} -> 0.32 | S12: {=Common_InputFunctions.Utility_DisplayArrayInTable(SourceData_Poultry.SourceData_Poultry_DietProperties_Data(), Table_SourceData_Poultry_DietProperties[[#Headers],[Nutrient analysis]], 0)} -> 0.47
A13: =HYPERLINK("#'Input - Grains'!A1", "Crop - Grains") -> Crop - Grains | D13: {=ManureManagement_Poultry_Methane.VEERG_4_6_1_1__6_VolatileSolidProduction_Arguments()} -> Ijk | E13: dry matter intake for each class and subclass : kg DM/head/day | G13: see Table_I_j_k | O13: {=Common_InputFunctions.Utility_DisplayArrayInTable(SourceData_Poultry.SourceData_Poultry_DietProperties_Data(), Table_SourceData_Poultry_DietProperties[[#Headers],[Nutrient analysis]], 0)} -> Manure ash | P13: {=Common_InputFunctions.Utility_DisplayArrayInTable(SourceData_Poultry.SourceData_Poultry_DietProperties_Data(), Table_SourceData_Poultry_DietProperties[[#Headers],[Nutrient analysis]], 0)} -> 0.18 | Q13: {=Common_InputFunctions.Utility_DisplayArrayInTable(SourceData_Poultry.SourceData_Poultry_DietProperties_Data(), Table_SourceData_Poultry_DietProperties[[#Headers],[Nutrient analysis]], 0)} -> 0.15 | R13: {=Common_InputFunctions.Utility_DisplayArrayInTable(SourceData_Poultry.SourceData_Poultry_DietProperties_Data(), Table_SourceData_Poultry_DietProperties[[#Headers],[Nutrient analysis]], 0)} -> 0.18 | S13: {=Common_InputFunctions.Utility_DisplayArrayInTable(SourceData_Poultry.SourceData_Poultry_DietProperties_Data(), Table_SourceData_Poultry_DietProperties[[#Headers],[Nutrient analysis]], 0)} -> 0.15
A14: =HYPERLINK("#'Input - Fert Lime Chem'!A1", "Fertiliser, Lime & Chemicals") -> Fertiliser, Lime & Chemicals | D14: DMDjk | E14: dry matter digestibility for each class and subclass : fraction | G14: see Table_DMD_j_k
A15: =HYPERLINK("#'Input - Fuel & Energy'!A1", "Electricity and fuel") -> Electricity and fuel | D15: Aj | E15: ash content of manure for each class and subclass : fraction | G15: see Table_A_j
A16: Waste
A17: Freight and transport | D17: Table_I_j_k | O17: {=SourceData_Poultry.SourceData_Poultry_MethaneEmissionsPotential_Title()} -> Poultry - Methane emissions potential per class
A18: =HYPERLINK("#'Input - Other Farm Inputs'!A1", "Other farm inputs") -> Other farm inputs | D18: Dry matter intake | O18: {=SourceData_Poultry.SourceData_Poultry_MethaneEmissionsPotential_Source()} -> VEERG 2026: 4.6.2.3 CONSTANT: Poultry - Methane emissions potential per class
A19: =HYPERLINK("#'Input - Data quality'!A1", "Data quality") -> Data quality | D19: Layers | E19: Meat chicken growers | F19: Meat chicken breeders | G19: Other | O19: Poultry class | P19: B0
D20: ='Input - MMS - Poultry'!$E$10 -> 10 | E20: ='Input - MMS - Poultry'!$F$10 -> 10 | F20: ='Input - MMS - Poultry'!$G$10 -> 10 | G20: ='Input - MMS - Poultry'!$H$10 -> 10 | H20: kg/head/day | O20: {=Common_InputFunctions.Utility_DisplayArrayInTable(SourceData_Poultry.SourceData_Poultry_MethaneEmissionsPotential_Data(), Table_SourceData_Poultry_MethaneEmissionsPotential[[#Headers],[Poultry class]], 0)} -> Layers | P20: {=Common_InputFunctions.Utility_DisplayArrayInTable(SourceData_Poultry.SourceData_Poultry_MethaneEmissionsPotential_Data(), Table_SourceData_Poultry_MethaneEmissionsPotential[[#Headers],[Poultry class]], 0)} -> 0.39
A21: CALCULATIONS | O21: {=Common_InputFunctions.Utility_DisplayArrayInTable(SourceData_Poultry.SourceData_Poultry_MethaneEmissionsPotential_Data(), Table_SourceData_Poultry_MethaneEmissionsPotential[[#Headers],[Poultry class]], 0)} -> Meat chickens | P21: {=Common_InputFunctions.Utility_DisplayArrayInTable(SourceData_Poultry.SourceData_Poultry_MethaneEmissionsPotential_Data(), Table_SourceData_Poultry_MethaneEmissionsPotential[[#Headers],[Poultry class]], 0)} -> 0.36
A22: N2O MMS | D22: Table_DMD_j_k
A23: Enteric methane | D23: Dry matter digestibility
A24: =HYPERLINK("#'Calcs - Fert Lime'!A1", "Fertiliser & soil amendments") -> Fertiliser & soil amendments | D24: Layers | E24: Meat chicken growers | F24: Meat chicken breeders | G24: Other
A25: =HYPERLINK("#'Calcs - Residue mgmt - Crop'!A1", "Residue management - Crop") -> Residue management - Crop | D25: ='Input - MMS - Poultry'!$E$11 -> 0.1 | E25: ='Input - MMS - Poultry'!$F$11 -> 0.1 | F25: ='Input - MMS - Poultry'!$G$11 -> 0.1 | G25: ='Input - MMS - Poultry'!$H$11 -> 0.1 | H25: Fraction
A26: =HYPERLINK("#'Calcs - Residue mgmt - Pasture'!A1", "Residue management - Pasture") -> Residue management - Pasture | O26: Poultry manure management systems | R26: Poultry manure management systems - Stage 1 | U26: Poultry manure management systems - Stage 2
A27: =HYPERLINK("#'Calcs - Field burning'!A1", "Field burning - Crop") -> Field burning - Crop | D27: Table_A_j
A28: =HYPERLINK("#'Calcs - Fuel'!A1", "Fuel") -> Fuel | D28: Ash content of manure | O28: MMS | P28: Symbol and MMS | R28: MMS | S28: Symbol and MMS | U28: MMS | V28: Symbol and MMS
A29: =HYPERLINK("#'Calcs - Electricity'!A1", "Electricity") -> Electricity | D29: Layers | E29: Meat chicken growers | F29: Meat chicken breeders | G29: Other | O29: ='Constants - Livestock'!$E$21 -> Poultry manure with bedding | P29: ='Constants - Livestock'!$F$21 -> Poultry manure with bedding (m=10) | R29: ='Constants - Livestock'!$E$21 -> Poultry manure with bedding | S29: ='Constants - Livestock'!$F$21 -> Poultry manure with bedding (m=10) | U29: ='Constants - Livestock'!$E$15 -> Solid storage | V29: ='Constants - Livestock'!$F$15 -> Solid storage (m=4)
A30: =HYPERLINK("#'Calcs - Refrigerants'!A1", "Refrigerants") -> Refrigerants | D30: =$P$13 -> 0.18 | E30: =$Q$13 -> 0.15 | F30: =$R$13 -> 0.18 | G30: =$S$13 -> 0.15 | H30: Fraction | O30: ='Constants - Livestock'!$E$23 -> Belt manure removal | P30: ='Constants - Livestock'!$F$23 -> Belt manure removal (m=11a) | R30: ='Constants - Livestock'!$E$23 -> Belt manure removal | S30: ='Constants - Livestock'!$F$23 -> Belt manure removal (m=11a) | U30: ='Constants - Livestock'!$E$17 -> Composting (passive windrow) | V30: ='Constants - Livestock'!$F$17 -> Composting (passive windrow) (m=6)
A31: Waste | O31: ='Constants - Livestock'!$E$24 -> Manure stored in house | P31: ='Constants - Livestock'!$F$24 -> Manure stored in house (m=11b) | R31: ='Constants - Livestock'!$E$24 -> Manure stored in house | S31: ='Constants - Livestock'!$F$24 -> Manure stored in house (m=11b) | U31: ='Constants - Livestock'!$E$18 -> Digester / covered lagoons | V31: ='Constants - Livestock'!$F$18 -> Digester / covered lagoons (m=7)
A32: Freight and transport | D32: Table_VS_j_k | O32: ='Constants - Livestock'!$E$27 -> Pasture range and paddock | P32: ='Constants - Livestock'!$F$27 -> Pasture range and paddock (m=14) | R32: ='Constants - Livestock'!$E$27 -> Pasture range and paddock | S32: ='Constants - Livestock'!$F$27 -> Pasture range and paddock (m=14) | U32: ='Constants - Livestock'!$E$25 -> Direct processing | V32: ='Constants - Livestock'!$F$25 -> Direct processing (m=12)
A33: =HYPERLINK("#'Calcs - Scope 3'!A1", "Purchased goods scope 3") -> Purchased goods scope 3 | D33: Volatile solid production | O33: ='Constants - Livestock'!$E$15 -> Solid storage | P33: ='Constants - Livestock'!$F$15 -> Solid storage (m=4) | R33: No MMS | S33: No MMS | U33: ='Constants - Livestock'!$E$26 -> Direct application | V33: ='Constants - Livestock'!$F$26 -> Direct application (m=13)
D34: Layers | E34: Meat chicken growers | F34: Meat chicken breeders | G34: Other | O34: ='Constants - Livestock'!$E$17 -> Composting (passive windrow) | P34: ='Constants - Livestock'!$F$17 -> Composting (passive windrow) (m=6) | U34: No MMS | V34: No MMS
A35: APPENDICES | D35: {=ManureManagement_Poultry_Methane.VEERG_4_6_1_1__6_VolatileSolidProduction(D20,D25,D30)} -> 7.38 | E35: {=ManureManagement_Poultry_Methane.VEERG_4_6_1_1__6_VolatileSolidProduction(E20,E25,E30)} -> 7.65 | F35: {=ManureManagement_Poultry_Methane.VEERG_4_6_1_1__6_VolatileSolidProduction(F20,F25,F30)} -> 7.38 | G35: {=ManureManagement_Poultry_Methane.VEERG_4_6_1_1__6_VolatileSolidProduction(G20,G25,G30)} -> 7.65 | H35: =E11 -> kg/head/day | O35: ='Constants - Livestock'!$E$18 -> Digester / covered lagoons | P35: ='Constants - Livestock'!$F$18 -> Digester / covered lagoons (m=7)
A36: =HYPERLINK("#'Constants - Common'!A1", "Constants - Common") -> Constants - Common | O36: ='Constants - Livestock'!$E$25 -> Direct processing | P36: ='Constants - Livestock'!$F$25 -> Direct processing (m=12)
A37: =HYPERLINK("#'Constants - Cropping'!A1", "Constants - Cropping") -> Constants - Cropping | O37: ='Constants - Livestock'!$E$26 -> Direct application | P37: ='Constants - Livestock'!$F$26 -> Direct application (m=13)
A38: =HYPERLINK("#'Constants - Livestock'!A1", "Constants - Livestock") -> Constants - Livestock | O38: No MMS | P38: No MMS
A39: =HYPERLINK("#'Constants - Dairy'!A1", "Constants - Dairy") -> Constants - Dairy | D39: {=ManureManagement_Poultry_Methane.VEERG_4_6_1_1__3_Stage1MethaneProduction_Title()} -> Production of methane in treatment stage 1 MMS
A40: Sources & acknowledgements | D40: {=ManureManagement_Poultry_Methane.VEERG_4_6_1_1__3_Stage1MethaneProduction_Source()} -> VEERG 2026: 4.6.1.1, Equation (3)
D41: Function name | E41: {=Common_InputFunctions.Utility_DisplayFunctionName(F86)} -> =ManureManagement_Poultry_Methane.VEERG_4_6_1_1__3_Stage1MethaneProduction(D$35,D$59,F64,VLOOKUP($E86, $D$72:$E$80, 2, FALSE), $G$52)
O42: Poultry production systems
O44: Production system
D45: Variable | E45: {=ManureManagement_Poultry_Methane.VEERG_4_6_1_1__3_Stage1MethaneProduction_Variable()} -> MjkmT1 | O45: {=Common_InputFunctions.Utility_DisplayArrayInTable(SourceData_Poultry.SourceData_Poultry_ProductionSystems_Data(), Table_SourceData_Poultry_ProductionSystems[[#Headers],[Production system]], 0)} -> Free range
D46: Unit | E46: {=ManureManagement_Poultry_Methane.VEERG_4_6_1_1__3_Stage1MethaneProduction_Unit()} -> kg CH4/head/day | O46: {=Common_InputFunctions.Utility_DisplayArrayInTable(SourceData_Poultry.SourceData_Poultry_ProductionSystems_Data(), Table_SourceData_Poultry_ProductionSystems[[#Headers],[Production system]], 0)} -> Barn
O47: {=Common_InputFunctions.Utility_DisplayArrayInTable(SourceData_Poultry.SourceData_Poultry_ProductionSystems_Data(), Table_SourceData_Poultry_ProductionSystems[[#Headers],[Production system]], 0)} -> Cage
D48: {=ManureManagement_Poultry_Methane.VEERG_4_6_1_1__3_Stage1MethaneProduction_Arguments()} -> VSjk | E48: volatile solid production for poultry classes and subclasses : kg/head/day | G48: See Table_VS_j_k
D49: BOj | E49: emissions potential per class : m3 CH4/kg VS | G49: See Table_B_0_j
D50: MMSjmT1 | E50: fraction of manure in each primary system : fraction | G50: See Table_MMS_j_m_T-1
D51: MCFim | E51: methane conversion factor for temperature zone and MMS : fraction | G51: See Table_MCF_i_m | I51: Add temperate zone lookup | O51: {=SourceData_Poultry.SourceData_Poultry_MCF_Title()} -> Poultry - MCFs
D52: rho | E52: density of methane : kg/m3 | G52: =#REF! -> #REF! | O52: {=SourceData_Poultry.SourceData_Poultry_MCF_Source()} -> VEERG 2026: Table A.1.7.4: Poultry - MCFs
D53: i | E53: state | G53: {=Common_InputFunctions.Utility_LookupValueInTable('Input - Site'!$E$21,#REF!,#REF!)} -> #REF! | O53: {=SourceData_Poultry.SourceData_Poultry_MCF_Variation()} -> VARIATION ON SOURCE:
O54: Split NSW and ACT into separate states. Split QLD and NT into separate states.
O55: Included values for each state when 'All states' value is given.
D56: Table_B_0_j | O56: Added 'NIR definition' column with MMS names that match NIR definitions.
D57: Methane emissions potential per class | O57: Duplicated 'Poultry manure without litter' row for NIR MMS 'Belt manure removal' and 'Manure stored in house'
D58: Layers | E58: Meat chicken growers | F58: Meat chicken breeders | G58: Other
D59: =$P$20 -> 0.39 | E59: =$P$21 -> 0.36 | F59: =$P$21 -> 0.36 | G59: =$P$21 -> 0.36 | O59: MMS m | P59: All states | Q59: NSW | R59: ACT | S59: QLD | T59: NT | U59: VIC | V59: SA | W59: WA | X59: TAS | Y59: NIR definition
O60: {=Common_InputFunctions.Utility_DisplayArrayInTable(SourceData_Poultry.SourceData_Poultry_MCF_Data(), Table_SourceData_Poultry_MMSMCF[[#Headers],[MMS m]], 0)} -> Poultry manure with litter | P60: {=Common_InputFunctions.Utility_DisplayArrayInTable(SourceData_Poultry.SourceData_Poultry_MCF_Data(), Table_SourceData_Poultry_MMSMCF[[#Headers],[MMS m]], 0)} -> 0.015 | Q60: {=Common_InputFunctions.Utility_DisplayArrayInTable(SourceData_Poultry.SourceData_Poultry_MCF_Data(), Table_SourceData_Poultry_MMSMCF[[#Headers],[MMS m]], 0)} -> 0.015 | R60: {=Common_InputFunctions.Utility_DisplayArrayInTable(SourceData_Poultry.SourceData_Poultry_MCF_Data(), Table_SourceData_Poultry_MMSMCF[[#Headers],[MMS m]], 0)} -> 0.015 | S60: {=Common_InputFunctions.Utility_DisplayArrayInTable(SourceData_Poultry.SourceData_Poultry_MCF_Data(), Table_SourceData_Poultry_MMSMCF[[#Headers],[MMS m]], 0)} -> 0.015 | T60: {=Common_InputFunctions.Utility_DisplayArrayInTable(SourceData_Poultry.SourceData_Poultry_MCF_Data(), Table_SourceData_Poultry_MMSMCF[[#Headers],[MMS m]], 0)} -> 0.015 | U60: {=Common_InputFunctions.Utility_DisplayArrayInTable(SourceData_Poultry.SourceData_Poultry_MCF_Data(), Table_SourceData_Poultry_MMSMCF[[#Headers],[MMS m]], 0)} -> 0.015 | V60: {=Common_InputFunctions.Utility_DisplayArrayInTable(SourceData_Poultry.SourceData_Poultry_MCF_Data(), Table_SourceData_Poultry_MMSMCF[[#Headers],[MMS m]], 0)} -> 0.015 | ... Y60: {=Common_InputFunctions.Utility_DisplayArrayInTable(SourceData_Poultry.SourceData_Poultry_MCF_Data(), Table_SourceData_Poultry_MMSMCF[[#Headers],[MMS m]], 0)} -> Poultry manure with bedding
D61: Table_MMS_j_m_T-1 | O61: {=Common_InputFunctions.Utility_DisplayArrayInTable(SourceData_Poultry.SourceData_Poultry_MCF_Data(), Table_SourceData_Poultry_MMSMCF[[#Headers],[MMS m]], 0)} -> Poultry manure without litter | P61: {=Common_InputFunctions.Utility_DisplayArrayInTable(SourceData_Poultry.SourceData_Poultry_MCF_Data(), Table_SourceData_Poultry_MMSMCF[[#Headers],[MMS m]], 0)} -> 0.015 | Q61: {=Common_InputFunctions.Utility_DisplayArrayInTable(SourceData_Poultry.SourceData_Poultry_MCF_Data(), Table_SourceData_Poultry_MMSMCF[[#Headers],[MMS m]], 0)} -> 0.015 | R61: {=Common_InputFunctions.Utility_DisplayArrayInTable(SourceData_Poultry.SourceData_Poultry_MCF_Data(), Table_SourceData_Poultry_MMSMCF[[#Headers],[MMS m]], 0)} -> 0.015 | S61: {=Common_InputFunctions.Utility_DisplayArrayInTable(SourceData_Poultry.SourceData_Poultry_MCF_Data(), Table_SourceData_Poultry_MMSMCF[[#Headers],[MMS m]], 0)} -> 0.015 | T61: {=Common_InputFunctions.Utility_DisplayArrayInTable(SourceData_Poultry.SourceData_Poultry_MCF_Data(), Table_SourceData_Poultry_MMSMCF[[#Headers],[MMS m]], 0)} -> 0.015 | U61: {=Common_InputFunctions.Utility_DisplayArrayInTable(SourceData_Poultry.SourceData_Poultry_MCF_Data(), Table_SourceData_Poultry_MMSMCF[[#Headers],[MMS m]], 0)} -> 0.015 | V61: {=Common_InputFunctions.Utility_DisplayArrayInTable(SourceData_Poultry.SourceData_Poultry_MCF_Data(), Table_SourceData_Poultry_MMSMCF[[#Headers],[MMS m]], 0)} -> 0.015 | ... Y61: {=Common_InputFunctions.Utility_DisplayArrayInTable(SourceData_Poultry.SourceData_Poultry_MCF_Data(), Table_SourceData_Poultry_MMSMCF[[#Headers],[MMS m]], 0)} -> Belt manure removal
D62: Fraction of manure in stage 1 MMS | O62: {=Common_InputFunctions.Utility_DisplayArrayInTable(SourceData_Poultry.SourceData_Poultry_MCF_Data(), Table_SourceData_Poultry_MMSMCF[[#Headers],[MMS m]], 0)} -> Poultry manure without litter | P62: {=Common_InputFunctions.Utility_DisplayArrayInTable(SourceData_Poultry.SourceData_Poultry_MCF_Data(), Table_SourceData_Poultry_MMSMCF[[#Headers],[MMS m]], 0)} -> 0.015 | Q62: {=Common_InputFunctions.Utility_DisplayArrayInTable(SourceData_Poultry.SourceData_Poultry_MCF_Data(), Table_SourceData_Poultry_MMSMCF[[#Headers],[MMS m]], 0)} -> 0.015 | R62: {=Common_InputFunctions.Utility_DisplayArrayInTable(SourceData_Poultry.SourceData_Poultry_MCF_Data(), Table_SourceData_Poultry_MMSMCF[[#Headers],[MMS m]], 0)} -> 0.015 | S62: {=Common_InputFunctions.Utility_DisplayArrayInTable(SourceData_Poultry.SourceData_Poultry_MCF_Data(), Table_SourceData_Poultry_MMSMCF[[#Headers],[MMS m]], 0)} -> 0.015 | T62: {=Common_InputFunctions.Utility_DisplayArrayInTable(SourceData_Poultry.SourceData_Poultry_MCF_Data(), Table_SourceData_Poultry_MMSMCF[[#Headers],[MMS m]], 0)} -> 0.015 | U62: {=Common_InputFunctions.Utility_DisplayArrayInTable(SourceData_Poultry.SourceData_Poultry_MCF_Data(), Table_SourceData_Poultry_MMSMCF[[#Headers],[MMS m]], 0)} -> 0.015 | V62: {=Common_InputFunctions.Utility_DisplayArrayInTable(SourceData_Poultry.SourceData_Poultry_MCF_Data(), Table_SourceData_Poultry_MMSMCF[[#Headers],[MMS m]], 0)} -> 0.015 | ... Y62: {=Common_InputFunctions.Utility_DisplayArrayInTable(SourceData_Poultry.SourceData_Poultry_MCF_Data(), Table_SourceData_Poultry_MMSMCF[[#Headers],[MMS m]], 0)} -> Manure stored in house
D63: Production system | E63: Stage 1 MMS | F63: Layers | G63: Meat chicken growers | H63: Meat chicken breeders | I63: Other | O63: {=Common_InputFunctions.Utility_DisplayArrayInTable(SourceData_Poultry.SourceData_Poultry_MCF_Data(), Table_SourceData_Poultry_MMSMCF[[#Headers],[MMS m]], 0)} -> Pasture range and paddock | P63: {=Common_InputFunctions.Utility_DisplayArrayInTable(SourceData_Poultry.SourceData_Poultry_MCF_Data(), Table_SourceData_Poultry_MMSMCF[[#Headers],[MMS m]], 0)} -> n/a | Q63: {=Common_InputFunctions.Utility_DisplayArrayInTable(SourceData_Poultry.SourceData_Poultry_MCF_Data(), Table_SourceData_Poultry_MMSMCF[[#Headers],[MMS m]], 0)} -> 0.01 | R63: {=Common_InputFunctions.Utility_DisplayArrayInTable(SourceData_Poultry.SourceData_Poultry_MCF_Data(), Table_SourceData_Poultry_MMSMCF[[#Headers],[MMS m]], 0)} -> 0.01 | S63: {=Common_InputFunctions.Utility_DisplayArrayInTable(SourceData_Poultry.SourceData_Poultry_MCF_Data(), Table_SourceData_Poultry_MMSMCF[[#Headers],[MMS m]], 0)} -> 0.03 | T63: {=Common_InputFunctions.Utility_DisplayArrayInTable(SourceData_Poultry.SourceData_Poultry_MCF_Data(), Table_SourceData_Poultry_MMSMCF[[#Headers],[MMS m]], 0)} -> 0.03 | U63: {=Common_InputFunctions.Utility_DisplayArrayInTable(SourceData_Poultry.SourceData_Poultry_MCF_Data(), Table_SourceData_Poultry_MMSMCF[[#Headers],[MMS m]], 0)} -> 0.01 | V63: {=Common_InputFunctions.Utility_DisplayArrayInTable(SourceData_Poultry.SourceData_Poultry_MCF_Data(), Table_SourceData_Poultry_MMSMCF[[#Headers],[MMS m]], 0)} -> 0.01 | ... Y63: {=Common_InputFunctions.Utility_DisplayArrayInTable(SourceData_Poultry.SourceData_Poultry_MCF_Data(), Table_SourceData_Poultry_MMSMCF[[#Headers],[MMS m]], 0)} -> Pasture range and paddock
D64: ='Input - MMS - Poultry'!$E$24 -> Free range | E64: ='Input - MMS - Poultry'!$D$29 -> Pasture range and paddock | F64: ='Input - MMS - Poultry'!E29 -> 0.5 | G64: ='Input - MMS - Poultry'!F29 -> 0.5 | H64: ='Input - MMS - Poultry'!G29 -> 0.5 | I64: ='Input - MMS - Poultry'!H29 -> 0.5 | J64: Fraction | O64: {=Common_InputFunctions.Utility_DisplayArrayInTable(SourceData_Poultry.SourceData_Poultry_MCF_Data(), Table_SourceData_Poultry_MMSMCF[[#Headers],[MMS m]], 0)} -> Solid storage | P64: {=Common_InputFunctions.Utility_DisplayArrayInTable(SourceData_Poultry.SourceData_Poultry_MCF_Data(), Table_SourceData_Poultry_MMSMCF[[#Headers],[MMS m]], 0)} -> 0.02 | Q64: {=Common_InputFunctions.Utility_DisplayArrayInTable(SourceData_Poultry.SourceData_Poultry_MCF_Data(), Table_SourceData_Poultry_MMSMCF[[#Headers],[MMS m]], 0)} -> 0.02 | R64: {=Common_InputFunctions.Utility_DisplayArrayInTable(SourceData_Poultry.SourceData_Poultry_MCF_Data(), Table_SourceData_Poultry_MMSMCF[[#Headers],[MMS m]], 0)} -> 0.02 | S64: {=Common_InputFunctions.Utility_DisplayArrayInTable(SourceData_Poultry.SourceData_Poultry_MCF_Data(), Table_SourceData_Poultry_MMSMCF[[#Headers],[MMS m]], 0)} -> 0.02 | T64: {=Common_InputFunctions.Utility_DisplayArrayInTable(SourceData_Poultry.SourceData_Poultry_MCF_Data(), Table_SourceData_Poultry_MMSMCF[[#Headers],[MMS m]], 0)} -> 0.02 | U64: {=Common_InputFunctions.Utility_DisplayArrayInTable(SourceData_Poultry.SourceData_Poultry_MCF_Data(), Table_SourceData_Poultry_MMSMCF[[#Headers],[MMS m]], 0)} -> 0.02 | V64: {=Common_InputFunctions.Utility_DisplayArrayInTable(SourceData_Poultry.SourceData_Poultry_MCF_Data(), Table_SourceData_Poultry_MMSMCF[[#Headers],[MMS m]], 0)} -> 0.02 | ... Y64: {=Common_InputFunctions.Utility_DisplayArrayInTable(SourceData_Poultry.SourceData_Poultry_MCF_Data(), Table_SourceData_Poultry_MMSMCF[[#Headers],[MMS m]], 0)} -> Solid storage
D65: ='Input - MMS - Poultry'!$E$24 -> Free range | E65: ='Input - MMS - Poultry'!$D$30 -> Belt manure removal | F65: ='Input - MMS - Poultry'!E30 -> 0.5 | G65: ='Input - MMS - Poultry'!F30 -> 0.5 | H65: ='Input - MMS - Poultry'!G30 -> 0.5 | I65: ='Input - MMS - Poultry'!H30 -> 0.5 | J65: Fraction | O65: {=Common_InputFunctions.Utility_DisplayArrayInTable(SourceData_Poultry.SourceData_Poultry_MCF_Data(), Table_SourceData_Poultry_MMSMCF[[#Headers],[MMS m]], 0)} -> Composting (passive windrow) | P65: {=Common_InputFunctions.Utility_DisplayArrayInTable(SourceData_Poultry.SourceData_Poultry_MCF_Data(), Table_SourceData_Poultry_MMSMCF[[#Headers],[MMS m]], 0)} -> n/a | Q65: {=Common_InputFunctions.Utility_DisplayArrayInTable(SourceData_Poultry.SourceData_Poultry_MCF_Data(), Table_SourceData_Poultry_MMSMCF[[#Headers],[MMS m]], 0)} -> 0.01 | R65: {=Common_InputFunctions.Utility_DisplayArrayInTable(SourceData_Poultry.SourceData_Poultry_MCF_Data(), Table_SourceData_Poultry_MMSMCF[[#Headers],[MMS m]], 0)} -> 0.01 | S65: {=Common_InputFunctions.Utility_DisplayArrayInTable(SourceData_Poultry.SourceData_Poultry_MCF_Data(), Table_SourceData_Poultry_MMSMCF[[#Headers],[MMS m]], 0)} -> 0.01 | T65: {=Common_InputFunctions.Utility_DisplayArrayInTable(SourceData_Poultry.SourceData_Poultry_MCF_Data(), Table_SourceData_Poultry_MMSMCF[[#Headers],[MMS m]], 0)} -> 0.01 | U65: {=Common_InputFunctions.Utility_DisplayArrayInTable(SourceData_Poultry.SourceData_Poultry_MCF_Data(), Table_SourceData_Poultry_MMSMCF[[#Headers],[MMS m]], 0)} -> 0.01 | V65: {=Common_InputFunctions.Utility_DisplayArrayInTable(SourceData_Poultry.SourceData_Poultry_MCF_Data(), Table_SourceData_Poultry_MMSMCF[[#Headers],[MMS m]], 0)} -> 0.01 | ... Y65: {=Common_InputFunctions.Utility_DisplayArrayInTable(SourceData_Poultry.SourceData_Poultry_MCF_Data(), Table_SourceData_Poultry_MMSMCF[[#Headers],[MMS m]], 0)} -> Composting (passive windrow)
D66: ='Input - MMS - Poultry'!$D$18 -> Cage | E66: ='Input - MMS - Poultry'!$D$79 -> Belt manure removal | F66: ='Input - MMS - Poultry'!E79 -> 0.5 | G66: ='Input - MMS - Poultry'!F79 -> 0.5 | H66: ='Input - MMS - Poultry'!G79 -> 0.5 | I66: ='Input - MMS - Poultry'!H79 -> 0.5 | J66: Fraction | O66: {=Common_InputFunctions.Utility_DisplayArrayInTable(SourceData_Poultry.SourceData_Poultry_MCF_Data(), Table_SourceData_Poultry_MMSMCF[[#Headers],[MMS m]], 0)} -> Anaerobic digester / Covered pond | P66: {=Common_InputFunctions.Utility_DisplayArrayInTable(SourceData_Poultry.SourceData_Poultry_MCF_Data(), Table_SourceData_Poultry_MMSMCF[[#Headers],[MMS m]], 0)} -> 0.1 | Q66: {=Common_InputFunctions.Utility_DisplayArrayInTable(SourceData_Poultry.SourceData_Poultry_MCF_Data(), Table_SourceData_Poultry_MMSMCF[[#Headers],[MMS m]], 0)} -> 0.1 | R66: {=Common_InputFunctions.Utility_DisplayArrayInTable(SourceData_Poultry.SourceData_Poultry_MCF_Data(), Table_SourceData_Poultry_MMSMCF[[#Headers],[MMS m]], 0)} -> 0.1 | S66: {=Common_InputFunctions.Utility_DisplayArrayInTable(SourceData_Poultry.SourceData_Poultry_MCF_Data(), Table_SourceData_Poultry_MMSMCF[[#Headers],[MMS m]], 0)} -> 0.1 | T66: {=Common_InputFunctions.Utility_DisplayArrayInTable(SourceData_Poultry.SourceData_Poultry_MCF_Data(), Table_SourceData_Poultry_MMSMCF[[#Headers],[MMS m]], 0)} -> 0.1 | U66: {=Common_InputFunctions.Utility_DisplayArrayInTable(SourceData_Poultry.SourceData_Poultry_MCF_Data(), Table_SourceData_Poultry_MMSMCF[[#Headers],[MMS m]], 0)} -> 0.1 | V66: {=Common_InputFunctions.Utility_DisplayArrayInTable(SourceData_Poultry.SourceData_Poultry_MCF_Data(), Table_SourceData_Poultry_MMSMCF[[#Headers],[MMS m]], 0)} -> 0.1 | ... Y66: {=Common_InputFunctions.Utility_DisplayArrayInTable(SourceData_Poultry.SourceData_Poultry_MCF_Data(), Table_SourceData_Poultry_MMSMCF[[#Headers],[MMS m]], 0)} -> Digester / covered lagoons
D67: ='Input - MMS - Poultry'!$D$18 -> Cage | E67: ='Input - MMS - Poultry'!$D$80 -> Poultry manure with bedding | F67: ='Input - MMS - Poultry'!E80 -> 0.5 | G67: ='Input - MMS - Poultry'!F80 -> 0.5 | H67: ='Input - MMS - Poultry'!G80 -> 0.5 | I67: ='Input - MMS - Poultry'!H80 -> 0.5 | J67: Fraction | O67: {=Common_InputFunctions.Utility_DisplayArrayInTable(SourceData_Poultry.SourceData_Poultry_MCF_Data(), Table_SourceData_Poultry_MMSMCF[[#Headers],[MMS m]], 0)} -> Direct processing | P67: {=Common_InputFunctions.Utility_DisplayArrayInTable(SourceData_Poultry.SourceData_Poultry_MCF_Data(), Table_SourceData_Poultry_MMSMCF[[#Headers],[MMS m]], 0)} -> 0 | Q67: {=Common_InputFunctions.Utility_DisplayArrayInTable(SourceData_Poultry.SourceData_Poultry_MCF_Data(), Table_SourceData_Poultry_MMSMCF[[#Headers],[MMS m]], 0)} -> 0 | R67: {=Common_InputFunctions.Utility_DisplayArrayInTable(SourceData_Poultry.SourceData_Poultry_MCF_Data(), Table_SourceData_Poultry_MMSMCF[[#Headers],[MMS m]], 0)} -> 0 | S67: {=Common_InputFunctions.Utility_DisplayArrayInTable(SourceData_Poultry.SourceData_Poultry_MCF_Data(), Table_SourceData_Poultry_MMSMCF[[#Headers],[MMS m]], 0)} -> 0 | T67: {=Common_InputFunctions.Utility_DisplayArrayInTable(SourceData_Poultry.SourceData_Poultry_MCF_Data(), Table_SourceData_Poultry_MMSMCF[[#Headers],[MMS m]], 0)} -> 0 | U67: {=Common_InputFunctions.Utility_DisplayArrayInTable(SourceData_Poultry.SourceData_Poultry_MCF_Data(), Table_SourceData_Poultry_MMSMCF[[#Headers],[MMS m]], 0)} -> 0 | V67: {=Common_InputFunctions.Utility_DisplayArrayInTable(SourceData_Poultry.SourceData_Poultry_MCF_Data(), Table_SourceData_Poultry_MMSMCF[[#Headers],[MMS m]], 0)} -> 0 | ... Y67: {=Common_InputFunctions.Utility_DisplayArrayInTable(SourceData_Poultry.SourceData_Poultry_MCF_Data(), Table_SourceData_Poultry_MMSMCF[[#Headers],[MMS m]], 0)} -> Direct processing
O68: {=Common_InputFunctions.Utility_DisplayArrayInTable(SourceData_Poultry.SourceData_Poultry_MCF_Data(), Table_SourceData_Poultry_MMSMCF[[#Headers],[MMS m]], 0)} -> Direct application to soil | P68: {=Common_InputFunctions.Utility_DisplayArrayInTable(SourceData_Poultry.SourceData_Poultry_MCF_Data(), Table_SourceData_Poultry_MMSMCF[[#Headers],[MMS m]], 0)} -> 0 | Q68: {=Common_InputFunctions.Utility_DisplayArrayInTable(SourceData_Poultry.SourceData_Poultry_MCF_Data(), Table_SourceData_Poultry_MMSMCF[[#Headers],[MMS m]], 0)} -> 0 | R68: {=Common_InputFunctions.Utility_DisplayArrayInTable(SourceData_Poultry.SourceData_Poultry_MCF_Data(), Table_SourceData_Poultry_MMSMCF[[#Headers],[MMS m]], 0)} -> 0 | S68: {=Common_InputFunctions.Utility_DisplayArrayInTable(SourceData_Poultry.SourceData_Poultry_MCF_Data(), Table_SourceData_Poultry_MMSMCF[[#Headers],[MMS m]], 0)} -> 0 | T68: {=Common_InputFunctions.Utility_DisplayArrayInTable(SourceData_Poultry.SourceData_Poultry_MCF_Data(), Table_SourceData_Poultry_MMSMCF[[#Headers],[MMS m]], 0)} -> 0 | U68: {=Common_InputFunctions.Utility_DisplayArrayInTable(SourceData_Poultry.SourceData_Poultry_MCF_Data(), Table_SourceData_Poultry_MMSMCF[[#Headers],[MMS m]], 0)} -> 0 | V68: {=Common_InputFunctions.Utility_DisplayArrayInTable(SourceData_Poultry.SourceData_Poultry_MCF_Data(), Table_SourceData_Poultry_MMSMCF[[#Headers],[MMS m]], 0)} -> 0 | ... Y68: {=Common_InputFunctions.Utility_DisplayArrayInTable(SourceData_Poultry.SourceData_Poultry_MCF_Data(), Table_SourceData_Poultry_MMSMCF[[#Headers],[MMS m]], 0)} -> Direct application
D69: Table_MCF_i_m
D70: Methane conversion factor for state
D71: MMS | E71: MCFim
D72: =$Y$60 -> Poultry manure with bedding | E72: {=CommonLivestock_InputFunctions.Livestock_LookupMCFState(D72,Table_SourceData_Poultry_MMSMCF[NIR definition],$G$53,Table_SourceData_Poultry_MMSMCF[#Headers],Table_SourceData_Poultry_MMSMCF[])} -> #REF! | O72: {=SourceData_Poultry.SourceData_Poultry_VSL_Title()} -> Poultry - Fraction of volatile solids lost in the primary MMS
D73: =$Y$61 -> Belt manure removal | E73: {=CommonLivestock_InputFunctions.Livestock_LookupMCFState(D73,Table_SourceData_Poultry_MMSMCF[NIR definition],$G$53,Table_SourceData_Poultry_MMSMCF[#Headers],Table_SourceData_Poultry_MMSMCF[])} -> #REF! | O73: {=SourceData_Poultry.SourceData_Poultry_VSL_Source()} -> VEERG 2026: 4.6.2.3 CONSTANT
D74: =$Y$62 -> Manure stored in house | E74: {=CommonLivestock_InputFunctions.Livestock_LookupMCFState(D74,Table_SourceData_Poultry_MMSMCF[NIR definition],$G$53,Table_SourceData_Poultry_MMSMCF[#Headers],Table_SourceData_Poultry_MMSMCF[])} -> #REF! | O74: {=SourceData_Poultry.SourceData_Poultry_VSL_Variation()} -> VARIATION ON SOURCE: Table generated from line items. Added 'NIR definition column'.
D75: =$Y$63 -> Pasture range and paddock | E75: {=CommonLivestock_InputFunctions.Livestock_LookupMCFState(D75,Table_SourceData_Poultry_MMSMCF[NIR definition],$G$53,Table_SourceData_Poultry_MMSMCF[#Headers],Table_SourceData_Poultry_MMSMCF[])} -> #REF! | O75: Couldn't find these numbers in NIR - what is the source?
D76: =$Y$64 -> Solid storage | E76: {=CommonLivestock_InputFunctions.Livestock_LookupMCFState(D76,Table_SourceData_Poultry_MMSMCF[NIR definition],$G$53,Table_SourceData_Poultry_MMSMCF[#Headers],Table_SourceData_Poultry_MMSMCF[])} -> #REF! | O76: MMS | P76: VSL | Q76: NIR definition
D77: =$Y$65 -> Composting (passive windrow) | E77: {=CommonLivestock_InputFunctions.Livestock_LookupMCFState(D77,Table_SourceData_Poultry_MMSMCF[NIR definition],$G$53,Table_SourceData_Poultry_MMSMCF[#Headers],Table_SourceData_Poultry_MMSMCF[])} -> #REF! | O77: {=Common_InputFunctions.Utility_DisplayArrayInTable(SourceData_Poultry.SourceData_Poultry_VSL_Data(), Table_SourceData_Poultry_MMSVSL[[#Headers],[MMS]], 0)} -> Poultry manure with litter | P77: {=Common_InputFunctions.Utility_DisplayArrayInTable(SourceData_Poultry.SourceData_Poultry_VSL_Data(), Table_SourceData_Poultry_MMSVSL[[#Headers],[MMS]], 0)} -> 0.85 | Q77: {=Common_InputFunctions.Utility_DisplayArrayInTable(SourceData_Poultry.SourceData_Poultry_VSL_Data(), Table_SourceData_Poultry_MMSVSL[[#Headers],[MMS]], 0)} -> Poultry manure with bedding
D78: =$Y$66 -> Digester / covered lagoons | E78: {=CommonLivestock_InputFunctions.Livestock_LookupMCFState(D78,Table_SourceData_Poultry_MMSMCF[NIR definition],$G$53,Table_SourceData_Poultry_MMSMCF[#Headers],Table_SourceData_Poultry_MMSMCF[])} -> #REF! | O78: {=Common_InputFunctions.Utility_DisplayArrayInTable(SourceData_Poultry.SourceData_Poultry_VSL_Data(), Table_SourceData_Poultry_MMSVSL[[#Headers],[MMS]], 0)} -> Poultry manure without litter - stored in house | P78: {=Common_InputFunctions.Utility_DisplayArrayInTable(SourceData_Poultry.SourceData_Poultry_VSL_Data(), Table_SourceData_Poultry_MMSVSL[[#Headers],[MMS]], 0)} -> 0.8 | Q78: {=Common_InputFunctions.Utility_DisplayArrayInTable(SourceData_Poultry.SourceData_Poultry_VSL_Data(), Table_SourceData_Poultry_MMSVSL[[#Headers],[MMS]], 0)} -> Manure stored in house
D79: =$Y$67 -> Direct processing | E79: {=CommonLivestock_InputFunctions.Livestock_LookupMCFState(D79,Table_SourceData_Poultry_MMSMCF[NIR definition],$G$53,Table_SourceData_Poultry_MMSMCF[#Headers],Table_SourceData_Poultry_MMSMCF[])} -> #REF! | O79: {=Common_InputFunctions.Utility_DisplayArrayInTable(SourceData_Poultry.SourceData_Poultry_VSL_Data(), Table_SourceData_Poultry_MMSVSL[[#Headers],[MMS]], 0)} -> Poultry manure without litter - belt removal | P79: {=Common_InputFunctions.Utility_DisplayArrayInTable(SourceData_Poultry.SourceData_Poultry_VSL_Data(), Table_SourceData_Poultry_MMSVSL[[#Headers],[MMS]], 0)} -> 1 | Q79: {=Common_InputFunctions.Utility_DisplayArrayInTable(SourceData_Poultry.SourceData_Poultry_VSL_Data(), Table_SourceData_Poultry_MMSVSL[[#Headers],[MMS]], 0)} -> Belt manure removal
D80: =$Y$68 -> Direct application | E80: {=CommonLivestock_InputFunctions.Livestock_LookupMCFState(D80,Table_SourceData_Poultry_MMSMCF[NIR definition],$G$53,Table_SourceData_Poultry_MMSMCF[#Headers],Table_SourceData_Poultry_MMSMCF[])} -> #REF!
D81: No MMS | E81: 0
D83: Table_M_j_k_m_T-1
D84: Production of methane in stage 1 MMS
D85: Production system | E85: Stage 1 MMS | F85: Layers | G85: Meat chicken growers | H85: Meat chicken breeders | I85: Other
D86: ='Input - MMS - Poultry'!$E$24 -> Free range | E86: ='Input - MMS - Poultry'!$D$29 -> Pasture range and paddock | F86: {=ManureManagement_Poultry_Methane.VEERG_4_6_1_1__3_Stage1MethaneProduction(D$35,D$59,F64,VLOOKUP($E86, $D$72:$E$80, 2, FALSE), $G$52)} -> #REF! | G86: {=ManureManagement_Poultry_Methane.VEERG_4_6_1_1__3_Stage1MethaneProduction(E$35,E$59,G64,VLOOKUP($E86, $D$72:$E$80, 2, FALSE), $G$52)} -> #REF! | H86: {=ManureManagement_Poultry_Methane.VEERG_4_6_1_1__3_Stage1MethaneProduction(F$35,F$59,H64,VLOOKUP($E86, $D$72:$E$80, 2, FALSE), $G$52)} -> #REF! | I86: {=ManureManagement_Poultry_Methane.VEERG_4_6_1_1__3_Stage1MethaneProduction(G$35,G$59,I64,VLOOKUP($E86, $D$72:$E$80, 2, FALSE), $G$52)} -> #REF! | J86: Fraction
D87: ='Input - MMS - Poultry'!$E$24 -> Free range | E87: ='Input - MMS - Poultry'!$D$30 -> Belt manure removal | F87: {=ManureManagement_Poultry_Methane.VEERG_4_6_1_1__3_Stage1MethaneProduction(D$35,D$59,F65,VLOOKUP($E87, $D$72:$E$80, 2, FALSE), $G$52)} -> #REF! | G87: {=ManureManagement_Poultry_Methane.VEERG_4_6_1_1__3_Stage1MethaneProduction(E$35,E$59,G65,VLOOKUP($E87, $D$72:$E$80, 2, FALSE), $G$52)} -> #REF! | H87: {=ManureManagement_Poultry_Methane.VEERG_4_6_1_1__3_Stage1MethaneProduction(F$35,F$59,H65,VLOOKUP($E87, $D$72:$E$80, 2, FALSE), $G$52)} -> #REF! | I87: {=ManureManagement_Poultry_Methane.VEERG_4_6_1_1__3_Stage1MethaneProduction(G$35,G$59,I65,VLOOKUP($E87, $D$72:$E$80, 2, FALSE), $G$52)} -> #REF! | J87: Fraction
D88: ='Input - MMS - Poultry'!$D$18 -> Cage | E88: ='Input - MMS - Poultry'!$D$79 -> Belt manure removal | F88: {=ManureManagement_Poultry_Methane.VEERG_4_6_1_1__3_Stage1MethaneProduction(D$35,D$59,F66,VLOOKUP($E88, $D$72:$E$80, 2, FALSE), $G$52)} -> #REF! | G88: {=ManureManagement_Poultry_Methane.VEERG_4_6_1_1__3_Stage1MethaneProduction(E$35,E$59,G66,VLOOKUP($E88, $D$72:$E$80, 2, FALSE), $G$52)} -> #REF! | H88: {=ManureManagement_Poultry_Methane.VEERG_4_6_1_1__3_Stage1MethaneProduction(F$35,F$59,H66,VLOOKUP($E88, $D$72:$E$80, 2, FALSE), $G$52)} -> #REF! | I88: {=ManureManagement_Poultry_Methane.VEERG_4_6_1_1__3_Stage1MethaneProduction(G$35,G$59,I66,VLOOKUP($E88, $D$72:$E$80, 2, FALSE), $G$52)} -> #REF! | J88: Fraction
D89: ='Input - MMS - Poultry'!$D$18 -> Cage | E89: ='Input - MMS - Poultry'!$D$80 -> Poultry manure with bedding | F89: {=ManureManagement_Poultry_Methane.VEERG_4_6_1_1__3_Stage1MethaneProduction(D$35,D$59,F67,VLOOKUP($E89, $D$72:$E$80, 2, FALSE), $G$52)} -> #REF! | G89: {=ManureManagement_Poultry_Methane.VEERG_4_6_1_1__3_Stage1MethaneProduction(E$35,E$59,G67,VLOOKUP($E89, $D$72:$E$80, 2, FALSE), $G$52)} -> #REF! | H89: {=ManureManagement_Poultry_Methane.VEERG_4_6_1_1__3_Stage1MethaneProduction(F$35,F$59,H67,VLOOKUP($E89, $D$72:$E$80, 2, FALSE), $G$52)} -> #REF! | I89: {=ManureManagement_Poultry_Methane.VEERG_4_6_1_1__3_Stage1MethaneProduction(G$35,G$59,I67,VLOOKUP($E89, $D$72:$E$80, 2, FALSE), $G$52)} -> #REF! | J89: Fraction
D93: {=ManureManagement_Poultry_Methane.VEERG_4_6_1_1__5_VolatileSolidsTransferredToStage2_Title()} -> Volatile solids transferred to treatment stage 2 MMS
D94: {=ManureManagement_Poultry_Methane.VEERG_4_6_1_1__5_VolatileSolidsTransferredToStage2_Source()} -> VEERG 2026: 4.6.1.1, Equation (5)
D95: Function name | E95: {=Common_InputFunctions.Utility_DisplayFunctionName(F117)} -> =ManureManagement_Poultry_Methane.VEERG_4_6_1_1__5_VolatileSolidsTransferredToStage2(D$35,F64,$F109)
D99: Variable | E99: {=ManureManagement_Poultry_Methane.VEERG_4_6_1_1__5_VolatileSolidsTransferredToStage2_Variable()} -> VSTjkmT2
D100: Unit | E100: {=ManureManagement_Poultry_Methane.VEERG_4_6_1_1__5_VolatileSolidsTransferredToStage2_Unit()} -> kg VS
D102: {=ManureManagement_Poultry_Methane.VEERG_4_6_1_1__5_VolatileSolidsTransferredToStage2_Arguments()} -> VSjk | E102: volatile solid production for poultry classes and subclasses : kg/head/day | G102: see Table_VS_j_k
D103: MMSjmT1 | E103: fraction of manure in each primary system : fraction | G103: see Table_MMS_j_m_T-1
D104: VSLmT1 | E104: fraction of volatile solids lost during storage in the primary system : fraction | G104: see Table_VSL_m_T-1
D106: Table_VSL_m_T-1
D107: Fraction volatile solids list in stage 1 MMS
D108: Production system | E108: Stage 1 MMS | F108: VSLmT=1
D109: ='Input - MMS - Poultry'!$E$24 -> Free range | E109: ='Input - MMS - Poultry'!$D$29 -> Pasture range and paddock | F109: {=IF(E109="Pasture range and paddock", "N/A", Common_InputFunctions.Utility_LookupValueInTableNumber(E109, Table_SourceData_Poultry_MMSVSL[NIR definition],Table_SourceData_Poultry_MMSVSL[VSL]))} -> N/A | G109: Fraction
D110: ='Input - MMS - Poultry'!$E$24 -> Free range | E110: ='Input - MMS - Poultry'!$D$30 -> Belt manure removal | F110: {=IF(E110="Pasture range and paddock", "N/A", Common_InputFunctions.Utility_LookupValueInTableNumber(E110, Table_SourceData_Poultry_MMSVSL[NIR definition],Table_SourceData_Poultry_MMSVSL[VSL]))} -> 1 | G110: Fraction | H110: belt removal VLS insinuates that there is no secondary MMS because al volatile solids are removed!!!!
D111: ='Input - MMS - Poultry'!$D$18 -> Cage | E111: ='Input - MMS - Poultry'!$D$79 -> Belt manure removal | F111: {=IF(E111="Pasture range and paddock", "N/A", Common_InputFunctions.Utility_LookupValueInTableNumber(E111, Table_SourceData_Poultry_MMSVSL[NIR definition],Table_SourceData_Poultry_MMSVSL[VSL]))} -> 1 | G111: Fraction | H111: What happens to the manure after belt reoval?
...

Sheet Input - Herd - Swine
A1: #VALUE! | C1: Input - Herd - Swine
A3: Home
A4: =HYPERLINK("#'Results'!A1", "Results") -> Results
D5: Head count
A6: INPUTS
A7: =HYPERLINK("#'Input - Site'!A1", "Site") -> Site | E7: Boars | F7: Sows | G7: Gilts | H7: Suckers | I7: Weaners | J7: Growers | K7: Slaughter pigs
A8: =HYPERLINK("#'Input - Production'!A1", "Production and outputs") -> Production and outputs | D8: Month | E8: Dj=1 | F8: Dj=2 | G8: Dj=3 | H8: Dj=4 | I8: Dj=4 | J8: Dj=4 | K8: Dj=4
A9: =HYPERLINK("#'Input - Herd - Dairy'!A1", "Herd - Dairy") -> Herd - Dairy | D9: =TEXT('Input - Site'!$E$12,"mmmm yyyy") -> January 2024 | E9: 120 | F9: 220 | G9: 320 | H9: 420 | I9: 520 | J9: 620 | K9: 720 | L9: Head
A10: =HYPERLINK("#'Input - Feed - Dairy'!A1", "Purchased feed - Livestock") -> Purchased feed - Livestock | D10: =TEXT(EDATE('Input - Site'!$E$12, 1),"mmmm yyyy") -> February 2024 | E10: 120 | F10: 220 | G10: 320 | H10: 420 | I10: 520 | J10: 620 | K10: 720 | L10: Head
A11: =HYPERLINK("#'Input - Herd - Feedlot'!A1", "Herd - Feedlot") -> Herd - Feedlot | D11: =TEXT(EDATE('Input - Site'!$E$12, 2),"mmmm yyyy") -> March 2024 | E11: 130 | F11: 230 | G11: 330 | H11: 430 | I11: 530 | J11: 630 | K11: 730 | L11: Head
A12: =HYPERLINK("#'Input - Pasture'!A1", "Pasture") -> Pasture | D12: =TEXT(EDATE('Input - Site'!$E$12, 3),"mmmm yyyy") -> April 2024 | E12: 130 | F12: 230 | G12: 330 | H12: 430 | I12: 530 | J12: 630 | K12: 730 | L12: Head
A13: =HYPERLINK("#'Input - Grains'!A1", "Crop - Grains") -> Crop - Grains | D13: =TEXT(EDATE('Input - Site'!$E$12, 4),"mmmm yyyy") -> May 2024 | E13: 130 | F13: 230 | G13: 330 | H13: 430 | I13: 530 | J13: 630 | K13: 730 | L13: Head
A14: =HYPERLINK("#'Input - Fert Lime Chem'!A1", "Fertiliser, Lime & Chemicals") -> Fertiliser, Lime & Chemicals | D14: =TEXT(EDATE('Input - Site'!$E$12, 5),"mmmm yyyy") -> June 2024 | E14: 140 | F14: 240 | G14: 340 | H14: 440 | I14: 540 | J14: 640 | K14: 740 | L14: Head
A15: =HYPERLINK("#'Input - Fuel & Energy'!A1", "Electricity and fuel") -> Electricity and fuel | D15: =TEXT(EDATE('Input - Site'!$E$12, 6),"mmmm yyyy") -> July 2024 | E15: 140 | F15: 230 | G15: 340 | H15: 440 | I15: 540 | J15: 640 | K15: 740 | L15: Head
A16: Waste | D16: =TEXT(EDATE('Input - Site'!$E$12, 7),"mmmm yyyy") -> August 2024 | E16: 140 | F16: 240 | G16: 340 | H16: 440 | I16: 540 | J16: 640 | K16: 740 | L16: Head
A17: Freight and transport | D17: =TEXT(EDATE('Input - Site'!$E$12, 8),"mmmm yyyy") -> September 2024 | E17: 110 | F17: 210 | G17: 310 | H17: 410 | I17: 510 | J17: 610 | K17: 710 | L17: Head
A18: =HYPERLINK("#'Input - Other Farm Inputs'!A1", "Other farm inputs") -> Other farm inputs | D18: =TEXT(EDATE('Input - Site'!$E$12, 9),"mmmm yyyy") -> October 2024 | E18: 110 | F18: 210 | G18: 310 | H18: 410 | I18: 510 | J18: 610 | K18: 710 | L18: Head
A19: =HYPERLINK("#'Input - Data quality'!A1", "Data quality") -> Data quality | D19: =TEXT(EDATE('Input - Site'!$E$12, 10),"mmmm yyyy") -> November 2024 | E19: 110 | F19: 210 | G19: 310 | H19: 410 | I19: 510 | J19: 610 | K19: 710 | L19: Head
D20: =TEXT(EDATE('Input - Site'!$E$12, 11),"mmmm yyyy") -> December 2024 | E20: 120 | F20: 220 | G20: 320 | H20: 420 | I20: 520 | J20: 620 | K20: 720 | L20: Head
A21: CALCULATIONS
A22: N2O MMS
A23: Enteric methane | D23: Duration of stay
A24: =HYPERLINK("#'Calcs - Fert Lime'!A1", "Fertiliser & soil amendments") -> Fertiliser & soil amendments
A25: =HYPERLINK("#'Calcs - Residue mgmt - Crop'!A1", "Residue management - Crop") -> Residue management - Crop | E25: Boars | F25: Sows | G25: Gilts | H25: Suckers | I25: Weaners | J25: Growers | K25: Slaughter pigs
A26: =HYPERLINK("#'Calcs - Residue mgmt - Pasture'!A1", "Residue management - Pasture") -> Residue management - Pasture | D26: Month | E26: Dj=1 | F26: Dj=2 | G26: Dj=3 | H26: Dj=4 | I26: Dj=4 | J26: Dj=4 | K26: Dj=4
A27: =HYPERLINK("#'Calcs - Field burning'!A1", "Field burning - Crop") -> Field burning - Crop | D27: =TEXT('Input - Site'!$E$12,"mmmm yyyy") -> January 2024 | E27: =DAY(EOMONTH($D27, 0)) -> 31 | F27: =DAY(EOMONTH($D27, 0)) -> 31 | G27: =DAY(EOMONTH($D27, 0)) -> 31 | H27: =DAY(EOMONTH($D27, 0)) -> 31 | I27: =DAY(EOMONTH($D27, 0)) -> 31 | J27: =DAY(EOMONTH($D27, 0)) -> 31 | K27: =DAY(EOMONTH($D27, 0)) -> 31 | L27: Days
A28: =HYPERLINK("#'Calcs - Fuel'!A1", "Fuel") -> Fuel | D28: =TEXT(EDATE('Input - Site'!$E$12, 1),"mmmm yyyy") -> February 2024 | E28: =DAY(EOMONTH($D28, 0)) -> 29 | F28: =DAY(EOMONTH($D28, 0)) -> 29 | G28: =DAY(EOMONTH($D28, 0)) -> 29 | H28: =DAY(EOMONTH($D28, 0)) -> 29 | I28: =DAY(EOMONTH($D28, 0)) -> 29 | J28: =DAY(EOMONTH($D28, 0)) -> 29 | K28: =DAY(EOMONTH($D28, 0)) -> 29 | L28: Days
A29: =HYPERLINK("#'Calcs - Electricity'!A1", "Electricity") -> Electricity | D29: =TEXT(EDATE('Input - Site'!$E$12, 2),"mmmm yyyy") -> March 2024 | E29: =DAY(EOMONTH($D29, 0)) -> 31 | F29: =DAY(EOMONTH($D29, 0)) -> 31 | G29: =DAY(EOMONTH($D29, 0)) -> 31 | H29: =DAY(EOMONTH($D29, 0)) -> 31 | I29: =DAY(EOMONTH($D29, 0)) -> 31 | J29: =DAY(EOMONTH($D29, 0)) -> 31 | K29: =DAY(EOMONTH($D29, 0)) -> 31 | L29: Days
A30: =HYPERLINK("#'Calcs - Refrigerants'!A1", "Refrigerants") -> Refrigerants | D30: =TEXT(EDATE('Input - Site'!$E$12, 3),"mmmm yyyy") -> April 2024 | E30: =DAY(EOMONTH($D30, 0)) -> 30 | F30: =DAY(EOMONTH($D30, 0)) -> 30 | G30: =DAY(EOMONTH($D30, 0)) -> 30 | H30: =DAY(EOMONTH($D30, 0)) -> 30 | I30: =DAY(EOMONTH($D30, 0)) -> 30 | J30: =DAY(EOMONTH($D30, 0)) -> 30 | K30: =DAY(EOMONTH($D30, 0)) -> 30 | L30: Days
A31: Waste | D31: =TEXT(EDATE('Input - Site'!$E$12, 4),"mmmm yyyy") -> May 2024 | E31: =DAY(EOMONTH($D31, 0)) -> 31 | F31: =DAY(EOMONTH($D31, 0)) -> 31 | G31: =DAY(EOMONTH($D31, 0)) -> 31 | H31: =DAY(EOMONTH($D31, 0)) -> 31 | I31: =DAY(EOMONTH($D31, 0)) -> 31 | J31: =DAY(EOMONTH($D31, 0)) -> 31 | K31: =DAY(EOMONTH($D31, 0)) -> 31 | L31: Days
A32: Freight and transport | D32: =TEXT(EDATE('Input - Site'!$E$12, 5),"mmmm yyyy") -> June 2024 | E32: =DAY(EOMONTH($D32, 0)) -> 30 | F32: =DAY(EOMONTH($D32, 0)) -> 30 | G32: =DAY(EOMONTH($D32, 0)) -> 30 | H32: =DAY(EOMONTH($D32, 0)) -> 30 | I32: =DAY(EOMONTH($D32, 0)) -> 30 | J32: =DAY(EOMONTH($D32, 0)) -> 30 | K32: =DAY(EOMONTH($D32, 0)) -> 30 | L32: Days
A33: =HYPERLINK("#'Calcs - Scope 3'!A1", "Purchased goods scope 3") -> Purchased goods scope 3 | D33: =TEXT(EDATE('Input - Site'!$E$12, 6),"mmmm yyyy") -> July 2024 | E33: =DAY(EOMONTH($D33, 0)) -> 31 | F33: =DAY(EOMONTH($D33, 0)) -> 31 | G33: =DAY(EOMONTH($D33, 0)) -> 31 | H33: =DAY(EOMONTH($D33, 0)) -> 31 | I33: =DAY(EOMONTH($D33, 0)) -> 31 | J33: =DAY(EOMONTH($D33, 0)) -> 31 | K33: =DAY(EOMONTH($D33, 0)) -> 31 | L33: Days
D34: =TEXT(EDATE('Input - Site'!$E$12, 7),"mmmm yyyy") -> August 2024 | E34: =DAY(EOMONTH($D34, 0)) -> 31 | F34: =DAY(EOMONTH($D34, 0)) -> 31 | G34: =DAY(EOMONTH($D34, 0)) -> 31 | H34: =DAY(EOMONTH($D34, 0)) -> 31 | I34: =DAY(EOMONTH($D34, 0)) -> 31 | J34: =DAY(EOMONTH($D34, 0)) -> 31 | K34: =DAY(EOMONTH($D34, 0)) -> 31 | L34: Days
A35: APPENDICES | D35: =TEXT(EDATE('Input - Site'!$E$12, 8),"mmmm yyyy") -> September 2024 | E35: =DAY(EOMONTH($D35, 0)) -> 30 | F35: =DAY(EOMONTH($D35, 0)) -> 30 | G35: =DAY(EOMONTH($D35, 0)) -> 30 | H35: =DAY(EOMONTH($D35, 0)) -> 30 | I35: =DAY(EOMONTH($D35, 0)) -> 30 | J35: =DAY(EOMONTH($D35, 0)) -> 30 | K35: =DAY(EOMONTH($D35, 0)) -> 30 | L35: Days
A36: =HYPERLINK("#'Constants - Common'!A1", "Constants - Common") -> Constants - Common | D36: =TEXT(EDATE('Input - Site'!$E$12, 9),"mmmm yyyy") -> October 2024 | E36: =DAY(EOMONTH($D36, 0)) -> 31 | F36: =DAY(EOMONTH($D36, 0)) -> 31 | G36: =DAY(EOMONTH($D36, 0)) -> 31 | H36: =DAY(EOMONTH($D36, 0)) -> 31 | I36: =DAY(EOMONTH($D36, 0)) -> 31 | J36: =DAY(EOMONTH($D36, 0)) -> 31 | K36: =DAY(EOMONTH($D36, 0)) -> 31 | L36: Days
A37: =HYPERLINK("#'Constants - Cropping'!A1", "Constants - Cropping") -> Constants - Cropping | D37: =TEXT(EDATE('Input - Site'!$E$12, 10),"mmmm yyyy") -> November 2024 | E37: =DAY(EOMONTH($D37, 0)) -> 30 | F37: =DAY(EOMONTH($D37, 0)) -> 30 | G37: =DAY(EOMONTH($D37, 0)) -> 30 | H37: =DAY(EOMONTH($D37, 0)) -> 30 | I37: =DAY(EOMONTH($D37, 0)) -> 30 | J37: =DAY(EOMONTH($D37, 0)) -> 30 | K37: =DAY(EOMONTH($D37, 0)) -> 30 | L37: Days
A38: =HYPERLINK("#'Constants - Livestock'!A1", "Constants - Livestock") -> Constants - Livestock | D38: =TEXT(EDATE('Input - Site'!$E$12, 11),"mmmm yyyy") -> December 2024 | E38: =DAY(EOMONTH($D38, 0)) -> 31 | F38: =DAY(EOMONTH($D38, 0)) -> 31 | G38: =DAY(EOMONTH($D38, 0)) -> 31 | H38: =DAY(EOMONTH($D38, 0)) -> 31 | I38: =DAY(EOMONTH($D38, 0)) -> 31 | J38: =DAY(EOMONTH($D38, 0)) -> 31 | K38: =DAY(EOMONTH($D38, 0)) -> 31 | L38: Days
A39: =HYPERLINK("#'Constants - Dairy'!A1", "Constants - Dairy") -> Constants - Dairy
A40: Sources & acknowledgements

Sheet Input - MMS - Swine
A1: #VALUE! | C1: Input - Manure Management - Swine
A3: Home
A4: =HYPERLINK("#'Results'!A1", "Results") -> Results
D5: This tool demostrates inputs for two production system combinations.
A6: INPUTS | D6: Each production system has two primary manure management systems (one is selectable, the other is hard coded as 'Post-separation solid storage'), and three possible secondary manure management systems.
A7: =HYPERLINK("#'Input - Site'!A1", "Site") -> Site
A8: =HYPERLINK("#'Input - Production'!A1", "Production and outputs") -> Production and outputs
A9: =HYPERLINK("#'Input - Herd - Dairy'!A1", "Herd - Dairy") -> Herd - Dairy | D9: Manure production
A10: =HYPERLINK("#'Input - Feed - Dairy'!A1", "Purchased feed - Livestock") -> Purchased feed - Livestock | E10: Boars | F10: Sows | G10: Gilts | H10: Suckers | I10: Weaners | J10: Growers | K10: Slaughter pigs
A11: =HYPERLINK("#'Input - Herd - Feedlot'!A1", "Herd - Feedlot") -> Herd - Feedlot | D11: Volatile solids produced per head per day | E11: {=Common_InputFunctions.Utility_LookupValueInTableNumber(E10, Table_SourceData_Swine_VolatileSolids[Class], Table_SourceData_Swine_VolatileSolids[VSj])} -> 0.4 | F11: {=Common_InputFunctions.Utility_LookupValueInTableNumber(F10, Table_SourceData_Swine_VolatileSolids[Class], Table_SourceData_Swine_VolatileSolids[VSj])} -> 0.46 | G11: {=Common_InputFunctions.Utility_LookupValueInTableNumber(G10, Table_SourceData_Swine_VolatileSolids[Class], Table_SourceData_Swine_VolatileSolids[VSj])} -> 0.55 | H11: {=Common_InputFunctions.Utility_LookupValueInTableNumber(H10, Table_SourceData_Swine_VolatileSolids[Class], Table_SourceData_Swine_VolatileSolids[VSj])} -> 0.39 | I11: {=Common_InputFunctions.Utility_LookupValueInTableNumber(I10, Table_SourceData_Swine_VolatileSolids[Class], Table_SourceData_Swine_VolatileSolids[VSj])} -> 0.39 | J11: {=Common_InputFunctions.Utility_LookupValueInTableNumber(J10, Table_SourceData_Swine_VolatileSolids[Class], Table_SourceData_Swine_VolatileSolids[VSj])} -> 0.39 | K11: {=Common_InputFunctions.Utility_LookupValueInTableNumber(K10, Table_SourceData_Swine_VolatileSolids[Class], Table_SourceData_Swine_VolatileSolids[VSj])} -> 0.39 | L11: kg/head/day
A12: =HYPERLINK("#'Input - Pasture'!A1", "Pasture") -> Pasture | D12: Nitrogen produced in swine waste per head per day | L12: kg N/head/day
A13: =HYPERLINK("#'Input - Grains'!A1", "Crop - Grains") -> Crop - Grains
A14: =HYPERLINK("#'Input - Fert Lime Chem'!A1", "Fertiliser, Lime & Chemicals") -> Fertiliser, Lime & Chemicals
A15: =HYPERLINK("#'Input - Fuel & Energy'!A1", "Electricity and fuel") -> Electricity and fuel | D15: Production systems
A16: Waste
A17: Freight and transport | D17: Production system (select) | E17: Stage 1 MMS 1 (select) | F17: Stage 1 MMS 2 | G17: Boars | H17: Sows | I17: Gilts | J17: Suckers | K17: Weaners | L17: Growers | M17: Slaughter pigs
A18: =HYPERLINK("#'Input - Other Farm Inputs'!A1", "Other farm inputs") -> Other farm inputs | D18: Conventional housing | E18: Solid storage | F18: =IF(E18="Solid storage", "N/A", "Post-separation solid storage") -> N/A | G18: 0.5 | H18: 0.5 | I18: 0.5 | J18: 0.5 | K18: 0.5 | L18: 0.5 | M18: 0.5 | N18: Percent
A19: =HYPERLINK("#'Input - Data quality'!A1", "Data quality") -> Data quality | D19: Deep litter housing | E19: Drylot (feed pad) | F19: =IF(E19="Solid storage", "N/A", "Post-separation solid storage") -> Post-separation solid storage | G19: 0.5 | H19: 0.5 | I19: 0.5 | J19: 0.5 | K19: 0.5 | L19: 0.5 | M19: 0.5 | N19: Percent
D20: Total (must equal 100%) | G20: =SUM(G18:G19) -> 1 | H20: =SUM(H18:H19) -> 1 | I20: =SUM(I18:I19) -> 1 | J20: =SUM(J18:J19) -> 1 | K20: =SUM(K18:K19) -> 1 | L20: =SUM(L18:L19) -> 1 | M20: =SUM(M18:M19) -> 1 | N20: Percent
A21: CALCULATIONS
A22: N2O MMS
A23: Enteric methane | D23: Production system 1 of 2
A24: =HYPERLINK("#'Calcs - Fert Lime'!A1", "Fertiliser & soil amendments") -> Fertiliser & soil amendments
A25: =HYPERLINK("#'Calcs - Residue mgmt - Crop'!A1", "Residue management - Crop") -> Residue management - Crop | D25: Production system | E25: =$D$18 -> Conventional housing | G25: Stage one MMS | H25: =$E$18 -> Solid storage | I25: =$F$18 -> N/A
A26: =HYPERLINK("#'Calcs - Residue mgmt - Pasture'!A1", "Residue management - Pasture") -> Residue management - Pasture
A27: =HYPERLINK("#'Calcs - Field burning'!A1", "Field burning - Crop") -> Field burning - Crop | D27: Production system 1: Stage 1
A28: =HYPERLINK("#'Calcs - Fuel'!A1", "Fuel") -> Fuel | D28: Does solid separation occur? | E28: Yes | F28: ← Please select
A29: =HYPERLINK("#'Calcs - Electricity'!A1", "Electricity") -> Electricity | D29: Percent solids separated is default, edit if known
A30: =HYPERLINK("#'Calcs - Refrigerants'!A1", "Refrigerants") -> Refrigerants | E30: Boars | F30: Sows | G30: Gilts | H30: Suckers | I30: Weaners | J30: Growers | K30: Slaughter pigs
A31: Waste | D31: ="Percent solids separated from " & H25 -> Percent solids separated from Solid storage | E31: =IF($H$25="Solid storage", "N/A", IF($E$28="Yes", 25%, 0)) -> N/A | F31: =IF($H$25="Solid storage", "N/A", IF($E$28="Yes", 25%, 0)) -> N/A | G31: =IF($H$25="Solid storage", "N/A", IF($E$28="Yes", 25%, 0)) -> N/A | H31: =IF($H$25="Solid storage", "N/A", IF($E$28="Yes", 25%, 0)) -> N/A | I31: =IF($H$25="Solid storage", "N/A", IF($E$28="Yes", 25%, 0)) -> N/A | J31: =IF($H$25="Solid storage", "N/A", IF($E$28="Yes", 25%, 0)) -> N/A | K31: =IF($H$25="Solid storage", "N/A", IF($E$28="Yes", 25%, 0)) -> N/A | L31: Percent
A32: Freight and transport
A33: =HYPERLINK("#'Calcs - Scope 3'!A1", "Purchased goods scope 3") -> Purchased goods scope 3 | D33: Production system 1: Stage 2: MMS
D34: Stage 2 MMS (select) | E34: Boars | F34: Sows | G34: Gilts | H34: Suckers | I34: Weaners | J34: Growers | K34: Slaughter pigs
A35: APPENDICES | D35: ="Sent from stage 1: " & $H$25 -> Sent from stage 1: Solid storage
A36: =HYPERLINK("#'Constants - Common'!A1", "Constants - Common") -> Constants - Common | D36: Digester / covered lagoons | E36: 0.2 | F36: 0.2 | G36: 0.2 | H36: 0.2 | I36: 0.2 | J36: 0.2 | K36: 0.2 | L36: Percent
A37: =HYPERLINK("#'Constants - Cropping'!A1", "Constants - Cropping") -> Constants - Cropping | D37: Anaerobic lagoon | E37: 0.2 | F37: 0.2 | G37: 0.2 | H37: 0.2 | I37: 0.2 | J37: 0.2 | K37: 0.2 | L37: Percent
A38: =HYPERLINK("#'Constants - Livestock'!A1", "Constants - Livestock") -> Constants - Livestock | D38: Direct application | E38: 0.2 | F38: 0.2 | G38: 0.2 | H38: 0.2 | I38: 0.2 | J38: 0.2 | K38: 0.2 | L38: Percent
A39: =HYPERLINK("#'Constants - Dairy'!A1", "Constants - Dairy") -> Constants - Dairy | D39: Applied to soils on the farm (for any purpose) | E39: 0.2 | F39: 0.2 | G39: 0.2 | H39: 0.2 | I39: 0.2 | J39: 0.2 | K39: 0.2 | L39: Percent
A40: Sources & acknowledgements | D40: Removed for sale | E40: 0.2 | F40: 0.2 | G40: 0.2 | H40: 0.2 | I40: 0.2 | J40: 0.2 | K40: 0.2 | L40: Percent
D41: Total (must equal 100%) | E41: =SUM(E36:E40) -> 1 | F41: =SUM(F36:F40) -> 1 | G41: =SUM(G36:G40) -> 1 | H41: =SUM(H36:H40) -> 1 | I41: =SUM(I36:I40) -> 1 | J41: =SUM(J36:J40) -> 1 | K41: =SUM(K36:K40) -> 1 | L41: Percent
D43: Post-Stage 2 destinations
D44: ="Percent sold from " & $D$36 -> Percent sold from Digester / covered lagoons | E44: 0.25 | F44: 0.25 | G44: 0.25 | H44: 0.25 | I44: 0.25 | J44: 0.25 | K44: 0.25 | L44: Percent
D45: ="Percent from " & $D$36 & " applied to soils on farm" -> Percent from Digester / covered lagoons applied to soils on farm | E45: =1-E44 -> 0.75 | F45: =1-F44 -> 0.75 | G45: =1-G44 -> 0.75 | H45: =1-H44 -> 0.75 | I45: =1-I44 -> 0.75 | J45: =1-J44 -> 0.75 | K45: =1-K44 -> 0.75 | L45: Percent
D47: ="Percent sold from " & $D$37 -> Percent sold from Anaerobic lagoon | E47: 0.25 | F47: 0.25 | G47: 0.25 | H47: 0.25 | I47: 0.25 | J47: 0.25 | K47: 0.25 | L47: Percent
D48: ="Percent from " & $D$37 & " applied to soils on farm" -> Percent from Anaerobic lagoon applied to soils on farm | E48: =1-E47 -> 0.75 | F48: =1-F47 -> 0.75 | G48: =1-G47 -> 0.75 | H48: =1-H47 -> 0.75 | I48: =1-I47 -> 0.75 | J48: =1-J47 -> 0.75 | K48: =1-K47 -> 0.75 | L48: Percent
D50: ="Percent sold from " & $D$38 & " for sale" -> Percent sold from Direct application for sale | E50: 0.25 | F50: 0.25 | G50: 0.25 | H50: 0.25 | I50: 0.25 | J50: 0.25 | K50: 0.25 | L50: Percent
D51: ="Percent from " & $D$38 & " applied to soils on farm" -> Percent from Direct application applied to soils on farm | E51: =1-E50 -> 0.75 | F51: =1-F50 -> 0.75 | G51: =1-G50 -> 0.75 | H51: =1-H50 -> 0.75 | I51: =1-I50 -> 0.75 | J51: =1-J50 -> 0.75 | K51: =1-K50 -> 0.75 | L51: Percent
D53: ="Production system 1: Stage 2: Post-separation solid storage " & IF($H$25="Solid storage", "(Not applicable because stage 1 MMS is Solid storage)", "") -> Production system 1: Stage 2: Post-separation solid storage (Not applicable because stage 1 MMS is Solid storage)
D54: =IF($H$25="Solid storage", "N/A", "Stage 2 MMS (select)") -> N/A | E54: =IF($H$25="Solid storage", "N/A", "Boars") -> N/A | F54: =IF($H$25="Solid storage", "N/A", "Sows") -> N/A | G54: =IF($H$25="Solid storage", "N/A", "Gilts") -> N/A | H54: =IF($H$25="Solid storage", "N/A", "Suckers") -> N/A | I54: =IF($H$25="Solid storage", "N/A", "Weaners") -> N/A | J54: =IF($H$25="Solid storage", "N/A", "Growers") -> N/A | K54: =IF($H$25="Solid storage", "N/A", "Slaughter pigs") -> N/A
D55: =IF($H$25="Solid storage", "N/A", "Sent from stage 1: " & $I$25) -> N/A
D56: Drylot (feed pad) | E56: 0.2 | F56: 0.2 | G56: 0.2 | H56: 0.2 | I56: 0.2 | J56: 0.2 | K56: 0.2 | L56: Percent
D57: Anaerobic lagoon | E57: 0.2 | F57: 0.2 | G57: 0.2 | H57: 0.2 | I57: 0.2 | J57: 0.2 | K57: 0.2 | L57: Percent
D58: Deep litter | E58: 0.2 | F58: 0.2 | G58: 0.2 | H58: 0.2 | I58: 0.2 | J58: 0.2 | K58: 0.2 | L58: Percent
D59: =IF($H$25="Solid storage", "N/A", "Applied to soils on the farm (for any purpose)") -> N/A | E59: 0.2 | F59: 0.2 | G59: 0.2 | H59: 0.2 | I59: 0.2 | J59: 0.2 | K59: 0.2 | L59: Percent
D60: =IF($H$25="Solid storage", "N/A", "Removed for sale") -> N/A | E60: 0.2 | F60: 0.2 | G60: 0.2 | H60: 0.2 | I60: 0.2 | J60: 0.2 | K60: 0.2 | L60: Percent
D61: =IF($H$25="Solid storage", "N/A", "Total (must equal 100%)") -> N/A | E61: =SUM(E56:E60) -> 1 | F61: =SUM(F56:F60) -> 1 | G61: =SUM(G56:G60) -> 1 | H61: =SUM(H56:H60) -> 1 | I61: =SUM(I56:I60) -> 1 | J61: =SUM(J56:J60) -> 1 | K61: =SUM(K56:K60) -> 1 | L61: Percent
D63: =IF($H$25="Solid storage", "N/A", "Post-Stage 2 destinations") -> N/A
D64: =IF($H$25="Solid storage", "N/A", "Percent sold from " & $D$56) -> N/A | E64: 0.25 | F64: 0.25 | G64: 0.25 | H64: 0.25 | I64: 0.25 | J64: 0.25 | K64: 0.25 | L64: Percent
D65: =IF($H$25="Solid storage", "N/A", "Percent deposited on farm soils from " & $D$56) -> N/A | E65: =IF($H$25="Solid storage", "N/A", 1-E64) -> N/A | F65: =IF($H$25="Solid storage", "N/A", 1-F64) -> N/A | G65: =IF($H$25="Solid storage", "N/A", 1-G64) -> N/A | H65: =IF($H$25="Solid storage", "N/A", 1-H64) -> N/A | I65: =IF($H$25="Solid storage", "N/A", 1-I64) -> N/A | J65: =IF($H$25="Solid storage", "N/A", 1-J64) -> N/A | K65: =IF($H$25="Solid storage", "N/A", 1-K64) -> N/A | L65: Percent
D67: =IF($H$25="Solid storage", "N/A", "Percent sold from " & $D$57) -> N/A | E67: 0.25 | F67: 0.25 | G67: 0.25 | H67: 0.25 | I67: 0.25 | J67: 0.25 | K67: 0.25 | L67: Percent
D68: =IF($H$25="Solid storage", "N/A", "Percent deposited on farm soils from " & $D$57) -> N/A | E68: =IF($H$25="Solid storage", "N/A", 1-E67) -> N/A | F68: =IF($H$25="Solid storage", "N/A", 1-F67) -> N/A | G68: =IF($H$25="Solid storage", "N/A", 1-G67) -> N/A | H68: =IF($H$25="Solid storage", "N/A", 1-H67) -> N/A | I68: =IF($H$25="Solid storage", "N/A", 1-I67) -> N/A | J68: =IF($H$25="Solid storage", "N/A", 1-J67) -> N/A | K68: =IF($H$25="Solid storage", "N/A", 1-K67) -> N/A | L68: Percent
D70: =IF($H$25="Solid storage", "N/A", "Percent sold from " & $D$58) -> N/A | E70: 0.25 | F70: 0.25 | G70: 0.25 | H70: 0.25 | I70: 0.25 | J70: 0.25 | K70: 0.25 | L70: Percent
D71: =IF($H$25="Solid storage", "N/A", "Percent deposited on farm soils from " & $D$58) -> N/A | E71: =IF($H$25="Solid storage", "N/A", 1-E70) -> N/A | F71: =IF($H$25="Solid storage", "N/A", 1-F70) -> N/A | G71: =IF($H$25="Solid storage", "N/A", 1-G70) -> N/A | H71: =IF($H$25="Solid storage", "N/A", 1-H70) -> N/A | I71: =IF($H$25="Solid storage", "N/A", 1-I70) -> N/A | J71: =IF($H$25="Solid storage", "N/A", 1-J70) -> N/A | K71: =IF($H$25="Solid storage", "N/A", 1-K70) -> N/A | L71: Percent
D75: Production system 2 of 2
D77: Production system | E77: =$D$19 -> Deep litter housing | G77: Stage one MMS | H77: =E$19 -> Drylot (feed pad) | I77: =$F$19 -> Post-separation solid storage
D79: Production system 2: Stage 1
D80: Does solid separation occur? | E80: Yes | F80: ← Please select
E82: Boars | F82: Sows | G82: Gilts | H82: Suckers | I82: Weaners | J82: Growers | K82: Slaughter pigs
D83: ="Percent solids separated from " & H77 -> Percent solids separated from Drylot (feed pad) | E83: =IF($H$77="Solid storage", "N/A", IF($E$80="Yes", 25%, 0)) -> 0.25 | F83: =IF($H$77="Solid storage", "N/A", IF($E$80="Yes", 25%, 0)) -> 0.25 | G83: =IF($H$77="Solid storage", "N/A", IF($E$80="Yes", 25%, 0)) -> 0.25 | H83: =IF($H$77="Solid storage", "N/A", IF($E$80="Yes", 25%, 0)) -> 0.25 | I83: =IF($H$77="Solid storage", "N/A", IF($E$80="Yes", 25%, 0)) -> 0.25 | J83: =IF($H$77="Solid storage", "N/A", IF($E$80="Yes", 25%, 0)) -> 0.25 | K83: =IF($H$77="Solid storage", "N/A", IF($E$80="Yes", 25%, 0)) -> 0.25 | L83: Percent
D85: Production system 2: Stage 2: MMS
D86: Stage 2 MMS (select) | E86: Boars | F86: Sows | G86: Gilts | H86: Suckers | I86: Weaners | J86: Growers | K86: Slaughter pigs
D87: ="Sent from stage 1: " & $H$77 -> Sent from stage 1: Drylot (feed pad)
D88: Digester / covered lagoons | E88: 0.2 | F88: 0.2 | G88: 0.2 | H88: 0.2 | I88: 0.2 | J88: 0.2 | K88: 0.2 | L88: Percent
D89: Anaerobic lagoon | E89: 0.2 | F89: 0.2 | G89: 0.2 | H89: 0.2 | I89: 0.2 | J89: 0.2 | K89: 0.2 | L89: Percent
D90: Pit storage | E90: 0.2 | F90: 0.2 | G90: 0.2 | H90: 0.2 | I90: 0.2 | J90: 0.2 | K90: 0.2 | L90: Percent
D91: Applied to soils on the farm (for any purpose) | E91: 0.2 | F91: 0.2 | G91: 0.2 | H91: 0.2 | I91: 0.2 | J91: 0.2 | K91: 0.2 | L91: Percent
D92: Removed for sale | E92: 0.2 | F92: 0.2 | G92: 0.2 | H92: 0.2 | I92: 0.2 | J92: 0.2 | K92: 0.2 | L92: Percent
D93: Total (must equal 100%) | E93: =SUM(E88:E92) -> 1 | F93: =SUM(F88:F92) -> 1 | G93: =SUM(G88:G92) -> 1 | H93: =SUM(H88:H92) -> 1 | I93: =SUM(I88:I92) -> 1 | J93: =SUM(J88:J92) -> 1 | K93: =SUM(K88:K92) -> 1 | L93: Percent
D95: Post-Stage 2 destinations
D96: ="Percent sold from " & $D$88 -> Percent sold from Digester / covered lagoons | E96: 0.25 | F96: 0.25 | G96: 0.25 | H96: 0.25 | I96: 0.25 | J96: 0.25 | K96: 0.25 | L96: Percent
D97: ="Percent deposited on farm soils from " & $D$88 -> Percent deposited on farm soils from Digester / covered lagoons | E97: {=1-E96:E96} -> 0.75 | F97: {=1-F96:F96} -> 0.75 | G97: {=1-G96:G96} -> 0.75 | H97: {=1-H96:H96} -> 0.75 | I97: {=1-I96:I96} -> 0.75 | J97: {=1-J96:J96} -> 0.75 | K97: {=1-K96:K96} -> 0.75 | L97: Percent
D99: ="Percent sold from " & $D$89 -> Percent sold from Anaerobic lagoon | E99: 0.25 | F99: 0.25 | G99: 0.25 | H99: 0.25 | I99: 0.25 | J99: 0.25 | K99: 0.25 | L99: Percent
D100: ="Percent deposited on farm soils from " & $D$89 -> Percent deposited on farm soils from Anaerobic lagoon | E100: =1-E99 -> 0.75 | F100: =1-F99 -> 0.75 | G100: =1-G99 -> 0.75 | H100: =1-H99 -> 0.75 | I100: =1-I99 -> 0.75 | J100: =1-J99 -> 0.75 | K100: =1-K99 -> 0.75 | L100: Percent
D102: ="Percent sold from " & $D$90 -> Percent sold from Pit storage | E102: 0.25 | F102: 0.25 | G102: 0.25 | H102: 0.25 | I102: 0.25 | J102: 0.25 | K102: 0.25 | L102: Percent
D103: ="Percent deposited on farm soils from " & $D$90 -> Percent deposited on farm soils from Pit storage | E103: =1-E102 -> 0.75 | F103: =1-F102 -> 0.75 | G103: =1-G102 -> 0.75 | H103: =1-H102 -> 0.75 | I103: =1-I102 -> 0.75 | J103: =1-J102 -> 0.75 | K103: =1-K102 -> 0.75 | L103: Percent
D106: ="Production system 1: Stage 2: Post-separation solid storage " & IF($H$77="Solid storage", "(Not applicable because stage 1 MMS is Solid storage)", "") -> Production system 1: Stage 2: Post-separation solid storage
D107: =IF($H$77="Solid storage", "N/A", "Stage 2 MMS (select)") -> Stage 2 MMS (select) | E107: =IF($H$77="Solid storage", "N/A", "Boars") -> Boars | F107: =IF($H$77="Solid storage", "N/A", "Sows") -> Sows | G107: =IF($H$77="Solid storage", "N/A", "Gilts") -> Gilts | H107: =IF($H$77="Solid storage", "N/A", "Suckers") -> Suckers | I107: =IF($H$77="Solid storage", "N/A", "Weaners") -> Weaners | J107: =IF($H$77="Solid storage", "N/A", "Growers") -> Growers | K107: =IF($H$77="Solid storage", "N/A", "Slaughter pigs") -> Slaughter pigs
D108: =IF($H$77="Solid storage", "N/A", "Sent from " & $I$77) -> Sent from Post-separation solid storage
D109: Digester / covered lagoons | E109: 0.2 | F109: 0.2 | G109: 0.2 | H109: 0.2 | I109: 0.2 | J109: 0.2 | K109: 0.2 | L109: Percent
D110: Deep litter | E110: 0.2 | F110: 0.2 | G110: 0.2 | H110: 0.2 | I110: 0.2 | J110: 0.2 | K110: 0.2 | L110: Percent
D111: Pit storage | E111: 0.2 | F111: 0.2 | G111: 0.2 | H111: 0.2 | I111: 0.2 | J111: 0.2 | K111: 0.2 | L111: Percent
D112: =IF($H$77="Solid storage", "N/A", "Applied to soils on the farm (for any purpose)") -> Applied to soils on the farm (for any purpose) | E112: 0.2 | F112: 0.2 | G112: 0.2 | H112: 0.2 | I112: 0.2 | J112: 0.2 | K112: 0.2 | L112: Percent
D113: =IF($H$77="Solid storage", "N/A", "Removed for sale") -> Removed for sale | E113: 0.2 | F113: 0.2 | G113: 0.2 | H113: 0.2 | I113: 0.2 | J113: 0.2 | K113: 0.2 | L113: Percent
D114: =IF($H$77="Solid storage", "N/A", "Total (must equal 100%)") -> Total (must equal 100%) | E114: =SUM(E109:E113) -> 1 | F114: =SUM(F109:F113) -> 1 | G114: =SUM(G109:G113) -> 1 | H114: =SUM(H109:H113) -> 1 | I114: =SUM(I109:I113) -> 1 | J114: =SUM(J109:J113) -> 1 | K114: =SUM(K109:K113) -> 1 | L114: Percent
D116: =IF($H$77="Solid storage", "N/A", "Post-Stage 2 destinations") -> Post-Stage 2 destinations
D117: =IF($H$77="Solid storage", "N/A", "Percent sold from " & $D$109) -> Percent sold from Digester / covered lagoons | E117: 0.25 | F117: 0.25 | G117: 0.25 | H117: 0.25 | I117: 0.25 | J117: 0.25 | K117: 0.25 | L117: Percent
D118: =IF($H$77="Solid storage", "N/A", "Percent deposited on farm soils from " & $D$109) -> Percent deposited on farm soils from Digester / covered lagoons | E118: =IF($H$77="Solid storage", "N/A", 1-E117) -> 0.75 | F118: =IF($H$77="Solid storage", "N/A", 1-F117) -> 0.75 | G118: =IF($H$77="Solid storage", "N/A", 1-G117) -> 0.75 | H118: =IF($H$77="Solid storage", "N/A", 1-H117) -> 0.75 | I118: =IF($H$77="Solid storage", "N/A", 1-I117) -> 0.75 | J118: =IF($H$77="Solid storage", "N/A", 1-J117) -> 0.75 | K118: =IF($H$77="Solid storage", "N/A", 1-K117) -> 0.75 | L118: Percent
D120: =IF($H$77="Solid storage", "N/A", "Percent sold from " & $D$110) -> Percent sold from Deep litter | E120: 0.25 | F120: 0.25 | G120: 0.25 | H120: 0.25 | I120: 0.25 | J120: 0.25 | K120: 0.25 | L120: Percent
D121: =IF($H$77="Solid storage", "N/A", "Percent deposited on farm soils from " & $D$110) -> Percent deposited on farm soils from Deep litter | E121: =IF($F$77="Solid storage","N/A",1-E120) -> 0.75 | F121: =IF($F$77="Solid storage","N/A",1-F120) -> 0.75 | G121: =IF($F$77="Solid storage","N/A",1-G120) -> 0.75 | H121: =IF($F$77="Solid storage","N/A",1-H120) -> 0.75 | I121: =IF($F$77="Solid storage","N/A",1-I120) -> 0.75 | J121: =IF($F$77="Solid storage","N/A",1-J120) -> 0.75 | K121: =IF($F$77="Solid storage","N/A",1-K120) -> 0.75 | L121: Percent
D123: =IF($H$77="Solid storage", "N/A", "Percent sold from " & $D$111) -> Percent sold from Pit storage | E123: 0.25 | F123: 0.25 | G123: 0.25 | H123: 0.25 | I123: 0.25 | J123: 0.25 | K123: 0.25 | L123: Percent
...

Sheet Calcs - CH4 MMS Swine
A1: #VALUE! | C1: Calculations - Manure management - Swine
A3: Home | D3: Equations | R3: Source data
A4: =HYPERLINK("#'Results'!A1", "Results") -> Results
D5: {=ManureManagement_Swine_Methane.VEERG_4_5_1_1__4_FractionVolatileSolidsPrimarySystem_Title()} -> Fraction of volatile solids in each primary system other than solid storage | R5: {=SourceData_Swine.SourceData_Swine_VolatileSolids_Title()} -> Swine - Volatile solids (VSj) - 2020 to 2024
A6: INPUTS | D6: {=ManureManagement_Swine_Methane.VEERG_4_5_1_1__4_FractionVolatileSolidsPrimarySystem_Source()} -> VEERG 2026: 4.5.1.1, Equation (4) | R6: {=SourceData_Swine.SourceData_Swine_VolatileSolids_Source()} -> VEERG 2026: Table A.1.6.1: Swine - Intake and manure characteristics derived from PigBal
A7: =HYPERLINK("#'Input - Site'!A1", "Site") -> Site | D7: Function name | E7: {=Common_InputFunctions.Utility_DisplayFunctionName(F38)} -> =IF($E38="Solid storage", "N/A", ManureManagement_Swine_Methane.VEERG_4_5_1_1__4_FractionVolatileSolidsPrimarySystem(F22,F30)) | R7: {=SourceData_Swine.SourceData_Swine_VolatileSolids_Variation()} -> VARIATION ON SOURCE DATA: Only uses data for 2020-2024. Added 'Suckers', 'Weaners' and 'Growers' classes which have the same values as 'Slaughter pigs'.
A8: =HYPERLINK("#'Input - Production'!A1", "Production and outputs") -> Production and outputs | D8: {=ManureManagement_Swine_Methane.VEERG_4_5_1_1__4_FractionVolatileSolidsPrimarySystem_Variation()} -> VARIATION ON SOURCE: Added check to convert 'N/A' value to zero. | U8: Added 'other' value from NIR
A9: =HYPERLINK("#'Input - Herd - Dairy'!A1", "Herd - Dairy") -> Herd - Dairy | R9: Class | S9: VSj
A10: =HYPERLINK("#'Input - Feed - Dairy'!A1", "Purchased feed - Livestock") -> Purchased feed - Livestock | R10: {=Common_InputFunctions.Utility_DisplayArrayInTable(SourceData_Swine.SourceData_Swine_VolatileSolids_Data(), Table_SourceData_Swine_VolatileSolids[[#Headers],[Class]], 0)} -> Boars | S10: {=Common_InputFunctions.Utility_DisplayArrayInTable(SourceData_Swine.SourceData_Swine_VolatileSolids_Data(), Table_SourceData_Swine_VolatileSolids[[#Headers],[Class]], 0)} -> 0.4
A11: =HYPERLINK("#'Input - Herd - Feedlot'!A1", "Herd - Feedlot") -> Herd - Feedlot | R11: {=Common_InputFunctions.Utility_DisplayArrayInTable(SourceData_Swine.SourceData_Swine_VolatileSolids_Data(), Table_SourceData_Swine_VolatileSolids[[#Headers],[Class]], 0)} -> Sows | S11: {=Common_InputFunctions.Utility_DisplayArrayInTable(SourceData_Swine.SourceData_Swine_VolatileSolids_Data(), Table_SourceData_Swine_VolatileSolids[[#Headers],[Class]], 0)} -> 0.46
A12: =HYPERLINK("#'Input - Pasture'!A1", "Pasture") -> Pasture | D12: Variable | E12: {=ManureManagement_Swine_Methane.VEERG_4_5_1_1__4_FractionVolatileSolidsPrimarySystem_Variable()} -> FVSjmT1 | G12: Inconsistencies - 'primary system' vs 'stage 1' | R12: {=Common_InputFunctions.Utility_DisplayArrayInTable(SourceData_Swine.SourceData_Swine_VolatileSolids_Data(), Table_SourceData_Swine_VolatileSolids[[#Headers],[Class]], 0)} -> Gilts | S12: {=Common_InputFunctions.Utility_DisplayArrayInTable(SourceData_Swine.SourceData_Swine_VolatileSolids_Data(), Table_SourceData_Swine_VolatileSolids[[#Headers],[Class]], 0)} -> 0.55
A13: =HYPERLINK("#'Input - Grains'!A1", "Crop - Grains") -> Crop - Grains | D13: Unit | E13: {=ManureManagement_Swine_Methane.VEERG_4_5_1_1__4_FractionVolatileSolidsPrimarySystem_Unit()} -> fraction | R13: {=Common_InputFunctions.Utility_DisplayArrayInTable(SourceData_Swine.SourceData_Swine_VolatileSolids_Data(), Table_SourceData_Swine_VolatileSolids[[#Headers],[Class]], 0)} -> Slaughter pigs | S13: {=Common_InputFunctions.Utility_DisplayArrayInTable(SourceData_Swine.SourceData_Swine_VolatileSolids_Data(), Table_SourceData_Swine_VolatileSolids[[#Headers],[Class]], 0)} -> 0.39
A14: =HYPERLINK("#'Input - Fert Lime Chem'!A1", "Fertiliser, Lime & Chemicals") -> Fertiliser, Lime & Chemicals | R14: {=Common_InputFunctions.Utility_DisplayArrayInTable(SourceData_Swine.SourceData_Swine_VolatileSolids_Data(), Table_SourceData_Swine_VolatileSolids[[#Headers],[Class]], 0)} -> Suckers | S14: {=Common_InputFunctions.Utility_DisplayArrayInTable(SourceData_Swine.SourceData_Swine_VolatileSolids_Data(), Table_SourceData_Swine_VolatileSolids[[#Headers],[Class]], 0)} -> 0.39
A15: =HYPERLINK("#'Input - Fuel & Energy'!A1", "Electricity and fuel") -> Electricity and fuel | D15: {=ManureManagement_Swine_Methane.VEERG_4_5_1_1__4_FractionVolatileSolidsPrimarySystem_Arguments()} -> MMSjmT1 | E15: fraction of manure to each primary MMS for each class prior to solid separation : fraction | H15: ="See " & $D$18 -> See Table_MMS_j_m-1-7-9-8_T-1 | I15: If this is directly related to equation 5, the mms numbers should be the same eg 1,7,9 (and probably 8,) | R15: {=Common_InputFunctions.Utility_DisplayArrayInTable(SourceData_Swine.SourceData_Swine_VolatileSolids_Data(), Table_SourceData_Swine_VolatileSolids[[#Headers],[Class]], 0)} -> Weaners | S15: {=Common_InputFunctions.Utility_DisplayArrayInTable(SourceData_Swine.SourceData_Swine_VolatileSolids_Data(), Table_SourceData_Swine_VolatileSolids[[#Headers],[Class]], 0)} -> 0.39
A16: Waste | D16: SSm | E16: fraction of volatile solids separated to solid storage for each MMS : fraction | H16: ="See " & $D$26 -> See Table_SS_m-1-7-9 | I16: SSm should be SSjm | R16: {=Common_InputFunctions.Utility_DisplayArrayInTable(SourceData_Swine.SourceData_Swine_VolatileSolids_Data(), Table_SourceData_Swine_VolatileSolids[[#Headers],[Class]], 0)} -> Growers | S16: {=Common_InputFunctions.Utility_DisplayArrayInTable(SourceData_Swine.SourceData_Swine_VolatileSolids_Data(), Table_SourceData_Swine_VolatileSolids[[#Headers],[Class]], 0)} -> 0.39
A17: Freight and transport
A18: =HYPERLINK("#'Input - Other Farm Inputs'!A1", "Other farm inputs") -> Other farm inputs | D18: Table_MMS_j_m-1-7-9-8_T-1
A19: =HYPERLINK("#'Input - Data quality'!A1", "Data quality") -> Data quality | D19: Fraction VS sent to MMS other than solid storage in stage 1 | R19: {=SourceData_Swine.SourceData_Swine_MethaneVolatileSolidsEmissionsPotential_Title()} -> Emissions potential of methane per kilogram of volatile solids
F20: Boars | G20: Sows | H20: Gilts | I20: Suckers | J20: Weaners | K20: Growers | L20: Slaughter pigs | R20: {=SourceData_Swine.SourceData_Swine_MethaneVolatileSolidsEmissionsPotential_Source()} -> IPCC (2019), Chapter 10 [4]
A21: CALCULATIONS | D21: Production system | E21: Stage 1 management | F21: MMSj=1,m=1,7,9,8,13,T=1 | G21: MMSj=2,m=1,7,9,8,13,T=1 | H21: MMSj=3,m=1,7,9,8,13,T=1 | I21: MMSj=4,m=1,7,9,8,13,T=1 | J21: MMSj=4,m=1,7,9,8,13,T=1 | K21: MMSj=4,m=1,7,9,8,13,T=1 | L21: MMSj=4,m=1,7,9,8,13,T=1 | R21: {=SourceData_Swine.SourceData_Swine_MethaneVolatileSolidsEmissionsPotential_Variable()} -> B0 | S21: {=SourceData_Swine.SourceData_Swine_MethaneVolatileSolidsEmissionsPotential_Data()} -> 0.19 | T21: {=SourceData_Swine.SourceData_Swine_MethaneVolatileSolidsEmissionsPotential_Unit()} -> m3 CH4 / kg VS
A22: N2O MMS | D22: ='Input - MMS - Swine'!$D$18 -> Conventional housing | E22: ='Input - MMS - Swine'!$E$18 -> Solid storage | F22: =IF($E22="Solid storage", "N/A", 'Input - MMS - Swine'!G18) -> N/A | G22: =IF($E22="Solid storage", "N/A", 'Input - MMS - Swine'!H18) -> N/A | H22: =IF($E22="Solid storage", "N/A", 'Input - MMS - Swine'!I18) -> N/A | I22: =IF($E22="Solid storage", "N/A", 'Input - MMS - Swine'!J18) -> N/A | J22: =IF($E22="Solid storage", "N/A", 'Input - MMS - Swine'!K18) -> N/A | K22: =IF($E22="Solid storage", "N/A", 'Input - MMS - Swine'!L18) -> N/A | L22: =IF($E22="Solid storage", "N/A", 'Input - MMS - Swine'!M18) -> N/A | M22: Fraction
A23: Enteric methane | D23: ='Input - MMS - Swine'!$D$19 -> Deep litter housing | E23: ='Input - MMS - Swine'!$E$19 -> Drylot (feed pad) | F23: =IF($E23="Solid storage", "N/A", 'Input - MMS - Swine'!G19) -> 0.5 | G23: =IF($E23="Solid storage", "N/A", 'Input - MMS - Swine'!H19) -> 0.5 | H23: =IF($E23="Solid storage", "N/A", 'Input - MMS - Swine'!I19) -> 0.5 | I23: =IF($E23="Solid storage", "N/A", 'Input - MMS - Swine'!J19) -> 0.5 | J23: =IF($E23="Solid storage", "N/A", 'Input - MMS - Swine'!K19) -> 0.5 | K23: =IF($E23="Solid storage", "N/A", 'Input - MMS - Swine'!L19) -> 0.5 | L23: =IF($E23="Solid storage", "N/A", 'Input - MMS - Swine'!M19) -> 0.5 | M23: Fraction
A24: =HYPERLINK("#'Calcs - Fert Lime'!A1", "Fertiliser & soil amendments") -> Fertiliser & soil amendments | R24: {=SourceData_Swine.SourceData_Swine_MMS_MCFs_Title()} -> Methane conversion factor for temperature zone and manure management system. | V24: CHange title to match source
A25: =HYPERLINK("#'Calcs - Residue mgmt - Crop'!A1", "Residue management - Crop") -> Residue management - Crop | R25: {=SourceData_Swine.SourceData_Swine_MMS_MCFs_Source()} -> VEERG 2026: Table A.1.6.4: Swine – MCFs (MCFim) | V25: CHange source
A26: =HYPERLINK("#'Calcs - Residue mgmt - Pasture'!A1", "Residue management - Pasture") -> Residue management - Pasture | D26: Table_SS_m-1-7-9 | R26: {=SourceData_Swine.SourceData_Swine_MMS_MCFs_Variation()} -> VARIATION ON SOURCE DATA: Added columns for ACT, split QLD and NT. Added extra column with MMS names that match NIR definitions
A27: =HYPERLINK("#'Calcs - Field burning'!A1", "Field burning - Crop") -> Field burning - Crop | D27: Fraction separated solids sent from MMS other than solid storage to solid storage in stage 1
A28: =HYPERLINK("#'Calcs - Fuel'!A1", "Fuel") -> Fuel | F28: Boars | G28: Sows | H28: Gilts | I28: Suckers | J28: Weaners | K28: Growers | L28: Slaughter pigs | R28: MMS | S28: NSW | T28: ACT | U28: QLD | V28: NT | W28: SA | X28: TAS | Y28: VIC | Z28: WA | AA28: NIR definition
A29: =HYPERLINK("#'Calcs - Electricity'!A1", "Electricity") -> Electricity | D29: Production system | E29: Stage 1 management | F29: SSj=1m=1,7,9 | G29: SSj=2m=1,7,9 | H29: SSj=3m=1,7,9 | I29: SSj=4m=1,7,9 | J29: SSj=4m=1,7,9 | K29: SSj=4m=1,7,9 | L29: SSj=4m=1,7,9 | R29: {=Common_InputFunctions.Utility_DisplayArrayInTable(SourceData_Swine.SourceData_Swine_MMS_MCFs_Data(),Table_SourceData_Swine_MMSMCF[[#Headers],[MMS]],0)} -> Outdoor (Dry lot) | S29: {=Common_InputFunctions.Utility_DisplayArrayInTable(SourceData_Swine.SourceData_Swine_MMS_MCFs_Data(),Table_SourceData_Swine_MMSMCF[[#Headers],[MMS]],0)} -> 0.01 | T29: {=Common_InputFunctions.Utility_DisplayArrayInTable(SourceData_Swine.SourceData_Swine_MMS_MCFs_Data(),Table_SourceData_Swine_MMSMCF[[#Headers],[MMS]],0)} -> 0.01 | U29: {=Common_InputFunctions.Utility_DisplayArrayInTable(SourceData_Swine.SourceData_Swine_MMS_MCFs_Data(),Table_SourceData_Swine_MMSMCF[[#Headers],[MMS]],0)} -> 0.03 | V29: {=Common_InputFunctions.Utility_DisplayArrayInTable(SourceData_Swine.SourceData_Swine_MMS_MCFs_Data(),Table_SourceData_Swine_MMSMCF[[#Headers],[MMS]],0)} -> 0.03 | W29: {=Common_InputFunctions.Utility_DisplayArrayInTable(SourceData_Swine.SourceData_Swine_MMS_MCFs_Data(),Table_SourceData_Swine_MMSMCF[[#Headers],[MMS]],0)} -> 0.01 | X29: {=Common_InputFunctions.Utility_DisplayArrayInTable(SourceData_Swine.SourceData_Swine_MMS_MCFs_Data(),Table_SourceData_Swine_MMSMCF[[#Headers],[MMS]],0)} -> 0.01 | Y29: {=Common_InputFunctions.Utility_DisplayArrayInTable(SourceData_Swine.SourceData_Swine_MMS_MCFs_Data(),Table_SourceData_Swine_MMSMCF[[#Headers],[MMS]],0)} -> 0.01 | ... AA29: {=Common_InputFunctions.Utility_DisplayArrayInTable(SourceData_Swine.SourceData_Swine_MMS_MCFs_Data(),Table_SourceData_Swine_MMSMCF[[#Headers],[MMS]],0)} -> Drylot (feed pad)
A30: =HYPERLINK("#'Calcs - Refrigerants'!A1", "Refrigerants") -> Refrigerants | D30: ='Input - MMS - Swine'!$D$18 -> Conventional housing | E30: ='Input - MMS - Swine'!$E$18 -> Solid storage | F30: =IF($E$30="Solid storage", "N/A", 'Input - MMS - Swine'!E31) -> N/A | G30: =IF($E$30="Solid storage", "N/A", 'Input - MMS - Swine'!F31) -> N/A | H30: =IF($E$30="Solid storage", "N/A", 'Input - MMS - Swine'!G31) -> N/A | I30: =IF($E$30="Solid storage", "N/A", 'Input - MMS - Swine'!H31) -> N/A | J30: =IF($E$30="Solid storage", "N/A", 'Input - MMS - Swine'!I31) -> N/A | K30: =IF($E$30="Solid storage", "N/A", 'Input - MMS - Swine'!J31) -> N/A | L30: =IF($E$30="Solid storage", "N/A", 'Input - MMS - Swine'!K31) -> N/A | M30: Fraction | R30: {=Common_InputFunctions.Utility_DisplayArrayInTable(SourceData_Swine.SourceData_Swine_MMS_MCFs_Data(),Table_SourceData_Swine_MMSMCF[[#Headers],[MMS]],0)} -> Deep litter | S30: {=Common_InputFunctions.Utility_DisplayArrayInTable(SourceData_Swine.SourceData_Swine_MMS_MCFs_Data(),Table_SourceData_Swine_MMSMCF[[#Headers],[MMS]],0)} -> 0.04 | T30: {=Common_InputFunctions.Utility_DisplayArrayInTable(SourceData_Swine.SourceData_Swine_MMS_MCFs_Data(),Table_SourceData_Swine_MMSMCF[[#Headers],[MMS]],0)} -> 0.04 | U30: {=Common_InputFunctions.Utility_DisplayArrayInTable(SourceData_Swine.SourceData_Swine_MMS_MCFs_Data(),Table_SourceData_Swine_MMSMCF[[#Headers],[MMS]],0)} -> 0.04 | V30: {=Common_InputFunctions.Utility_DisplayArrayInTable(SourceData_Swine.SourceData_Swine_MMS_MCFs_Data(),Table_SourceData_Swine_MMSMCF[[#Headers],[MMS]],0)} -> 0.04 | W30: {=Common_InputFunctions.Utility_DisplayArrayInTable(SourceData_Swine.SourceData_Swine_MMS_MCFs_Data(),Table_SourceData_Swine_MMSMCF[[#Headers],[MMS]],0)} -> 0.04 | X30: {=Common_InputFunctions.Utility_DisplayArrayInTable(SourceData_Swine.SourceData_Swine_MMS_MCFs_Data(),Table_SourceData_Swine_MMSMCF[[#Headers],[MMS]],0)} -> 0.04 | Y30: {=Common_InputFunctions.Utility_DisplayArrayInTable(SourceData_Swine.SourceData_Swine_MMS_MCFs_Data(),Table_SourceData_Swine_MMSMCF[[#Headers],[MMS]],0)} -> 0.04 | ... AA30: {=Common_InputFunctions.Utility_DisplayArrayInTable(SourceData_Swine.SourceData_Swine_MMS_MCFs_Data(),Table_SourceData_Swine_MMSMCF[[#Headers],[MMS]],0)} -> Deep litter
A31: Waste | D31: ='Input - MMS - Swine'!$D$19 -> Deep litter housing | E31: ='Input - MMS - Swine'!$E$19 -> Drylot (feed pad) | F31: =IF($E$31="Solid storage", "N/A", 'Input - MMS - Swine'!E83) -> 0.25 | G31: =IF($E$31="Solid storage", "N/A", 'Input - MMS - Swine'!F83) -> 0.25 | H31: =IF($E$31="Solid storage", "N/A", 'Input - MMS - Swine'!G83) -> 0.25 | I31: =IF($E$31="Solid storage", "N/A", 'Input - MMS - Swine'!H83) -> 0.25 | J31: =IF($E$31="Solid storage", "N/A", 'Input - MMS - Swine'!I83) -> 0.25 | K31: =IF($E$31="Solid storage", "N/A", 'Input - MMS - Swine'!J83) -> 0.25 | L31: =IF($E$31="Solid storage", "N/A", 'Input - MMS - Swine'!K83) -> 0.25 | M31: Fraction | R31: {=Common_InputFunctions.Utility_DisplayArrayInTable(SourceData_Swine.SourceData_Swine_MMS_MCFs_Data(),Table_SourceData_Swine_MMSMCF[[#Headers],[MMS]],0)} -> Stockpile (Solid storage) | S31: {=Common_InputFunctions.Utility_DisplayArrayInTable(SourceData_Swine.SourceData_Swine_MMS_MCFs_Data(),Table_SourceData_Swine_MMSMCF[[#Headers],[MMS]],0)} -> 0.02 | T31: {=Common_InputFunctions.Utility_DisplayArrayInTable(SourceData_Swine.SourceData_Swine_MMS_MCFs_Data(),Table_SourceData_Swine_MMSMCF[[#Headers],[MMS]],0)} -> 0.02 | U31: {=Common_InputFunctions.Utility_DisplayArrayInTable(SourceData_Swine.SourceData_Swine_MMS_MCFs_Data(),Table_SourceData_Swine_MMSMCF[[#Headers],[MMS]],0)} -> 0.02 | V31: {=Common_InputFunctions.Utility_DisplayArrayInTable(SourceData_Swine.SourceData_Swine_MMS_MCFs_Data(),Table_SourceData_Swine_MMSMCF[[#Headers],[MMS]],0)} -> 0.02 | W31: {=Common_InputFunctions.Utility_DisplayArrayInTable(SourceData_Swine.SourceData_Swine_MMS_MCFs_Data(),Table_SourceData_Swine_MMSMCF[[#Headers],[MMS]],0)} -> 0.02 | X31: {=Common_InputFunctions.Utility_DisplayArrayInTable(SourceData_Swine.SourceData_Swine_MMS_MCFs_Data(),Table_SourceData_Swine_MMSMCF[[#Headers],[MMS]],0)} -> 0.02 | Y31: {=Common_InputFunctions.Utility_DisplayArrayInTable(SourceData_Swine.SourceData_Swine_MMS_MCFs_Data(),Table_SourceData_Swine_MMSMCF[[#Headers],[MMS]],0)} -> 0.02 | ... AA31: {=Common_InputFunctions.Utility_DisplayArrayInTable(SourceData_Swine.SourceData_Swine_MMS_MCFs_Data(),Table_SourceData_Swine_MMSMCF[[#Headers],[MMS]],0)} -> Solid storage
A32: Freight and transport | R32: {=Common_InputFunctions.Utility_DisplayArrayInTable(SourceData_Swine.SourceData_Swine_MMS_MCFs_Data(),Table_SourceData_Swine_MMSMCF[[#Headers],[MMS]],0)} -> Effluent pond (Uncovered anaerobic lagoon) | S32: {=Common_InputFunctions.Utility_DisplayArrayInTable(SourceData_Swine.SourceData_Swine_MMS_MCFs_Data(),Table_SourceData_Swine_MMSMCF[[#Headers],[MMS]],0)} -> 0.75 | T32: {=Common_InputFunctions.Utility_DisplayArrayInTable(SourceData_Swine.SourceData_Swine_MMS_MCFs_Data(),Table_SourceData_Swine_MMSMCF[[#Headers],[MMS]],0)} -> 0.75 | U32: {=Common_InputFunctions.Utility_DisplayArrayInTable(SourceData_Swine.SourceData_Swine_MMS_MCFs_Data(),Table_SourceData_Swine_MMSMCF[[#Headers],[MMS]],0)} -> 0.78 | V32: {=Common_InputFunctions.Utility_DisplayArrayInTable(SourceData_Swine.SourceData_Swine_MMS_MCFs_Data(),Table_SourceData_Swine_MMSMCF[[#Headers],[MMS]],0)} -> 0.78 | W32: {=Common_InputFunctions.Utility_DisplayArrayInTable(SourceData_Swine.SourceData_Swine_MMS_MCFs_Data(),Table_SourceData_Swine_MMSMCF[[#Headers],[MMS]],0)} -> 0.75 | X32: {=Common_InputFunctions.Utility_DisplayArrayInTable(SourceData_Swine.SourceData_Swine_MMS_MCFs_Data(),Table_SourceData_Swine_MMSMCF[[#Headers],[MMS]],0)} -> 0.7 | Y32: {=Common_InputFunctions.Utility_DisplayArrayInTable(SourceData_Swine.SourceData_Swine_MMS_MCFs_Data(),Table_SourceData_Swine_MMSMCF[[#Headers],[MMS]],0)} -> 0.74 | ... AA32: {=Common_InputFunctions.Utility_DisplayArrayInTable(SourceData_Swine.SourceData_Swine_MMS_MCFs_Data(),Table_SourceData_Swine_MMSMCF[[#Headers],[MMS]],0)} -> Anaerobic lagoon
A33: =HYPERLINK("#'Calcs - Scope 3'!A1", "Purchased goods scope 3") -> Purchased goods scope 3 | R33: {=Common_InputFunctions.Utility_DisplayArrayInTable(SourceData_Swine.SourceData_Swine_MMS_MCFs_Data(),Table_SourceData_Swine_MMSMCF[[#Headers],[MMS]],0)} -> Anaerobic digester / Covered lagoon | S33: {=Common_InputFunctions.Utility_DisplayArrayInTable(SourceData_Swine.SourceData_Swine_MMS_MCFs_Data(),Table_SourceData_Swine_MMSMCF[[#Headers],[MMS]],0)} -> 0.1 | T33: {=Common_InputFunctions.Utility_DisplayArrayInTable(SourceData_Swine.SourceData_Swine_MMS_MCFs_Data(),Table_SourceData_Swine_MMSMCF[[#Headers],[MMS]],0)} -> 0.1 | U33: {=Common_InputFunctions.Utility_DisplayArrayInTable(SourceData_Swine.SourceData_Swine_MMS_MCFs_Data(),Table_SourceData_Swine_MMSMCF[[#Headers],[MMS]],0)} -> 0.1 | V33: {=Common_InputFunctions.Utility_DisplayArrayInTable(SourceData_Swine.SourceData_Swine_MMS_MCFs_Data(),Table_SourceData_Swine_MMSMCF[[#Headers],[MMS]],0)} -> 0.1 | W33: {=Common_InputFunctions.Utility_DisplayArrayInTable(SourceData_Swine.SourceData_Swine_MMS_MCFs_Data(),Table_SourceData_Swine_MMSMCF[[#Headers],[MMS]],0)} -> 0.1 | X33: {=Common_InputFunctions.Utility_DisplayArrayInTable(SourceData_Swine.SourceData_Swine_MMS_MCFs_Data(),Table_SourceData_Swine_MMSMCF[[#Headers],[MMS]],0)} -> 0.1 | Y33: {=Common_InputFunctions.Utility_DisplayArrayInTable(SourceData_Swine.SourceData_Swine_MMS_MCFs_Data(),Table_SourceData_Swine_MMSMCF[[#Headers],[MMS]],0)} -> 0.1 | ... AA33: {=Common_InputFunctions.Utility_DisplayArrayInTable(SourceData_Swine.SourceData_Swine_MMS_MCFs_Data(),Table_SourceData_Swine_MMSMCF[[#Headers],[MMS]],0)} -> Digester / covered lagoons
D34: Table_FVS_j_m-1-7-9_T-1 | R34: {=Common_InputFunctions.Utility_DisplayArrayInTable(SourceData_Swine.SourceData_Swine_MMS_MCFs_Data(),Table_SourceData_Swine_MMSMCF[[#Headers],[MMS]],0)} -> Short HRT tank storage < 1 month (pit storage) | S34: {=Common_InputFunctions.Utility_DisplayArrayInTable(SourceData_Swine.SourceData_Swine_MMS_MCFs_Data(),Table_SourceData_Swine_MMSMCF[[#Headers],[MMS]],0)} -> 0.03 | T34: {=Common_InputFunctions.Utility_DisplayArrayInTable(SourceData_Swine.SourceData_Swine_MMS_MCFs_Data(),Table_SourceData_Swine_MMSMCF[[#Headers],[MMS]],0)} -> 0.03 | U34: {=Common_InputFunctions.Utility_DisplayArrayInTable(SourceData_Swine.SourceData_Swine_MMS_MCFs_Data(),Table_SourceData_Swine_MMSMCF[[#Headers],[MMS]],0)} -> 0.03 | V34: {=Common_InputFunctions.Utility_DisplayArrayInTable(SourceData_Swine.SourceData_Swine_MMS_MCFs_Data(),Table_SourceData_Swine_MMSMCF[[#Headers],[MMS]],0)} -> 0.03 | W34: {=Common_InputFunctions.Utility_DisplayArrayInTable(SourceData_Swine.SourceData_Swine_MMS_MCFs_Data(),Table_SourceData_Swine_MMSMCF[[#Headers],[MMS]],0)} -> 0.03 | X34: {=Common_InputFunctions.Utility_DisplayArrayInTable(SourceData_Swine.SourceData_Swine_MMS_MCFs_Data(),Table_SourceData_Swine_MMSMCF[[#Headers],[MMS]],0)} -> 0.03 | Y34: {=Common_InputFunctions.Utility_DisplayArrayInTable(SourceData_Swine.SourceData_Swine_MMS_MCFs_Data(),Table_SourceData_Swine_MMSMCF[[#Headers],[MMS]],0)} -> 0.03 | ... AA34: {=Common_InputFunctions.Utility_DisplayArrayInTable(SourceData_Swine.SourceData_Swine_MMS_MCFs_Data(),Table_SourceData_Swine_MMSMCF[[#Headers],[MMS]],0)} -> Pit storage
A35: APPENDICES | D35: Fraction VS in MMS other than solid storage in stage 1 | R35: {=Common_InputFunctions.Utility_DisplayArrayInTable(SourceData_Swine.SourceData_Swine_MMS_MCFs_Data(),Table_SourceData_Swine_MMSMCF[[#Headers],[MMS]],0)} -> Direct Application to soil | S35: {=Common_InputFunctions.Utility_DisplayArrayInTable(SourceData_Swine.SourceData_Swine_MMS_MCFs_Data(),Table_SourceData_Swine_MMSMCF[[#Headers],[MMS]],0)} -> 0 | T35: {=Common_InputFunctions.Utility_DisplayArrayInTable(SourceData_Swine.SourceData_Swine_MMS_MCFs_Data(),Table_SourceData_Swine_MMSMCF[[#Headers],[MMS]],0)} -> 0 | U35: {=Common_InputFunctions.Utility_DisplayArrayInTable(SourceData_Swine.SourceData_Swine_MMS_MCFs_Data(),Table_SourceData_Swine_MMSMCF[[#Headers],[MMS]],0)} -> 0 | V35: {=Common_InputFunctions.Utility_DisplayArrayInTable(SourceData_Swine.SourceData_Swine_MMS_MCFs_Data(),Table_SourceData_Swine_MMSMCF[[#Headers],[MMS]],0)} -> 0 | W35: {=Common_InputFunctions.Utility_DisplayArrayInTable(SourceData_Swine.SourceData_Swine_MMS_MCFs_Data(),Table_SourceData_Swine_MMSMCF[[#Headers],[MMS]],0)} -> 0 | X35: {=Common_InputFunctions.Utility_DisplayArrayInTable(SourceData_Swine.SourceData_Swine_MMS_MCFs_Data(),Table_SourceData_Swine_MMSMCF[[#Headers],[MMS]],0)} -> 0 | Y35: {=Common_InputFunctions.Utility_DisplayArrayInTable(SourceData_Swine.SourceData_Swine_MMS_MCFs_Data(),Table_SourceData_Swine_MMSMCF[[#Headers],[MMS]],0)} -> 0 | ... AA35: {=Common_InputFunctions.Utility_DisplayArrayInTable(SourceData_Swine.SourceData_Swine_MMS_MCFs_Data(),Table_SourceData_Swine_MMSMCF[[#Headers],[MMS]],0)} -> Direct application
A36: =HYPERLINK("#'Constants - Common'!A1", "Constants - Common") -> Constants - Common | F36: Boars | G36: Sows | H36: Gilts | I36: Suckers | J36: Weaners | K36: Growers | L36: Slaughter pigs
A37: =HYPERLINK("#'Constants - Cropping'!A1", "Constants - Cropping") -> Constants - Cropping | D37: Production system | E37: Stage 1 management | F37: FVSj,m=1,7,9,T=1 | G37: FVSj,m=1,7,9,T=1 | H37: FVSj,m=1,7,9,T=1 | I37: FVSj,m=1,7,9,T=1 | J37: FVSj,m=1,7,9,T=1 | K37: FVSj,m=1,7,9,T=1 | L37: FVSj,m=1,7,9,T=1
A38: =HYPERLINK("#'Constants - Livestock'!A1", "Constants - Livestock") -> Constants - Livestock | D38: ='Input - MMS - Swine'!$D$18 -> Conventional housing | E38: ='Input - MMS - Swine'!$E$18 -> Solid storage | F38: {=IF($E38="Solid storage", "N/A", ManureManagement_Swine_Methane.VEERG_4_5_1_1__4_FractionVolatileSolidsPrimarySystem(F22,F30))} -> N/A | G38: {=IF($E38="Solid storage", "N/A", ManureManagement_Swine_Methane.VEERG_4_5_1_1__4_FractionVolatileSolidsPrimarySystem(G22,G30))} -> N/A | H38: {=IF($E38="Solid storage", "N/A", ManureManagement_Swine_Methane.VEERG_4_5_1_1__4_FractionVolatileSolidsPrimarySystem(H22,H30))} -> N/A | I38: {=IF($E38="Solid storage", "N/A", ManureManagement_Swine_Methane.VEERG_4_5_1_1__4_FractionVolatileSolidsPrimarySystem(I22,I30))} -> N/A | J38: {=IF($E38="Solid storage", "N/A", ManureManagement_Swine_Methane.VEERG_4_5_1_1__4_FractionVolatileSolidsPrimarySystem(J22,J30))} -> N/A | K38: {=IF($E38="Solid storage", "N/A", ManureManagement_Swine_Methane.VEERG_4_5_1_1__4_FractionVolatileSolidsPrimarySystem(K22,K30))} -> N/A | L38: {=IF($E38="Solid storage", "N/A", ManureManagement_Swine_Methane.VEERG_4_5_1_1__4_FractionVolatileSolidsPrimarySystem(L22,L30))} -> N/A | M38: Fraction | R38: Swine Manure management systems | U38: Swine Manure management systems excl. solid storage and direct application | Y38: Swine Manure management systems excl. direct application
A39: =HYPERLINK("#'Constants - Dairy'!A1", "Constants - Dairy") -> Constants - Dairy | D39: ='Input - MMS - Swine'!$D$19 -> Deep litter housing | E39: ='Input - MMS - Swine'!$E$19 -> Drylot (feed pad) | F39: {=IF($E39="Solid storage", "N/A", ManureManagement_Swine_Methane.VEERG_4_5_1_1__4_FractionVolatileSolidsPrimarySystem(F23,F31))} -> 0.375 | G39: {=IF($E39="Solid storage", "N/A", ManureManagement_Swine_Methane.VEERG_4_5_1_1__4_FractionVolatileSolidsPrimarySystem(G23,G31))} -> 0.375 | H39: {=IF($E39="Solid storage", "N/A", ManureManagement_Swine_Methane.VEERG_4_5_1_1__4_FractionVolatileSolidsPrimarySystem(H23,H31))} -> 0.375 | I39: {=IF($E39="Solid storage", "N/A", ManureManagement_Swine_Methane.VEERG_4_5_1_1__4_FractionVolatileSolidsPrimarySystem(I23,I31))} -> 0.375 | J39: {=IF($E39="Solid storage", "N/A", ManureManagement_Swine_Methane.VEERG_4_5_1_1__4_FractionVolatileSolidsPrimarySystem(J23,J31))} -> 0.375 | K39: {=IF($E39="Solid storage", "N/A", ManureManagement_Swine_Methane.VEERG_4_5_1_1__4_FractionVolatileSolidsPrimarySystem(K23,K31))} -> 0.375 | L39: {=IF($E39="Solid storage", "N/A", ManureManagement_Swine_Methane.VEERG_4_5_1_1__4_FractionVolatileSolidsPrimarySystem(L23,L31))} -> 0.375 | M39: Fraction
A40: Sources & acknowledgements | R40: MMS | S40: Symbol and MMS | U40: MMS | V40: Symbol and MMS | Y40: MMS | Z40: Symbol and MMS
R41: ='Constants - Livestock'!$E$10 -> Anaerobic lagoon | S41: ='Constants - Livestock'!$F$10 -> Anaerobic lagoon (m=1) | U41: ='Constants - Livestock'!$E$10 -> Anaerobic lagoon | V41: ='Constants - Livestock'!$F$10 -> Anaerobic lagoon (m=1) | Y41: ='Constants - Livestock'!$E$10 -> Anaerobic lagoon | Z41: ='Constants - Livestock'!$F$10 -> Anaerobic lagoon (m=1)
R42: ='Constants - Livestock'!$E$15 -> Solid storage | S42: ='Constants - Livestock'!$F$15 -> Solid storage (m=4) | U42: ='Constants - Livestock'!$E$16 -> Drylot (feed pad) | V42: ='Constants - Livestock'!$F$16 -> Drylot (feed pad) (m=5) | Y42: ='Constants - Livestock'!$E$15 -> Solid storage | Z42: ='Constants - Livestock'!$F$15 -> Solid storage (m=4)
D43: {=ManureManagement_Swine_Methane.VEERG_4_5_1_1__5_FractionVolatileSolidsSolidStorage_Title()} -> Fraction of volatile solids in solid storage | F43: Rename to 'Fraction of volatile solids in primary system in solid storage' | R43: ='Constants - Livestock'!$E$16 -> Drylot (feed pad) | S43: ='Constants - Livestock'!$F$16 -> Drylot (feed pad) (m=5) | U43: ='Constants - Livestock'!$E$18 -> Digester / covered lagoons | V43: ='Constants - Livestock'!$F$18 -> Digester / covered lagoons (m=7) | Y43: ='Constants - Livestock'!$E$16 -> Drylot (feed pad) | Z43: ='Constants - Livestock'!$F$16 -> Drylot (feed pad) (m=5)
D44: {=ManureManagement_Swine_Methane.VEERG_4_5_1_1__5_FractionVolatileSolidsSolidStorage_Source()} -> VEERG 2026: 4.5.1.1, Equation (5) | R44: ='Constants - Livestock'!$E$18 -> Digester / covered lagoons | S44: ='Constants - Livestock'!$F$18 -> Digester / covered lagoons (m=7) | U44: ='Constants - Livestock'!$E$19 -> Deep litter | V44: ='Constants - Livestock'!$F$19 -> Deep litter (m=8) | Y44: ='Constants - Livestock'!$E$18 -> Digester / covered lagoons | Z44: ='Constants - Livestock'!$F$18 -> Digester / covered lagoons (m=7)
D45: Function name | E45: {=Common_InputFunctions.Utility_DisplayFunctionName(F68)} -> =ManureManagement_Swine_Methane.VEERG_4_5_1_1__5_FractionVolatileSolidsSolidStorage(F60,F22,F30) | R45: ='Constants - Livestock'!$E$19 -> Deep litter | S45: ='Constants - Livestock'!$F$19 -> Deep litter (m=8) | U45: ='Constants - Livestock'!$E$20 -> Pit storage | V45: ='Constants - Livestock'!$F$20 -> Pit storage (m=9) | Y45: ='Constants - Livestock'!$E$19 -> Deep litter | Z45: ='Constants - Livestock'!$F$19 -> Deep litter (m=8)
R46: ='Constants - Livestock'!$E$20 -> Pit storage | S46: ='Constants - Livestock'!$F$20 -> Pit storage (m=9) | Y46: ='Constants - Livestock'!$E$20 -> Pit storage | Z46: ='Constants - Livestock'!$F$20 -> Pit storage (m=9)
R47: ='Constants - Livestock'!$E$26 -> Direct application | S47: ='Constants - Livestock'!$F$26 -> Direct application (m=13)
D49: Variable | E49: {=ManureManagement_Swine_Methane.VEERG_4_5_1_1__5_FractionVolatileSolidsSolidStorage_Variable()} -> FVSjm4T1 | I49: should have mms numbers in SSm
D50: Unit | E50: {=ManureManagement_Swine_Methane.VEERG_4_5_1_1__5_FractionVolatileSolidsSolidStorage_Unit()} -> fraction
R51: Fraction volatile solids lost during storage in primary system | U51: Swine housing
D52: {=ManureManagement_Swine_Methane.VEERG_4_5_1_1__5_FractionVolatileSolidsSolidStorage_Arguments()} -> MMSjm4T1 | E52: fraction of manure in solid storage primary system : fraction | G52: ="See " & $D$56 -> See Table_MMS_j_m-4_T-1
D53: MMSjm179T1 | E53: fraction of manure in MMS 1, 7, and 9 in treatment stage 1 : fraction | G53: ="See " & $D$18 -> See Table_MMS_j_m-1-7-9-8_T-1 | R53: MMS | S53: VSL | U53: Production system
D54: SSm | E54: fraction of volatile solids separated to solid storage for each MMS : fraction | G54: ="See " & $D$26 -> See Table_SS_m-1-7-9 | R54: ='Constants - Livestock'!$E$10 -> Anaerobic lagoon | S54: 0 | U54: {=Common_InputFunctions.Utility_DisplayArrayInTable(SourceData_Swine.SourceData_Swine_ProductionSystems_Data(), Table_SourceData_Swine_ProductionSystems[[#Headers],[Production system]], 0)} -> Conventional housing
R55: ='Constants - Livestock'!$E$15 -> Solid storage | S55: 0 | U55: {=Common_InputFunctions.Utility_DisplayArrayInTable(SourceData_Swine.SourceData_Swine_ProductionSystems_Data(), Table_SourceData_Swine_ProductionSystems[[#Headers],[Production system]], 0)} -> Deep litter housing
D56: Table_MMS_j_m-4_T-1 | R56: ='Constants - Livestock'!$E$16 -> Drylot (feed pad) | S56: 0 | U56: {=Common_InputFunctions.Utility_DisplayArrayInTable(SourceData_Swine.SourceData_Swine_ProductionSystems_Data(), Table_SourceData_Swine_ProductionSystems[[#Headers],[Production system]], 0)} -> Outdoor/free range
D57: Fraction primary system solid storage | R57: ='Constants - Livestock'!$E$18 -> Digester / covered lagoons | S57: 0.75
F58: Boars | G58: Sows | H58: Gilts | I58: Suckers | J58: Weaners | K58: Growers | L58: Slaughter pigs | R58: ='Constants - Livestock'!$E$19 -> Deep litter | S58: 0.05
D59: Production system | E59: Stage 1 management | F59: MMSj=1,m=4,T=1 | G59: MMSj=2,m=4,T=1 | H59: MMSj=3,m=4,T=1 | I59: MMSj=4,m=4,T=1 | J59: MMSj=4,m=4,T=1 | K59: MMSj=4,m=4,T=1 | L59: MMSj=4,m=4,T=1 | R59: ='Constants - Livestock'!$E$20 -> Pit storage | S59: 0
D60: ='Input - MMS - Swine'!$D$18 -> Conventional housing | E60: ='Input - MMS - Swine'!$E$18 -> Solid storage | F60: =IF($E60="Solid storage", 'Input - MMS - Swine'!G18, "N/A") -> 0.5 | G60: =IF($E60="Solid storage", 'Input - MMS - Swine'!H18, "N/A") -> 0.5 | H60: =IF($E60="Solid storage", 'Input - MMS - Swine'!I18, "N/A") -> 0.5 | I60: =IF($E60="Solid storage", 'Input - MMS - Swine'!J18, "N/A") -> 0.5 | J60: =IF($E60="Solid storage", 'Input - MMS - Swine'!K18, "N/A") -> 0.5 | K60: =IF($E60="Solid storage", 'Input - MMS - Swine'!L18, "N/A") -> 0.5 | L60: =IF($E60="Solid storage", 'Input - MMS - Swine'!M18, "N/A") -> 0.5 | M60: Fraction | R60: ='Constants - Livestock'!$E$26 -> Direct application | S60: 0
D61: ='Input - MMS - Swine'!$D$19 -> Deep litter housing | E61: ='Input - MMS - Swine'!$E$19 -> Drylot (feed pad) | F61: =IF($E61="Solid storage", 'Input - MMS - Swine'!G19, "N/A") -> N/A | G61: =IF($E61="Solid storage", 'Input - MMS - Swine'!H19, "N/A") -> N/A | H61: =IF($E61="Solid storage", 'Input - MMS - Swine'!I19, "N/A") -> N/A | I61: =IF($E61="Solid storage", 'Input - MMS - Swine'!J19, "N/A") -> N/A | J61: =IF($E61="Solid storage", 'Input - MMS - Swine'!K19, "N/A") -> N/A | K61: =IF($E61="Solid storage", 'Input - MMS - Swine'!L19, "N/A") -> N/A | L61: =IF($E61="Solid storage", 'Input - MMS - Swine'!M19, "N/A") -> N/A | M61: Fraction
D64: Table_FVS_j_m-4_T-1
D65: Fraction VS in stage 1 solid storage
F66: Boars | G66: Sows | H66: Gilts | I66: Suckers | J66: Weaners | K66: Growers | L66: Slaughter pigs
D67: Production system | E67: Stage 1 management | F67: FVSj=1,m=4,T=1 | G67: FVSj=2,m=4,T=1 | H67: FVSj=3,m=4,T=1 | I67: FVSj=4,m=4,T=1 | J67: FVSj=4,m=4,T=1 | K67: FVSj=4,m=4,T=1 | L67: FVSj=4,m=4,T=1
D68: ='Input - MMS - Swine'!$D$18 -> Conventional housing | E68: =IF('Input - MMS - Swine'!$H$25="Solid storage", 'Input - MMS - Swine'!$H$25, 'Input - MMS - Swine'!$F$18) -> Solid storage | F68: {=ManureManagement_Swine_Methane.VEERG_4_5_1_1__5_FractionVolatileSolidsSolidStorage(F60,F22,F30)} -> 0.5 | G68: {=ManureManagement_Swine_Methane.VEERG_4_5_1_1__5_FractionVolatileSolidsSolidStorage(G60,G22,G30)} -> 0.5 | H68: {=ManureManagement_Swine_Methane.VEERG_4_5_1_1__5_FractionVolatileSolidsSolidStorage(H60,H22,H30)} -> 0.5 | I68: {=ManureManagement_Swine_Methane.VEERG_4_5_1_1__5_FractionVolatileSolidsSolidStorage(I60,I22,I30)} -> 0.5 | J68: {=ManureManagement_Swine_Methane.VEERG_4_5_1_1__5_FractionVolatileSolidsSolidStorage(J60,J22,J30)} -> 0.5 | K68: {=ManureManagement_Swine_Methane.VEERG_4_5_1_1__5_FractionVolatileSolidsSolidStorage(K60,K22,K30)} -> 0.5 | L68: {=ManureManagement_Swine_Methane.VEERG_4_5_1_1__5_FractionVolatileSolidsSolidStorage(L60,L22,L30)} -> 0.5 | M68: Fraction
D69: ='Input - MMS - Swine'!$D$19 -> Deep litter housing | E69: =IF('Input - MMS - Swine'!$H$77="Solid storage", 'Input - MMS - Swine'!$H$77, 'Input - MMS - Swine'!$F$19) -> Post-separation solid storage | F69: {=ManureManagement_Swine_Methane.VEERG_4_5_1_1__5_FractionVolatileSolidsSolidStorage(F61,F23,F31)} -> 0.125 | G69: {=ManureManagement_Swine_Methane.VEERG_4_5_1_1__5_FractionVolatileSolidsSolidStorage(G61,G23,G31)} -> 0.125 | H69: {=ManureManagement_Swine_Methane.VEERG_4_5_1_1__5_FractionVolatileSolidsSolidStorage(H61,H23,H31)} -> 0.125 | I69: {=ManureManagement_Swine_Methane.VEERG_4_5_1_1__5_FractionVolatileSolidsSolidStorage(I61,I23,I31)} -> 0.125 | J69: {=ManureManagement_Swine_Methane.VEERG_4_5_1_1__5_FractionVolatileSolidsSolidStorage(J61,J23,J31)} -> 0.125 | K69: {=ManureManagement_Swine_Methane.VEERG_4_5_1_1__5_FractionVolatileSolidsSolidStorage(K61,K23,K31)} -> 0.125 | L69: {=ManureManagement_Swine_Methane.VEERG_4_5_1_1__5_FractionVolatileSolidsSolidStorage(L61,L23,L31)} -> 0.125 | M69: Fraction
D74: {=ManureManagement_Swine_Methane.VEERG_4_5_1_1__7_VolatileSolidsTransferredStage2_Title()} -> Volatile solids transferred to treatment stage 2 MMS
D75: {=ManureManagement_Swine_Methane.VEERG_4_5_1_1__7_VolatileSolidsTransferredStage2_Source()} -> VEERG 2026: 4.5.1.1, Equation (7)
D76: Function name | E76: {=Common_InputFunctions.Utility_DisplayFunctionName(F107)} -> =IF('Input - MMS - Swine'!$H$25="Solid storage", ManureManagement_Swine_Methane.VEERG_4_5_1_1__7_VolatileSolidsTransferredStage2(D$91,F68,$F$99), ManureManagement_Swine_Methane.VEERG_4_5_1_1__7_VolatileSolidsTransferredStage2(D$91,F38,$F$99))
D80: Variable | E80: {=ManureManagement_Swine_Methane.VEERG_4_5_1_1__7_VolatileSolidsTransferredStage2_Variable()} -> VSTijmT2
D81: Unit | E81: {=ManureManagement_Swine_Methane.VEERG_4_5_1_1__7_VolatileSolidsTransferredStage2_Unit()} -> kg VS | F81: Should be kg/head/day
D83: {=ManureManagement_Swine_Methane.VEERG_4_5_1_1__7_VolatileSolidsTransferredStage2_Arguments()} -> VSj | E83: volatile solid production from swine in each class : kg/head/day | G83: ="See " & $D$87 -> See Table_VS_j
D84: FVSjmT1 | E84: fraction of volatile solids in each primary system : fraction | G84: ="See " & $D$34 & " and " & $D$64 -> See Table_FVS_j_m-1-7-9_T-1 and Table_FVS_j_m-4_T-1
D85: VSLmT1 | E85: fraction of volatile solids lost during storage in the primary system : fraction | G85: ="See " & $D$94 -> See Table_VSL_m_T-1
D87: Table_VS_j
D88: Daily volatile solid production
D89: Boars | E89: Sows | F89: Gilts | G89: Suckers | H89: Weaners | I89: Growers | J89: Slaughter pigs
D90: VSj=1 | E90: VSj=2 | F90: VSj=3 | G90: VSj=4 | H90: VSj=4 | I90: VSj=4 | J90: VSj=4
D91: ='Input - MMS - Swine'!$E$11 -> 0.4 | E91: ='Input - MMS - Swine'!$F$11 -> 0.46 | F91: ='Input - MMS - Swine'!$G$11 -> 0.55 | G91: ='Input - MMS - Swine'!$H$11 -> 0.39 | H91: ='Input - MMS - Swine'!$I$11 -> 0.39 | I91: ='Input - MMS - Swine'!$J$11 -> 0.39 | J91: ='Input - MMS - Swine'!$K$11 -> 0.39 | K91: kg/head/day
D94: Table_VSL_m_T-1
D95: Fraction volatile solids lost during storage in primary system
D96: Production system | E96: Stage 1 management | F96: VSLm,T=1
D97: ='Input - MMS - Swine'!$D$18 -> Conventional housing | E97: ='Input - MMS - Swine'!$E$18 -> Solid storage | F97: {=IF(E97="N/A", "N/A", Common_InputFunctions.Utility_LookupValueInTableNumber(E97,Table_SourceData_SwineVSL[MMS],Table_SourceData_SwineVSL[VSL]))} -> 0 | G97: Fraction | H97: create source data in sourcedata file
D98: ='Input - MMS - Swine'!$D$18 -> Conventional housing | E98: ='Input - MMS - Swine'!$F$18 -> N/A | F98: {=IF(E98="N/A", "N/A", Common_InputFunctions.Utility_LookupValueInTableNumber(E98,Table_SourceData_SwineVSL[MMS],Table_SourceData_SwineVSL[VSL]))} -> N/A | G98: Fraction
D99: ='Input - MMS - Swine'!$D$19 -> Deep litter housing | E99: ='Input - MMS - Swine'!$E$19 -> Drylot (feed pad) | F99: {=IF(E99="N/A", "N/A", Common_InputFunctions.Utility_LookupValueInTableNumber(E99,Table_SourceData_SwineVSL[MMS],Table_SourceData_SwineVSL[VSL]))} -> 0 | G99: Fraction
D100: ='Input - MMS - Swine'!$D$19 -> Deep litter housing | E100: ='Input - MMS - Swine'!$F$19 -> Post-separation solid storage | F100: {=IF(E100="N/A", "N/A", Common_InputFunctions.Utility_LookupValueInTableNumber(E100,Table_SourceData_SwineVSL[MMS],Table_SourceData_SwineVSL[VSL]))} -> 0 | G100: Fraction
D103: Table_VST_j_m_T-2
D104: Volatile solids transferred from stage 1 to stage 2
F105: Boars | G105: Sows | H105: Gilts | I105: Suckers | J105: Weaners | K105: Growers | L105: Slaughter pigs
D106: Production system | E106: Stage 1 management | F106: VSTj=1,m,T=2 | G106: VSTj=2,m,T=1 | H106: VSTj=3,m,T=1 | I106: VSTj=4,m,T=1 | J106: VSTj=4,m,T=1 | K106: VSTj=4,m,T=1 | L106: VSTj=4,m,T=1
D107: ='Input - MMS - Swine'!$D$18 -> Conventional housing | E107: ='Input - MMS - Swine'!$E$18 -> Solid storage | F107: {=IF('Input - MMS - Swine'!$H$25="Solid storage", ManureManagement_Swine_Methane.VEERG_4_5_1_1__7_VolatileSolidsTransferredStage2(D$91,F68,$F$99), ManureManagement_Swine_Methane.VEERG_4_5_1_1__7_VolatileSolidsTransferredStage2(D$91,F38,$F$99))} -> 0.2 | G107: {=IF('Input - MMS - Swine'!$H$25="Solid storage", ManureManagement_Swine_Methane.VEERG_4_5_1_1__7_VolatileSolidsTransferredStage2(E$91,G68,$F$99), ManureManagement_Swine_Methane.VEERG_4_5_1_1__7_VolatileSolidsTransferredStage2(E$91,G38,$F$99))} -> 0.23 | H107: {=IF('Input - MMS - Swine'!$H$25="Solid storage", ManureManagement_Swine_Methane.VEERG_4_5_1_1__7_VolatileSolidsTransferredStage2(F$91,H68,$F$99), ManureManagement_Swine_Methane.VEERG_4_5_1_1__7_VolatileSolidsTransferredStage2(F$91,H38,$F$99))} -> 0.275 | I107: {=IF('Input - MMS - Swine'!$H$25="Solid storage", ManureManagement_Swine_Methane.VEERG_4_5_1_1__7_VolatileSolidsTransferredStage2(G$91,I68,$F$99), ManureManagement_Swine_Methane.VEERG_4_5_1_1__7_VolatileSolidsTransferredStage2(G$91,I38,$F$99))} -> 0.195 | J107: {=IF('Input - MMS - Swine'!$H$25="Solid storage", ManureManagement_Swine_Methane.VEERG_4_5_1_1__7_VolatileSolidsTransferredStage2(H$91,J68,$F$99), ManureManagement_Swine_Methane.VEERG_4_5_1_1__7_VolatileSolidsTransferredStage2(H$91,J38,$F$99))} -> 0.195 | K107: {=IF('Input - MMS - Swine'!$H$25="Solid storage", ManureManagement_Swine_Methane.VEERG_4_5_1_1__7_VolatileSolidsTransferredStage2(I$91,K68,$F$99), ManureManagement_Swine_Methane.VEERG_4_5_1_1__7_VolatileSolidsTransferredStage2(I$91,K38,$F$99))} -> 0.195 | L107: {=IF('Input - MMS - Swine'!$H$25="Solid storage", ManureManagement_Swine_Methane.VEERG_4_5_1_1__7_VolatileSolidsTransferredStage2(J$91,L68,$F$99), ManureManagement_Swine_Methane.VEERG_4_5_1_1__7_VolatileSolidsTransferredStage2(J$91,L38,$F$99))} -> 0.195 | M107: =$E$81 -> kg VS
D108: ='Input - MMS - Swine'!$D$18 -> Conventional housing | E108: ='Input - MMS - Swine'!$F$18 -> N/A | F108: {=IF('Input - MMS - Swine'!$H$25="Solid storage", "N/A", ManureManagement_Swine_Methane.VEERG_4_5_1_1__7_VolatileSolidsTransferredStage2(D$91,F68,$F$97))} -> N/A | G108: {=IF('Input - MMS - Swine'!$H$25="Solid storage", "N/A", ManureManagement_Swine_Methane.VEERG_4_5_1_1__7_VolatileSolidsTransferredStage2(E$91,G68,$F$97))} -> N/A | H108: {=IF('Input - MMS - Swine'!$H$25="Solid storage", "N/A", ManureManagement_Swine_Methane.VEERG_4_5_1_1__7_VolatileSolidsTransferredStage2(F$91,H68,$F$97))} -> N/A | I108: {=IF('Input - MMS - Swine'!$H$25="Solid storage", "N/A", ManureManagement_Swine_Methane.VEERG_4_5_1_1__7_VolatileSolidsTransferredStage2(G$91,I68,$F$97))} -> N/A | J108: {=IF('Input - MMS - Swine'!$H$25="Solid storage", "N/A", ManureManagement_Swine_Methane.VEERG_4_5_1_1__7_VolatileSolidsTransferredStage2(H$91,J68,$F$97))} -> N/A | K108: {=IF('Input - MMS - Swine'!$H$25="Solid storage", "N/A", ManureManagement_Swine_Methane.VEERG_4_5_1_1__7_VolatileSolidsTransferredStage2(I$91,K68,$F$97))} -> N/A | L108: {=IF('Input - MMS - Swine'!$H$25="Solid storage", "N/A", ManureManagement_Swine_Methane.VEERG_4_5_1_1__7_VolatileSolidsTransferredStage2(J$91,L68,$F$97))} -> N/A | M108: =$E$81 -> kg VS
D109: ='Input - MMS - Swine'!$D$19 -> Deep litter housing | E109: ='Input - MMS - Swine'!$E$19 -> Drylot (feed pad) | F109: {=IF('Input - MMS - Swine'!$H$77="Solid storage", ManureManagement_Swine_Methane.VEERG_4_5_1_1__7_VolatileSolidsTransferredStage2(D$91,F69,$F$99), ManureManagement_Swine_Methane.VEERG_4_5_1_1__7_VolatileSolidsTransferredStage2(D$91,F39,$F$99))} -> 0.15 | G109: {=IF('Input - MMS - Swine'!$H$77="Solid storage", ManureManagement_Swine_Methane.VEERG_4_5_1_1__7_VolatileSolidsTransferredStage2(E$91,G69,$F$99), ManureManagement_Swine_Methane.VEERG_4_5_1_1__7_VolatileSolidsTransferredStage2(E$91,G39,$F$99))} -> 0.1725 | H109: {=IF('Input - MMS - Swine'!$H$77="Solid storage", ManureManagement_Swine_Methane.VEERG_4_5_1_1__7_VolatileSolidsTransferredStage2(F$91,H69,$F$99), ManureManagement_Swine_Methane.VEERG_4_5_1_1__7_VolatileSolidsTransferredStage2(F$91,H39,$F$99))} -> 0.20625 | I109: {=IF('Input - MMS - Swine'!$H$77="Solid storage", ManureManagement_Swine_Methane.VEERG_4_5_1_1__7_VolatileSolidsTransferredStage2(G$91,I69,$F$99), ManureManagement_Swine_Methane.VEERG_4_5_1_1__7_VolatileSolidsTransferredStage2(G$91,I39,$F$99))} -> 0.14625 | J109: {=IF('Input - MMS - Swine'!$H$77="Solid storage", ManureManagement_Swine_Methane.VEERG_4_5_1_1__7_VolatileSolidsTransferredStage2(H$91,J69,$F$99), ManureManagement_Swine_Methane.VEERG_4_5_1_1__7_VolatileSolidsTransferredStage2(H$91,J39,$F$99))} -> 0.14625 | K109: {=IF('Input - MMS - Swine'!$H$77="Solid storage", ManureManagement_Swine_Methane.VEERG_4_5_1_1__7_VolatileSolidsTransferredStage2(I$91,K69,$F$99), ManureManagement_Swine_Methane.VEERG_4_5_1_1__7_VolatileSolidsTransferredStage2(I$91,K39,$F$99))} -> 0.14625 | L109: {=IF('Input - MMS - Swine'!$H$77="Solid storage", ManureManagement_Swine_Methane.VEERG_4_5_1_1__7_VolatileSolidsTransferredStage2(J$91,L69,$F$99), ManureManagement_Swine_Methane.VEERG_4_5_1_1__7_VolatileSolidsTransferredStage2(J$91,L39,$F$99))} -> 0.14625 | M109: =$E$81 -> kg VS
D110: ='Input - MMS - Swine'!$D$19 -> Deep litter housing | E110: ='Input - MMS - Swine'!$F$19 -> Post-separation solid storage | F110: {=IF('Input - MMS - Swine'!$H$77="Solid storage", "N/A", ManureManagement_Swine_Methane.VEERG_4_5_1_1__7_VolatileSolidsTransferredStage2(D$91,F69,$F$97))} -> 0.05 | G110: {=IF('Input - MMS - Swine'!$H$77="Solid storage", "N/A", ManureManagement_Swine_Methane.VEERG_4_5_1_1__7_VolatileSolidsTransferredStage2(E$91,G69,$F$97))} -> 0.0575 | H110: {=IF('Input - MMS - Swine'!$H$77="Solid storage", "N/A", ManureManagement_Swine_Methane.VEERG_4_5_1_1__7_VolatileSolidsTransferredStage2(F$91,H69,$F$97))} -> 0.06875 | I110: {=IF('Input - MMS - Swine'!$H$77="Solid storage", "N/A", ManureManagement_Swine_Methane.VEERG_4_5_1_1__7_VolatileSolidsTransferredStage2(G$91,I69,$F$97))} -> 0.04875 | J110: {=IF('Input - MMS - Swine'!$H$77="Solid storage", "N/A", ManureManagement_Swine_Methane.VEERG_4_5_1_1__7_VolatileSolidsTransferredStage2(H$91,J69,$F$97))} -> 0.04875 | K110: {=IF('Input - MMS - Swine'!$H$77="Solid storage", "N/A", ManureManagement_Swine_Methane.VEERG_4_5_1_1__7_VolatileSolidsTransferredStage2(I$91,K69,$F$97))} -> 0.04875 | L110: {=IF('Input - MMS - Swine'!$H$77="Solid storage", "N/A", ManureManagement_Swine_Methane.VEERG_4_5_1_1__7_VolatileSolidsTransferredStage2(J$91,L69,$F$97))} -> 0.04875 | M110: =$E$81 -> kg VS
D114: {=ManureManagement_Swine_Methane.VEERG_4_5_1_1__6_Stage2MethaneProduction_Title()} -> Production of methane in each treatment stage 2 MMS
D115: {=ManureManagement_Swine_Methane.VEERG_4_5_1_1__6_Stage2MethaneProduction_Source()} -> VEERG 2026: 4.5.1.1, Equation (6)
D116: Function name | E116: {=Common_InputFunctions.Utility_DisplayFunctionName(G165)} -> =ManureManagement_Swine_Methane.VEERG_4_5_1_1__6_Stage2MethaneProduction(F$107,$G$124,G134,VLOOKUP($F165,$D$152:$E$159,2, FALSE),$G$127)
D117: Add variation - temperature zone or state
D120: Variable | E120: {=ManureManagement_Swine_Methane.VEERG_4_5_1_1__6_Stage2MethaneProduction_Variable()} -> MijmT2
D121: Unit | E121: {=ManureManagement_Swine_Methane.VEERG_4_5_1_1__6_Stage2MethaneProduction_Unit()} -> kg CH4/head/day
D123: {=ManureManagement_Swine_Methane.VEERG_4_5_1_1__6_Stage2MethaneProduction_Arguments()} -> VSTjmT2 | E123: volatile solids transferred to treatment stage 2 MMS : kg/head/day | G123: ="See " & D103 -> See Table_VST_j_m_T-2
...

Sheet Tab template
A1: #VALUE!
A3: Home
A4: =HYPERLINK("#'Results'!A1", "Results") -> Results
A6: INPUTS
A7: =HYPERLINK("#'Input - Site'!A1", "Site") -> Site
A8: =HYPERLINK("#'Input - Production'!A1", "Production and outputs") -> Production and outputs
A9: =HYPERLINK("#'Input - Herd - Dairy'!A1", "Herd - Dairy") -> Herd - Dairy
A10: =HYPERLINK("#'Input - Feed - Dairy'!A1", "Purchased feed - Livestock") -> Purchased feed - Livestock
A11: =HYPERLINK("#'Input - Herd - Feedlot'!A1", "Herd - Feedlot") -> Herd - Feedlot
A12: =HYPERLINK("#'Input - Pasture'!A1", "Pasture") -> Pasture
A13: =HYPERLINK("#'Input - Grains'!A1", "Crop - Grains") -> Crop - Grains
A14: =HYPERLINK("#'Input - Fert Lime Chem'!A1", "Fertiliser, Lime & Chemicals") -> Fertiliser, Lime & Chemicals
A15: =HYPERLINK("#'Input - Fuel & Energy'!A1", "Electricity and fuel") -> Electricity and fuel
A16: Waste
A17: Freight and transport
A18: =HYPERLINK("#'Input - Other Farm Inputs'!A1", "Other farm inputs") -> Other farm inputs
A19: =HYPERLINK("#'Input - Data quality'!A1", "Data quality") -> Data quality
A21: CALCULATIONS
A22: N2O MMS
A23: Enteric methane
A24: =HYPERLINK("#'Calcs - Fert Lime'!A1", "Fertiliser & soil amendments") -> Fertiliser & soil amendments
A25: =HYPERLINK("#'Calcs - Residue mgmt - Crop'!A1", "Residue management - Crop") -> Residue management - Crop
A26: =HYPERLINK("#'Calcs - Residue mgmt - Pasture'!A1", "Residue management - Pasture") -> Residue management - Pasture
A27: =HYPERLINK("#'Calcs - Field burning'!A1", "Field burning - Crop") -> Field burning - Crop
A28: =HYPERLINK("#'Calcs - Fuel'!A1", "Fuel") -> Fuel
A29: =HYPERLINK("#'Calcs - Electricity'!A1", "Electricity") -> Electricity
A30: =HYPERLINK("#'Calcs - Refrigerants'!A1", "Refrigerants") -> Refrigerants
A31: Waste
A32: Freight and transport
A33: =HYPERLINK("#'Calcs - Scope 3'!A1", "Purchased goods scope 3") -> Purchased goods scope 3
A35: APPENDICES
A36: =HYPERLINK("#'Constants - Common'!A1", "Constants - Common") -> Constants - Common
A37: =HYPERLINK("#'Constants - Cropping'!A1", "Constants - Cropping") -> Constants - Cropping
A38: =HYPERLINK("#'Constants - Livestock'!A1", "Constants - Livestock") -> Constants - Livestock
A39: =HYPERLINK("#'Constants - Dairy'!A1", "Constants - Dairy") -> Constants - Dairy
A40: Sources & acknowledgements

Sheet Results
A1: #VALUE! | C1: =#REF! -> #REF!
A3: Home
A4: =HYPERLINK("#'Results'!A1", "Results") -> Results | D4: Emissions overview
A6: INPUTS | D6: Net emissions
A7: =HYPERLINK("#'Input - Site'!A1", "Site") -> Site | D7: Scope 1 | E7: 123
A8: =HYPERLINK("#'Input - Production'!A1", "Production and outputs") -> Production and outputs | D8: Scope 2 | E8: 20
A9: =HYPERLINK("#'Input - Herd - Dairy'!A1", "Herd - Dairy") -> Herd - Dairy | D9: Scope 3 | E9: 300
A10: =HYPERLINK("#'Input - Feed - Dairy'!A1", "Purchased feed - Livestock") -> Purchased feed - Livestock | D10: Sequestration | E10: -10
A11: =HYPERLINK("#'Input - Herd - Feedlot'!A1", "Herd - Feedlot") -> Herd - Feedlot | D11: Net farm emissions | E11: =SUM(E7:E10) -> 433 | F11: t CO2-e / farm
A12: =HYPERLINK("#'Input - Pasture'!A1", "Pasture") -> Pasture
A13: =HYPERLINK("#'Input - Grains'!A1", "Crop - Grains") -> Crop - Grains | D13: Emissions intensity - IF THIS YEAR IS FULL PRODUCTION CYCLE
A14: =HYPERLINK("#'Input - Fert Lime Chem'!A1", "Fertiliser, Lime & Chemicals") -> Fertiliser, Lime & Chemicals | D14: Allocation method: Mass
A15: =HYPERLINK("#'Input - Fuel & Energy'!A1", "Electricity and fuel") -> Electricity and fuel | D15: Allocation of net emissions between primary product, co-products and residual products
A16: Waste | D16: Grains allocation | E16: 0.9 | F16: percent
A17: Freight and transport | D17: Fodder allocation | E17: 0.1 | F17: percent
A18: =HYPERLINK("#'Input - Other Farm Inputs'!A1", "Other farm inputs") -> Other farm inputs | D18: Residual product X allocation | E18: N/A
A19: =HYPERLINK("#'Input - Data quality'!A1", "Data quality") -> Data quality | D19: For production timeframes that touch multiple years, use the emissions intensity tool
D20: Grains emissions intensity
A21: CALCULATIONS | D21: Grains yield | E21: 100 | F21: tonnes
A22: N2O MMS | D22: Grains emissions intensity : Excluding sequestration | E22: =(E11+E10)*E16/E21 -> 3.807 | F22: t CO2-e / t grains
A23: Enteric methane | D23: Grains emissions intensity : Including sequestration | E23: =E11*E16/E21 -> 3.897 | F23: t CO2-e / t grains
A24: =HYPERLINK("#'Calcs - Fert Lime'!A1", "Fertiliser & soil amendments") -> Fertiliser & soil amendments
A25: =HYPERLINK("#'Calcs - Residue mgmt - Crop'!A1", "Residue management - Crop") -> Residue management - Crop | D25: Fodder emissions intensity
A26: =HYPERLINK("#'Calcs - Residue mgmt - Pasture'!A1", "Residue management - Pasture") -> Residue management - Pasture | D26: Fodder yield | E26: 10 | F26: tonnes
A27: =HYPERLINK("#'Calcs - Field burning'!A1", "Field burning - Crop") -> Field burning - Crop | D27: Fodder emissions intensity : Excluding sequestration | E27: =(E11+E10)*E17/E26 -> 4.23 | F27: t CO2-e / t fodder
A28: =HYPERLINK("#'Calcs - Fuel'!A1", "Fuel") -> Fuel | D28: Fodder emissions intensity : Including sequestration | E28: =E11*E17/E26 -> 4.33 | F28: t CO2-e / t fodder
A29: =HYPERLINK("#'Calcs - Electricity'!A1", "Electricity") -> Electricity
A30: =HYPERLINK("#'Calcs - Refrigerants'!A1", "Refrigerants") -> Refrigerants | D30: Residual product X emissions intensity (only the processing of the residual product)
A31: Waste | D31: Residual product X yield / amount produced | E31: 50 | F31: tonnes
A32: Freight and transport | D32: Residual product X emissions intensity : Excluding sequestration | E32: =(E11+E10)/E31 -> 8.46 | F32: t CO2-e / t fodder
A33: =HYPERLINK("#'Calcs - Scope 3'!A1", "Purchased goods scope 3") -> Purchased goods scope 3 | D33: Residual product X emissions intensity : Including sequestration | E33: =E11/E31 -> 8.66 | F33: t CO2-e / t fodder
A35: APPENDICES
A36: =HYPERLINK("#'Constants - Common'!A1", "Constants - Common") -> Constants - Common | D36: Emissions breakdown
A37: =HYPERLINK("#'Constants - Cropping'!A1", "Constants - Cropping") -> Constants - Cropping
A38: =HYPERLINK("#'Constants - Livestock'!A1", "Constants - Livestock") -> Constants - Livestock | D38: Scope 1 | F38: Notes | G38: ='Input - Production'!D21 -> 01 Jan 2020 to 31 Dec 2020 | I38: ='Input - Production'!D22 -> 01 Jan 2021 to 31 Dec 2021
A39: =HYPERLINK("#'Constants - Dairy'!A1", "Constants - Dairy") -> Constants - Dairy | D39: CO2 - Fuel | E39: ='Calcs - Fuel'!E154 -> 1.5048585 | F39: Most fuel used at harvest | G39: 0.2 | H39: =E39*G39 -> 0.3009717 | I39: 0.8 | J39: =E39*I39 -> 1.2038868
A40: Sources & acknowledgements | D40: CO2 - Lime | E40: ='Calcs - Fert Lime'!E180 -> 0 | F40: Applied lime before planting | G40: 1 | H40: =E40*G40 -> 0 | I40: 0 | J40: =E40*I40 -> 0
D41: CO2 - Urea | E41: ='Calcs - Fert Lime'!E101 -> 0 | F41: Urea at start | G41: 1 | H41: =E41*G41 -> 0 | I41: 0 | J41: =E41*I41 -> 0
D42: CH4 - Fuel | E42: ='Calcs - Fuel'!E155 -> 0.02029255 | F42: Most fuel used at harvest | G42: 0.2 | H42: =E42*G42 -> 0.00405851 | I42: 0.8 | J42: =E42*I42 -> 0.01623404
D43: CH4 - Enteric | E43: 3 | F43: Cows all the way through | G43: 0.5 | H43: =E43*G43 -> 1.5 | I43: 0.5 | J43: =E43*I43 -> 1.5
D44: CH4 - Manure Management | E44: 7 | F44: Cows all the way through | G44: 0.5 | H44: =E44*G44 -> 3.5 | I44: 0.5 | J44: =E44*I44 -> 3.5
D45: CH4 - Savannah Burning | E45: 123 | F45: burned at end | G45: 0 | H45: =E45*G45 -> 0 | I45: 1 | J45: =E45*I45 -> 123
D46: N2O - Fertiliser - inorganic | E46: ='Calcs - Fert Lime'!E61 -> 0 | F46: 3 fert applications | G46: 0.6 | H46: =E46*G46 -> 0 | I46: 0.4 | J46: =E46*I46 -> 0
D47: N2O - Fertiliser - organic | E47: ='Calcs - Fert Lime'!E150 -> 0 | H47: =E47*G47 -> 0 | J47: =E47*I47 -> 0
D48: N2O - Urine and Dung | E48: 123 | F48: Cows all the way through | G48: 0.5 | H48: =E48*G48 -> 61.5 | I48: 0.5 | J48: =E48*I48 -> 61.5
D49: N2O - Atmospheric Deposition | E49: 1054 | H49: =E49*G49 -> 0 | J49: =E49*I49 -> 0
D50: N2O - Leaching and Runoff | E50: 600 | H50: =E50*G50 -> 0 | J50: =E50*I50 -> 0
D51: N2O - Savannah Burning | E51: 82 | H51: =E51*G51 -> 0 | J51: =E51*I51 -> 0
D52: N2O - Fuel | E52: ='Calcs - Fuel'!E156 -> 0.00943 | H52: =E52*G52 -> 0 | J52: =E52*I52 -> 0
D53: Total scope 1 emissions | E53: =SUM(E39:E52) -> 1993.5346 | H53: =SUM(H39:H52) -> 66.80503 | J53: =SUM(J39:J52) -> 190.72012
D55: Scope 1 greenhouse gas breakdown
D56: CO2 : Carbon dioxide | E56: 300 | F56: t CO2-e
D57: CH4 : Methane | E57: 500 | F57: t CO2-e
D58: N2O : Nitrous oxide | E58: 20 | F58: t CO2-e
D61: Scope 2
D62: CO2 : Fuel | E62: ='Calcs - Electricity'!E21 -> 0.28
D63: Total scope 2 emissions | E63: 123 | F63: t CO2-e
D65: Scope 3
D66: Fertiliser | E66: 123
D67: Purchased mineral supplementation | E67: 80
D68: Purchased feed | E68: 654
D69: Herbicides/pesticides | E69: 6
D70: Electricity | E70: ='Calcs - Electricity'!E42 -> 0.045
D71: Fuel | E71: ='Calcs - Fuel'!E157 -> 0.3937095
D72: Lime | E72: 3
D73: Purchased livestock | E73: 180
D74: CO2 : Fuel | E74: 12
D75: CO2 : Fuel | E75: 67
D76: CO2 : Fuel | E76: 123
D77: CO2 : Fuel | E77: 893
D78: Total scope 3 emissions | E78: 123 | F78: t CO2-e
D82: Sequestered CO2
D83: Plantings | E83: 123
D84: Total scope sequestered CO2 emissions | E84: 123 | F84: t CO2-e

Sheet Input - Site
A1: #VALUE! | C1: Input - Site
A3: Home
A4: =HYPERLINK("#'Results'!A1", "Results") -> Results
D5: Your business
A6: INPUTS
A7: =HYPERLINK("#'Input - Site'!A1", "Site") -> Site | D7: Farm name | E7: Test Farms
A8: =HYPERLINK("#'Input - Production'!A1", "Production and outputs") -> Production and outputs | D8: Reporting entity name | E8: Test Farms Pty Ltd
A9: =HYPERLINK("#'Input - Herd - Dairy'!A1", "Herd - Dairy") -> Herd - Dairy
A10: =HYPERLINK("#'Input - Feed - Dairy'!A1", "Purchased feed - Livestock") -> Purchased feed - Livestock | D10: 💡An 'Emissions accounting period' is a 12 month period where the business can report on the emissions, and is typically the same as the business' financial accounting period.
A11: =HYPERLINK("#'Input - Herd - Feedlot'!A1", "Herd - Feedlot") -> Herd - Feedlot
A12: =HYPERLINK("#'Input - Pasture'!A1", "Pasture") -> Pasture | D12: Emissions calculation period start date | E12: 45292 | F12: ← DD/MM/YYYY or DD Month YYYY
A13: =HYPERLINK("#'Input - Grains'!A1", "Crop - Grains") -> Crop - Grains | D13: Emissions calculation period end date | E13: =DATE(YEAR(E12)+1,MONTH(E12),DAY(E12))-1 -> 45657 | F13: ← Automatically calculated, 12 months after start date
A14: =HYPERLINK("#'Input - Fert Lime Chem'!A1", "Fertiliser, Lime & Chemicals") -> Fertiliser, Lime & Chemicals
A15: =HYPERLINK("#'Input - Fuel & Energy'!A1", "Electricity and fuel") -> Electricity and fuel
A16: Waste | D16: Location and climate
A17: Freight and transport
A18: =HYPERLINK("#'Input - Other Farm Inputs'!A1", "Other farm inputs") -> Other farm inputs | D18: Location information is used to reference some region and climate-specific emission factors
A19: =HYPERLINK("#'Input - Data quality'!A1", "Data quality") -> Data quality | D19: Tip: Use the web-based GAF Location Helper tool to easily get region and climate information. You will need an internet connection to use the GAF Location Helper.
A21: CALCULATIONS | D21: State | E21: Western Australia | F21: ← Please select
A22: N2O MMS | D22: Region (ABS Statistical area level 4) if state is WA | E22: Western Australia - Outback (South) | F22: ← Please select
A23: Enteric methane | D23: Leaching zone | E23: NO - Not in leaching zone | F23: ← Please select
A24: =HYPERLINK("#'Calcs - Fert Lime'!A1", "Fertiliser & soil amendments") -> Fertiliser & soil amendments | D24: Elevation | E24: 307.7 | F24: Meters
A25: =HYPERLINK("#'Calcs - Residue mgmt - Crop'!A1", "Residue management - Crop") -> Residue management - Crop | D25: Average temperature for reporting period | E25: 19 | F25: Degrees celsius
A26: =HYPERLINK("#'Calcs - Residue mgmt - Pasture'!A1", "Residue management - Pasture") -> Residue management - Pasture | D26: Total rainfall for reporting period | E26: 3000 | F26: Millimetres
A27: =HYPERLINK("#'Calcs - Field burning'!A1", "Field burning - Crop") -> Field burning - Crop | D27: Potential evapotranspiration for reporting period | E27: 1326 | F27: Millimetres
A28: =HYPERLINK("#'Calcs - Fuel'!A1", "Fuel") -> Fuel | D28: Number of frost days for reporting period | E28: 7 | F28: Days
A29: =HYPERLINK("#'Calcs - Electricity'!A1", "Electricity") -> Electricity | D29: MAP:PET ratio | E29: =E26/E27 -> 2.2624434
A30: =HYPERLINK("#'Calcs - Refrigerants'!A1", "Refrigerants") -> Refrigerants | D30: Rainfall zone | E30: {=Common_InputFunctions.Utility_LookupItemFromMinMax(E26,#REF!,#REF!,#REF!)} -> #REF!
A31: Waste | D31: Climate zone | E31: {=Common_InputFunctions.Utility_GetClimateZone(E25,E26,E28,E24,E29)} -> #REF!
A32: Freight and transport | D32: Wet or dry climate zone | E32: {=Common_InputFunctions.Utility_LookupValueInTable($E$31,#REF!,#REF!)} -> #REF!
A33: =HYPERLINK("#'Calcs - Scope 3'!A1", "Purchased goods scope 3") -> Purchased goods scope 3 | D33: Temperature zone | E33: {=Common_InputFunctions.Utility_LookupItemFromMinMax(E25,#REF!,#REF!,#REF!)} -> #REF!
A35: APPENDICES
A36: =HYPERLINK("#'Constants - Common'!A1", "Constants - Common") -> Constants - Common
A37: =HYPERLINK("#'Constants - Cropping'!A1", "Constants - Cropping") -> Constants - Cropping
A38: =HYPERLINK("#'Constants - Livestock'!A1", "Constants - Livestock") -> Constants - Livestock
A39: =HYPERLINK("#'Constants - Dairy'!A1", "Constants - Dairy") -> Constants - Dairy
A40: Sources & acknowledgements

Sheet Input - Production
A1: #VALUE! | C1: Input - Production and yield
A3: Home
A4: =HYPERLINK("#'Results'!A1", "Results") -> Results
D5: Production cycle
A6: INPUTS
A7: =HYPERLINK("#'Input - Site'!A1", "Site") -> Site | D7: 💡A 'Production cycle' is the period from starting production to either the sale of your main products or transfer of main products to the next production cycle (eg: harvested fruit to packaging).
A8: =HYPERLINK("#'Input - Production'!A1", "Production and outputs") -> Production and outputs | D8: The timing of your 'Production cycle' may be different to your business' emissions accounting timeframe.
A9: =HYPERLINK("#'Input - Herd - Dairy'!A1", "Herd - Dairy") -> Herd - Dairy | D9: If your main products are sold throughout the production cycle (as with most livestock enterprises), make the production cycle the same as the emissions accounting period.
A10: =HYPERLINK("#'Input - Feed - Dairy'!A1", "Purchased feed - Livestock") -> Purchased feed - Livestock | D10: Production cycles can be longer than emissions accounting periods, and production cycles may overlap with multiple emissions accounting periods.
A11: =HYPERLINK("#'Input - Herd - Feedlot'!A1", "Herd - Feedlot") -> Herd - Feedlot | D11: In these cases you will need to have one GAF for each emissions accounting period that overlaps with the production cycle.
A12: =HYPERLINK("#'Input - Pasture'!A1", "Pasture") -> Pasture
A13: =HYPERLINK("#'Input - Grains'!A1", "Crop - Grains") -> Crop - Grains | D13: Production cycle start date | E13: 44105 | F13: Date
A14: =HYPERLINK("#'Input - Fert Lime Chem'!A1", "Fertiliser, Lime & Chemicals") -> Fertiliser, Lime & Chemicals | D14: Production cycle end date | E14: 45382 | F14: Date
A15: =HYPERLINK("#'Input - Fuel & Energy'!A1", "Electricity and fuel") -> Electricity and fuel | D15: Production timeframe length | E15: =DATEDIF(EOMONTH(E13, -1),EOMONTH(E14, 0),"m") -> 42 | F15: Months
A16: Waste
A17: Freight and transport | D17: Emissions accounting period start date | E17: ='Input - Site'!E12 -> 45292 | F17: Date
A18: =HYPERLINK("#'Input - Other Farm Inputs'!A1", "Other farm inputs") -> Other farm inputs | D18: Emissions accounting period end date | E18: ='Input - Site'!E13 -> 45657 | F18: Date
A19: =HYPERLINK("#'Input - Data quality'!A1", "Data quality") -> Data quality
D20: {="There are "& Common_InputFunctions.getOverlappingReportingCycles(E13,E14,E17) & " emissions accounting periods that need to be completed to calculate emissions for the full production cycle:"} -> There are 5 emissions accounting periods that need to be completed to calculate emissions for the full production cycle:
A21: CALCULATIONS | D21: {=Common_InputFunctions.getOverlappingReportingPeriods(E13,E14,E17)} -> 01 Jan 2020 to 31 Dec 2020
A22: N2O MMS | D22: 01 Jan 2021 to 31 Dec 2021
A23: Enteric methane | D23: 01 Jan 2022 to 31 Dec 2022
A24: =HYPERLINK("#'Calcs - Fert Lime'!A1", "Fertiliser & soil amendments") -> Fertiliser & soil amendments | D24: 01 Jan 2023 to 31 Dec 2023
A25: =HYPERLINK("#'Calcs - Residue mgmt - Crop'!A1", "Residue management - Crop") -> Residue management - Crop | D25: 01 Jan 2024 to 31 Dec 2024
A26: =HYPERLINK("#'Calcs - Residue mgmt - Pasture'!A1", "Residue management - Pasture") -> Residue management - Pasture | D26: Main product, co-product yields and other outputs
A27: =HYPERLINK("#'Calcs - Field burning'!A1", "Field burning - Crop") -> Field burning - Crop | D27: Dairy
A28: =HYPERLINK("#'Calcs - Fuel'!A1", "Fuel") -> Fuel | D28: Product | E28: Type | F28: ="Amount produced " & TEXT($E$17, "d/m/y") & " - " & TEXT($E$18, "d/m/y") -> Amount produced 1/1/24 - 31/12/24 | G28: Amount unit | H28: ="% of revenue " & TEXT($E$17, "d/m/y") & " - " & TEXT($E$18, "d/m/y") -> % of revenue 1/1/24 - 31/12/24
A29: =HYPERLINK("#'Calcs - Electricity'!A1", "Electricity") -> Electricity | D29: Milk (Fat and protein corrected) | E29: Main product | G29: Litres | H29: 0.75
A30: =HYPERLINK("#'Calcs - Refrigerants'!A1", "Refrigerants") -> Refrigerants | D30: Livestock sold | E30: Co-product | F30: =SUM(#REF!) -> #REF! | G30: Kilograms | H30: 0.12
A31: Waste | D31: Liveweight grown | E31: Co-product | F31: =SUM(#REF!) -> #REF! | G31: Kilograms | H31: N/A
A32: Freight and transport | D32: Manure from solid storage (sold or transferred) | E32: Co-product | G32: Kilograms | H32: 0.13
A33: =HYPERLINK("#'Calcs - Scope 3'!A1", "Purchased goods scope 3") -> Purchased goods scope 3 | D33: Manure from anaerobic lagoon (sold or transferred) | E33: Co-product | G33: Kilograms | H33: 0
A35: APPENDICES | D35: Grains production
A36: =HYPERLINK("#'Constants - Common'!A1", "Constants - Common") -> Constants - Common | D36: Product | E36: Type | F36: ="Amount produced " & TEXT($E$17, "d/m/y") & " - " & TEXT($E$18, "d/m/y") -> Amount produced 1/1/24 - 31/12/24 | G36: Percent sold | H36: Amount sold | I36: Amount unit | J36: ="% of revenue " & TEXT($E$17, "d/m/y") & " - " & TEXT($E$18, "d/m/y") -> % of revenue 1/1/24 - 31/12/24
A37: =HYPERLINK("#'Constants - Cropping'!A1", "Constants - Cropping") -> Constants - Cropping | D37: ="Harvested " & LOWER('Input - Grains'!$E$9) & " grain" -> Harvested wheat grain | E37: Main product | F37: ='Input - Grains'!E26 -> 1000 | G37: 1 | H37: =F37*G37 -> 1000 | I37: Tonnes | J37: 0.75
A38: =HYPERLINK("#'Constants - Livestock'!A1", "Constants - Livestock") -> Constants - Livestock | D38: ="Whole " & LOWER('Input - Grains'!$E$9) & " plant harvested for feed" -> Whole wheat plant harvested for feed | E38: By-product (if sold) | F38: ='Input - Grains'!E27 -> 0 | G38: 0.5 | H38: =F38*G38 -> 0 | I38: Tonnes | J38: 0.12
A39: =HYPERLINK("#'Constants - Dairy'!A1", "Constants - Dairy") -> Constants - Dairy | D39: ="Baled harvested " & LOWER('Input - Grains'!$E$9) & " residue" -> Baled harvested wheat residue | E39: By-product (if sold) | F39: ='Input - Grains'!E37 -> 0 | G39: 0.5 | H39: =F39*G39 -> 0 | I39: Tonnes | J39: 0.12
A40: Sources & acknowledgements | D40: ="Baled failed/cover " & LOWER('Input - Grains'!$E$9) & " crop" -> Baled failed/cover wheat crop | E40: By-product (if sold) | F40: ='Input - Grains'!E76 -> 0 | G40: 0 | H40: =F40*G40 -> 0 | I40: Tonnes | J40: 0
E42: Emissions calculation periods
D43: Activity | E43: {=TRANSPOSE(Common_InputFunctions.getOverlappingReportingPeriods(E13,E14,E17))} -> 01 Jan 2020 to 31 Dec 2020 | F43: 01 Jan 2021 to 31 Dec 2021 | G43: 01 Jan 2022 to 31 Dec 2022 | H43: 01 Jan 2023 to 31 Dec 2023 | I43: 01 Jan 2024 to 31 Dec 2024
D44: Fuel use | E44: =IF(COUNTA($E$43:$I$43)>=1, 1/COUNTA($E$43:$I$43), "") -> 0.2 | F44: =IF(COUNTA($E$43:$I$43)>=2, 1/COUNTA($E$43:$I$43), "") -> 0.2 | G44: =IF(COUNTA($E$43:$I$43)>=3, 1/COUNTA($E$43:$I$43), "") -> 0.2 | H44: =IF(COUNTA($E$43:$I$43)>=4, 1/COUNTA($E$43:$I$43), "") -> 0.2 | I44: =IF(COUNTA($E$43:$I$43)>=5, 1/COUNTA($E$43:$I$43), "") -> 0.2
D45: Fertiliser application | E45: =IF(COUNTA($E$43:$I$43)>=1, 1/COUNTA($E$43:$I$43), "") -> 0.2 | F45: =IF(COUNTA($E$43:$I$43)>=2, 1/COUNTA($E$43:$I$43), "") -> 0.2 | G45: =IF(COUNTA($E$43:$I$43)>=3, 1/COUNTA($E$43:$I$43), "") -> 0.2 | H45: =IF(COUNTA($E$43:$I$43)>=4, 1/COUNTA($E$43:$I$43), "") -> 0.2 | I45: =IF(COUNTA($E$43:$I$43)>=5, 1/COUNTA($E$43:$I$43), "") -> 0.2
D46: Lime application | E46: =IF(COUNTA($E$43:$I$43)>=1, 1/COUNTA($E$43:$I$43), "") -> 0.2 | F46: =IF(COUNTA($E$43:$I$43)>=2, 1/COUNTA($E$43:$I$43), "") -> 0.2 | G46: =IF(COUNTA($E$43:$I$43)>=3, 1/COUNTA($E$43:$I$43), "") -> 0.2 | H46: =IF(COUNTA($E$43:$I$43)>=4, 1/COUNTA($E$43:$I$43), "") -> 0.2 | I46: =IF(COUNTA($E$43:$I$43)>=5, 1/COUNTA($E$43:$I$43), "") -> 0.2
D47: Agrochemical application | E47: =IF(COUNTA($E$43:$I$43)>=1, 1/COUNTA($E$43:$I$43), "") -> 0.2 | F47: =IF(COUNTA($E$43:$I$43)>=2, 1/COUNTA($E$43:$I$43), "") -> 0.2 | G47: =IF(COUNTA($E$43:$I$43)>=3, 1/COUNTA($E$43:$I$43), "") -> 0.2 | H47: =IF(COUNTA($E$43:$I$43)>=4, 1/COUNTA($E$43:$I$43), "") -> 0.2 | I47: =IF(COUNTA($E$43:$I$43)>=5, 1/COUNTA($E$43:$I$43), "") -> 0.2
D48: Electricity use | E48: =IF(COUNTA($E$43:$I$43)>=1, 1/COUNTA($E$43:$I$43), "") -> 0.2 | F48: =IF(COUNTA($E$43:$I$43)>=2, 1/COUNTA($E$43:$I$43), "") -> 0.2 | G48: =IF(COUNTA($E$43:$I$43)>=3, 1/COUNTA($E$43:$I$43), "") -> 0.2 | H48: =IF(COUNTA($E$43:$I$43)>=4, 1/COUNTA($E$43:$I$43), "") -> 0.2 | I48: =IF(COUNTA($E$43:$I$43)>=5, 1/COUNTA($E$43:$I$43), "") -> 0.2
D49: Refrigerant use | E49: =IF(COUNTA($E$43:$I$43)>=1, 1/COUNTA($E$43:$I$43), "") -> 0.2 | F49: =IF(COUNTA($E$43:$I$43)>=2, 1/COUNTA($E$43:$I$43), "") -> 0.2 | G49: =IF(COUNTA($E$43:$I$43)>=3, 1/COUNTA($E$43:$I$43), "") -> 0.2 | H49: =IF(COUNTA($E$43:$I$43)>=4, 1/COUNTA($E$43:$I$43), "") -> 0.2 | I49: =IF(COUNTA($E$43:$I$43)>=5, 1/COUNTA($E$43:$I$43), "") -> 0.2
D50: Waste generation | E50: =IF(COUNTA($E$43:$I$43)>=1, 1/COUNTA($E$43:$I$43), "") -> 0.2 | F50: =IF(COUNTA($E$43:$I$43)>=2, 1/COUNTA($E$43:$I$43), "") -> 0.2 | G50: =IF(COUNTA($E$43:$I$43)>=3, 1/COUNTA($E$43:$I$43), "") -> 0.2 | H50: =IF(COUNTA($E$43:$I$43)>=4, 1/COUNTA($E$43:$I$43), "") -> 0.2 | I50: =IF(COUNTA($E$43:$I$43)>=5, 1/COUNTA($E$43:$I$43), "") -> 0.2
D51: Livestock management (don't edit) | E51: =IF(COUNTA($E$43:$I$43)>=1, 1/COUNTA($E$43:$I$43), "") -> 0.2 | F51: =IF(COUNTA($E$43:$I$43)>=2, 1/COUNTA($E$43:$I$43), "") -> 0.2 | G51: =IF(COUNTA($E$43:$I$43)>=3, 1/COUNTA($E$43:$I$43), "") -> 0.2 | H51: =IF(COUNTA($E$43:$I$43)>=4, 1/COUNTA($E$43:$I$43), "") -> 0.2 | I51: =IF(COUNTA($E$43:$I$43)>=5, 1/COUNTA($E$43:$I$43), "") -> 0.2
D55: Purchases
D56: Feed | E56: =IF(COUNTA($E$43:$I$43)>=1, 1/COUNTA($E$43:$I$43), "") -> 0.2 | F56: =IF(COUNTA($E$43:$I$43)>=2, 1/COUNTA($E$43:$I$43), "") -> 0.2 | G56: =IF(COUNTA($E$43:$I$43)>=3, 1/COUNTA($E$43:$I$43), "") -> 0.2 | H56: =IF(COUNTA($E$43:$I$43)>=4, 1/COUNTA($E$43:$I$43), "") -> 0.2 | I56: =IF(COUNTA($E$43:$I$43)>=5, 1/COUNTA($E$43:$I$43), "") -> 0.2
D57: Cleaning chemicals | E57: =IF(COUNTA($E$43:$I$43)>=1, 1/COUNTA($E$43:$I$43), "") -> 0.2 | F57: =IF(COUNTA($E$43:$I$43)>=2, 1/COUNTA($E$43:$I$43), "") -> 0.2 | G57: =IF(COUNTA($E$43:$I$43)>=3, 1/COUNTA($E$43:$I$43), "") -> 0.2 | H57: =IF(COUNTA($E$43:$I$43)>=4, 1/COUNTA($E$43:$I$43), "") -> 0.2 | I57: =IF(COUNTA($E$43:$I$43)>=5, 1/COUNTA($E$43:$I$43), "") -> 0.2
D58: ear tags | E58: =IF(COUNTA($E$43:$I$43)>=1, 1/COUNTA($E$43:$I$43), "") -> 0.2 | F58: =IF(COUNTA($E$43:$I$43)>=2, 1/COUNTA($E$43:$I$43), "") -> 0.2 | G58: =IF(COUNTA($E$43:$I$43)>=3, 1/COUNTA($E$43:$I$43), "") -> 0.2 | H58: =IF(COUNTA($E$43:$I$43)>=4, 1/COUNTA($E$43:$I$43), "") -> 0.2 | I58: =IF(COUNTA($E$43:$I$43)>=5, 1/COUNTA($E$43:$I$43), "") -> 0.2

Sheet Input - Herd - Dairy
A1: #VALUE! | C1: Input - Herd - Dairy
A3: Home
A4: =HYPERLINK("#'Results'!A1", "Results") -> Results
D5: Monthly average head count
A6: INPUTS
A7: =HYPERLINK("#'Input - Site'!A1", "Site") -> Site | D7: Month | E7: Milking cows | F7: Heifers > 1 year | G7: Heifers < 1 year | H7: Bulls > 1 year | I7: Bulls < 1 year
A8: =HYPERLINK("#'Input - Production'!A1", "Production and outputs") -> Production and outputs | D8: =TEXT('Input - Site'!$E$12,"mmmm yyyy") -> January 2024 | E8: 120 | F8: 75 | G8: 55 | H8: 3 | I8: 3 | J8: Head
A9: =HYPERLINK("#'Input - Herd - Dairy'!A1", "Herd - Dairy") -> Herd - Dairy | D9: =TEXT(EDATE('Input - Site'!$E$12, 1),"mmmm yyyy") -> February 2024 | E9: 120 | F9: 75 | G9: 55 | H9: 3 | I9: 3 | J9: Head
A10: =HYPERLINK("#'Input - Feed - Dairy'!A1", "Purchased feed - Livestock") -> Purchased feed - Livestock | D10: =TEXT(EDATE('Input - Site'!$E$12, 2),"mmmm yyyy") -> March 2024 | E10: 120 | F10: 75 | G10: 55 | H10: 3 | I10: 3 | J10: Head
A11: =HYPERLINK("#'Input - Herd - Feedlot'!A1", "Herd - Feedlot") -> Herd - Feedlot | D11: =TEXT(EDATE('Input - Site'!$E$12, 3),"mmmm yyyy") -> April 2024 | E11: 120 | F11: 75 | G11: 55 | H11: 3 | I11: 3 | J11: Head
A12: =HYPERLINK("#'Input - Pasture'!A1", "Pasture") -> Pasture | D12: =TEXT(EDATE('Input - Site'!$E$12, 4),"mmmm yyyy") -> May 2024 | E12: 120 | F12: 75 | G12: 55 | H12: 3 | I12: 3 | J12: Head
A13: =HYPERLINK("#'Input - Grains'!A1", "Crop - Grains") -> Crop - Grains | D13: =TEXT(EDATE('Input - Site'!$E$12, 5),"mmmm yyyy") -> June 2024 | E13: 120 | F13: 75 | G13: 55 | H13: 3 | I13: 3 | J13: Head
A14: =HYPERLINK("#'Input - Fert Lime Chem'!A1", "Fertiliser, Lime & Chemicals") -> Fertiliser, Lime & Chemicals | D14: =TEXT(EDATE('Input - Site'!$E$12, 6),"mmmm yyyy") -> July 2024 | E14: 120 | F14: 75 | G14: 55 | H14: 3 | I14: 3 | J14: Head
A15: =HYPERLINK("#'Input - Fuel & Energy'!A1", "Electricity and fuel") -> Electricity and fuel | D15: =TEXT(EDATE('Input - Site'!$E$12, 7),"mmmm yyyy") -> August 2024 | E15: 120 | F15: 75 | G15: 55 | H15: 3 | I15: 3 | J15: Head
A16: Waste | D16: =TEXT(EDATE('Input - Site'!$E$12, 8),"mmmm yyyy") -> September 2024 | E16: 120 | F16: 103 | G16: 57.5 | H16: 4.5 | I16: 31.5 | J16: Head
A17: Freight and transport | D17: =TEXT(EDATE('Input - Site'!$E$12, 9),"mmmm yyyy") -> October 2024 | E17: 120 | F17: 130 | G17: 60 | H17: 8 | I17: 60 | J17: Head
A18: =HYPERLINK("#'Input - Other Farm Inputs'!A1", "Other farm inputs") -> Other farm inputs | D18: =TEXT(EDATE('Input - Site'!$E$12, 10),"mmmm yyyy") -> November 2024 | E18: 120 | F18: 130 | G18: 60 | H18: 6 | I18: 32.5 | J18: Head
A19: =HYPERLINK("#'Input - Data quality'!A1", "Data quality") -> Data quality | D19: =TEXT(EDATE('Input - Site'!$E$12, 11),"mmmm yyyy") -> December 2024 | E19: 120 | F19: 130 | G19: 60 | H19: 6 | I19: 5 | J19: Head
A21: CALCULATIONS
A22: N2O MMS | D22: Monthly average liveweight
A23: Enteric methane
A24: =HYPERLINK("#'Calcs - Fert Lime'!A1", "Fertiliser & soil amendments") -> Fertiliser & soil amendments | D24: Month | E24: Milking cows | F24: Heifers > 1 year | G24: Heifers < 1 year | H24: Bulls > 1 year | I24: Bulls < 1 year
A25: =HYPERLINK("#'Calcs - Residue mgmt - Crop'!A1", "Residue management - Crop") -> Residue management - Crop | D25: =TEXT('Input - Site'!$E$12,"mmmm yyyy") -> January 2024 | E25: 510 | F25: 452.17 | G25: 215.52055 | H25: 500.21233 | I25: 215.94521 | J25: kg/head
A26: =HYPERLINK("#'Calcs - Residue mgmt - Pasture'!A1", "Residue management - Pasture") -> Residue management - Pasture | D26: =TEXT(EDATE('Input - Site'!$E$12, 1),"mmmm yyyy") -> February 2024 | E26: 510 | F26: 456.37 | G26: 226.20548 | H26: 500.62329 | I26: 227.45205 | J26: kg/head
A27: =HYPERLINK("#'Calcs - Field burning'!A1", "Field burning - Crop") -> Field burning - Crop | D27: =TEXT(EDATE('Input - Site'!$E$12, 2),"mmmm yyyy") -> March 2024 | E27: 510 | F27: 460.57 | G27: 236.89041 | H27: 501.03425 | I27: 238.9589 | J27: kg/head
A28: =HYPERLINK("#'Calcs - Fuel'!A1", "Fuel") -> Fuel | D28: =TEXT(EDATE('Input - Site'!$E$12, 3),"mmmm yyyy") -> April 2024 | E28: 510 | F28: 464.84 | G28: 247.75342 | H28: 501.45205 | I28: 250.65753 | J28: kg/head
A29: =HYPERLINK("#'Calcs - Electricity'!A1", "Electricity") -> Electricity | D29: =TEXT(EDATE('Input - Site'!$E$12, 4),"mmmm yyyy") -> May 2024 | E29: 510 | F29: 469.11 | G29: 258.61644 | H29: 501.86986 | I29: 262.35616 | J29: kg/head
A30: =HYPERLINK("#'Calcs - Refrigerants'!A1", "Refrigerants") -> Refrigerants | D30: =TEXT(EDATE('Input - Site'!$E$12, 5),"mmmm yyyy") -> June 2024 | E30: 510 | F30: 473.38 | G30: 269.47945 | H30: 502.28767 | I30: 274.05479 | J30: kg/head
A31: Waste | D31: =TEXT(EDATE('Input - Site'!$E$12, 6),"mmmm yyyy") -> July 2024 | E31: 510 | F31: 477.65 | G31: 280.34247 | H31: 502.70548 | I31: 285.75342 | J31: kg/head
A32: Freight and transport | D32: =TEXT(EDATE('Input - Site'!$E$12, 7),"mmmm yyyy") -> August 2024 | E32: 510 | F32: 481.99 | G32: 291.38356 | H32: 503.13014 | I32: 297.64384 | J32: kg/head
A33: =HYPERLINK("#'Calcs - Scope 3'!A1", "Purchased goods scope 3") -> Purchased goods scope 3 | D33: =TEXT(EDATE('Input - Site'!$E$12, 8),"mmmm yyyy") -> September 2024 | E33: 510 | F33: 455.29077 | G33: 201.94521 | H33: 465.15753 | I33: 205.47945 | J33: kg/head
D34: =TEXT(EDATE('Input - Site'!$E$12, 9),"mmmm yyyy") -> October 2024 | E34: 510 | F34: 428.59154 | G34: 112.50685 | H34: 427.18493 | I34: 113.31507 | J34: kg/head
A35: APPENDICES | D35: =TEXT(EDATE('Input - Site'!$E$12, 10),"mmmm yyyy") -> November 2024 | E35: 510 | F35: 432.86154 | G35: 123.36986 | H35: 427.60274 | I35: 125.0137 | J35: kg/head
