Workbook
Name _Toc225350871: '5.4.1.1-4 Atmos deposition'!$C$1
Name _Toc225350871: '5.5.1.1-2 Leaching and runoff'!$C$1
Name AgResidue_Equations_CropResidue.VEERG_6_1_1_1__1__NitrousOxideEmissionsFromCropResidues: _xlfn.LAMBDA(_xlpm.M_c,_xlpm.EF_Ni,_xlpm.C_N2O, _xlpm.M_c * _xlpm.EF_Ni * _xlpm.C_N2O * 10 ^ (-3))
Name AgResidue_Equations_CropResidue.VEERG_6_1_1_1__1__NitrousOxideEmissionsFromCropResidues_FunctionName: _xlfn.LAMBDA("VEERG_6_1_1_1__1__NitrousOxideEmissionsFromCropResidues")
Name AgResidue_Equations_CropResidue.VEERG_6_1_1_1__1__NitrousOxideEmissionsFromCropResidues_LatexEquation: _xlfn.LAMBDA("E=\sum\nolimits_c\left(M_{c}\times EF_{N}\right)\times C_{g,N2O}\times 10^{-3}")
Name AgResidue_Equations_CropResidue.VEERG_6_1_1_1__1__NitrousOxideEmissionsFromCropResidues_NIRReference: _xlfn.LAMBDA("")
Name AgResidue_Equations_CropResidue.VEERG_6_1_1_1__1__NitrousOxideEmissionsFromCropResidues_Source: _xlfn.LAMBDA("VEERG 2026: 6.1.1.1, Equation (1)")
Name AgResidue_Equations_CropResidue.VEERG_6_1_1_1__1__NitrousOxideEmissionsFromCropResidues_Title: _xlfn.LAMBDA("Nitrous oxide emissions from the return of crop residues across all crops c to the soil")
Name AgResidue_Equations_CropResidue.VEERG_6_1_1_1__1__NitrousOxideEmissionsFromCropResidues_Unit: _xlfn.LAMBDA("t N2O")
Name AgResidue_Equations_CropResidue.VEERG_6_1_1_1__1__NitrousOxideEmissionsFromCropResidues_Variable: _xlfn.LAMBDA("E")
Name AgResidue_Equations_CropResidue.VEERG_6_1_1_1__2__MassOfNitrogenInCropResidues_LatexEquation: _xlfn.LAMBDA("M_{c}=(P_{c}\times R_{AGc}\times(1-F_{c}-FFOD_{c})\times DM_{c}\times NC_{AGc})+(P_{c}\times R_{AGc}\times R_{BGc}\times DM_{c}\times NC_{BGc})")
Name AgResidue_Equations_CropResidue.VEERG_6_1_1_1__2__MassOfNitrogenInCropResidues_NIRReference: _xlfn.LAMBDA("")
Name AgResidue_Equations_CropResidue.VEERG_6_1_1_1__2__MassOfNitrogenInCropResidues_Source: _xlfn.LAMBDA("VEERG 2026: 6.1.1.1, Equation (2)")
Name AgResidue_Equations_CropResidue.VEERG_6_1_1_1__2__MassOfNitrogenInCropResidues_Title: _xlfn.LAMBDA("Mass of nitrogen in crop residues returned to the soil")
Name AgResidue_Equations_CropResidue.VEERG_6_1_1_1__2__MassOfNitrogenInCropResidues_Unit: _xlfn.LAMBDA("kg N")
Name AgResidue_Equations_CropResidue.VEERG_6_1_1_1__2__MassOfNitrogenInCropResidues_Variable: _xlfn.LAMBDA("M_c")
Name AgResidue_Equations_CropResidue.VEERG_6_1_1_2__1__FractionOfCropResidueRemovedBaled: _xlfn.LAMBDA(_xlpm.B,_xlpm.M_B,_xlpm.P_c,_xlpm.R_AGc, IFERROR((_xlpm.B * _xlpm.M_B) / (_xlpm.P_c * _xlpm.R_AGc), 0))
Name AgResidue_Equations_CropResidue.VEERG_6_1_1_2__1__FractionOfCropResidueRemovedBaled_LatexEquation: _xlfn.LAMBDA("FFOD_{c,baled}=\frac{B\times M_{B}}{P_{c}\times R_{AG,c}}")
Name AgResidue_Equations_CropResidue.VEERG_6_1_1_2__1__FractionOfCropResidueRemovedBaled_NIRReference: _xlfn.LAMBDA("")
Name AgResidue_Equations_CropResidue.VEERG_6_1_1_2__1__FractionOfCropResidueRemovedBaled_Source: _xlfn.LAMBDA("VEERG 2026: 6.1.1.2, Equation (1)")
Name AgResidue_Equations_CropResidue.VEERG_6_1_1_2__1__FractionOfCropResidueRemovedBaled_Title: _xlfn.LAMBDA("Fraction of crop residue that is removed for crop c, calculated where residues are baled")
Name AgResidue_Equations_CropResidue.VEERG_6_1_1_2__1__FractionOfCropResidueRemovedBaled_Unit: _xlfn.LAMBDA("dimensionless")
Name AgResidue_Equations_CropResidue.VEERG_6_1_1_2__1__FractionOfCropResidueRemovedBaled_Variable: _xlfn.LAMBDA("FFOD_cbaled")
Name AgResidue_Equations_CropResidue.VEERG_6_1_1_2__1__FractionOfCropResidueRemovedBaled_Variation: _xlfn.LAMBDA("VARIATION FROM SOURCE: Added 'baled' to variable subscript")
Name AgResidue_Equations_CropResidue.VEERG_6_1_1_2__1a__FractionOfCropResidueRemoved: _xlfn.LAMBDA(_xlpm.FFOD_cbaled,_xlpm.FFOD_cother, _xlpm.FFOD_cbaled + _xlpm.FFOD_cother)
Name AgResidue_Equations_CropResidue.VEERG_6_1_1_2__1a__FractionOfCropResidueRemoved_LatexEquation: _xlfn.LAMBDA("FFOD_{c} = FFOD_{c,baled} + FFOD_{c,other}")
Name AgResidue_Equations_CropResidue.VEERG_6_1_1_2__1a__FractionOfCropResidueRemoved_NIRReference: _xlfn.LAMBDA("")
Name AgResidue_Equations_CropResidue.VEERG_6_1_1_2__1a__FractionOfCropResidueRemoved_Source: _xlfn.LAMBDA("")
Name AgResidue_Equations_CropResidue.VEERG_6_1_1_2__1a__FractionOfCropResidueRemoved_Title: _xlfn.LAMBDA("Fraction of crop residue that is removed for crop c")
Name AgResidue_Equations_CropResidue.VEERG_6_1_1_2__1a__FractionOfCropResidueRemoved_Unit: _xlfn.LAMBDA("dimensionless")
Name AgResidue_Equations_CropResidue.VEERG_6_1_1_2__1a__FractionOfCropResidueRemoved_Variable: _xlfn.LAMBDA("FFOD_c")
Name AgResidue_Equations_CropResidue.VEERG_6_1_1_2__1a__FractionOfCropResidueRemoved_Variation: _xlfn.LAMBDA("VARIATION FROM SOURCE: Added this equation to accommodate user-defined residue removal other than baling.")
Name AgResidue_Equations_FieldBurning.VEERG_6_4_1_1__1__MethaneEmissionsFromBurningOfCropResidues: _xlfn.LAMBDA(_xlpm.M_burnc,_xlpm.CC_c,_xlpm.EF_CH4,_xlpm.C_CH4, (_xlpm.M_burnc * _xlpm.CC_c) * _xlpm.EF_CH4 * _xlpm.C_CH4 * 10 ^ (-3))
Name AgResidue_Equations_FieldBurning.VEERG_6_4_1_1__1__MethaneEmissionsFromBurningOfCropResidues: _xlfn.LAMBDA(_xlpm.M_burnc,_xlpm.CC_c,_xlpm.EF_CH4,_xlpm.C_CH4, (_xlpm.M_burnc * _xlpm.CC_c) * _xlpm.EF_CH4 * _xlpm.C_CH4 * 10 ^ (-3))
Name AgResidue_Equations_FieldBurning.VEERG_6_4_1_1__1__MethaneEmissionsFromBurningOfCropResidues: _xlfn.LAMBDA(_xlpm.M_burnc,_xlpm.CC_c,_xlpm.EF_CH4,_xlpm.C_CH4, (_xlpm.M_burnc * _xlpm.CC_c) * _xlpm.EF_CH4 * _xlpm.C_CH4 * 10 ^ (-3))
Name AgResidue_Equations_FieldBurning.VEERG_6_4_1_1__1__MethaneEmissionsFromBurningOfCropResidues: _xlfn.LAMBDA(_xlpm.M_burnc,_xlpm.CC_c,_xlpm.EF_CH4,_xlpm.C_CH4, (_xlpm.M_burnc * _xlpm.CC_c) * _xlpm.EF_CH4 * _xlpm.C_CH4 * 10 ^ (-3))
Name AgResidue_Equations_FieldBurning.VEERG_6_4_1_1__1__MethaneEmissionsFromBurningOfCropResidues: _xlfn.LAMBDA(_xlpm.Mburnc,_xlpm.CCc,_xlpm.EFCH4,_xlpm.C_CH4, _xlpm.Mburnc * _xlpm.CCc * _xlpm.EFCH4 * _xlpm.C_CH4 * 10 ^ (-3))
Name AgResidue_Equations_FieldBurning.VEERG_6_4_1_1__1__MethaneEmissionsFromBurningOfCropResidues_FunctionName: _xlfn.LAMBDA("VEERG_6_4_1_1__1__MethaneEmissionsFromBurningOfCropResidues")
Name AgResidue_Equations_FieldBurning.VEERG_6_4_1_1__1__MethaneEmissionsFromBurningOfCropResidues_LatexEquation: _xlfn.LAMBDA("E_{CH4}=\sum\nolimits_c(M_{burn,c}\times CC_{c})\times EF_{CH4}\times C_{CH4}\times 10^{-3}")
Name AgResidue_Equations_FieldBurning.VEERG_6_4_1_1__1__MethaneEmissionsFromBurningOfCropResidues_LatexEquation: _xlfn.LAMBDA("E_{CH4}=\sum\nolimits_c(M_{burn,c}\times CC_{c})\times EF_{CH4}\times C_{CH4}\times 10^{-3}")
Name AgResidue_Equations_FieldBurning.VEERG_6_4_1_1__1__MethaneEmissionsFromBurningOfCropResidues_LatexEquation: _xlfn.LAMBDA("E_{CH4}=\sum\nolimits_c(M_{burn,c}\times CC_{c})\times EF_{CH4}\times C_{CH4}\times 10^{-3}")
Name AgResidue_Equations_FieldBurning.VEERG_6_4_1_1__1__MethaneEmissionsFromBurningOfCropResidues_LatexEquation: _xlfn.LAMBDA("E_{CH4}=\sum\nolimits_c(M_{burn,c}\times CC_{c})\times EF_{CH4}\times C_{CH4}\times 10^{-3}")
Name AgResidue_Equations_FieldBurning.VEERG_6_4_1_1__1__MethaneEmissionsFromBurningOfCropResidues_LatexEquation: _xlfn.LAMBDA("E_{CH4}=\sum_{c}(M_{burn,c}\times CC_{c}\times EF_{CH4}\times C_{CH4}\times 10^{-3})")
Name AgResidue_Equations_FieldBurning.VEERG_6_4_1_1__1__MethaneEmissionsFromBurningOfCropResidues_NIRReference: _xlfn.LAMBDA("")
Name AgResidue_Equations_FieldBurning.VEERG_6_4_1_1__1__MethaneEmissionsFromBurningOfCropResidues_Source: _xlfn.LAMBDA("VEERG 2026: 6.4.1.1, Equation (1)")
Name AgResidue_Equations_FieldBurning.VEERG_6_4_1_1__1__MethaneEmissionsFromBurningOfCropResidues_Title: _xlfn.LAMBDA("Methane emissions from the burning of crop residues")
Name AgResidue_Equations_FieldBurning.VEERG_6_4_1_1__1__MethaneEmissionsFromBurningOfCropResidues_Unit: _xlfn.LAMBDA("t CH4")
Name AgResidue_Equations_FieldBurning.VEERG_6_4_1_1__1__MethaneEmissionsFromBurningOfCropResidues_Variable: _xlfn.LAMBDA("ECH4")
Name AgResidue_Equations_FieldBurning.VEERG_6_4_1_1__2__NitrousOxideEmissionsFromBurningOfCropResidues: _xlfn.LAMBDA(_xlpm.M_burnc,_xlpm.NC_AGc,_xlpm.EF_N2O,_xlpm.C_N2O, (_xlpm.M_burnc * _xlpm.NC_AGc) * _xlpm.EF_N2O * _xlpm.C_N2O * 10 ^ (-3))
Name AgResidue_Equations_FieldBurning.VEERG_6_4_1_1__2__NitrousOxideEmissionsFromBurningOfCropResidues: _xlfn.LAMBDA(_xlpm.M_burnc,_xlpm.NC_AGc,_xlpm.EF_N2O,_xlpm.C_N2O, (_xlpm.M_burnc * _xlpm.NC_AGc) * _xlpm.EF_N2O * _xlpm.C_N2O * 10 ^ (-3))
Name AgResidue_Equations_FieldBurning.VEERG_6_4_1_1__2__NitrousOxideEmissionsFromBurningOfCropResidues: _xlfn.LAMBDA(_xlpm.M_burnc,_xlpm.NC_AGc,_xlpm.EF_N2O,_xlpm.C_N2O, (_xlpm.M_burnc * _xlpm.NC_AGc) * _xlpm.EF_N2O * _xlpm.C_N2O * 10 ^ (-3))
Name AgResidue_Equations_FieldBurning.VEERG_6_4_1_1__2__NitrousOxideEmissionsFromBurningOfCropResidues: _xlfn.LAMBDA(_xlpm.M_burnc,_xlpm.NC_AGc,_xlpm.EF_N2O,_xlpm.C_N2O, (_xlpm.M_burnc * _xlpm.NC_AGc) * _xlpm.EF_N2O * _xlpm.C_N2O * 10 ^ (-3))
Name AgResidue_Equations_FieldBurning.VEERG_6_4_1_1__2__NitrousOxideEmissionsFromBurningOfCropResidues: _xlfn.LAMBDA(_xlpm.Mburnc,_xlpm.NCAGc,_xlpm.EFN2O,_xlpm.CN2O, _xlpm.Mburnc * _xlpm.NCAGc * _xlpm.EFN2O * _xlpm.CN2O * 10 ^ (-3))
Name AgResidue_Equations_FieldBurning.VEERG_6_4_1_1__2__NitrousOxideEmissionsFromBurningOfCropResidues_FunctionName: _xlfn.LAMBDA("VEERG_6_4_1_1__2__NitrousOxideEmissionsFromBurningOfCropResidues")
Name AgResidue_Equations_FieldBurning.VEERG_6_4_1_1__2__NitrousOxideEmissionsFromBurningOfCropResidues_LatexEquation: _xlfn.LAMBDA("E_{N2O}=\sum\nolimits_c(M_{burn,c}\times NC_{AGc})\times EF_{N2O}\times C_{N2O}\times 10^{-3}")
Name AgResidue_Equations_FieldBurning.VEERG_6_4_1_1__2__NitrousOxideEmissionsFromBurningOfCropResidues_LatexEquation: _xlfn.LAMBDA("E_{N2O}=\sum\nolimits_c(M_{burn,c}\times NC_{AGc})\times EF_{N2O}\times C_{N2O}\times 10^{-3}")
Name AgResidue_Equations_FieldBurning.VEERG_6_4_1_1__2__NitrousOxideEmissionsFromBurningOfCropResidues_LatexEquation: _xlfn.LAMBDA("E_{N2O}=\sum\nolimits_c(M_{burn,c}\times NC_{AGc})\times EF_{N2O}\times C_{N2O}\times 10^{-3}")
Name AgResidue_Equations_FieldBurning.VEERG_6_4_1_1__2__NitrousOxideEmissionsFromBurningOfCropResidues_LatexEquation: _xlfn.LAMBDA("E_{N2O}=\sum\nolimits_c(M_{burn,c}\times NC_{AGc})\times EF_{N2O}\times C_{N2O}\times 10^{-3}")
Name AgResidue_Equations_FieldBurning.VEERG_6_4_1_1__2__NitrousOxideEmissionsFromBurningOfCropResidues_LatexEquation: _xlfn.LAMBDA("E_{N2O}=\sum_{c}(M_{burn,c}\times NC_{AGc}\times EF_{N2O}\times C_{N2O}\times 10^{-3})")
Name AgResidue_Equations_FieldBurning.VEERG_6_4_1_1__2__NitrousOxideEmissionsFromBurningOfCropResidues_NIRReference: _xlfn.LAMBDA("")

Sheet Home
A1: #VALUE!
A3: =HYPERLINK("#'Home'!A1", "Home") -> Home
A4: =HYPERLINK("#'Results'!A1", "Results") -> Results
A7: INPUTS
A8: =HYPERLINK("#'Input - Enterprise'!A1", "Enterprise") -> Enterprise
A9: =HYPERLINK("#'Input - Site'!A1", "Site") -> Site
A10: =HYPERLINK("#'Input - Pasture Beef'!A1", "Pasture Beef") -> Pasture Beef
A11: =HYPERLINK("#'Input - Pasture Beef (Enteric)'!A1", "Pasture Beef (Enteric)") -> Pasture Beef (Enteric)
A12: =HYPERLINK("#'Input - Pasture'!A1", "Pasture") -> Pasture
A13: =HYPERLINK("#'Input - Fertiliser'!A1", "Fertiliser") -> Fertiliser
A14: =HYPERLINK("#'Input - Fuel'!A1", "Fuel") -> Fuel
A15: =HYPERLINK("#'Input - Electricity'!A1", "Electricity") -> Electricity
A18: CALCULATIONS
A19: =HYPERLINK("#'3.2.1.1-2 Enteric Methane'!A1", "3.2.1.1-2 Enteric methane") -> 3.2.1.1-2 Enteric methane
A20: =HYPERLINK("#'4.2.1.1-2 Methane'!A1", "4.2.1.1-2 Manure methane") -> 4.2.1.1-2 Manure methane
A21: =HYPERLINK("#'4.2.1.3-4 Soil direct N20'!A1", "4.2.1.3-4 Soil direct N2O") -> 4.2.1.3-4 Soil direct N2O
A22: =HYPERLINK("#'4.2.1.5-6 Soil Atmos Dep'!A1", "4.2.1.5-6 Soil atm. deposition") -> 4.2.1.5-6 Soil atm. deposition
A23: =HYPERLINK("#'4.2.1.7-8 Soil leach runoff'!A1", "4.2.1.7-8 Soil leach & runoff") -> 4.2.1.7-8 Soil leach & runoff
A24: =HYPERLINK("#'5.1.1.1-2 Inorganic fert N2O'!A1", "5.1.1.1-2 Inorganic fert N2O") -> 5.1.1.1-2 Inorganic fert N2O
A25: =HYPERLINK("#'5.1.1.3-4 Inorganic fert CO2'!A1", "5.1.1.3-4 Inorganic fert CO2") -> 5.1.1.3-4 Inorganic fert CO2
A26: =HYPERLINK("#'5.2.1.1-2 Organic Fert N2O'!A1", "5.2.1.1-2 Organic fert N2O") -> 5.2.1.1-2 Organic fert N2O
A27: =HYPERLINK("#'5.3.1.1-2 Lime CO2'!A1", "5.3.1.1-2 Lime CO2") -> 5.3.1.1-2 Lime CO2
A28: =HYPERLINK("#'5.4.1.1-4 Atmos deposition'!A1", "5.4.1.1-4 Atmos. deposition") -> 5.4.1.1-4 Atmos. deposition
A29: =HYPERLINK("#'5.5.1.1-2 Leaching and runoff'!A1", "5.5.1.1-2 Leaching & runoff") -> 5.5.1.1-2 Leaching & runoff
A30: =HYPERLINK("#'6.2.1.1-2 Pasture residue N2O'!A1", "6.2.1.1-2 Pasture residue N2O") -> 6.2.1.1-2 Pasture residue N2O
A31: =HYPERLINK("#'6.3.1.1-2 Leach runoff pasture'!A1", "6.3.1.1-2 Leach & runoff (pasture)") -> 6.3.1.1-2 Leach & runoff (pasture)
A32: =HYPERLINK("#'8.1.1.1-2 Transport fuel'!A1", "8.1.1.1-2 Transport fuel") -> 8.1.1.1-2 Transport fuel
A33: =HYPERLINK("#'8.2.1.1-2 Stationary fuel'!A1", "8.2.1.1-2 Stationary fuel") -> 8.2.1.1-2 Stationary fuel
A34: =HYPERLINK("#'14.1.1-2 Purchased electricity'!A1", "14.1.1-2 Purchased electricity") -> 14.1.1-2 Purchased electricity
A37: APPENDICES
A38: =HYPERLINK("#'Constants - Pasture Beef'!A1", "Constants - Pasture Beef") -> Constants - Pasture Beef
A39: =HYPERLINK("#'Constants - Ag Residue'!A1", "Constants - Ag residue") -> Constants - Ag residue
A40: =HYPERLINK("#'Constants - Common Livestock'!A1", "Constants - Common Livestock") -> Constants - Common Livestock
A41: =HYPERLINK("#'Constants - Electricity'!A1", "Constants - Electricity") -> Constants - Electricity
A42: =HYPERLINK("#'Constants - Fertiliser'!A1", "Constants - Fertiliser") -> Constants - Fertiliser
A43: =HYPERLINK("#'Constants - Fuel'!A1", "Constants - Fuel") -> Constants - Fuel
A44: =HYPERLINK("#'Constants - Common'!A1", "Constants - Common") -> Constants - Common
A45: =HYPERLINK("#'Acknowledgements'!A1", "Acknowledgements") -> Acknowledgements
A46: =HYPERLINK("#'Overview'!A1", "Overview") -> Overview

Sheet Results
A1: #VALUE! | C1: 4.2 Manure management: Pasture Beef: Results
A3: =HYPERLINK("#'Home'!A1", "Home") -> Home
A4: =HYPERLINK("#'Results'!A1", "Results") -> Results | D4: ="Emissions breakdown for activities running between " & TEXT(X_Cell_Site_StartDate, "dd mmmm yyyy") & " and " & TEXT('Input - Enterprise'!E13, "dd mmmm yyyy") -> Emissions breakdown for activities running between 01 January 2025 and 31 December 2025
D6: Scope 1 source | E6: GHG emissions method 1 | F6: GHG emissions method 2 | G6: GHG Unit | H6: CO2-e emissions method 1 | I6: CO2-e emissions method 2
A7: INPUTS | D7: 3.2.1.1-2 Enteric methane | E7: {=VEERG_3_2_1_1__1_TotalAnnualMethaneFromEntericFermentation_Result_Method1} -> 54.595755 | F7: {=VEERG_3_2_1_1__1_TotalAnnualMethaneFromEntericFermentation_Result_Method2} -> 54.699182 | G7: t CH4 | H7: {=Common_Equations.Common_ConvertCH4ToCO2e(E7,_xlfn.XLOOKUP("CH4", Table_GWPData[Gas],Table_GWPData[CO2-e factor]))} -> 1528.6812 | I7: {=Common_Equations.Common_ConvertCH4ToCO2e(F7,_xlfn.XLOOKUP("CH4", Table_GWPData[Gas],Table_GWPData[CO2-e factor]))} -> 1531.5771 | J7: t CO2e
A8: =HYPERLINK("#'Input - Enterprise'!A1", "Enterprise") -> Enterprise | D8: 4.2.1.1-2 Manure methane | E8: {=VEERG_4_2_1_1__1_TotalAnnualMethaneProductionFromManureManagement_Result_Method1} -> 0.88628531 | F8: {=VEERG_4_2_1_1__1_TotalAnnualMethaneProductionFromManureManagement_Result_Method2} -> 0.87215903 | G8: t CH4 | H8: {=Common_Equations.Common_ConvertCH4ToCO2e(E8,_xlfn.XLOOKUP("CH4", Table_GWPData[Gas],Table_GWPData[CO2-e factor]))} -> 24.815989 | I8: {=Common_Equations.Common_ConvertCH4ToCO2e(F8,_xlfn.XLOOKUP("CH4", Table_GWPData[Gas],Table_GWPData[CO2-e factor]))} -> 24.420453 | J8: t CO2e
A9: =HYPERLINK("#'Input - Site'!A1", "Site") -> Site | D9: 4.2.1.3-4 Soil direct N2O | E9: {=VEERG_4_2_1_3__1_DirectNitrousOxideEmissionsOnPasture_Result_Method1} -> 0.19011253 | F9: {=VEERG_4_2_1_3__1_DirectNitrousOxideEmissionsOnPasture_Result_Method2} -> 0.18099391 | G9: t N2O | H9: {=Common_Equations.Common_ConvertN2OToCO2e(E9,_xlfn.XLOOKUP("N2O", Table_GWPData[Gas],Table_GWPData[CO2-e factor]))} -> 50.37982 | I9: {=Common_Equations.Common_ConvertN2OToCO2e(F9,_xlfn.XLOOKUP("N2O", Table_GWPData[Gas],Table_GWPData[CO2-e factor]))} -> 47.963385 | J9: t CO2e
A10: =HYPERLINK("#'Input - Pasture Beef'!A1", "Pasture Beef") -> Pasture Beef | D10: 4.2.1.5-6 Soil atmospheric deposition | E10: {=VEERG_4_2_1_5__1_AtmosphericDepositionEmissionsFromUrineAndDungOnPasture_Result_Method1} -> 0.11777471 | F10: {=VEERG_4_2_1_5__1_AtmosphericDepositionEmissionsFromUrineAndDungOnPasture_Result_Method2} -> 0.11212572 | G10: t N2O | H10: {=Common_Equations.Common_ConvertN2OToCO2e(E10,_xlfn.XLOOKUP("N2O", Table_GWPData[Gas],Table_GWPData[CO2-e factor]))} -> 31.210298 | I10: {=Common_Equations.Common_ConvertN2OToCO2e(F10,_xlfn.XLOOKUP("N2O", Table_GWPData[Gas],Table_GWPData[CO2-e factor]))} -> 29.713317 | J10: t CO2e
A11: =HYPERLINK("#'Input - Pasture Beef (Enteric)'!A1", "Pasture Beef (Enteric)") -> Pasture Beef (Enteric) | D11: 4.2.1.7-8 Soil leaching and runoff | E11: {=VEERG_4_2_1_7__1_LeachingAndRunoffEmissionsFromUrineAndDungOnPasture_Result_Method1} -> 0.25094854 | F11: {=VEERG_4_2_1_7__1_LeachingAndRunoffEmissionsFromUrineAndDungOnPasture_Result_Method2} -> 0.23891196 | G11: t N2O | H11: {=Common_Equations.Common_ConvertN2OToCO2e(E11,_xlfn.XLOOKUP("N2O", Table_GWPData[Gas],Table_GWPData[CO2-e factor]))} -> 66.501362 | I11: {=Common_Equations.Common_ConvertN2OToCO2e(F11,_xlfn.XLOOKUP("N2O", Table_GWPData[Gas],Table_GWPData[CO2-e factor]))} -> 63.311668 | J11: t CO2e
A12: =HYPERLINK("#'Input - Pasture'!A1", "Pasture") -> Pasture | D12: 5.1.1.1-2 Inorganic fert N2O | E12: {=VEERG_5_1_1_1__1_InorganicFertiliserApplicationN2OEmissions_Result_Method1} -> 0.1431067 | F12: {=VEERG_5_1_1_1__1_InorganicFertiliserApplicationN2OEmissions_Result_Method2} -> 0.1431067 | G12: t N2O | H12: {=Common_Equations.Common_ConvertN2OToCO2e(E12,_xlfn.XLOOKUP("N2O", Table_GWPData[Gas],Table_GWPData[CO2-e factor]))} -> 37.923276 | I12: {=Common_Equations.Common_ConvertN2OToCO2e(F12,_xlfn.XLOOKUP("N2O", Table_GWPData[Gas],Table_GWPData[CO2-e factor]))} -> 37.923276 | J12: t CO2e
A13: =HYPERLINK("#'Input - Fertiliser'!A1", "Fertiliser") -> Fertiliser | D13: 5.1.1.3-4 Inorganic fert CO2 | E13: {=VEERG_5_1_1_3__1_InorganicFertiliserApplicationCO2Emissions_Result_Method1} -> 7.3333333 | F13: =E13 -> 7.3333333 | G13: t CO2 | H13: =E13 -> 7.3333333 | I13: =F13 -> 7.3333333 | J13: t CO2e
A14: =HYPERLINK("#'Input - Fuel'!A1", "Fuel") -> Fuel | D14: 5.2.1.1-2 Organic fert N2O | E14: {=VEERG_5_2_1_1__2_MassOfNitrogenInOrganicFertiliser_Result_Method1} -> 0.0055785714 | F14: =E14 -> 0.0055785714 | G14: t N2O | H14: {=Common_Equations.Common_ConvertN2OToCO2e(E14,_xlfn.XLOOKUP("N2O", Table_GWPData[Gas],Table_GWPData[CO2-e factor]))} -> 1.4783214 | I14: {=Common_Equations.Common_ConvertN2OToCO2e(F14,_xlfn.XLOOKUP("N2O", Table_GWPData[Gas],Table_GWPData[CO2-e factor]))} -> 1.4783214 | J14: t CO2e
A15: =HYPERLINK("#'Input - Electricity'!A1", "Electricity") -> Electricity | D15: 5.3.1.1-2 Lime CO2 | E15: {=VEERG_5_3_1_1__1_LimeApplicationCO2Emissions_Result_Method1} -> 75.808333 | F15: =E15 -> 75.808333 | G15: t CO2 | H15: =E15 -> 75.808333 | I15: =F15 -> 75.808333 | J15: t CO2e
D16: 5.4.1.1-4 Atmos. deposition | E16: {=VEERG_5_4_1_3__1_OrganicFertiliserAtmosphericDepositionN2OEmissions_Result_Method1} -> 0.0016401 | F16: =E16 -> 0.0016401 | G16: t N2O | H16: {=Common_Equations.Common_ConvertN2OToCO2e(E16,_xlfn.XLOOKUP("N2O", Table_GWPData[Gas],Table_GWPData[CO2-e factor]))} -> 0.4346265 | I16: {=Common_Equations.Common_ConvertN2OToCO2e(F16,_xlfn.XLOOKUP("N2O", Table_GWPData[Gas],Table_GWPData[CO2-e factor]))} -> 0.4346265 | J16: t CO2e
D17: 5.5.1.1-2 Leaching & runoff | E17: {=VEERG_5_5_1_1__1_FertiliserLeachingAndRunoffN2OEmissions_result_Method1} -> 0.056917155 | F17: =E17 -> 0.056917155 | G17: t N2O | H17: {=Common_Equations.Common_ConvertN2OToCO2e(E17,_xlfn.XLOOKUP("N2O", Table_GWPData[Gas],Table_GWPData[CO2-e factor]))} -> 15.083046 | I17: {=Common_Equations.Common_ConvertN2OToCO2e(F17,_xlfn.XLOOKUP("N2O", Table_GWPData[Gas],Table_GWPData[CO2-e factor]))} -> 15.083046 | J17: t CO2e
A18: CALCULATIONS | D18: 6.2.1.1-2 Pasture residue N2O | E18: {=VEERG_6_2_1_1__1__NitrousOxideEmissionsFromPastureResidues_Result_Method1} -> 5.8320429e-07 | F18: {=VEERG_6_2_1_1__1__NitrousOxideEmissionsFromPastureResidues_Result_Method2} -> 5.8320429e-07 | G18: t N2O | H18: {=Common_Equations.Common_ConvertN2OToCO2e(E18,_xlfn.XLOOKUP("N2O", Table_GWPData[Gas],Table_GWPData[CO2-e factor]))} -> 0.00015454914 | I18: {=Common_Equations.Common_ConvertN2OToCO2e(F18,_xlfn.XLOOKUP("N2O", Table_GWPData[Gas],Table_GWPData[CO2-e factor]))} -> 0.00015454914 | J18: t CO2e
A19: =HYPERLINK("#'3.2.1.1-2 Enteric Methane'!A1", "3.2.1.1-2 Enteric methane") -> 3.2.1.1-2 Enteric methane | D19: 6.3.1.1-2 Leach & runoff (pasture) | E19: {=VEERG_6_3_1_1__1__LeachingAndRunoffEmissionsCropAndPastureResidue_PastureOnly_Result_Method1} -> 3.0793186e-07 | F19: {=VEERG_6_3_1_1__1__LeachingAndRunoffEmissionsCropAndPastureResidue_PastureOnly_Result_Method2} -> 3.0793186e-07 | G19: t N2O | H19: {=Common_Equations.Common_ConvertN2OToCO2e(E19,_xlfn.XLOOKUP("N2O", Table_GWPData[Gas],Table_GWPData[CO2-e factor]))} -> 8.1601944e-05 | I19: {=Common_Equations.Common_ConvertN2OToCO2e(F19,_xlfn.XLOOKUP("N2O", Table_GWPData[Gas],Table_GWPData[CO2-e factor]))} -> 8.1601944e-05 | J19: t CO2e
A20: =HYPERLINK("#'4.2.1.1-2 Methane'!A1", "4.2.1.1-2 Manure methane") -> 4.2.1.1-2 Manure methane | D20: 8.1.1.1-2 Transport fuel CO2 | E20: {=VEERG_8_1_1_1__1_FuelCombustionTransport_Result_CO2} -> 83.182 | F20: =E20 -> 83.182 | G20: t CO2 | H20: =E20 -> 83.182 | I20: =F20 -> 83.182 | J20: t CO2e
A21: =HYPERLINK("#'4.2.1.3-4 Soil direct N20'!A1", "4.2.1.3-4 Soil direct N2O") -> 4.2.1.3-4 Soil direct N2O | D21: 8.1.1.1-2 Transport fuel CH4 | E21: {=VEERG_8_1_1_1__1_FuelCombustionTransport_Result_CH4} -> 0.19906 | F21: =E21 -> 0.19906 | G21: t CH4 | H21: {=Common_Equations.Common_ConvertCH4ToCO2e(E21,_xlfn.XLOOKUP("CH4", Table_GWPData[Gas],Table_GWPData[CO2-e factor]))} -> 5.57368 | I21: {=Common_Equations.Common_ConvertCH4ToCO2e(F21,_xlfn.XLOOKUP("CH4", Table_GWPData[Gas],Table_GWPData[CO2-e factor]))} -> 5.57368 | J21: t CO2e
A22: =HYPERLINK("#'4.2.1.5-6 Soil Atmos Dep'!A1", "4.2.1.5-6 Soil atm. deposition") -> 4.2.1.5-6 Soil atm. deposition | D22: 8.1.1.1-2 Transport fuel N2O | E22: {=VEERG_8_1_1_1__1_FuelCombustionTransport_Result_N2O} -> 0.5845 | F22: =E22 -> 0.5845 | G22: t N2O | H22: {=Common_Equations.Common_ConvertN2OToCO2e(E22,_xlfn.XLOOKUP("N2O", Table_GWPData[Gas],Table_GWPData[CO2-e factor]))} -> 154.8925 | I22: {=Common_Equations.Common_ConvertN2OToCO2e(F22,_xlfn.XLOOKUP("N2O", Table_GWPData[Gas],Table_GWPData[CO2-e factor]))} -> 154.8925 | J22: t CO2e
A23: =HYPERLINK("#'4.2.1.7-8 Soil leach runoff'!A1", "4.2.1.7-8 Soil leach & runoff") -> 4.2.1.7-8 Soil leach & runoff | D23: 8.2.1.1-2 Stationary fuel CO2 | E23: {=VEERG_8_2_1_1__1_FuelCombustionStationary_Result_CO2} -> 29.0708 | F23: =E23 -> 29.0708 | G23: t CO2 | H23: =E23 -> 29.0708 | I23: =F23 -> 29.0708 | J23: t CO2e
A24: =HYPERLINK("#'5.1.1.1-2 Inorganic fert N2O'!A1", "5.1.1.1-2 Inorganic fert N2O") -> 5.1.1.1-2 Inorganic fert N2O | D24: 8.2.1.1-2 Stationary fuel CH4 | E24: {=VEERG_8_2_1_1__1_FuelCombustionStationary_Result_CH4} -> 0.0724 | F24: =E24 -> 0.0724 | G24: t CH4 | H24: {=Common_Equations.Common_ConvertCH4ToCO2e(E24,_xlfn.XLOOKUP("CH4", Table_GWPData[Gas],Table_GWPData[CO2-e factor]))} -> 2.0272 | I24: {=Common_Equations.Common_ConvertCH4ToCO2e(F24,_xlfn.XLOOKUP("CH4", Table_GWPData[Gas],Table_GWPData[CO2-e factor]))} -> 2.0272 | J24: t CO2e
A25: =HYPERLINK("#'5.1.1.3-4 Inorganic fert CO2'!A1", "5.1.1.3-4 Inorganic fert CO2") -> 5.1.1.3-4 Inorganic fert CO2 | D25: 8.2.1.1-2 Stationary fuel N2O | E25: {=VEERG_8_2_1_1__1_FuelCombustionStationary_Result_N2O} -> 0.0714 | F25: =E25 -> 0.0714 | G25: t N2O | H25: {=Common_Equations.Common_ConvertN2OToCO2e(E25,_xlfn.XLOOKUP("N2O", Table_GWPData[Gas],Table_GWPData[CO2-e factor]))} -> 18.921 | I25: {=Common_Equations.Common_ConvertN2OToCO2e(F25,_xlfn.XLOOKUP("N2O", Table_GWPData[Gas],Table_GWPData[CO2-e factor]))} -> 18.921 | J25: t CO2e
A26: =HYPERLINK("#'5.2.1.1-2 Organic Fert N2O'!A1", "5.2.1.1-2 Organic fert N2O") -> 5.2.1.1-2 Organic fert N2O | D26: 14.1.1-2 Purchased electricity (Location-based) | E26: {=VEERG_14_1_1__1_LocationBasedScopeElectricityEmissions_Result_Method1} -> 16.8 | F26: =E26 -> 16.8 | G26: t CO2e | H26: =E26 -> 16.8 | I26: =F26 -> 16.8 | J26: t CO2e
A27: =HYPERLINK("#'5.3.1.1-2 Lime CO2'!A1", "5.3.1.1-2 Lime CO2") -> 5.3.1.1-2 Lime CO2 | D27: 14.1.1-2 Purchased electricity (Market-based) | E27: {=VEERG_14_1_2__1_MarketBasedScopeElectricityEmissionsVariation_Result_Method1} -> 13.77 | F27: =E27 -> 13.77 | G27: t CO2e | H27: =E27 -> 13.77 | I27: =F27 -> 13.77 | J27: t CO2e
A28: =HYPERLINK("#'5.4.1.1-4 Atmos deposition'!A1", "5.4.1.1-4 Atmos. deposition") -> 5.4.1.1-4 Atmos. deposition | D28: Total | H28: =SUM(H7:H27) -> 2163.887 | I28: =SUM(I7:I27) -> 2159.2843 | J28: t CO2e
A29: =HYPERLINK("#'5.5.1.1-2 Leaching and runoff'!A1", "5.5.1.1-2 Leaching & runoff") -> 5.5.1.1-2 Leaching & runoff
A30: =HYPERLINK("#'6.2.1.1-2 Pasture residue N2O'!A1", "6.2.1.1-2 Pasture residue N2O") -> 6.2.1.1-2 Pasture residue N2O
A31: =HYPERLINK("#'6.3.1.1-2 Leach runoff pasture'!A1", "6.3.1.1-2 Leach & runoff (pasture)") -> 6.3.1.1-2 Leach & runoff (pasture)
A32: =HYPERLINK("#'8.1.1.1-2 Transport fuel'!A1", "8.1.1.1-2 Transport fuel") -> 8.1.1.1-2 Transport fuel | D32: Emissions for whole production cycle
A33: =HYPERLINK("#'8.2.1.1-2 Stationary fuel'!A1", "8.2.1.1-2 Stationary fuel") -> 8.2.1.1-2 Stationary fuel | D33: {="There are " & Common_InputFunctions.getOverlappingReportingCycles(X_Cell_Enterprise_ProductionTimeframeStart,X_Cell_Enterprise_ProductionTimeframeEnd,X_Cell_Site_StartDate) & " emissions calculation periods that need to be completed before total product emissions can be determined."} -> There are 3 emissions calculation periods that need to be completed before total product emissions can be determined.
A34: =HYPERLINK("#'14.1.1-2 Purchased electricity'!A1", "14.1.1-2 Purchased electricity") -> 14.1.1-2 Purchased electricity | D34: Enter the method 1 and 2 CO2e emissions from prevoius emissions calculation periods if applicable.
D36: Emissions calculation cycle | E36: CO2-e emissions method 1 | F36: CO2-e emissions method 2
A37: APPENDICES | D37: {=Common_InputFunctions.getOverlappingReportingPeriods(X_Cell_Enterprise_ProductionTimeframeStart,X_Cell_Enterprise_ProductionTimeframeEnd,X_Cell_Site_StartDate)} -> 01 Jan 2023 to 31 Dec 2023 | E37: 01 Jan 2023 to 31 Dec 2023 | F37: Enter value | G37: t CO2e
A38: =HYPERLINK("#'Constants - Pasture Beef'!A1", "Constants - Pasture Beef") -> Constants - Pasture Beef | D38: 01 Jan 2024 to 31 Dec 2024 | E38: 01 Jan 2024 to 31 Dec 2024 (This reporting cycle) | F38: 2163.887 | G38: t CO2e
A39: =HYPERLINK("#'Constants - Ag Residue'!A1", "Constants - Ag residue") -> Constants - Ag residue | D39: 01 Jan 2025 to 31 Dec 2025 (This reporting cycle) | E39: 01 Jan 2025 to 31 Dec 2025 | F39: Enter value | G39: t CO2e
A40: =HYPERLINK("#'Constants - Common Livestock'!A1", "Constants - Common Livestock") -> Constants - Common Livestock | G40: t CO2e
A41: =HYPERLINK("#'Constants - Electricity'!A1", "Constants - Electricity") -> Constants - Electricity | G41: t CO2e
A42: =HYPERLINK("#'Constants - Fertiliser'!A1", "Constants - Fertiliser") -> Constants - Fertiliser | D42: Total emissions for production cycle | E42: =SUM(E37:E41) -> 0 | F42: =SUM(F37:F41) -> 2163.887
A43: =HYPERLINK("#'Constants - Fuel'!A1", "Constants - Fuel") -> Constants - Fuel
A44: =HYPERLINK("#'Constants - Common'!A1", "Constants - Common") -> Constants - Common
A45: =HYPERLINK("#'Acknowledgements'!A1", "Acknowledgements") -> Acknowledgements | D45: Carbon removals from plantings
A46: =HYPERLINK("#'Overview'!A1", "Overview") -> Overview
D47: Emissions calculation cycle | E47: CO2 removed attributed to this enterprise
D48: {=Common_InputFunctions.getOverlappingReportingPeriods(X_Cell_Enterprise_ProductionTimeframeStart,X_Cell_Enterprise_ProductionTimeframeEnd,X_Cell_Site_StartDate)} -> 01 Jan 2023 to 31 Dec 2023 | E48: 01 Jan 2023 to 31 Dec 2023 | F48: t CO2
D49: 01 Jan 2024 to 31 Dec 2024 | E49: 01 Jan 2024 to 31 Dec 2024 (This reporting cycle) | F49: t CO2
D50: 01 Jan 2025 to 31 Dec 2025 (This reporting cycle) | E50: 01 Jan 2025 to 31 Dec 2025 | F50: t CO2
F51: t CO2
F52: t CO2
D53: Total carbon removals for production cycle | E53: =SUM(E48:E51) -> 0
D56: Product emissions
E58: Method 1 | F58: Method 2
D59: Net emissions | E59: =E42-E53 -> 0 | F59: =F42-E53 -> 2163.887
D61: Product | E61: Product type | F61: Amount (tonnnes) | G61: Emissions allocation (mass) | H61: Emissions intensity (Method 1) | I61: Emissions intensity (Method 2) | J61: Unit
D62: Liveweight sold | E62: Main product | F62: ='Input - Enterprise'!E22 -> =SUM(Table_Input_LivestockSales348[Total liveweight sold])*10^-3 | G62: =F62/(F62+F63) -> #VALUE! | H62: =($E$42/F62)*G62 -> #VALUE! | I62: =($F$42/F62)*G62 -> #VALUE! | J62: t co2e/t liveweight sold
D63: Manure sold | E63: Co-product | F63: ='Input - Enterprise'!E25*'Input - Enterprise'!E26 -> #VALUE! | G63: =F63/(F62+F63) -> #VALUE! | H63: =($E$42/F63)*G63 -> #VALUE! | I63: =($F$42/F63)*G63 -> #VALUE! | J63: t co2e/t manure
D64: Manure used as fertiliser on own farm | E64: Residual product | F64: ='Input - Enterprise'!E25*'Input - Enterprise'!E27 -> #VALUE! | G64: N/A | H64: N/A | I64: N/A
D66: Liveweight grown - Method 1 | E66: N/A | F66: ='Input - Enterprise'!E23 -> =SUM(Enterprise_PastureBeef_InputFunctions.multiplyCorrespondingCells('Input - Pasture Beef'!X_Table_PastureBeef_Head_Method1, 'Input - Pasture Beef'!X_Table_PastureBeef_Duration_Method1, 'Input - Pasture Beef'!X_Table_PastureBeef_LiveweightGain_Method1))*10^-3 | G66: N/A | H66: =E59/F66 -> #VALUE! | I66: N/A | J66: t co2e/t liveweight grown
D67: Liveweight grown - Method 2 | E67: N/A | F67: ='Input - Enterprise'!E24 -> =SUM(Enterprise_PastureBeef_InputFunctions.multiplyCorrespondingCells('Input - Pasture Beef'!X_Table_PastureBeef_Head_Method2, 'Input - Pasture Beef'!X_Table_PastureBeef_Duration_Method2, 'Input - Pasture Beef'!X_Table_PastureBeef_LiveweightGain_Method2))*10^-3 | G67: N/A | H67: N/A | I67: =F59/F67 -> #VALUE! | J67: t co2e/t liveweight grown

Sheet Input - Enterprise
A1: #VALUE! | C1: Input - Enterprise
A3: =HYPERLINK("#'Home'!A1", "Home") -> Home
A4: =HYPERLINK("#'Results'!A1", "Results") -> Results
D5: Your business
A7: INPUTS | D7: Farm name | E7: My test farm
A8: =HYPERLINK("#'Input - Enterprise'!A1", "Enterprise") -> Enterprise | D8: Reporting entity name | E8: My test Farms Pty Ltd
A9: =HYPERLINK("#'Input - Site'!A1", "Site") -> Site
A10: =HYPERLINK("#'Input - Pasture Beef'!A1", "Pasture Beef") -> Pasture Beef | D10: 💡An 'Emissions accounting period' is a 12 month period where the business can report on the emissions, and is typically the same as the business' financial accounting period.
A11: =HYPERLINK("#'Input - Pasture Beef (Enteric)'!A1", "Pasture Beef (Enteric)") -> Pasture Beef (Enteric)
A12: =HYPERLINK("#'Input - Pasture'!A1", "Pasture") -> Pasture | D12: Emissions calculation period start date | E12: 45658 | F12: ← DD/MM/YYYY or DD Month YYYY
A13: =HYPERLINK("#'Input - Fertiliser'!A1", "Fertiliser") -> Fertiliser | D13: Emissions calculation period end date | E13: =DATE(YEAR(E12)+1,MONTH(E12),DAY(E12))-1 -> 46022 | F13: ← Automatically calculated, 12 months after start date
A14: =HYPERLINK("#'Input - Fuel'!A1", "Fuel") -> Fuel
A15: =HYPERLINK("#'Input - Electricity'!A1", "Electricity") -> Electricity
D16: Production
A18: CALCULATIONS | D18: Production timeframe start | E18: 45231 | F18: ← DD/MM/YYYY or DD Month YYYY
A19: =HYPERLINK("#'3.2.1.1-2 Enteric Methane'!A1", "3.2.1.1-2 Enteric methane") -> 3.2.1.1-2 Enteric methane | D19: Production timeframe end | E19: 45747 | F19: ← DD/MM/YYYY or DD Month YYYY
A20: =HYPERLINK("#'4.2.1.1-2 Methane'!A1", "4.2.1.1-2 Manure methane") -> 4.2.1.1-2 Manure methane | D20: Production timeframe length | E20: =DATEDIF(E18,E19+1,"m") -> 17 | F20: Months
A21: =HYPERLINK("#'4.2.1.3-4 Soil direct N20'!A1", "4.2.1.3-4 Soil direct N2O") -> 4.2.1.3-4 Soil direct N2O
A22: =HYPERLINK("#'4.2.1.5-6 Soil Atmos Dep'!A1", "4.2.1.5-6 Soil atm. deposition") -> 4.2.1.5-6 Soil atm. deposition | D22: Liveweight sold | E22: =SUM(Table_Input_LivestockSales348[Total liveweight sold])*10^-3 | G22: tonnes
A23: =HYPERLINK("#'4.2.1.7-8 Soil leach runoff'!A1", "4.2.1.7-8 Soil leach & runoff") -> 4.2.1.7-8 Soil leach & runoff | D23: Liveweight grown - method 1 | E23: =SUM(Enterprise_PastureBeef_InputFunctions.multiplyCorrespondingCells('Input - Pasture Beef'!X_Table_PastureBeef_Head_Method1, 'Input - Pasture Beef'!X_Table_PastureBeef_Duration_Method1, 'Input - Pasture Beef'!X_Table_PastureBeef_LiveweightGain_Method1))*10^-3 | G23: tonnes
A24: =HYPERLINK("#'5.1.1.1-2 Inorganic fert N2O'!A1", "5.1.1.1-2 Inorganic fert N2O") -> 5.1.1.1-2 Inorganic fert N2O | D24: Liveweight grown - method 2 | E24: =SUM(Enterprise_PastureBeef_InputFunctions.multiplyCorrespondingCells('Input - Pasture Beef'!X_Table_PastureBeef_Head_Method2, 'Input - Pasture Beef'!X_Table_PastureBeef_Duration_Method2, 'Input - Pasture Beef'!X_Table_PastureBeef_LiveweightGain_Method2))*10^-3 | G24: tonnes
A25: =HYPERLINK("#'5.1.1.3-4 Inorganic fert CO2'!A1", "5.1.1.3-4 Inorganic fert CO2") -> 5.1.1.3-4 Inorganic fert CO2 | D25: Manure produced - method 1 | E25: =SUM(Enterprise_PastureBeef_InputFunctions.multiplyCorrespondingCells('Input - Pasture Beef'!X_Table_PastureBeef_Head_Method1, Input - Pasture Beef'!X_Table_PastureBeef_Duration_Method1, '4.2.1.1-2 Methane'!M1_Table_VS_j_k_l))*10^-3 | G25: tonnes
A26: =HYPERLINK("#'5.2.1.1-2 Organic Fert N2O'!A1", "5.2.1.1-2 Organic fert N2O") -> 5.2.1.1-2 Organic fert N2O | D26: Manure produced - method 2 | E26: =SUM(Enterprise_PastureBeef_InputFunctions.multiplyCorrespondingCells('Input - Pasture Beef'!X_Table_PastureBeef_Head_Method2, 'Input - Pasture Beef'!X_Table_PastureBeef_Duration_Method2, M2_Table_VS_j_k_l))*10^-3 | G26: tonnes
A27: =HYPERLINK("#'5.3.1.1-2 Lime CO2'!A1", "5.3.1.1-2 Lime CO2") -> 5.3.1.1-2 Lime CO2 | D27: Percent manure sold | E27: 0.1 | G27: percent
A28: =HYPERLINK("#'5.4.1.1-4 Atmos deposition'!A1", "5.4.1.1-4 Atmos. deposition") -> 5.4.1.1-4 Atmos. deposition | D28: Percent manure applied as fertiliser on own farm | E28: 0.2 | G28: percent
A29: =HYPERLINK("#'5.5.1.1-2 Leaching and runoff'!A1", "5.5.1.1-2 Leaching & runoff") -> 5.5.1.1-2 Leaching & runoff | D29: Percent manure applied to soil with no purpose (as waste) | E29: =100%-E27-E28 -> 0.7 | G29: percent
A30: =HYPERLINK("#'6.2.1.1-2 Pasture residue N2O'!A1", "6.2.1.1-2 Pasture residue N2O") -> 6.2.1.1-2 Pasture residue N2O
A31: =HYPERLINK("#'6.3.1.1-2 Leach runoff pasture'!A1", "6.3.1.1-2 Leach & runoff (pasture)") -> 6.3.1.1-2 Leach & runoff (pasture) | D31: Percentage of income from liveweight sold | E31: 0.8 | G31: percent
A32: =HYPERLINK("#'8.1.1.1-2 Transport fuel'!A1", "8.1.1.1-2 Transport fuel") -> 8.1.1.1-2 Transport fuel | D32: Percentage of income from manure sold | E32: 0.2 | G32: percent
A33: =HYPERLINK("#'8.2.1.1-2 Stationary fuel'!A1", "8.2.1.1-2 Stationary fuel") -> 8.2.1.1-2 Stationary fuel
A34: =HYPERLINK("#'14.1.1-2 Purchased electricity'!A1", "14.1.1-2 Purchased electricity") -> 14.1.1-2 Purchased electricity
A37: APPENDICES
A38: =HYPERLINK("#'Constants - Pasture Beef'!A1", "Constants - Pasture Beef") -> Constants - Pasture Beef
A39: =HYPERLINK("#'Constants - Ag Residue'!A1", "Constants - Ag residue") -> Constants - Ag residue
A40: =HYPERLINK("#'Constants - Common Livestock'!A1", "Constants - Common Livestock") -> Constants - Common Livestock
A41: =HYPERLINK("#'Constants - Electricity'!A1", "Constants - Electricity") -> Constants - Electricity
A42: =HYPERLINK("#'Constants - Fertiliser'!A1", "Constants - Fertiliser") -> Constants - Fertiliser
A43: =HYPERLINK("#'Constants - Fuel'!A1", "Constants - Fuel") -> Constants - Fuel
A44: =HYPERLINK("#'Constants - Common'!A1", "Constants - Common") -> Constants - Common
A45: =HYPERLINK("#'Acknowledgements'!A1", "Acknowledgements") -> Acknowledgements
A46: =HYPERLINK("#'Overview'!A1", "Overview") -> Overview

Sheet Input - Site
A1: #VALUE! | C1: Input - Site
A3: =HYPERLINK("#'Home'!A1", "Home") -> Home
A4: =HYPERLINK("#'Results'!A1", "Results") -> Results
D5: Location and climate
A7: INPUTS | D7: Location information is used to reference some region and climate-specific emission factors
A8: =HYPERLINK("#'Input - Enterprise'!A1", "Enterprise") -> Enterprise | D8: Tip: Use the web-based GAF Location Helper tool to easily get region and climate information. You will need an internet connection to use the GAF Location Helper.
A9: =HYPERLINK("#'Input - Site'!A1", "Site") -> Site
A10: =HYPERLINK("#'Input - Pasture Beef'!A1", "Pasture Beef") -> Pasture Beef | D10: State | E10: Western Australia | F10: ← Please select
A11: =HYPERLINK("#'Input - Pasture Beef (Enteric)'!A1", "Pasture Beef (Enteric)") -> Pasture Beef (Enteric) | D11: Region (ABS Statistical area level 4) if state is WA | E11: Western Australia - Outback (South) | F11: ← Please select
A12: =HYPERLINK("#'Input - Pasture'!A1", "Pasture") -> Pasture | D12: Leaching zone | E12: NO - Not in leaching zone | F12: ← Please select
A13: =HYPERLINK("#'Input - Fertiliser'!A1", "Fertiliser") -> Fertiliser | D13: Elevation | E13: 307.7 | F13: Meters
A14: =HYPERLINK("#'Input - Fuel'!A1", "Fuel") -> Fuel | D14: Average temperature for reporting period | E14: 18 | F14: Degrees celsius
A15: =HYPERLINK("#'Input - Electricity'!A1", "Electricity") -> Electricity | D15: Total rainfall for reporting period | E15: 601 | F15: Millimetres
D16: Potential evapotranspiration for reporting period | E16: 1326 | F16: Millimetres
D17: Number of frost days for reporting period | E17: 7 | F17: Days
A18: CALCULATIONS | D18: MAP:PET ratio | E18: =E15/E16 -> 0.45324284
A19: =HYPERLINK("#'3.2.1.1-2 Enteric Methane'!A1", "3.2.1.1-2 Enteric methane") -> 3.2.1.1-2 Enteric methane | D19: Rainfall zone | E19: =Common_InputFunctions.Utility_LookupItemFromMinMax(E15,Table_SourceData_RainfallZones[Min rainfall],Table_SourceData_RainfallZones[Max rainfall],Table_SourceData_RainfallZones[Rainfall Zone]) -> High rainfall
A20: =HYPERLINK("#'4.2.1.1-2 Methane'!A1", "4.2.1.1-2 Manure methane") -> 4.2.1.1-2 Manure methane | D20: Climate zone | E20: =Common_InputFunctions.Utility_GetClimateZone(E14,E15,E17,E13,E18,Table_SourceData_ClimateZones[Min temp],Table_SourceData_ClimateZones[Max temp],Table_SourceData_ClimateZones[Min rainfall],Table_SourceData_ClimateZones[Max rainfall],Table_SourceData_ClimateZones[Min frost days],Table_SourceData_ClimateZones[Max frost days],Table_SourceData_ClimateZones[Min elevation],Table_SourceData_ClimateZones[Max elevation],Table_SourceData_ClimateZones[Min MAP:PET],Table_SourceData_ClimateZones[Max MAP:PET],Table_SourceData_ClimateZones[Climate zone]) -> Warm temperate dry
A21: =HYPERLINK("#'4.2.1.3-4 Soil direct N20'!A1", "4.2.1.3-4 Soil direct N2O") -> 4.2.1.3-4 Soil direct N2O | D21: Wet or dry climate zone | E21: =Common_InputFunctions.Utility_LookupValueInTable($E$20,Table_SourceData_WetDryZones[Climate zone],Table_SourceData_WetDryZones[Wet or Dry Zone]) -> Dry climate zone
A22: =HYPERLINK("#'4.2.1.5-6 Soil Atmos Dep'!A1", "4.2.1.5-6 Soil atm. deposition") -> 4.2.1.5-6 Soil atm. deposition | D22: Temperature zone | E22: =Common_InputFunctions.Utility_LookupItemFromMinMax(E14,Table_SourceData_TemperatureZones[Min MAT],Table_SourceData_TemperatureZones[Max MAT],Table_SourceData_TemperatureZones[Temperature Zone]) -> Temperate
A23: =HYPERLINK("#'4.2.1.7-8 Soil leach runoff'!A1", "4.2.1.7-8 Soil leach & runoff") -> 4.2.1.7-8 Soil leach & runoff
A24: =HYPERLINK("#'5.1.1.1-2 Inorganic fert N2O'!A1", "5.1.1.1-2 Inorganic fert N2O") -> 5.1.1.1-2 Inorganic fert N2O
A25: =HYPERLINK("#'5.1.1.3-4 Inorganic fert CO2'!A1", "5.1.1.3-4 Inorganic fert CO2") -> 5.1.1.3-4 Inorganic fert CO2
A26: =HYPERLINK("#'5.2.1.1-2 Organic Fert N2O'!A1", "5.2.1.1-2 Organic fert N2O") -> 5.2.1.1-2 Organic fert N2O
A27: =HYPERLINK("#'5.3.1.1-2 Lime CO2'!A1", "5.3.1.1-2 Lime CO2") -> 5.3.1.1-2 Lime CO2
A28: =HYPERLINK("#'5.4.1.1-4 Atmos deposition'!A1", "5.4.1.1-4 Atmos. deposition") -> 5.4.1.1-4 Atmos. deposition
A29: =HYPERLINK("#'5.5.1.1-2 Leaching and runoff'!A1", "5.5.1.1-2 Leaching & runoff") -> 5.5.1.1-2 Leaching & runoff
A30: =HYPERLINK("#'6.2.1.1-2 Pasture residue N2O'!A1", "6.2.1.1-2 Pasture residue N2O") -> 6.2.1.1-2 Pasture residue N2O
A31: =HYPERLINK("#'6.3.1.1-2 Leach runoff pasture'!A1", "6.3.1.1-2 Leach & runoff (pasture)") -> 6.3.1.1-2 Leach & runoff (pasture)
A32: =HYPERLINK("#'8.1.1.1-2 Transport fuel'!A1", "8.1.1.1-2 Transport fuel") -> 8.1.1.1-2 Transport fuel
A33: =HYPERLINK("#'8.2.1.1-2 Stationary fuel'!A1", "8.2.1.1-2 Stationary fuel") -> 8.2.1.1-2 Stationary fuel
A34: =HYPERLINK("#'14.1.1-2 Purchased electricity'!A1", "14.1.1-2 Purchased electricity") -> 14.1.1-2 Purchased electricity
A37: APPENDICES
A38: =HYPERLINK("#'Constants - Pasture Beef'!A1", "Constants - Pasture Beef") -> Constants - Pasture Beef
A39: =HYPERLINK("#'Constants - Ag Residue'!A1", "Constants - Ag residue") -> Constants - Ag residue
A40: =HYPERLINK("#'Constants - Common Livestock'!A1", "Constants - Common Livestock") -> Constants - Common Livestock
A41: =HYPERLINK("#'Constants - Electricity'!A1", "Constants - Electricity") -> Constants - Electricity
A42: =HYPERLINK("#'Constants - Fertiliser'!A1", "Constants - Fertiliser") -> Constants - Fertiliser
A43: =HYPERLINK("#'Constants - Fuel'!A1", "Constants - Fuel") -> Constants - Fuel
A44: =HYPERLINK("#'Constants - Common'!A1", "Constants - Common") -> Constants - Common
A45: =HYPERLINK("#'Acknowledgements'!A1", "Acknowledgements") -> Acknowledgements
A46: =HYPERLINK("#'Overview'!A1", "Overview") -> Overview

Sheet Input - Pasture Beef
A1: #VALUE! | C1: Input -Pasture Beef
A3: =HYPERLINK("#'Home'!A1", "Home") -> Home
A4: =HYPERLINK("#'Results'!A1", "Results") -> Results
D5: Herd movement
A7: INPUTS | D7: State | E7: =X_Cell_Site_State -> Western Australia
A8: =HYPERLINK("#'Input - Enterprise'!A1", "Enterprise") -> Enterprise | D8: Livestock production region | E8: South West | F8: ← Please select
A9: =HYPERLINK("#'Input - Site'!A1", "Site") -> Site | D9: Cattle breed | E9: Hereford or Shorthorn breeds | F9: ← Please select
A10: =HYPERLINK("#'Input - Pasture Beef'!A1", "Pasture Beef") -> Pasture Beef
A11: =HYPERLINK("#'Input - Pasture Beef (Enteric)'!A1", "Pasture Beef (Enteric)") -> Pasture Beef (Enteric)
A12: =HYPERLINK("#'Input - Pasture'!A1", "Pasture") -> Pasture
A13: =HYPERLINK("#'Input - Fertiliser'!A1", "Fertiliser") -> Fertiliser | D13: NOTE: VEERG states that under method 2, time periods may be seasons, months or a custom time period. In this example, method 2 time periods are months.
A14: =HYPERLINK("#'Input - Fuel'!A1", "Fuel") -> Fuel
A15: =HYPERLINK("#'Input - Electricity'!A1", "Electricity") -> Electricity | D15: Duration on farm
D16: Method 1 default values (do not edit) | E16: Bulls < 1 year | F16: Bulls > 1 year | G16: Cows < 1 year | H16: Cows 1-2 years | I16: Cows 2-3 years | J16: Cows > 3 years | K16: Steers < 1 year | L16: Steers 1-2 years | M16: Steers 2-3 years | N16: Steers >3 years
D17: Spring | E17: 91.25 | F17: 91.25 | G17: 91.25 | H17: 91.25 | I17: 91.25 | J17: 91.25 | K17: 91.25 | L17: 91.25 | M17: 91.25 | N17: 91.25 | O17: Days
A18: CALCULATIONS | D18: Summer | E18: 91.25 | F18: 91.25 | G18: 91.25 | H18: 91.25 | I18: 91.25 | J18: 91.25 | K18: 91.25 | L18: 91.25 | M18: 91.25 | N18: 91.25 | O18: Days
A19: =HYPERLINK("#'3.2.1.1-2 Enteric Methane'!A1", "3.2.1.1-2 Enteric methane") -> 3.2.1.1-2 Enteric methane | D19: Autumn | E19: 91.25 | F19: 91.25 | G19: 91.25 | H19: 91.25 | I19: 91.25 | J19: 91.25 | K19: 91.25 | L19: 91.25 | M19: 91.25 | N19: 91.25 | O19: Days
A20: =HYPERLINK("#'4.2.1.1-2 Methane'!A1", "4.2.1.1-2 Manure methane") -> 4.2.1.1-2 Manure methane | D20: Winter | E20: 91.25 | F20: 91.25 | G20: 91.25 | H20: 91.25 | I20: 91.25 | J20: 91.25 | K20: 91.25 | L20: 91.25 | M20: 91.25 | N20: 91.25 | O20: Days
A21: =HYPERLINK("#'4.2.1.3-4 Soil direct N20'!A1", "4.2.1.3-4 Soil direct N2O") -> 4.2.1.3-4 Soil direct N2O
A22: =HYPERLINK("#'4.2.1.5-6 Soil Atmos Dep'!A1", "4.2.1.5-6 Soil atm. deposition") -> 4.2.1.5-6 Soil atm. deposition | D22: Method 2 custom values (edit if known) | E22: Bulls < 1 year | F22: Bulls > 1 year | G22: Cows < 1 year | H22: Cows 1-2 years | I22: Cows 2-3 years | J22: Cows > 3 years | K22: Steers < 1 year | L22: Steers 1-2 years | M22: Steers 2-3 years | N22: Steers >3 years
A23: =HYPERLINK("#'4.2.1.7-8 Soil leach runoff'!A1", "4.2.1.7-8 Soil leach & runoff") -> 4.2.1.7-8 Soil leach & runoff | D23: =TEXT(X_Cell_Site_StartDate, "mmmm yyyy") -> January 2025 | E23: 31 | F23: 31 | G23: 31 | H23: 31 | I23: 31 | J23: 31 | K23: 31 | L23: 31 | M23: 31 | N23: 31 | O23: Days
A24: =HYPERLINK("#'5.1.1.1-2 Inorganic fert N2O'!A1", "5.1.1.1-2 Inorganic fert N2O") -> 5.1.1.1-2 Inorganic fert N2O | D24: =TEXT(EDATE(X_Cell_Site_StartDate,1), "mmmm yyyy") -> February 2025 | E24: 29 | F24: 29 | G24: 29 | H24: 29 | I24: 29 | J24: 29 | K24: 29 | L24: 29 | M24: 29 | N24: 29 | O24: Days
A25: =HYPERLINK("#'5.1.1.3-4 Inorganic fert CO2'!A1", "5.1.1.3-4 Inorganic fert CO2") -> 5.1.1.3-4 Inorganic fert CO2 | D25: =TEXT(EDATE(X_Cell_Site_StartDate,2), "mmmm yyyy") -> March 2025 | E25: 31 | F25: 31 | G25: 31 | H25: 31 | I25: 31 | J25: 31 | K25: 31 | L25: 31 | M25: 31 | N25: 31 | O25: Days
A26: =HYPERLINK("#'5.2.1.1-2 Organic Fert N2O'!A1", "5.2.1.1-2 Organic fert N2O") -> 5.2.1.1-2 Organic fert N2O | D26: =TEXT(EDATE(X_Cell_Site_StartDate,3), "mmmm yyyy") -> April 2025 | E26: 30 | F26: 30 | G26: 30 | H26: 30 | I26: 30 | J26: 30 | K26: 30 | L26: 30 | M26: 30 | N26: 30 | O26: Days
A27: =HYPERLINK("#'5.3.1.1-2 Lime CO2'!A1", "5.3.1.1-2 Lime CO2") -> 5.3.1.1-2 Lime CO2 | D27: =TEXT(EDATE(X_Cell_Site_StartDate,4), "mmmm yyyy") -> May 2025 | E27: 31 | F27: 31 | G27: 31 | H27: 31 | I27: 31 | J27: 31 | K27: 31 | L27: 31 | M27: 31 | N27: 31 | O27: Days
A28: =HYPERLINK("#'5.4.1.1-4 Atmos deposition'!A1", "5.4.1.1-4 Atmos. deposition") -> 5.4.1.1-4 Atmos. deposition | D28: =TEXT(EDATE(X_Cell_Site_StartDate,5), "mmmm yyyy") -> June 2025 | E28: 30 | F28: 30 | G28: 30 | H28: 30 | I28: 30 | J28: 30 | K28: 30 | L28: 30 | M28: 30 | N28: 30 | O28: Days
A29: =HYPERLINK("#'5.5.1.1-2 Leaching and runoff'!A1", "5.5.1.1-2 Leaching & runoff") -> 5.5.1.1-2 Leaching & runoff | D29: =TEXT(EDATE(X_Cell_Site_StartDate,6), "mmmm yyyy") -> July 2025 | E29: 31 | F29: 31 | G29: 31 | H29: 31 | I29: 31 | J29: 31 | K29: 31 | L29: 31 | M29: 31 | N29: 31 | O29: Days
A30: =HYPERLINK("#'6.2.1.1-2 Pasture residue N2O'!A1", "6.2.1.1-2 Pasture residue N2O") -> 6.2.1.1-2 Pasture residue N2O | D30: =TEXT(EDATE(X_Cell_Site_StartDate,7), "mmmm yyyy") -> August 2025 | E30: 31 | F30: 31 | G30: 31 | H30: 31 | I30: 31 | J30: 31 | K30: 31 | L30: 31 | M30: 31 | N30: 31 | O30: Days
A31: =HYPERLINK("#'6.3.1.1-2 Leach runoff pasture'!A1", "6.3.1.1-2 Leach & runoff (pasture)") -> 6.3.1.1-2 Leach & runoff (pasture) | D31: =TEXT(EDATE(X_Cell_Site_StartDate,8), "mmmm yyyy") -> September 2025 | E31: 30 | F31: 30 | G31: 30 | H31: 30 | I31: 30 | J31: 30 | K31: 30 | L31: 30 | M31: 30 | N31: 30 | O31: Days
A32: =HYPERLINK("#'8.1.1.1-2 Transport fuel'!A1", "8.1.1.1-2 Transport fuel") -> 8.1.1.1-2 Transport fuel | D32: =TEXT(EDATE(X_Cell_Site_StartDate,9), "mmmm yyyy") -> October 2025 | E32: 31 | F32: 31 | G32: 31 | H32: 31 | I32: 31 | J32: 31 | K32: 31 | L32: 31 | M32: 31 | N32: 31 | O32: Days
A33: =HYPERLINK("#'8.2.1.1-2 Stationary fuel'!A1", "8.2.1.1-2 Stationary fuel") -> 8.2.1.1-2 Stationary fuel | D33: =TEXT(EDATE(X_Cell_Site_StartDate,10), "mmmm yyyy") -> November 2025 | E33: 30 | F33: 30 | G33: 30 | H33: 30 | I33: 30 | J33: 30 | K33: 30 | L33: 30 | M33: 30 | N33: 30 | O33: Days
A34: =HYPERLINK("#'14.1.1-2 Purchased electricity'!A1", "14.1.1-2 Purchased electricity") -> 14.1.1-2 Purchased electricity | D34: =TEXT(EDATE(X_Cell_Site_StartDate,11), "mmmm yyyy") -> December 2025 | E34: 31 | F34: 31 | G34: 31 | H34: 31 | I34: 31 | J34: 31 | K34: 31 | L34: 31 | M34: 31 | N34: 31 | O34: Days
A37: APPENDICES | D37: Head
A38: =HYPERLINK("#'Constants - Pasture Beef'!A1", "Constants - Pasture Beef") -> Constants - Pasture Beef | D38: Method 1 values | E38: Bulls < 1 year | F38: Bulls > 1 year | G38: Cows < 1 year | H38: Cows 1-2 years | I38: Cows 2-3 years | J38: Cows > 3 years | K38: Steers < 1 year | L38: Steers 1-2 years | M38: Steers 2-3 years | N38: Steers >3 years
A39: =HYPERLINK("#'Constants - Ag Residue'!A1", "Constants - Ag residue") -> Constants - Ag residue | D39: Spring | E39: 100 | F39: 100 | G39: 100 | H39: 100 | I39: 100 | J39: 100 | K39: 100 | L39: 100 | M39: 100 | N39: 100 | O39: Head
A40: =HYPERLINK("#'Constants - Common Livestock'!A1", "Constants - Common Livestock") -> Constants - Common Livestock | D40: Summer | E40: 100 | F40: 100 | G40: 100 | H40: 100 | I40: 100 | J40: 100 | K40: 100 | L40: 100 | M40: 100 | N40: 100 | O40: Head
A41: =HYPERLINK("#'Constants - Electricity'!A1", "Constants - Electricity") -> Constants - Electricity | D41: Autumn | E41: 100 | F41: 100 | G41: 100 | H41: 100 | I41: 100 | J41: 100 | K41: 100 | L41: 100 | M41: 100 | N41: 100 | O41: Head
A42: =HYPERLINK("#'Constants - Fertiliser'!A1", "Constants - Fertiliser") -> Constants - Fertiliser | D42: Winter | E42: 100 | F42: 100 | G42: 100 | H42: 100 | I42: 100 | J42: 100 | K42: 100 | L42: 100 | M42: 100 | N42: 100 | O42: Head
A43: =HYPERLINK("#'Constants - Fuel'!A1", "Constants - Fuel") -> Constants - Fuel
A44: =HYPERLINK("#'Constants - Common'!A1", "Constants - Common") -> Constants - Common | D44: Method 2 values | E44: Bulls < 1 year | F44: Bulls > 1 year | G44: Cows < 1 year | H44: Cows 1-2 years | I44: Cows 2-3 years | J44: Cows > 3 years | K44: Steers < 1 year | L44: Steers 1-2 years | M44: Steers 2-3 years | N44: Steers >3 years
A45: =HYPERLINK("#'Acknowledgements'!A1", "Acknowledgements") -> Acknowledgements | D45: =TEXT(X_Cell_Site_StartDate, "mmmm yyyy") -> January 2025 | E45: 100 | F45: 100 | G45: 100 | H45: 100 | I45: 100 | J45: 100 | K45: 100 | L45: 100 | M45: 100 | N45: 100 | O45: Head
A46: =HYPERLINK("#'Overview'!A1", "Overview") -> Overview | D46: =TEXT(EDATE(X_Cell_Site_StartDate,1), "mmmm yyyy") -> February 2025 | E46: 100 | F46: 100 | G46: 100 | H46: 100 | I46: 100 | J46: 100 | K46: 100 | L46: 100 | M46: 100 | N46: 100 | O46: Head
D47: =TEXT(EDATE(X_Cell_Site_StartDate,2), "mmmm yyyy") -> March 2025 | E47: 100 | F47: 100 | G47: 100 | H47: 100 | I47: 100 | J47: 100 | K47: 100 | L47: 100 | M47: 100 | N47: 100 | O47: Head
D48: =TEXT(EDATE(X_Cell_Site_StartDate,3), "mmmm yyyy") -> April 2025 | E48: 100 | F48: 100 | G48: 100 | H48: 100 | I48: 100 | J48: 100 | K48: 100 | L48: 100 | M48: 100 | N48: 100 | O48: Head
D49: =TEXT(EDATE(X_Cell_Site_StartDate,4), "mmmm yyyy") -> May 2025 | E49: 100 | F49: 100 | G49: 100 | H49: 100 | I49: 100 | J49: 100 | K49: 100 | L49: 100 | M49: 100 | N49: 100 | O49: Head
D50: =TEXT(EDATE(X_Cell_Site_StartDate,5), "mmmm yyyy") -> June 2025 | E50: 100 | F50: 100 | G50: 100 | H50: 100 | I50: 100 | J50: 100 | K50: 100 | L50: 100 | M50: 100 | N50: 100 | O50: Head
D51: =TEXT(EDATE(X_Cell_Site_StartDate,6), "mmmm yyyy") -> July 2025 | E51: 100 | F51: 100 | G51: 100 | H51: 100 | I51: 100 | J51: 100 | K51: 100 | L51: 100 | M51: 100 | N51: 100 | O51: Head
D52: =TEXT(EDATE(X_Cell_Site_StartDate,7), "mmmm yyyy") -> August 2025 | E52: 100 | F52: 100 | G52: 100 | H52: 100 | I52: 100 | J52: 100 | K52: 100 | L52: 100 | M52: 100 | N52: 100 | O52: Head
D53: =TEXT(EDATE(X_Cell_Site_StartDate,8), "mmmm yyyy") -> September 2025 | E53: 100 | F53: 100 | G53: 100 | H53: 100 | I53: 100 | J53: 100 | K53: 100 | L53: 100 | M53: 100 | N53: 100 | O53: Head
D54: =TEXT(EDATE(X_Cell_Site_StartDate,9), "mmmm yyyy") -> October 2025 | E54: 100 | F54: 100 | G54: 100 | H54: 100 | I54: 100 | J54: 100 | K54: 100 | L54: 100 | M54: 100 | N54: 100 | O54: Head
D55: =TEXT(EDATE(X_Cell_Site_StartDate,10), "mmmm yyyy") -> November 2025 | E55: 100 | F55: 100 | G55: 100 | H55: 100 | I55: 100 | J55: 100 | K55: 100 | L55: 100 | M55: 100 | N55: 100 | O55: Head
D56: =TEXT(EDATE(X_Cell_Site_StartDate,11), "mmmm yyyy") -> December 2025 | E56: 100 | F56: 100 | G56: 100 | H56: 100 | I56: 100 | J56: 100 | K56: 100 | L56: 100 | M56: 100 | N56: 100 | O56: Head
D59: Liveweight
D60: Method 1 default values (do not edit) | E60: Bulls < 1 year | F60: Bulls > 1 year | G60: Cows < 1 year | H60: Cows 1-2 years | I60: Cows 2-3 years | J60: Cows > 3 years | K60: Steers < 1 year | L60: Steers 1-2 years | M60: Steers 2-3 years | N60: Steers >3 years
D61: Spring | E61: 340 | F61: 800 | G61: 260 | H61: 420 | I61: 550 | J61: 550 | K61: 300 | L61: 480 | M61: 480 | N61: 480 | O61: kg/head
D62: Summer | E62: 380 | F62: 780 | G62: 300 | H62: 450 | I62: 530 | J62: 530 | K62: 340 | L62: 470 | M62: 470 | N62: 470 | O62: kg/head
D63: Autumn | E63: 100 | F63: 680 | G63: 80 | H63: 320 | I63: 480 | J63: 480 | K63: 100 | L63: 340 | M63: 340 | N63: 340 | O63: kg/head
D64: Winter | E64: 190 | F64: 700 | G64: 150 | H64: 330 | I64: 490 | J64: 490 | K64: 170 | L64: 360 | M64: 360 | N64: 360 | O64: kg/head
D66: Method 2 custom values (edit if known) | E66: Bulls < 1 year | F66: Bulls > 1 year | G66: Cows < 1 year | H66: Cows 1-2 years | I66: Cows 2-3 years | J66: Cows > 3 years | K66: Steers < 1 year | L66: Steers 1-2 years | M66: Steers 2-3 years | N66: Steers >3 years
D67: =TEXT(X_Cell_Site_StartDate, "mmmm yyyy") -> January 2025 | E67: 380 | F67: 780 | G67: 300 | H67: 450 | I67: 530 | J67: 530 | K67: 340 | L67: 470 | M67: 470 | N67: 470 | O67: kg/head
D68: =TEXT(EDATE(X_Cell_Site_StartDate,1), "mmmm yyyy") -> February 2025 | E68: 380 | F68: 780 | G68: 300 | H68: 450 | I68: 530 | J68: 530 | K68: 340 | L68: 470 | M68: 470 | N68: 470 | O68: kg/head
D69: =TEXT(EDATE(X_Cell_Site_StartDate,2), "mmmm yyyy") -> March 2025 | E69: 100 | F69: 680 | G69: 80 | H69: 320 | I69: 480 | J69: 480 | K69: 100 | L69: 340 | M69: 340 | N69: 340 | O69: kg/head
D70: =TEXT(EDATE(X_Cell_Site_StartDate,3), "mmmm yyyy") -> April 2025 | E70: 100 | F70: 680 | G70: 80 | H70: 320 | I70: 480 | J70: 480 | K70: 100 | L70: 340 | M70: 340 | N70: 340 | O70: kg/head
D71: =TEXT(EDATE(X_Cell_Site_StartDate,4), "mmmm yyyy") -> May 2025 | E71: 100 | F71: 680 | G71: 80 | H71: 320 | I71: 480 | J71: 480 | K71: 100 | L71: 340 | M71: 340 | N71: 340 | O71: kg/head
D72: =TEXT(EDATE(X_Cell_Site_StartDate,5), "mmmm yyyy") -> June 2025 | E72: 190 | F72: 700 | G72: 150 | H72: 330 | I72: 490 | J72: 490 | K72: 170 | L72: 360 | M72: 360 | N72: 360 | O72: kg/head
D73: =TEXT(EDATE(X_Cell_Site_StartDate,6), "mmmm yyyy") -> July 2025 | E73: 190 | F73: 700 | G73: 150 | H73: 330 | I73: 490 | J73: 490 | K73: 170 | L73: 360 | M73: 360 | N73: 360 | O73: kg/head
D74: =TEXT(EDATE(X_Cell_Site_StartDate,7), "mmmm yyyy") -> August 2025 | E74: 190 | F74: 700 | G74: 150 | H74: 330 | I74: 490 | J74: 490 | K74: 170 | L74: 360 | M74: 360 | N74: 360 | O74: kg/head
D75: =TEXT(EDATE(X_Cell_Site_StartDate,8), "mmmm yyyy") -> September 2025 | E75: 340 | F75: 800 | G75: 260 | H75: 420 | I75: 550 | J75: 550 | K75: 300 | L75: 480 | M75: 480 | N75: 480 | O75: kg/head
D76: =TEXT(EDATE(X_Cell_Site_StartDate,9), "mmmm yyyy") -> October 2025 | E76: 340 | F76: 800 | G76: 260 | H76: 420 | I76: 550 | J76: 550 | K76: 300 | L76: 480 | M76: 480 | N76: 480 | O76: kg/head
D77: =TEXT(EDATE(X_Cell_Site_StartDate,10), "mmmm yyyy") -> November 2025 | E77: 340 | F77: 800 | G77: 260 | H77: 420 | I77: 550 | J77: 550 | K77: 300 | L77: 480 | M77: 480 | N77: 480 | O77: kg/head
D78: =TEXT(EDATE(X_Cell_Site_StartDate,11), "mmmm yyyy") -> December 2025 | E78: 380 | F78: 780 | G78: 300 | H78: 450 | I78: 530 | J78: 530 | K78: 340 | L78: 470 | M78: 470 | N78: 470 | O78: kg/head
D81: Liveweight gain
D82: Method 1 default values (do not edit) | E82: Bulls < 1 year | F82: Bulls > 1 year | G82: Cows < 1 year | H82: Cows 1-2 years | I82: Cows 2-3 years | J82: Cows > 3 years | K82: Steers < 1 year | L82: Steers 1-2 years | M82: Steers 2-3 years | N82: Steers >3 years
D83: Spring | E83: 1.64 | F83: 1.1 | G83: 1.21 | H83: 0.99 | I83: 0.66 | J83: 0.66 | K83: 1.42 | L83: 1.1 | M83: 1.1 | N83: 1.1 | O83: kg/head/day
D84: Summer | E84: 0.44 | F84: -0.22 | G84: 0.44 | H84: 0.33 | I84: -0.22 | J84: -0.22 | K84: 0.44 | L84: -0.11 | M84: -0.11 | N84: -0.11 | O84: kg/head/day
D85: Autumn | E85: 0.6 | F85: 0 | G85: 0.6 | H85: 0.22 | I85: -0.55 | J85: -0.55 | K85: 0.6 | L85: 0 | M85: 0 | N85: 0 | O85: kg/head/day
D86: Winter | E86: 0.99 | F86: 0.22 | G86: 0.77 | H86: 0.11 | I86: 0.11 | J86: 0.11 | K86: 0.77 | L86: 0.44 | M86: 0.44 | N86: 0.44 | O86: kg/head/day
D88: Method 2 custom values (edit if known) | E88: Bulls < 1 year | F88: Bulls > 1 year | G88: Cows < 1 year | H88: Cows 1-2 years | I88: Cows 2-3 years | J88: Cows > 3 years | K88: Steers < 1 year | L88: Steers 1-2 years | M88: Steers 2-3 years | N88: Steers >3 years
D89: =TEXT(X_Cell_Site_StartDate, "mmmm yyyy") -> January 2025 | E89: 0.44 | F89: -0.22 | G89: 0.44 | H89: 0.33 | I89: -0.22 | J89: -0.22 | K89: 0.44 | L89: -0.11 | M89: -0.11 | N89: -0.11 | O89: kg/head/day
D90: =TEXT(EDATE(X_Cell_Site_StartDate,1), "mmmm yyyy") -> February 2025 | E90: 0.44 | F90: -0.22 | G90: 0.44 | H90: 0.33 | I90: -0.22 | J90: -0.22 | K90: 0.44 | L90: -0.11 | M90: -0.11 | N90: -0.11 | O90: kg/head/day
D91: =TEXT(EDATE(X_Cell_Site_StartDate,2), "mmmm yyyy") -> March 2025 | E91: 0.6 | F91: 0 | G91: 0.6 | H91: 0.22 | I91: -0.55 | J91: -0.55 | K91: 0.6 | L91: 0 | M91: 0 | N91: 0 | O91: kg/head/day
D92: =TEXT(EDATE(X_Cell_Site_StartDate,3), "mmmm yyyy") -> April 2025 | E92: 0.6 | F92: 0 | G92: 0.6 | H92: 0.22 | I92: -0.55 | J92: -0.55 | K92: 0.6 | L92: 0 | M92: 0 | N92: 0 | O92: kg/head/day
D93: =TEXT(EDATE(X_Cell_Site_StartDate,4), "mmmm yyyy") -> May 2025 | E93: 0.6 | F93: 0 | G93: 0.6 | H93: 0.22 | I93: -0.55 | J93: -0.55 | K93: 0.6 | L93: 0 | M93: 0 | N93: 0 | O93: kg/head/day
D94: =TEXT(EDATE(X_Cell_Site_StartDate,5), "mmmm yyyy") -> June 2025 | E94: 0.99 | F94: 0.22 | G94: 0.77 | H94: 0.11 | I94: 0.11 | J94: 0.11 | K94: 0.77 | L94: 0.44 | M94: 0.44 | N94: 0.44 | O94: kg/head/day
D95: =TEXT(EDATE(X_Cell_Site_StartDate,6), "mmmm yyyy") -> July 2025 | E95: 0.99 | F95: 0.22 | G95: 0.77 | H95: 0.11 | I95: 0.11 | J95: 0.11 | K95: 0.77 | L95: 0.44 | M95: 0.44 | N95: 0.44 | O95: kg/head/day
D96: =TEXT(EDATE(X_Cell_Site_StartDate,7), "mmmm yyyy") -> August 2025 | E96: 0.99 | F96: 0.22 | G96: 0.77 | H96: 0.11 | I96: 0.11 | J96: 0.11 | K96: 0.77 | L96: 0.44 | M96: 0.44 | N96: 0.44 | O96: kg/head/day
D97: =TEXT(EDATE(X_Cell_Site_StartDate,8), "mmmm yyyy") -> September 2025 | E97: 1.64 | F97: 1.1 | G97: 1.21 | H97: 0.99 | I97: 0.66 | J97: 0.66 | K97: 1.42 | L97: 1.1 | M97: 1.1 | N97: 1.1 | O97: kg/head/day
D98: =TEXT(EDATE(X_Cell_Site_StartDate,9), "mmmm yyyy") -> October 2025 | E98: 1.64 | F98: 1.1 | G98: 1.21 | H98: 0.99 | I98: 0.66 | J98: 0.66 | K98: 1.42 | L98: 1.1 | M98: 1.1 | N98: 1.1 | O98: kg/head/day
D99: =TEXT(EDATE(X_Cell_Site_StartDate,10), "mmmm yyyy") -> November 2025 | E99: 1.64 | F99: 1.1 | G99: 1.21 | H99: 0.99 | I99: 0.66 | J99: 0.66 | K99: 1.42 | L99: 1.1 | M99: 1.1 | N99: 1.1 | O99: kg/head/day
D100: =TEXT(EDATE(X_Cell_Site_StartDate,11), "mmmm yyyy") -> December 2025 | E100: 0.44 | F100: -0.22 | G100: 0.44 | H100: 0.33 | I100: -0.22 | J100: -0.22 | K100: 0.44 | L100: -0.11 | M100: -0.11 | N100: -0.11 | O100: kg/head/day
D103: Proportion of cows > 1 years in calf in the season of calving
D104: Method 1 values
D105: Calving season | E105: Winter | F105: ← Please select
K108: Calves born
E110: Calving season (select) | F110: Cows 1-2 years | G110: Cows 2-3 years | H110: Cows > 3 years | L110: Cows < 1 year | M110: Steers < 1 year
D111: ="Proportion of cows > 1 years in calf in " & E105 -> Proportion of cows > 1 years in calf in Winter | E111: Yes | F111: 0.7 | G111: 0.5 | H111: 0.5 | I111: Percent | L111: =MAX(0, G42-G41) -> 0 | M111: =MAX(0,K42-K41) -> 0
D112: Spring | E112: Yes | F112: 0.1 | G112: 0.4 | H112: 0.4 | I112: Percent | L112: =MAX(0, G39-G42) -> 0 | M112: =MAX(0,K39-K42) -> 0
D113: Summer | E113: Yes | F113: 0.1 | G113: 0 | H113: 0 | I113: Percent | L113: =MAX(0, G40-G39) -> 0 | M113: =MAX(0,K40-K39) -> 0
D114: Autumn | E114: No | F114: 0 | G114: 0 | H114: 0 | I114: Percent | L114: =MAX(0,G41-G40) -> 0 | M114: =MAX(0,K41-K40) -> 0
J115: Proportion born this season
...

Sheet Input - Pasture Beef (Enteric)
A1: #VALUE! | C1: Input -Pasture Beef
A3: =HYPERLINK("#'Home'!A1", "Home") -> Home
A4: =HYPERLINK("#'Results'!A1", "Results") -> Results
D5: Herd movement
A7: INPUTS | D7: State | E7: =X_Cell_Site_State -> Western Australia
A8: =HYPERLINK("#'Input - Enterprise'!A1", "Enterprise") -> Enterprise | D8: Livestock production region | E8: South West | F8: ← Please select
A9: =HYPERLINK("#'Input - Site'!A1", "Site") -> Site | D9: Cattle breed | E9: Hereford or Shorthorn breeds | F9: ← Please select
A10: =HYPERLINK("#'Input - Pasture Beef'!A1", "Pasture Beef") -> Pasture Beef
A11: =HYPERLINK("#'Input - Pasture Beef (Enteric)'!A1", "Pasture Beef (Enteric)") -> Pasture Beef (Enteric)
A12: =HYPERLINK("#'Input - Pasture'!A1", "Pasture") -> Pasture
A13: =HYPERLINK("#'Input - Fertiliser'!A1", "Fertiliser") -> Fertiliser | D13: NOTE: VEERG states that under method 2, time periods may be seasons, months or a custom time period. In this example, method 2 time periods are months.
A14: =HYPERLINK("#'Input - Fuel'!A1", "Fuel") -> Fuel
A15: =HYPERLINK("#'Input - Electricity'!A1", "Electricity") -> Electricity | D15: Duration on farm
D16: Method 1 default values (do not edit) | E16: Bulls < 1 year | F16: Bulls > 1 year | G16: Cows < 1 year | H16: Cows 1-2 years | I16: Cows 2-3 years | J16: Cows > 3 years | K16: Steers < 1 year | L16: Steers 1-2 years | M16: Steers 2-3 years | N16: Steers >3 years
D17: Spring | E17: 91.25 | F17: 91.25 | G17: 91.25 | H17: 91.25 | I17: 91.25 | J17: 91.25 | K17: 91.25 | L17: 91.25 | M17: 91.25 | N17: 91.25 | O17: Days
A18: CALCULATIONS | D18: Summer | E18: 91.25 | F18: 91.25 | G18: 91.25 | H18: 91.25 | I18: 91.25 | J18: 91.25 | K18: 91.25 | L18: 91.25 | M18: 91.25 | N18: 91.25 | O18: Days
A19: =HYPERLINK("#'3.2.1.1-2 Enteric Methane'!A1", "3.2.1.1-2 Enteric methane") -> 3.2.1.1-2 Enteric methane | D19: Autumn | E19: 91.25 | F19: 91.25 | G19: 91.25 | H19: 91.25 | I19: 91.25 | J19: 91.25 | K19: 91.25 | L19: 91.25 | M19: 91.25 | N19: 91.25 | O19: Days
A20: =HYPERLINK("#'4.2.1.1-2 Methane'!A1", "4.2.1.1-2 Manure methane") -> 4.2.1.1-2 Manure methane | D20: Winter | E20: 91.25 | F20: 91.25 | G20: 91.25 | H20: 91.25 | I20: 91.25 | J20: 91.25 | K20: 91.25 | L20: 91.25 | M20: 91.25 | N20: 91.25 | O20: Days
A21: =HYPERLINK("#'4.2.1.3-4 Soil direct N20'!A1", "4.2.1.3-4 Soil direct N2O") -> 4.2.1.3-4 Soil direct N2O
A22: =HYPERLINK("#'4.2.1.5-6 Soil Atmos Dep'!A1", "4.2.1.5-6 Soil atm. deposition") -> 4.2.1.5-6 Soil atm. deposition | D22: Method 2 custom values (edit if known) | E22: Bulls < 1 year | F22: Bulls > 1 year | G22: Cows < 1 year | H22: Cows 1-2 years | I22: Cows 2-3 years | J22: Cows > 3 years | K22: Steers < 1 year | L22: Steers 1-2 years | M22: Steers 2-3 years | N22: Steers >3 years
A23: =HYPERLINK("#'4.2.1.7-8 Soil leach runoff'!A1", "4.2.1.7-8 Soil leach & runoff") -> 4.2.1.7-8 Soil leach & runoff | D23: =TEXT(X_Cell_Site_StartDate, "mmmm yyyy") -> January 2025 | E23: =DAY(EOMONTH($D23,0)) -> 31 | F23: =DAY(EOMONTH($D23,0)) -> 31 | G23: =DAY(EOMONTH($D23,0)) -> 31 | H23: =DAY(EOMONTH($D23,0)) -> 31 | I23: =DAY(EOMONTH($D23,0)) -> 31 | J23: =DAY(EOMONTH($D23,0)) -> 31 | K23: =DAY(EOMONTH($D23,0)) -> 31 | L23: =DAY(EOMONTH($D23,0)) -> 31 | ... N23: =DAY(EOMONTH($D23,0)) -> 31 | O23: Days
A24: =HYPERLINK("#'5.1.1.1-2 Inorganic fert N2O'!A1", "5.1.1.1-2 Inorganic fert N2O") -> 5.1.1.1-2 Inorganic fert N2O | D24: =TEXT(EDATE(X_Cell_Site_StartDate,1), "mmmm yyyy") -> February 2025 | E24: =DAY(EOMONTH($D24,0)) -> 28 | F24: =DAY(EOMONTH($D24,0)) -> 28 | G24: =DAY(EOMONTH($D24,0)) -> 28 | H24: =DAY(EOMONTH($D24,0)) -> 28 | I24: =DAY(EOMONTH($D24,0)) -> 28 | J24: =DAY(EOMONTH($D24,0)) -> 28 | K24: =DAY(EOMONTH($D24,0)) -> 28 | L24: =DAY(EOMONTH($D24,0)) -> 28 | ... N24: =DAY(EOMONTH($D24,0)) -> 28 | O24: Days
A25: =HYPERLINK("#'5.1.1.3-4 Inorganic fert CO2'!A1", "5.1.1.3-4 Inorganic fert CO2") -> 5.1.1.3-4 Inorganic fert CO2 | D25: =TEXT(EDATE(X_Cell_Site_StartDate,2), "mmmm yyyy") -> March 2025 | E25: =DAY(EOMONTH($D25,0)) -> 31 | F25: =DAY(EOMONTH($D25,0)) -> 31 | G25: =DAY(EOMONTH($D25,0)) -> 31 | H25: =DAY(EOMONTH($D25,0)) -> 31 | I25: =DAY(EOMONTH($D25,0)) -> 31 | J25: =DAY(EOMONTH($D25,0)) -> 31 | K25: =DAY(EOMONTH($D25,0)) -> 31 | L25: =DAY(EOMONTH($D25,0)) -> 31 | ... N25: =DAY(EOMONTH($D25,0)) -> 31 | O25: Days
A26: =HYPERLINK("#'5.2.1.1-2 Organic Fert N2O'!A1", "5.2.1.1-2 Organic fert N2O") -> 5.2.1.1-2 Organic fert N2O | D26: =TEXT(EDATE(X_Cell_Site_StartDate,3), "mmmm yyyy") -> April 2025 | E26: =DAY(EOMONTH($D26,0)) -> 30 | F26: =DAY(EOMONTH($D26,0)) -> 30 | G26: =DAY(EOMONTH($D26,0)) -> 30 | H26: =DAY(EOMONTH($D26,0)) -> 30 | I26: =DAY(EOMONTH($D26,0)) -> 30 | J26: =DAY(EOMONTH($D26,0)) -> 30 | K26: =DAY(EOMONTH($D26,0)) -> 30 | L26: =DAY(EOMONTH($D26,0)) -> 30 | ... N26: =DAY(EOMONTH($D26,0)) -> 30 | O26: Days
A27: =HYPERLINK("#'5.3.1.1-2 Lime CO2'!A1", "5.3.1.1-2 Lime CO2") -> 5.3.1.1-2 Lime CO2 | D27: =TEXT(EDATE(X_Cell_Site_StartDate,4), "mmmm yyyy") -> May 2025 | E27: =DAY(EOMONTH($D27,0)) -> 31 | F27: =DAY(EOMONTH($D27,0)) -> 31 | G27: =DAY(EOMONTH($D27,0)) -> 31 | H27: =DAY(EOMONTH($D27,0)) -> 31 | I27: =DAY(EOMONTH($D27,0)) -> 31 | J27: =DAY(EOMONTH($D27,0)) -> 31 | K27: =DAY(EOMONTH($D27,0)) -> 31 | L27: =DAY(EOMONTH($D27,0)) -> 31 | ... N27: =DAY(EOMONTH($D27,0)) -> 31 | O27: Days
A28: =HYPERLINK("#'5.4.1.1-4 Atmos deposition'!A1", "5.4.1.1-4 Atmos. deposition") -> 5.4.1.1-4 Atmos. deposition | D28: =TEXT(EDATE(X_Cell_Site_StartDate,5), "mmmm yyyy") -> June 2025 | E28: =DAY(EOMONTH($D28,0)) -> 30 | F28: =DAY(EOMONTH($D28,0)) -> 30 | G28: =DAY(EOMONTH($D28,0)) -> 30 | H28: =DAY(EOMONTH($D28,0)) -> 30 | I28: =DAY(EOMONTH($D28,0)) -> 30 | J28: =DAY(EOMONTH($D28,0)) -> 30 | K28: =DAY(EOMONTH($D28,0)) -> 30 | L28: =DAY(EOMONTH($D28,0)) -> 30 | ... N28: =DAY(EOMONTH($D28,0)) -> 30 | O28: Days
A29: =HYPERLINK("#'5.5.1.1-2 Leaching and runoff'!A1", "5.5.1.1-2 Leaching & runoff") -> 5.5.1.1-2 Leaching & runoff | D29: =TEXT(EDATE(X_Cell_Site_StartDate,6), "mmmm yyyy") -> July 2025 | E29: =DAY(EOMONTH($D29,0)) -> 31 | F29: =DAY(EOMONTH($D29,0)) -> 31 | G29: =DAY(EOMONTH($D29,0)) -> 31 | H29: =DAY(EOMONTH($D29,0)) -> 31 | I29: =DAY(EOMONTH($D29,0)) -> 31 | J29: =DAY(EOMONTH($D29,0)) -> 31 | K29: =DAY(EOMONTH($D29,0)) -> 31 | L29: =DAY(EOMONTH($D29,0)) -> 31 | ... N29: =DAY(EOMONTH($D29,0)) -> 31 | O29: Days
A30: =HYPERLINK("#'6.2.1.1-2 Pasture residue N2O'!A1", "6.2.1.1-2 Pasture residue N2O") -> 6.2.1.1-2 Pasture residue N2O | D30: =TEXT(EDATE(X_Cell_Site_StartDate,7), "mmmm yyyy") -> August 2025 | E30: =DAY(EOMONTH($D30,0)) -> 31 | F30: =DAY(EOMONTH($D30,0)) -> 31 | G30: =DAY(EOMONTH($D30,0)) -> 31 | H30: =DAY(EOMONTH($D30,0)) -> 31 | I30: =DAY(EOMONTH($D30,0)) -> 31 | J30: =DAY(EOMONTH($D30,0)) -> 31 | K30: =DAY(EOMONTH($D30,0)) -> 31 | L30: =DAY(EOMONTH($D30,0)) -> 31 | ... N30: =DAY(EOMONTH($D30,0)) -> 31 | O30: Days
A31: =HYPERLINK("#'6.3.1.1-2 Leach runoff pasture'!A1", "6.3.1.1-2 Leach & runoff (pasture)") -> 6.3.1.1-2 Leach & runoff (pasture) | D31: =TEXT(EDATE(X_Cell_Site_StartDate,8), "mmmm yyyy") -> September 2025 | E31: =DAY(EOMONTH($D31,0)) -> 30 | F31: =DAY(EOMONTH($D31,0)) -> 30 | G31: =DAY(EOMONTH($D31,0)) -> 30 | H31: =DAY(EOMONTH($D31,0)) -> 30 | I31: =DAY(EOMONTH($D31,0)) -> 30 | J31: =DAY(EOMONTH($D31,0)) -> 30 | K31: =DAY(EOMONTH($D31,0)) -> 30 | L31: =DAY(EOMONTH($D31,0)) -> 30 | ... N31: =DAY(EOMONTH($D31,0)) -> 30 | O31: Days
A32: =HYPERLINK("#'8.1.1.1-2 Transport fuel'!A1", "8.1.1.1-2 Transport fuel") -> 8.1.1.1-2 Transport fuel | D32: =TEXT(EDATE(X_Cell_Site_StartDate,9), "mmmm yyyy") -> October 2025 | E32: =DAY(EOMONTH($D32,0)) -> 31 | F32: =DAY(EOMONTH($D32,0)) -> 31 | G32: =DAY(EOMONTH($D32,0)) -> 31 | H32: =DAY(EOMONTH($D32,0)) -> 31 | I32: =DAY(EOMONTH($D32,0)) -> 31 | J32: =DAY(EOMONTH($D32,0)) -> 31 | K32: =DAY(EOMONTH($D32,0)) -> 31 | L32: =DAY(EOMONTH($D32,0)) -> 31 | ... N32: =DAY(EOMONTH($D32,0)) -> 31 | O32: Days
A33: =HYPERLINK("#'8.2.1.1-2 Stationary fuel'!A1", "8.2.1.1-2 Stationary fuel") -> 8.2.1.1-2 Stationary fuel | D33: =TEXT(EDATE(X_Cell_Site_StartDate,10), "mmmm yyyy") -> November 2025 | E33: =DAY(EOMONTH($D33,0)) -> 30 | F33: =DAY(EOMONTH($D33,0)) -> 30 | G33: =DAY(EOMONTH($D33,0)) -> 30 | H33: =DAY(EOMONTH($D33,0)) -> 30 | I33: =DAY(EOMONTH($D33,0)) -> 30 | J33: =DAY(EOMONTH($D33,0)) -> 30 | K33: =DAY(EOMONTH($D33,0)) -> 30 | L33: =DAY(EOMONTH($D33,0)) -> 30 | ... N33: =DAY(EOMONTH($D33,0)) -> 30 | O33: Days
A34: =HYPERLINK("#'14.1.1-2 Purchased electricity'!A1", "14.1.1-2 Purchased electricity") -> 14.1.1-2 Purchased electricity | D34: =TEXT(EDATE(X_Cell_Site_StartDate,11), "mmmm yyyy") -> December 2025 | E34: =DAY(EOMONTH($D34,0)) -> 31 | F34: =DAY(EOMONTH($D34,0)) -> 31 | G34: =DAY(EOMONTH($D34,0)) -> 31 | H34: =DAY(EOMONTH($D34,0)) -> 31 | I34: =DAY(EOMONTH($D34,0)) -> 31 | J34: =DAY(EOMONTH($D34,0)) -> 31 | K34: =DAY(EOMONTH($D34,0)) -> 31 | L34: =DAY(EOMONTH($D34,0)) -> 31 | ... N34: =DAY(EOMONTH($D34,0)) -> 31 | O34: Days
A37: APPENDICES | D37: Head
A38: =HYPERLINK("#'Constants - Pasture Beef'!A1", "Constants - Pasture Beef") -> Constants - Pasture Beef | D38: Method 1 values | E38: Bulls < 1 year | F38: Bulls > 1 year | G38: Cows < 1 year | H38: Cows 1-2 years | I38: Cows 2-3 years | J38: Cows > 3 years | K38: Steers < 1 year | L38: Steers 1-2 years | M38: Steers 2-3 years | N38: Steers >3 years
A39: =HYPERLINK("#'Constants - Ag Residue'!A1", "Constants - Ag residue") -> Constants - Ag residue | D39: Spring | E39: 100 | F39: 100 | G39: 100 | H39: 100 | I39: 100 | J39: 100 | K39: 100 | L39: 100 | M39: 100 | N39: 100 | O39: Head
A40: =HYPERLINK("#'Constants - Common Livestock'!A1", "Constants - Common Livestock") -> Constants - Common Livestock | D40: Summer | E40: 100 | F40: 100 | G40: 100 | H40: 100 | I40: 100 | J40: 100 | K40: 100 | L40: 100 | M40: 100 | N40: 100 | O40: Head
A41: =HYPERLINK("#'Constants - Electricity'!A1", "Constants - Electricity") -> Constants - Electricity | D41: Autumn | E41: 100 | F41: 100 | G41: 100 | H41: 100 | I41: 100 | J41: 100 | K41: 100 | L41: 100 | M41: 100 | N41: 100 | O41: Head
A42: =HYPERLINK("#'Constants - Fertiliser'!A1", "Constants - Fertiliser") -> Constants - Fertiliser | D42: Winter | E42: 100 | F42: 100 | G42: 100 | H42: 100 | I42: 100 | J42: 100 | K42: 100 | L42: 100 | M42: 100 | N42: 100 | O42: Head
A43: =HYPERLINK("#'Constants - Fuel'!A1", "Constants - Fuel") -> Constants - Fuel
A44: =HYPERLINK("#'Constants - Common'!A1", "Constants - Common") -> Constants - Common | D44: Method 2 values | E44: Bulls < 1 year | F44: Bulls > 1 year | G44: Cows < 1 year | H44: Cows 1-2 years | I44: Cows 2-3 years | J44: Cows > 3 years | K44: Steers < 1 year | L44: Steers 1-2 years | M44: Steers 2-3 years | N44: Steers >3 years
A45: =HYPERLINK("#'Acknowledgements'!A1", "Acknowledgements") -> Acknowledgements | D45: =TEXT(X_Cell_Site_StartDate, "mmmm yyyy") -> January 2025 | E45: 100 | F45: 100 | G45: 100 | H45: 100 | I45: 100 | J45: 100 | K45: 100 | L45: 100 | M45: 100 | N45: 100 | O45: Head
A46: =HYPERLINK("#'Overview'!A1", "Overview") -> Overview | D46: =TEXT(EDATE(X_Cell_Site_StartDate,1), "mmmm yyyy") -> February 2025 | E46: 100 | F46: 100 | G46: 100 | H46: 100 | I46: 100 | J46: 100 | K46: 100 | L46: 100 | M46: 100 | N46: 100 | O46: Head
D47: =TEXT(EDATE(X_Cell_Site_StartDate,2), "mmmm yyyy") -> March 2025 | E47: 100 | F47: 100 | G47: 100 | H47: 100 | I47: 100 | J47: 100 | K47: 100 | L47: 100 | M47: 100 | N47: 100 | O47: Head
D48: =TEXT(EDATE(X_Cell_Site_StartDate,3), "mmmm yyyy") -> April 2025 | E48: 100 | F48: 100 | G48: 100 | H48: 100 | I48: 100 | J48: 100 | K48: 100 | L48: 100 | M48: 100 | N48: 100 | O48: Head
D49: =TEXT(EDATE(X_Cell_Site_StartDate,4), "mmmm yyyy") -> May 2025 | E49: 100 | F49: 100 | G49: 100 | H49: 100 | I49: 100 | J49: 100 | K49: 100 | L49: 100 | M49: 100 | N49: 100 | O49: Head
D50: =TEXT(EDATE(X_Cell_Site_StartDate,5), "mmmm yyyy") -> June 2025 | E50: 100 | F50: 100 | G50: 100 | H50: 100 | I50: 100 | J50: 100 | K50: 100 | L50: 100 | M50: 100 | N50: 100 | O50: Head
D51: =TEXT(EDATE(X_Cell_Site_StartDate,6), "mmmm yyyy") -> July 2025 | E51: 100 | F51: 100 | G51: 100 | H51: 100 | I51: 100 | J51: 100 | K51: 100 | L51: 100 | M51: 100 | N51: 100 | O51: Head
D52: =TEXT(EDATE(X_Cell_Site_StartDate,7), "mmmm yyyy") -> August 2025 | E52: 100 | F52: 100 | G52: 100 | H52: 100 | I52: 100 | J52: 100 | K52: 100 | L52: 100 | M52: 100 | N52: 100 | O52: Head
D53: =TEXT(EDATE(X_Cell_Site_StartDate,8), "mmmm yyyy") -> September 2025 | E53: 100 | F53: 100 | G53: 100 | H53: 100 | I53: 100 | J53: 100 | K53: 100 | L53: 100 | M53: 100 | N53: 100 | O53: Head
D54: =TEXT(EDATE(X_Cell_Site_StartDate,9), "mmmm yyyy") -> October 2025 | E54: 100 | F54: 100 | G54: 100 | H54: 100 | I54: 100 | J54: 100 | K54: 100 | L54: 100 | M54: 100 | N54: 100 | O54: Head
D55: =TEXT(EDATE(X_Cell_Site_StartDate,10), "mmmm yyyy") -> November 2025 | E55: 100 | F55: 100 | G55: 100 | H55: 100 | I55: 100 | J55: 100 | K55: 100 | L55: 100 | M55: 100 | N55: 100 | O55: Head
D56: =TEXT(EDATE(X_Cell_Site_StartDate,11), "mmmm yyyy") -> December 2025 | E56: 100 | F56: 100 | G56: 100 | H56: 100 | I56: 100 | J56: 100 | K56: 100 | L56: 100 | M56: 100 | N56: 100 | O56: Head
D59: Liveweight
D60: Method 1 default values (do not edit) | E60: Bulls < 1 year | F60: Bulls > 1 year | G60: Cows < 1 year | H60: Cows 1-2 years | I60: Cows 2-3 years | J60: Cows > 3 years | K60: Steers < 1 year | L60: Steers 1-2 years | M60: Steers 2-3 years | N60: Steers >3 years
D61: Spring | E61: =InputFunctions_PastureBeef.LookupLiveweightFromSeason($E$7,$E$8,$D61,E$60,Table_SourceData_PastureBeef_LiveweightAllStates[State],Table_SourceData_PastureBeef_LiveweightAllStates[Region],Table_SourceData_PastureBeef_LiveweightAllStates[Season],Table_SourceData_PastureBeef_LiveweightAllStates[#Headers],Table_SourceData_PastureBeef_LiveweightAllStates[#Data],Table_AustralianStates[Common Name],Table_AustralianStates[Abbreviation]) -> 340 | F61: =InputFunctions_PastureBeef.LookupLiveweightFromSeason($E$7,$E$8,$D61,F$60,Table_SourceData_PastureBeef_LiveweightAllStates[State],Table_SourceData_PastureBeef_LiveweightAllStates[Region],Table_SourceData_PastureBeef_LiveweightAllStates[Season],Table_SourceData_PastureBeef_LiveweightAllStates[#Headers],Table_SourceData_PastureBeef_LiveweightAllStates[#Data],Table_AustralianStates[Common Name],Table_AustralianStates[Abbreviation]) -> 800 | G61: =InputFunctions_PastureBeef.LookupLiveweightFromSeason($E$7,$E$8,$D61,G$60,Table_SourceData_PastureBeef_LiveweightAllStates[State],Table_SourceData_PastureBeef_LiveweightAllStates[Region],Table_SourceData_PastureBeef_LiveweightAllStates[Season],Table_SourceData_PastureBeef_LiveweightAllStates[#Headers],Table_SourceData_PastureBeef_LiveweightAllStates[#Data],Table_AustralianStates[Common Name],Table_AustralianStates[Abbreviation]) -> 260 | H61: =InputFunctions_PastureBeef.LookupLiveweightFromSeason($E$7,$E$8,$D61,H$60,Table_SourceData_PastureBeef_LiveweightAllStates[State],Table_SourceData_PastureBeef_LiveweightAllStates[Region],Table_SourceData_PastureBeef_LiveweightAllStates[Season],Table_SourceData_PastureBeef_LiveweightAllStates[#Headers],Table_SourceData_PastureBeef_LiveweightAllStates[#Data],Table_AustralianStates[Common Name],Table_AustralianStates[Abbreviation]) -> 420 | I61: =InputFunctions_PastureBeef.LookupLiveweightFromSeason($E$7,$E$8,$D61,I$60,Table_SourceData_PastureBeef_LiveweightAllStates[State],Table_SourceData_PastureBeef_LiveweightAllStates[Region],Table_SourceData_PastureBeef_LiveweightAllStates[Season],Table_SourceData_PastureBeef_LiveweightAllStates[#Headers],Table_SourceData_PastureBeef_LiveweightAllStates[#Data],Table_AustralianStates[Common Name],Table_AustralianStates[Abbreviation]) -> 550 | J61: =InputFunctions_PastureBeef.LookupLiveweightFromSeason($E$7,$E$8,$D61,J$60,Table_SourceData_PastureBeef_LiveweightAllStates[State],Table_SourceData_PastureBeef_LiveweightAllStates[Region],Table_SourceData_PastureBeef_LiveweightAllStates[Season],Table_SourceData_PastureBeef_LiveweightAllStates[#Headers],Table_SourceData_PastureBeef_LiveweightAllStates[#Data],Table_AustralianStates[Common Name],Table_AustralianStates[Abbreviation]) -> 550 | K61: =InputFunctions_PastureBeef.LookupLiveweightFromSeason($E$7,$E$8,$D61,K$60,Table_SourceData_PastureBeef_LiveweightAllStates[State],Table_SourceData_PastureBeef_LiveweightAllStates[Region],Table_SourceData_PastureBeef_LiveweightAllStates[Season],Table_SourceData_PastureBeef_LiveweightAllStates[#Headers],Table_SourceData_PastureBeef_LiveweightAllStates[#Data],Table_AustralianStates[Common Name],Table_AustralianStates[Abbreviation]) -> 300 | L61: =InputFunctions_PastureBeef.LookupLiveweightFromSeason($E$7,$E$8,$D61,L$60,Table_SourceData_PastureBeef_LiveweightAllStates[State],Table_SourceData_PastureBeef_LiveweightAllStates[Region],Table_SourceData_PastureBeef_LiveweightAllStates[Season],Table_SourceData_PastureBeef_LiveweightAllStates[#Headers],Table_SourceData_PastureBeef_LiveweightAllStates[#Data],Table_AustralianStates[Common Name],Table_AustralianStates[Abbreviation]) -> 480 | ... N61: =InputFunctions_PastureBeef.LookupLiveweightFromSeason($E$7,$E$8,$D61,N$60,Table_SourceData_PastureBeef_LiveweightAllStates[State],Table_SourceData_PastureBeef_LiveweightAllStates[Region],Table_SourceData_PastureBeef_LiveweightAllStates[Season],Table_SourceData_PastureBeef_LiveweightAllStates[#Headers],Table_SourceData_PastureBeef_LiveweightAllStates[#Data],Table_AustralianStates[Common Name],Table_AustralianStates[Abbreviation]) -> 480 | O61: kg/head
D62: Summer | E62: =InputFunctions_PastureBeef.LookupLiveweightFromSeason($E$7,$E$8,$D62,E$60,Table_SourceData_PastureBeef_LiveweightAllStates[State],Table_SourceData_PastureBeef_LiveweightAllStates[Region],Table_SourceData_PastureBeef_LiveweightAllStates[Season],Table_SourceData_PastureBeef_LiveweightAllStates[#Headers],Table_SourceData_PastureBeef_LiveweightAllStates[#Data],Table_AustralianStates[Common Name],Table_AustralianStates[Abbreviation]) -> 380 | F62: =InputFunctions_PastureBeef.LookupLiveweightFromSeason($E$7,$E$8,$D62,F$60,Table_SourceData_PastureBeef_LiveweightAllStates[State],Table_SourceData_PastureBeef_LiveweightAllStates[Region],Table_SourceData_PastureBeef_LiveweightAllStates[Season],Table_SourceData_PastureBeef_LiveweightAllStates[#Headers],Table_SourceData_PastureBeef_LiveweightAllStates[#Data],Table_AustralianStates[Common Name],Table_AustralianStates[Abbreviation]) -> 780 | G62: =InputFunctions_PastureBeef.LookupLiveweightFromSeason($E$7,$E$8,$D62,G$60,Table_SourceData_PastureBeef_LiveweightAllStates[State],Table_SourceData_PastureBeef_LiveweightAllStates[Region],Table_SourceData_PastureBeef_LiveweightAllStates[Season],Table_SourceData_PastureBeef_LiveweightAllStates[#Headers],Table_SourceData_PastureBeef_LiveweightAllStates[#Data],Table_AustralianStates[Common Name],Table_AustralianStates[Abbreviation]) -> 300 | H62: =InputFunctions_PastureBeef.LookupLiveweightFromSeason($E$7,$E$8,$D62,H$60,Table_SourceData_PastureBeef_LiveweightAllStates[State],Table_SourceData_PastureBeef_LiveweightAllStates[Region],Table_SourceData_PastureBeef_LiveweightAllStates[Season],Table_SourceData_PastureBeef_LiveweightAllStates[#Headers],Table_SourceData_PastureBeef_LiveweightAllStates[#Data],Table_AustralianStates[Common Name],Table_AustralianStates[Abbreviation]) -> 450 | I62: =InputFunctions_PastureBeef.LookupLiveweightFromSeason($E$7,$E$8,$D62,I$60,Table_SourceData_PastureBeef_LiveweightAllStates[State],Table_SourceData_PastureBeef_LiveweightAllStates[Region],Table_SourceData_PastureBeef_LiveweightAllStates[Season],Table_SourceData_PastureBeef_LiveweightAllStates[#Headers],Table_SourceData_PastureBeef_LiveweightAllStates[#Data],Table_AustralianStates[Common Name],Table_AustralianStates[Abbreviation]) -> 530 | J62: =InputFunctions_PastureBeef.LookupLiveweightFromSeason($E$7,$E$8,$D62,J$60,Table_SourceData_PastureBeef_LiveweightAllStates[State],Table_SourceData_PastureBeef_LiveweightAllStates[Region],Table_SourceData_PastureBeef_LiveweightAllStates[Season],Table_SourceData_PastureBeef_LiveweightAllStates[#Headers],Table_SourceData_PastureBeef_LiveweightAllStates[#Data],Table_AustralianStates[Common Name],Table_AustralianStates[Abbreviation]) -> 530 | K62: =InputFunctions_PastureBeef.LookupLiveweightFromSeason($E$7,$E$8,$D62,K$60,Table_SourceData_PastureBeef_LiveweightAllStates[State],Table_SourceData_PastureBeef_LiveweightAllStates[Region],Table_SourceData_PastureBeef_LiveweightAllStates[Season],Table_SourceData_PastureBeef_LiveweightAllStates[#Headers],Table_SourceData_PastureBeef_LiveweightAllStates[#Data],Table_AustralianStates[Common Name],Table_AustralianStates[Abbreviation]) -> 340 | L62: =InputFunctions_PastureBeef.LookupLiveweightFromSeason($E$7,$E$8,$D62,L$60,Table_SourceData_PastureBeef_LiveweightAllStates[State],Table_SourceData_PastureBeef_LiveweightAllStates[Region],Table_SourceData_PastureBeef_LiveweightAllStates[Season],Table_SourceData_PastureBeef_LiveweightAllStates[#Headers],Table_SourceData_PastureBeef_LiveweightAllStates[#Data],Table_AustralianStates[Common Name],Table_AustralianStates[Abbreviation]) -> 470 | ... N62: =InputFunctions_PastureBeef.LookupLiveweightFromSeason($E$7,$E$8,$D62,N$60,Table_SourceData_PastureBeef_LiveweightAllStates[State],Table_SourceData_PastureBeef_LiveweightAllStates[Region],Table_SourceData_PastureBeef_LiveweightAllStates[Season],Table_SourceData_PastureBeef_LiveweightAllStates[#Headers],Table_SourceData_PastureBeef_LiveweightAllStates[#Data],Table_AustralianStates[Common Name],Table_AustralianStates[Abbreviation]) -> 470 | O62: kg/head
D63: Autumn | E63: =InputFunctions_PastureBeef.LookupLiveweightFromSeason($E$7,$E$8,$D63,E$60,Table_SourceData_PastureBeef_LiveweightAllStates[State],Table_SourceData_PastureBeef_LiveweightAllStates[Region],Table_SourceData_PastureBeef_LiveweightAllStates[Season],Table_SourceData_PastureBeef_LiveweightAllStates[#Headers],Table_SourceData_PastureBeef_LiveweightAllStates[#Data],Table_AustralianStates[Common Name],Table_AustralianStates[Abbreviation]) -> 100 | F63: =InputFunctions_PastureBeef.LookupLiveweightFromSeason($E$7,$E$8,$D63,F$60,Table_SourceData_PastureBeef_LiveweightAllStates[State],Table_SourceData_PastureBeef_LiveweightAllStates[Region],Table_SourceData_PastureBeef_LiveweightAllStates[Season],Table_SourceData_PastureBeef_LiveweightAllStates[#Headers],Table_SourceData_PastureBeef_LiveweightAllStates[#Data],Table_AustralianStates[Common Name],Table_AustralianStates[Abbreviation]) -> 680 | G63: =InputFunctions_PastureBeef.LookupLiveweightFromSeason($E$7,$E$8,$D63,G$60,Table_SourceData_PastureBeef_LiveweightAllStates[State],Table_SourceData_PastureBeef_LiveweightAllStates[Region],Table_SourceData_PastureBeef_LiveweightAllStates[Season],Table_SourceData_PastureBeef_LiveweightAllStates[#Headers],Table_SourceData_PastureBeef_LiveweightAllStates[#Data],Table_AustralianStates[Common Name],Table_AustralianStates[Abbreviation]) -> 80 | H63: =InputFunctions_PastureBeef.LookupLiveweightFromSeason($E$7,$E$8,$D63,H$60,Table_SourceData_PastureBeef_LiveweightAllStates[State],Table_SourceData_PastureBeef_LiveweightAllStates[Region],Table_SourceData_PastureBeef_LiveweightAllStates[Season],Table_SourceData_PastureBeef_LiveweightAllStates[#Headers],Table_SourceData_PastureBeef_LiveweightAllStates[#Data],Table_AustralianStates[Common Name],Table_AustralianStates[Abbreviation]) -> 320 | I63: =InputFunctions_PastureBeef.LookupLiveweightFromSeason($E$7,$E$8,$D63,I$60,Table_SourceData_PastureBeef_LiveweightAllStates[State],Table_SourceData_PastureBeef_LiveweightAllStates[Region],Table_SourceData_PastureBeef_LiveweightAllStates[Season],Table_SourceData_PastureBeef_LiveweightAllStates[#Headers],Table_SourceData_PastureBeef_LiveweightAllStates[#Data],Table_AustralianStates[Common Name],Table_AustralianStates[Abbreviation]) -> 480 | J63: =InputFunctions_PastureBeef.LookupLiveweightFromSeason($E$7,$E$8,$D63,J$60,Table_SourceData_PastureBeef_LiveweightAllStates[State],Table_SourceData_PastureBeef_LiveweightAllStates[Region],Table_SourceData_PastureBeef_LiveweightAllStates[Season],Table_SourceData_PastureBeef_LiveweightAllStates[#Headers],Table_SourceData_PastureBeef_LiveweightAllStates[#Data],Table_AustralianStates[Common Name],Table_AustralianStates[Abbreviation]) -> 480 | K63: =InputFunctions_PastureBeef.LookupLiveweightFromSeason($E$7,$E$8,$D63,K$60,Table_SourceData_PastureBeef_LiveweightAllStates[State],Table_SourceData_PastureBeef_LiveweightAllStates[Region],Table_SourceData_PastureBeef_LiveweightAllStates[Season],Table_SourceData_PastureBeef_LiveweightAllStates[#Headers],Table_SourceData_PastureBeef_LiveweightAllStates[#Data],Table_AustralianStates[Common Name],Table_AustralianStates[Abbreviation]) -> 100 | L63: =InputFunctions_PastureBeef.LookupLiveweightFromSeason($E$7,$E$8,$D63,L$60,Table_SourceData_PastureBeef_LiveweightAllStates[State],Table_SourceData_PastureBeef_LiveweightAllStates[Region],Table_SourceData_PastureBeef_LiveweightAllStates[Season],Table_SourceData_PastureBeef_LiveweightAllStates[#Headers],Table_SourceData_PastureBeef_LiveweightAllStates[#Data],Table_AustralianStates[Common Name],Table_AustralianStates[Abbreviation]) -> 340 | ... N63: =InputFunctions_PastureBeef.LookupLiveweightFromSeason($E$7,$E$8,$D63,N$60,Table_SourceData_PastureBeef_LiveweightAllStates[State],Table_SourceData_PastureBeef_LiveweightAllStates[Region],Table_SourceData_PastureBeef_LiveweightAllStates[Season],Table_SourceData_PastureBeef_LiveweightAllStates[#Headers],Table_SourceData_PastureBeef_LiveweightAllStates[#Data],Table_AustralianStates[Common Name],Table_AustralianStates[Abbreviation]) -> 340 | O63: kg/head
D64: Winter | E64: =InputFunctions_PastureBeef.LookupLiveweightFromSeason($E$7,$E$8,$D64,E$60,Table_SourceData_PastureBeef_LiveweightAllStates[State],Table_SourceData_PastureBeef_LiveweightAllStates[Region],Table_SourceData_PastureBeef_LiveweightAllStates[Season],Table_SourceData_PastureBeef_LiveweightAllStates[#Headers],Table_SourceData_PastureBeef_LiveweightAllStates[#Data],Table_AustralianStates[Common Name],Table_AustralianStates[Abbreviation]) -> 190 | F64: =InputFunctions_PastureBeef.LookupLiveweightFromSeason($E$7,$E$8,$D64,F$60,Table_SourceData_PastureBeef_LiveweightAllStates[State],Table_SourceData_PastureBeef_LiveweightAllStates[Region],Table_SourceData_PastureBeef_LiveweightAllStates[Season],Table_SourceData_PastureBeef_LiveweightAllStates[#Headers],Table_SourceData_PastureBeef_LiveweightAllStates[#Data],Table_AustralianStates[Common Name],Table_AustralianStates[Abbreviation]) -> 700 | G64: =InputFunctions_PastureBeef.LookupLiveweightFromSeason($E$7,$E$8,$D64,G$60,Table_SourceData_PastureBeef_LiveweightAllStates[State],Table_SourceData_PastureBeef_LiveweightAllStates[Region],Table_SourceData_PastureBeef_LiveweightAllStates[Season],Table_SourceData_PastureBeef_LiveweightAllStates[#Headers],Table_SourceData_PastureBeef_LiveweightAllStates[#Data],Table_AustralianStates[Common Name],Table_AustralianStates[Abbreviation]) -> 150 | H64: =InputFunctions_PastureBeef.LookupLiveweightFromSeason($E$7,$E$8,$D64,H$60,Table_SourceData_PastureBeef_LiveweightAllStates[State],Table_SourceData_PastureBeef_LiveweightAllStates[Region],Table_SourceData_PastureBeef_LiveweightAllStates[Season],Table_SourceData_PastureBeef_LiveweightAllStates[#Headers],Table_SourceData_PastureBeef_LiveweightAllStates[#Data],Table_AustralianStates[Common Name],Table_AustralianStates[Abbreviation]) -> 330 | I64: =InputFunctions_PastureBeef.LookupLiveweightFromSeason($E$7,$E$8,$D64,I$60,Table_SourceData_PastureBeef_LiveweightAllStates[State],Table_SourceData_PastureBeef_LiveweightAllStates[Region],Table_SourceData_PastureBeef_LiveweightAllStates[Season],Table_SourceData_PastureBeef_LiveweightAllStates[#Headers],Table_SourceData_PastureBeef_LiveweightAllStates[#Data],Table_AustralianStates[Common Name],Table_AustralianStates[Abbreviation]) -> 490 | J64: =InputFunctions_PastureBeef.LookupLiveweightFromSeason($E$7,$E$8,$D64,J$60,Table_SourceData_PastureBeef_LiveweightAllStates[State],Table_SourceData_PastureBeef_LiveweightAllStates[Region],Table_SourceData_PastureBeef_LiveweightAllStates[Season],Table_SourceData_PastureBeef_LiveweightAllStates[#Headers],Table_SourceData_PastureBeef_LiveweightAllStates[#Data],Table_AustralianStates[Common Name],Table_AustralianStates[Abbreviation]) -> 490 | K64: =InputFunctions_PastureBeef.LookupLiveweightFromSeason($E$7,$E$8,$D64,K$60,Table_SourceData_PastureBeef_LiveweightAllStates[State],Table_SourceData_PastureBeef_LiveweightAllStates[Region],Table_SourceData_PastureBeef_LiveweightAllStates[Season],Table_SourceData_PastureBeef_LiveweightAllStates[#Headers],Table_SourceData_PastureBeef_LiveweightAllStates[#Data],Table_AustralianStates[Common Name],Table_AustralianStates[Abbreviation]) -> 170 | L64: =InputFunctions_PastureBeef.LookupLiveweightFromSeason($E$7,$E$8,$D64,L$60,Table_SourceData_PastureBeef_LiveweightAllStates[State],Table_SourceData_PastureBeef_LiveweightAllStates[Region],Table_SourceData_PastureBeef_LiveweightAllStates[Season],Table_SourceData_PastureBeef_LiveweightAllStates[#Headers],Table_SourceData_PastureBeef_LiveweightAllStates[#Data],Table_AustralianStates[Common Name],Table_AustralianStates[Abbreviation]) -> 360 | ... N64: =InputFunctions_PastureBeef.LookupLiveweightFromSeason($E$7,$E$8,$D64,N$60,Table_SourceData_PastureBeef_LiveweightAllStates[State],Table_SourceData_PastureBeef_LiveweightAllStates[Region],Table_SourceData_PastureBeef_LiveweightAllStates[Season],Table_SourceData_PastureBeef_LiveweightAllStates[#Headers],Table_SourceData_PastureBeef_LiveweightAllStates[#Data],Table_AustralianStates[Common Name],Table_AustralianStates[Abbreviation]) -> 360 | O64: kg/head
D66: Method 2 custom values (edit if known) | E66: Bulls < 1 year | F66: Bulls > 1 year | G66: Cows < 1 year | H66: Cows 1-2 years | I66: Cows 2-3 years | J66: Cows > 3 years | K66: Steers < 1 year | L66: Steers 1-2 years | M66: Steers 2-3 years | N66: Steers >3 years
D67: =TEXT(X_Cell_Site_StartDate, "mmmm yyyy") -> January 2025 | E67: =InputFunctions_PastureBeef.LookupLiveweightFromMonth($E$7,$E$8,$D67,E$66,Table_SourceData_PastureBeef_LiveweightAllStates[State],Table_SourceData_PastureBeef_LiveweightAllStates[Region],Table_SourceData_PastureBeef_LiveweightAllStates[Season],Table_SourceData_PastureBeef_LiveweightAllStates[#Headers],Table_SourceData_PastureBeef_LiveweightAllStates[#Data],Table_AustralianStates[Common Name],Table_AustralianStates[Abbreviation],Table_SourceData_Common_MonthToSeason[Month],Table_SourceData_Common_MonthToSeason[Season]) -> 380 | F67: =InputFunctions_PastureBeef.LookupLiveweightFromMonth($E$7,$E$8,$D67,F$66,Table_SourceData_PastureBeef_LiveweightAllStates[State],Table_SourceData_PastureBeef_LiveweightAllStates[Region],Table_SourceData_PastureBeef_LiveweightAllStates[Season],Table_SourceData_PastureBeef_LiveweightAllStates[#Headers],Table_SourceData_PastureBeef_LiveweightAllStates[#Data],Table_AustralianStates[Common Name],Table_AustralianStates[Abbreviation],Table_SourceData_Common_MonthToSeason[Month],Table_SourceData_Common_MonthToSeason[Season]) -> 780 | G67: =InputFunctions_PastureBeef.LookupLiveweightFromMonth($E$7,$E$8,$D67,G$66,Table_SourceData_PastureBeef_LiveweightAllStates[State],Table_SourceData_PastureBeef_LiveweightAllStates[Region],Table_SourceData_PastureBeef_LiveweightAllStates[Season],Table_SourceData_PastureBeef_LiveweightAllStates[#Headers],Table_SourceData_PastureBeef_LiveweightAllStates[#Data],Table_AustralianStates[Common Name],Table_AustralianStates[Abbreviation],Table_SourceData_Common_MonthToSeason[Month],Table_SourceData_Common_MonthToSeason[Season]) -> 300 | H67: =InputFunctions_PastureBeef.LookupLiveweightFromMonth($E$7,$E$8,$D67,H$66,Table_SourceData_PastureBeef_LiveweightAllStates[State],Table_SourceData_PastureBeef_LiveweightAllStates[Region],Table_SourceData_PastureBeef_LiveweightAllStates[Season],Table_SourceData_PastureBeef_LiveweightAllStates[#Headers],Table_SourceData_PastureBeef_LiveweightAllStates[#Data],Table_AustralianStates[Common Name],Table_AustralianStates[Abbreviation],Table_SourceData_Common_MonthToSeason[Month],Table_SourceData_Common_MonthToSeason[Season]) -> 450 | I67: =InputFunctions_PastureBeef.LookupLiveweightFromMonth($E$7,$E$8,$D67,I$66,Table_SourceData_PastureBeef_LiveweightAllStates[State],Table_SourceData_PastureBeef_LiveweightAllStates[Region],Table_SourceData_PastureBeef_LiveweightAllStates[Season],Table_SourceData_PastureBeef_LiveweightAllStates[#Headers],Table_SourceData_PastureBeef_LiveweightAllStates[#Data],Table_AustralianStates[Common Name],Table_AustralianStates[Abbreviation],Table_SourceData_Common_MonthToSeason[Month],Table_SourceData_Common_MonthToSeason[Season]) -> 530 | J67: =InputFunctions_PastureBeef.LookupLiveweightFromMonth($E$7,$E$8,$D67,J$66,Table_SourceData_PastureBeef_LiveweightAllStates[State],Table_SourceData_PastureBeef_LiveweightAllStates[Region],Table_SourceData_PastureBeef_LiveweightAllStates[Season],Table_SourceData_PastureBeef_LiveweightAllStates[#Headers],Table_SourceData_PastureBeef_LiveweightAllStates[#Data],Table_AustralianStates[Common Name],Table_AustralianStates[Abbreviation],Table_SourceData_Common_MonthToSeason[Month],Table_SourceData_Common_MonthToSeason[Season]) -> 530 | K67: =InputFunctions_PastureBeef.LookupLiveweightFromMonth($E$7,$E$8,$D67,K$66,Table_SourceData_PastureBeef_LiveweightAllStates[State],Table_SourceData_PastureBeef_LiveweightAllStates[Region],Table_SourceData_PastureBeef_LiveweightAllStates[Season],Table_SourceData_PastureBeef_LiveweightAllStates[#Headers],Table_SourceData_PastureBeef_LiveweightAllStates[#Data],Table_AustralianStates[Common Name],Table_AustralianStates[Abbreviation],Table_SourceData_Common_MonthToSeason[Month],Table_SourceData_Common_MonthToSeason[Season]) -> 340 | L67: =InputFunctions_PastureBeef.LookupLiveweightFromMonth($E$7,$E$8,$D67,L$66,Table_SourceData_PastureBeef_LiveweightAllStates[State],Table_SourceData_PastureBeef_LiveweightAllStates[Region],Table_SourceData_PastureBeef_LiveweightAllStates[Season],Table_SourceData_PastureBeef_LiveweightAllStates[#Headers],Table_SourceData_PastureBeef_LiveweightAllStates[#Data],Table_AustralianStates[Common Name],Table_AustralianStates[Abbreviation],Table_SourceData_Common_MonthToSeason[Month],Table_SourceData_Common_MonthToSeason[Season]) -> 470 | ... N67: =InputFunctions_PastureBeef.LookupLiveweightFromMonth($E$7,$E$8,$D67,N$66,Table_SourceData_PastureBeef_LiveweightAllStates[State],Table_SourceData_PastureBeef_LiveweightAllStates[Region],Table_SourceData_PastureBeef_LiveweightAllStates[Season],Table_SourceData_PastureBeef_LiveweightAllStates[#Headers],Table_SourceData_PastureBeef_LiveweightAllStates[#Data],Table_AustralianStates[Common Name],Table_AustralianStates[Abbreviation],Table_SourceData_Common_MonthToSeason[Month],Table_SourceData_Common_MonthToSeason[Season]) -> 470 | O67: kg/head
D68: =TEXT(EDATE(X_Cell_Site_StartDate,1), "mmmm yyyy") -> February 2025 | E68: =InputFunctions_PastureBeef.LookupLiveweightFromMonth($E$7,$E$8,$D68,E$66,Table_SourceData_PastureBeef_LiveweightAllStates[State],Table_SourceData_PastureBeef_LiveweightAllStates[Region],Table_SourceData_PastureBeef_LiveweightAllStates[Season],Table_SourceData_PastureBeef_LiveweightAllStates[#Headers],Table_SourceData_PastureBeef_LiveweightAllStates[#Data],Table_AustralianStates[Common Name],Table_AustralianStates[Abbreviation],Table_SourceData_Common_MonthToSeason[Month],Table_SourceData_Common_MonthToSeason[Season]) -> 380 | F68: =InputFunctions_PastureBeef.LookupLiveweightFromMonth($E$7,$E$8,$D68,F$66,Table_SourceData_PastureBeef_LiveweightAllStates[State],Table_SourceData_PastureBeef_LiveweightAllStates[Region],Table_SourceData_PastureBeef_LiveweightAllStates[Season],Table_SourceData_PastureBeef_LiveweightAllStates[#Headers],Table_SourceData_PastureBeef_LiveweightAllStates[#Data],Table_AustralianStates[Common Name],Table_AustralianStates[Abbreviation],Table_SourceData_Common_MonthToSeason[Month],Table_SourceData_Common_MonthToSeason[Season]) -> 780 | G68: =InputFunctions_PastureBeef.LookupLiveweightFromMonth($E$7,$E$8,$D68,G$66,Table_SourceData_PastureBeef_LiveweightAllStates[State],Table_SourceData_PastureBeef_LiveweightAllStates[Region],Table_SourceData_PastureBeef_LiveweightAllStates[Season],Table_SourceData_PastureBeef_LiveweightAllStates[#Headers],Table_SourceData_PastureBeef_LiveweightAllStates[#Data],Table_AustralianStates[Common Name],Table_AustralianStates[Abbreviation],Table_SourceData_Common_MonthToSeason[Month],Table_SourceData_Common_MonthToSeason[Season]) -> 300 | H68: =InputFunctions_PastureBeef.LookupLiveweightFromMonth($E$7,$E$8,$D68,H$66,Table_SourceData_PastureBeef_LiveweightAllStates[State],Table_SourceData_PastureBeef_LiveweightAllStates[Region],Table_SourceData_PastureBeef_LiveweightAllStates[Season],Table_SourceData_PastureBeef_LiveweightAllStates[#Headers],Table_SourceData_PastureBeef_LiveweightAllStates[#Data],Table_AustralianStates[Common Name],Table_AustralianStates[Abbreviation],Table_SourceData_Common_MonthToSeason[Month],Table_SourceData_Common_MonthToSeason[Season]) -> 450 | I68: =InputFunctions_PastureBeef.LookupLiveweightFromMonth($E$7,$E$8,$D68,I$66,Table_SourceData_PastureBeef_LiveweightAllStates[State],Table_SourceData_PastureBeef_LiveweightAllStates[Region],Table_SourceData_PastureBeef_LiveweightAllStates[Season],Table_SourceData_PastureBeef_LiveweightAllStates[#Headers],Table_SourceData_PastureBeef_LiveweightAllStates[#Data],Table_AustralianStates[Common Name],Table_AustralianStates[Abbreviation],Table_SourceData_Common_MonthToSeason[Month],Table_SourceData_Common_MonthToSeason[Season]) -> 530 | J68: =InputFunctions_PastureBeef.LookupLiveweightFromMonth($E$7,$E$8,$D68,J$66,Table_SourceData_PastureBeef_LiveweightAllStates[State],Table_SourceData_PastureBeef_LiveweightAllStates[Region],Table_SourceData_PastureBeef_LiveweightAllStates[Season],Table_SourceData_PastureBeef_LiveweightAllStates[#Headers],Table_SourceData_PastureBeef_LiveweightAllStates[#Data],Table_AustralianStates[Common Name],Table_AustralianStates[Abbreviation],Table_SourceData_Common_MonthToSeason[Month],Table_SourceData_Common_MonthToSeason[Season]) -> 530 | K68: =InputFunctions_PastureBeef.LookupLiveweightFromMonth($E$7,$E$8,$D68,K$66,Table_SourceData_PastureBeef_LiveweightAllStates[State],Table_SourceData_PastureBeef_LiveweightAllStates[Region],Table_SourceData_PastureBeef_LiveweightAllStates[Season],Table_SourceData_PastureBeef_LiveweightAllStates[#Headers],Table_SourceData_PastureBeef_LiveweightAllStates[#Data],Table_AustralianStates[Common Name],Table_AustralianStates[Abbreviation],Table_SourceData_Common_MonthToSeason[Month],Table_SourceData_Common_MonthToSeason[Season]) -> 340 | L68: =InputFunctions_PastureBeef.LookupLiveweightFromMonth($E$7,$E$8,$D68,L$66,Table_SourceData_PastureBeef_LiveweightAllStates[State],Table_SourceData_PastureBeef_LiveweightAllStates[Region],Table_SourceData_PastureBeef_LiveweightAllStates[Season],Table_SourceData_PastureBeef_LiveweightAllStates[#Headers],Table_SourceData_PastureBeef_LiveweightAllStates[#Data],Table_AustralianStates[Common Name],Table_AustralianStates[Abbreviation],Table_SourceData_Common_MonthToSeason[Month],Table_SourceData_Common_MonthToSeason[Season]) -> 470 | ... N68: =InputFunctions_PastureBeef.LookupLiveweightFromMonth($E$7,$E$8,$D68,N$66,Table_SourceData_PastureBeef_LiveweightAllStates[State],Table_SourceData_PastureBeef_LiveweightAllStates[Region],Table_SourceData_PastureBeef_LiveweightAllStates[Season],Table_SourceData_PastureBeef_LiveweightAllStates[#Headers],Table_SourceData_PastureBeef_LiveweightAllStates[#Data],Table_AustralianStates[Common Name],Table_AustralianStates[Abbreviation],Table_SourceData_Common_MonthToSeason[Month],Table_SourceData_Common_MonthToSeason[Season]) -> 470 | O68: kg/head
D69: =TEXT(EDATE(X_Cell_Site_StartDate,2), "mmmm yyyy") -> March 2025 | E69: =InputFunctions_PastureBeef.LookupLiveweightFromMonth($E$7,$E$8,$D69,E$66,Table_SourceData_PastureBeef_LiveweightAllStates[State],Table_SourceData_PastureBeef_LiveweightAllStates[Region],Table_SourceData_PastureBeef_LiveweightAllStates[Season],Table_SourceData_PastureBeef_LiveweightAllStates[#Headers],Table_SourceData_PastureBeef_LiveweightAllStates[#Data],Table_AustralianStates[Common Name],Table_AustralianStates[Abbreviation],Table_SourceData_Common_MonthToSeason[Month],Table_SourceData_Common_MonthToSeason[Season]) -> 100 | F69: =InputFunctions_PastureBeef.LookupLiveweightFromMonth($E$7,$E$8,$D69,F$66,Table_SourceData_PastureBeef_LiveweightAllStates[State],Table_SourceData_PastureBeef_LiveweightAllStates[Region],Table_SourceData_PastureBeef_LiveweightAllStates[Season],Table_SourceData_PastureBeef_LiveweightAllStates[#Headers],Table_SourceData_PastureBeef_LiveweightAllStates[#Data],Table_AustralianStates[Common Name],Table_AustralianStates[Abbreviation],Table_SourceData_Common_MonthToSeason[Month],Table_SourceData_Common_MonthToSeason[Season]) -> 680 | G69: =InputFunctions_PastureBeef.LookupLiveweightFromMonth($E$7,$E$8,$D69,G$66,Table_SourceData_PastureBeef_LiveweightAllStates[State],Table_SourceData_PastureBeef_LiveweightAllStates[Region],Table_SourceData_PastureBeef_LiveweightAllStates[Season],Table_SourceData_PastureBeef_LiveweightAllStates[#Headers],Table_SourceData_PastureBeef_LiveweightAllStates[#Data],Table_AustralianStates[Common Name],Table_AustralianStates[Abbreviation],Table_SourceData_Common_MonthToSeason[Month],Table_SourceData_Common_MonthToSeason[Season]) -> 80 | H69: =InputFunctions_PastureBeef.LookupLiveweightFromMonth($E$7,$E$8,$D69,H$66,Table_SourceData_PastureBeef_LiveweightAllStates[State],Table_SourceData_PastureBeef_LiveweightAllStates[Region],Table_SourceData_PastureBeef_LiveweightAllStates[Season],Table_SourceData_PastureBeef_LiveweightAllStates[#Headers],Table_SourceData_PastureBeef_LiveweightAllStates[#Data],Table_AustralianStates[Common Name],Table_AustralianStates[Abbreviation],Table_SourceData_Common_MonthToSeason[Month],Table_SourceData_Common_MonthToSeason[Season]) -> 320 | I69: =InputFunctions_PastureBeef.LookupLiveweightFromMonth($E$7,$E$8,$D69,I$66,Table_SourceData_PastureBeef_LiveweightAllStates[State],Table_SourceData_PastureBeef_LiveweightAllStates[Region],Table_SourceData_PastureBeef_LiveweightAllStates[Season],Table_SourceData_PastureBeef_LiveweightAllStates[#Headers],Table_SourceData_PastureBeef_LiveweightAllStates[#Data],Table_AustralianStates[Common Name],Table_AustralianStates[Abbreviation],Table_SourceData_Common_MonthToSeason[Month],Table_SourceData_Common_MonthToSeason[Season]) -> 480 | J69: =InputFunctions_PastureBeef.LookupLiveweightFromMonth($E$7,$E$8,$D69,J$66,Table_SourceData_PastureBeef_LiveweightAllStates[State],Table_SourceData_PastureBeef_LiveweightAllStates[Region],Table_SourceData_PastureBeef_LiveweightAllStates[Season],Table_SourceData_PastureBeef_LiveweightAllStates[#Headers],Table_SourceData_PastureBeef_LiveweightAllStates[#Data],Table_AustralianStates[Common Name],Table_AustralianStates[Abbreviation],Table_SourceData_Common_MonthToSeason[Month],Table_SourceData_Common_MonthToSeason[Season]) -> 480 | K69: =InputFunctions_PastureBeef.LookupLiveweightFromMonth($E$7,$E$8,$D69,K$66,Table_SourceData_PastureBeef_LiveweightAllStates[State],Table_SourceData_PastureBeef_LiveweightAllStates[Region],Table_SourceData_PastureBeef_LiveweightAllStates[Season],Table_SourceData_PastureBeef_LiveweightAllStates[#Headers],Table_SourceData_PastureBeef_LiveweightAllStates[#Data],Table_AustralianStates[Common Name],Table_AustralianStates[Abbreviation],Table_SourceData_Common_MonthToSeason[Month],Table_SourceData_Common_MonthToSeason[Season]) -> 100 | L69: =InputFunctions_PastureBeef.LookupLiveweightFromMonth($E$7,$E$8,$D69,L$66,Table_SourceData_PastureBeef_LiveweightAllStates[State],Table_SourceData_PastureBeef_LiveweightAllStates[Region],Table_SourceData_PastureBeef_LiveweightAllStates[Season],Table_SourceData_PastureBeef_LiveweightAllStates[#Headers],Table_SourceData_PastureBeef_LiveweightAllStates[#Data],Table_AustralianStates[Common Name],Table_AustralianStates[Abbreviation],Table_SourceData_Common_MonthToSeason[Month],Table_SourceData_Common_MonthToSeason[Season]) -> 340 | ... N69: =InputFunctions_PastureBeef.LookupLiveweightFromMonth($E$7,$E$8,$D69,N$66,Table_SourceData_PastureBeef_LiveweightAllStates[State],Table_SourceData_PastureBeef_LiveweightAllStates[Region],Table_SourceData_PastureBeef_LiveweightAllStates[Season],Table_SourceData_PastureBeef_LiveweightAllStates[#Headers],Table_SourceData_PastureBeef_LiveweightAllStates[#Data],Table_AustralianStates[Common Name],Table_AustralianStates[Abbreviation],Table_SourceData_Common_MonthToSeason[Month],Table_SourceData_Common_MonthToSeason[Season]) -> 340 | O69: kg/head
D70: =TEXT(EDATE(X_Cell_Site_StartDate,3), "mmmm yyyy") -> April 2025 | E70: =InputFunctions_PastureBeef.LookupLiveweightFromMonth($E$7,$E$8,$D70,E$66,Table_SourceData_PastureBeef_LiveweightAllStates[State],Table_SourceData_PastureBeef_LiveweightAllStates[Region],Table_SourceData_PastureBeef_LiveweightAllStates[Season],Table_SourceData_PastureBeef_LiveweightAllStates[#Headers],Table_SourceData_PastureBeef_LiveweightAllStates[#Data],Table_AustralianStates[Common Name],Table_AustralianStates[Abbreviation],Table_SourceData_Common_MonthToSeason[Month],Table_SourceData_Common_MonthToSeason[Season]) -> 100 | F70: =InputFunctions_PastureBeef.LookupLiveweightFromMonth($E$7,$E$8,$D70,F$66,Table_SourceData_PastureBeef_LiveweightAllStates[State],Table_SourceData_PastureBeef_LiveweightAllStates[Region],Table_SourceData_PastureBeef_LiveweightAllStates[Season],Table_SourceData_PastureBeef_LiveweightAllStates[#Headers],Table_SourceData_PastureBeef_LiveweightAllStates[#Data],Table_AustralianStates[Common Name],Table_AustralianStates[Abbreviation],Table_SourceData_Common_MonthToSeason[Month],Table_SourceData_Common_MonthToSeason[Season]) -> 680 | G70: =InputFunctions_PastureBeef.LookupLiveweightFromMonth($E$7,$E$8,$D70,G$66,Table_SourceData_PastureBeef_LiveweightAllStates[State],Table_SourceData_PastureBeef_LiveweightAllStates[Region],Table_SourceData_PastureBeef_LiveweightAllStates[Season],Table_SourceData_PastureBeef_LiveweightAllStates[#Headers],Table_SourceData_PastureBeef_LiveweightAllStates[#Data],Table_AustralianStates[Common Name],Table_AustralianStates[Abbreviation],Table_SourceData_Common_MonthToSeason[Month],Table_SourceData_Common_MonthToSeason[Season]) -> 80 | H70: =InputFunctions_PastureBeef.LookupLiveweightFromMonth($E$7,$E$8,$D70,H$66,Table_SourceData_PastureBeef_LiveweightAllStates[State],Table_SourceData_PastureBeef_LiveweightAllStates[Region],Table_SourceData_PastureBeef_LiveweightAllStates[Season],Table_SourceData_PastureBeef_LiveweightAllStates[#Headers],Table_SourceData_PastureBeef_LiveweightAllStates[#Data],Table_AustralianStates[Common Name],Table_AustralianStates[Abbreviation],Table_SourceData_Common_MonthToSeason[Month],Table_SourceData_Common_MonthToSeason[Season]) -> 320 | I70: =InputFunctions_PastureBeef.LookupLiveweightFromMonth($E$7,$E$8,$D70,I$66,Table_SourceData_PastureBeef_LiveweightAllStates[State],Table_SourceData_PastureBeef_LiveweightAllStates[Region],Table_SourceData_PastureBeef_LiveweightAllStates[Season],Table_SourceData_PastureBeef_LiveweightAllStates[#Headers],Table_SourceData_PastureBeef_LiveweightAllStates[#Data],Table_AustralianStates[Common Name],Table_AustralianStates[Abbreviation],Table_SourceData_Common_MonthToSeason[Month],Table_SourceData_Common_MonthToSeason[Season]) -> 480 | J70: =InputFunctions_PastureBeef.LookupLiveweightFromMonth($E$7,$E$8,$D70,J$66,Table_SourceData_PastureBeef_LiveweightAllStates[State],Table_SourceData_PastureBeef_LiveweightAllStates[Region],Table_SourceData_PastureBeef_LiveweightAllStates[Season],Table_SourceData_PastureBeef_LiveweightAllStates[#Headers],Table_SourceData_PastureBeef_LiveweightAllStates[#Data],Table_AustralianStates[Common Name],Table_AustralianStates[Abbreviation],Table_SourceData_Common_MonthToSeason[Month],Table_SourceData_Common_MonthToSeason[Season]) -> 480 | K70: =InputFunctions_PastureBeef.LookupLiveweightFromMonth($E$7,$E$8,$D70,K$66,Table_SourceData_PastureBeef_LiveweightAllStates[State],Table_SourceData_PastureBeef_LiveweightAllStates[Region],Table_SourceData_PastureBeef_LiveweightAllStates[Season],Table_SourceData_PastureBeef_LiveweightAllStates[#Headers],Table_SourceData_PastureBeef_LiveweightAllStates[#Data],Table_AustralianStates[Common Name],Table_AustralianStates[Abbreviation],Table_SourceData_Common_MonthToSeason[Month],Table_SourceData_Common_MonthToSeason[Season]) -> 100 | L70: =InputFunctions_PastureBeef.LookupLiveweightFromMonth($E$7,$E$8,$D70,L$66,Table_SourceData_PastureBeef_LiveweightAllStates[State],Table_SourceData_PastureBeef_LiveweightAllStates[Region],Table_SourceData_PastureBeef_LiveweightAllStates[Season],Table_SourceData_PastureBeef_LiveweightAllStates[#Headers],Table_SourceData_PastureBeef_LiveweightAllStates[#Data],Table_AustralianStates[Common Name],Table_AustralianStates[Abbreviation],Table_SourceData_Common_MonthToSeason[Month],Table_SourceData_Common_MonthToSeason[Season]) -> 340 | ... N70: =InputFunctions_PastureBeef.LookupLiveweightFromMonth($E$7,$E$8,$D70,N$66,Table_SourceData_PastureBeef_LiveweightAllStates[State],Table_SourceData_PastureBeef_LiveweightAllStates[Region],Table_SourceData_PastureBeef_LiveweightAllStates[Season],Table_SourceData_PastureBeef_LiveweightAllStates[#Headers],Table_SourceData_PastureBeef_LiveweightAllStates[#Data],Table_AustralianStates[Common Name],Table_AustralianStates[Abbreviation],Table_SourceData_Common_MonthToSeason[Month],Table_SourceData_Common_MonthToSeason[Season]) -> 340 | O70: kg/head
D71: =TEXT(EDATE(X_Cell_Site_StartDate,4), "mmmm yyyy") -> May 2025 | E71: =InputFunctions_PastureBeef.LookupLiveweightFromMonth($E$7,$E$8,$D71,E$66,Table_SourceData_PastureBeef_LiveweightAllStates[State],Table_SourceData_PastureBeef_LiveweightAllStates[Region],Table_SourceData_PastureBeef_LiveweightAllStates[Season],Table_SourceData_PastureBeef_LiveweightAllStates[#Headers],Table_SourceData_PastureBeef_LiveweightAllStates[#Data],Table_AustralianStates[Common Name],Table_AustralianStates[Abbreviation],Table_SourceData_Common_MonthToSeason[Month],Table_SourceData_Common_MonthToSeason[Season]) -> 100 | F71: =InputFunctions_PastureBeef.LookupLiveweightFromMonth($E$7,$E$8,$D71,F$66,Table_SourceData_PastureBeef_LiveweightAllStates[State],Table_SourceData_PastureBeef_LiveweightAllStates[Region],Table_SourceData_PastureBeef_LiveweightAllStates[Season],Table_SourceData_PastureBeef_LiveweightAllStates[#Headers],Table_SourceData_PastureBeef_LiveweightAllStates[#Data],Table_AustralianStates[Common Name],Table_AustralianStates[Abbreviation],Table_SourceData_Common_MonthToSeason[Month],Table_SourceData_Common_MonthToSeason[Season]) -> 680 | G71: =InputFunctions_PastureBeef.LookupLiveweightFromMonth($E$7,$E$8,$D71,G$66,Table_SourceData_PastureBeef_LiveweightAllStates[State],Table_SourceData_PastureBeef_LiveweightAllStates[Region],Table_SourceData_PastureBeef_LiveweightAllStates[Season],Table_SourceData_PastureBeef_LiveweightAllStates[#Headers],Table_SourceData_PastureBeef_LiveweightAllStates[#Data],Table_AustralianStates[Common Name],Table_AustralianStates[Abbreviation],Table_SourceData_Common_MonthToSeason[Month],Table_SourceData_Common_MonthToSeason[Season]) -> 80 | H71: =InputFunctions_PastureBeef.LookupLiveweightFromMonth($E$7,$E$8,$D71,H$66,Table_SourceData_PastureBeef_LiveweightAllStates[State],Table_SourceData_PastureBeef_LiveweightAllStates[Region],Table_SourceData_PastureBeef_LiveweightAllStates[Season],Table_SourceData_PastureBeef_LiveweightAllStates[#Headers],Table_SourceData_PastureBeef_LiveweightAllStates[#Data],Table_AustralianStates[Common Name],Table_AustralianStates[Abbreviation],Table_SourceData_Common_MonthToSeason[Month],Table_SourceData_Common_MonthToSeason[Season]) -> 320 | I71: =InputFunctions_PastureBeef.LookupLiveweightFromMonth($E$7,$E$8,$D71,I$66,Table_SourceData_PastureBeef_LiveweightAllStates[State],Table_SourceData_PastureBeef_LiveweightAllStates[Region],Table_SourceData_PastureBeef_LiveweightAllStates[Season],Table_SourceData_PastureBeef_LiveweightAllStates[#Headers],Table_SourceData_PastureBeef_LiveweightAllStates[#Data],Table_AustralianStates[Common Name],Table_AustralianStates[Abbreviation],Table_SourceData_Common_MonthToSeason[Month],Table_SourceData_Common_MonthToSeason[Season]) -> 480 | J71: =InputFunctions_PastureBeef.LookupLiveweightFromMonth($E$7,$E$8,$D71,J$66,Table_SourceData_PastureBeef_LiveweightAllStates[State],Table_SourceData_PastureBeef_LiveweightAllStates[Region],Table_SourceData_PastureBeef_LiveweightAllStates[Season],Table_SourceData_PastureBeef_LiveweightAllStates[#Headers],Table_SourceData_PastureBeef_LiveweightAllStates[#Data],Table_AustralianStates[Common Name],Table_AustralianStates[Abbreviation],Table_SourceData_Common_MonthToSeason[Month],Table_SourceData_Common_MonthToSeason[Season]) -> 480 | K71: =InputFunctions_PastureBeef.LookupLiveweightFromMonth($E$7,$E$8,$D71,K$66,Table_SourceData_PastureBeef_LiveweightAllStates[State],Table_SourceData_PastureBeef_LiveweightAllStates[Region],Table_SourceData_PastureBeef_LiveweightAllStates[Season],Table_SourceData_PastureBeef_LiveweightAllStates[#Headers],Table_SourceData_PastureBeef_LiveweightAllStates[#Data],Table_AustralianStates[Common Name],Table_AustralianStates[Abbreviation],Table_SourceData_Common_MonthToSeason[Month],Table_SourceData_Common_MonthToSeason[Season]) -> 100 | L71: =InputFunctions_PastureBeef.LookupLiveweightFromMonth($E$7,$E$8,$D71,L$66,Table_SourceData_PastureBeef_LiveweightAllStates[State],Table_SourceData_PastureBeef_LiveweightAllStates[Region],Table_SourceData_PastureBeef_LiveweightAllStates[Season],Table_SourceData_PastureBeef_LiveweightAllStates[#Headers],Table_SourceData_PastureBeef_LiveweightAllStates[#Data],Table_AustralianStates[Common Name],Table_AustralianStates[Abbreviation],Table_SourceData_Common_MonthToSeason[Month],Table_SourceData_Common_MonthToSeason[Season]) -> 340 | ... N71: =InputFunctions_PastureBeef.LookupLiveweightFromMonth($E$7,$E$8,$D71,N$66,Table_SourceData_PastureBeef_LiveweightAllStates[State],Table_SourceData_PastureBeef_LiveweightAllStates[Region],Table_SourceData_PastureBeef_LiveweightAllStates[Season],Table_SourceData_PastureBeef_LiveweightAllStates[#Headers],Table_SourceData_PastureBeef_LiveweightAllStates[#Data],Table_AustralianStates[Common Name],Table_AustralianStates[Abbreviation],Table_SourceData_Common_MonthToSeason[Month],Table_SourceData_Common_MonthToSeason[Season]) -> 340 | O71: kg/head
D72: =TEXT(EDATE(X_Cell_Site_StartDate,5), "mmmm yyyy") -> June 2025 | E72: =InputFunctions_PastureBeef.LookupLiveweightFromMonth($E$7,$E$8,$D72,E$66,Table_SourceData_PastureBeef_LiveweightAllStates[State],Table_SourceData_PastureBeef_LiveweightAllStates[Region],Table_SourceData_PastureBeef_LiveweightAllStates[Season],Table_SourceData_PastureBeef_LiveweightAllStates[#Headers],Table_SourceData_PastureBeef_LiveweightAllStates[#Data],Table_AustralianStates[Common Name],Table_AustralianStates[Abbreviation],Table_SourceData_Common_MonthToSeason[Month],Table_SourceData_Common_MonthToSeason[Season]) -> 190 | F72: =InputFunctions_PastureBeef.LookupLiveweightFromMonth($E$7,$E$8,$D72,F$66,Table_SourceData_PastureBeef_LiveweightAllStates[State],Table_SourceData_PastureBeef_LiveweightAllStates[Region],Table_SourceData_PastureBeef_LiveweightAllStates[Season],Table_SourceData_PastureBeef_LiveweightAllStates[#Headers],Table_SourceData_PastureBeef_LiveweightAllStates[#Data],Table_AustralianStates[Common Name],Table_AustralianStates[Abbreviation],Table_SourceData_Common_MonthToSeason[Month],Table_SourceData_Common_MonthToSeason[Season]) -> 700 | G72: =InputFunctions_PastureBeef.LookupLiveweightFromMonth($E$7,$E$8,$D72,G$66,Table_SourceData_PastureBeef_LiveweightAllStates[State],Table_SourceData_PastureBeef_LiveweightAllStates[Region],Table_SourceData_PastureBeef_LiveweightAllStates[Season],Table_SourceData_PastureBeef_LiveweightAllStates[#Headers],Table_SourceData_PastureBeef_LiveweightAllStates[#Data],Table_AustralianStates[Common Name],Table_AustralianStates[Abbreviation],Table_SourceData_Common_MonthToSeason[Month],Table_SourceData_Common_MonthToSeason[Season]) -> 150 | H72: =InputFunctions_PastureBeef.LookupLiveweightFromMonth($E$7,$E$8,$D72,H$66,Table_SourceData_PastureBeef_LiveweightAllStates[State],Table_SourceData_PastureBeef_LiveweightAllStates[Region],Table_SourceData_PastureBeef_LiveweightAllStates[Season],Table_SourceData_PastureBeef_LiveweightAllStates[#Headers],Table_SourceData_PastureBeef_LiveweightAllStates[#Data],Table_AustralianStates[Common Name],Table_AustralianStates[Abbreviation],Table_SourceData_Common_MonthToSeason[Month],Table_SourceData_Common_MonthToSeason[Season]) -> 330 | I72: =InputFunctions_PastureBeef.LookupLiveweightFromMonth($E$7,$E$8,$D72,I$66,Table_SourceData_PastureBeef_LiveweightAllStates[State],Table_SourceData_PastureBeef_LiveweightAllStates[Region],Table_SourceData_PastureBeef_LiveweightAllStates[Season],Table_SourceData_PastureBeef_LiveweightAllStates[#Headers],Table_SourceData_PastureBeef_LiveweightAllStates[#Data],Table_AustralianStates[Common Name],Table_AustralianStates[Abbreviation],Table_SourceData_Common_MonthToSeason[Month],Table_SourceData_Common_MonthToSeason[Season]) -> 490 | J72: =InputFunctions_PastureBeef.LookupLiveweightFromMonth($E$7,$E$8,$D72,J$66,Table_SourceData_PastureBeef_LiveweightAllStates[State],Table_SourceData_PastureBeef_LiveweightAllStates[Region],Table_SourceData_PastureBeef_LiveweightAllStates[Season],Table_SourceData_PastureBeef_LiveweightAllStates[#Headers],Table_SourceData_PastureBeef_LiveweightAllStates[#Data],Table_AustralianStates[Common Name],Table_AustralianStates[Abbreviation],Table_SourceData_Common_MonthToSeason[Month],Table_SourceData_Common_MonthToSeason[Season]) -> 490 | K72: =InputFunctions_PastureBeef.LookupLiveweightFromMonth($E$7,$E$8,$D72,K$66,Table_SourceData_PastureBeef_LiveweightAllStates[State],Table_SourceData_PastureBeef_LiveweightAllStates[Region],Table_SourceData_PastureBeef_LiveweightAllStates[Season],Table_SourceData_PastureBeef_LiveweightAllStates[#Headers],Table_SourceData_PastureBeef_LiveweightAllStates[#Data],Table_AustralianStates[Common Name],Table_AustralianStates[Abbreviation],Table_SourceData_Common_MonthToSeason[Month],Table_SourceData_Common_MonthToSeason[Season]) -> 170 | L72: =InputFunctions_PastureBeef.LookupLiveweightFromMonth($E$7,$E$8,$D72,L$66,Table_SourceData_PastureBeef_LiveweightAllStates[State],Table_SourceData_PastureBeef_LiveweightAllStates[Region],Table_SourceData_PastureBeef_LiveweightAllStates[Season],Table_SourceData_PastureBeef_LiveweightAllStates[#Headers],Table_SourceData_PastureBeef_LiveweightAllStates[#Data],Table_AustralianStates[Common Name],Table_AustralianStates[Abbreviation],Table_SourceData_Common_MonthToSeason[Month],Table_SourceData_Common_MonthToSeason[Season]) -> 360 | ... N72: =InputFunctions_PastureBeef.LookupLiveweightFromMonth($E$7,$E$8,$D72,N$66,Table_SourceData_PastureBeef_LiveweightAllStates[State],Table_SourceData_PastureBeef_LiveweightAllStates[Region],Table_SourceData_PastureBeef_LiveweightAllStates[Season],Table_SourceData_PastureBeef_LiveweightAllStates[#Headers],Table_SourceData_PastureBeef_LiveweightAllStates[#Data],Table_AustralianStates[Common Name],Table_AustralianStates[Abbreviation],Table_SourceData_Common_MonthToSeason[Month],Table_SourceData_Common_MonthToSeason[Season]) -> 360 | O72: kg/head
D73: =TEXT(EDATE(X_Cell_Site_StartDate,6), "mmmm yyyy") -> July 2025 | E73: =InputFunctions_PastureBeef.LookupLiveweightFromMonth($E$7,$E$8,$D73,E$66,Table_SourceData_PastureBeef_LiveweightAllStates[State],Table_SourceData_PastureBeef_LiveweightAllStates[Region],Table_SourceData_PastureBeef_LiveweightAllStates[Season],Table_SourceData_PastureBeef_LiveweightAllStates[#Headers],Table_SourceData_PastureBeef_LiveweightAllStates[#Data],Table_AustralianStates[Common Name],Table_AustralianStates[Abbreviation],Table_SourceData_Common_MonthToSeason[Month],Table_SourceData_Common_MonthToSeason[Season]) -> 190 | F73: =InputFunctions_PastureBeef.LookupLiveweightFromMonth($E$7,$E$8,$D73,F$66,Table_SourceData_PastureBeef_LiveweightAllStates[State],Table_SourceData_PastureBeef_LiveweightAllStates[Region],Table_SourceData_PastureBeef_LiveweightAllStates[Season],Table_SourceData_PastureBeef_LiveweightAllStates[#Headers],Table_SourceData_PastureBeef_LiveweightAllStates[#Data],Table_AustralianStates[Common Name],Table_AustralianStates[Abbreviation],Table_SourceData_Common_MonthToSeason[Month],Table_SourceData_Common_MonthToSeason[Season]) -> 700 | G73: =InputFunctions_PastureBeef.LookupLiveweightFromMonth($E$7,$E$8,$D73,G$66,Table_SourceData_PastureBeef_LiveweightAllStates[State],Table_SourceData_PastureBeef_LiveweightAllStates[Region],Table_SourceData_PastureBeef_LiveweightAllStates[Season],Table_SourceData_PastureBeef_LiveweightAllStates[#Headers],Table_SourceData_PastureBeef_LiveweightAllStates[#Data],Table_AustralianStates[Common Name],Table_AustralianStates[Abbreviation],Table_SourceData_Common_MonthToSeason[Month],Table_SourceData_Common_MonthToSeason[Season]) -> 150 | H73: =InputFunctions_PastureBeef.LookupLiveweightFromMonth($E$7,$E$8,$D73,H$66,Table_SourceData_PastureBeef_LiveweightAllStates[State],Table_SourceData_PastureBeef_LiveweightAllStates[Region],Table_SourceData_PastureBeef_LiveweightAllStates[Season],Table_SourceData_PastureBeef_LiveweightAllStates[#Headers],Table_SourceData_PastureBeef_LiveweightAllStates[#Data],Table_AustralianStates[Common Name],Table_AustralianStates[Abbreviation],Table_SourceData_Common_MonthToSeason[Month],Table_SourceData_Common_MonthToSeason[Season]) -> 330 | I73: =InputFunctions_PastureBeef.LookupLiveweightFromMonth($E$7,$E$8,$D73,I$66,Table_SourceData_PastureBeef_LiveweightAllStates[State],Table_SourceData_PastureBeef_LiveweightAllStates[Region],Table_SourceData_PastureBeef_LiveweightAllStates[Season],Table_SourceData_PastureBeef_LiveweightAllStates[#Headers],Table_SourceData_PastureBeef_LiveweightAllStates[#Data],Table_AustralianStates[Common Name],Table_AustralianStates[Abbreviation],Table_SourceData_Common_MonthToSeason[Month],Table_SourceData_Common_MonthToSeason[Season]) -> 490 | J73: =InputFunctions_PastureBeef.LookupLiveweightFromMonth($E$7,$E$8,$D73,J$66,Table_SourceData_PastureBeef_LiveweightAllStates[State],Table_SourceData_PastureBeef_LiveweightAllStates[Region],Table_SourceData_PastureBeef_LiveweightAllStates[Season],Table_SourceData_PastureBeef_LiveweightAllStates[#Headers],Table_SourceData_PastureBeef_LiveweightAllStates[#Data],Table_AustralianStates[Common Name],Table_AustralianStates[Abbreviation],Table_SourceData_Common_MonthToSeason[Month],Table_SourceData_Common_MonthToSeason[Season]) -> 490 | K73: =InputFunctions_PastureBeef.LookupLiveweightFromMonth($E$7,$E$8,$D73,K$66,Table_SourceData_PastureBeef_LiveweightAllStates[State],Table_SourceData_PastureBeef_LiveweightAllStates[Region],Table_SourceData_PastureBeef_LiveweightAllStates[Season],Table_SourceData_PastureBeef_LiveweightAllStates[#Headers],Table_SourceData_PastureBeef_LiveweightAllStates[#Data],Table_AustralianStates[Common Name],Table_AustralianStates[Abbreviation],Table_SourceData_Common_MonthToSeason[Month],Table_SourceData_Common_MonthToSeason[Season]) -> 170 | L73: =InputFunctions_PastureBeef.LookupLiveweightFromMonth($E$7,$E$8,$D73,L$66,Table_SourceData_PastureBeef_LiveweightAllStates[State],Table_SourceData_PastureBeef_LiveweightAllStates[Region],Table_SourceData_PastureBeef_LiveweightAllStates[Season],Table_SourceData_PastureBeef_LiveweightAllStates[#Headers],Table_SourceData_PastureBeef_LiveweightAllStates[#Data],Table_AustralianStates[Common Name],Table_AustralianStates[Abbreviation],Table_SourceData_Common_MonthToSeason[Month],Table_SourceData_Common_MonthToSeason[Season]) -> 360 | ... N73: =InputFunctions_PastureBeef.LookupLiveweightFromMonth($E$7,$E$8,$D73,N$66,Table_SourceData_PastureBeef_LiveweightAllStates[State],Table_SourceData_PastureBeef_LiveweightAllStates[Region],Table_SourceData_PastureBeef_LiveweightAllStates[Season],Table_SourceData_PastureBeef_LiveweightAllStates[#Headers],Table_SourceData_PastureBeef_LiveweightAllStates[#Data],Table_AustralianStates[Common Name],Table_AustralianStates[Abbreviation],Table_SourceData_Common_MonthToSeason[Month],Table_SourceData_Common_MonthToSeason[Season]) -> 360 | O73: kg/head
D74: =TEXT(EDATE(X_Cell_Site_StartDate,7), "mmmm yyyy") -> August 2025 | E74: =InputFunctions_PastureBeef.LookupLiveweightFromMonth($E$7,$E$8,$D74,E$66,Table_SourceData_PastureBeef_LiveweightAllStates[State],Table_SourceData_PastureBeef_LiveweightAllStates[Region],Table_SourceData_PastureBeef_LiveweightAllStates[Season],Table_SourceData_PastureBeef_LiveweightAllStates[#Headers],Table_SourceData_PastureBeef_LiveweightAllStates[#Data],Table_AustralianStates[Common Name],Table_AustralianStates[Abbreviation],Table_SourceData_Common_MonthToSeason[Month],Table_SourceData_Common_MonthToSeason[Season]) -> 190 | F74: =InputFunctions_PastureBeef.LookupLiveweightFromMonth($E$7,$E$8,$D74,F$66,Table_SourceData_PastureBeef_LiveweightAllStates[State],Table_SourceData_PastureBeef_LiveweightAllStates[Region],Table_SourceData_PastureBeef_LiveweightAllStates[Season],Table_SourceData_PastureBeef_LiveweightAllStates[#Headers],Table_SourceData_PastureBeef_LiveweightAllStates[#Data],Table_AustralianStates[Common Name],Table_AustralianStates[Abbreviation],Table_SourceData_Common_MonthToSeason[Month],Table_SourceData_Common_MonthToSeason[Season]) -> 700 | G74: =InputFunctions_PastureBeef.LookupLiveweightFromMonth($E$7,$E$8,$D74,G$66,Table_SourceData_PastureBeef_LiveweightAllStates[State],Table_SourceData_PastureBeef_LiveweightAllStates[Region],Table_SourceData_PastureBeef_LiveweightAllStates[Season],Table_SourceData_PastureBeef_LiveweightAllStates[#Headers],Table_SourceData_PastureBeef_LiveweightAllStates[#Data],Table_AustralianStates[Common Name],Table_AustralianStates[Abbreviation],Table_SourceData_Common_MonthToSeason[Month],Table_SourceData_Common_MonthToSeason[Season]) -> 150 | H74: =InputFunctions_PastureBeef.LookupLiveweightFromMonth($E$7,$E$8,$D74,H$66,Table_SourceData_PastureBeef_LiveweightAllStates[State],Table_SourceData_PastureBeef_LiveweightAllStates[Region],Table_SourceData_PastureBeef_LiveweightAllStates[Season],Table_SourceData_PastureBeef_LiveweightAllStates[#Headers],Table_SourceData_PastureBeef_LiveweightAllStates[#Data],Table_AustralianStates[Common Name],Table_AustralianStates[Abbreviation],Table_SourceData_Common_MonthToSeason[Month],Table_SourceData_Common_MonthToSeason[Season]) -> 330 | I74: =InputFunctions_PastureBeef.LookupLiveweightFromMonth($E$7,$E$8,$D74,I$66,Table_SourceData_PastureBeef_LiveweightAllStates[State],Table_SourceData_PastureBeef_LiveweightAllStates[Region],Table_SourceData_PastureBeef_LiveweightAllStates[Season],Table_SourceData_PastureBeef_LiveweightAllStates[#Headers],Table_SourceData_PastureBeef_LiveweightAllStates[#Data],Table_AustralianStates[Common Name],Table_AustralianStates[Abbreviation],Table_SourceData_Common_MonthToSeason[Month],Table_SourceData_Common_MonthToSeason[Season]) -> 490 | J74: =InputFunctions_PastureBeef.LookupLiveweightFromMonth($E$7,$E$8,$D74,J$66,Table_SourceData_PastureBeef_LiveweightAllStates[State],Table_SourceData_PastureBeef_LiveweightAllStates[Region],Table_SourceData_PastureBeef_LiveweightAllStates[Season],Table_SourceData_PastureBeef_LiveweightAllStates[#Headers],Table_SourceData_PastureBeef_LiveweightAllStates[#Data],Table_AustralianStates[Common Name],Table_AustralianStates[Abbreviation],Table_SourceData_Common_MonthToSeason[Month],Table_SourceData_Common_MonthToSeason[Season]) -> 490 | K74: =InputFunctions_PastureBeef.LookupLiveweightFromMonth($E$7,$E$8,$D74,K$66,Table_SourceData_PastureBeef_LiveweightAllStates[State],Table_SourceData_PastureBeef_LiveweightAllStates[Region],Table_SourceData_PastureBeef_LiveweightAllStates[Season],Table_SourceData_PastureBeef_LiveweightAllStates[#Headers],Table_SourceData_PastureBeef_LiveweightAllStates[#Data],Table_AustralianStates[Common Name],Table_AustralianStates[Abbreviation],Table_SourceData_Common_MonthToSeason[Month],Table_SourceData_Common_MonthToSeason[Season]) -> 170 | L74: =InputFunctions_PastureBeef.LookupLiveweightFromMonth($E$7,$E$8,$D74,L$66,Table_SourceData_PastureBeef_LiveweightAllStates[State],Table_SourceData_PastureBeef_LiveweightAllStates[Region],Table_SourceData_PastureBeef_LiveweightAllStates[Season],Table_SourceData_PastureBeef_LiveweightAllStates[#Headers],Table_SourceData_PastureBeef_LiveweightAllStates[#Data],Table_AustralianStates[Common Name],Table_AustralianStates[Abbreviation],Table_SourceData_Common_MonthToSeason[Month],Table_SourceData_Common_MonthToSeason[Season]) -> 360 | ... N74: =InputFunctions_PastureBeef.LookupLiveweightFromMonth($E$7,$E$8,$D74,N$66,Table_SourceData_PastureBeef_LiveweightAllStates[State],Table_SourceData_PastureBeef_LiveweightAllStates[Region],Table_SourceData_PastureBeef_LiveweightAllStates[Season],Table_SourceData_PastureBeef_LiveweightAllStates[#Headers],Table_SourceData_PastureBeef_LiveweightAllStates[#Data],Table_AustralianStates[Common Name],Table_AustralianStates[Abbreviation],Table_SourceData_Common_MonthToSeason[Month],Table_SourceData_Common_MonthToSeason[Season]) -> 360 | O74: kg/head
D75: =TEXT(EDATE(X_Cell_Site_StartDate,8), "mmmm yyyy") -> September 2025 | E75: =InputFunctions_PastureBeef.LookupLiveweightFromMonth($E$7,$E$8,$D75,E$66,Table_SourceData_PastureBeef_LiveweightAllStates[State],Table_SourceData_PastureBeef_LiveweightAllStates[Region],Table_SourceData_PastureBeef_LiveweightAllStates[Season],Table_SourceData_PastureBeef_LiveweightAllStates[#Headers],Table_SourceData_PastureBeef_LiveweightAllStates[#Data],Table_AustralianStates[Common Name],Table_AustralianStates[Abbreviation],Table_SourceData_Common_MonthToSeason[Month],Table_SourceData_Common_MonthToSeason[Season]) -> 340 | F75: =InputFunctions_PastureBeef.LookupLiveweightFromMonth($E$7,$E$8,$D75,F$66,Table_SourceData_PastureBeef_LiveweightAllStates[State],Table_SourceData_PastureBeef_LiveweightAllStates[Region],Table_SourceData_PastureBeef_LiveweightAllStates[Season],Table_SourceData_PastureBeef_LiveweightAllStates[#Headers],Table_SourceData_PastureBeef_LiveweightAllStates[#Data],Table_AustralianStates[Common Name],Table_AustralianStates[Abbreviation],Table_SourceData_Common_MonthToSeason[Month],Table_SourceData_Common_MonthToSeason[Season]) -> 800 | G75: =InputFunctions_PastureBeef.LookupLiveweightFromMonth($E$7,$E$8,$D75,G$66,Table_SourceData_PastureBeef_LiveweightAllStates[State],Table_SourceData_PastureBeef_LiveweightAllStates[Region],Table_SourceData_PastureBeef_LiveweightAllStates[Season],Table_SourceData_PastureBeef_LiveweightAllStates[#Headers],Table_SourceData_PastureBeef_LiveweightAllStates[#Data],Table_AustralianStates[Common Name],Table_AustralianStates[Abbreviation],Table_SourceData_Common_MonthToSeason[Month],Table_SourceData_Common_MonthToSeason[Season]) -> 260 | H75: =InputFunctions_PastureBeef.LookupLiveweightFromMonth($E$7,$E$8,$D75,H$66,Table_SourceData_PastureBeef_LiveweightAllStates[State],Table_SourceData_PastureBeef_LiveweightAllStates[Region],Table_SourceData_PastureBeef_LiveweightAllStates[Season],Table_SourceData_PastureBeef_LiveweightAllStates[#Headers],Table_SourceData_PastureBeef_LiveweightAllStates[#Data],Table_AustralianStates[Common Name],Table_AustralianStates[Abbreviation],Table_SourceData_Common_MonthToSeason[Month],Table_SourceData_Common_MonthToSeason[Season]) -> 420 | I75: =InputFunctions_PastureBeef.LookupLiveweightFromMonth($E$7,$E$8,$D75,I$66,Table_SourceData_PastureBeef_LiveweightAllStates[State],Table_SourceData_PastureBeef_LiveweightAllStates[Region],Table_SourceData_PastureBeef_LiveweightAllStates[Season],Table_SourceData_PastureBeef_LiveweightAllStates[#Headers],Table_SourceData_PastureBeef_LiveweightAllStates[#Data],Table_AustralianStates[Common Name],Table_AustralianStates[Abbreviation],Table_SourceData_Common_MonthToSeason[Month],Table_SourceData_Common_MonthToSeason[Season]) -> 550 | J75: =InputFunctions_PastureBeef.LookupLiveweightFromMonth($E$7,$E$8,$D75,J$66,Table_SourceData_PastureBeef_LiveweightAllStates[State],Table_SourceData_PastureBeef_LiveweightAllStates[Region],Table_SourceData_PastureBeef_LiveweightAllStates[Season],Table_SourceData_PastureBeef_LiveweightAllStates[#Headers],Table_SourceData_PastureBeef_LiveweightAllStates[#Data],Table_AustralianStates[Common Name],Table_AustralianStates[Abbreviation],Table_SourceData_Common_MonthToSeason[Month],Table_SourceData_Common_MonthToSeason[Season]) -> 550 | K75: =InputFunctions_PastureBeef.LookupLiveweightFromMonth($E$7,$E$8,$D75,K$66,Table_SourceData_PastureBeef_LiveweightAllStates[State],Table_SourceData_PastureBeef_LiveweightAllStates[Region],Table_SourceData_PastureBeef_LiveweightAllStates[Season],Table_SourceData_PastureBeef_LiveweightAllStates[#Headers],Table_SourceData_PastureBeef_LiveweightAllStates[#Data],Table_AustralianStates[Common Name],Table_AustralianStates[Abbreviation],Table_SourceData_Common_MonthToSeason[Month],Table_SourceData_Common_MonthToSeason[Season]) -> 300 | L75: =InputFunctions_PastureBeef.LookupLiveweightFromMonth($E$7,$E$8,$D75,L$66,Table_SourceData_PastureBeef_LiveweightAllStates[State],Table_SourceData_PastureBeef_LiveweightAllStates[Region],Table_SourceData_PastureBeef_LiveweightAllStates[Season],Table_SourceData_PastureBeef_LiveweightAllStates[#Headers],Table_SourceData_PastureBeef_LiveweightAllStates[#Data],Table_AustralianStates[Common Name],Table_AustralianStates[Abbreviation],Table_SourceData_Common_MonthToSeason[Month],Table_SourceData_Common_MonthToSeason[Season]) -> 480 | ... N75: =InputFunctions_PastureBeef.LookupLiveweightFromMonth($E$7,$E$8,$D75,N$66,Table_SourceData_PastureBeef_LiveweightAllStates[State],Table_SourceData_PastureBeef_LiveweightAllStates[Region],Table_SourceData_PastureBeef_LiveweightAllStates[Season],Table_SourceData_PastureBeef_LiveweightAllStates[#Headers],Table_SourceData_PastureBeef_LiveweightAllStates[#Data],Table_AustralianStates[Common Name],Table_AustralianStates[Abbreviation],Table_SourceData_Common_MonthToSeason[Month],Table_SourceData_Common_MonthToSeason[Season]) -> 480 | O75: kg/head
D76: =TEXT(EDATE(X_Cell_Site_StartDate,9), "mmmm yyyy") -> October 2025 | E76: =InputFunctions_PastureBeef.LookupLiveweightFromMonth($E$7,$E$8,$D76,E$66,Table_SourceData_PastureBeef_LiveweightAllStates[State],Table_SourceData_PastureBeef_LiveweightAllStates[Region],Table_SourceData_PastureBeef_LiveweightAllStates[Season],Table_SourceData_PastureBeef_LiveweightAllStates[#Headers],Table_SourceData_PastureBeef_LiveweightAllStates[#Data],Table_AustralianStates[Common Name],Table_AustralianStates[Abbreviation],Table_SourceData_Common_MonthToSeason[Month],Table_SourceData_Common_MonthToSeason[Season]) -> 340 | F76: =InputFunctions_PastureBeef.LookupLiveweightFromMonth($E$7,$E$8,$D76,F$66,Table_SourceData_PastureBeef_LiveweightAllStates[State],Table_SourceData_PastureBeef_LiveweightAllStates[Region],Table_SourceData_PastureBeef_LiveweightAllStates[Season],Table_SourceData_PastureBeef_LiveweightAllStates[#Headers],Table_SourceData_PastureBeef_LiveweightAllStates[#Data],Table_AustralianStates[Common Name],Table_AustralianStates[Abbreviation],Table_SourceData_Common_MonthToSeason[Month],Table_SourceData_Common_MonthToSeason[Season]) -> 800 | G76: =InputFunctions_PastureBeef.LookupLiveweightFromMonth($E$7,$E$8,$D76,G$66,Table_SourceData_PastureBeef_LiveweightAllStates[State],Table_SourceData_PastureBeef_LiveweightAllStates[Region],Table_SourceData_PastureBeef_LiveweightAllStates[Season],Table_SourceData_PastureBeef_LiveweightAllStates[#Headers],Table_SourceData_PastureBeef_LiveweightAllStates[#Data],Table_AustralianStates[Common Name],Table_AustralianStates[Abbreviation],Table_SourceData_Common_MonthToSeason[Month],Table_SourceData_Common_MonthToSeason[Season]) -> 260 | H76: =InputFunctions_PastureBeef.LookupLiveweightFromMonth($E$7,$E$8,$D76,H$66,Table_SourceData_PastureBeef_LiveweightAllStates[State],Table_SourceData_PastureBeef_LiveweightAllStates[Region],Table_SourceData_PastureBeef_LiveweightAllStates[Season],Table_SourceData_PastureBeef_LiveweightAllStates[#Headers],Table_SourceData_PastureBeef_LiveweightAllStates[#Data],Table_AustralianStates[Common Name],Table_AustralianStates[Abbreviation],Table_SourceData_Common_MonthToSeason[Month],Table_SourceData_Common_MonthToSeason[Season]) -> 420 | I76: =InputFunctions_PastureBeef.LookupLiveweightFromMonth($E$7,$E$8,$D76,I$66,Table_SourceData_PastureBeef_LiveweightAllStates[State],Table_SourceData_PastureBeef_LiveweightAllStates[Region],Table_SourceData_PastureBeef_LiveweightAllStates[Season],Table_SourceData_PastureBeef_LiveweightAllStates[#Headers],Table_SourceData_PastureBeef_LiveweightAllStates[#Data],Table_AustralianStates[Common Name],Table_AustralianStates[Abbreviation],Table_SourceData_Common_MonthToSeason[Month],Table_SourceData_Common_MonthToSeason[Season]) -> 550 | J76: =InputFunctions_PastureBeef.LookupLiveweightFromMonth($E$7,$E$8,$D76,J$66,Table_SourceData_PastureBeef_LiveweightAllStates[State],Table_SourceData_PastureBeef_LiveweightAllStates[Region],Table_SourceData_PastureBeef_LiveweightAllStates[Season],Table_SourceData_PastureBeef_LiveweightAllStates[#Headers],Table_SourceData_PastureBeef_LiveweightAllStates[#Data],Table_AustralianStates[Common Name],Table_AustralianStates[Abbreviation],Table_SourceData_Common_MonthToSeason[Month],Table_SourceData_Common_MonthToSeason[Season]) -> 550 | K76: =InputFunctions_PastureBeef.LookupLiveweightFromMonth($E$7,$E$8,$D76,K$66,Table_SourceData_PastureBeef_LiveweightAllStates[State],Table_SourceData_PastureBeef_LiveweightAllStates[Region],Table_SourceData_PastureBeef_LiveweightAllStates[Season],Table_SourceData_PastureBeef_LiveweightAllStates[#Headers],Table_SourceData_PastureBeef_LiveweightAllStates[#Data],Table_AustralianStates[Common Name],Table_AustralianStates[Abbreviation],Table_SourceData_Common_MonthToSeason[Month],Table_SourceData_Common_MonthToSeason[Season]) -> 300 | L76: =InputFunctions_PastureBeef.LookupLiveweightFromMonth($E$7,$E$8,$D76,L$66,Table_SourceData_PastureBeef_LiveweightAllStates[State],Table_SourceData_PastureBeef_LiveweightAllStates[Region],Table_SourceData_PastureBeef_LiveweightAllStates[Season],Table_SourceData_PastureBeef_LiveweightAllStates[#Headers],Table_SourceData_PastureBeef_LiveweightAllStates[#Data],Table_AustralianStates[Common Name],Table_AustralianStates[Abbreviation],Table_SourceData_Common_MonthToSeason[Month],Table_SourceData_Common_MonthToSeason[Season]) -> 480 | ... N76: =InputFunctions_PastureBeef.LookupLiveweightFromMonth($E$7,$E$8,$D76,N$66,Table_SourceData_PastureBeef_LiveweightAllStates[State],Table_SourceData_PastureBeef_LiveweightAllStates[Region],Table_SourceData_PastureBeef_LiveweightAllStates[Season],Table_SourceData_PastureBeef_LiveweightAllStates[#Headers],Table_SourceData_PastureBeef_LiveweightAllStates[#Data],Table_AustralianStates[Common Name],Table_AustralianStates[Abbreviation],Table_SourceData_Common_MonthToSeason[Month],Table_SourceData_Common_MonthToSeason[Season]) -> 480 | O76: kg/head
D77: =TEXT(EDATE(X_Cell_Site_StartDate,10), "mmmm yyyy") -> November 2025 | E77: =InputFunctions_PastureBeef.LookupLiveweightFromMonth($E$7,$E$8,$D77,E$66,Table_SourceData_PastureBeef_LiveweightAllStates[State],Table_SourceData_PastureBeef_LiveweightAllStates[Region],Table_SourceData_PastureBeef_LiveweightAllStates[Season],Table_SourceData_PastureBeef_LiveweightAllStates[#Headers],Table_SourceData_PastureBeef_LiveweightAllStates[#Data],Table_AustralianStates[Common Name],Table_AustralianStates[Abbreviation],Table_SourceData_Common_MonthToSeason[Month],Table_SourceData_Common_MonthToSeason[Season]) -> 340 | F77: =InputFunctions_PastureBeef.LookupLiveweightFromMonth($E$7,$E$8,$D77,F$66,Table_SourceData_PastureBeef_LiveweightAllStates[State],Table_SourceData_PastureBeef_LiveweightAllStates[Region],Table_SourceData_PastureBeef_LiveweightAllStates[Season],Table_SourceData_PastureBeef_LiveweightAllStates[#Headers],Table_SourceData_PastureBeef_LiveweightAllStates[#Data],Table_AustralianStates[Common Name],Table_AustralianStates[Abbreviation],Table_SourceData_Common_MonthToSeason[Month],Table_SourceData_Common_MonthToSeason[Season]) -> 800 | G77: =InputFunctions_PastureBeef.LookupLiveweightFromMonth($E$7,$E$8,$D77,G$66,Table_SourceData_PastureBeef_LiveweightAllStates[State],Table_SourceData_PastureBeef_LiveweightAllStates[Region],Table_SourceData_PastureBeef_LiveweightAllStates[Season],Table_SourceData_PastureBeef_LiveweightAllStates[#Headers],Table_SourceData_PastureBeef_LiveweightAllStates[#Data],Table_AustralianStates[Common Name],Table_AustralianStates[Abbreviation],Table_SourceData_Common_MonthToSeason[Month],Table_SourceData_Common_MonthToSeason[Season]) -> 260 | H77: =InputFunctions_PastureBeef.LookupLiveweightFromMonth($E$7,$E$8,$D77,H$66,Table_SourceData_PastureBeef_LiveweightAllStates[State],Table_SourceData_PastureBeef_LiveweightAllStates[Region],Table_SourceData_PastureBeef_LiveweightAllStates[Season],Table_SourceData_PastureBeef_LiveweightAllStates[#Headers],Table_SourceData_PastureBeef_LiveweightAllStates[#Data],Table_AustralianStates[Common Name],Table_AustralianStates[Abbreviation],Table_SourceData_Common_MonthToSeason[Month],Table_SourceData_Common_MonthToSeason[Season]) -> 420 | I77: =InputFunctions_PastureBeef.LookupLiveweightFromMonth($E$7,$E$8,$D77,I$66,Table_SourceData_PastureBeef_LiveweightAllStates[State],Table_SourceData_PastureBeef_LiveweightAllStates[Region],Table_SourceData_PastureBeef_LiveweightAllStates[Season],Table_SourceData_PastureBeef_LiveweightAllStates[#Headers],Table_SourceData_PastureBeef_LiveweightAllStates[#Data],Table_AustralianStates[Common Name],Table_AustralianStates[Abbreviation],Table_SourceData_Common_MonthToSeason[Month],Table_SourceData_Common_MonthToSeason[Season]) -> 550 | J77: =InputFunctions_PastureBeef.LookupLiveweightFromMonth($E$7,$E$8,$D77,J$66,Table_SourceData_PastureBeef_LiveweightAllStates[State],Table_SourceData_PastureBeef_LiveweightAllStates[Region],Table_SourceData_PastureBeef_LiveweightAllStates[Season],Table_SourceData_PastureBeef_LiveweightAllStates[#Headers],Table_SourceData_PastureBeef_LiveweightAllStates[#Data],Table_AustralianStates[Common Name],Table_AustralianStates[Abbreviation],Table_SourceData_Common_MonthToSeason[Month],Table_SourceData_Common_MonthToSeason[Season]) -> 550 | K77: =InputFunctions_PastureBeef.LookupLiveweightFromMonth($E$7,$E$8,$D77,K$66,Table_SourceData_PastureBeef_LiveweightAllStates[State],Table_SourceData_PastureBeef_LiveweightAllStates[Region],Table_SourceData_PastureBeef_LiveweightAllStates[Season],Table_SourceData_PastureBeef_LiveweightAllStates[#Headers],Table_SourceData_PastureBeef_LiveweightAllStates[#Data],Table_AustralianStates[Common Name],Table_AustralianStates[Abbreviation],Table_SourceData_Common_MonthToSeason[Month],Table_SourceData_Common_MonthToSeason[Season]) -> 300 | L77: =InputFunctions_PastureBeef.LookupLiveweightFromMonth($E$7,$E$8,$D77,L$66,Table_SourceData_PastureBeef_LiveweightAllStates[State],Table_SourceData_PastureBeef_LiveweightAllStates[Region],Table_SourceData_PastureBeef_LiveweightAllStates[Season],Table_SourceData_PastureBeef_LiveweightAllStates[#Headers],Table_SourceData_PastureBeef_LiveweightAllStates[#Data],Table_AustralianStates[Common Name],Table_AustralianStates[Abbreviation],Table_SourceData_Common_MonthToSeason[Month],Table_SourceData_Common_MonthToSeason[Season]) -> 480 | ... N77: =InputFunctions_PastureBeef.LookupLiveweightFromMonth($E$7,$E$8,$D77,N$66,Table_SourceData_PastureBeef_LiveweightAllStates[State],Table_SourceData_PastureBeef_LiveweightAllStates[Region],Table_SourceData_PastureBeef_LiveweightAllStates[Season],Table_SourceData_PastureBeef_LiveweightAllStates[#Headers],Table_SourceData_PastureBeef_LiveweightAllStates[#Data],Table_AustralianStates[Common Name],Table_AustralianStates[Abbreviation],Table_SourceData_Common_MonthToSeason[Month],Table_SourceData_Common_MonthToSeason[Season]) -> 480 | O77: kg/head
D78: =TEXT(EDATE(X_Cell_Site_StartDate,11), "mmmm yyyy") -> December 2025 | E78: =InputFunctions_PastureBeef.LookupLiveweightFromMonth($E$7,$E$8,$D78,E$66,Table_SourceData_PastureBeef_LiveweightAllStates[State],Table_SourceData_PastureBeef_LiveweightAllStates[Region],Table_SourceData_PastureBeef_LiveweightAllStates[Season],Table_SourceData_PastureBeef_LiveweightAllStates[#Headers],Table_SourceData_PastureBeef_LiveweightAllStates[#Data],Table_AustralianStates[Common Name],Table_AustralianStates[Abbreviation],Table_SourceData_Common_MonthToSeason[Month],Table_SourceData_Common_MonthToSeason[Season]) -> 380 | F78: =InputFunctions_PastureBeef.LookupLiveweightFromMonth($E$7,$E$8,$D78,F$66,Table_SourceData_PastureBeef_LiveweightAllStates[State],Table_SourceData_PastureBeef_LiveweightAllStates[Region],Table_SourceData_PastureBeef_LiveweightAllStates[Season],Table_SourceData_PastureBeef_LiveweightAllStates[#Headers],Table_SourceData_PastureBeef_LiveweightAllStates[#Data],Table_AustralianStates[Common Name],Table_AustralianStates[Abbreviation],Table_SourceData_Common_MonthToSeason[Month],Table_SourceData_Common_MonthToSeason[Season]) -> 780 | G78: =InputFunctions_PastureBeef.LookupLiveweightFromMonth($E$7,$E$8,$D78,G$66,Table_SourceData_PastureBeef_LiveweightAllStates[State],Table_SourceData_PastureBeef_LiveweightAllStates[Region],Table_SourceData_PastureBeef_LiveweightAllStates[Season],Table_SourceData_PastureBeef_LiveweightAllStates[#Headers],Table_SourceData_PastureBeef_LiveweightAllStates[#Data],Table_AustralianStates[Common Name],Table_AustralianStates[Abbreviation],Table_SourceData_Common_MonthToSeason[Month],Table_SourceData_Common_MonthToSeason[Season]) -> 300 | H78: =InputFunctions_PastureBeef.LookupLiveweightFromMonth($E$7,$E$8,$D78,H$66,Table_SourceData_PastureBeef_LiveweightAllStates[State],Table_SourceData_PastureBeef_LiveweightAllStates[Region],Table_SourceData_PastureBeef_LiveweightAllStates[Season],Table_SourceData_PastureBeef_LiveweightAllStates[#Headers],Table_SourceData_PastureBeef_LiveweightAllStates[#Data],Table_AustralianStates[Common Name],Table_AustralianStates[Abbreviation],Table_SourceData_Common_MonthToSeason[Month],Table_SourceData_Common_MonthToSeason[Season]) -> 450 | I78: =InputFunctions_PastureBeef.LookupLiveweightFromMonth($E$7,$E$8,$D78,I$66,Table_SourceData_PastureBeef_LiveweightAllStates[State],Table_SourceData_PastureBeef_LiveweightAllStates[Region],Table_SourceData_PastureBeef_LiveweightAllStates[Season],Table_SourceData_PastureBeef_LiveweightAllStates[#Headers],Table_SourceData_PastureBeef_LiveweightAllStates[#Data],Table_AustralianStates[Common Name],Table_AustralianStates[Abbreviation],Table_SourceData_Common_MonthToSeason[Month],Table_SourceData_Common_MonthToSeason[Season]) -> 530 | J78: =InputFunctions_PastureBeef.LookupLiveweightFromMonth($E$7,$E$8,$D78,J$66,Table_SourceData_PastureBeef_LiveweightAllStates[State],Table_SourceData_PastureBeef_LiveweightAllStates[Region],Table_SourceData_PastureBeef_LiveweightAllStates[Season],Table_SourceData_PastureBeef_LiveweightAllStates[#Headers],Table_SourceData_PastureBeef_LiveweightAllStates[#Data],Table_AustralianStates[Common Name],Table_AustralianStates[Abbreviation],Table_SourceData_Common_MonthToSeason[Month],Table_SourceData_Common_MonthToSeason[Season]) -> 530 | K78: =InputFunctions_PastureBeef.LookupLiveweightFromMonth($E$7,$E$8,$D78,K$66,Table_SourceData_PastureBeef_LiveweightAllStates[State],Table_SourceData_PastureBeef_LiveweightAllStates[Region],Table_SourceData_PastureBeef_LiveweightAllStates[Season],Table_SourceData_PastureBeef_LiveweightAllStates[#Headers],Table_SourceData_PastureBeef_LiveweightAllStates[#Data],Table_AustralianStates[Common Name],Table_AustralianStates[Abbreviation],Table_SourceData_Common_MonthToSeason[Month],Table_SourceData_Common_MonthToSeason[Season]) -> 340 | L78: =InputFunctions_PastureBeef.LookupLiveweightFromMonth($E$7,$E$8,$D78,L$66,Table_SourceData_PastureBeef_LiveweightAllStates[State],Table_SourceData_PastureBeef_LiveweightAllStates[Region],Table_SourceData_PastureBeef_LiveweightAllStates[Season],Table_SourceData_PastureBeef_LiveweightAllStates[#Headers],Table_SourceData_PastureBeef_LiveweightAllStates[#Data],Table_AustralianStates[Common Name],Table_AustralianStates[Abbreviation],Table_SourceData_Common_MonthToSeason[Month],Table_SourceData_Common_MonthToSeason[Season]) -> 470 | ... N78: =InputFunctions_PastureBeef.LookupLiveweightFromMonth($E$7,$E$8,$D78,N$66,Table_SourceData_PastureBeef_LiveweightAllStates[State],Table_SourceData_PastureBeef_LiveweightAllStates[Region],Table_SourceData_PastureBeef_LiveweightAllStates[Season],Table_SourceData_PastureBeef_LiveweightAllStates[#Headers],Table_SourceData_PastureBeef_LiveweightAllStates[#Data],Table_AustralianStates[Common Name],Table_AustralianStates[Abbreviation],Table_SourceData_Common_MonthToSeason[Month],Table_SourceData_Common_MonthToSeason[Season]) -> 470 | O78: kg/head
D81: Liveweight gain
D82: Method 1 default values (do not edit) | E82: Bulls < 1 year | F82: Bulls > 1 year | G82: Cows < 1 year | H82: Cows 1-2 years | I82: Cows 2-3 years | J82: Cows > 3 years | K82: Steers < 1 year | L82: Steers 1-2 years | M82: Steers 2-3 years | N82: Steers >3 years
D83: Spring | E83: =InputFunctions_PastureBeef.LookupLiveweightFromSeason($E$7,$E$8,$D83,E$82,Table_SourceData_PastureBeef_LiveweightGainAllStates[State],Table_SourceData_PastureBeef_LiveweightGainAllStates[Region],Table_SourceData_PastureBeef_LiveweightGainAllStates[Season],Table_SourceData_PastureBeef_LiveweightGainAllStates[#Headers],Table_SourceData_PastureBeef_LiveweightGainAllStates[#Data],Table_AustralianStates[Common Name],Table_AustralianStates[Abbreviation]) -> 1.64 | F83: =InputFunctions_PastureBeef.LookupLiveweightFromSeason($E$7,$E$8,$D83,F$82,Table_SourceData_PastureBeef_LiveweightGainAllStates[State],Table_SourceData_PastureBeef_LiveweightGainAllStates[Region],Table_SourceData_PastureBeef_LiveweightGainAllStates[Season],Table_SourceData_PastureBeef_LiveweightGainAllStates[#Headers],Table_SourceData_PastureBeef_LiveweightGainAllStates[#Data],Table_AustralianStates[Common Name],Table_AustralianStates[Abbreviation]) -> 1.1 | G83: =InputFunctions_PastureBeef.LookupLiveweightFromSeason($E$7,$E$8,$D83,G$82,Table_SourceData_PastureBeef_LiveweightGainAllStates[State],Table_SourceData_PastureBeef_LiveweightGainAllStates[Region],Table_SourceData_PastureBeef_LiveweightGainAllStates[Season],Table_SourceData_PastureBeef_LiveweightGainAllStates[#Headers],Table_SourceData_PastureBeef_LiveweightGainAllStates[#Data],Table_AustralianStates[Common Name],Table_AustralianStates[Abbreviation]) -> 1.21 | H83: =InputFunctions_PastureBeef.LookupLiveweightFromSeason($E$7,$E$8,$D83,H$82,Table_SourceData_PastureBeef_LiveweightGainAllStates[State],Table_SourceData_PastureBeef_LiveweightGainAllStates[Region],Table_SourceData_PastureBeef_LiveweightGainAllStates[Season],Table_SourceData_PastureBeef_LiveweightGainAllStates[#Headers],Table_SourceData_PastureBeef_LiveweightGainAllStates[#Data],Table_AustralianStates[Common Name],Table_AustralianStates[Abbreviation]) -> 0.99 | I83: =InputFunctions_PastureBeef.LookupLiveweightFromSeason($E$7,$E$8,$D83,I$82,Table_SourceData_PastureBeef_LiveweightGainAllStates[State],Table_SourceData_PastureBeef_LiveweightGainAllStates[Region],Table_SourceData_PastureBeef_LiveweightGainAllStates[Season],Table_SourceData_PastureBeef_LiveweightGainAllStates[#Headers],Table_SourceData_PastureBeef_LiveweightGainAllStates[#Data],Table_AustralianStates[Common Name],Table_AustralianStates[Abbreviation]) -> 0.66 | J83: =InputFunctions_PastureBeef.LookupLiveweightFromSeason($E$7,$E$8,$D83,J$82,Table_SourceData_PastureBeef_LiveweightGainAllStates[State],Table_SourceData_PastureBeef_LiveweightGainAllStates[Region],Table_SourceData_PastureBeef_LiveweightGainAllStates[Season],Table_SourceData_PastureBeef_LiveweightGainAllStates[#Headers],Table_SourceData_PastureBeef_LiveweightGainAllStates[#Data],Table_AustralianStates[Common Name],Table_AustralianStates[Abbreviation]) -> 0.66 | K83: =InputFunctions_PastureBeef.LookupLiveweightFromSeason($E$7,$E$8,$D83,K$82,Table_SourceData_PastureBeef_LiveweightGainAllStates[State],Table_SourceData_PastureBeef_LiveweightGainAllStates[Region],Table_SourceData_PastureBeef_LiveweightGainAllStates[Season],Table_SourceData_PastureBeef_LiveweightGainAllStates[#Headers],Table_SourceData_PastureBeef_LiveweightGainAllStates[#Data],Table_AustralianStates[Common Name],Table_AustralianStates[Abbreviation]) -> 1.42 | L83: =InputFunctions_PastureBeef.LookupLiveweightFromSeason($E$7,$E$8,$D83,L$82,Table_SourceData_PastureBeef_LiveweightGainAllStates[State],Table_SourceData_PastureBeef_LiveweightGainAllStates[Region],Table_SourceData_PastureBeef_LiveweightGainAllStates[Season],Table_SourceData_PastureBeef_LiveweightGainAllStates[#Headers],Table_SourceData_PastureBeef_LiveweightGainAllStates[#Data],Table_AustralianStates[Common Name],Table_AustralianStates[Abbreviation]) -> 1.1 | ... N83: =InputFunctions_PastureBeef.LookupLiveweightFromSeason($E$7,$E$8,$D83,N$82,Table_SourceData_PastureBeef_LiveweightGainAllStates[State],Table_SourceData_PastureBeef_LiveweightGainAllStates[Region],Table_SourceData_PastureBeef_LiveweightGainAllStates[Season],Table_SourceData_PastureBeef_LiveweightGainAllStates[#Headers],Table_SourceData_PastureBeef_LiveweightGainAllStates[#Data],Table_AustralianStates[Common Name],Table_AustralianStates[Abbreviation]) -> 1.1 | O83: kg/head/day
D84: Summer | E84: =InputFunctions_PastureBeef.LookupLiveweightFromSeason($E$7,$E$8,$D84,E$82,Table_SourceData_PastureBeef_LiveweightGainAllStates[State],Table_SourceData_PastureBeef_LiveweightGainAllStates[Region],Table_SourceData_PastureBeef_LiveweightGainAllStates[Season],Table_SourceData_PastureBeef_LiveweightGainAllStates[#Headers],Table_SourceData_PastureBeef_LiveweightGainAllStates[#Data],Table_AustralianStates[Common Name],Table_AustralianStates[Abbreviation]) -> 0.44 | F84: =InputFunctions_PastureBeef.LookupLiveweightFromSeason($E$7,$E$8,$D84,F$82,Table_SourceData_PastureBeef_LiveweightGainAllStates[State],Table_SourceData_PastureBeef_LiveweightGainAllStates[Region],Table_SourceData_PastureBeef_LiveweightGainAllStates[Season],Table_SourceData_PastureBeef_LiveweightGainAllStates[#Headers],Table_SourceData_PastureBeef_LiveweightGainAllStates[#Data],Table_AustralianStates[Common Name],Table_AustralianStates[Abbreviation]) -> -0.22 | G84: =InputFunctions_PastureBeef.LookupLiveweightFromSeason($E$7,$E$8,$D84,G$82,Table_SourceData_PastureBeef_LiveweightGainAllStates[State],Table_SourceData_PastureBeef_LiveweightGainAllStates[Region],Table_SourceData_PastureBeef_LiveweightGainAllStates[Season],Table_SourceData_PastureBeef_LiveweightGainAllStates[#Headers],Table_SourceData_PastureBeef_LiveweightGainAllStates[#Data],Table_AustralianStates[Common Name],Table_AustralianStates[Abbreviation]) -> 0.44 | H84: =InputFunctions_PastureBeef.LookupLiveweightFromSeason($E$7,$E$8,$D84,H$82,Table_SourceData_PastureBeef_LiveweightGainAllStates[State],Table_SourceData_PastureBeef_LiveweightGainAllStates[Region],Table_SourceData_PastureBeef_LiveweightGainAllStates[Season],Table_SourceData_PastureBeef_LiveweightGainAllStates[#Headers],Table_SourceData_PastureBeef_LiveweightGainAllStates[#Data],Table_AustralianStates[Common Name],Table_AustralianStates[Abbreviation]) -> 0.33 | I84: =InputFunctions_PastureBeef.LookupLiveweightFromSeason($E$7,$E$8,$D84,I$82,Table_SourceData_PastureBeef_LiveweightGainAllStates[State],Table_SourceData_PastureBeef_LiveweightGainAllStates[Region],Table_SourceData_PastureBeef_LiveweightGainAllStates[Season],Table_SourceData_PastureBeef_LiveweightGainAllStates[#Headers],Table_SourceData_PastureBeef_LiveweightGainAllStates[#Data],Table_AustralianStates[Common Name],Table_AustralianStates[Abbreviation]) -> -0.22 | J84: =InputFunctions_PastureBeef.LookupLiveweightFromSeason($E$7,$E$8,$D84,J$82,Table_SourceData_PastureBeef_LiveweightGainAllStates[State],Table_SourceData_PastureBeef_LiveweightGainAllStates[Region],Table_SourceData_PastureBeef_LiveweightGainAllStates[Season],Table_SourceData_PastureBeef_LiveweightGainAllStates[#Headers],Table_SourceData_PastureBeef_LiveweightGainAllStates[#Data],Table_AustralianStates[Common Name],Table_AustralianStates[Abbreviation]) -> -0.22 | K84: =InputFunctions_PastureBeef.LookupLiveweightFromSeason($E$7,$E$8,$D84,K$82,Table_SourceData_PastureBeef_LiveweightGainAllStates[State],Table_SourceData_PastureBeef_LiveweightGainAllStates[Region],Table_SourceData_PastureBeef_LiveweightGainAllStates[Season],Table_SourceData_PastureBeef_LiveweightGainAllStates[#Headers],Table_SourceData_PastureBeef_LiveweightGainAllStates[#Data],Table_AustralianStates[Common Name],Table_AustralianStates[Abbreviation]) -> 0.44 | L84: =InputFunctions_PastureBeef.LookupLiveweightFromSeason($E$7,$E$8,$D84,L$82,Table_SourceData_PastureBeef_LiveweightGainAllStates[State],Table_SourceData_PastureBeef_LiveweightGainAllStates[Region],Table_SourceData_PastureBeef_LiveweightGainAllStates[Season],Table_SourceData_PastureBeef_LiveweightGainAllStates[#Headers],Table_SourceData_PastureBeef_LiveweightGainAllStates[#Data],Table_AustralianStates[Common Name],Table_AustralianStates[Abbreviation]) -> -0.11 | ... N84: =InputFunctions_PastureBeef.LookupLiveweightFromSeason($E$7,$E$8,$D84,N$82,Table_SourceData_PastureBeef_LiveweightGainAllStates[State],Table_SourceData_PastureBeef_LiveweightGainAllStates[Region],Table_SourceData_PastureBeef_LiveweightGainAllStates[Season],Table_SourceData_PastureBeef_LiveweightGainAllStates[#Headers],Table_SourceData_PastureBeef_LiveweightGainAllStates[#Data],Table_AustralianStates[Common Name],Table_AustralianStates[Abbreviation]) -> -0.11 | O84: kg/head/day
D85: Autumn | E85: =InputFunctions_PastureBeef.LookupLiveweightFromSeason($E$7,$E$8,$D85,E$82,Table_SourceData_PastureBeef_LiveweightGainAllStates[State],Table_SourceData_PastureBeef_LiveweightGainAllStates[Region],Table_SourceData_PastureBeef_LiveweightGainAllStates[Season],Table_SourceData_PastureBeef_LiveweightGainAllStates[#Headers],Table_SourceData_PastureBeef_LiveweightGainAllStates[#Data],Table_AustralianStates[Common Name],Table_AustralianStates[Abbreviation]) -> 0.6 | F85: =InputFunctions_PastureBeef.LookupLiveweightFromSeason($E$7,$E$8,$D85,F$82,Table_SourceData_PastureBeef_LiveweightGainAllStates[State],Table_SourceData_PastureBeef_LiveweightGainAllStates[Region],Table_SourceData_PastureBeef_LiveweightGainAllStates[Season],Table_SourceData_PastureBeef_LiveweightGainAllStates[#Headers],Table_SourceData_PastureBeef_LiveweightGainAllStates[#Data],Table_AustralianStates[Common Name],Table_AustralianStates[Abbreviation]) -> 0 | G85: =InputFunctions_PastureBeef.LookupLiveweightFromSeason($E$7,$E$8,$D85,G$82,Table_SourceData_PastureBeef_LiveweightGainAllStates[State],Table_SourceData_PastureBeef_LiveweightGainAllStates[Region],Table_SourceData_PastureBeef_LiveweightGainAllStates[Season],Table_SourceData_PastureBeef_LiveweightGainAllStates[#Headers],Table_SourceData_PastureBeef_LiveweightGainAllStates[#Data],Table_AustralianStates[Common Name],Table_AustralianStates[Abbreviation]) -> 0.6 | H85: =InputFunctions_PastureBeef.LookupLiveweightFromSeason($E$7,$E$8,$D85,H$82,Table_SourceData_PastureBeef_LiveweightGainAllStates[State],Table_SourceData_PastureBeef_LiveweightGainAllStates[Region],Table_SourceData_PastureBeef_LiveweightGainAllStates[Season],Table_SourceData_PastureBeef_LiveweightGainAllStates[#Headers],Table_SourceData_PastureBeef_LiveweightGainAllStates[#Data],Table_AustralianStates[Common Name],Table_AustralianStates[Abbreviation]) -> 0.22 | I85: =InputFunctions_PastureBeef.LookupLiveweightFromSeason($E$7,$E$8,$D85,I$82,Table_SourceData_PastureBeef_LiveweightGainAllStates[State],Table_SourceData_PastureBeef_LiveweightGainAllStates[Region],Table_SourceData_PastureBeef_LiveweightGainAllStates[Season],Table_SourceData_PastureBeef_LiveweightGainAllStates[#Headers],Table_SourceData_PastureBeef_LiveweightGainAllStates[#Data],Table_AustralianStates[Common Name],Table_AustralianStates[Abbreviation]) -> -0.55 | J85: =InputFunctions_PastureBeef.LookupLiveweightFromSeason($E$7,$E$8,$D85,J$82,Table_SourceData_PastureBeef_LiveweightGainAllStates[State],Table_SourceData_PastureBeef_LiveweightGainAllStates[Region],Table_SourceData_PastureBeef_LiveweightGainAllStates[Season],Table_SourceData_PastureBeef_LiveweightGainAllStates[#Headers],Table_SourceData_PastureBeef_LiveweightGainAllStates[#Data],Table_AustralianStates[Common Name],Table_AustralianStates[Abbreviation]) -> -0.55 | K85: =InputFunctions_PastureBeef.LookupLiveweightFromSeason($E$7,$E$8,$D85,K$82,Table_SourceData_PastureBeef_LiveweightGainAllStates[State],Table_SourceData_PastureBeef_LiveweightGainAllStates[Region],Table_SourceData_PastureBeef_LiveweightGainAllStates[Season],Table_SourceData_PastureBeef_LiveweightGainAllStates[#Headers],Table_SourceData_PastureBeef_LiveweightGainAllStates[#Data],Table_AustralianStates[Common Name],Table_AustralianStates[Abbreviation]) -> 0.6 | L85: =InputFunctions_PastureBeef.LookupLiveweightFromSeason($E$7,$E$8,$D85,L$82,Table_SourceData_PastureBeef_LiveweightGainAllStates[State],Table_SourceData_PastureBeef_LiveweightGainAllStates[Region],Table_SourceData_PastureBeef_LiveweightGainAllStates[Season],Table_SourceData_PastureBeef_LiveweightGainAllStates[#Headers],Table_SourceData_PastureBeef_LiveweightGainAllStates[#Data],Table_AustralianStates[Common Name],Table_AustralianStates[Abbreviation]) -> 0 | ... N85: =InputFunctions_PastureBeef.LookupLiveweightFromSeason($E$7,$E$8,$D85,N$82,Table_SourceData_PastureBeef_LiveweightGainAllStates[State],Table_SourceData_PastureBeef_LiveweightGainAllStates[Region],Table_SourceData_PastureBeef_LiveweightGainAllStates[Season],Table_SourceData_PastureBeef_LiveweightGainAllStates[#Headers],Table_SourceData_PastureBeef_LiveweightGainAllStates[#Data],Table_AustralianStates[Common Name],Table_AustralianStates[Abbreviation]) -> 0 | O85: kg/head/day
D86: Winter | E86: =InputFunctions_PastureBeef.LookupLiveweightFromSeason($E$7,$E$8,$D86,E$82,Table_SourceData_PastureBeef_LiveweightGainAllStates[State],Table_SourceData_PastureBeef_LiveweightGainAllStates[Region],Table_SourceData_PastureBeef_LiveweightGainAllStates[Season],Table_SourceData_PastureBeef_LiveweightGainAllStates[#Headers],Table_SourceData_PastureBeef_LiveweightGainAllStates[#Data],Table_AustralianStates[Common Name],Table_AustralianStates[Abbreviation]) -> 0.99 | F86: =InputFunctions_PastureBeef.LookupLiveweightFromSeason($E$7,$E$8,$D86,F$82,Table_SourceData_PastureBeef_LiveweightGainAllStates[State],Table_SourceData_PastureBeef_LiveweightGainAllStates[Region],Table_SourceData_PastureBeef_LiveweightGainAllStates[Season],Table_SourceData_PastureBeef_LiveweightGainAllStates[#Headers],Table_SourceData_PastureBeef_LiveweightGainAllStates[#Data],Table_AustralianStates[Common Name],Table_AustralianStates[Abbreviation]) -> 0.22 | G86: =InputFunctions_PastureBeef.LookupLiveweightFromSeason($E$7,$E$8,$D86,G$82,Table_SourceData_PastureBeef_LiveweightGainAllStates[State],Table_SourceData_PastureBeef_LiveweightGainAllStates[Region],Table_SourceData_PastureBeef_LiveweightGainAllStates[Season],Table_SourceData_PastureBeef_LiveweightGainAllStates[#Headers],Table_SourceData_PastureBeef_LiveweightGainAllStates[#Data],Table_AustralianStates[Common Name],Table_AustralianStates[Abbreviation]) -> 0.77 | H86: =InputFunctions_PastureBeef.LookupLiveweightFromSeason($E$7,$E$8,$D86,H$82,Table_SourceData_PastureBeef_LiveweightGainAllStates[State],Table_SourceData_PastureBeef_LiveweightGainAllStates[Region],Table_SourceData_PastureBeef_LiveweightGainAllStates[Season],Table_SourceData_PastureBeef_LiveweightGainAllStates[#Headers],Table_SourceData_PastureBeef_LiveweightGainAllStates[#Data],Table_AustralianStates[Common Name],Table_AustralianStates[Abbreviation]) -> 0.11 | I86: =InputFunctions_PastureBeef.LookupLiveweightFromSeason($E$7,$E$8,$D86,I$82,Table_SourceData_PastureBeef_LiveweightGainAllStates[State],Table_SourceData_PastureBeef_LiveweightGainAllStates[Region],Table_SourceData_PastureBeef_LiveweightGainAllStates[Season],Table_SourceData_PastureBeef_LiveweightGainAllStates[#Headers],Table_SourceData_PastureBeef_LiveweightGainAllStates[#Data],Table_AustralianStates[Common Name],Table_AustralianStates[Abbreviation]) -> 0.11 | J86: =InputFunctions_PastureBeef.LookupLiveweightFromSeason($E$7,$E$8,$D86,J$82,Table_SourceData_PastureBeef_LiveweightGainAllStates[State],Table_SourceData_PastureBeef_LiveweightGainAllStates[Region],Table_SourceData_PastureBeef_LiveweightGainAllStates[Season],Table_SourceData_PastureBeef_LiveweightGainAllStates[#Headers],Table_SourceData_PastureBeef_LiveweightGainAllStates[#Data],Table_AustralianStates[Common Name],Table_AustralianStates[Abbreviation]) -> 0.11 | K86: =InputFunctions_PastureBeef.LookupLiveweightFromSeason($E$7,$E$8,$D86,K$82,Table_SourceData_PastureBeef_LiveweightGainAllStates[State],Table_SourceData_PastureBeef_LiveweightGainAllStates[Region],Table_SourceData_PastureBeef_LiveweightGainAllStates[Season],Table_SourceData_PastureBeef_LiveweightGainAllStates[#Headers],Table_SourceData_PastureBeef_LiveweightGainAllStates[#Data],Table_AustralianStates[Common Name],Table_AustralianStates[Abbreviation]) -> 0.77 | L86: =InputFunctions_PastureBeef.LookupLiveweightFromSeason($E$7,$E$8,$D86,L$82,Table_SourceData_PastureBeef_LiveweightGainAllStates[State],Table_SourceData_PastureBeef_LiveweightGainAllStates[Region],Table_SourceData_PastureBeef_LiveweightGainAllStates[Season],Table_SourceData_PastureBeef_LiveweightGainAllStates[#Headers],Table_SourceData_PastureBeef_LiveweightGainAllStates[#Data],Table_AustralianStates[Common Name],Table_AustralianStates[Abbreviation]) -> 0.44 | ... N86: =InputFunctions_PastureBeef.LookupLiveweightFromSeason($E$7,$E$8,$D86,N$82,Table_SourceData_PastureBeef_LiveweightGainAllStates[State],Table_SourceData_PastureBeef_LiveweightGainAllStates[Region],Table_SourceData_PastureBeef_LiveweightGainAllStates[Season],Table_SourceData_PastureBeef_LiveweightGainAllStates[#Headers],Table_SourceData_PastureBeef_LiveweightGainAllStates[#Data],Table_AustralianStates[Common Name],Table_AustralianStates[Abbreviation]) -> 0.44 | O86: kg/head/day
D88: Method 2 custom values (edit if known) | E88: Bulls < 1 year | F88: Bulls > 1 year | G88: Cows < 1 year | H88: Cows 1-2 years | I88: Cows 2-3 years | J88: Cows > 3 years | K88: Steers < 1 year | L88: Steers 1-2 years | M88: Steers 2-3 years | N88: Steers >3 years
D89: =TEXT(X_Cell_Site_StartDate, "mmmm yyyy") -> January 2025 | E89: =InputFunctions_PastureBeef.LookupLiveweightFromMonth($E$7,$E$8,$D89,E$88,Table_SourceData_PastureBeef_LiveweightGainAllStates[State],Table_SourceData_PastureBeef_LiveweightGainAllStates[Region],Table_SourceData_PastureBeef_LiveweightGainAllStates[Season],Table_SourceData_PastureBeef_LiveweightGainAllStates[#Headers],Table_SourceData_PastureBeef_LiveweightGainAllStates[#Data],Table_AustralianStates[Common Name],Table_AustralianStates[Abbreviation],Table_SourceData_Common_MonthToSeason[Month],Table_SourceData_Common_MonthToSeason[Season]) -> 0.44 | F89: =InputFunctions_PastureBeef.LookupLiveweightFromMonth($E$7,$E$8,$D89,F$88,Table_SourceData_PastureBeef_LiveweightGainAllStates[State],Table_SourceData_PastureBeef_LiveweightGainAllStates[Region],Table_SourceData_PastureBeef_LiveweightGainAllStates[Season],Table_SourceData_PastureBeef_LiveweightGainAllStates[#Headers],Table_SourceData_PastureBeef_LiveweightGainAllStates[#Data],Table_AustralianStates[Common Name],Table_AustralianStates[Abbreviation],Table_SourceData_Common_MonthToSeason[Month],Table_SourceData_Common_MonthToSeason[Season]) -> -0.22 | G89: =InputFunctions_PastureBeef.LookupLiveweightFromMonth($E$7,$E$8,$D89,G$88,Table_SourceData_PastureBeef_LiveweightGainAllStates[State],Table_SourceData_PastureBeef_LiveweightGainAllStates[Region],Table_SourceData_PastureBeef_LiveweightGainAllStates[Season],Table_SourceData_PastureBeef_LiveweightGainAllStates[#Headers],Table_SourceData_PastureBeef_LiveweightGainAllStates[#Data],Table_AustralianStates[Common Name],Table_AustralianStates[Abbreviation],Table_SourceData_Common_MonthToSeason[Month],Table_SourceData_Common_MonthToSeason[Season]) -> 0.44 | H89: =InputFunctions_PastureBeef.LookupLiveweightFromMonth($E$7,$E$8,$D89,H$88,Table_SourceData_PastureBeef_LiveweightGainAllStates[State],Table_SourceData_PastureBeef_LiveweightGainAllStates[Region],Table_SourceData_PastureBeef_LiveweightGainAllStates[Season],Table_SourceData_PastureBeef_LiveweightGainAllStates[#Headers],Table_SourceData_PastureBeef_LiveweightGainAllStates[#Data],Table_AustralianStates[Common Name],Table_AustralianStates[Abbreviation],Table_SourceData_Common_MonthToSeason[Month],Table_SourceData_Common_MonthToSeason[Season]) -> 0.33 | I89: =InputFunctions_PastureBeef.LookupLiveweightFromMonth($E$7,$E$8,$D89,I$88,Table_SourceData_PastureBeef_LiveweightGainAllStates[State],Table_SourceData_PastureBeef_LiveweightGainAllStates[Region],Table_SourceData_PastureBeef_LiveweightGainAllStates[Season],Table_SourceData_PastureBeef_LiveweightGainAllStates[#Headers],Table_SourceData_PastureBeef_LiveweightGainAllStates[#Data],Table_AustralianStates[Common Name],Table_AustralianStates[Abbreviation],Table_SourceData_Common_MonthToSeason[Month],Table_SourceData_Common_MonthToSeason[Season]) -> -0.22 | J89: =InputFunctions_PastureBeef.LookupLiveweightFromMonth($E$7,$E$8,$D89,J$88,Table_SourceData_PastureBeef_LiveweightGainAllStates[State],Table_SourceData_PastureBeef_LiveweightGainAllStates[Region],Table_SourceData_PastureBeef_LiveweightGainAllStates[Season],Table_SourceData_PastureBeef_LiveweightGainAllStates[#Headers],Table_SourceData_PastureBeef_LiveweightGainAllStates[#Data],Table_AustralianStates[Common Name],Table_AustralianStates[Abbreviation],Table_SourceData_Common_MonthToSeason[Month],Table_SourceData_Common_MonthToSeason[Season]) -> -0.22 | K89: =InputFunctions_PastureBeef.LookupLiveweightFromMonth($E$7,$E$8,$D89,K$88,Table_SourceData_PastureBeef_LiveweightGainAllStates[State],Table_SourceData_PastureBeef_LiveweightGainAllStates[Region],Table_SourceData_PastureBeef_LiveweightGainAllStates[Season],Table_SourceData_PastureBeef_LiveweightGainAllStates[#Headers],Table_SourceData_PastureBeef_LiveweightGainAllStates[#Data],Table_AustralianStates[Common Name],Table_AustralianStates[Abbreviation],Table_SourceData_Common_MonthToSeason[Month],Table_SourceData_Common_MonthToSeason[Season]) -> 0.44 | L89: =InputFunctions_PastureBeef.LookupLiveweightFromMonth($E$7,$E$8,$D89,L$88,Table_SourceData_PastureBeef_LiveweightGainAllStates[State],Table_SourceData_PastureBeef_LiveweightGainAllStates[Region],Table_SourceData_PastureBeef_LiveweightGainAllStates[Season],Table_SourceData_PastureBeef_LiveweightGainAllStates[#Headers],Table_SourceData_PastureBeef_LiveweightGainAllStates[#Data],Table_AustralianStates[Common Name],Table_AustralianStates[Abbreviation],Table_SourceData_Common_MonthToSeason[Month],Table_SourceData_Common_MonthToSeason[Season]) -> -0.11 | ... N89: =InputFunctions_PastureBeef.LookupLiveweightFromMonth($E$7,$E$8,$D89,N$88,Table_SourceData_PastureBeef_LiveweightGainAllStates[State],Table_SourceData_PastureBeef_LiveweightGainAllStates[Region],Table_SourceData_PastureBeef_LiveweightGainAllStates[Season],Table_SourceData_PastureBeef_LiveweightGainAllStates[#Headers],Table_SourceData_PastureBeef_LiveweightGainAllStates[#Data],Table_AustralianStates[Common Name],Table_AustralianStates[Abbreviation],Table_SourceData_Common_MonthToSeason[Month],Table_SourceData_Common_MonthToSeason[Season]) -> -0.11 | O89: kg/head/day
D90: =TEXT(EDATE(X_Cell_Site_StartDate,1), "mmmm yyyy") -> February 2025 | E90: =InputFunctions_PastureBeef.LookupLiveweightFromMonth($E$7,$E$8,$D90,E$88,Table_SourceData_PastureBeef_LiveweightGainAllStates[State],Table_SourceData_PastureBeef_LiveweightGainAllStates[Region],Table_SourceData_PastureBeef_LiveweightGainAllStates[Season],Table_SourceData_PastureBeef_LiveweightGainAllStates[#Headers],Table_SourceData_PastureBeef_LiveweightGainAllStates[#Data],Table_AustralianStates[Common Name],Table_AustralianStates[Abbreviation],Table_SourceData_Common_MonthToSeason[Month],Table_SourceData_Common_MonthToSeason[Season]) -> 0.44 | F90: =InputFunctions_PastureBeef.LookupLiveweightFromMonth($E$7,$E$8,$D90,F$88,Table_SourceData_PastureBeef_LiveweightGainAllStates[State],Table_SourceData_PastureBeef_LiveweightGainAllStates[Region],Table_SourceData_PastureBeef_LiveweightGainAllStates[Season],Table_SourceData_PastureBeef_LiveweightGainAllStates[#Headers],Table_SourceData_PastureBeef_LiveweightGainAllStates[#Data],Table_AustralianStates[Common Name],Table_AustralianStates[Abbreviation],Table_SourceData_Common_MonthToSeason[Month],Table_SourceData_Common_MonthToSeason[Season]) -> -0.22 | G90: =InputFunctions_PastureBeef.LookupLiveweightFromMonth($E$7,$E$8,$D90,G$88,Table_SourceData_PastureBeef_LiveweightGainAllStates[State],Table_SourceData_PastureBeef_LiveweightGainAllStates[Region],Table_SourceData_PastureBeef_LiveweightGainAllStates[Season],Table_SourceData_PastureBeef_LiveweightGainAllStates[#Headers],Table_SourceData_PastureBeef_LiveweightGainAllStates[#Data],Table_AustralianStates[Common Name],Table_AustralianStates[Abbreviation],Table_SourceData_Common_MonthToSeason[Month],Table_SourceData_Common_MonthToSeason[Season]) -> 0.44 | H90: =InputFunctions_PastureBeef.LookupLiveweightFromMonth($E$7,$E$8,$D90,H$88,Table_SourceData_PastureBeef_LiveweightGainAllStates[State],Table_SourceData_PastureBeef_LiveweightGainAllStates[Region],Table_SourceData_PastureBeef_LiveweightGainAllStates[Season],Table_SourceData_PastureBeef_LiveweightGainAllStates[#Headers],Table_SourceData_PastureBeef_LiveweightGainAllStates[#Data],Table_AustralianStates[Common Name],Table_AustralianStates[Abbreviation],Table_SourceData_Common_MonthToSeason[Month],Table_SourceData_Common_MonthToSeason[Season]) -> 0.33 | I90: =InputFunctions_PastureBeef.LookupLiveweightFromMonth($E$7,$E$8,$D90,I$88,Table_SourceData_PastureBeef_LiveweightGainAllStates[State],Table_SourceData_PastureBeef_LiveweightGainAllStates[Region],Table_SourceData_PastureBeef_LiveweightGainAllStates[Season],Table_SourceData_PastureBeef_LiveweightGainAllStates[#Headers],Table_SourceData_PastureBeef_LiveweightGainAllStates[#Data],Table_AustralianStates[Common Name],Table_AustralianStates[Abbreviation],Table_SourceData_Common_MonthToSeason[Month],Table_SourceData_Common_MonthToSeason[Season]) -> -0.22 | J90: =InputFunctions_PastureBeef.LookupLiveweightFromMonth($E$7,$E$8,$D90,J$88,Table_SourceData_PastureBeef_LiveweightGainAllStates[State],Table_SourceData_PastureBeef_LiveweightGainAllStates[Region],Table_SourceData_PastureBeef_LiveweightGainAllStates[Season],Table_SourceData_PastureBeef_LiveweightGainAllStates[#Headers],Table_SourceData_PastureBeef_LiveweightGainAllStates[#Data],Table_AustralianStates[Common Name],Table_AustralianStates[Abbreviation],Table_SourceData_Common_MonthToSeason[Month],Table_SourceData_Common_MonthToSeason[Season]) -> -0.22 | K90: =InputFunctions_PastureBeef.LookupLiveweightFromMonth($E$7,$E$8,$D90,K$88,Table_SourceData_PastureBeef_LiveweightGainAllStates[State],Table_SourceData_PastureBeef_LiveweightGainAllStates[Region],Table_SourceData_PastureBeef_LiveweightGainAllStates[Season],Table_SourceData_PastureBeef_LiveweightGainAllStates[#Headers],Table_SourceData_PastureBeef_LiveweightGainAllStates[#Data],Table_AustralianStates[Common Name],Table_AustralianStates[Abbreviation],Table_SourceData_Common_MonthToSeason[Month],Table_SourceData_Common_MonthToSeason[Season]) -> 0.44 | L90: =InputFunctions_PastureBeef.LookupLiveweightFromMonth($E$7,$E$8,$D90,L$88,Table_SourceData_PastureBeef_LiveweightGainAllStates[State],Table_SourceData_PastureBeef_LiveweightGainAllStates[Region],Table_SourceData_PastureBeef_LiveweightGainAllStates[Season],Table_SourceData_PastureBeef_LiveweightGainAllStates[#Headers],Table_SourceData_PastureBeef_LiveweightGainAllStates[#Data],Table_AustralianStates[Common Name],Table_AustralianStates[Abbreviation],Table_SourceData_Common_MonthToSeason[Month],Table_SourceData_Common_MonthToSeason[Season]) -> -0.11 | ... N90: =InputFunctions_PastureBeef.LookupLiveweightFromMonth($E$7,$E$8,$D90,N$88,Table_SourceData_PastureBeef_LiveweightGainAllStates[State],Table_SourceData_PastureBeef_LiveweightGainAllStates[Region],Table_SourceData_PastureBeef_LiveweightGainAllStates[Season],Table_SourceData_PastureBeef_LiveweightGainAllStates[#Headers],Table_SourceData_PastureBeef_LiveweightGainAllStates[#Data],Table_AustralianStates[Common Name],Table_AustralianStates[Abbreviation],Table_SourceData_Common_MonthToSeason[Month],Table_SourceData_Common_MonthToSeason[Season]) -> -0.11 | O90: kg/head/day
D91: =TEXT(EDATE(X_Cell_Site_StartDate,2), "mmmm yyyy") -> March 2025 | E91: =InputFunctions_PastureBeef.LookupLiveweightFromMonth($E$7,$E$8,$D91,E$88,Table_SourceData_PastureBeef_LiveweightGainAllStates[State],Table_SourceData_PastureBeef_LiveweightGainAllStates[Region],Table_SourceData_PastureBeef_LiveweightGainAllStates[Season],Table_SourceData_PastureBeef_LiveweightGainAllStates[#Headers],Table_SourceData_PastureBeef_LiveweightGainAllStates[#Data],Table_AustralianStates[Common Name],Table_AustralianStates[Abbreviation],Table_SourceData_Common_MonthToSeason[Month],Table_SourceData_Common_MonthToSeason[Season]) -> 0.6 | F91: =InputFunctions_PastureBeef.LookupLiveweightFromMonth($E$7,$E$8,$D91,F$88,Table_SourceData_PastureBeef_LiveweightGainAllStates[State],Table_SourceData_PastureBeef_LiveweightGainAllStates[Region],Table_SourceData_PastureBeef_LiveweightGainAllStates[Season],Table_SourceData_PastureBeef_LiveweightGainAllStates[#Headers],Table_SourceData_PastureBeef_LiveweightGainAllStates[#Data],Table_AustralianStates[Common Name],Table_AustralianStates[Abbreviation],Table_SourceData_Common_MonthToSeason[Month],Table_SourceData_Common_MonthToSeason[Season]) -> 0 | G91: =InputFunctions_PastureBeef.LookupLiveweightFromMonth($E$7,$E$8,$D91,G$88,Table_SourceData_PastureBeef_LiveweightGainAllStates[State],Table_SourceData_PastureBeef_LiveweightGainAllStates[Region],Table_SourceData_PastureBeef_LiveweightGainAllStates[Season],Table_SourceData_PastureBeef_LiveweightGainAllStates[#Headers],Table_SourceData_PastureBeef_LiveweightGainAllStates[#Data],Table_AustralianStates[Common Name],Table_AustralianStates[Abbreviation],Table_SourceData_Common_MonthToSeason[Month],Table_SourceData_Common_MonthToSeason[Season]) -> 0.6 | H91: =InputFunctions_PastureBeef.LookupLiveweightFromMonth($E$7,$E$8,$D91,H$88,Table_SourceData_PastureBeef_LiveweightGainAllStates[State],Table_SourceData_PastureBeef_LiveweightGainAllStates[Region],Table_SourceData_PastureBeef_LiveweightGainAllStates[Season],Table_SourceData_PastureBeef_LiveweightGainAllStates[#Headers],Table_SourceData_PastureBeef_LiveweightGainAllStates[#Data],Table_AustralianStates[Common Name],Table_AustralianStates[Abbreviation],Table_SourceData_Common_MonthToSeason[Month],Table_SourceData_Common_MonthToSeason[Season]) -> 0.22 | I91: =InputFunctions_PastureBeef.LookupLiveweightFromMonth($E$7,$E$8,$D91,I$88,Table_SourceData_PastureBeef_LiveweightGainAllStates[State],Table_SourceData_PastureBeef_LiveweightGainAllStates[Region],Table_SourceData_PastureBeef_LiveweightGainAllStates[Season],Table_SourceData_PastureBeef_LiveweightGainAllStates[#Headers],Table_SourceData_PastureBeef_LiveweightGainAllStates[#Data],Table_AustralianStates[Common Name],Table_AustralianStates[Abbreviation],Table_SourceData_Common_MonthToSeason[Month],Table_SourceData_Common_MonthToSeason[Season]) -> -0.55 | J91: =InputFunctions_PastureBeef.LookupLiveweightFromMonth($E$7,$E$8,$D91,J$88,Table_SourceData_PastureBeef_LiveweightGainAllStates[State],Table_SourceData_PastureBeef_LiveweightGainAllStates[Region],Table_SourceData_PastureBeef_LiveweightGainAllStates[Season],Table_SourceData_PastureBeef_LiveweightGainAllStates[#Headers],Table_SourceData_PastureBeef_LiveweightGainAllStates[#Data],Table_AustralianStates[Common Name],Table_AustralianStates[Abbreviation],Table_SourceData_Common_MonthToSeason[Month],Table_SourceData_Common_MonthToSeason[Season]) -> -0.55 | K91: =InputFunctions_PastureBeef.LookupLiveweightFromMonth($E$7,$E$8,$D91,K$88,Table_SourceData_PastureBeef_LiveweightGainAllStates[State],Table_SourceData_PastureBeef_LiveweightGainAllStates[Region],Table_SourceData_PastureBeef_LiveweightGainAllStates[Season],Table_SourceData_PastureBeef_LiveweightGainAllStates[#Headers],Table_SourceData_PastureBeef_LiveweightGainAllStates[#Data],Table_AustralianStates[Common Name],Table_AustralianStates[Abbreviation],Table_SourceData_Common_MonthToSeason[Month],Table_SourceData_Common_MonthToSeason[Season]) -> 0.6 | L91: =InputFunctions_PastureBeef.LookupLiveweightFromMonth($E$7,$E$8,$D91,L$88,Table_SourceData_PastureBeef_LiveweightGainAllStates[State],Table_SourceData_PastureBeef_LiveweightGainAllStates[Region],Table_SourceData_PastureBeef_LiveweightGainAllStates[Season],Table_SourceData_PastureBeef_LiveweightGainAllStates[#Headers],Table_SourceData_PastureBeef_LiveweightGainAllStates[#Data],Table_AustralianStates[Common Name],Table_AustralianStates[Abbreviation],Table_SourceData_Common_MonthToSeason[Month],Table_SourceData_Common_MonthToSeason[Season]) -> 0 | ... N91: =InputFunctions_PastureBeef.LookupLiveweightFromMonth($E$7,$E$8,$D91,N$88,Table_SourceData_PastureBeef_LiveweightGainAllStates[State],Table_SourceData_PastureBeef_LiveweightGainAllStates[Region],Table_SourceData_PastureBeef_LiveweightGainAllStates[Season],Table_SourceData_PastureBeef_LiveweightGainAllStates[#Headers],Table_SourceData_PastureBeef_LiveweightGainAllStates[#Data],Table_AustralianStates[Common Name],Table_AustralianStates[Abbreviation],Table_SourceData_Common_MonthToSeason[Month],Table_SourceData_Common_MonthToSeason[Season]) -> 0 | O91: kg/head/day
D92: =TEXT(EDATE(X_Cell_Site_StartDate,3), "mmmm yyyy") -> April 2025 | E92: =InputFunctions_PastureBeef.LookupLiveweightFromMonth($E$7,$E$8,$D92,E$88,Table_SourceData_PastureBeef_LiveweightGainAllStates[State],Table_SourceData_PastureBeef_LiveweightGainAllStates[Region],Table_SourceData_PastureBeef_LiveweightGainAllStates[Season],Table_SourceData_PastureBeef_LiveweightGainAllStates[#Headers],Table_SourceData_PastureBeef_LiveweightGainAllStates[#Data],Table_AustralianStates[Common Name],Table_AustralianStates[Abbreviation],Table_SourceData_Common_MonthToSeason[Month],Table_SourceData_Common_MonthToSeason[Season]) -> 0.6 | F92: =InputFunctions_PastureBeef.LookupLiveweightFromMonth($E$7,$E$8,$D92,F$88,Table_SourceData_PastureBeef_LiveweightGainAllStates[State],Table_SourceData_PastureBeef_LiveweightGainAllStates[Region],Table_SourceData_PastureBeef_LiveweightGainAllStates[Season],Table_SourceData_PastureBeef_LiveweightGainAllStates[#Headers],Table_SourceData_PastureBeef_LiveweightGainAllStates[#Data],Table_AustralianStates[Common Name],Table_AustralianStates[Abbreviation],Table_SourceData_Common_MonthToSeason[Month],Table_SourceData_Common_MonthToSeason[Season]) -> 0 | G92: =InputFunctions_PastureBeef.LookupLiveweightFromMonth($E$7,$E$8,$D92,G$88,Table_SourceData_PastureBeef_LiveweightGainAllStates[State],Table_SourceData_PastureBeef_LiveweightGainAllStates[Region],Table_SourceData_PastureBeef_LiveweightGainAllStates[Season],Table_SourceData_PastureBeef_LiveweightGainAllStates[#Headers],Table_SourceData_PastureBeef_LiveweightGainAllStates[#Data],Table_AustralianStates[Common Name],Table_AustralianStates[Abbreviation],Table_SourceData_Common_MonthToSeason[Month],Table_SourceData_Common_MonthToSeason[Season]) -> 0.6 | H92: =InputFunctions_PastureBeef.LookupLiveweightFromMonth($E$7,$E$8,$D92,H$88,Table_SourceData_PastureBeef_LiveweightGainAllStates[State],Table_SourceData_PastureBeef_LiveweightGainAllStates[Region],Table_SourceData_PastureBeef_LiveweightGainAllStates[Season],Table_SourceData_PastureBeef_LiveweightGainAllStates[#Headers],Table_SourceData_PastureBeef_LiveweightGainAllStates[#Data],Table_AustralianStates[Common Name],Table_AustralianStates[Abbreviation],Table_SourceData_Common_MonthToSeason[Month],Table_SourceData_Common_MonthToSeason[Season]) -> 0.22 | I92: =InputFunctions_PastureBeef.LookupLiveweightFromMonth($E$7,$E$8,$D92,I$88,Table_SourceData_PastureBeef_LiveweightGainAllStates[State],Table_SourceData_PastureBeef_LiveweightGainAllStates[Region],Table_SourceData_PastureBeef_LiveweightGainAllStates[Season],Table_SourceData_PastureBeef_LiveweightGainAllStates[#Headers],Table_SourceData_PastureBeef_LiveweightGainAllStates[#Data],Table_AustralianStates[Common Name],Table_AustralianStates[Abbreviation],Table_SourceData_Common_MonthToSeason[Month],Table_SourceData_Common_MonthToSeason[Season]) -> -0.55 | J92: =InputFunctions_PastureBeef.LookupLiveweightFromMonth($E$7,$E$8,$D92,J$88,Table_SourceData_PastureBeef_LiveweightGainAllStates[State],Table_SourceData_PastureBeef_LiveweightGainAllStates[Region],Table_SourceData_PastureBeef_LiveweightGainAllStates[Season],Table_SourceData_PastureBeef_LiveweightGainAllStates[#Headers],Table_SourceData_PastureBeef_LiveweightGainAllStates[#Data],Table_AustralianStates[Common Name],Table_AustralianStates[Abbreviation],Table_SourceData_Common_MonthToSeason[Month],Table_SourceData_Common_MonthToSeason[Season]) -> -0.55 | K92: =InputFunctions_PastureBeef.LookupLiveweightFromMonth($E$7,$E$8,$D92,K$88,Table_SourceData_PastureBeef_LiveweightGainAllStates[State],Table_SourceData_PastureBeef_LiveweightGainAllStates[Region],Table_SourceData_PastureBeef_LiveweightGainAllStates[Season],Table_SourceData_PastureBeef_LiveweightGainAllStates[#Headers],Table_SourceData_PastureBeef_LiveweightGainAllStates[#Data],Table_AustralianStates[Common Name],Table_AustralianStates[Abbreviation],Table_SourceData_Common_MonthToSeason[Month],Table_SourceData_Common_MonthToSeason[Season]) -> 0.6 | L92: =InputFunctions_PastureBeef.LookupLiveweightFromMonth($E$7,$E$8,$D92,L$88,Table_SourceData_PastureBeef_LiveweightGainAllStates[State],Table_SourceData_PastureBeef_LiveweightGainAllStates[Region],Table_SourceData_PastureBeef_LiveweightGainAllStates[Season],Table_SourceData_PastureBeef_LiveweightGainAllStates[#Headers],Table_SourceData_PastureBeef_LiveweightGainAllStates[#Data],Table_AustralianStates[Common Name],Table_AustralianStates[Abbreviation],Table_SourceData_Common_MonthToSeason[Month],Table_SourceData_Common_MonthToSeason[Season]) -> 0 | ... N92: =InputFunctions_PastureBeef.LookupLiveweightFromMonth($E$7,$E$8,$D92,N$88,Table_SourceData_PastureBeef_LiveweightGainAllStates[State],Table_SourceData_PastureBeef_LiveweightGainAllStates[Region],Table_SourceData_PastureBeef_LiveweightGainAllStates[Season],Table_SourceData_PastureBeef_LiveweightGainAllStates[#Headers],Table_SourceData_PastureBeef_LiveweightGainAllStates[#Data],Table_AustralianStates[Common Name],Table_AustralianStates[Abbreviation],Table_SourceData_Common_MonthToSeason[Month],Table_SourceData_Common_MonthToSeason[Season]) -> 0 | O92: kg/head/day
D93: =TEXT(EDATE(X_Cell_Site_StartDate,4), "mmmm yyyy") -> May 2025 | E93: =InputFunctions_PastureBeef.LookupLiveweightFromMonth($E$7,$E$8,$D93,E$88,Table_SourceData_PastureBeef_LiveweightGainAllStates[State],Table_SourceData_PastureBeef_LiveweightGainAllStates[Region],Table_SourceData_PastureBeef_LiveweightGainAllStates[Season],Table_SourceData_PastureBeef_LiveweightGainAllStates[#Headers],Table_SourceData_PastureBeef_LiveweightGainAllStates[#Data],Table_AustralianStates[Common Name],Table_AustralianStates[Abbreviation],Table_SourceData_Common_MonthToSeason[Month],Table_SourceData_Common_MonthToSeason[Season]) -> 0.6 | F93: =InputFunctions_PastureBeef.LookupLiveweightFromMonth($E$7,$E$8,$D93,F$88,Table_SourceData_PastureBeef_LiveweightGainAllStates[State],Table_SourceData_PastureBeef_LiveweightGainAllStates[Region],Table_SourceData_PastureBeef_LiveweightGainAllStates[Season],Table_SourceData_PastureBeef_LiveweightGainAllStates[#Headers],Table_SourceData_PastureBeef_LiveweightGainAllStates[#Data],Table_AustralianStates[Common Name],Table_AustralianStates[Abbreviation],Table_SourceData_Common_MonthToSeason[Month],Table_SourceData_Common_MonthToSeason[Season]) -> 0 | G93: =InputFunctions_PastureBeef.LookupLiveweightFromMonth($E$7,$E$8,$D93,G$88,Table_SourceData_PastureBeef_LiveweightGainAllStates[State],Table_SourceData_PastureBeef_LiveweightGainAllStates[Region],Table_SourceData_PastureBeef_LiveweightGainAllStates[Season],Table_SourceData_PastureBeef_LiveweightGainAllStates[#Headers],Table_SourceData_PastureBeef_LiveweightGainAllStates[#Data],Table_AustralianStates[Common Name],Table_AustralianStates[Abbreviation],Table_SourceData_Common_MonthToSeason[Month],Table_SourceData_Common_MonthToSeason[Season]) -> 0.6 | H93: =InputFunctions_PastureBeef.LookupLiveweightFromMonth($E$7,$E$8,$D93,H$88,Table_SourceData_PastureBeef_LiveweightGainAllStates[State],Table_SourceData_PastureBeef_LiveweightGainAllStates[Region],Table_SourceData_PastureBeef_LiveweightGainAllStates[Season],Table_SourceData_PastureBeef_LiveweightGainAllStates[#Headers],Table_SourceData_PastureBeef_LiveweightGainAllStates[#Data],Table_AustralianStates[Common Name],Table_AustralianStates[Abbreviation],Table_SourceData_Common_MonthToSeason[Month],Table_SourceData_Common_MonthToSeason[Season]) -> 0.22 | I93: =InputFunctions_PastureBeef.LookupLiveweightFromMonth($E$7,$E$8,$D93,I$88,Table_SourceData_PastureBeef_LiveweightGainAllStates[State],Table_SourceData_PastureBeef_LiveweightGainAllStates[Region],Table_SourceData_PastureBeef_LiveweightGainAllStates[Season],Table_SourceData_PastureBeef_LiveweightGainAllStates[#Headers],Table_SourceData_PastureBeef_LiveweightGainAllStates[#Data],Table_AustralianStates[Common Name],Table_AustralianStates[Abbreviation],Table_SourceData_Common_MonthToSeason[Month],Table_SourceData_Common_MonthToSeason[Season]) -> -0.55 | J93: =InputFunctions_PastureBeef.LookupLiveweightFromMonth($E$7,$E$8,$D93,J$88,Table_SourceData_PastureBeef_LiveweightGainAllStates[State],Table_SourceData_PastureBeef_LiveweightGainAllStates[Region],Table_SourceData_PastureBeef_LiveweightGainAllStates[Season],Table_SourceData_PastureBeef_LiveweightGainAllStates[#Headers],Table_SourceData_PastureBeef_LiveweightGainAllStates[#Data],Table_AustralianStates[Common Name],Table_AustralianStates[Abbreviation],Table_SourceData_Common_MonthToSeason[Month],Table_SourceData_Common_MonthToSeason[Season]) -> -0.55 | K93: =InputFunctions_PastureBeef.LookupLiveweightFromMonth($E$7,$E$8,$D93,K$88,Table_SourceData_PastureBeef_LiveweightGainAllStates[State],Table_SourceData_PastureBeef_LiveweightGainAllStates[Region],Table_SourceData_PastureBeef_LiveweightGainAllStates[Season],Table_SourceData_PastureBeef_LiveweightGainAllStates[#Headers],Table_SourceData_PastureBeef_LiveweightGainAllStates[#Data],Table_AustralianStates[Common Name],Table_AustralianStates[Abbreviation],Table_SourceData_Common_MonthToSeason[Month],Table_SourceData_Common_MonthToSeason[Season]) -> 0.6 | L93: =InputFunctions_PastureBeef.LookupLiveweightFromMonth($E$7,$E$8,$D93,L$88,Table_SourceData_PastureBeef_LiveweightGainAllStates[State],Table_SourceData_PastureBeef_LiveweightGainAllStates[Region],Table_SourceData_PastureBeef_LiveweightGainAllStates[Season],Table_SourceData_PastureBeef_LiveweightGainAllStates[#Headers],Table_SourceData_PastureBeef_LiveweightGainAllStates[#Data],Table_AustralianStates[Common Name],Table_AustralianStates[Abbreviation],Table_SourceData_Common_MonthToSeason[Month],Table_SourceData_Common_MonthToSeason[Season]) -> 0 | ... N93: =InputFunctions_PastureBeef.LookupLiveweightFromMonth($E$7,$E$8,$D93,N$88,Table_SourceData_PastureBeef_LiveweightGainAllStates[State],Table_SourceData_PastureBeef_LiveweightGainAllStates[Region],Table_SourceData_PastureBeef_LiveweightGainAllStates[Season],Table_SourceData_PastureBeef_LiveweightGainAllStates[#Headers],Table_SourceData_PastureBeef_LiveweightGainAllStates[#Data],Table_AustralianStates[Common Name],Table_AustralianStates[Abbreviation],Table_SourceData_Common_MonthToSeason[Month],Table_SourceData_Common_MonthToSeason[Season]) -> 0 | O93: kg/head/day
D94: =TEXT(EDATE(X_Cell_Site_StartDate,5), "mmmm yyyy") -> June 2025 | E94: =InputFunctions_PastureBeef.LookupLiveweightFromMonth($E$7,$E$8,$D94,E$88,Table_SourceData_PastureBeef_LiveweightGainAllStates[State],Table_SourceData_PastureBeef_LiveweightGainAllStates[Region],Table_SourceData_PastureBeef_LiveweightGainAllStates[Season],Table_SourceData_PastureBeef_LiveweightGainAllStates[#Headers],Table_SourceData_PastureBeef_LiveweightGainAllStates[#Data],Table_AustralianStates[Common Name],Table_AustralianStates[Abbreviation],Table_SourceData_Common_MonthToSeason[Month],Table_SourceData_Common_MonthToSeason[Season]) -> 0.99 | F94: =InputFunctions_PastureBeef.LookupLiveweightFromMonth($E$7,$E$8,$D94,F$88,Table_SourceData_PastureBeef_LiveweightGainAllStates[State],Table_SourceData_PastureBeef_LiveweightGainAllStates[Region],Table_SourceData_PastureBeef_LiveweightGainAllStates[Season],Table_SourceData_PastureBeef_LiveweightGainAllStates[#Headers],Table_SourceData_PastureBeef_LiveweightGainAllStates[#Data],Table_AustralianStates[Common Name],Table_AustralianStates[Abbreviation],Table_SourceData_Common_MonthToSeason[Month],Table_SourceData_Common_MonthToSeason[Season]) -> 0.22 | G94: =InputFunctions_PastureBeef.LookupLiveweightFromMonth($E$7,$E$8,$D94,G$88,Table_SourceData_PastureBeef_LiveweightGainAllStates[State],Table_SourceData_PastureBeef_LiveweightGainAllStates[Region],Table_SourceData_PastureBeef_LiveweightGainAllStates[Season],Table_SourceData_PastureBeef_LiveweightGainAllStates[#Headers],Table_SourceData_PastureBeef_LiveweightGainAllStates[#Data],Table_AustralianStates[Common Name],Table_AustralianStates[Abbreviation],Table_SourceData_Common_MonthToSeason[Month],Table_SourceData_Common_MonthToSeason[Season]) -> 0.77 | H94: =InputFunctions_PastureBeef.LookupLiveweightFromMonth($E$7,$E$8,$D94,H$88,Table_SourceData_PastureBeef_LiveweightGainAllStates[State],Table_SourceData_PastureBeef_LiveweightGainAllStates[Region],Table_SourceData_PastureBeef_LiveweightGainAllStates[Season],Table_SourceData_PastureBeef_LiveweightGainAllStates[#Headers],Table_SourceData_PastureBeef_LiveweightGainAllStates[#Data],Table_AustralianStates[Common Name],Table_AustralianStates[Abbreviation],Table_SourceData_Common_MonthToSeason[Month],Table_SourceData_Common_MonthToSeason[Season]) -> 0.11 | I94: =InputFunctions_PastureBeef.LookupLiveweightFromMonth($E$7,$E$8,$D94,I$88,Table_SourceData_PastureBeef_LiveweightGainAllStates[State],Table_SourceData_PastureBeef_LiveweightGainAllStates[Region],Table_SourceData_PastureBeef_LiveweightGainAllStates[Season],Table_SourceData_PastureBeef_LiveweightGainAllStates[#Headers],Table_SourceData_PastureBeef_LiveweightGainAllStates[#Data],Table_AustralianStates[Common Name],Table_AustralianStates[Abbreviation],Table_SourceData_Common_MonthToSeason[Month],Table_SourceData_Common_MonthToSeason[Season]) -> 0.11 | J94: =InputFunctions_PastureBeef.LookupLiveweightFromMonth($E$7,$E$8,$D94,J$88,Table_SourceData_PastureBeef_LiveweightGainAllStates[State],Table_SourceData_PastureBeef_LiveweightGainAllStates[Region],Table_SourceData_PastureBeef_LiveweightGainAllStates[Season],Table_SourceData_PastureBeef_LiveweightGainAllStates[#Headers],Table_SourceData_PastureBeef_LiveweightGainAllStates[#Data],Table_AustralianStates[Common Name],Table_AustralianStates[Abbreviation],Table_SourceData_Common_MonthToSeason[Month],Table_SourceData_Common_MonthToSeason[Season]) -> 0.11 | K94: =InputFunctions_PastureBeef.LookupLiveweightFromMonth($E$7,$E$8,$D94,K$88,Table_SourceData_PastureBeef_LiveweightGainAllStates[State],Table_SourceData_PastureBeef_LiveweightGainAllStates[Region],Table_SourceData_PastureBeef_LiveweightGainAllStates[Season],Table_SourceData_PastureBeef_LiveweightGainAllStates[#Headers],Table_SourceData_PastureBeef_LiveweightGainAllStates[#Data],Table_AustralianStates[Common Name],Table_AustralianStates[Abbreviation],Table_SourceData_Common_MonthToSeason[Month],Table_SourceData_Common_MonthToSeason[Season]) -> 0.77 | L94: =InputFunctions_PastureBeef.LookupLiveweightFromMonth($E$7,$E$8,$D94,L$88,Table_SourceData_PastureBeef_LiveweightGainAllStates[State],Table_SourceData_PastureBeef_LiveweightGainAllStates[Region],Table_SourceData_PastureBeef_LiveweightGainAllStates[Season],Table_SourceData_PastureBeef_LiveweightGainAllStates[#Headers],Table_SourceData_PastureBeef_LiveweightGainAllStates[#Data],Table_AustralianStates[Common Name],Table_AustralianStates[Abbreviation],Table_SourceData_Common_MonthToSeason[Month],Table_SourceData_Common_MonthToSeason[Season]) -> 0.44 | ... N94: =InputFunctions_PastureBeef.LookupLiveweightFromMonth($E$7,$E$8,$D94,N$88,Table_SourceData_PastureBeef_LiveweightGainAllStates[State],Table_SourceData_PastureBeef_LiveweightGainAllStates[Region],Table_SourceData_PastureBeef_LiveweightGainAllStates[Season],Table_SourceData_PastureBeef_LiveweightGainAllStates[#Headers],Table_SourceData_PastureBeef_LiveweightGainAllStates[#Data],Table_AustralianStates[Common Name],Table_AustralianStates[Abbreviation],Table_SourceData_Common_MonthToSeason[Month],Table_SourceData_Common_MonthToSeason[Season]) -> 0.44 | O94: kg/head/day
